Workbook

Sheet Trading Multiples
B1: Trading Multiples
E2: Market Data ($) | J2: Financial (€) | P2: Valuation (x)
B3: Company | H3: Shares Out | P3: EV/ | Q3: EV/
B4: Name | E4: Price | F4: Mkt Cap (M) | G4: EV (M) | H4: Diluted (M) | J4: Sales (M) | K4: EBIT (M) | L4: EBITDA (M) | M4: Last Debt | N4: Last Cash | P4: EBIT | Q4: EBITDA
B5: Tapestry, Inc. (NYSE:TPR) | E5: 32.49 | F5: =H5*E5 -> 9402.606 | G5: =F5+M5-N5 -> 10036.106 | H5: 289.4 | J5: 5988.1 | K5: 985.3 | L5: 1245.6 | M5: 1602.7 | N5: 969.2 | P5: =$G5/K5 -> 10.185838 | Q5: =$G5/L5 -> 8.0572463
B6: American Eagle Outfitters, Inc. (NYSE:AEO) | E6: 22.17 | F6: =H6*E6 -> 3912.4729 | G6: =F6+M6-N6 -> 3579.1429 | H6: 176.476 | J6: 4035.7 | K6: 340.7 | L6: 509.2 | M6: 0 | N6: 333.33 | P6: =$G6/K6 -> 10.505262 | Q6: =$G6/L6 -> 7.0289531
B7: Under Armour, Inc. (NYSE:UAA) | E7: 21.14 | F7: =H7*E7 -> 9533.3578 | G7: =F7+M7-N7 -> 10044.508 | H7: 450.963 | J7: 5193.2 | K7: 178.9 | L7: 360.7 | M7: 1299.222 | N7: 788.072 | P7: =$G7/K7 -> 56.145935 | Q7: =$G7/L7 -> 27.847263
B8: Lululemon Athletica Inc. (NasdaqGS:LULU) | E8: 163.87 | F8: =H8*E8 -> 21862.388 | G8: =F8+M8-N8 -> 20981.068 | H8: 133.413 | J8: 3288.3 | K8: 704.4 | L8: 826.9 | M8: 0 | N8: 881.32 | P8: =$G8/K8 -> 29.78573 | Q8: =$G8/L8 -> 25.373163
B9: Ralph Lauren Corporation (NYSE:RL) | E9: 129.68 | F9: =H9*E9 -> 10452.208 | G9: =F9+M9-N9 -> 10798.008 | H9: 80.6 | J9: 6336.5 | K9: 710.7 | L9: 984.4 | M9: 929.9 | N9: 584.1 | P9: =$G9/K9 -> 15.193482 | Q9: =$G9/L9 -> 10.969126
B10: Capri Holdings Limited (NYSE:CPRI) | E10: 45.75 | F10: =H10*E10 -> 6851.7703 | G10: =F10+M10-N10 -> 9245.7703 | H10: 149.76547 | J10: 5073.9 | K10: 912.8 | L10: 1130.9 | M10: 2566 | N10: 172 | P10: =$G10/K10 -> 10.129021 | Q10: =$G10/L10 -> 8.175586
B11: L Brands, Inc. (NYSE:LB) | E11: 27.58 | F11: =H11*E11 -> 7612.08 | G11: =F11+M11-N11 -> 12037.08 | H11: 276 | J11: 13237 | K11: 1440 | L11: 2030 | M11: 5838 | N11: 1413 | P11: =$G11/K11 -> 8.3590833 | Q11: =$G11/L11 -> 5.9295961
B12: The Gap, Inc. (NYSE:GPS) | E12: 26.18 | F12: =H12*E12 -> 10079.3 | G12: =F12+M12-N12 -> 10247.3 | H12: 385 | J12: 16580 | K12: 1374 | L12: 1952 | M12: 1249 | N12: 1081 | P12: =$G12/K12 -> 7.4580058 | Q12: =$G12/L12 -> 5.2496414
B13: Hugo Boss AG (XTRA:BOSS) | E13: 22.87 | F13: =H13*E13 -> 1578.3998 | G13: =F13+M13-N13 -> 2620.9008 | H13: 69.01617 | J13: 3086.5 | K13: 379.8 | L13: 490.6 | M13: 1175.127 | N13: 132.626 | P13: =$G13/K13 -> 6.9007394 | Q13: =$G13/L13 -> 5.3422356
B14: Burberry Group plc (LSE:BRBY) | E14: 13.62 | F14: =H14*E14 -> 5615.526 | G14: =F14+M14-N14 -> 4778.226 | H14: 412.3 | J14: 3267.4 | K14: 552.7 | L14: 651.9 | M14: 37.2 | N14: 874.5 | P14: =$G14/K14 -> 8.6452434 | Q14: =$G14/L14 -> 7.3296917
B15: Compagnie Financière Richemont SA (SWX:CFR) | E15: 54.31 | F15: =H15*E15 -> 30647.133 | G15: =F15+M15-N15 -> 32662.133 | H15: 564.3 | J15: 15601.5 | K15: 2117.9 | L15: 2774 | M15: 7075 | N15: 5060 | P15: =$G15/K15 -> 15.421943 | Q15: =$G15/L15 -> 11.774381
B16: Kering SA (ENXTPA:KER) | E16: 449.17 | F16: =H16*E16 -> 56370.283 | G16: =F16+M16-N16 -> 63501.483 | H16: 125.49877 | J16: 16998.6 | K16: 5113.8 | L16: 5649.4 | M16: 9417.1 | N16: 2285.9 | P16: =$G16/K16 -> 12.41767 | Q16: =$G16/L16 -> 11.240394
... B22: TIF | E22: 105.55 | F22: =H22*E22 -> 12972.095 | G22: =F22+M22-N22 -> 13113.595 | H22: 122.9 | J22: 4442.1 | K22: 775.5 | L22: 1004.5 | M22: 996.8 | N22: 855.3 | P22: =$G22/K22 -> 16.909858 | Q22: =$G22/L22 -> 13.054848
B23: Average | P23: =AVERAGE(P5:P22) -> 17.243333 | Q23: =AVERAGE(Q5:Q22) -> 12.456255
B24: Median | P24: =MEDIAN(P5:P22) -> 13.805576 | Q24: =MEDIAN(Q5:Q22) -> 11.10476
B25: ST. Dev. | P25: =_xlfn.STDEV.S(P5:P22) -> 12.224901 | Q25: =_xlfn.STDEV.S(Q5:Q22) -> 7.1372159

Sheet Premium
A2: x | B2: LVMH offer of Tiffany & Co.
B3: in millions
B4: CS Outstanding (2019) | D4: 122.9
B6: Trading $/Share | D6: 98.55
B7: Total Market Cap | D7: =D4*D6 -> 12111.795
B9: Offer $/Share | D9: =D10/D4 -> 117.9821
B10: Offer Market Cap | D10: 14500
B12: Premium % | D12: =D10/D7-1 -> 0.1971801
B13: Premium $ | D13: =D10-D7 -> 2388.205
B15: Tiffany & Co. Simple Value Calculation
B17: High End | E17: EBIT | F17: EBITDA | I17: Base Case | L17: EBIT | M17: EBITDA | P17: Low End | S17: EBIT | T17: EBITDA
B18: Industry Average EV Multiple | E18: ='Trading Multiples'!$P$23+'Trading Multiples'!P25 -> 29.468233 | F18: ='Trading Multiples'!$Q$23+'Trading Multiples'!Q25 -> 19.593471 | I18: Industry Average EV Multiple | L18: ='Trading Multiples'!$P$23 -> 17.243333 | M18: ='Trading Multiples'!$Q$23 -> 12.456255 | P18: Industry Average EV Multiple | S18: ='Trading Multiples'!$P$23-+'Trading Multiples'!P25 -> 5.018432 | T18: ='Trading Multiples'!$Q$23-+'Trading Multiples'!Q25 -> 5.3190388
B19: Tiffany Results 2019 | E19: ='Trading Multiples'!$K$22 -> 775.5 | F19: ='Trading Multiples'!$L$22 -> 1004.5 | I19: Tiffany Results 2019 | L19: ='Trading Multiples'!$K$22 -> 775.5 | M19: ='Trading Multiples'!$L$22 -> 1004.5 | P19: Tiffany Results 2019 | S19: ='Trading Multiples'!$K$22 -> 775.5 | T19: ='Trading Multiples'!$L$22 -> 1004.5
B20: Tiffany Implied EV | E20: =E19*E18 -> 22852.615 | F20: =F19*F18 -> 19681.641 | I20: Tiffany Implied EV | L20: =L19*L18 -> 13372.204 | M20: =M19*M18 -> 12512.308 | P20: Tiffany Implied EV | S20: =S19*S18 -> 3891.794 | T20: =T19*T18 -> 5342.9745
B21: (-) Debt | E21: ='Trading Multiples'!$M$22 -> 996.8 | I21: (-) Debt | L21: ='Trading Multiples'!$M$22 -> 996.8 | P21: (-) Debt | S21: ='Trading Multiples'!$M$22 -> 996.8
B22: (+) Cash | E22: ='Trading Multiples'!$N$22 -> 855.3 | I22: (+) Cash | L22: ='Trading Multiples'!$N$22 -> 855.3 | P22: (+) Cash | S22: ='Trading Multiples'!$N$22 -> 855.3
B23: Implied Market Value | E23: =E20-$L$21+$L$22 -> 22711.115 | F23: =F20-$L$21+$L$22 -> 19540.141 | I23: Implied Market Value | L23: =L20-$L$21+$L$22 -> 13230.704 | M23: =M20-$L$21+$L$22 -> 12370.808 | P23: Implied Market Value | S23: =S20-$L$21+$L$22 -> 3750.294 | T23: =T20-$L$21+$L$22 -> 5201.4745
B24: Implied $/Share | E24: =E23/$D$4 -> 184.79345 | F24: =F23/$D$4 -> 158.9922 | I24: Implied $/Share | L24: =L23/$D$4 -> 107.65423 | M24: =M23/$D$4 -> 100.65751 | P24: Implied $/Share | S24: =S23/$D$4 -> 30.515004 | T24: =T23/$D$4 -> 42.322819
B25: Average | G25: =AVERAGE(E24:F24) -> 171.89282 | I25: Average | N25: =AVERAGE(L24:M24) -> 104.15587 | P25: Average | U25: =AVERAGE(S24:T24) -> 36.418912
