Workbook

Sheet Candelaria Inputs
G1: Units | H1: Average / Total | I1: 2023 | J1: =I1+1 -> 2024 | K1: =J1+1 -> 2025 | L1: =K1+1 -> 2026 | M1: =L1+1 -> 2027 | N1: =M1+1 -> 2028 | O1: =N1+1 -> 2029 | P1: =O1+1 -> 2030 | Q1: =P1+1 -> 2031 | ... AF1: =AE1+1 -> 2046
D2: Production | G2: Units | H2: Average / Total
D3: Candelaria Open Pit to Candelaria Plant
D4: Candelaria Open Pit Waste Mined | E4: Base Case | I4: =INDEX(I5:I9,MATCH($E4,$D5:$D9,0)) -> 72094 | J4: =INDEX(J5:J9,MATCH($E4,$D5:$D9,0)) -> 67516 | K4: =INDEX(K5:K9,MATCH($E4,$D5:$D9,0)) -> 64748 | L4: =INDEX(L5:L9,MATCH($E4,$D5:$D9,0)) -> 52918 | M4: =INDEX(M5:M9,MATCH($E4,$D5:$D9,0)) -> 61881 | N4: =INDEX(N5:N9,MATCH($E4,$D5:$D9,0)) -> 75416 | O4: =INDEX(O5:O9,MATCH($E4,$D5:$D9,0)) -> 73631 | P4: =INDEX(P5:P9,MATCH($E4,$D5:$D9,0)) -> 66729 | ... AF4: =INDEX(AF5:AF9,MATCH($E4,$D5:$D9,0)) -> 0
D5: Base Case | G5: Kt | I5: 72094 | J5: 67516 | K5: 64748 | L5: 52918 | M5: 61881 | N5: 75416 | O5: 73631 | P5: 66729 | Q5: 54220 | R5: 37531 | S5: 30774 | T5: 21924 | U5: 16842 | V5: 13896 | W5: 11263 | X5: 10226 | Y5: 7752 | Z5: 8992 | AA5: 5230 | AB5: 0 | AC5: 0 | AD5: 0 | AE5: 0 | AF5: 0
D6: Base Case + 10% | E6: 0.1 | G6: Kt | I6: =I5*(1+$E6) -> 79303.4 | J6: =J5*(1+$E6) -> 74267.6 | K6: =K5*(1+$E6) -> 71222.8 | L6: =L5*(1+$E6) -> 58209.8 | M6: =M5*(1+$E6) -> 68069.1 | N6: =N5*(1+$E6) -> 82957.6 | O6: =O5*(1+$E6) -> 80994.1 | P6: =P5*(1+$E6) -> 73401.9 | ... AF6: =AF5*(1+$E6) -> 0
D7: Base Case - 10% | E7: -0.1 | G7: Kt | I7: =I6*(1+$E7) -> 71373.06 | J7: =J6*(1+$E7) -> 66840.84 | K7: =K6*(1+$E7) -> 64100.52 | L7: =L6*(1+$E7) -> 52388.82 | M7: =M6*(1+$E7) -> 61262.19 | N7: =N6*(1+$E7) -> 74661.84 | O7: =O6*(1+$E7) -> 72894.69 | P7: =P6*(1+$E7) -> 66061.71 | ... AF7: =AF6*(1+$E7) -> 0
D8: Free #1 | G8: Kt | I8: 0 | J8: 0 | K8: 0 | L8: 0 | M8: 0 | N8: 0 | O8: 0 | P8: 0 | Q8: 0 | R8: 0 | S8: 0 | T8: 0 | U8: 0 | V8: 0 | W8: 0 | X8: 0 | Y8: 0 | Z8: 0 | AA8: 0 | AB8: 0 | AC8: 0 | AD8: 0 | AE8: 0 | AF8: 0
D9: Free #2 | G9: Kt | I9: 0 | J9: 0 | K9: 0 | L9: 0 | M9: 0 | N9: 0 | O9: 0 | P9: 0 | Q9: 0 | R9: 0 | S9: 0 | T9: 0 | U9: 0 | V9: 0 | W9: 0 | X9: 0 | Y9: 0 | Z9: 0 | AA9: 0 | AB9: 0 | AC9: 0 | AD9: 0 | AE9: 0 | AF9: 0
D11: Candelaria Open Pit Ore to Mill | E11: Base Case | I11: =INDEX(I12:I16,MATCH($E11,$D12:$D16,0)) -> 13723 | J11: =INDEX(J12:J16,MATCH($E11,$D12:$D16,0)) -> 17280 | K11: =INDEX(K12:K16,MATCH($E11,$D12:$D16,0)) -> 19122 | L11: =INDEX(L12:L16,MATCH($E11,$D12:$D16,0)) -> 16053 | M11: =INDEX(M12:M16,MATCH($E11,$D12:$D16,0)) -> 15601 | N11: =INDEX(N12:N16,MATCH($E11,$D12:$D16,0)) -> 12155 | O11: =INDEX(O12:O16,MATCH($E11,$D12:$D16,0)) -> 6100 | P11: =INDEX(P12:P16,MATCH($E11,$D12:$D16,0)) -> 2725 | ... AF11: =INDEX(AF12:AF16,MATCH($E11,$D12:$D16,0)) -> 0
D12: Base Case | G12: Kt | I12: 13723 | J12: 17280 | K12: 19122 | L12: 16053 | M12: 15601 | N12: 12155 | O12: 6100 | P12: 2725 | Q12: 3343 | R12: 8965 | S12: 9686 | T12: 7530 | U12: 7571 | V12: 8568 | W12: 12517 | X12: 13499 | Y12: 16352 | Z12: 8973 | AA12: 4771 | AB12: 0 | AC12: 0 | AD12: 0 | AE12: 0 | AF12: 0
D13: Base Case + 10% | E13: 0.1 | G13: Kt | I13: =I12*(1+$E13) -> 15095.3 | J13: =J12*(1+$E13) -> 19008 | K13: =K12*(1+$E13) -> 21034.2 | L13: =L12*(1+$E13) -> 17658.3 | M13: =M12*(1+$E13) -> 17161.1 | N13: =N12*(1+$E13) -> 13370.5 | O13: =O12*(1+$E13) -> 6710 | P13: =P12*(1+$E13) -> 2997.5 | ... AF13: =AF12*(1+$E13) -> 0
D14: Base Case - 10% | E14: -0.1 | G14: Kt | I14: =I13*(1+$E14) -> 13585.77 | J14: =J13*(1+$E14) -> 17107.2 | K14: =K13*(1+$E14) -> 18930.78 | L14: =L13*(1+$E14) -> 15892.47 | M14: =M13*(1+$E14) -> 15444.99 | N14: =N13*(1+$E14) -> 12033.45 | O14: =O13*(1+$E14) -> 6039 | P14: =P13*(1+$E14) -> 2697.75 | ... AF14: =AF13*(1+$E14) -> 0
D15: Free #1 | G15: Kt | I15: 0 | J15: 0 | K15: 0 | L15: 0 | M15: 0 | N15: 0 | O15: 0 | P15: 0 | Q15: 0 | R15: 0 | S15: 0 | T15: 0 | U15: 0 | V15: 0 | W15: 0 | X15: 0 | Y15: 0 | Z15: 0 | AA15: 0 | AB15: 0 | AC15: 0 | AD15: 0 | AE15: 0 | AF15: 0
D16: Free #2 | G16: Kt | I16: 0 | J16: 0 | K16: 0 | L16: 0 | M16: 0 | N16: 0 | O16: 0 | P16: 0 | Q16: 0 | R16: 0 | S16: 0 | T16: 0 | U16: 0 | V16: 0 | W16: 0 | X16: 0 | Y16: 0 | Z16: 0 | AA16: 0 | AB16: 0 | AC16: 0 | AD16: 0 | AE16: 0 | AF16: 0
D18: Cu Grade | E18: Base Case | I18: =INDEX(I19:I23,MATCH($E18,$D19:$D23,0)) -> 0.0057 | J18: =INDEX(J19:J23,MATCH($E18,$D19:$D23,0)) -> 0.0064 | K18: =INDEX(K19:K23,MATCH($E18,$D19:$D23,0)) -> 0.0051 | L18: =INDEX(L19:L23,MATCH($E18,$D19:$D23,0)) -> 0.0058 | M18: =INDEX(M19:M23,MATCH($E18,$D19:$D23,0)) -> 0.0058 | N18: =INDEX(N19:N23,MATCH($E18,$D19:$D23,0)) -> 0.0059 | O18: =INDEX(O19:O23,MATCH($E18,$D19:$D23,0)) -> 0.0054 | P18: =INDEX(P19:P23,MATCH($E18,$D19:$D23,0)) -> 0.0046 | ... AF18: =INDEX(AF19:AF23,MATCH($E18,$D19:$D23,0)) -> 0
D19: Base Case | G19: Cu (%) | I19: 0.0057 | J19: 0.0064 | K19: 0.0051 | L19: 0.0058 | M19: 0.0058 | N19: 0.0059 | O19: 0.0054 | P19: 0.0046 | Q19: 0.0091 | R19: 0.0084 | S19: 0.0059 | T19: 0.0049 | U19: 0.005 | V19: 0.0057 | W19: 0.0069 | X19: 0.0076 | Y19: 0.0065 | Z19: 0.0054 | AA19: 0.0055 | AB19: 0 | AC19: 0 | AD19: 0 | AE19: 0 | AF19: 0
D20: Base Case + 10% | E20: 0.1 | G20: Cu (%) | I20: =I19*(1+$E20) -> 0.00627 | J20: =J19*(1+$E20) -> 0.00704 | K20: =K19*(1+$E20) -> 0.00561 | L20: =L19*(1+$E20) -> 0.00638 | M20: =M19*(1+$E20) -> 0.00638 | N20: =N19*(1+$E20) -> 0.00649 | O20: =O19*(1+$E20) -> 0.00594 | P20: =P19*(1+$E20) -> 0.00506 | ... AF20: =AF19*(1+$E20) -> 0
D21: Base Case - 10% | E21: -0.1 | G21: Cu (%) | I21: =I20*(1+$E21) -> 0.005643 | J21: =J20*(1+$E21) -> 0.006336 | K21: =K20*(1+$E21) -> 0.005049 | L21: =L20*(1+$E21) -> 0.005742 | M21: =M20*(1+$E21) -> 0.005742 | N21: =N20*(1+$E21) -> 0.005841 | O21: =O20*(1+$E21) -> 0.005346 | P21: =P20*(1+$E21) -> 0.004554 | ... AF21: =AF20*(1+$E21) -> 0
D22: Free #1 | G22: Cu (%) | I22: 0 | J22: 0 | K22: 0 | L22: 0 | M22: 0 | N22: 0 | O22: 0 | P22: 0 | Q22: 0 | R22: 0 | S22: 0 | T22: 0 | U22: 0 | V22: 0 | W22: 0 | X22: 0 | Y22: 0 | Z22: 0 | AA22: 0 | AB22: 0 | AC22: 0 | AD22: 0 | AE22: 0 | AF22: 0
D23: Free #2 | G23: Cu (%) | I23: 0 | J23: 0 | K23: 0 | L23: 0 | M23: 0 | N23: 0 | O23: 0 | P23: 0 | Q23: 0 | R23: 0 | S23: 0 | T23: 0 | U23: 0 | V23: 0 | W23: 0 | X23: 0 | Y23: 0 | Z23: 0 | AA23: 0 | AB23: 0 | AC23: 0 | AD23: 0 | AE23: 0 | AF23: 0
D25: Au Grade | E25: Base Case | I25: =INDEX(I26:I30,MATCH($E25,$D26:$D30,0)) -> 0.13 | J25: =INDEX(J26:J30,MATCH($E25,$D26:$D30,0)) -> 0.16 | K25: =INDEX(K26:K30,MATCH($E25,$D26:$D30,0)) -> 0.12 | L25: =INDEX(L26:L30,MATCH($E25,$D26:$D30,0)) -> 0.13 | M25: =INDEX(M26:M30,MATCH($E25,$D26:$D30,0)) -> 0.13 | N25: =INDEX(N26:N30,MATCH($E25,$D26:$D30,0)) -> 0.13 | O25: =INDEX(O26:O30,MATCH($E25,$D26:$D30,0)) -> 0.12 | P25: =INDEX(P26:P30,MATCH($E25,$D26:$D30,0)) -> 0.11 | ... AF25: =INDEX(AF26:AF30,MATCH($E25,$D26:$D30,0)) -> 0
D26: Base Case | G26: Au (g/t) | I26: 0.13 | J26: 0.16 | K26: 0.12 | L26: 0.13 | M26: 0.13 | N26: 0.13 | O26: 0.12 | P26: 0.11 | Q26: 0.2 | R26: 0.19 | S26: 0.15 | T26: 0.13 | U26: 0.12 | V26: 0.13 | W26: 0.15 | X26: 0.17 | Y26: 0.14 | Z26: 0.12 | AA26: 0.13 | AB26: 0 | AC26: 0 | AD26: 0 | AE26: 0 | AF26: 0
D27: Base Case + 10% | E27: 0.1 | G27: Au (g/t) | I27: =I26*(1+$E27) -> 0.143 | J27: =J26*(1+$E27) -> 0.176 | K27: =K26*(1+$E27) -> 0.132 | L27: =L26*(1+$E27) -> 0.143 | M27: =M26*(1+$E27) -> 0.143 | N27: =N26*(1+$E27) -> 0.143 | O27: =O26*(1+$E27) -> 0.132 | P27: =P26*(1+$E27) -> 0.121 | ... AF27: =AF26*(1+$E27) -> 0
D28: Base Case - 10% | E28: -0.1 | G28: Au (g/t) | I28: =I27*(1+$E28) -> 0.1287 | J28: =J27*(1+$E28) -> 0.1584 | K28: =K27*(1+$E28) -> 0.1188 | L28: =L27*(1+$E28) -> 0.1287 | M28: =M27*(1+$E28) -> 0.1287 | N28: =N27*(1+$E28) -> 0.1287 | O28: =O27*(1+$E28) -> 0.1188 | P28: =P27*(1+$E28) -> 0.1089 | ... AF28: =AF27*(1+$E28) -> 0
D29: Free #1 | G29: Au (g/t) | I29: 0 | J29: 0 | K29: 0 | L29: 0 | M29: 0 | N29: 0 | O29: 0 | P29: 0 | Q29: 0 | R29: 0 | S29: 0 | T29: 0 | U29: 0 | V29: 0 | W29: 0 | X29: 0 | Y29: 0 | Z29: 0 | AA29: 0 | AB29: 0 | AC29: 0 | AD29: 0 | AE29: 0 | AF29: 0
D30: Free #2 | G30: Au (g/t) | I30: 0 | J30: 0 | K30: 0 | L30: 0 | M30: 0 | N30: 0 | O30: 0 | P30: 0 | Q30: 0 | R30: 0 | S30: 0 | T30: 0 | U30: 0 | V30: 0 | W30: 0 | X30: 0 | Y30: 0 | Z30: 0 | AA30: 0 | AB30: 0 | AC30: 0 | AD30: 0 | AE30: 0 | AF30: 0
D32: Ag Grade | E32: Base Case | I32: =INDEX(I33:I37,MATCH($E32,$D33:$D37,0)) -> 1.46 | J32: =INDEX(J33:J37,MATCH($E32,$D33:$D37,0)) -> 2.74 | K32: =INDEX(K33:K37,MATCH($E32,$D33:$D37,0)) -> 2.03 | L32: =INDEX(L33:L37,MATCH($E32,$D33:$D37,0)) -> 1.8 | M32: =INDEX(M33:M37,MATCH($E32,$D33:$D37,0)) -> 1.71 | N32: =INDEX(N33:N37,MATCH($E32,$D33:$D37,0)) -> 1.94 | O32: =INDEX(O33:O37,MATCH($E32,$D33:$D37,0)) -> 1.49 | P32: =INDEX(P33:P37,MATCH($E32,$D33:$D37,0)) -> 1.26 | ... AF32: =INDEX(AF33:AF37,MATCH($E32,$D33:$D37,0)) -> 0
D33: Base Case | G33: Ag (g/t) | I33: 1.46 | J33: 2.74 | K33: 2.03 | L33: 1.8 | M33: 1.71 | N33: 1.94 | O33: 1.49 | P33: 1.26 | Q33: 2.73 | R33: 2.29 | S33: 1.55 | T33: 1.19 | U33: 1.14 | V33: 1.22 | W33: 1.7 | X33: 2.4 | Y33: 2.224 | Z33: 1.53 | AA33: 1.27 | AB33: 0 | AC33: 0 | AD33: 0 | AE33: 0 | AF33: 0
D34: Base Case + 10% | E34: 0.1 | G34: Ag (g/t) | I34: =I33*(1+$E34) -> 1.606 | J34: =J33*(1+$E34) -> 3.014 | K34: =K33*(1+$E34) -> 2.233 | L34: =L33*(1+$E34) -> 1.98 | M34: =M33*(1+$E34) -> 1.881 | N34: =N33*(1+$E34) -> 2.134 | O34: =O33*(1+$E34) -> 1.639 | P34: =P33*(1+$E34) -> 1.386 | ... AF34: =AF33*(1+$E34) -> 0
D35: Base Case - 10% | E35: -0.1 | G35: Ag (g/t) | I35: =I34*(1+$E35) -> 1.4454 | J35: =J34*(1+$E35) -> 2.7126 | K35: =K34*(1+$E35) -> 2.0097 | L35: =L34*(1+$E35) -> 1.782 | M35: =M34*(1+$E35) -> 1.6929 | N35: =N34*(1+$E35) -> 1.9206 | O35: =O34*(1+$E35) -> 1.4751 | P35: =P34*(1+$E35) -> 1.2474 | ... AF35: =AF34*(1+$E35) -> 0
D36: Free #1 | G36: Ag (g/t) | I36: 0 | J36: 0 | K36: 0 | L36: 0 | M36: 0 | N36: 0 | O36: 0 | P36: 0 | Q36: 0 | R36: 0 | S36: 0 | T36: 0 | U36: 0 | V36: 0 | W36: 0 | X36: 0 | Y36: 0 | Z36: 0 | AA36: 0 | AB36: 0 | AC36: 0 | AD36: 0 | AE36: 0 | AF36: 0
D37: Free #2 | G37: Ag (g/t) | I37: 0 | J37: 0 | K37: 0 | L37: 0 | M37: 0 | N37: 0 | O37: 0 | P37: 0 | Q37: 0 | R37: 0 | S37: 0 | T37: 0 | U37: 0 | V37: 0 | W37: 0 | X37: 0 | Y37: 0 | Z37: 0 | AA37: 0 | AB37: 0 | AC37: 0 | AD37: 0 | AE37: 0 | AF37: 0
D39: Espanola to Candelaria Plant
D40: Espanola Open Pit Waste Mined | E40: Base Case | I40: =INDEX(I41:I45,MATCH($E40,$D41:$D45,0)) -> 0 | J40: =INDEX(J41:J45,MATCH($E40,$D41:$D45,0)) -> 9655 | K40: =INDEX(K41:K45,MATCH($E40,$D41:$D45,0)) -> 17090 | L40: =INDEX(L41:L45,MATCH($E40,$D41:$D45,0)) -> 19267 | M40: =INDEX(M41:M45,MATCH($E40,$D41:$D45,0)) -> 17113 | N40: =INDEX(N41:N45,MATCH($E40,$D41:$D45,0)) -> 15524 | O40: =INDEX(O41:O45,MATCH($E40,$D41:$D45,0)) -> 13588 | P40: =INDEX(P41:P45,MATCH($E40,$D41:$D45,0)) -> 12084 | ... AF40: =INDEX(AF41:AF45,MATCH($E40,$D41:$D45,0)) -> 0
D41: Base Case | G41: Kt | I41: 0 | J41: 9655 | K41: 17090 | L41: 19267 | M41: 17113 | N41: 15524 | O41: 13588 | P41: 12084 | Q41: 10635 | R41: 9952 | S41: 6643 | T41: 3865 | U41: 1424 | V41: 2049 | W41: 0 | X41: 0 | Y41: 0 | Z41: 0 | AA41: 0 | AB41: 0 | AC41: 0 | AD41: 0 | AE41: 0 | AF41: 0
D42: Base Case + 10% | E42: 0.1 | G42: Kt | I42: =I41*(1+$E42) -> 0 | J42: =J41*(1+$E42) -> 10620.5 | K42: =K41*(1+$E42) -> 18799 | L42: =L41*(1+$E42) -> 21193.7 | M42: =M41*(1+$E42) -> 18824.3 | N42: =N41*(1+$E42) -> 17076.4 | O42: =O41*(1+$E42) -> 14946.8 | P42: =P41*(1+$E42) -> 13292.4 | ... AF42: =AF41*(1+$E42) -> 0
D43: Base Case - 10% | E43: -0.1 | G43: Kt | I43: =I42*(1+$E43) -> 0 | J43: =J42*(1+$E43) -> 9558.45 | K43: =K42*(1+$E43) -> 16919.1 | L43: =L42*(1+$E43) -> 19074.33 | M43: =M42*(1+$E43) -> 16941.87 | N43: =N42*(1+$E43) -> 15368.76 | O43: =O42*(1+$E43) -> 13452.12 | P43: =P42*(1+$E43) -> 11963.16 | ... AF43: =AF42*(1+$E43) -> 0
D44: Free #1 | G44: Kt | I44: 0 | J44: 0 | K44: 0 | L44: 0 | M44: 0 | N44: 0 | O44: 0 | P44: 0 | Q44: 0 | R44: 0 | S44: 0 | T44: 0 | U44: 0 | V44: 0 | W44: 0 | X44: 0 | Y44: 0 | Z44: 0 | AA44: 0 | AB44: 0 | AC44: 0 | AD44: 0 | AE44: 0 | AF44: 0
D45: Free #2 | G45: Kt | I45: 0 | J45: 0 | K45: 0 | L45: 0 | M45: 0 | N45: 0 | O45: 0 | P45: 0 | Q45: 0 | R45: 0 | S45: 0 | T45: 0 | U45: 0 | V45: 0 | W45: 0 | X45: 0 | Y45: 0 | Z45: 0 | AA45: 0 | AB45: 0 | AC45: 0 | AD45: 0 | AE45: 0 | AF45: 0
D47: Espanola Open Pit Ore to Mill | E47: Base Case | I47: =INDEX(I48:I52,MATCH($E47,$D48:$D52,0)) -> 0 | J47: =INDEX(J48:J52,MATCH($E47,$D48:$D52,0)) -> 0 | K47: =INDEX(K48:K52,MATCH($E47,$D48:$D52,0)) -> 0 | L47: =INDEX(L48:L52,MATCH($E47,$D48:$D52,0)) -> 2395 | M47: =INDEX(M48:M52,MATCH($E47,$D48:$D52,0)) -> 3965 | N47: =INDEX(N48:N52,MATCH($E47,$D48:$D52,0)) -> 424 | O47: =INDEX(O48:O52,MATCH($E47,$D48:$D52,0)) -> 6162 | P47: =INDEX(P48:P52,MATCH($E47,$D48:$D52,0)) -> 7707 | ... AF47: =INDEX(AF48:AF52,MATCH($E47,$D48:$D52,0)) -> 0
D48: Base Case | G48: Kt | I48: 0 | J48: 0 | K48: 0 | L48: 2395 | M48: 3965 | N48: 424 | O48: 6162 | P48: 7707 | Q48: 7927 | R48: 6143 | S48: 6855 | T48: 4792 | U48: 2049 | V48: 290 | W48: 0 | X48: 0 | Y48: 0 | Z48: 0 | AA48: 0 | AB48: 0 | AC48: 0 | AD48: 0 | AE48: 0 | AF48: 0
D49: Base Case + 10% | E49: 0.1 | G49: Kt | I49: =I48*(1+$E49) -> 0 | J49: =J48*(1+$E49) -> 0 | K49: =K48*(1+$E49) -> 0 | L49: =L48*(1+$E49) -> 2634.5 | M49: =M48*(1+$E49) -> 4361.5 | N49: =N48*(1+$E49) -> 466.4 | O49: =O48*(1+$E49) -> 6778.2 | P49: =P48*(1+$E49) -> 8477.7 | ... AF49: =AF48*(1+$E49) -> 0
D50: Base Case - 10% | E50: -0.1 | G50: Kt | I50: =I49*(1+$E50) -> 0 | J50: =J49*(1+$E50) -> 0 | K50: =K49*(1+$E50) -> 0 | L50: =L49*(1+$E50) -> 2371.05 | M50: =M49*(1+$E50) -> 3925.35 | N50: =N49*(1+$E50) -> 419.76 | O50: =O49*(1+$E50) -> 6100.38 | P50: =P49*(1+$E50) -> 7629.93 | ... AF50: =AF49*(1+$E50) -> 0
D51: Free #1 | G51: Kt | I51: 0 | J51: 0 | K51: 0 | L51: 0 | M51: 0 | N51: 0 | O51: 0 | P51: 0 | Q51: 0 | R51: 0 | S51: 0 | T51: 0 | U51: 0 | V51: 0 | W51: 0 | X51: 0 | Y51: 0 | Z51: 0 | AA51: 0 | AB51: 0 | AC51: 0 | AD51: 0 | AE51: 0 | AF51: 0
D52: Free #2 | G52: Kt | I52: 0 | J52: 0 | K52: 0 | L52: 0 | M52: 0 | N52: 0 | O52: 0 | P52: 0 | Q52: 0 | R52: 0 | S52: 0 | T52: 0 | U52: 0 | V52: 0 | W52: 0 | X52: 0 | Y52: 0 | Z52: 0 | AA52: 0 | AB52: 0 | AC52: 0 | AD52: 0 | AE52: 0 | AF52: 0
D54: Cu Grade | E54: Base Case | I54: =INDEX(I55:I59,MATCH($E54,$D55:$D59,0)) -> 0 | J54: =INDEX(J55:J59,MATCH($E54,$D55:$D59,0)) -> 0 | K54: =INDEX(K55:K59,MATCH($E54,$D55:$D59,0)) -> 0 | L54: =INDEX(L55:L59,MATCH($E54,$D55:$D59,0)) -> 0.0042 | M54: =INDEX(M55:M59,MATCH($E54,$D55:$D59,0)) -> 0.004 | N54: =INDEX(N55:N59,MATCH($E54,$D55:$D59,0)) -> 0.0043 | O54: =INDEX(O55:O59,MATCH($E54,$D55:$D59,0)) -> 0.0042 | P54: =INDEX(P55:P59,MATCH($E54,$D55:$D59,0)) -> 0.0044 | ... AF54: =INDEX(AF55:AF59,MATCH($E54,$D55:$D59,0)) -> 0
D55: Base Case | G55: Cu (%) | I55: 0 | J55: 0 | K55: 0 | L55: 0.0042 | M55: 0.004 | N55: 0.0043 | O55: 0.0042 | P55: 0.0044 | Q55: 0.004 | R55: 0.0041 | S55: 0.0045 | T55: 0.0047 | U55: 0.004 | V55: 0.004 | W55: 0 | X55: 0 | Y55: 0 | Z55: 0 | AA55: 0 | AB55: 0 | AC55: 0 | AD55: 0 | AE55: 0 | AF55: 0
D56: Base Case + 10% | E56: 0.1 | G56: Cu (%) | I56: =I55*(1+$E56) -> 0 | J56: =J55*(1+$E56) -> 0 | K56: =K55*(1+$E56) -> 0 | L56: =L55*(1+$E56) -> 0.00462 | M56: =M55*(1+$E56) -> 0.0044 | N56: =N55*(1+$E56) -> 0.00473 | O56: =O55*(1+$E56) -> 0.00462 | P56: =P55*(1+$E56) -> 0.00484 | ... AF56: =AF55*(1+$E56) -> 0
D57: Base Case - 10% | E57: -0.1 | G57: Cu (%) | I57: =I56*(1+$E57) -> 0 | J57: =J56*(1+$E57) -> 0 | K57: =K56*(1+$E57) -> 0 | L57: =L56*(1+$E57) -> 0.004158 | M57: =M56*(1+$E57) -> 0.00396 | N57: =N56*(1+$E57) -> 0.004257 | O57: =O56*(1+$E57) -> 0.004158 | P57: =P56*(1+$E57) -> 0.004356 | ... AF57: =AF56*(1+$E57) -> 0
D58: Free #1 | G58: Cu (%) | I58: 0 | J58: 0 | K58: 0 | L58: 0 | M58: 0 | N58: 0 | O58: 0 | P58: 0 | Q58: 0 | R58: 0 | S58: 0 | T58: 0 | U58: 0 | V58: 0 | W58: 0 | X58: 0 | Y58: 0 | Z58: 0 | AA58: 0 | AB58: 0 | AC58: 0 | AD58: 0 | AE58: 0 | AF58: 0
D59: Free #2 | G59: Cu (%) | I59: 0 | J59: 0 | K59: 0 | L59: 0 | M59: 0 | N59: 0 | O59: 0 | P59: 0 | Q59: 0 | R59: 0 | S59: 0 | T59: 0 | U59: 0 | V59: 0 | W59: 0 | X59: 0 | Y59: 0 | Z59: 0 | AA59: 0 | AB59: 0 | AC59: 0 | AD59: 0 | AE59: 0 | AF59: 0
D61: Au Grade | E61: Base Case | I61: =INDEX(I62:I66,MATCH($E61,$D62:$D66,0)) -> 0 | J61: =INDEX(J62:J66,MATCH($E61,$D62:$D66,0)) -> 0 | K61: =INDEX(K62:K66,MATCH($E61,$D62:$D66,0)) -> 0 | L61: =INDEX(L62:L66,MATCH($E61,$D62:$D66,0)) -> 0.09 | M61: =INDEX(M62:M66,MATCH($E61,$D62:$D66,0)) -> 0.08 | N61: =INDEX(N62:N66,MATCH($E61,$D62:$D66,0)) -> 0.09 | O61: =INDEX(O62:O66,MATCH($E61,$D62:$D66,0)) -> 0.09 | P61: =INDEX(P62:P66,MATCH($E61,$D62:$D66,0)) -> 0.09 | ... AF61: =INDEX(AF62:AF66,MATCH($E61,$D62:$D66,0)) -> 0
D62: Base Case | G62: Au (g/t) | I62: 0 | J62: 0 | K62: 0 | L62: 0.09 | M62: 0.08 | N62: 0.09 | O62: 0.09 | P62: 0.09 | Q62: 0.09 | R62: 0.09 | S62: 0.09 | T62: 0.09 | U62: 0.08 | V62: 0.1 | W62: 0 | X62: 0 | Y62: 0 | Z62: 0 | AA62: 0 | AB62: 0 | AC62: 0 | AD62: 0 | AE62: 0 | AF62: 0
D63: Base Case + 10% | E63: 0.1 | G63: Au (g/t) | I63: =I62*(1+$E63) -> 0 | J63: =J62*(1+$E63) -> 0 | K63: =K62*(1+$E63) -> 0 | L63: =L62*(1+$E63) -> 0.099 | M63: =M62*(1+$E63) -> 0.088 | N63: =N62*(1+$E63) -> 0.099 | O63: =O62*(1+$E63) -> 0.099 | P63: =P62*(1+$E63) -> 0.099 | ... AF63: =AF62*(1+$E63) -> 0
D64: Base Case - 10% | E64: -0.1 | G64: Au (g/t) | I64: =I63*(1+$E64) -> 0 | J64: =J63*(1+$E64) -> 0 | K64: =K63*(1+$E64) -> 0 | L64: =L63*(1+$E64) -> 0.0891 | M64: =M63*(1+$E64) -> 0.0792 | N64: =N63*(1+$E64) -> 0.0891 | O64: =O63*(1+$E64) -> 0.0891 | P64: =P63*(1+$E64) -> 0.0891 | ... AF64: =AF63*(1+$E64) -> 0
D65: Free #1 | G65: Au (g/t) | I65: 0 | J65: 0 | K65: 0 | L65: 0 | M65: 0 | N65: 0 | O65: 0 | P65: 0 | Q65: 0 | R65: 0 | S65: 0 | T65: 0 | U65: 0 | V65: 0 | W65: 0 | X65: 0 | Y65: 0 | Z65: 0 | AA65: 0 | AB65: 0 | AC65: 0 | AD65: 0 | AE65: 0 | AF65: 0
D66: Free #2 | G66: Au (g/t) | I66: 0 | J66: 0 | K66: 0 | L66: 0 | M66: 0 | N66: 0 | O66: 0 | P66: 0 | Q66: 0 | R66: 0 | S66: 0 | T66: 0 | U66: 0 | V66: 0 | W66: 0 | X66: 0 | Y66: 0 | Z66: 0 | AA66: 0 | AB66: 0 | AC66: 0 | AD66: 0 | AE66: 0 | AF66: 0
D68: Ag Grade | E68: Base Case | I68: =INDEX(I69:I73,MATCH($E68,$D69:$D73,0)) -> 0 | J68: =INDEX(J69:J73,MATCH($E68,$D69:$D73,0)) -> 0 | K68: =INDEX(K69:K73,MATCH($E68,$D69:$D73,0)) -> 0 | L68: =INDEX(L69:L73,MATCH($E68,$D69:$D73,0)) -> 0.35 | M68: =INDEX(M69:M73,MATCH($E68,$D69:$D73,0)) -> 0.37 | N68: =INDEX(N69:N73,MATCH($E68,$D69:$D73,0)) -> 0.36 | O68: =INDEX(O69:O73,MATCH($E68,$D69:$D73,0)) -> 0.33 | P68: =INDEX(P69:P73,MATCH($E68,$D69:$D73,0)) -> 0.36 | ... AF68: =INDEX(AF69:AF73,MATCH($E68,$D69:$D73,0)) -> 0
D69: Base Case | G69: Ag (g/t) | I69: 0 | J69: 0 | K69: 0 | L69: 0.35 | M69: 0.37 | N69: 0.36 | O69: 0.33 | P69: 0.36 | Q69: 0.4 | R69: 0.56 | S69: 0.4 | T69: 0.37 | U69: 0.34 | V69: 0.28 | W69: 0 | X69: 0 | Y69: 0 | Z69: 0 | AA69: 0 | AB69: 0 | AC69: 0 | AD69: 0 | AE69: 0 | AF69: 0
D70: Base Case + 10% | E70: 0.1 | G70: Ag (g/t) | I70: =I69*(1+$E70) -> 0 | J70: =J69*(1+$E70) -> 0 | K70: =K69*(1+$E70) -> 0 | L70: =L69*(1+$E70) -> 0.385 | M70: =M69*(1+$E70) -> 0.407 | N70: =N69*(1+$E70) -> 0.396 | O70: =O69*(1+$E70) -> 0.363 | P70: =P69*(1+$E70) -> 0.396 | ... AF70: =AF69*(1+$E70) -> 0
D71: Base Case - 10% | E71: -0.1 | G71: Ag (g/t) | I71: =I70*(1+$E71) -> 0 | J71: =J70*(1+$E71) -> 0 | K71: =K70*(1+$E71) -> 0 | L71: =L70*(1+$E71) -> 0.3465 | M71: =M70*(1+$E71) -> 0.3663 | N71: =N70*(1+$E71) -> 0.3564 | O71: =O70*(1+$E71) -> 0.3267 | P71: =P70*(1+$E71) -> 0.3564 | ... AF71: =AF70*(1+$E71) -> 0
D72: Free #1 | G72: Ag (g/t) | I72: 0 | J72: 0 | K72: 0 | L72: 0 | M72: 0 | N72: 0 | O72: 0 | P72: 0 | Q72: 0 | R72: 0 | S72: 0 | T72: 0 | U72: 0 | V72: 0 | W72: 0 | X72: 0 | Y72: 0 | Z72: 0 | AA72: 0 | AB72: 0 | AC72: 0 | AD72: 0 | AE72: 0 | AF72: 0
D73: Free #2 | G73: Ag (g/t) | I73: 0 | J73: 0 | K73: 0 | L73: 0 | M73: 0 | N73: 0 | O73: 0 | P73: 0 | Q73: 0 | R73: 0 | S73: 0 | T73: 0 | U73: 0 | V73: 0 | W73: 0 | X73: 0 | Y73: 0 | Z73: 0 | AA73: 0 | AB73: 0 | AC73: 0 | AD73: 0 | AE73: 0 | AF73: 0
D75: Candelaria Open Pit + Espanola to WIP
D76: Candelaria Open Pit + Espanola Ore to WIP | E76: Base Case | I76: =INDEX(I77:I81,MATCH($E76,$D77:$D81,0)) -> 4610 | J76: =INDEX(J77:J81,MATCH($E76,$D77:$D81,0)) -> 12464 | K76: =INDEX(K77:K81,MATCH($E76,$D77:$D81,0)) -> 13998 | L76: =INDEX(L77:L81,MATCH($E76,$D77:$D81,0)) -> 19387 | M76: =INDEX(M77:M81,MATCH($E76,$D77:$D81,0)) -> 13281 | N76: =INDEX(N77:N81,MATCH($E76,$D77:$D81,0)) -> 13553 | O76: =INDEX(O77:O81,MATCH($E76,$D77:$D81,0)) -> 10012 | P76: =INDEX(P77:P81,MATCH($E76,$D77:$D81,0)) -> 7480 | ... AF76: =INDEX(AF77:AF81,MATCH($E76,$D77:$D81,0)) -> 0
D77: Base Case | G77: Kt | I77: 4610 | J77: 12464 | K77: 13998 | L77: 19387 | M77: 13281 | N77: 13553 | O77: 10012 | P77: 7480 | Q77: 4394 | R77: 6158 | S77: 10541 | T77: 12189 | U77: 11421 | V77: 7643 | W77: 6220 | X77: 5775 | Y77: 5192 | Z77: 7136 | AA77: 2872 | AB77: 0 | AC77: 0 | AD77: 0 | AE77: 0 | AF77: 0
D78: Base Case + 10% | E78: 0.1 | G78: Kt | I78: =I77*(1+$E78) -> 5071 | J78: =J77*(1+$E78) -> 13710.4 | K78: =K77*(1+$E78) -> 15397.8 | L78: =L77*(1+$E78) -> 21325.7 | M78: =M77*(1+$E78) -> 14609.1 | N78: =N77*(1+$E78) -> 14908.3 | O78: =O77*(1+$E78) -> 11013.2 | P78: =P77*(1+$E78) -> 8228 | ... AF78: =AF77*(1+$E78) -> 0
D79: Base Case - 10% | E79: -0.1 | G79: Kt | I79: =I78*(1+$E79) -> 4563.9 | J79: =J78*(1+$E79) -> 12339.36 | K79: =K78*(1+$E79) -> 13858.02 | L79: =L78*(1+$E79) -> 19193.13 | M79: =M78*(1+$E79) -> 13148.19 | N79: =N78*(1+$E79) -> 13417.47 | O79: =O78*(1+$E79) -> 9911.88 | P79: =P78*(1+$E79) -> 7405.2 | ... AF79: =AF78*(1+$E79) -> 0
D80: Free #1 | G80: Kt | I80: 0 | J80: 0 | K80: 0 | L80: 0 | M80: 0 | N80: 0 | O80: 0 | P80: 0 | Q80: 0 | R80: 0 | S80: 0 | T80: 0 | U80: 0 | V80: 0 | W80: 0 | X80: 0 | Y80: 0 | Z80: 0 | AA80: 0 | AB80: 0 | AC80: 0 | AD80: 0 | AE80: 0 | AF80: 0
D81: Free #2 | G81: Kt | I81: 0 | J81: 0 | K81: 0 | L81: 0 | M81: 0 | N81: 0 | O81: 0 | P81: 0 | Q81: 0 | R81: 0 | S81: 0 | T81: 0 | U81: 0 | V81: 0 | W81: 0 | X81: 0 | Y81: 0 | Z81: 0 | AA81: 0 | AB81: 0 | AC81: 0 | AD81: 0 | AE81: 0 | AF81: 0
D83: Cu Grade | E83: Base Case | I83: =INDEX(I84:I88,MATCH($E83,$D84:$D88,0)) -> 0.002 | J83: =INDEX(J84:J88,MATCH($E83,$D84:$D88,0)) -> 0.0022 | K83: =INDEX(K84:K88,MATCH($E83,$D84:$D88,0)) -> 0.0023 | L83: =INDEX(L84:L88,MATCH($E83,$D84:$D88,0)) -> 0.0024 | M83: =INDEX(M84:M88,MATCH($E83,$D84:$D88,0)) -> 0.0025 | N83: =INDEX(N84:N88,MATCH($E83,$D84:$D88,0)) -> 0.0029 | O83: =INDEX(O84:O88,MATCH($E83,$D84:$D88,0)) -> 0.0024 | P83: =INDEX(P84:P88,MATCH($E83,$D84:$D88,0)) -> 0.0023 | ... AF83: =INDEX(AF84:AF88,MATCH($E83,$D84:$D88,0)) -> 0
D84: Base Case | G84: Cu (%) | I84: 0.002 | J84: 0.0022 | K84: 0.0023 | L84: 0.0024 | M84: 0.0025 | N84: 0.0029 | O84: 0.0024 | P84: 0.0023 | Q84: 0.0025 | R84: 0.0022 | S84: 0.0024 | T84: 0.0021 | U84: 0.0021 | V84: 0.0021 | W84: 0.0022 | X84: 0.0021 | Y84: 0.0022 | Z84: 0.0021 | AA84: 0.0022 | AB84: 0 | AC84: 0 | AD84: 0 | AE84: 0 | AF84: 0
D85: Base Case + 10% | E85: 0.1 | G85: Cu (%) | I85: =I84*(1+$E85) -> 0.0022 | J85: =J84*(1+$E85) -> 0.00242 | K85: =K84*(1+$E85) -> 0.00253 | L85: =L84*(1+$E85) -> 0.00264 | M85: =M84*(1+$E85) -> 0.00275 | N85: =N84*(1+$E85) -> 0.00319 | O85: =O84*(1+$E85) -> 0.00264 | P85: =P84*(1+$E85) -> 0.00253 | ... AF85: =AF84*(1+$E85) -> 0
D86: Base Case - 10% | E86: -0.1 | G86: Cu (%) | I86: =I85*(1+$E86) -> 0.00198 | J86: =J85*(1+$E86) -> 0.002178 | K86: =K85*(1+$E86) -> 0.002277 | L86: =L85*(1+$E86) -> 0.002376 | M86: =M85*(1+$E86) -> 0.002475 | N86: =N85*(1+$E86) -> 0.002871 | O86: =O85*(1+$E86) -> 0.002376 | P86: =P85*(1+$E86) -> 0.002277 | ... AF86: =AF85*(1+$E86) -> 0
D87: Free #1 | G87: Cu (%) | I87: 0 | J87: 0 | K87: 0 | L87: 0 | M87: 0 | N87: 0 | O87: 0 | P87: 0 | Q87: 0 | R87: 0 | S87: 0 | T87: 0 | U87: 0 | V87: 0 | W87: 0 | X87: 0 | Y87: 0 | Z87: 0 | AA87: 0 | AB87: 0 | AC87: 0 | AD87: 0 | AE87: 0 | AF87: 0
D88: Free #2 | G88: Cu (%) | I88: 0 | J88: 0 | K88: 0 | L88: 0 | M88: 0 | N88: 0 | O88: 0 | P88: 0 | Q88: 0 | R88: 0 | S88: 0 | T88: 0 | U88: 0 | V88: 0 | W88: 0 | X88: 0 | Y88: 0 | Z88: 0 | AA88: 0 | AB88: 0 | AC88: 0 | AD88: 0 | AE88: 0 | AF88: 0
D90: Au Grade | E90: Base Case | I90: =INDEX(I91:I95,MATCH($E90,$D91:$D95,0)) -> 0.06 | J90: =INDEX(J91:J95,MATCH($E90,$D91:$D95,0)) -> 0.07 | K90: =INDEX(K91:K95,MATCH($E90,$D91:$D95,0)) -> 0.06 | L90: =INDEX(L91:L95,MATCH($E90,$D91:$D95,0)) -> 0.07 | M90: =INDEX(M91:M95,MATCH($E90,$D91:$D95,0)) -> 0.07 | N90: =INDEX(N91:N95,MATCH($E90,$D91:$D95,0)) -> 0.07 | O90: =INDEX(O91:O95,MATCH($E90,$D91:$D95,0)) -> 0.06 | P90: =INDEX(P91:P95,MATCH($E90,$D91:$D95,0)) -> 0.06 | ... AF90: =INDEX(AF91:AF95,MATCH($E90,$D91:$D95,0)) -> 0
D91: Base Case | G91: Au (g/t) | I91: 0.06 | J91: 0.07 | K91: 0.06 | L91: 0.07 | M91: 0.07 | N91: 0.07 | O91: 0.06 | P91: 0.06 | Q91: 0.07 | R91: 0.06 | S91: 0.06 | T91: 0.06 | U91: 0.05 | V91: 0.05 | W91: 0.06 | X91: 0.06 | Y91: 0.06 | Z91: 0.06 | AA91: 0.07 | AB91: 0 | AC91: 0 | AD91: 0 | AE91: 0 | AF91: 0
D92: Base Case + 10% | E92: 0.1 | G92: Au (g/t) | I92: =I91*(1+$E92) -> 0.066 | J92: =J91*(1+$E92) -> 0.077 | K92: =K91*(1+$E92) -> 0.066 | L92: =L91*(1+$E92) -> 0.077 | M92: =M91*(1+$E92) -> 0.077 | N92: =N91*(1+$E92) -> 0.077 | O92: =O91*(1+$E92) -> 0.066 | P92: =P91*(1+$E92) -> 0.066 | ... AF92: =AF91*(1+$E92) -> 0
D93: Base Case - 10% | E93: -0.1 | G93: Au (g/t) | I93: =I92*(1+$E93) -> 0.0594 | J93: =J92*(1+$E93) -> 0.0693 | K93: =K92*(1+$E93) -> 0.0594 | L93: =L92*(1+$E93) -> 0.0693 | M93: =M92*(1+$E93) -> 0.0693 | N93: =N92*(1+$E93) -> 0.0693 | O93: =O92*(1+$E93) -> 0.0594 | P93: =P92*(1+$E93) -> 0.0594 | ... AF93: =AF92*(1+$E93) -> 0
D94: Free #1 | G94: Au (g/t) | I94: 0 | J94: 0 | K94: 0 | L94: 0 | M94: 0 | N94: 0 | O94: 0 | P94: 0 | Q94: 0 | R94: 0 | S94: 0 | T94: 0 | U94: 0 | V94: 0 | W94: 0 | X94: 0 | Y94: 0 | Z94: 0 | AA94: 0 | AB94: 0 | AC94: 0 | AD94: 0 | AE94: 0 | AF94: 0
D95: Free #2 | G95: Au (g/t) | I95: 0 | J95: 0 | K95: 0 | L95: 0 | M95: 0 | N95: 0 | O95: 0 | P95: 0 | Q95: 0 | R95: 0 | S95: 0 | T95: 0 | U95: 0 | V95: 0 | W95: 0 | X95: 0 | Y95: 0 | Z95: 0 | AA95: 0 | AB95: 0 | AC95: 0 | AD95: 0 | AE95: 0 | AF95: 0
D97: Ag Grade | E97: Base Case | I97: =INDEX(I98:I102,MATCH($E97,$D98:$D102,0)) -> 0.95 | J97: =INDEX(J98:J102,MATCH($E97,$D98:$D102,0)) -> 1.26 | K97: =INDEX(K98:K102,MATCH($E97,$D98:$D102,0)) -> 1.07 | L97: =INDEX(L98:L102,MATCH($E97,$D98:$D102,0)) -> 1.25 | M97: =INDEX(M98:M102,MATCH($E97,$D98:$D102,0)) -> 0.98 | N97: =INDEX(N98:N102,MATCH($E97,$D98:$D102,0)) -> 0.75 | O97: =INDEX(O98:O102,MATCH($E97,$D98:$D102,0)) -> 0.83 | P97: =INDEX(P98:P102,MATCH($E97,$D98:$D102,0)) -> 0.67 | ... AF97: =INDEX(AF98:AF102,MATCH($E97,$D98:$D102,0)) -> 0
D98: Base Case | G98: Ag (g/t) | I98: 0.95 | J98: 1.26 | K98: 1.07 | L98: 1.25 | M98: 0.98 | N98: 0.75 | O98: 0.83 | P98: 0.67 | Q98: 0.73 | R98: 0.95 | S98: 0.75 | T98: 0.65 | U98: 0.56 | V98: 0.6 | W98: 0.59 | X98: 0.98 | Y98: 1.24 | Z98: 0.73 | AA98: 0.65 | AB98: 0 | AC98: 0 | AD98: 0 | AE98: 0 | AF98: 0
D99: Base Case + 10% | E99: 0.1 | G99: Ag (g/t) | I99: =I98*(1+$E99) -> 1.045 | J99: =J98*(1+$E99) -> 1.386 | K99: =K98*(1+$E99) -> 1.177 | L99: =L98*(1+$E99) -> 1.375 | M99: =M98*(1+$E99) -> 1.078 | N99: =N98*(1+$E99) -> 0.825 | O99: =O98*(1+$E99) -> 0.913 | P99: =P98*(1+$E99) -> 0.737 | ... AF99: =AF98*(1+$E99) -> 0
D100: Base Case - 10% | E100: -0.1 | G100: Ag (g/t) | I100: =I99*(1+$E100) -> 0.9405 | J100: =J99*(1+$E100) -> 1.2474 | K100: =K99*(1+$E100) -> 1.0593 | L100: =L99*(1+$E100) -> 1.2375 | M100: =M99*(1+$E100) -> 0.9702 | N100: =N99*(1+$E100) -> 0.7425 | O100: =O99*(1+$E100) -> 0.8217 | P100: =P99*(1+$E100) -> 0.6633 | ... AF100: =AF99*(1+$E100) -> 0
D101: Free #1 | G101: Ag (g/t) | I101: 0 | J101: 0 | K101: 0 | L101: 0 | M101: 0 | N101: 0 | O101: 0 | P101: 0 | Q101: 0 | R101: 0 | S101: 0 | T101: 0 | U101: 0 | V101: 0 | W101: 0 | X101: 0 | Y101: 0 | Z101: 0 | AA101: 0 | AB101: 0 | AC101: 0 | AD101: 0 | AE101: 0 | AF101: 0
D102: Free #2 | G102: Ag (g/t) | I102: 0 | J102: 0 | K102: 0 | L102: 0 | M102: 0 | N102: 0 | O102: 0 | P102: 0 | Q102: 0 | R102: 0 | S102: 0 | T102: 0 | U102: 0 | V102: 0 | W102: 0 | X102: 0 | Y102: 0 | Z102: 0 | AA102: 0 | AB102: 0 | AC102: 0 | AD102: 0 | AE102: 0 | AF102: 0
D104: WIP Rehandle to Candelaria Plant
D105: WIP Rehandle Ore to Mill | E105: Base Case | I105: =INDEX(I106:I110,MATCH($E105,$D106:$D110,0)) -> 7133 | J105: =INDEX(J106:J110,MATCH($E105,$D106:$D110,0)) -> 3106 | K105: =INDEX(K106:K110,MATCH($E105,$D106:$D110,0)) -> 2395 | L105: =INDEX(L106:L110,MATCH($E105,$D106:$D110,0)) -> 3673 | M105: =INDEX(M106:M110,MATCH($E105,$D106:$D110,0)) -> 2612 | N105: =INDEX(N106:N110,MATCH($E105,$D106:$D110,0)) -> 9639 | O105: =INDEX(O106:O110,MATCH($E105,$D106:$D110,0)) -> 9784 | P105: =INDEX(P106:P110,MATCH($E105,$D106:$D110,0)) -> 11540 | ... AF105: =INDEX(AF106:AF110,MATCH($E105,$D106:$D110,0)) -> 3235
D106: Base Case | G106: Kt | I106: 7133 | J106: 3106 | K106: 2395 | L106: 3673 | M106: 2612 | N106: 9639 | O106: 9784 | P106: 11540 | Q106: 10162 | R106: 6818 | S106: 5475 | T106: 9725 | U106: 12427 | V106: 13286 | W106: 9623 | X106: 8312 | Y106: 5475 | Z106: 12778 | AA106: 16730 | AB106: 22170 | AC106: 22170 | AD106: 22231 | AE106: 22170 | AF106: 3235
D107: Base Case + 10% | E107: 0.1 | G107: Kt | I107: =I106*(1+$E107) -> 7846.3 | J107: =J106*(1+$E107) -> 3416.6 | K107: =K106*(1+$E107) -> 2634.5 | L107: =L106*(1+$E107) -> 4040.3 | M107: =M106*(1+$E107) -> 2873.2 | N107: =N106*(1+$E107) -> 10602.9 | O107: =O106*(1+$E107) -> 10762.4 | P107: =P106*(1+$E107) -> 12694 | ... AF107: =AF106*(1+$E107) -> 3558.5
D108: Base Case - 10% | E108: -0.1 | G108: Kt | I108: =I107*(1+$E108) -> 7061.67 | J108: =J107*(1+$E108) -> 3074.94 | K108: =K107*(1+$E108) -> 2371.05 | L108: =L107*(1+$E108) -> 3636.27 | M108: =M107*(1+$E108) -> 2585.88 | N108: =N107*(1+$E108) -> 9542.61 | O108: =O107*(1+$E108) -> 9686.16 | P108: =P107*(1+$E108) -> 11424.6 | ... AF108: =AF107*(1+$E108) -> 3202.65
D109: Free #1 | G109: Kt | I109: 0 | J109: 0 | K109: 0 | L109: 0 | M109: 0 | N109: 0 | O109: 0 | P109: 0 | Q109: 0 | R109: 0 | S109: 0 | T109: 0 | U109: 0 | V109: 0 | W109: 0 | X109: 0 | Y109: 0 | Z109: 0 | AA109: 0 | AB109: 0 | AC109: 0 | AD109: 0 | AE109: 0 | AF109: 0
D110: Free #2 | G110: Kt | I110: 0 | J110: 0 | K110: 0 | L110: 0 | M110: 0 | N110: 0 | O110: 0 | P110: 0 | Q110: 0 | R110: 0 | S110: 0 | T110: 0 | U110: 0 | V110: 0 | W110: 0 | X110: 0 | Y110: 0 | Z110: 0 | AA110: 0 | AB110: 0 | AC110: 0 | AD110: 0 | AE110: 0 | AF110: 0
D112: Cu Grade | E112: Base Case | I112: =INDEX(I113:I117,MATCH($E112,$D113:$D117,0)) -> 0.0028 | J112: =INDEX(J113:J117,MATCH($E112,$D113:$D117,0)) -> 0.0023 | K112: =INDEX(K113:K117,MATCH($E112,$D113:$D117,0)) -> 0.0024 | L112: =INDEX(L113:L117,MATCH($E112,$D113:$D117,0)) -> 0.0026 | M112: =INDEX(M113:M117,MATCH($E112,$D113:$D117,0)) -> 0.0024 | N112: =INDEX(N113:N117,MATCH($E112,$D113:$D117,0)) -> 0.0025 | O112: =INDEX(O113:O117,MATCH($E112,$D113:$D117,0)) -> 0.0031 | P112: =INDEX(P113:P117,MATCH($E112,$D113:$D117,0)) -> 0.0027 | ... AF112: =INDEX(AF113:AF117,MATCH($E112,$D113:$D117,0)) -> 0.0017
D113: Base Case | G113: Cu (%) | I113: 0.0028 | J113: 0.0023 | K113: 0.0024 | L113: 0.0026 | M113: 0.0024 | N113: 0.0025 | O113: 0.0031 | P113: 0.0027 | Q113: 0.0029 | R113: 0.0029 | S113: 0.0028 | T113: 0.0028 | U113: 0.0028 | V113: 0.0028 | W113: 0.0027 | X113: 0.0027 | Y113: 0.0027 | Z113: 0.0027 | AA113: 0.0027 | AB113: 0.0027 | AC113: 0.002 | AD113: 0.0017 | AE113: 0.0017 | AF113: 0.0017
D114: Base Case + 10% | E114: 0.1 | G114: Cu (%) | I114: =I113*(1+$E114) -> 0.00308 | J114: =J113*(1+$E114) -> 0.00253 | K114: =K113*(1+$E114) -> 0.00264 | L114: =L113*(1+$E114) -> 0.00286 | M114: =M113*(1+$E114) -> 0.00264 | N114: =N113*(1+$E114) -> 0.00275 | O114: =O113*(1+$E114) -> 0.00341 | P114: =P113*(1+$E114) -> 0.00297 | ... AF114: =AF113*(1+$E114) -> 0.00187
D115: Base Case - 10% | E115: -0.1 | G115: Cu (%) | I115: =I114*(1+$E115) -> 0.002772 | J115: =J114*(1+$E115) -> 0.002277 | K115: =K114*(1+$E115) -> 0.002376 | L115: =L114*(1+$E115) -> 0.002574 | M115: =M114*(1+$E115) -> 0.002376 | N115: =N114*(1+$E115) -> 0.002475 | O115: =O114*(1+$E115) -> 0.003069 | P115: =P114*(1+$E115) -> 0.002673 | ... AF115: =AF114*(1+$E115) -> 0.001683
...

Sheet Candelaria Opmod V2Cleaned
I1: 2023 | J1: =I1+1 -> 2024 | K1: =J1+1 -> 2025 | L1: =K1+1 -> 2026 | M1: =L1+1 -> 2027 | N1: =M1+1 -> 2028 | O1: =N1+1 -> 2029 | P1: =O1+1 -> 2030 | Q1: =P1+1 -> 2031 | ... AF1: =AE1+1 -> 2046
D2: Price Deck | G2: Units | H2: Average/Total
D3: Price Deck
D5: Live Price Deck
D6: Cu | I6: 3.82 | J6: 3.78 | K6: 3.63 | L6: 3.97 | M6: 3.97 | N6: 3.97 | O6: 3.97 | P6: 3.97 | Q6: 3.97 | R6: 3.97 | S6: 3.97 | T6: 3.97 | U6: 3.97 | V6: 3.97 | W6: 3.97 | X6: 3.97 | Y6: 3.97 | Z6: 3.97 | AA6: 3.97 | AB6: 3.97 | AC6: 3.97 | AD6: 3.97 | AE6: 3.97 | AF6: 3.97
D7: Au | I7: 1991 | J7: 1950 | K7: 1875 | L7: 1850 | M7: 1850 | N7: 1850 | O7: 1850 | P7: 1850 | Q7: 1850 | R7: 1850 | S7: 1850 | T7: 1850 | U7: 1850 | V7: 1850 | W7: 1850 | X7: 1850 | Y7: 1850 | Z7: 1850 | AA7: 1850 | AB7: 1850 | AC7: 1850 | AD7: 1850 | AE7: 1850 | AF7: 1850
D8: Ag | I8: 23.39 | J8: 22.7 | K8: 22.75 | L8: 22.25 | M8: 22.25 | N8: 22.25 | O8: 22.25 | P8: 22.25 | Q8: 22.25 | R8: 22.25 | S8: 22.25 | T8: 22.25 | U8: 22.25 | V8: 22.25 | W8: 22.25 | X8: 22.25 | Y8: 22.25 | Z8: 22.25 | AA8: 22.25 | AB8: 22.25 | AC8: 22.25 | AD8: 22.25 | AE8: 22.25 | AF8: 22.25
D10: Production | G10: Units | H10: Average/Total
D12: Mine Plan
D14: Candelaria Open Pit Ore to Mill
D15: Candelaria Open Pit Waste Mined | G15: Kt | H15: =SUM(I15:AF15) -> 753583 | I15: ='Candelaria Inputs'!I4 -> 72094 | J15: ='Candelaria Inputs'!J4 -> 67516 | K15: ='Candelaria Inputs'!K4 -> 64748 | L15: ='Candelaria Inputs'!L4 -> 52918 | M15: ='Candelaria Inputs'!M4 -> 61881 | N15: ='Candelaria Inputs'!N4 -> 75416 | O15: ='Candelaria Inputs'!O4 -> 73631 | P15: ='Candelaria Inputs'!P4 -> 66729 | ... AF15: ='Candelaria Inputs'!AF4 -> 0
D16: Ore to Candelaria Plant | G16: Kt | H16: =SUM(I16:AF16) -> 204534 | I16: ='Candelaria Inputs'!I11 -> 13723 | J16: ='Candelaria Inputs'!J11 -> 17280 | K16: ='Candelaria Inputs'!K11 -> 19122 | L16: ='Candelaria Inputs'!L11 -> 16053 | M16: ='Candelaria Inputs'!M11 -> 15601 | N16: ='Candelaria Inputs'!N11 -> 12155 | O16: ='Candelaria Inputs'!O11 -> 6100 | P16: ='Candelaria Inputs'!P11 -> 2725 | ... AF16: ='Candelaria Inputs'!AF11 -> 0
D17: Cu | G17: % | H17: =IF(SUM(I16:AF16)<>0,SUMPRODUCT(I16:AF16,I17:AF17)/SUM(I16:AF16),0) -> 0.0060797946 | I17: ='Candelaria Inputs'!I18 -> 0.0057 | J17: ='Candelaria Inputs'!J18 -> 0.0064 | K17: ='Candelaria Inputs'!K18 -> 0.0051 | L17: ='Candelaria Inputs'!L18 -> 0.0058 | M17: ='Candelaria Inputs'!M18 -> 0.0058 | N17: ='Candelaria Inputs'!N18 -> 0.0059 | O17: ='Candelaria Inputs'!O18 -> 0.0054 | P17: ='Candelaria Inputs'!P18 -> 0.0046 | ... AF17: ='Candelaria Inputs'!AF18 -> 0
D18: Au | G18: g/t | H18: =IF(SUM(I17:AF17)<>0,SUMPRODUCT(I17:AF17,I18:AF18)/SUM(I17:AF17),0) -> 0.14433391 | I18: ='Candelaria Inputs'!I25 -> 0.13 | J18: ='Candelaria Inputs'!J25 -> 0.16 | K18: ='Candelaria Inputs'!K25 -> 0.12 | L18: ='Candelaria Inputs'!L25 -> 0.13 | M18: ='Candelaria Inputs'!M25 -> 0.13 | N18: ='Candelaria Inputs'!N25 -> 0.13 | O18: ='Candelaria Inputs'!O25 -> 0.12 | P18: ='Candelaria Inputs'!P25 -> 0.11 | ... AF18: ='Candelaria Inputs'!AF25 -> 0
D19: Ag | G19: g/t | H19: =IF(SUM(I18:AF18)<>0,SUMPRODUCT(I18:AF18,I19:AF19)/SUM(I18:AF18),0) -> 1.8362632 | I19: ='Candelaria Inputs'!I32 -> 1.46 | J19: ='Candelaria Inputs'!J32 -> 2.74 | K19: ='Candelaria Inputs'!K32 -> 2.03 | L19: ='Candelaria Inputs'!L32 -> 1.8 | M19: ='Candelaria Inputs'!M32 -> 1.71 | N19: ='Candelaria Inputs'!N32 -> 1.94 | O19: ='Candelaria Inputs'!O32 -> 1.49 | P19: ='Candelaria Inputs'!P32 -> 1.26 | ... AF19: ='Candelaria Inputs'!AF32 -> 0
D21: Espanola Ore to Mill
D22: Espanola Open Pit Waste Mined | G22: Kt | H22: =SUM(I22:AF22) -> 138889 | I22: ='Candelaria Inputs'!I40 -> 0 | J22: ='Candelaria Inputs'!J40 -> 9655 | K22: ='Candelaria Inputs'!K40 -> 17090 | L22: ='Candelaria Inputs'!L40 -> 19267 | M22: ='Candelaria Inputs'!M40 -> 17113 | N22: ='Candelaria Inputs'!N40 -> 15524 | O22: ='Candelaria Inputs'!O40 -> 13588 | P22: ='Candelaria Inputs'!P40 -> 12084 | ... AF22: ='Candelaria Inputs'!AF40 -> 0
D23: Ore to Candelaria Plant | G23: Kt | H23: =SUM(I23:AF23) -> 48709 | I23: ='Candelaria Inputs'!I47 -> 0 | J23: ='Candelaria Inputs'!J47 -> 0 | K23: ='Candelaria Inputs'!K47 -> 0 | L23: ='Candelaria Inputs'!L47 -> 2395 | M23: ='Candelaria Inputs'!M47 -> 3965 | N23: ='Candelaria Inputs'!N47 -> 424 | O23: ='Candelaria Inputs'!O47 -> 6162 | P23: ='Candelaria Inputs'!P47 -> 7707 | ... AF23: ='Candelaria Inputs'!AF47 -> 0
D24: Cu | G24: % | H24: =IF(SUM(I23:AF23)<>0,SUMPRODUCT(I23:AF23,I24:AF24)/SUM(I23:AF23),0) -> 0.0042528814 | I24: ='Candelaria Inputs'!I54 -> 0 | J24: ='Candelaria Inputs'!J54 -> 0 | K24: ='Candelaria Inputs'!K54 -> 0 | L24: ='Candelaria Inputs'!L54 -> 0.0042 | M24: ='Candelaria Inputs'!M54 -> 0.004 | N24: ='Candelaria Inputs'!N54 -> 0.0043 | O24: ='Candelaria Inputs'!O54 -> 0.0042 | P24: ='Candelaria Inputs'!P54 -> 0.0044 | ... AF24: ='Candelaria Inputs'!AF54 -> 0
D25: Au | G25: g/t | H25: =IF(SUM(I24:AF24)<>0,SUMPRODUCT(I24:AF24,I25:AF25)/SUM(I24:AF24),0) -> 0.089137931 | I25: ='Candelaria Inputs'!I61 -> 0 | J25: ='Candelaria Inputs'!J61 -> 0 | K25: ='Candelaria Inputs'!K61 -> 0 | L25: ='Candelaria Inputs'!L61 -> 0.09 | M25: ='Candelaria Inputs'!M61 -> 0.08 | N25: ='Candelaria Inputs'!N61 -> 0.09 | O25: ='Candelaria Inputs'!O61 -> 0.09 | P25: ='Candelaria Inputs'!P61 -> 0.09 | ... AF25: ='Candelaria Inputs'!AF61 -> 0
D26: Ag | G26: g/t | H26: =IF(SUM(I25:AF25)<>0,SUMPRODUCT(I25:AF25,I26:AF26)/SUM(I25:AF25),0) -> 0.37397959 | I26: ='Candelaria Inputs'!I68 -> 0 | J26: ='Candelaria Inputs'!J68 -> 0 | K26: ='Candelaria Inputs'!K68 -> 0 | L26: ='Candelaria Inputs'!L68 -> 0.35 | M26: ='Candelaria Inputs'!M68 -> 0.37 | N26: ='Candelaria Inputs'!N68 -> 0.36 | O26: ='Candelaria Inputs'!O68 -> 0.33 | P26: ='Candelaria Inputs'!P68 -> 0.36 | ... AF26: ='Candelaria Inputs'!AF68 -> 0
D28: Candelaria Open Pit + Espanola to WIP
D29: Ore to Candelaria Plant | G29: Kt | H29: =SUM(I29:AF29) -> 174326 | I29: ='Candelaria Inputs'!I76 -> 4610 | J29: ='Candelaria Inputs'!J76 -> 12464 | K29: ='Candelaria Inputs'!K76 -> 13998 | L29: ='Candelaria Inputs'!L76 -> 19387 | M29: ='Candelaria Inputs'!M76 -> 13281 | N29: ='Candelaria Inputs'!N76 -> 13553 | O29: ='Candelaria Inputs'!O76 -> 10012 | P29: ='Candelaria Inputs'!P76 -> 7480 | ... AF29: ='Candelaria Inputs'!AF76 -> 0
D30: Cu | G30: % | H30: =IF(SUM(I29:AF29)<>0,SUMPRODUCT(I29:AF29,I30:AF30)/SUM(I29:AF29),0) -> 0.0023123585 | I30: ='Candelaria Inputs'!I83 -> 0.002 | J30: ='Candelaria Inputs'!J83 -> 0.0022 | K30: ='Candelaria Inputs'!K83 -> 0.0023 | L30: ='Candelaria Inputs'!L83 -> 0.0024 | M30: ='Candelaria Inputs'!M83 -> 0.0025 | N30: ='Candelaria Inputs'!N83 -> 0.0029 | O30: ='Candelaria Inputs'!O83 -> 0.0024 | P30: ='Candelaria Inputs'!P83 -> 0.0023 | ... AF30: ='Candelaria Inputs'!AF83 -> 0
D31: Au | G31: g/t | H31: =IF(SUM(I29:AF29)<>0,SUMPRODUCT(I29:AF29,I31:AF31)/SUM(I29:AF29),0) -> 0.062689616 | I31: ='Candelaria Inputs'!I90 -> 0.06 | J31: ='Candelaria Inputs'!J90 -> 0.07 | K31: ='Candelaria Inputs'!K90 -> 0.06 | L31: ='Candelaria Inputs'!L90 -> 0.07 | M31: ='Candelaria Inputs'!M90 -> 0.07 | N31: ='Candelaria Inputs'!N90 -> 0.07 | O31: ='Candelaria Inputs'!O90 -> 0.06 | P31: ='Candelaria Inputs'!P90 -> 0.06 | ... AF31: ='Candelaria Inputs'!AF90 -> 0
D32: Ag | G32: g/t | H32: =IF(SUM(I29:AF29)<>0,SUMPRODUCT(I29:AF29,I32:AF32)/SUM(I29:AF29),0) -> 0.88632092 | I32: ='Candelaria Inputs'!I97 -> 0.95 | J32: ='Candelaria Inputs'!J97 -> 1.26 | K32: ='Candelaria Inputs'!K97 -> 1.07 | L32: ='Candelaria Inputs'!L97 -> 1.25 | M32: ='Candelaria Inputs'!M97 -> 0.98 | N32: ='Candelaria Inputs'!N97 -> 0.75 | O32: ='Candelaria Inputs'!O97 -> 0.83 | P32: ='Candelaria Inputs'!P97 -> 0.67 | ... AF32: ='Candelaria Inputs'!AF97 -> 0
D34: WIP Rehandle Ore to Mill
D35: Ore to Candelaria Plant | G35: Kt | H35: =SUM(I35:AF35) -> 252669 | I35: ='Candelaria Inputs'!I105 -> 7133 | J35: ='Candelaria Inputs'!J105 -> 3106 | K35: ='Candelaria Inputs'!K105 -> 2395 | L35: ='Candelaria Inputs'!L105 -> 3673 | M35: ='Candelaria Inputs'!M105 -> 2612 | N35: ='Candelaria Inputs'!N105 -> 9639 | O35: ='Candelaria Inputs'!O105 -> 9784 | P35: ='Candelaria Inputs'!P105 -> 11540 | ... AF35: ='Candelaria Inputs'!AF105 -> 3235
D36: Cu | G36: % | H36: =IF(SUM(I35:AF35)<>0,SUMPRODUCT(I35:AF35,I36:AF36)/SUM(I35:AF35),0) -> 0.002478048 | I36: ='Candelaria Inputs'!I112 -> 0.0028 | J36: ='Candelaria Inputs'!J112 -> 0.0023 | K36: ='Candelaria Inputs'!K112 -> 0.0024 | L36: ='Candelaria Inputs'!L112 -> 0.0026 | M36: ='Candelaria Inputs'!M112 -> 0.0024 | N36: ='Candelaria Inputs'!N112 -> 0.0025 | O36: ='Candelaria Inputs'!O112 -> 0.0031 | P36: ='Candelaria Inputs'!P112 -> 0.0027 | ... AF36: ='Candelaria Inputs'!AF112 -> 0.0017
D37: Au | G37: g/t | H37: =IF(SUM(I35:AF35)<>0,SUMPRODUCT(I35:AF35,I37:AF37)/SUM(I35:AF35),0) -> 0.071079119 | I37: ='Candelaria Inputs'!I119 -> 0.08 | J37: ='Candelaria Inputs'!J119 -> 0.07 | K37: ='Candelaria Inputs'!K119 -> 0.07 | L37: ='Candelaria Inputs'!L119 -> 0.07 | M37: ='Candelaria Inputs'!M119 -> 0.07 | N37: ='Candelaria Inputs'!N119 -> 0.07 | O37: ='Candelaria Inputs'!O119 -> 0.08 | P37: ='Candelaria Inputs'!P119 -> 0.08 | ... AF37: ='Candelaria Inputs'!AF119 -> 0.05
D38: Ag | G38: g/t | H38: =IF(SUM(I35:AF35)<>0,SUMPRODUCT(I35:AF35,I38:AF38)/SUM(I35:AF35),0) -> 1.0685556 | I38: ='Candelaria Inputs'!I126 -> 1.2 | J38: ='Candelaria Inputs'!J126 -> 1.06 | K38: ='Candelaria Inputs'!K126 -> 1.06 | L38: ='Candelaria Inputs'!L126 -> 0.94 | M38: ='Candelaria Inputs'!M126 -> 1.1 | N38: ='Candelaria Inputs'!N126 -> 1.14 | O38: ='Candelaria Inputs'!O126 -> 0.71 | P38: ='Candelaria Inputs'!P126 -> 1.19 | ... AF38: ='Candelaria Inputs'!AF126 -> 0.93
D40: Candelaria Underground Ore to Mill
D41: Ore to Candelaria Plant | G41: Kt | H41: =SUM(I41:AF41) -> 131507 | I41: ='Candelaria Inputs'!I134 -> 5462 | J41: ='Candelaria Inputs'!J134 -> 5490 | K41: ='Candelaria Inputs'!K134 -> 5475 | L41: ='Candelaria Inputs'!L134 -> 5475 | M41: ='Candelaria Inputs'!M134 -> 5505 | N41: ='Candelaria Inputs'!N134 -> 5490 | O41: ='Candelaria Inputs'!O134 -> 5475 | P41: ='Candelaria Inputs'!P134 -> 5475 | ... AF41: ='Candelaria Inputs'!AF134 -> 5475
D42: Cu | G42: % | H42: =IF(SUM(I41:AF41)<>0,SUMPRODUCT(I41:AF41,I42:AF42)/SUM(I41:AF41),0) -> 0.0078751922 | I42: ='Candelaria Inputs'!I141 -> 0.0087 | J42: ='Candelaria Inputs'!J141 -> 0.0091 | K42: ='Candelaria Inputs'!K141 -> 0.0093 | L42: ='Candelaria Inputs'!L141 -> 0.0081 | M42: ='Candelaria Inputs'!M141 -> 0.0082 | N42: ='Candelaria Inputs'!N141 -> 0.0081 | O42: ='Candelaria Inputs'!O141 -> 0.0095 | P42: ='Candelaria Inputs'!P141 -> 0.0086 | ... AF42: ='Candelaria Inputs'!AF141 -> 0.0063
D43: Au | G43: g/t | H43: =IF(SUM(I41:AF41)<>0,SUMPRODUCT(I41:AF41,I43:AF43)/SUM(I41:AF41),0) -> 0.17959538 | I43: ='Candelaria Inputs'!I148 -> 0.2 | J43: ='Candelaria Inputs'!J148 -> 0.2 | K43: ='Candelaria Inputs'!K148 -> 0.2 | L43: ='Candelaria Inputs'!L148 -> 0.19 | M43: ='Candelaria Inputs'!M148 -> 0.22 | N43: ='Candelaria Inputs'!N148 -> 0.19 | O43: ='Candelaria Inputs'!O148 -> 0.2 | P43: ='Candelaria Inputs'!P148 -> 0.19 | ... AF43: ='Candelaria Inputs'!AF148 -> 0.15
D44: Ag | G44: g/t | H44: =IF(SUM(I41:AF41)<>0,SUMPRODUCT(I41:AF41,I44:AF44)/SUM(I41:AF41),0) -> 3.2032639 | I44: ='Candelaria Inputs'!I155 -> 3.69 | J44: ='Candelaria Inputs'!J155 -> 3.34 | K44: ='Candelaria Inputs'!K155 -> 2.78 | L44: ='Candelaria Inputs'!L155 -> 3 | M44: ='Candelaria Inputs'!M155 -> 2.66 | N44: ='Candelaria Inputs'!N155 -> 2.86 | O44: ='Candelaria Inputs'!O155 -> 4.37 | P44: ='Candelaria Inputs'!P155 -> 3.68 | ... AF44: ='Candelaria Inputs'!AF155 -> 2.72
D46: Santos Ore to Candelaria Mill
D47: Ore to Candelaria Plant | G47: Kt | H47: =SUM(I47:AF47) -> 1534 | I47: ='Candelaria Inputs'!I163 -> 511 | J47: ='Candelaria Inputs'!J163 -> 512 | K47: ='Candelaria Inputs'!K163 -> 511 | L47: ='Candelaria Inputs'!L163 -> 0 | M47: ='Candelaria Inputs'!M163 -> 0 | N47: ='Candelaria Inputs'!N163 -> 0 | O47: ='Candelaria Inputs'!O163 -> 0 | P47: ='Candelaria Inputs'!P163 -> 0 | ... AF47: ='Candelaria Inputs'!AF163 -> 0
D48: Cu | G48: % | H48: =IF(SUM(I47:AF47)<>0,SUMPRODUCT(I47:AF47,I48:AF48)/SUM(I47:AF47),0) -> 0.0085331812 | I48: ='Candelaria Inputs'!I170 -> 0.0085 | J48: ='Candelaria Inputs'!J170 -> 0.0083 | K48: ='Candelaria Inputs'!K170 -> 0.0088 | L48: ='Candelaria Inputs'!L170 -> 0 | M48: ='Candelaria Inputs'!M170 -> 0 | N48: ='Candelaria Inputs'!N170 -> 0 | O48: ='Candelaria Inputs'!O170 -> 0 | P48: ='Candelaria Inputs'!P170 -> 0 | ... AF48: ='Candelaria Inputs'!AF170 -> 0
D49: Au | G49: g/t | H49: =IF(SUM(I47:AF47)<>0,SUMPRODUCT(I47:AF47,I49:AF49)/SUM(I47:AF47),0) -> 0.19 | I49: ='Candelaria Inputs'!I177 -> 0.18 | J49: ='Candelaria Inputs'!J177 -> 0.19 | K49: ='Candelaria Inputs'!K177 -> 0.2 | L49: ='Candelaria Inputs'!L177 -> 0 | M49: ='Candelaria Inputs'!M177 -> 0 | N49: ='Candelaria Inputs'!N177 -> 0 | O49: ='Candelaria Inputs'!O177 -> 0 | P49: ='Candelaria Inputs'!P177 -> 0 | ... AF49: ='Candelaria Inputs'!AF177 -> 0
D50: Ag | G50: g/t | H50: =IF(SUM(I47:AF47)<>0,SUMPRODUCT(I47:AF47,I50:AF50)/SUM(I47:AF47),0) -> 1.9400587 | I50: ='Candelaria Inputs'!I184 -> 1.74 | J50: ='Candelaria Inputs'!J184 -> 2.03 | K50: ='Candelaria Inputs'!K184 -> 2.05 | L50: ='Candelaria Inputs'!L184 -> 0 | M50: ='Candelaria Inputs'!M184 -> 0 | N50: ='Candelaria Inputs'!N184 -> 0 | O50: ='Candelaria Inputs'!O184 -> 0 | P50: ='Candelaria Inputs'!P184 -> 0 | ... AF50: ='Candelaria Inputs'!AF184 -> 0
D52: Alcaparrosa Ore to Mill
D53: Ore to Candelaria Plant | G53: Kt | H53: =SUM(I53:AF53) -> 0 | I53: ='Candelaria Inputs'!I192 -> 0 | J53: ='Candelaria Inputs'!J192 -> 0 | K53: ='Candelaria Inputs'!K192 -> 0 | L53: ='Candelaria Inputs'!L192 -> 0 | M53: ='Candelaria Inputs'!M192 -> 0 | N53: ='Candelaria Inputs'!N192 -> 0 | O53: ='Candelaria Inputs'!O192 -> 0 | P53: ='Candelaria Inputs'!P192 -> 0 | ... AF53: ='Candelaria Inputs'!AF192 -> 0
D54: Cu | G54: % | H54: =IF(SUM(I53:AF53)<>0,SUMPRODUCT(I53:AF53,I54:AF54)/SUM(I53:AF53),0) -> 0 | I54: ='Candelaria Inputs'!I199 -> 0 | J54: ='Candelaria Inputs'!J199 -> 0 | K54: ='Candelaria Inputs'!K199 -> 0 | L54: ='Candelaria Inputs'!L199 -> 0 | M54: ='Candelaria Inputs'!M199 -> 0 | N54: ='Candelaria Inputs'!N199 -> 0 | O54: ='Candelaria Inputs'!O199 -> 0 | P54: ='Candelaria Inputs'!P199 -> 0 | ... AF54: ='Candelaria Inputs'!AF199 -> 0
D55: Au | G55: g/t | H55: =IF(SUM(I53:AF53)<>0,SUMPRODUCT(I53:AF53,I55:AF55)/SUM(I53:AF53),0) -> 0 | I55: ='Candelaria Inputs'!I206 -> 0 | J55: ='Candelaria Inputs'!J206 -> 0 | K55: ='Candelaria Inputs'!K206 -> 0 | L55: ='Candelaria Inputs'!L206 -> 0 | M55: ='Candelaria Inputs'!M206 -> 0 | N55: ='Candelaria Inputs'!N206 -> 0 | O55: ='Candelaria Inputs'!O206 -> 0 | P55: ='Candelaria Inputs'!P206 -> 0 | ... AF55: ='Candelaria Inputs'!AF206 -> 0
D56: Ag | G56: g/t | H56: =IF(SUM(I53:AF53)<>0,SUMPRODUCT(I53:AF53,I56:AF56)/SUM(I53:AF53),0) -> 0 | I56: ='Candelaria Inputs'!I213 -> 0 | J56: ='Candelaria Inputs'!J213 -> 0 | K56: ='Candelaria Inputs'!K213 -> 0 | L56: ='Candelaria Inputs'!L213 -> 0 | M56: ='Candelaria Inputs'!M213 -> 0 | N56: ='Candelaria Inputs'!N213 -> 0 | O56: ='Candelaria Inputs'!O213 -> 0 | P56: ='Candelaria Inputs'!P213 -> 0 | ... AF56: ='Candelaria Inputs'!AF213 -> 0
D58: Santos Ore to PAC Mill
D59: Ore to PAC Plant | G59: Kt | H59: =SUM(I59:AF59) -> 15263 | I59: ='Candelaria Inputs'!I221 -> 1312 | J59: ='Candelaria Inputs'!J221 -> 1329 | K59: ='Candelaria Inputs'!K221 -> 1327 | L59: ='Candelaria Inputs'!L221 -> 1348 | M59: ='Candelaria Inputs'!M221 -> 1358 | N59: ='Candelaria Inputs'!N221 -> 1354 | O59: ='Candelaria Inputs'!O221 -> 1351 | P59: ='Candelaria Inputs'!P221 -> 1351 | ... AF59: ='Candelaria Inputs'!AF221 -> 0
D60: Cu | G60: % | H60: =IF(SUM(I59:AF59)<>0,SUMPRODUCT(I59:AF59,I60:AF60)/SUM(I59:AF59),0) -> 0.0088602503 | I60: ='Candelaria Inputs'!I228 -> 0.0103 | J60: ='Candelaria Inputs'!J228 -> 0.01 | K60: ='Candelaria Inputs'!K228 -> 0.0105 | L60: ='Candelaria Inputs'!L228 -> 0.0102 | M60: ='Candelaria Inputs'!M228 -> 0.0092 | N60: ='Candelaria Inputs'!N228 -> 0.0093 | O60: ='Candelaria Inputs'!O228 -> 0.0087 | P60: ='Candelaria Inputs'!P228 -> 0.007 | ... AF60: ='Candelaria Inputs'!AF228 -> 0
D61: Au | G61: g/t | H61: =IF(SUM(I59:AF59)<>0,SUMPRODUCT(I59:AF59,I61:AF61)/SUM(I59:AF59),0) -> 0.20630217 | I61: ='Candelaria Inputs'!I235 -> 0.22 | J61: ='Candelaria Inputs'!J235 -> 0.23 | K61: ='Candelaria Inputs'!K235 -> 0.24 | L61: ='Candelaria Inputs'!L235 -> 0.23 | M61: ='Candelaria Inputs'!M235 -> 0.22 | N61: ='Candelaria Inputs'!N235 -> 0.22 | O61: ='Candelaria Inputs'!O235 -> 0.2 | P61: ='Candelaria Inputs'!P235 -> 0.17 | ... AF61: ='Candelaria Inputs'!AF235 -> 0
D62: Ag | G62: g/t | H62: =IF(SUM(I59:AF59)<>0,SUMPRODUCT(I59:AF59,I62:AF62)/SUM(I59:AF59),0) -> 2.0628029 | I62: ='Candelaria Inputs'!I242 -> 2.1 | J62: ='Candelaria Inputs'!J242 -> 2.44 | K62: ='Candelaria Inputs'!K242 -> 2.44 | L62: ='Candelaria Inputs'!L242 -> 2.47 | M62: ='Candelaria Inputs'!M242 -> 2.54 | N62: ='Candelaria Inputs'!N242 -> 2.11 | O62: ='Candelaria Inputs'!O242 -> 1.95 | P62: ='Candelaria Inputs'!P242 -> 1.48 | ... AF62: ='Candelaria Inputs'!AF242 -> 0
D64: Inventory Movement
D66: WIP Movement
D67: Beginning WIP Balance | G67: Kt | I67: 78343 | J67: =I79 -> 75820 | K67: =J79 -> 85178 | L67: =K79 -> 96781 | M67: =L79 -> 112495 | N67: =M79 -> 123164 | O67: =N79 -> 127078 | P67: =O79 -> 127306 | Q67: =P79 -> 123246 | ... AF67: =AE79 -> 3235
D68: Cu | G68: % | I68: 0.0028467342 | J68: =I80 -> 0.0027996479 | K68: =J80 -> 0.0027301216 | L68: =K80 -> 0.00267608 | M68: =L80 -> 0.0026309854 | N68: =M80 -> 0.0026217596 | O68: =N80 -> 0.0026606698 | P68: =O80 -> 0.002606405 | Q68: =P80 -> 0.0025790452 | ... AF68: =AE80 -> 0.0017
D69: Au | G69: g/t | I69: 0.089747138 | J69: =I81 -> 0.088855447 | K69: =J81 -> 0.086783911 | L69: =K81 -> 0.083325343 | M69: =L81 -> 0.081463976 | N69: =M81 -> 0.080470917 | O69: =N81 -> 0.080148413 | P69: =O81 -> 0.078575244 | Q69: =P81 -> 0.077314477 | ... AF69: =AE81 -> 0.05
D70: Ag | G70: g/t | I70: 1.4740575 | J70: =I82 -> 1.4679767 | K70: =J82 -> 1.4524205 | L70: =K82 -> 1.4068198 | M70: =L82 -> 1.3950359 | N70: =M82 -> 1.3565388 | O70: =N82 -> 1.3082755 | P70: =O82 -> 1.3166414 | Q70: =P82 -> 1.2892536 | ... AF70: =AE82 -> 0.93
D71: WIP Inflow | G71: Kt | I71: =I29 -> 4610 | J71: =J29 -> 12464 | K71: =K29 -> 13998 | L71: =L29 -> 19387 | M71: =M29 -> 13281 | N71: =N29 -> 13553 | O71: =O29 -> 10012 | P71: =P29 -> 7480 | ... AF71: =AF29 -> 0
D72: Cu | G72: % | I72: =I30 -> 0.002 | J72: =J30 -> 0.0022 | K72: =K30 -> 0.0023 | L72: =L30 -> 0.0024 | M72: =M30 -> 0.0025 | N72: =N30 -> 0.0029 | O72: =O30 -> 0.0024 | P72: =P30 -> 0.0023 | ... AF72: =AF30 -> 0
D73: Au | G73: g/t | I73: =I31 -> 0.06 | J73: =J31 -> 0.07 | K73: =K31 -> 0.06 | L73: =L31 -> 0.07 | M73: =M31 -> 0.07 | N73: =N31 -> 0.07 | O73: =O31 -> 0.06 | P73: =P31 -> 0.06 | ... AF73: =AF31 -> 0
D74: Ag | G74: g/t | I74: =I32 -> 0.95 | J74: =J32 -> 1.26 | K74: =K32 -> 1.07 | L74: =L32 -> 1.25 | M74: =M32 -> 0.98 | N74: =N32 -> 0.75 | O74: =O32 -> 0.83 | P74: =P32 -> 0.67 | ... AF74: =AF32 -> 0
D75: WIP Outflow | G75: Kt | I75: =IF((I67+I71)>=I35,I35,I67+I71) -> 7133 | J75: =IF((J67+J71)>=J35,J35,J67+J71) -> 3106 | K75: =IF((K67+K71)>=K35,K35,K67+K71) -> 2395 | L75: =IF((L67+L71)>=L35,L35,L67+L71) -> 3673 | M75: =IF((M67+M71)>=M35,M35,M67+M71) -> 2612 | N75: =IF((N67+N71)>=N35,N35,N67+N71) -> 9639 | O75: =IF((O67+O71)>=O35,O35,O67+O71) -> 9784 | P75: =IF((P67+P71)>=P35,P35,P67+P71) -> 11540 | ... AF75: =IF((AF67+AF71)>=AF35,AF35,AF67+AF71) -> 3235
D76: Cu | G76: % | I76: =IF(I36<=(I$67*I68+I$71*I72)/I$75,I36,(I$67*I68+I$71*I72)/I$75) -> 0.0028 | J76: =IF(J36<=(J$67*J68+J$71*J72)/J$75,J36,(J$67*J68+J$71*J72)/J$75) -> 0.0023 | K76: =IF(K36<=(K$67*K68+K$71*K72)/K$75,K36,(K$67*K68+K$71*K72)/K$75) -> 0.0024 | L76: =IF(L36<=(L$67*L68+L$71*L72)/L$75,L36,(L$67*L68+L$71*L72)/L$75) -> 0.0026 | M76: =IF(M36<=(M$67*M68+M$71*M72)/M$75,M36,(M$67*M68+M$71*M72)/M$75) -> 0.0024 | N76: =IF(N36<=(N$67*N68+N$71*N72)/N$75,N36,(N$67*N68+N$71*N72)/N$75) -> 0.0025 | O76: =IF(O36<=(O$67*O68+O$71*O72)/O$75,O36,(O$67*O68+O$71*O72)/O$75) -> 0.0031 | P76: =IF(P36<=(P$67*P68+P$71*P72)/P$75,P36,(P$67*P68+P$71*P72)/P$75) -> 0.0027 | ... AF76: =IF(AF36<=(AF$67*AF68+AF$71*AF72)/AF$75,AF36,(AF$67*AF68+AF$71*AF72)/AF$75) -> 0.0017
D77: Au | G77: g/t | I77: =IF(I37<=(I$67*I69+I$71*I73)/I$75,I37,(I$67*I69+I$71*I73)/I$75) -> 0.08 | J77: =IF(J37<=(J$67*J69+J$71*J73)/J$75,J37,(J$67*J69+J$71*J73)/J$75) -> 0.07 | K77: =IF(K37<=(K$67*K69+K$71*K73)/K$75,K37,(K$67*K69+K$71*K73)/K$75) -> 0.07 | L77: =IF(L37<=(L$67*L69+L$71*L73)/L$75,L37,(L$67*L69+L$71*L73)/L$75) -> 0.07 | M77: =IF(M37<=(M$67*M69+M$71*M73)/M$75,M37,(M$67*M69+M$71*M73)/M$75) -> 0.07 | N77: =IF(N37<=(N$67*N69+N$71*N73)/N$75,N37,(N$67*N69+N$71*N73)/N$75) -> 0.07 | O77: =IF(O37<=(O$67*O69+O$71*O73)/O$75,O37,(O$67*O69+O$71*O73)/O$75) -> 0.08 | P77: =IF(P37<=(P$67*P69+P$71*P73)/P$75,P37,(P$67*P69+P$71*P73)/P$75) -> 0.08 | ... AF77: =IF(AF37<=(AF$67*AF69+AF$71*AF73)/AF$75,AF37,(AF$67*AF69+AF$71*AF73)/AF$75) -> 0.05
D78: Ag | G78: g/t | I78: =IF(I38<=(I$67*I70+I$71*I74)/I$75,I38,(I$67*I70+I$71*I74)/I$75) -> 1.2 | J78: =IF(J38<=(J$67*J70+J$71*J74)/J$75,J38,(J$67*J70+J$71*J74)/J$75) -> 1.06 | K78: =IF(K38<=(K$67*K70+K$71*K74)/K$75,K38,(K$67*K70+K$71*K74)/K$75) -> 1.06 | L78: =IF(L38<=(L$67*L70+L$71*L74)/L$75,L38,(L$67*L70+L$71*L74)/L$75) -> 0.94 | M78: =IF(M38<=(M$67*M70+M$71*M74)/M$75,M38,(M$67*M70+M$71*M74)/M$75) -> 1.1 | N78: =IF(N38<=(N$67*N70+N$71*N74)/N$75,N38,(N$67*N70+N$71*N74)/N$75) -> 1.14 | O78: =IF(O38<=(O$67*O70+O$71*O74)/O$75,O38,(O$67*O70+O$71*O74)/O$75) -> 0.71 | P78: =IF(P38<=(P$67*P70+P$71*P74)/P$75,P38,(P$67*P70+P$71*P74)/P$75) -> 1.19 | ... AF78: =IF(AF38<=(AF$67*AF70+AF$71*AF74)/AF$75,AF38,(AF$67*AF70+AF$71*AF74)/AF$75) -> 0.93
D79: Ending WIP Balance | G79: Kt | I79: =I67+I71-I75 -> 75820 | J79: =J67+J71-J75 -> 85178 | K79: =K67+K71-K75 -> 96781 | L79: =L67+L71-L75 -> 112495 | M79: =M67+M71-M75 -> 123164 | N79: =N67+N71-N75 -> 127078 | O79: =O67+O71-O75 -> 127306 | P79: =P67+P71-P75 -> 123246 | ... AF79: =AF67+AF71-AF75 -> 0
D80: Cu | G80: % | I80: =IF((I67+I71-I75)<>0,(I67*I68+I71*I72-I75*I76)/(I67+I71-I75),0) -> 0.0027996479 | J80: =IF((J67+J71-J75)<>0,(J67*J68+J71*J72-J75*J76)/(J67+J71-J75),0) -> 0.0027301216 | K80: =IF((K67+K71-K75)<>0,(K67*K68+K71*K72-K75*K76)/(K67+K71-K75),0) -> 0.00267608 | L80: =IF((L67+L71-L75)<>0,(L67*L68+L71*L72-L75*L76)/(L67+L71-L75),0) -> 0.0026309854 | M80: =IF((M67+M71-M75)<>0,(M67*M68+M71*M72-M75*M76)/(M67+M71-M75),0) -> 0.0026217596 | N80: =IF((N67+N71-N75)<>0,(N67*N68+N71*N72-N75*N76)/(N67+N71-N75),0) -> 0.0026606698 | O80: =IF((O67+O71-O75)<>0,(O67*O68+O71*O72-O75*O76)/(O67+O71-O75),0) -> 0.002606405 | P80: =IF((P67+P71-P75)<>0,(P67*P68+P71*P72-P75*P76)/(P67+P71-P75),0) -> 0.0025790452 | ... AF80: =IF((AF67+AF71-AF75)<>0,(AF67*AF68+AF71*AF72-AF75*AF76)/(AF67+AF71-AF75),0) -> 0
D81: Au | G81: g/t | I81: =IF((I67+I71-I75)<>0,(I67*I69+I71*I73-I75*I77)/(I67+I71-I75),0) -> 0.088855447 | J81: =IF((J67+J71-J75)<>0,(J67*J69+J71*J73-J75*J77)/(J67+J71-J75),0) -> 0.086783911 | K81: =IF((K67+K71-K75)<>0,(K67*K69+K71*K73-K75*K77)/(K67+K71-K75),0) -> 0.083325343 | L81: =IF((L67+L71-L75)<>0,(L67*L69+L71*L73-L75*L77)/(L67+L71-L75),0) -> 0.081463976 | M81: =IF((M67+M71-M75)<>0,(M67*M69+M71*M73-M75*M77)/(M67+M71-M75),0) -> 0.080470917 | N81: =IF((N67+N71-N75)<>0,(N67*N69+N71*N73-N75*N77)/(N67+N71-N75),0) -> 0.080148413 | O81: =IF((O67+O71-O75)<>0,(O67*O69+O71*O73-O75*O77)/(O67+O71-O75),0) -> 0.078575244 | P81: =IF((P67+P71-P75)<>0,(P67*P69+P71*P73-P75*P77)/(P67+P71-P75),0) -> 0.077314477 | ... AF81: =IF((AF67+AF71-AF75)<>0,(AF67*AF69+AF71*AF73-AF75*AF77)/(AF67+AF71-AF75),0) -> 0
D82: Ag | G82: g/t | I82: =IF((I67+I71-I75)<>0,(I67*I70+I71*I74-I75*I78)/(I67+I71-I75),0) -> 1.4679767 | J82: =IF((J67+J71-J75)<>0,(J67*J70+J71*J74-J75*J78)/(J67+J71-J75),0) -> 1.4524205 | K82: =IF((K67+K71-K75)<>0,(K67*K70+K71*K74-K75*K78)/(K67+K71-K75),0) -> 1.4068198 | L82: =IF((L67+L71-L75)<>0,(L67*L70+L71*L74-L75*L78)/(L67+L71-L75),0) -> 1.3950359 | M82: =IF((M67+M71-M75)<>0,(M67*M70+M71*M74-M75*M78)/(M67+M71-M75),0) -> 1.3565388 | N82: =IF((N67+N71-N75)<>0,(N67*N70+N71*N74-N75*N78)/(N67+N71-N75),0) -> 1.3082755 | O82: =IF((O67+O71-O75)<>0,(O67*O70+O71*O74-O75*O78)/(O67+O71-O75),0) -> 1.3166414 | P82: =IF((P67+P71-P75)<>0,(P67*P70+P71*P74-P75*P78)/(P67+P71-P75),0) -> 1.2892536 | ... AF82: =IF((AF67+AF71-AF75)<>0,(AF67*AF70+AF71*AF74-AF75*AF78)/(AF67+AF71-AF75),0) -> 0
D84: Mill Production
D86: Total Ore to Candelaria Plant
D87: Ore to Candelaria Plant | G87: Kt | H87: =SUM(I87:AF87) -> 638953 | I87: =I16+I23+I35+I41+I47+I53 -> 26829 | J87: =J16+J23+J35+J41+J47+J53 -> 26388 | K87: =K16+K23+K35+K41+K47+K53 -> 27503 | L87: =L16+L23+L35+L41+L47+L53 -> 27596 | M87: =M16+M23+M35+M41+M47+M53 -> 27683 | N87: =N16+N23+N35+N41+N47+N53 -> 27708 | O87: =O16+O23+O35+O41+O47+O53 -> 27521 | P87: =P16+P23+P35+P41+P47+P53 -> 27447 | ... AF87: =AF16+AF23+AF35+AF41+AF47+AF53 -> 8710
D88: Cu | G88: % | H88: =IF(SUM(I87:AF87)<>0,SUMPRODUCT(I87:AF87,I88:AF88)/SUM(I87:AF87),0) -> 0.004891654 | I88: =(I$16*I17+I$23*I24+I$35*I36+I$41*I42+I$47*I48+I$53*I54)/I$87 -> 0.0055930672 | J88: =(J$16*J17+J$23*J24+J$35*J36+J$41*J42+J$47*J48+J$53*J54)/J$87 -> 0.0065160073 | K88: =(K$16*K17+K$23*K24+K$35*K36+K$41*K42+K$47*K48+K$53*K54)/K$87 -> 0.005769716 | L88: =(L$16*L17+L$23*L24+L$35*L36+L$41*L42+L$47*L48+L$53*L54)/L$87 -> 0.0056915386 | M88: =(M$16*M17+M$23*M24+M$35*M36+M$41*M42+M$47*M48+M$53*M54)/M$87 -> 0.0056986454 | N88: =(N$16*N17+N$23*N24+N$35*N36+N$41*N42+N$47*N48+N$53*N54)/N$87 -> 0.0051286343 | O88: =(O$16*O17+O$23*O24+O$35*O36+O$41*O42+O$47*O48+O$53*O54)/O$87 -> 0.005129294 | P88: =(P$16*P17+P$23*P24+P$35*P36+P$41*P42+P$47*P48+P$53*P54)/P$87 -> 0.0045428936 | ... AF88: =(AF$16*AF17+AF$23*AF24+AF$35*AF36+AF$41*AF42+AF$47*AF48+AF$53*AF54)/AF$87 -> 0.004591504
D89: Au | G89: g/t | H89: =IF(SUM(I88:AF88)<>0,SUMPRODUCT(I88:AF88,I89:AF89)/SUM(I88:AF88),0) -> 0.12180022 | I89: =(I$16*I18+I$23*I25+I$35*I37+I$41*I43+I$47*I49+I$53*I55)/I$87 -> 0.13190987 | J89: =(J$16*J18+J$23*J25+J$35*J37+J$41*J43+J$47*J49+J$53*J55)/J$87 -> 0.1583106 | K89: =(K$16*K18+K$23*K25+K$35*K37+K$41*K43+K$47*K49+K$53*K55)/K$87 -> 0.13305785 | L89: =(L$16*L18+L$23*L25+L$35*L37+L$41*L43+L$47*L49+L$53*L55)/L$87 -> 0.13044644 | M89: =(M$16*M18+M$23*M25+M$35*M37+M$41*M43+M$47*M49+M$53*M55)/M$87 -> 0.13507459 | N89: =(N$16*N18+N$23*N25+N$35*N37+N$41*N43+N$47*N49+N$53*N55)/N$87 -> 0.12040349 | O89: =(O$16*O18+O$23*O25+O$35*O37+O$41*O43+O$47*O49+O$53*O55)/O$87 -> 0.11497765 | P89: =(P$16*P18+P$23*P25+P$35*P37+P$41*P43+P$47*P49+P$53*P55)/P$87 -> 0.10772871 | ... AF89: =(AF$16*AF18+AF$23*AF25+AF$35*AF37+AF$41*AF43+AF$47*AF49+AF$53*AF55)/AF$87 -> 0.11285878
D90: Ag | G90: g/t | H90: =IF(SUM(I89:AF89)<>0,SUMPRODUCT(I89:AF89,I90:AF90)/SUM(I89:AF89),0) -> 1.7698598 | I90: =(I$16*I19+I$23*I26+I$35*I38+I$41*I44+I$47*I50+I$53*I56)/I$87 -> 1.8502031 | J90: =(J$16*J19+J$23*J26+J$35*J38+J$41*J44+J$47*J50+J$53*J56)/J$87 -> 2.6533091 | K90: =(K$16*K19+K$23*K26+K$35*K38+K$41*K44+K$47*K50+K$53*K56)/K$87 -> 2.0952045 | L90: =(L$16*L19+L$23*L26+L$35*L38+L$41*L44+L$47*L50+L$53*L56)/L$87 -> 1.7977703 | M90: =(M$16*M19+M$23*M26+M$35*M38+M$41*M44+M$47*M50+M$53*M56)/M$87 -> 1.6494332 | N90: =(N$16*N19+N$23*N26+N$35*N38+N$41*N44+N$47*N50+N$53*N56)/N$87 -> 1.8198066 | O90: =(O$16*O19+O$23*O26+O$35*O38+O$41*O44+O$47*O50+O$53*O56)/O$87 -> 1.5259202 | P90: =(P$16*P19+P$23*P26+P$35*P38+P$41*P44+P$47*P50+P$53*P56)/P$87 -> 1.4605829 | ... AF90: =(AF$16*AF19+AF$23*AF26+AF$35*AF38+AF$41*AF44+AF$47*AF50+AF$53*AF56)/AF$87 -> 2.0551722
D91: Total Cu in Concentrate to Candelaria Plant | G91: Kt | H91: =SUM(I91:AF91) -> 3125.537 | I91: =I87*I88 -> 150.0564 | J91: =J87*J88 -> 171.9444 | K91: =K87*K88 -> 158.6845 | L91: =L87*L88 -> 157.0637 | M91: =M87*M88 -> 157.7556 | N91: =N87*N88 -> 142.1042 | O91: =O87*O88 -> 141.1633 | P91: =P87*P88 -> 124.6888 | ... AF91: =AF87*AF88 -> 39.992
D92: Total Au in Concentrate to Candelaria Plant | G92: Koz | H92: =SUM(I92:AF92) -> 2403.2867 | I92: =I87*I89*32.1507/1000 -> 113.78165 | J92: =J87*J89*32.1507/1000 -> 134.30955 | K92: =K87*K89*32.1507/1000 -> 117.65517 | L92: =L87*L89*32.1507/1000 -> 115.73609 | M92: =M87*M89*32.1507/1000 -> 120.22015 | N92: =N87*N89*32.1507/1000 -> 107.25924 | O92: =O87*O89*32.1507/1000 -> 101.73446 | P92: =P87*P89*32.1507/1000 -> 95.064154 | ... AF92: =AF87*AF89*32.1507/1000 -> 31.604138
D93: Total Ag in Concentrate to Candelaria Plant | G93: Koz | H93: =SUM(I93:AF93) -> 35166.768 | I93: =I87*I90*32.1507/1000 -> 1595.9318 | J93: =J87*J90*32.1507/1000 -> 2251.048 | K93: =K87*K90*32.1507/1000 -> 1852.6651 | L93: =L87*L90*32.1507/1000 -> 1595.0371 | M93: =M87*M90*32.1507/1000 -> 1468.0415 | N93: =N87*N90*32.1507/1000 -> 1621.1412 | O93: =O87*O90*32.1507/1000 -> 1350.1638 | P93: =P87*P90*32.1507/1000 -> 1288.8772 | ... AF93: =AF87*AF90*32.1507/1000 -> 575.51521
D95: Cu Recovery - Candelaria Plant | G95: % | H95: =IF(SUM(I91:AF91)<>0,SUMPRODUCT(I91:AF91,I95:AF95)/SUM(I91:AF91),0) -> 0.90582647 | I95: ='Candelaria Inputs'!I250 -> 0.921 | J95: ='Candelaria Inputs'!J250 -> 0.929 | K95: ='Candelaria Inputs'!K250 -> 0.931 | L95: ='Candelaria Inputs'!L250 -> 0.928 | M95: ='Candelaria Inputs'!M250 -> 0.93 | N95: ='Candelaria Inputs'!N250 -> 0.925 | O95: ='Candelaria Inputs'!O250 -> 0.922 | P95: ='Candelaria Inputs'!P250 -> 0.93 | ... AF95: ='Candelaria Inputs'!AF250 -> 0.826
D96: Au Recovery - Candelaria Plant | G96: % | H96: =IF(SUM(I92:AF92)<>0,SUMPRODUCT(I92:AF92,I96:AF96)/SUM(I92:AF92),0) -> 0.70457113 | I96: ='Candelaria Inputs'!I257 -> 0.709 | J96: ='Candelaria Inputs'!J257 -> 0.722 | K96: ='Candelaria Inputs'!K257 -> 0.718 | L96: ='Candelaria Inputs'!L257 -> 0.718 | M96: ='Candelaria Inputs'!M257 -> 0.718 | N96: ='Candelaria Inputs'!N257 -> 0.699 | O96: ='Candelaria Inputs'!O257 -> 0.699 | P96: ='Candelaria Inputs'!P257 -> 0.699 | ... AF96: ='Candelaria Inputs'!AF257 -> 0.699
D97: Ag Recovery - Candelaria Plant | G97: % | H97: =IF(SUM(I93:AF93)<>0,SUMPRODUCT(I93:AF93,I97:AF97)/SUM(I93:AF93),0) -> 0.81123287 | I97: ='Candelaria Inputs'!I264 -> 0.815 | J97: ='Candelaria Inputs'!J264 -> 0.827 | K97: ='Candelaria Inputs'!K264 -> 0.822 | L97: ='Candelaria Inputs'!L264 -> 0.814 | M97: ='Candelaria Inputs'!M264 -> 0.814 | N97: ='Candelaria Inputs'!N264 -> 0.814 | O97: ='Candelaria Inputs'!O264 -> 0.799 | P97: ='Candelaria Inputs'!P264 -> 0.799 | ... AF97: ='Candelaria Inputs'!AF264 -> 0.814
D99: Recovered Cu in Concentrate - Candelaria Plant | G99: Kt | H99: =SUM(I99:AF99) -> 2831.1941 | I99: =I91*I95 -> 138.20194 | J99: =J91*J95 -> 159.73635 | K99: =K91*K95 -> 147.73527 | L99: =L91*L95 -> 145.75511 | M99: =M91*M95 -> 146.71271 | N99: =N91*N95 -> 131.44638 | O99: =O91*O95 -> 130.15256 | P99: =P91*P95 -> 115.96058 | ... AF99: =AF91*AF95 -> 33.033392
D100: Recovered Au in Concentrate - Candelaria Plant | G100: Koz | H100: =SUM(I100:AF100) -> 1693.2864 | I100: =I92*I96 -> 80.671189 | J100: =J92*J96 -> 96.971495 | K100: =K92*K96 -> 84.476409 | L100: =L92*L96 -> 83.098513 | M100: =M92*M96 -> 86.318066 | N100: =N92*N96 -> 74.974206 | O100: =O92*O96 -> 71.112388 | P100: =P92*P96 -> 66.449844 | ... AF100: =AF92*AF96 -> 22.091293
D101: Recovered Ag in Concentrate - Candelaria Plant | G101: Koz | H101: =SUM(I101:AF101) -> 28528.438 | I101: =I93*I97 -> 1300.6844 | J101: =J93*J97 -> 1861.6167 | K101: =K93*K97 -> 1522.8907 | L101: =L93*L97 -> 1298.3602 | M101: =M93*M97 -> 1194.9858 | N101: =N93*N97 -> 1319.6089 | O101: =O93*O97 -> 1078.7809 | P101: =P93*P97 -> 1029.8129 | ... AF101: =AF93*AF97 -> 468.46938
D103: Total Ore to PAC
D104: Ore to PAC Plant | G104: Kt | H104: =SUM(I104:AF104) -> 15263 | I104: =I59 -> 1312 | J104: =J59 -> 1329 | K104: =K59 -> 1327 | L104: =L59 -> 1348 | M104: =M59 -> 1358 | N104: =N59 -> 1354 | O104: =O59 -> 1351 | P104: =P59 -> 1351 | ... AF104: =AF59 -> 0
D105: Cu | G105: % | H105: =SUMPRODUCT(I104:AF104,I105:AF105)/SUM(I104:AF104) -> 0.0088602503 | I105: =I60 -> 0.0103 | J105: =J60 -> 0.01 | K105: =K60 -> 0.0105 | L105: =L60 -> 0.0102 | M105: =M60 -> 0.0092 | N105: =N60 -> 0.0093 | O105: =O60 -> 0.0087 | P105: =P60 -> 0.007 | ... AF105: =AF60 -> 0
D106: Au | G106: g/t | H106: =SUMPRODUCT(I104:AF104,I106:AF106)/SUM(I104:AF104) -> 0.20630217 | I106: =I61 -> 0.22 | J106: =J61 -> 0.23 | K106: =K61 -> 0.24 | L106: =L61 -> 0.23 | M106: =M61 -> 0.22 | N106: =N61 -> 0.22 | O106: =O61 -> 0.2 | P106: =P61 -> 0.17 | ... AF106: =AF61 -> 0
D107: Ag | G107: g/t | H107: =SUMPRODUCT(I104:AF104,I107:AF107)/SUM(I104:AF104) -> 2.0628029 | I107: =I62 -> 2.1 | J107: =J62 -> 2.44 | K107: =K62 -> 2.44 | L107: =L62 -> 2.47 | M107: =M62 -> 2.54 | N107: =N62 -> 2.11 | O107: =O62 -> 1.95 | P107: =P62 -> 1.48 | ... AF107: =AF62 -> 0
D108: Total Cu in Concentrate to PAC Plant | G108: Kt | H108: =SUM(I108:AF108) -> 135.234 | I108: =I104*I105 -> 13.5136 | J108: =J104*J105 -> 13.29 | K108: =K104*K105 -> 13.9335 | L108: =L104*L105 -> 13.7496 | M108: =M104*M105 -> 12.4936 | N108: =N104*N105 -> 12.5922 | O108: =O104*O105 -> 11.7537 | P108: =P104*P105 -> 9.457 | ... AF108: =AF104*AF105 -> 0
D109: Total Au in Concentrate to PAC Plant | G109: Koz | H109: =SUM(I109:AF109) -> 101.2358 | I109: =I104*I106*32.1507/1000 -> 9.279978 | J109: =J104*J106*32.1507/1000 -> 9.8275045 | K109: =K104*K106*32.1507/1000 -> 10.239355 | L109: =L104*L106*32.1507/1000 -> 9.968003 | M109: =M104*M106*32.1507/1000 -> 9.6053431 | N109: =N104*N106*32.1507/1000 -> 9.5770505 | O109: =O104*O106*32.1507/1000 -> 8.6871191 | P109: =P104*P106*32.1507/1000 -> 7.3840513 | ... AF109: =AF104*AF106*32.1507/1000 -> 0
D110: Total Ag in Concentrate to PAC Plant | G110: Koz | H110: =SUM(I110:AF110) -> 1012.2506 | I110: =I104*I107*32.1507/1000 -> 88.581609 | J110: =J104*J107*32.1507/1000 -> 104.257 | K110: =K104*K107*32.1507/1000 -> 104.10011 | L110: =L104*L107*32.1507/1000 -> 107.04768 | M110: =M104*M107*32.1507/1000 -> 110.89805 | N110: =N104*N107*32.1507/1000 -> 91.852621 | O110: =O104*O107*32.1507/1000 -> 84.699412 | P110: =P104*P107*32.1507/1000 -> 64.284682 | ... AF110: =AF104*AF107*32.1507/1000 -> 0
D112: Cu Recovery - PAC Plant | G112: % | H112: =IF(SUM(I108:AF108)<>0,SUMPRODUCT(I108:AF108,I112:AF112)/SUM(I108:AF108),0) -> 0.935 | I112: ='Candelaria Inputs'!I272 -> 0.935 | J112: ='Candelaria Inputs'!J272 -> 0.935 | K112: ='Candelaria Inputs'!K272 -> 0.935 | L112: ='Candelaria Inputs'!L272 -> 0.935 | M112: ='Candelaria Inputs'!M272 -> 0.935 | N112: ='Candelaria Inputs'!N272 -> 0.935 | O112: ='Candelaria Inputs'!O272 -> 0.935 | P112: ='Candelaria Inputs'!P272 -> 0.935 | ... AF112: ='Candelaria Inputs'!AF272 -> 0
D113: Au Recovery - PAC Plant | G113: % | H113: =IF(SUM(I109:AF109)<>0,SUMPRODUCT(I109:AF109,I113:AF113)/SUM(I109:AF109),0) -> 0.741 | I113: ='Candelaria Inputs'!I279 -> 0.741 | J113: ='Candelaria Inputs'!J279 -> 0.741 | K113: ='Candelaria Inputs'!K279 -> 0.741 | L113: ='Candelaria Inputs'!L279 -> 0.741 | M113: ='Candelaria Inputs'!M279 -> 0.741 | N113: ='Candelaria Inputs'!N279 -> 0.741 | O113: ='Candelaria Inputs'!O279 -> 0.741 | P113: ='Candelaria Inputs'!P279 -> 0.741 | ... AF113: ='Candelaria Inputs'!AF279 -> 0
D114: Ag Recovery - PAC Plant | G114: % | H114: =IF(SUM(I110:AF110)<>0,SUMPRODUCT(I110:AF110,I114:AF114)/SUM(I110:AF110),0) -> 0.82 | I114: ='Candelaria Inputs'!I286 -> 0.82 | J114: ='Candelaria Inputs'!J286 -> 0.82 | K114: ='Candelaria Inputs'!K286 -> 0.82 | L114: ='Candelaria Inputs'!L286 -> 0.82 | M114: ='Candelaria Inputs'!M286 -> 0.82 | N114: ='Candelaria Inputs'!N286 -> 0.82 | O114: ='Candelaria Inputs'!O286 -> 0.82 | P114: ='Candelaria Inputs'!P286 -> 0.82 | ... AF114: ='Candelaria Inputs'!AF286 -> 0
D116: Recovered Cu in Concentrate - PAC Plant | G116: Kt | H116: =SUM(I116:AF116) -> 126.44379 | I116: =I108*I112 -> 12.635216 | J116: =J108*J112 -> 12.42615 | K116: =K108*K112 -> 13.027823 | L116: =L108*L112 -> 12.855876 | M116: =M108*M112 -> 11.681516 | N116: =N108*N112 -> 11.773707 | O116: =O108*O112 -> 10.98971 | P116: =P108*P112 -> 8.842295 | ... AF116: =AF108*AF112 -> 0
D117: Recovered Au in Concentrate - PAC Plant | G117: Koz | H117: =SUM(I117:AF117) -> 75.01573 | I117: =I109*I113 -> 6.8764637 | J117: =J109*J113 -> 7.2821808 | K117: =K109*K113 -> 7.587362 | L117: =L109*L113 -> 7.3862902 | M117: =M109*M113 -> 7.1175593 | N117: =N109*N113 -> 7.0965944 | O117: =O109*O113 -> 6.4371553 | P117: =P109*P113 -> 5.471582 | ... AF117: =AF109*AF113 -> 0
D118: Recovered Ag in Concentrate - PAC Plant | G118: Koz | H118: =SUM(I118:AF118) -> 830.04553 | I118: =I110*I114 -> 72.636919 | J118: =J110*J114 -> 85.490743 | K118: =K110*K114 -> 85.362089 | L118: =L110*L114 -> 87.779101 | M118: =M110*M114 -> 90.936403 | N118: =N110*N114 -> 75.319149 | O118: =O110*O114 -> 69.453518 | P118: =P110*P114 -> 52.713439 | ... AF118: =AF110*AF114 -> 0
D120: Payable Metals
D121: Total Cu in Concentrate | G121: Kt | H121: =SUM(I121:AF121) -> 2957.6379 | I121: =I99+I116 -> 150.83716 | J121: =J99+J116 -> 172.1625 | K121: =K99+K116 -> 160.76309 | L121: =L99+L116 -> 158.61099 | M121: =M99+M116 -> 158.39422 | N121: =N99+N116 -> 143.22009 | O121: =O99+O116 -> 141.14227 | P121: =P99+P116 -> 124.80288 | ... AF121: =AF99+AF116 -> 33.033392
...
