Workbook
Name Cash_to_sales_ratio: CCA!$AF$52
Name cs_fd_outstanding: 'Main Financials'!$N$83
Name MarginalTax: #REF!
Name MarginalTax: #REF!
Name TGR: Valuation!$D$10

Sheet __FDSCACHE__
B1: This sheet contains FactSet XML data for use with this workbook's =FDS codes. Modifying the worksheet's contents may damage the workbook's =FDS functionality.

Sheet Cover
C3: Price for Renault Group
C5: Rotterdam School of Management
C6: Msc. Finance & Investment
C8: Last Update: | D8: 45988
C10: Authors: Jordy Dikken (673670), Jorick Stoel (694007),
C11: Rikus van der Vegt (666665) & Theodor Hogan (754441)
C13: Note:
C15: #VALUE!
C21: Format: | E21: =D2*1.1+25*A2 -> 0
C22: Hardcode | D22: XXX
C23: Sheet Link | D23: XXX
C24: Ext. Link | D24: XXX | E24: Note: FactSet live links have been broken for compatability.
C25: Mixed Formula | D25: XXX | E25: =_xlfn.FORMULATEXT(E21) -> =D2*1.1+25*A2
C26: Assumptions | D26: XXX
C28: Font | D28: Arial
C29: Default | D29: 10 pt
C31: Input Field | D31: [Input]

Sheet Assignment Manager
B2: Basics
B4: Company | E4: Renault SA
B5: $/Share Estimate Deadline | E5: 45962
B6: Final Document Deadline | E6: 45989
B7: OUR DEADLINE | E7: 45983
B9: Grading Rubric
B11: Team Members | E11: ID | G11: Abbreviation
B12: Jordy Dikken | E12: 673670 | G12: JD
B13: Jorick Stoel | E13: 694007 | G13: JS
B14: Rikus van der Vegt | E14: 666665 | G14: RV
B15: Theodor Hogan | E15: 754441 | G15: TH
B17: Grading Rubric
B19: Evaluation Criterion | H19: Weight
B20: Reorganizing balancsheet and income statement | H20: 0.1 | I20: TH
B21: Adjustments to income statement and balancesheet; calculating key ratios | H21: 0.1 | I21: JD
B22: Projections of future cash cashflows and continuing (i.e. stable) growth rate | H22: 0.2 | I22: TH, RV
B23: Estimating the cost of debt, cost of equity, cost of capital | H23: 0.2 | I23: JD, JS
B24: Implemeting WACC; appropriate post DCF value adj. to estime $/shr | H24: 0.15 | I24: TH, RV
B25: Sensititivity analysis | H25: 0.05 | I25: RV
B26: Correctly identifiying peers and implementing multiples valuation | H26: 0.15 | I26: JD, JS
B27: General presentation and readability of Excel file | H27: 0.05 | I27: JD, JS, RV, TH
B28: Total | H28: =SUM(H20:H27) -> 1

Sheet Main Financials
B2: Income Statement
B4: Income Statement Adjusted and Reorganized
B5: All figures in EUR(€) millions unless stated
E6: 2015 | F6: =+E6+1 -> 2016 | G6: =+F6+1 -> 2017 | H6: =+G6+1 -> 2018 | I6: =+H6+1 -> 2019 | J6: =+I6+1 -> 2020 | K6: =+J6+1 -> 2021 | L6: =+K6+1 -> 2022 | M6: =+L6+1 -> 2023 | ... U6: =+T6+1 -> 2031
E7: 2015 | F7: =E7+1 -> 2016 | G7: =F7+1 -> 2017 | H7: =G7+1 -> 2018 | I7: =H7+1 -> 2019 | J7: =I7+1 -> 2020 | K7: =J7+1 -> 2021 | L7: =K7+1 -> 2022 | M7: =L7+1 -> 2023 | ... U7: =T7+1 -> 2031
B8: Revenues | E8: =E32+E39+E41 -> 45327 | F8: =F32+F39+F41 -> 51243 | G8: =G32+G39+G41 -> 56066 | H8: =H32+H39+H41 -> 54588 | I8: =I32+I39+I41 -> 52537 | J8: =J32+J39+J41 -> 41022 | K8: =K32+K39+K41 -> 43600 | L8: =L32+L39+L41 -> 46391 | ... U8: =U32+U39+U41 -> 65725.275
B9: Cost of sales (excl. D&A exp.) | E9: =E49-E413-E440 -> -33385 | F9: =F49-F413-F440-F25 -> -37374 | G9: =G49-G413-G440-G25 -> -43370 | H9: =H49-H413-H440-H25 -> -42072 | I9: =I49-I413-I440 -> -40860 | J9: =J49-J413-J440 -> -31508 | K9: =K49-K413-K440 -> -33481 | L9: =L49-L413-L440 -> -31348 | M9: =M49-M413-M440 -> -38229 | N9: =N49-N413-N440 -> -41332 | O9: =O346 -> -40730.819 | P9: =P346 -> -42301.955 | Q9: =Q346 -> -43958.884 | R9: =R346 -> -44767.303 | S9: =S346 -> -46492.074 | T9: =T346 -> -44247.227 | U9: =U346 -> -45576.103
B10: Gross profit | E10: =E8+E9 -> 11942 | F10: =F8+F9 -> 13869 | G10: =G8+G9 -> 12696 | H10: =H8+H9 -> 12516 | I10: =I8+I9 -> 11677 | J10: =J8+J9 -> 9514 | K10: =K8+K9 -> 10119 | L10: =L8+L9 -> 15043 | ... U10: =U8+U9 -> 20149.172
B11: Total SGA + other operating expenses (excl. D&A) | E11: =E348+E389+E373-E413-E440 -> -7104 | F11: =F348+F389+F373-F413-F440-F24 -> -7810.8045 | G11: =G348+G389+G373-G413-G440-G24 -> -5994.2932 | H11: =H348+H389+H373-H413-H440-H24 -> -6298.7443 | I11: =I348+I389+I373-I413-I440 -> -5686 | J11: =J348+J389+J373-J413-J440 -> -6767 | K11: =K348+K389+K373-K413-K440 -> -4676 | L11: =L348+L389+L373-L413-L440 -> -7031 | M11: =M348+M389+M373-M413-M440 -> -8478 | N11: =N348+N389+N373-N413-N440 -> -9154 | O11: =O348+O389+O373-O413-O440 -> -10007.358 | P11: =P348+P389+P373-P413-P440 -> -10682.17 | ... U11: =U348+U389+U373-U413-U440 -> -12050.705
B12: EBITDA | E12: =E10+E11 -> 4838 | F12: =F10+F11 -> 6058.1955 | G12: =G10+G11 -> 6701.7068 | H12: =H10+H11 -> 6217.2557 | I12: =I10+I11 -> 5991 | J12: =J10+J11 -> 2747 | K12: =K10+K11 -> 5443 | L12: =L10+L11 -> 8012 | ... U12: =U10+U11 -> 8098.4674
B13: Depreciation expenses | E13: =E413-E26 -> -1916 | F13: =F413-F26 -> -1963 | G13: =G413-G26 -> -2061 | H13: =H413-H26 -> -2294 | I13: =I413-I26 -> -2549 | J13: =J413-J26 -> -2869 | K13: =K413-K26 -> -2792 | L13: =L413-L26 -> -3522 | ... U13: =U413-U26 -> -2629.011
B14: Depreciation on right-of-use assets (i.e., operating lease assets) | E14: =E26 -> 0 | F14: =F26 -> -36.1955 | G14: =G26 -> -75.706794 | H14: =H26 -> -89.25565 | I14: =I26 -> 0 | J14: =J26 -> 0 | K14: =K26 -> 0 | L14: =L26 -> 0 | ... U14: =U26 -> 0
B15: EBITA | E15: =E12+E13+E14 -> 2922 | F15: =F12+F13+F14 -> 4059 | G15: =G12+G13+G14 -> 4565 | H15: =H12+H13+H14 -> 3834 | I15: =I12+I13+I14 -> 3442 | J15: =J12+J13+J14 -> -122 | K15: =K12+K13+K14 -> 2651 | L15: =L12+L13+L14 -> 4490 | ... U15: =U12+U13+U14 -> 5469.4564
B16: Amortization expenses | E16: =E440 -> -812 | F16: =F440 -> -877 | G16: =G440 -> -961 | H16: =H440 -> -950 | I16: =I440 -> -1256 | J16: =J440 -> -1880 | K16: =K440 -> -1253 | L16: =L440 -> -2275 | ... U16: =U440 -> -1643.1319
B17: EBIT before non-recurring items | E17: =E15+E16 -> 2110 | F17: =F15+F16 -> 3182 | G17: =G15+G16 -> 3604 | H17: =H15+H16 -> 2884 | I17: =I15+I16 -> 2186 | J17: =J15+J16 -> -2002 | K17: =K15+K16 -> 1398 | L17: =L15+L16 -> 2215 | ... U17: =U15+U16 -> 3826.3245
B19: Adjustments to Income Statement
B20: All figures in EUR(€) millions unless stated
E21: 2015 | F21: =+E21+1 -> 2016 | G21: =+F21+1 -> 2017 | H21: =+G21+1 -> 2018 | I21: =+H21+1 -> 2019 | J21: =+I21+1 -> 2020 | K21: =+J21+1 -> 2021 | L21: =+K21+1 -> 2022 | M21: =+L21+1 -> 2023 | N21: =+M21+1 -> 2024
E22: 2015 | F22: =E22+1 -> 2016 | G22: =F22+1 -> 2017 | H22: =G22+1 -> 2018 | I22: =H22+1 -> 2019 | J22: =I22+1 -> 2020 | K22: =J22+1 -> 2021 | L22: =K22+1 -> 2022 | M22: =L22+1 -> 2023 | N22: =M22+1 -> 2024
B24: Operating lease costs expensed | E24: =E263 -> 0 | F24: =F263 -> 42 | G24: =G263 -> 85 | H24: =H263 -> 101 | I24: =I263 -> 0 | J24: =J263 -> 0 | K24: =K263 -> 0 | L24: =L263 -> 0 | ... N24: =N263 -> 0
B25: Interest expense on right-of-use asset (i.e., operating lease asset) | E25: =E264 -> 0 | F25: =F264 -> -5.8045 | G25: =G264 -> -9.2932056 | H25: =H264 -> -11.74435 | I25: =I264 -> 0 | J25: =J264 -> 0 | K25: =K264 -> 0 | L25: =L264 -> 0 | ... N25: =N264 -> 0
B26: Depreciation expense on right-of-use asset (i.e., operating lease asset) | E26: =E265 -> 0 | F26: =F265 -> -36.1955 | G26: =G265 -> -75.706794 | H26: =H265 -> -89.25565 | I26: =I265 -> 0 | J26: =J265 -> 0 | K26: =K265 -> 0 | L26: =L265 -> 0 | ... N26: =N265 -> 0
B28: Revenue Breakdown and Forecast unadj.
B29: All figures in EUR(€) millions unless stated
E30: 2015 | F30: =+E30+1 -> 2016 | G30: =+F30+1 -> 2017 | H30: =+G30+1 -> 2018 | I30: =+H30+1 -> 2019 | J30: =+I30+1 -> 2020 | K30: =+J30+1 -> 2021 | L30: =+K30+1 -> 2022 | M30: =+L30+1 -> 2023 | ... U30: =+T30+1 -> 2031
E31: 2015 | F31: =E31+1 -> 2016 | G31: =F31+1 -> 2017 | H31: =G31+1 -> 2018 | I31: =H31+1 -> 2019 | J31: =I31+1 -> 2020 | K31: =J31+1 -> 2021 | L31: =K31+1 -> 2022 | M31: =L31+1 -> 2023 | ... U31: =T31+1 -> 2031
B32: Total Automotive | E32: =+E33+E34+E35+E36+E37 -> 43108 | F32: =+F33+F34+F35+F36+F37 -> 48995 | G32: =+G33+G34+G35+G36+G37 -> 53553 | H32: =+H33+H34+H35+H36+H37 -> 51380 | I32: =+I33+I34+I35+I36+I37 -> 49132 | J32: =+J33+J34+J35+J36+J37 -> 37865 | K32: =+K33+K34+K35+K36+K37 -> 40641 | L32: =+L33+L34+L35+L36+L37 -> 43121 | ... U32: =+U33+U34+U35+U36+U37 -> 57490.338
B33: ACEA Europe | E33: =E316 -> 24772.652 | F33: =F316 -> 27791.582 | G33: =G316 -> 27208.61 | H33: =H316 -> 25406.856 | I33: =I316 -> 25468.602 | J33: =J316 -> 18539.589 | K33: =K316 -> 21529.684 | L33: =L316 -> 27629.195 | ... U33: =U316 -> 39598.558
B34: Eurasia | E34: =E321 -> 5466.7725 | F34: =F321 -> 5610.55 | G34: =G321 -> 10432.405 | H34: =H321 -> 9888.9994 | I34: =I321 -> 9824.1278 | J34: =J321 -> 9537.0455 | K34: =K321 -> 9947.184 | L34: =L321 -> 3231.8348 | ... U34: =U321 -> 6395.7338
B35: Africa & Middle East | E35: =E326 -> 5525.2898 | F35: =F326 -> 7561.0363 | G35: =G326 -> 7579.4549 | H35: =H326 -> 5938.6616 | I35: =I326 -> 5932.1779 | J35: =J326 -> 4441.6774 | K35: =K326 -> 2272.6335 | L35: =L326 -> 2751.3596 | ... U35: =U326 -> 3214.8507
B36: Asia-Pacific | E36: =E331 -> 1909.417 | F36: =F331 -> 2576.4739 | G36: =G331 -> 2788.5149 | H36: =H331 -> 4361.7302 | I36: =I331 -> 2350.3818 | J36: =J331 -> 2005.8001 | K36: =K331 -> 2926.1087 | L36: =L331 -> 3506.6589 | ... U36: =U331 -> 2663.2185
B37: Americas | E37: =E336 -> 5433.869 | F37: =F336 -> 5455.3578 | G37: =G336 -> 5544.0151 | H37: =H336 -> 5783.7528 | I37: =I336 -> 5556.7105 | J37: =J336 -> 3340.8879 | K37: =K336 -> 3965.3899 | L37: =L336 -> 6001.9517 | ... U37: =U336 -> 5617.9779
B39: Total Sales Financing | E39: =E359 -> 2219 | F39: =F359 -> 2248 | G39: =G359 -> 2513 | H39: =H359 -> 3208 | I39: =I359 -> 3405 | J39: =J359 -> 3138 | K39: =K359 -> 2935 | L39: =L359 -> 3235 | ... U39: =U359 -> 7891.377
B41: Total Mobility Services | E41: =E381 -> 0 | F41: =F381 -> 0 | G41: =G381 -> 0 | H41: =H381 -> 0 | I41: =I381 -> 0 | J41: =J381 -> 19 | K41: =K381 -> 24 | L41: =L381 -> 35 | ... U41: =U381 -> 343.55985
B44: Income Statement Historical IFRS
B45: All figures in EUR(€) millions unless stated
E46: 2015 | F46: =+E46+1 -> 2016 | G46: =+F46+1 -> 2017 | H46: =+G46+1 -> 2018 | I46: =+H46+1 -> 2019 | J46: =+I46+1 -> 2020 | K46: =+J46+1 -> 2021 | L46: =+K46+1 -> 2022 | M46: =+L46+1 -> 2023 | N46: =+M46+1 -> 2024
E47: 2015 | F47: =E47+1 -> 2016 | G47: =F47+1 -> 2017 | H47: =G47+1 -> 2018 | I47: =H47+1 -> 2019 | J47: =I47+1 -> 2020 | K47: =J47+1 -> 2021 | L47: =K47+1 -> 2022 | M47: =L47+1 -> 2023 | N47: =M47+1 -> 2024
B48: Revenues | E48: 45327 | F48: 51243 | G48: 58770 | H48: 57419 | I48: 55537 | J48: 43474 | K48: 46213 | L48: 46391 | M48: 52376 | N48: 56232
B49: Cost of goods and services sold | E49: -36113 | F49: -40256 | G49: -46477 | H49: -45417 | I49: -44665 | J49: -36257 | K49: -37526 | L49: -37145 | M49: -41414 | N49: -44500
B50: Research and development expenses | E50: -2075 | F50: -2370 | G50: -2590 | H50: -2598 | I50: -2658 | J50: -2569 | K50: -2365 | L50: -2125 | M50: -2144 | N50: -2274
B51: Selling, general and administrative expenses | E51: -4819 | F51: -5335 | G51: -5849 | H51: -5792 | I51: -5552 | J51: -4985 | K51: -4659 | L51: -4526 | M51: -4701 | N51: -5195
B52: Operating margin | E52: =E48+E49+E50+E51 -> 2320 | F52: =F48+F49+F50+F51 -> 3282 | G52: =G48+G49+G50+G51 -> 3854 | H52: =H48+H49+H50+H51 -> 3612 | I52: =I48+I49+I50+I51 -> 2662 | J52: =J48+J49+J50+J51 -> -337 | K52: =K48+K49+K50+K51 -> 1663 | L52: =L48+L49+L50+L51 -> 2595 | ... N52: =N48+N49+N50+N51 -> 4263
B53: Other operating income and expenses | E53: =+E54+E55 -> -199 | F53: =+F54+F55 -> 1 | G53: =+G54+G55 -> -48 | H53: =+H54+H55 -> -625 | I53: =+I54+I55 -> -557 | J53: =+J54+J55 -> -1662 | K53: =+K54+K55 -> -265 | L53: =+L54+L55 -> -379 | ... N53: =+N54+N55 -> -1687
B54: Other operating income | E54: 77 | F54: 727 | G54: 214 | H54: 149 | I54: 80 | J54: 181 | K54: 728 | L54: 425 | M54: 430 | N54: 798
B55: Other operating expenses | E55: -276 | F55: -726 | G55: -262 | H55: -774 | I55: -637 | J55: -1843 | K55: -993 | L55: -804 | M55: -2062 | N55: -2485
B56: Operating income / loss | E56: =E52+E53 -> 2121 | F56: =F52+F53 -> 3283 | G56: =G52+G53 -> 3806 | H56: =H52+H53 -> 2987 | I56: =I52+I53 -> 2105 | J56: =J52+J53 -> -1999 | K56: =K52+K53 -> 1398 | L56: =L52+L53 -> 2216 | ... N56: =N52+N53 -> 2576
B57: Financial income / expenses | E57: =E58+E59+E60 -> -221 | F57: =F58+F59+F60 -> -323 | G57: =G58+G59+G60 -> -504 | H57: =H58+H59+H60 -> -353 | I57: =I58+I59+I60 -> -442 | J57: =J58+J59+J60 -> -482 | K57: =K58+K59+K60 -> -350 | L57: =L58+L59+L60 -> -486 | ... N57: =N58+N59+N60 -> -517
B58: Cost of gross financial indebtedness | E58: -387 | F58: -385 | G58: -441 | H58: -373 | I58: -386 | J58: -355 | K58: -381 | L58: -349 | M58: -326 | N58: -336
B59: Income on cash and financial assets | E59: 162 | F59: 101 | G59: 72 | H59: 65 | I59: 75 | J59: 18 | K59: 73 | L59: 168 | M59: 414 | N59: 440
B60: Other financial income and expenses | E60: 4 | F60: -39 | G60: -135 | H60: -45 | I60: -131 | J60: -145 | K60: -42 | L60: -305 | M60: -615 | N60: -621
B61: Share in net income / loss of associates and joint ventures | E61: =E62+E63+E64 -> 1371 | F61: =F62+F63+F64 -> 1638 | G61: =G62+G63+G64 -> 2799 | H61: =H62+H63+H64 -> 1540 | I61: =I62+I63+I64 -> -190 | J61: =J62+J63+J64 -> -5145 | K61: =K62+K63+K64 -> 515 | L61: =L62+L63+L64 -> 423 | ... N61: =N62+N63+N64 -> -521
B62: Nissan | E62: 1976 | F62: 1741 | G62: 2791 | H62: 1509 | I62: 242 | J62: -4970 | K62: 380 | L62: 526 | M62: 797 | N62: -483
B63: Volvo | E63: 0 | F63: 0 | G63: 0 | H63: 0 | I63: 0 | J63: 0 | K63: 0 | L63: 0 | M63: 0 | N63: 0
B64: Other associates and joint ventures | E64: -605 | F64: -103 | G64: 8 | H64: 31 | I64: -432 | J64: -175 | K64: 135 | L64: -103 | M64: 83 | N64: -38
B65: Pre-tax income | E65: =E56+E57+E61 -> 3271 | F65: =F56+F57+F61 -> 4598 | G65: =G56+G57+G61 -> 6101 | H65: =H56+H57+H61 -> 4174 | I65: =I56+I57+I61 -> 1473 | J65: =J56+J57+J61 -> -7626 | K65: =K56+K57+K61 -> 1563 | L65: =L56+L57+L61 -> 2153 | ... N65: =N56+N57+N61 -> 1538
B66: Current and deferred taxes | E66: -311 | F66: -1055 | G66: -891 | H66: -723 | I66: -1454 | J66: -420 | K66: -596 | L66: -533 | M66: -523 | N66: -647
B67: Net income from continuing operations | E67: =E65+E66 -> 2960 | F67: =F65+F66 -> 3543 | G67: =G65+G66 -> 5210 | H67: =H65+H66 -> 3451 | I67: =I65+I66 -> 19 | J67: =J65+J66 -> -8046 | K67: =K65+K66 -> 967 | L67: =L65+L66 -> 1620 | ... N67: =N65+N66 -> 891
B68: Net income from discontinued operations | E68: =+E69+E70 -> 0 | F68: =+F69+F70 -> 0 | G68: =+G69+G70 -> 0 | H68: =+H69+H70 -> 0 | I68: =+I69+I70 -> 0 | J68: =+J69+J70 -> 0 | K68: =+K69+K70 -> 0 | L68: =+L69+L70 -> -2320 | ... N68: =+N69+N70 -> 0
B69: Net income from discontinued operations - parent-company shareholders share | E69: 0 | F69: 0 | G69: 0 | H69: 0 | I69: 0 | J69: 0 | K69: 0 | L69: -1988 | M69: 0 | N69: 0
B70: Net income from discontinued operations - non-controlling interests share | E70: 0 | F70: 0 | G70: 0 | H70: 0 | I70: 0 | J70: 0 | K70: 0 | L70: -332 | M70: 0 | N70: 0
B71: Net income or loss | E71: =E67+E68 -> 2960 | F71: =F67+F68 -> 3543 | G71: =G67+G68 -> 5210 | H71: =H67+H68 -> 3451 | I71: =I67+I68 -> 19 | J71: =J67+J68 -> -8046 | K71: =K67+K68 -> 967 | L71: =L67+L68 -> -700 | ... N71: =N67+N68 -> 891
B72: Net income / loss - non-controlling interests' share | E72: -137 | F72: -124 | G72: -96 | H72: -149 | I72: -160 | J72: 38 | K72: -79 | L72: 362 | M72: -117 | N72: -139
B73: Net income - parent company shareholders' share | E73: =E71+E72 -> 2823 | F73: =F71+F72 -> 3419 | G73: =G71+G72 -> 5114 | H73: =H71+H72 -> 3302 | I73: =I71+I72 -> -141 | J73: =J71+J72 -> -8008 | K73: =K71+K72 -> 888 | L73: =L71+L72 -> -338 | ... N73: =N71+N72 -> 752
B74: Per share
B75: Basic | E75: 10.35 | F75: 12.57 | G75: 18.87 | H75: 12.24 | I75: -0.52 | J75: -29.51 | K75: 3.26 | L75: =L76+L77 -> -1.24 | M75: =M76+M77 -> 8.11 | N75: 2.76
B76: Continuing operations | E76: 0 | F76: 0 | G76: 0 | H76: 0 | I76: 0 | J76: 0 | K76: 0 | L76: 6.07 | M76: 8.11 | N76: 0
B77: Discontinued operations | E77: 0 | F77: 0 | G77: 0 | H77: 0 | I77: 0 | J77: 0 | K77: 0 | L77: -7.31 | M77: 0 | N77: 0
B78: Diluted | E78: 10.29 | F78: 12.46 | G78: 18.68 | H78: 12.13 | I78: 0.52 | J78: 29.51 | K78: 3.24 | L78: =L79+L80 -> -1.24 | M78: =M79+M80 -> 7.99 | N78: 2.72
B79: Continuing operations | E79: 0 | F79: 0 | G79: 0 | H79: 0 | I79: 0 | J79: 0 | K79: 0 | L79: 6.07 | M79: 7.99 | N79: 0
B80: Discontinued operations | E80: 0 | F80: 0 | G80: 0 | H80: 0 | I80: 0 | J80: 0 | K80: 0 | L80: -7.31 | M80: 0 | N80: 0
B81: Weighted average shares
B82: Basic | E82: 272.708 | F82: 271.968 | G82: 271.08 | H82: 269.85 | I82: 271.639 | J82: 271.349 | K82: 272.102 | L82: 272.097 | M82: 271.009 | N82: 272.374
B83: Diluted | E83: 274.314 | F83: 274.331 | G83: 273.749 | H83: 272.222 | I83: 273.569 | J83: 271.349 | K83: 273.868 | L83: 274.251 | M83: 275.141 | N83: 276.883
B86: Balance Sheet
B88: Balance Sheet Adjusted and Reorganized
B89: All figures in EUR(€) millions unless stated
E90: 2015 | F90: =+E90+1 -> 2016 | G90: =+F90+1 -> 2017 | H90: =+G90+1 -> 2018 | I90: =+H90+1 -> 2019 | J90: =+I90+1 -> 2020 | K90: =+J90+1 -> 2021 | L90: =+K90+1 -> 2022 | M90: =+L90+1 -> 2023 | ... U90: =+T90+1 -> 2031
E91: 2015 | F91: =E91+1 -> 2016 | G91: =F91+1 -> 2017 | H91: =G91+1 -> 2018 | I91: =H91+1 -> 2019 | J91: =I91+1 -> 2020 | K91: =J91+1 -> 2021 | L91: =K91+1 -> 2022 | M91: =L91+1 -> 2023 | ... U91: =T91+1 -> 2031
B92: Operating fixed assets | E92: =E93+E94+E95 -> 15872 | F92: =F93+F94+F95 -> 19649.443 | G92: =G93+G94+G95 -> 20756.76 | H92: =H93+H94+H95 -> 22305.351 | I92: =I93+I94+I95 -> 25073 | J92: =J93+J94+J95 -> 24438 | K92: =K93+K94+K95 -> 23531 | L92: =L93+L94+L95 -> 17343 | ... U92: =U93+U94+U95 -> 34530.454
B93: =B165 -> Intangible assets and goodwill | E93: =E165+E150 -> 3570 | F93: =F165+F150 -> 5295.4426 | G93: =G165+G150 -> 5739.7596 | H93: =H165+H150 -> 6516.3507 | I93: =I165+I150 -> 6949 | J93: =J165+J150 -> 6347 | K93: =K165+K150 -> 6398 | L93: =L165+L150 -> 4700 | ... N93: =N165+N150 -> 5164 | O93: =O442 -> 5798.7009 | P93: =P442 -> 6460.8188 | Q93: =Q442 -> 7161.8147 | R93: =R442 -> 7883.3701 | S93: =S442 -> 8645.0337 | T93: =T442 -> 9396.0973 | U93: =U442 -> 10175.547
B94: =B166 -> Property, plant and equipment | E94: =E166 -> 11171 | F94: =F166 -> 12988 | G94: =G166 -> 13582 | H94: =H166 -> 14304 | I94: =I166 -> 16900 | J94: =J166 -> 17135 | K94: =K166 -> 16167 | L94: =L166 -> 11705 | ... N94: =N166 -> 13861 | O94: =O415 -> 15037.215 | P94: =P415 -> 16252.175 | Q94: =Q415 -> 17538.794 | R94: =R415 -> 18858.87 | S94: =S415 -> 20249.686 | T94: =T415 -> 21622.081 | U94: =U415 -> 23040.402
B95: =B172 -> Other non-current assets | E95: =E172 -> 1131 | F95: =F172 -> 1366 | G95: =G172 -> 1435 | H95: =H172 -> 1485 | I95: =I172 -> 1224 | J95: =J172 -> 956 | K95: =K172 -> 966 | L95: =L172 -> 938 | ... N95: =N172 -> 1053 | O95: =O446 -> 1151.9022 | P95: =P446 -> 1204.1174 | Q95: =Q446 -> 1248.08 | R95: =R446 -> 1269.7159 | S95: =S446 -> 1320.841 | T95: =T446 -> 1272.3194 | U95: =U446 -> 1314.5055
B97: Operating net working capital | E97: =E98+E99+E100+E101+E102+E103+E104 -> 12649 | F97: =F98+F99+F100+F101+F102+F103+F104 -> 14523 | G97: =G98+G99+G100+G101+G102+G103+G104 -> 14450 | H97: =H98+H99+H100+H101+H102+H103+H104 -> 14279 | I97: =I98+I99+I100+I101+I102+I103+I104 -> 14645 | J97: =J98+J99+J100+J101+J102+J103+J104 -> 15582.23 | K97: =K98+K99+K100+K101+K102+K103+K104 -> 15370.48 | L97: =L98+L99+L100+L101+L102+L103+L104 -> 17868.385 | ... U97: =U98+U99+U100+U101+U102+U103+U104 -> 20647.895
B98: =B175 -> Inventories | E98: =E175 -> 4128 | F98: =F175 -> 5821 | G98: =G175 -> 6328 | H98: =H175 -> 5879 | I98: =I175 -> 5780 | J98: =J175 -> 5640 | K98: =K175 -> 4792 | L98: =L175 -> 5213 | ... N98: =N175 -> 5468 | O98: =O467 -> 5579.5642 | P98: =P467 -> 5794.7884 | Q98: =Q467 -> 6021.765 | R98: =R467 -> 6132.5072 | S98: =S467 -> 6368.7772 | T98: =T467 -> 6061.2639 | U98: =U467 -> 6243.3018
B99: Sales financing recievables | E99: =E176 -> 28605 | F99: =F176 -> 34358 | G99: =G176 -> 39334 | H99: =H176 -> 42067 | I99: =I176 -> 45374 | J99: =J176 -> 40820 | K99: =K176 -> 39498 | L99: =L176 -> 44247 | ... N99: =N176 -> 54355 | O99: =O468 -> 53650.241 | P99: =P468 -> 56082.18 | Q99: =Q468 -> 58129.754 | R99: =R468 -> 59137.452 | S99: =S468 -> 61518.624 | T99: =T468 -> 59258.714 | U99: =U468 -> 61223.544
B100: Automotive recivable & other current assets (excl. tax and current tax due) | E100: =E177+E184 -> 4330 | F100: =F177+F184 -> 5526 | G100: =G177+G184 -> 5767 | H100: =H177+H184 -> 5178 | I100: =I177+I184 -> 5340 | J100: =J177+J184 -> 4784 | K100: =K177+K184 -> 4476 | L100: =L177+L184 -> 5095 | ... N100: =N177+N184 -> 6137 | O100: =O469 -> 6311.793 | P100: =P469 -> 6597.9035 | Q100: =Q469 -> 6838.7946 | R100: =R469 -> 6957.3473 | S100: =S469 -> 7237.4851 | T100: =T469 -> 6971.6134 | U100: =U469 -> 7202.7699
B101: =B180 -> Derivatives of financing operations by the Automotive segment | E101: =E180 -> 488 | F101: =F180 -> 539 | G101: =G180 -> 263 | H101: =H180 -> 378 | I101: =I180 -> 216 | J101: =J180 -> 298 | K101: =K180 -> 181 | L101: =L180 -> 410 | ... N101: =N180 -> 356 | O101: =O473 -> 324.8 | P101: =P473 -> 324.8 | Q101: =Q473 -> 324.8 | R101: =R473 -> 324.8 | S101: =S473 -> 324.8 | T101: =T473 -> 324.8 | U101: =U473 -> 324.8
B102: =B186 -> Operating Cash | E102: =E186 -> 14133 | F102: =F186 -> 13853 | G102: =G186 -> 14057 | H102: =H186 -> 14777 | I102: =I186 -> 14982 | J102: =J186 -> 19864.23 | K102: =K186 -> 19521.48 | L102: =L186 -> 20307.385 | ... N102: =N186 -> 22203.41 | O102: =O474 -> 22185.952 | P102: =P474 -> 23191.631 | Q102: =Q474 -> 24038.363 | R102: =R474 -> 24455.076 | S102: =S474 -> 25439.76 | T102: =T474 -> 24505.221 | U102: =U474 -> 25317.736
B103: =B219 -> Sales financing debts | E103: =-E219 -> -30740 | F103: =-F219 -> -36041 | G103: =-G219 -> -41395 | H103: =-H219 -> -44495 | I103: =-I219 -> -47465 | J103: =-J219 -> -47547 | K103: =-K219 -> -45123 | L103: =-L219 -> -48999 | ... N103: =-N219 -> -60438 | O103: =O471 -> -59962.034 | P103: =P471 -> -62680.084 | Q103: =Q471 -> -64968.548 | R103: =R471 -> -66094.799 | S103: =S471 -> -68756.109 | T103: =T471 -> -66230.327 | U103: =U471 -> -68426.314
B104: Trade payables (current) | E104: =-E220 -> -8295 | F104: =-F220 -> -9533 | G104: =-G220 -> -9904 | H104: =-H220 -> -9505 | I104: =-I220 -> -9582 | J104: =-J220 -> -8277 | K104: =-K220 -> -7975 | L104: =-L220 -> -8405 | ... N104: =-N220 -> -9809 | O104: =O470 -> -10043.216 | P104: =P470 -> -10430.619 | Q104: =Q470 -> -10839.177 | R104: =R470 -> -11038.513 | S104: =S470 -> -11463.799 | T104: =T470 -> -10910.275 | U104: =U470 -> -11237.943
B106: Operating Liabilities | E106: =+E107+E109+E110+E108 -> -12331 | F106: =+F107+F109+F110+F108 -> -14549 | G106: =+G107+G109+G110+G108 -> -15247 | H106: =+H107+H109+H110+H108 -> -15894 | I106: =+I107+I109+I110+I108 -> -17170 | J106: =+J107+J109+J110+J108 -> -16061 | K106: =+K107+K109+K110+K108 -> -14775 | L106: =+L107+L109+L110+L108 -> -14592 | ... U106: =+U107+U109+U110+U108 -> -18531.899
B107: Net deferred tax liabilities associated with operating ítems | E107: =E153 -> -807 | F107: =F153 -> -697 | G107: =G153 -> -1053 | H107: =H153 -> -1437 | I107: =I153 -> -1695 | J107: =J153 -> -1402 | K107: =K153 -> -1495 | L107: =L153 -> -1527 | ... N107: =N153 -> -1269 | O107: =O492 -> -1290.1305 | P107: =P492 -> -1348.6115 | Q107: =Q492 -> -1397.8496 | R107: =R492 -> -1422.0818 | S107: =S492 -> -1479.342 | T107: =T492 -> -1424.9978 | U107: =U492 -> -1472.2462
B108: Tax Liabilitity | E108: =-E221 -> -219 | F108: =-F221 -> -321 | G108: =-G221 -> -246 | H108: =-H221 -> -289 | I108: =-I221 -> -223 | J108: =-J221 -> -221 | K108: =-K221 -> -266 | L108: =-L221 -> -312 | ... N108: =-N221 -> -370 | O108: =O493 -> -354.78589 | P108: =P493 -> -370.86816 | Q108: =Q493 -> -384.40864 | R108: =R493 -> -391.07249 | S108: =S493 -> -406.81904 | T108: =T493 -> -391.87439 | U108: =U493 -> -404.8677
B109: Operating provisions (non-current + current) | E109: =(E215+E206)*(-1) -> -2175 | F109: =(F215+F206)*(-1) -> -2562 | G109: =(G215+G206)*(-1) -> -2429 | H109: =(H215+H206)*(-1) -> -2668 | I109: =(I215+I206)*(-1) -> -2717 | J109: =(J215+J206)*(-1) -> -3111 | K109: =(K215+K206)*(-1) -> -3064 | L109: =(L215+L206)*(-1) -> -2683 | ... N109: =(N215+N206)*(-1) -> -2630 | O109: =O494 -> -2741.5273 | P109: =P494 -> -2865.7994 | Q109: =Q494 -> -2970.4304 | R109: =R494 -> -3021.9238 | S109: =S494 -> -3143.6017 | T109: =T494 -> -3028.1203 | U109: =U494 -> -3128.5231
B110: Other liabilities (non-current + current) | E110: =(E210+E222)*(-1) -> -9130 | F110: =(F210+F222)*(-1) -> -10969 | G110: =(G210+G222)*(-1) -> -11519 | H110: =(H210+H222)*(-1) -> -11500 | I110: =(I210+I222)*(-1) -> -12535 | J110: =(J210+J222)*(-1) -> -11327 | K110: =(K210+K222)*(-1) -> -9950 | L110: =(L210+L222)*(-1) -> -10070 | ... N110: =(N210+N222)*(-1) -> -11711 | O110: =O495 -> -11853.074 | P110: =P495 -> -12390.368 | Q110: =Q495 -> -12842.743 | R110: =R495 -> -13065.376 | S110: =S495 -> -13591.454 | T110: =T495 -> -13092.167 | U110: =U495 -> -13526.262
B112: Operating Capital | E112: =E106+E97+E92 -> 16190 | F112: =F106+F97+F92 -> 19623.443 | G112: =G106+G97+G92 -> 19959.76 | H112: =H106+H97+H92 -> 20690.351 | I112: =I106+I97+I92 -> 22548 | J112: =J106+J97+J92 -> 23959.23 | K112: =K106+K97+K92 -> 24126.48 | L112: =L106+L97+L92 -> 20619.385 | ... U112: =U106+U97+U92 -> 36646.451
B114: Non-operating assets | E114: =E115+E116+E117+E118+E119+E120 -> 23474 | F114: =F115+F116+F117+F118+F119+F120 -> 23073 | G114: =G115+G116+G117+G118+G119+G120 -> 24373 | H114: =H115+H116+H117+H118+H119+H120 -> 25847 | I114: =I115+I116+I117+I118+I119+I120 -> 25565 | J114: =J115+J116+J117+J118+J119+J120 -> 19977.77 | K114: =K115+K116+K117+K118+K119+K120 -> 21945.52 | L114: =L115+L116+L117+L118+L119+L120 -> 26027.615 | ... N114: =N115+N116+N117+N118+N119+N120 -> 20829.59
B115: =B167 -> Investments in associates and joint ventures | E115: =E167 -> 19356 | F115: =F167 -> 19026 | G115: =G167 -> 19811 | H115: =H167 -> 21439 | I115: =I167 -> 21232 | J115: =J167 -> 15120 | K115: =K167 -> 16955 | L115: =L167 -> 18210 | ... N115: =N167 -> 17063
B116: Non current finacial assets + marketable securities + loans and others | E116: =E170+E179+E181 -> 2750 | F116: =F170+F179+F181 -> 2761 | G116: =G170+G179+G181 -> 3064 | H116: =H170+H179+H181 -> 2513 | I116: =I170+I179+I181 -> 3072 | J116: =J170+J179+J181 -> 2136 | K116: =K170+K179+K181 -> 1572 | L116: =L170+L179+L181 -> 1419 | ... N116: =N170+N179+N181 -> 2458
...

Sheet WACC
B2: Levered β Assumptions | F2: Macro Factors | R2: Country Equity Risk Premium Calculation
B3: Method | C3: β | D3: Weight | I3: 2025 | J3: =+I3+1 -> 2026 | K3: =+J3+1 -> 2027 | L3: =+K3+1 -> 2028 | M3: =+L3+1 -> 2029 | N3: =+M3+1 -> 2030 | O3: =+N3+1 -> 2031 | P3: Terminal | R3: Country | S3: ERP | T3: GDP 2023 | U3: Weight GDP
B4: Regression | C4: =Beta!C23 -> 1.6732075 | D4: 0.5 | F4: EU inflation | I4: =Macro!O6 -> 0.02253 | J4: =Macro!P6 -> 0.02074 | K4: =Macro!Q6 -> 0.02157 | L4: =Macro!R6 -> 0.02097 | M4: =Macro!S6 -> 0.02122 | N4: =Macro!T6 -> 0.02065 | O4: =Macro!U6 -> 0.02 | P4: =Macro!U6 -> 0.02 | R4: Austria | S4: 0.0486 | T4: 477837.3 | U4: =T4/$T$31 -> 0.027688969
B5: Bottom-up | C5: =Beta!C24 -> 2.6130474 | D5: =1-D4 -> 0.5 | F5: Risk-free rate | I5: =U45 -> 0.01973334 | J5: =V45 -> 0.01964279 | K5: =W45 -> 0.02135805 | L5: =X45 -> 0.02349382 | M5: =Y45 -> 0.02544581 | N5: =Z45 -> 0.02741186 | O5: =AA45 -> 0.02904171 | P5: =AB45 -> 0.031974435 | R5: Belgium | S5: 0.0513 | T5: 602376.3 | U5: =T5/$T$31 -> 0.034905561
B6: WA β | C6: =SUMPRODUCT(C4:C5,D4:D5) -> 2.1431275 | D6: =SUM(D4:D5) -> 1 | F6: Expected loss from default | I6: 0.003 | J6: 0.003 | K6: 0.003 | L6: 0.003 | M6: 0.003 | N6: 0.003 | O6: 0.003 | P6: 0.003 | R6: Bulgaria | S6: 0.0646 | T6: 94526.6 | U6: =T6/$T$31 -> 0.0054774797
R7: Croatia | S7: 0.0593 | T7: 79186.3 | U7: =T7/$T$31 -> 0.004588564
B8: Debt to Equity Forecast | F8: Assumptions for Cost of Equity | R8: Cyprus | S8: 0.0593 | T8: 32439.2 | U8: =T8/$T$31 -> 0.0018797361
B9: Year | C9: Ratio | I9: 2025 | J9: =+I9+1 -> 2026 | K9: =+J9+1 -> 2027 | L9: =+K9+1 -> 2028 | M9: =+L9+1 -> 2029 | N9: =+M9+1 -> 2030 | O9: =+N9+1 -> 2031 | P9: Terminal | R9: Czech Republic | S9: 0.0513 | T9: 319099.1 | U9: =T9/$T$31 -> 0.018490656
B10: 2025 | C10: =CCA!J54/CCA!H54 -> 7.584024 | D10: Explainer | F10: Levered β | I10: =$C$6 -> 2.1431275 | J10: =$C$6 -> 2.1431275 | K10: =$C$6 -> 2.1431275 | L10: =$C$6 -> 2.1431275 | M10: =$C$6 -> 2.1431275 | N10: =$C$6 -> 2.1431275 | O10: =$C$6 -> 2.1431275 | P10: =$C$6 -> 2.1431275 | R10: Denmark | S10: 0.0433 | T10: 374173.6 | U10: =T10/$T$31 -> 0.021682027
B11: =+B10+1 -> 2026 | C11: =C10+0.01 -> 7.594024 | F11: Risk-free rate | I11: =I5 -> 0.01973334 | J11: =J5 -> 0.01964279 | K11: =K5 -> 0.02135805 | L11: =L5 -> 0.02349382 | M11: =M5 -> 0.02544581 | N11: =N5 -> 0.02741186 | O11: =O5 -> 0.02904171 | P11: =P5 -> 0.031974435 | R11: Estonia | S11: 0.0527 | T11: 38353.4 | U11: =T11/$T$31 -> 0.0022224429
B12: =+B11+1 -> 2027 | C12: =C11+0.01 -> 7.604024 | F12: Equity risk premium | I12: =$U$32 -> 0.05352576 | J12: =$U$32 -> 0.05352576 | K12: =$U$32 -> 0.05352576 | L12: =$U$32 -> 0.05352576 | M12: =$U$32 -> 0.05352576 | N12: =$U$32 -> 0.05352576 | O12: =$U$32 -> 0.05352576 | P12: =$U$32 -> 0.05352576 | R12: Finland | S12: 0.0486 | T12: 272848 | U12: =T12/$T$31 -> 0.01581057
B13: =+B12+1 -> 2028 | C13: =C12+0.01 -> 7.614024 | F13: Cost of Equity | I13: =I11+I10*(I12) -> 0.13444587 | J13: =J11+J10*(J12) -> 0.13435532 | K13: =K11+K10*(K12) -> 0.13607058 | L13: =L11+L10*(L12) -> 0.13820635 | M13: =M11+M10*(M12) -> 0.14015834 | N13: =N11+N10*(N12) -> 0.14212439 | O13: =O11+O10*(O12) -> 0.14375424 | P13: =P11+P10*(P12) -> 0.14668696 | R13: France | S13: 0.0513 | T13: 2826541.5 | U13: =T13/$T$31 -> 0.16378801
B14: =+B13+1 -> 2029 | C14: =C13+0.01 -> 7.624024 | R14: Germany | S14: 0.0433 | T14: 4219310 | U14: =T14/$T$31 -> 0.24449398
B15: =+B14+1 -> 2030 | C15: =C14+0.01 -> 7.634024 | F15: Assumptions for Cost of Debt | R15: Greece | S15: 0.0767 | T15: 224686.2 | U15: =T15/$T$31 -> 0.013019765
B16: =+B15+1 -> 2031 | C16: =C15+0.01 -> 7.644024 | I16: 2025 | J16: =+I16+1 -> 2026 | K16: =+J16+1 -> 2027 | L16: =+K16+1 -> 2028 | M16: =+L16+1 -> 2029 | N16: =+M16+1 -> 2030 | O16: =+N16+1 -> 2031 | P16: Terminal | R16: Hungary | S16: 0.0687 | T16: 197178.7 | U16: =T16/$T$31 -> 0.011425803
B17: Terminal | C17: =C16 -> 7.644024 | F17: Accounting cost of debt adj. | I17: =$E$54 -> 0.029861358 | J17: =$I$17*(J5/J4) -> 0.0282816 | K17: =$I$17*(K5/K4) -> 0.029567936 | L17: =$I$17*(L5/L4) -> 0.033455287 | M17: =$I$17*(M5/M4) -> 0.035808032 | N17: =$I$17*(N5/N4) -> 0.039639485 | O17: =$I$17*(O5/O4) -> 0.043361245 | P17: =$I$17*(P5/P4) -> 0.047740002 | R17: Ireland | S17: 0.0513 | T17: 524728.8 | U17: =T17/$T$31 -> 0.030406165
F18: Credit Spread | I18: =$D$67 -> 0.016321429 | J18: =$D$67 -> 0.016321429 | K18: =$D$67 -> 0.016321429 | L18: =$D$67 -> 0.016321429 | M18: =$D$67 -> 0.016321429 | N18: =$D$67 -> 0.016321429 | O18: =$D$67 -> 0.016321429 | P18: =$D$67 -> 0.016321429 | R18: Italy | S18: 0.0726 | T18: 2142601.7 | U18: =T18/$T$31 -> 0.12415614
F19: Expected loss from default | I19: =I6 -> 0.003 | J19: =J6 -> 0.003 | K19: =K6 -> 0.003 | L19: =L6 -> 0.003 | M19: =M6 -> 0.003 | N19: =N6 -> 0.003 | O19: =O6 -> 0.003 | P19: =P6 -> 0.003 | R19: Latvia | S19: 0.0593 | T19: 39564.2 | U19: =T19/$T$31 -> 0.0022926044
F20: Cost of Debt | I20: =I17+I18-I19 -> 0.043182787 | J20: =J17+J18-J19 -> 0.041603029 | K20: =K17+K18-K19 -> 0.042889364 | L20: =L17+L18-L19 -> 0.046776716 | M20: =M17+M18-M19 -> 0.049129461 | N20: =N17+N18-N19 -> 0.052960914 | O20: =O17+O18-O19 -> 0.056682674 | P20: =P17+P18-P19 -> 0.061061431 | R20: Lithuania | S20: 0.0546 | T20: 74317 | U20: =T20/$T$31 -> 0.0043064054
R21: Luxembourg | S21: 0.0433 | T21: 82115.5 | U21: =T21/$T$31 -> 0.0047583007
F22: WACC | R22: Malta | S22: 0.0546 | T22: 20911.2 | U22: =T22/$T$31 -> 0.0012117295
I23: 2025 | J23: =+I23+1 -> 2026 | K23: =+J23+1 -> 2027 | L23: =+K23+1 -> 2028 | M23: =+L23+1 -> 2029 | N23: =+M23+1 -> 2030 | O23: =+N23+1 -> 2031 | P23: Terminal | R23: Netherlands | S23: 0.0433 | T23: 1050133 | U23: =T23/$T$31 -> 0.060851466
F24: Weight of equity | I24: =1-I26 -> 0.11649548 | J24: =1-J26 -> 0.11635993 | K24: =1-K26 -> 0.11622469 | L24: =1-L26 -> 0.11608976 | M24: =1-M26 -> 0.11595515 | N24: =1-N26 -> 0.11582085 | O24: =1-O26 -> 0.11568686 | P24: =1-P26 -> 0.11568686 | R24: Poland | S24: 0.0546 | T24: 751931.7 | U24: =T24/$T$31 -> 0.043571763
F25: Cost of Equity | I25: =I13 -> 0.13444587 | J25: =J13 -> 0.13435532 | K25: =K13 -> 0.13607058 | L25: =L13 -> 0.13820635 | M25: =M13 -> 0.14015834 | N25: =N13 -> 0.14212439 | O25: =O13 -> 0.14375424 | P25: =P13 -> 0.14668696 | R25: Portugal | S25: 0.0593 | T25: 270352.6 | U25: =T25/$T$31 -> 0.01566597
F26: Weight of Debt | I26: =C10/(1+C10) -> 0.88350452 | J26: =C11/(1+C11) -> 0.88364007 | K26: =C12/(1+C12) -> 0.88377531 | L26: =C13/(1+C13) -> 0.88391024 | M26: =C14/(1+C14) -> 0.88404485 | N26: =C15/(1+C15) -> 0.88417915 | O26: =C16/(1+C16) -> 0.88431314 | P26: =C17/(1+C17) -> 0.88431314 | R26: Romania | S26: 0.0726 | T26: 321577.9 | U26: =T26/$T$31 -> 0.018634294
F27: Tax Rate | I27: =Macro!O17 -> 0.25 | J27: =Macro!P17 -> 0.25 | K27: =Macro!Q17 -> 0.25 | L27: =Macro!R17 -> 0.25 | M27: =Macro!S17 -> 0.25 | N27: =Macro!T17 -> 0.25 | O27: =Macro!U17 -> 0.25 | P27: =Macro!U17 -> 0.25 | R27: Slovakia | S27: 0.0593 | T27: 123538.7 | U27: =T27/$T$31 -> 0.0071586276
F28: Cost of Debt | I28: =I20 -> 0.043182787 | J28: =J20 -> 0.041603029 | K28: =K20 -> 0.042889364 | L28: =L20 -> 0.046776716 | M28: =M20 -> 0.049129461 | N28: =N20 -> 0.052960914 | O28: =O20 -> 0.056682674 | P28: =P20 -> 0.061061431 | R28: Slovenia | S28: 0.0593 | T28: 64050 | U28: =T28/$T$31 -> 0.0037114693
F29: WACC | I29: =I24*I25+I26*(1-I27)*I28 -> 0.044276476 | J29: =J24*J25+J26*(1-J27)*J28 -> 0.043205152 | K29: =K24*K25+K26*(1-K27)*K28 -> 0.044243181 | L29: =L24*L25+L26*(1-L27)*L28 -> 0.047054155 | M29: =M24*M25+M26*(1-M27)*M28 -> 0.048826566 | N29: =N24*N25+N26*(1-N27)*N28 -> 0.051581169 | O29: =O24*O25+O26*(1-O27)*O28 -> 0.054224401 | P29: =P24*P25+P26*(1-P27)*P28 -> 0.057467823 | R29: Spain | S29: 0.0646 | T29: 1497761 | U29: =T29/$T$31 -> 0.086789914
R30: Sweden | S30: 0.0433 | T30: 535176.8 | U30: =T30/$T$31 -> 0.031011589
F31: WACC | I31: {=INDEX(I33:I35,Valuation!$E$9)} -> 0.047752691 | J31: {=INDEX(J33:J35,Valuation!$E$9)} -> 0.046679585 | K31: {=INDEX(K33:K35,Valuation!$E$9)} -> 0.047715836 | L31: {=INDEX(L33:L35,Valuation!$E$9)} -> 0.050525036 | M31: {=INDEX(M33:M35,Valuation!$E$9)} -> 0.052295677 | N31: {=INDEX(N33:N35,Valuation!$E$9)} -> 0.055048514 | O31: {=INDEX(O33:O35,Valuation!$E$9)} -> 0.057689985 | P31: {=INDEX(P33:P35,Valuation!$E$9)} -> 0.060933407 | R31: Total GDP | T31: =SUM(T4:T30) -> 17257316
R32: Weighted average ERP by GDP | U32: =SUMPRODUCT(S4:S30,U4:U30) -> 0.05352576
F33: Best Case | I33: 0.039574598 | J33: 0.038330559 | K33: 0.039233985 | L33: 0.04202971 | M33: 0.044062299 | N33: 0.047052911 | O33: 0.050053871 | P33: 0.055243347
F34: Base Case | I34: =I29 -> 0.044276476 | J34: =J29 -> 0.043205152 | K34: =K29 -> 0.044243181 | L34: =L29 -> 0.047054155 | M34: =M29 -> 0.048826566 | N34: =N29 -> 0.051581169 | O34: =O29 -> 0.054224401 | P34: =P29 -> 0.057467823
F35: Worst Case | I35: 0.047752691 | J35: 0.046679585 | K35: 0.047715836 | L35: 0.050525036 | M35: 0.052295677 | N35: 0.055048514 | O35: 0.057689985 | P35: 0.060933407
B38: Debt and Ratings | R38: Risk-free Rate Assumptions
U39: 2025 | V39: =+U39+1 -> 2026 | W39: =+V39+1 -> 2027 | X39: =+W39+1 -> 2028 | Y39: =+X39+1 -> 2029 | Z39: =+Y39+1 -> 2030 | AA39: =Z39+1 -> 2031 | AB39: Terminal
B40: Debt Breakdown 2024 | I40: Synthetic rating | R40: Instantaneous Forward AAA EU gov. bonds | U40: 0.01896668 | V40: 0.01928558 | W40: 0.0207661 | X40: 0.02288764 | Y40: 0.02524162 | Z40: 0.02757372 | AA40: 0.02973342 | AB40: 0.03559887
E41: Non-current | F41: Current | G41: Total | I41: If interest coverage ratio is greater than | J41: to ≤ | K41: Rating | L41: Spread | M41: Debt-Recovery Rates | O41: Drop in EBITDA | R41: EURIBOR 3 month swap futures | U41: =(100-97.95)/100 -> 0.0205 | V41: =(100-98)/100 -> 0.02 | W41: =(100-97.805)/100 -> 0.02195 | X41: =(100-97.59)/100 -> 0.0241 | Y41: =(100-97.435)/100 -> 0.02565 | Z41: =(100-97.275)/100 -> 0.02725 | AA41: =(100-97.165)/100 -> 0.02835 | AB41: =(100-97.165)/100 -> 0.02835
B42: Renault SA redeemable shares | E42: 260 | F42: 0 | I42: 8.5 | J42: 100000 | K42: Aaa/AAA | L42: 0.0045 | M42: 1 | O42: 0
B43: Bonds | E43: 4631 | F43: 2283 | I43: 6.5 | J43: 8.5 | K43: Aa2/AA | L43: 0.006 | M43: 0.954 | O43: 0 | R43: Instantaneous weight | T43: 0.5
B44: Other debt represented by certificate | E44: 0 | F44: 665 | I44: 5.5 | J44: 6.5 | K44: A1/A+ | L44: 0.0077 | M44: 0.7335 | O44: 0 | R44: EURIBOR weight | T44: =1-T43 -> 0.5
B45: Borrowings from credit institutions | E45: 52 | F45: 296 | I45: 4.25 | J45: 5.5 | K45: A2/A | L45: 0.0085 | M45: 0.513 | O45: 0 | R45: Weighted average implied risk-free rate | U45: =U40*$T$43+U41*$T$44 -> 0.01973334 | V45: =V40*$T$43+V41*$T$44 -> 0.01964279 | W45: =W40*$T$43+W41*$T$44 -> 0.02135805 | X45: =X40*$T$43+X41*$T$44 -> 0.02349382 | Y45: =Y40*$T$43+Y41*$T$44 -> 0.02544581 | Z45: =Z40*$T$43+Z41*$T$44 -> 0.02741186 | AA45: =AA40*$T$43+AA41*$T$44 -> 0.02904171 | AB45: =AB40*$T$43+AB41*$T$44 -> 0.031974435
B46: Lease liabilities | E46: 441 | F46: 103 | I46: 3 | J46: 4.25 | K46: A3/A- | L46: 0.0095 | M46: 0.473 | O46: -0.02
B47: Other financial liabilities | E47: 141 | F47: 263 | I47: 2.5 | J47: 3 | K47: Baa2/BBB | L47: 0.012 | M47: 0.433 | O47: -0.1
B48: Derivatives on financing | E48: 49 | F48: 368 | I48: 2.25 | J48: 2.5 | K48: Ba1/BB+ | L48: 0.0155 | M48: 0.405 | O48: -0.2
B49: Financial liabilities internal | E49: 14 | F49: 8 | I49: 2 | J49: 2.25 | K49: Ba2/BB | L49: 0.0183 | M49: 0.377 | O49: -0.2
B50: Subordinated loans Diac | E50: 1678 | F50: 0 | I50: 1.75 | J50: 2 | K50: B1/B+ | L50: 0.0261 | M50: 0.368 | O50: -0.2
B51: Total Financial Liabilities | E51: =SUM(E42:E50) -> 7266 | F51: =SUM(F42:F50) -> 3986 | G51: =SUM(E51:F51) -> 11252 | I51: 1.5 | J51: 1.75 | K51: B2/B | L51: 0.03 | M51: 0.359 | O51: -0.2
I52: 1.25 | J52: 1.5 | K52: B3/B- | L52: 0.0442 | M52: 0.3215 | O52: -0.25
B53: Gross cost of financial indebtness | G53: 336 | I53: 0.8 | J53: 1.25 | K53: Caa/CCC | L53: 0.0728 | M53: 0.284 | O53: -0.4
B54: Implied rate of financial debt | E54: =G53/G51 -> 0.029861358 | I54: 0.65 | J54: 0.8 | K54: Ca2/CC | L54: 0.101 | M54: 0.1893 | O54: -0.4
I55: 0.2 | J55: 0.65 | K55: C2/C | L55: 0.155 | M55: 0.0947 | O55: -0.4
I56: -100000 | J56: 0.2 | K56: D2/D | L56: 0.19 | M56: 0 | O56: -0.5
B58: Renault Credit Rating Details | I58: Synthetic Rating Spread
B59: Rating Agency | C59: Rating | D59: Date | E59: Weight | I59: Rating | J59: 2019 | K59: 2020 | L59: 2021 | M59: 2022 | N59: 2023 | O59: 2024 | P59: 2025
B60: S&P | C60: BB+ | D60: 45727 | I60: Aaa/AAA | J60: 0.0075 | K60: 0.0063 | L60: 0.0069 | M60: 0.0067 | N60: 0.0069 | O60: 0.0059 | P60: 0.0045
I61: Aa2/AA | J61: 0.01 | K61: 0.0078 | L61: 0.0085 | M61: 0.0082 | N61: 0.0085 | O61: 0.007 | P61: 0.006
B62: Interest coverage ratio | D62: ='Main Financials'!N17/-('Main Financials'!N58+'Main Financials'!N60) -> 2.6938349 | I62: A1/A+ | J62: 0.0125 | K62: 0.0098 | L62: 0.0107 | M62: 0.0103 | N62: 0.0123 | O62: 0.0092 | P62: 0.0077
I63: A2/A | J63: 0.0138 | K63: 0.0108 | L63: 0.0118 | M63: 0.0114 | N63: 0.0142 | O63: 0.0107 | P63: 0.0085
B64: Spread based financials | D64: =L47 -> 0.012 | E64: 0.5 | I64: A3/A- | J64: 0.0156 | K64: 0.0122 | L64: 0.0133 | M64: 0.0129 | N64: 0.0162 | O64: 0.0121 | P64: 0.0095
B65: Avg. pread based on rating | D65: =AVERAGE(J66:P66) -> 0.020642857 | E65: =1-E64 -> 0.5 | I65: Baa2/BBB | J65: 0.02 | K65: 0.0156 | L65: 0.0171 | M65: 0.0159 | N65: 0.02 | O65: 0.0147 | P65: 0.012
I66: Ba1/BB+ | J66: 0.025 | K66: 0.02 | L66: 0.0231 | M66: 0.0193 | N66: 0.0242 | O66: 0.0174 | P66: 0.0155
B67: WA spread | D67: =SUMPRODUCT(D64:D65,E64:E65) -> 0.016321429 | I67: Ba2/BB | J67: 0.036 | K67: 0.024 | L67: 0.0277 | M67: 0.0215 | N67: 0.0313 | O67: 0.0221 | P67: 0.0183
I68: B1/B+ | J68: 0.045 | K68: 0.0351 | L68: 0.0405 | M68: 0.0315 | N68: 0.0455 | O68: 0.0314 | P68: 0.0261
I69: B2/B | J69: 0.054 | K69: 0.0421 | L69: 0.0486 | M69: 0.0378 | N69: 0.0526 | O69: 0.0361 | P69: 0.03
I70: B3/B- | J70: 0.066 | K70: 0.0515 | L70: 0.0594 | M70: 0.0462 | N70: 0.0737 | O70: 0.0524 | P70: 0.0442
I71: Caa/CCC | J71: 0.09 | K71: 0.082 | L71: 0.0946 | M71: 0.0778 | N71: 0.1157 | O71: 0.0851 | P71: 0.0728
I72: Ca2/CC | J72: 0.1108 | K72: 0.0864 | L72: 0.0997 | M72: 0.082 | N72: 0.1578 | O72: 0.1178 | P72: 0.101
I73: C2/C | J73: 0.1454 | K73: 0.1134 | L73: 0.1309 | M73: 0.1076 | N73: 0.175 | O73: 0.17 | P73: 0.155
I74: D2/D | J74: 0.1938 | K74: 0.1512 | L74: 0.1744 | M74: 0.1434 | N74: 0.2 | O74: 0.2 | P74: 0.19

Sheet Beta
B2: Comparable Companies Unlevered Beta Calculation
B3: Companies | C3: €/ Share | D3: FD Shares | E3: Market Cap | F3: Total Debt | G3: Levered β | H3: Tax Rate | I3: Unlevered β | J3: Last Report
B4: Renault | C4: =CCA!F54 -> 33.79 | D4: =CCA!G54 -> 273.46 | E4: =C4*D4 -> 9240.2134 | F4: =CCA!J54 -> 70078 | G4: =M33 -> 1.6732075 | H4: =F19 -> 0.2583 | I4: =G4/(1+(1-H4)*(F4/E4)) -> 0.25255693 | J4: 45838
B5: Stellantis | C5: {=INDIRECT($B5&"!F9")} -> 8.778 | D5: {=INDIRECT($B5&"!R29")} -> 2888.724 | E5: =C5*D5 -> 25357.219 | F5: {=INDIRECT($B5&"!R27")} -> 40799 | G5: =P33 -> 1.5370731 | H5: =Macro!N22 -> 0.24 | I5: =G5/(1+(1-H5)*(F5/E5)) -> 0.69149778 | J5: {=INDIRECT($B5&"!I6")} -> 45838
B6: Volkswagen | C6: {=INDIRECT(B6&"!F9")} -> 91.35 | D6: {=INDIRECT($B6&"!R29")} -> 501.29526 | E6: =C6*D6 -> 45793.322 | F6: {=INDIRECT($B6&"!R27")} -> 271470 | G6: =R33 -> 1.384302 | H6: =Macro!N23 -> 0.15825 | I6: =G6/(1+(1-H6)*(F6/E6)) -> 0.23110117 | J6: {=INDIRECT($B6&"!I6")} -> 09/30/2025
B7: Nissan | C7: {=INDIRECT(B7&"!F9")} -> 1.9880741 | D7: {=INDIRECT($B7&"!R29")} -> 3495.7389 | E7: =C7*D7 -> 6949.788 | F7: {=INDIRECT($B7&"!R27")} -> 51122.825 | G7: =T33 -> 0.68546068 | H7: =Macro!N24 -> 0.232 | I7: =G7/(1+(1-H7)*(F7/E7)) -> 0.10308566 | J7: {=INDIRECT($B7&"!I6")} -> 09/30/2025
B8: BMW | C8: {=INDIRECT(B8&"!F9")} -> 80.72 | D8: {=INDIRECT($B8&"!R29")} -> 609.81512 | E8: =C8*D8 -> 49224.277 | F8: {=INDIRECT($B8&"!R27")} -> 107748 | G8: =V33 -> 1.2319778 | H8: =Macro!N25 -> 0.15825 | I8: =G8/(1+(1-H8)*(F8/E8)) -> 0.43340992 | J8: {=INDIRECT($B8&"!I6")} -> 09/30/2025
B9: MercedesBenz | C9: {=INDIRECT(B9&"!F9")} -> 56.21 | D9: {=INDIRECT($B9&"!R29")} -> 962.9037 | E9: =C9*D9 -> 54124.817 | F9: {=INDIRECT($B9&"!R27")} -> 102343 | G9: =X33 -> 1.5464015 | H9: =Macro!N26 -> 0.15825 | I9: =G9/(1+(1-H9)*(F9/E9)) -> 0.5966884 | J9: {=INDIRECT($B9&"!I6")} -> 09/30/2025
B10: Ford | C10: {=INDIRECT(B10&"!F9")} -> 11.375845 | D10: {=INDIRECT($B10&"!R29")} -> 4203 | E10: =C10*D10 -> 47812.677 | F10: {=INDIRECT($B10&"!R27")} -> 139899.58 | G10: =Z33 -> 1.2815918 | H10: =Macro!N27 -> 0.232 | I10: =G10/(1+(1-H10)*(F10/E10)) -> 0.39468046 | J10: {=INDIRECT($B10&"!I6")} -> 09/30/2025
B11: Toyota | C11: {=INDIRECT(B11&"!F9")} -> 17.648024 | D11: {=INDIRECT($B11&"!R29")} -> 13033.389 | E11: =C11*D11 -> 230013.57 | F11: {=INDIRECT($B11&"!R27")} -> 229725.74 | G11: =AB33 -> 0.59175927 | H11: =Macro!N28 -> 0.232 | I11: =G11/(1+(1-H11)*(F11/E11)) -> 0.33488751 | J11: {=INDIRECT($B11&"!I6")} -> 09/30/2025
B12: GeneralMotors | C12: {=INDIRECT(B12&"!F9")} -> 59.85964 | D12: {=INDIRECT($B12&"!R29")} -> 933 | E12: =C12*D12 -> 55849.044 | F12: {=INDIRECT($B12&"!R27")} -> 112768.51 | G12: =AD33 -> 1.2630494 | H12: =Macro!N29 -> 0.21 | I12: =G12/(1+(1-H12)*(F12/E12)) -> 0.48669771 | J12: {=INDIRECT($B12&"!I6")} -> 09/30/2025
B13: Honda | C13: {=INDIRECT(B13&"!F9")} -> 8.7733965 | D13: {=INDIRECT($B13&"!R29")} -> 3892.5506 | E13: =C13*D13 -> 34150.89 | F13: {=INDIRECT($B13&"!R27")} -> 72636.764 | G13: =AF33 -> 0.73802082 | H13: =Macro!N30 -> 0.21 | I13: =G13/(1+(1-H13)*(F13/E13)) -> 0.27535218 | J13: {=INDIRECT($B13&"!I6")} -> 09/30/2025
B14: Mean | I14: =AVERAGE(I5:I13) -> 0.39415564
B15: Median | I15: =MEDIAN(I5:I13) -> 0.39468046
B17: Bottom Up Beta
C18: Unlevered β | D18: Market Cap | E18: Total Debt | F18: Tax Rate | G18: Levered β
B19: Mean | C19: =I14 -> 0.39415564 | D19: =$E$4 -> 9240.2134 | E19: =$F$4 -> 70078 | F19: =Macro!$N$17 -> 0.2583 | G19: =C19*(1+(1-F19)*(E19/D19)) -> 2.611309
B20: Median | C20: =I15 -> 0.39468046 | D20: =$E$4 -> 9240.2134 | E20: =$F$4 -> 70078 | F20: =Macro!$N$17 -> 0.2583 | G20: =C20*(1+(1-F20)*(E20/D20)) -> 2.6147859
B22: Beta Summary
B23: Regression β | C23: =M33 -> 1.6732075
B24: Bottom up β | C24: =AVERAGE(G19:G20) -> 2.6130474
B26: Stock Return History and Levered Beta Calculations
B27: All return values are taken from FactSet as total return measures and converted to € by their currency conversion, yields are also taken from FactSet as Yield-to-Maturity values.
B29: Risk Free Data | E29: Return Data and Levered Beta Calculations | O29: Comparables Levered Beta Calculations
B30: Eurozone 10-year Bond | E30: Date | F30: 45962 | H30: Frequency | J30: W | L30: Currency | M30: EUR
B31: Note: Negative in '20-'21 | E31: Start | F31: 43831 | H31: Return Convention | J31: 7-DAY | O31: Stellantis | Q31: Volkswagen | S31: Nissan | U31: BMW | W31: Mercedez-Benz | Y31: Ford | AA31: Toyota | AC31: General Motors | AE31: Honda
O32: Stock Levered β | Q32: Stock Levered β | S32: Stock Levered β | U32: Stock Levered β | W32: Stock Levered β | Y32: Stock Levered β | AA32: Stock Levered β | AC32: Stock Levered β | AE32: Stock Levered β
B33: EU10YR | F33: RNO | G33: STOXX600 | H33: RNO | I33: STOXX600 | K33: Renault Levered β | M33: =_xlfn.COVARIANCE.P(H35:H339,I35:I339)/_xlfn.VAR.P(I35:I339) -> 1.6732075 | P33: =_xlfn.COVARIANCE.P(P35:P339,$I$35:$I$339)/_xlfn.VAR.P($I$35:$I$339) -> 1.5370731 | R33: =_xlfn.COVARIANCE.P(R35:R339,$I$35:$I$339)/_xlfn.VAR.P($I$35:$I$339) -> 1.384302 | T33: =_xlfn.COVARIANCE.P(T35:T339,$I$35:$I$339)/_xlfn.VAR.P($I$35:$I$339) -> 0.68546068 | V33: =_xlfn.COVARIANCE.P(V35:V339,$I$35:$I$339)/_xlfn.VAR.P($I$35:$I$339) -> 1.2319778 | X33: =_xlfn.COVARIANCE.P(X35:X339,$I$35:$I$339)/_xlfn.VAR.P($I$35:$I$339) -> 1.5464015 | Z33: =_xlfn.COVARIANCE.P(Z35:Z339,$I$35:$I$339)/_xlfn.VAR.P($I$35:$I$339) -> 1.2815918 | AB33: =_xlfn.COVARIANCE.P(AB35:AB339,$I$35:$I$339)/_xlfn.VAR.P($I$35:$I$339) -> 0.59175927 | AD33: =_xlfn.COVARIANCE.P(AD35:AD339,$I$35:$I$339)/_xlfn.VAR.P($I$35:$I$339) -> 1.2630494 | AF33: =_xlfn.COVARIANCE.P(AF35:AF339,$I$35:$I$339)/_xlfn.VAR.P($I$35:$I$339) -> 0.73802082
B34: YTM | C34: Weekly rf | E34: Date | F34: Return | G34: Return | H34: Excess | I34: Excess | O34: Return | P34: Excess | Q34: Return | R34: Excess | S34: Return | T34: Excess | U34: Return | V34: Excess | W34: Return | X34: Excess | Y34: Return | Z34: Excess | AA34: Return | AB34: Excess | AC34: Return | AD34: Excess | AE34: Return | AF34: Excess
B35: 0.02644 | C35: =(1+B35)^(1/52)-1 -> 0.00050198181 | E35: 45961 | F35: -0.019493699 | G35: -0.006721556 | H35: =F35-$C35 -> -0.019995681 | I35: =G35-C35 -> -0.0072235378 | O35: -0.070619345 | P35: =O35-$C35 -> -0.071121327 | Q35: -0.0010935068 | R35: =Q35-$C35 -> -0.0015954886 | S35: -0.06036663 | T35: =S35-$C35 -> -0.060868612 | U35: -0.0054214 | V35: =U35-$C35 -> -0.0059233818 | W35: 0.045767426 | X35: =W35-$C35 -> 0.045265444 | Y35: -0.04439622 | Z35: =Y35-$C35 -> -0.044898202 | AA35: 0.0024225712 | AB35: =AA35-$C35 -> 0.0019205894 | AC35: -0.00096452236 | AD35: =AC35-$C35 -> -0.0014665042 | AE35: -0.02270466 | AF35: =AE35-$C35 -> -0.023206642
B36: 0.02627 | C36: =(1+B36)^(1/52)-1 -> 0.00049879493 | E36: 45954 | F36: -0.00058156252 | G36: 0.016812682 | H36: =F36-C36 -> -0.0010803575 | I36: =G36-C36 -> 0.016313887 | O36: 0.05945039 | P36: =O36-$C36 -> 0.058951595 | Q36: -0.011351407 | R36: =Q36-$C36 -> -0.011850202 | S36: 0.05584359 | T36: =S36-$C36 -> 0.055344795 | U36: 0.011717796 | V36: =U36-$C36 -> 0.011219001 | W36: 0.0071201324 | X36: =W36-$C36 -> 0.0066213375 | Y36: 0.16521824 | Z36: =Y36-$C36 -> 0.16471945 | AA36: 0.053311944 | AB36: =AA36-$C36 -> 0.052813149 | AC36: 0.19747602 | AD36: =AC36-$C36 -> 0.19697723 | AE36: 0.038271666 | AF36: =AE36-$C36 -> 0.037772871
B37: 0.02583 | C37: =(1+B37)^(1/52)-1 -> 0.00049054414 | E37: 45947 | F37: 0.0017477274 | G37: 0.003686905 | H37: =F37-C37 -> 0.0012571833 | I37: =G37-C37 -> 0.0031963609 | O37: 0.04147196 | P37: =O37-$C37 -> 0.040981416 | Q37: 0.018161774 | R37: =Q37-$C37 -> 0.01767123 | S37: -0.012245059 | T37: =S37-$C37 -> -0.012735603 | U37: 0.02217126 | V37: =U37-$C37 -> 0.021680716 | W37: 0.003195405 | X37: =W37-$C37 -> 0.0027048609 | Y37: 0.03686297 | Z37: =Y37-$C37 -> 0.036372426 | AA37: 0.017873764 | AB37: =AA37-$C37 -> 0.01738322 | AC37: 0.04683256 | AD37: =AC37-$C37 -> 0.046342016 | AE37: -0.019155204 | AF37: =AE37-$C37 -> -0.019645748
B38: 0.02667 | C38: =(1+B38)^(1/52)-1 -> 0.00050629264 | E38: 45940 | F38: -0.04052538 | G38: -0.011026442 | H38: =F38-C38 -> -0.041031673 | I38: =G38-C38 -> -0.011532735 | O38: -0.05099779 | P38: =O38-$C38 -> -0.051504083 | Q38: -0.035562634 | R38: =Q38-$C38 -> -0.036068927 | S38: -0.023082614 | T38: =S38-$C38 -> -0.023588907 | U38: -0.0918768 | V38: =U38-$C38 -> -0.092383093 | W38: -0.039884508 | X38: =W38-$C38 -> -0.040390801 | Y38: -0.0869658 | Z38: =Y38-$C38 -> -0.087472093 | AA38: 0.0011146069 | AB38: =AA38-$C38 -> 0.00060831422 | AC38: -0.066736164 | AD38: =AC38-$C38 -> -0.067242457 | AE38: 0.0010011196 | AF38: =AE38-$C38 -> 0.00049482696
B39: 0.02703 | C39: =(1+B39)^(1/52)-1 -> 0.00051303813 | E39: 45933 | F39: 0.029640198 | G39: 0.028727531 | H39: =F39-C39 -> 0.02912716 | I39: =G39-C39 -> 0.028214493 | O39: 0.1410501 | P39: =O39-$C39 -> 0.14053706 | Q39: 0.017278552 | R39: =Q39-$C39 -> 0.016765514 | S39: -0.022078216 | T39: =S39-$C39 -> -0.022591254 | U39: 0.007930994 | V39: =U39-$C39 -> 0.0074179559 | W39: 0.039197326 | X39: =W39-$C39 -> 0.038684288 | Y39: 0.05059612 | Z39: =Y39-$C39 -> 0.050083082 | AA39: -0.03445673 | AB39: =AA39-$C39 -> -0.034969768 | AC39: -0.02218157 | AD39: =AC39-$C39 -> -0.022694608 | AE39: -0.067053614 | AF39: =AE39-$C39 -> -0.067566652
B40: 0.02741 | C40: =(1+B40)^(1/52)-1 -> 0.00052015586 | E40: 45926 | F40: -0.017528951 | G40: 0.00072193146 | H40: =F40-C40 -> -0.018049107 | I40: =G40-C40 -> 0.0002017756 | O40: -0.06416476 | P40: =O40-$C40 -> -0.064684916 | Q40: -0.057985783 | R40: =Q40-$C40 -> -0.058505939 | S40: 0.0066804886 | T40: =S40-$C40 -> 0.0061603327 | U40: 0.02978611 | V40: =U40-$C40 -> 0.029265954 | W40: 0.035742044 | X40: =W40-$C40 -> 0.035221888 | Y40: 0.03939712 | Z40: =Y40-$C40 -> 0.038876964 | AA40: 0.010572672 | AB40: =AA40-$C40 -> 0.010052516 | AC40: 0.0441792 | AD40: =AC40-$C40 -> 0.043659044 | AE40: 0.0063358545 | AF40: =AE40-$C40 -> 0.0058156986
B41: 0.02738 | C41: =(1+B41)^(1/52)-1 -> 0.00051959402 | E41: 45919 | F41: 0.029095173 | G41: -0.0012977123 | H41: =F41-C41 -> 0.028575579 | I41: =G41-C41 -> -0.0018173063 | O41: 0.056535244 | P41: =O41-$C41 -> 0.05601565 | Q41: -0.047480583 | R41: =Q41-$C41 -> -0.048000177 | S41: 0.0022317171 | T41: =S41-$C41 -> 0.0017121231 | U41: -0.0066809654 | V41: =U41-$C41 -> -0.0072005594 | W41: -0.0040626526 | X41: =W41-$C41 -> -0.0045822466 | Y41: -0.0077599883 | Z41: =Y41-$C41 -> -0.0082795823 | AA41: 0.007668376 | AB41: =AA41-$C41 -> 0.007148782 | AC41: 0.0055470467 | AD41: =AC41-$C41 -> 0.0050274527 | AE41: -0.015222728 | AF41: =AE41-$C41 -> -0.015742322
B42: 0.02704 | C42: =(1+B42)^(1/52)-1 -> 0.00051322547 | E42: 45912 | F42: 0.041199684 | G42: 0.010251045 | H42: =F42-C42 -> 0.040686459 | I42: =G42-C42 -> 0.0097378195 | O42: 0.031612873 | P42: =O42-$C42 -> 0.031099648 | Q42: 0.017751455 | R42: =Q42-$C42 -> 0.01723823 | S42: 0.053081512 | T42: =S42-$C42 -> 0.052568287 | U42: -0.05223882 | V42: =U42-$C42 -> -0.052752045 | W42: -0.023242593 | X42: =W42-$C42 -> -0.023755818 | Y42: -0.0043047667 | Z42: =Y42-$C42 -> -0.0048179922 | AA42: -0.027985632 | AB42: =AA42-$C42 -> -0.028498857 | AC42: 0.0047603846 | AD42: =AC42-$C42 -> 0.0042471591 | AE42: -0.02886659 | AF42: =AE42-$C42 -> -0.029379815
B43: 0.02663 | C43: =(1+B43)^(1/52)-1 -> 0.000505543 | E43: 45905 | F43: -0.017559528 | G43: -0.0016904473 | H43: =F43-C43 -> -0.018065071 | I43: =G43-C43 -> -0.0021959903 | O43: -0.05303031 | P43: =O43-$C43 -> -0.053535853 | Q43: -0.007827759 | R43: =Q43-$C43 -> -0.008333302 | S43: 0.033361077 | T43: =S43-$C43 -> 0.032855534 | U43: -0.011401713 | V43: =U43-$C43 -> -0.011907256 | W43: -0.0080599785 | X43: =W43-$C43 -> -0.0085655215 | Y43: -0.0052259564 | Z43: =Y43-$C43 -> -0.0057314994 | AA43: 0.0266366 | AB43: =AA43-$C43 -> 0.026131057 | AC43: -0.008130908 | AD43: =AC43-$C43 -> -0.008636451 | AE43: 0.02654457 | AF43: =AE43-$C43 -> 0.026039027
B44: 0.02713 | C44: =(1+B44)^(1/52)-1 -> 0.00051491147 | E44: 45898 | F44: 0.0011918545 | G44: -0.019882381 | H44: =F44-C44 -> 0.00067694303 | I44: =G44-C44 -> -0.020397292 | O44: -0.053435087 | P44: =O44-$C44 -> -0.053949998 | Q44: -0.0266667 | R44: =Q44-$C44 -> -0.027181611 | S44: -0.054171267 | T44: =S44-$C44 -> -0.054686178 | U44: -0.021439493 | V44: =U44-$C44 -> -0.021954404 | W44: -0.032462835 | X44: =W44-$C44 -> -0.032977746 | Y44: 0.003668785 | Z44: =Y44-$C44 -> 0.0031538735 | AA44: -0.02250141 | AB44: =AA44-$C44 -> -0.023016321 | AC44: 0.0048837662 | AD44: =AC44-$C44 -> 0.0043688547 | AE44: -0.02075076 | AF44: =AE44-$C44 -> -0.021265671
B45: 0.02727 | C45: =(1+B45)^(1/52)-1 -> 0.00051753384 | E45: 45891 | F45: 0.013591051 | G45: 0.013982177 | H45: =F45-C45 -> 0.013073517 | I45: =G45-C45 -> 0.013464643 | O45: 0.038683295 | P45: =O45-$C45 -> 0.038165761 | Q45: 0.029411793 | R45: =Q45-$C45 -> 0.028894259 | S45: 0.04378557 | T45: =S45-$C45 -> 0.043268036 | U45: 0.014200091 | V45: =U45-$C45 -> 0.013682557 | W45: 0.03046167 | X45: =W45-$C45 -> 0.029944136 | Y45: 0.025698304 | Z45: =Y45-$C45 -> 0.02518077 | AA45: 0.0307616 | AB45: =AA45-$C45 -> 0.030244066 | AC45: 0.036052346 | AD45: =AC45-$C45 -> 0.035534812 | AE45: 0.024923205 | AF45: =AE45-$C45 -> 0.024405671
B46: 0.02773 | C46: =(1+B46)^(1/52)-1 -> 0.00052614773 | E46: 45884 | F46: 0.020968199 | G46: 0.011844635 | H46: =F46-C46 -> 0.020442051 | I46: =G46-C46 -> 0.011318487 | O46: 0.029433608 | P46: =O46-$C46 -> 0.02890746 | Q46: 0.04401231 | R46: =Q46-$C46 -> 0.043486162 | S46: 0.01524651 | T46: =S46-$C46 -> 0.014720362 | U46: 0.030878305 | V46: =U46-$C46 -> 0.030352157 | W46: 0.026669264 | X46: =W46-$C46 -> 0.026143116 | Y46: 0.0057685375 | Z46: =Y46-$C46 -> 0.0052423898 | AA46: 0.030949354 | AB46: =AA46-$C46 -> 0.030423206 | AC46: 0.04690373 | AD46: =AC46-$C46 -> 0.046377582 | AE46: 0.0210191 | AF46: =AE46-$C46 -> 0.020492952
B47: 0.02678 | C47: =(1+B47)^(1/52)-1 -> 0.00050835401 | E47: 45877 | F47: 0.007455826 | G47: 0.021071792 | H47: =F47-C47 -> 0.006947472 | I47: =G47-C47 -> 0.020563438 | O47: 0.06548965 | P47: =O47-$C47 -> 0.064981296 | Q47: 0.069512844 | R47: =Q47-$C47 -> 0.06900449 | S47: -0.0039014816 | T47: =S47-$C47 -> -0.0044098356 | U47: 0.065042734 | V47: =U47-$C47 -> 0.06453438 | W47: 0.061507106 | X47: =W47-$C47 -> 0.060998752 | Y47: 0.037100434 | Z47: =Y47-$C47 -> 0.03659208 | AA47: 0.010781407 | AB47: =AA47-$C47 -> 0.010273053 | AC47: 0.010163069 | AD47: =AC47-$C47 -> 0.009654715 | AE47: 0.011680126 | AF47: =AE47-$C47 -> 0.011171772
... B339: -0.00277 | C339: =(1+B339)^(1/52)-1 -> -5.3341722e-05 | E339: 43833 | F339: -0.041395307 | G339: -0.0033592582 | H339: =F339-C339 -> -0.041341965 | I339: =G339-C339 -> -0.0033059165 | O339: -0.02621007 | P339: =O339-$C339 -> -0.026156728 | Q339: 0.00028634071 | R339: =Q339-$C339 -> 0.00033968243 | S339: 0.00965631 | T339: =S339-$C339 -> 0.0097096517 | U339: -0.0025846958 | V339: =U339-$C339 -> -0.0025313541 | W339: -0.015449405 | X339: =W339-$C339 -> -0.015396063 | Y339: -0.016201913 | Z339: =Y339-$C339 -> -0.016148571 | AA339: 0.011767387 | AB339: =AA339-$C339 -> 0.011820729 | AC339: -0.0067425966 | AD339: =AC339-$C339 -> -0.0066892549 | AE339: 0.0026123524 | AF339: =AE339-$C339 -> 0.0026656941
B340: Source: FactSet Global

Sheet CCA
B2: Comparable Companies Analysis
B4: =N87 -> Valuation Summary - Renault | G4: =S87 -> Implied Per Share Multiples Value Range | J4: Football Field
F5: =R88 -> 25th | H5: =T88 -> 75th
B6: =N89 -> Comparables | E6: =Q89 -> Minimum | F6: =R89 -> Percentile | G6: =S89 -> Median | H6: =T89 -> Percentile | I6: =U89 -> Maximum
B7: =N90 -> 2027E Enterprise Value / Revenue | E7: =Q90 | F7: =R90 | G7: =S90 -> 9.9641178 | H7: =T90 -> 27.369287 | I7: =U90 -> 138.58244
B8: =N91 -> 2026E Enterprise Value / Revenue | E8: =Q91 | F8: =R91 | G8: =S91 -> 5.5871732 | H8: =T91 -> 26.75349 | I8: =U91 -> 135.45151
B9: =N92 -> 2025E Enterprise Value / Revenue | E9: =Q92 | F9: =R92 | G9: =S92 | H9: =T92 -> 23.417907 | I9: =U92 -> 130.74177
E10: =Q93 | F10: =R93 | G10: =S93 | H10: =T93 | I10: =U93
B11: =N94 -> 2027E Enterprise Value / EBITDA | E11: =Q94 | F11: =R94 | G11: =S94 -> 32.812612 | H11: =T94 -> 114.0622 | I11: =U94 -> 167.98164
B12: =N95 -> 2026E Enterprise Value / EBITDA | E12: =Q95 | F12: =R95 | G12: =S95 -> 29.976955 | H12: =T95 -> 122.18452 | I12: =U95 -> 230.6229
B13: =N96 -> 2025E Enterprise Value / EBITDA | E13: =Q96 | F13: =R96 | G13: =S96 -> 48.711798 | H13: =T96 -> 140.50703 | I13: =U96 -> 630.11649
B15: =N98 -> 2027E P/E Ratio | E15: =Q98 -> 26.000423 | F15: =R98 -> 42.575907 | G15: =S98 -> 51.979337 | H15: =T98 -> 63.193527 | I15: =U98 -> 76.0307
B16: =N99 -> 2026E P/E Ratio | E16: =Q99 -> 31.233211 | F16: =R99 -> 45.010506 | G16: =S99 -> 60.326446 | H16: =T99 -> 70.31905 | I16: =U99 -> 683.35123
B17: =N100 -> 2025E P/E Ratio | E17: =Q100 -> 0 | F17: =R100 -> 0 | G17: =S100 -> 0 | H17: =T100 -> 0 | I17: =U100 -> 0
B19: =N102 -> 2027E Price / Sales | E19: =Q102 -> 22.739119 | F19: =R102 -> 34.774634 | G19: =S102 -> 65.680217 | H19: =T102 -> 77.538196 | I19: =U102 -> 180.59822
B20: =N103 -> 2026E Price / Sales | E20: =Q103 -> 22.362181 | F20: =R103 -> 34.787437 | G20: =S103 -> 65.505591 | H20: =T103 -> 75.931122 | I20: =U103 -> 178.85444
B21: =N104 -> 2025E Price / Sales | E21: =Q104 -> 21.910685 | F21: =R104 -> 35.008505 | G21: =S104 -> 63.892517 | H21: =T104 -> 74.738867 | I21: =U104 -> 176.23135
B23: Valuation Summary - Renault | G23: Implied Per Share Multiples Value Range
F24: 25th | H24: 75th
B25: Comparables | E25: Minimum | F25: Percentile | G25: Median | H25: Percentile | I25: Maximum
B26: CCA EV/Sales | E26: =F126 | F26: =G126 | G26: =H126 -> 8.5051363 | H26: =I126 -> 25.846895 | I26: =J126 -> 134.92524
B27: CCA EV/EBITDA | E27: =F127 | F27: =G127 | G27: =H127 -> 37.167122 | H27: =I127 -> 125.58458 | I27: =J127 -> 342.90701
B28: CCA P/E Multiple | E28: =F128 -> 28.616817 | F28: =G128 -> 43.793207 | G28: =H128 -> 56.152892 | H28: =I128 -> 66.756289 | I28: =J128 -> 379.69096
B29: CCA Price/Sales | E29: =F129 -> 22.337328 | F29: =G129 -> 34.856859 | G29: =H129 -> 65.026108 | H29: =I129 -> 76.069395 | I29: =J129 -> 178.56134
B31: DCF Bear Case | E31: =F131 -> 20.86042 | F31: =G131 -> 25.102995 | G31: =H131 -> 29.933881 | H31: =I131 -> 35.690848 | I31: =J131 -> 42.393804
B32: DCF Base Case | E32: =F132 -> 33.62765 | F32: =G132 -> 40.073925 | G32: =H132 -> 47.649078 | H32: =I132 -> 57.111045 | I32: =J132 -> 68.637101
B33: DCF Bull Case | E33: =F133 -> 51.522008 | F33: =G133 -> 61.420805 | G33: =H133 -> 73.488656 | H33: =I133 -> 89.453925 | I33: =J133 -> 110.06476
B35: CCA Average Value | E35: =F135 -> 24.849124 | F35: =G135 -> 38.431398 | G35: =H135 -> 40.40008 | H35: =I135 -> 74.1832 | I35: =J135 -> 248.05115
B36: DCF Average Value | E36: =F136 -> 35.336693 | F36: =G136 -> 42.199242 | G36: =H136 -> 50.357205 | H36: =I136 -> 60.75194 | I36: =J136 -> 73.698554 | L36: Price on Nov 1st: 33.79
B39: CCA - Comparable Companies Analysis | AC39: Operating cash assessment
AC40: Cash to Sales | AF40: 2017 | AG40: =+AF40+1 -> 2018 | AH40: =+AG40+1 -> 2019 | AI40: =+AH40+1 -> 2020 | AJ40: =+AI40+1 -> 2021 | AK40: =+AJ40+1 -> 2022 | AL40: =+AK40+1 -> 2023 | AM40: =+AL40+1 -> 2024
B41: Operating Statistics | E41: Capitalization | N41: Revenue | Q41: EBITDA | T41: Net Income | Y41: EBITDA Margin | AC41: Stellantis | AF41: {=INDIRECT($AC41&"!E26")/INDIRECT($AC41&"!E16")} -> 0.12413695 | AG41: {=INDIRECT($AC41&"!F26")/INDIRECT($AC41&"!F16")} -> 0.11832953 | AH41: {=INDIRECT($AC41&"!G26")/INDIRECT($AC41&"!G16")} -> 0.14497121 | AI41: {=INDIRECT($AC41&"!H26")/INDIRECT($AC41&"!H16")} -> 0.5 | AJ41: {=INDIRECT($AC41&"!I26")/INDIRECT($AC41&"!I16")} -> 0.34444749 | AK41: {=INDIRECT($AC41&"!J26")/INDIRECT($AC41&"!J16")} -> 0.2800069 | AL41: {=INDIRECT($AC41&"!K26")/INDIRECT($AC41&"!K16")} -> 0.25575064 | AM41: {=INDIRECT($AC41&"!L26")/INDIRECT($AC41&"!L16")} -> 0.23702495
H42: Equity Value € | K42: Enterprise € | W42: Projected | X42: Projected | AC42: Volkswagen | AF42: {=INDIRECT($AC42&"!E26")/INDIRECT($AC42&"!E16")} -> 0.16223481 | AG42: {=INDIRECT($AC42&"!F26")/INDIRECT($AC42&"!F16")} -> 0.20379565 | AH42: {=INDIRECT($AC42&"!G26")/INDIRECT($AC42&"!G16")} -> 0.16898889 | AI42: {=INDIRECT($AC42&"!H26")/INDIRECT($AC42&"!H16")} -> 0.24708368 | AJ42: {=INDIRECT($AC42&"!I26")/INDIRECT($AC42&"!I16")} -> 0.24882094 | AK42: {=INDIRECT($AC42&"!J26")/INDIRECT($AC42&"!J16")} -> 0.23787135 | AL42: {=INDIRECT($AC42&"!K26")/INDIRECT($AC42&"!K16")} -> 0.21788547 | AM42: {=INDIRECT($AC42&"!L26")/INDIRECT($AC42&"!L16")} -> 0.20828816
B43: Company Name | E43: Share Price | G43: Diluted Shares | H43: Millions | I43: Cash | J43: Debt | K43: Value | L43: ROE | M43: ROIC | N43: 2025E | O43: 2026E | P43: 2027E | Q43: 2025E | R43: 2026E | S43: 2027E | T43: 2025E | U43: 2026E | V43: 2027E | W43: Revenue Growth | X43: EBITDA Growth | Y43: 2025E | Z43: 2026E | AA43: 2027E | AC43: Nissan | AF43: {=INDIRECT($AC43&"!E26")/INDIRECT($AC43&"!E16")} -> 0.099928232 | AG43: {=INDIRECT($AC43&"!F26")/INDIRECT($AC43&"!F16")} -> 0.12126319 | AH43: {=INDIRECT($AC43&"!G26")/INDIRECT($AC43&"!G16")} -> 0.16960048 | AI43: {=INDIRECT($AC43&"!H26")/INDIRECT($AC43&"!H16")} -> 0.24617634 | AJ43: {=INDIRECT($AC43&"!I26")/INDIRECT($AC43&"!I16")} -> 0.20564118 | AK43: {=INDIRECT($AC43&"!J26")/INDIRECT($AC43&"!J16")} -> 0.18528059 | AL43: {=INDIRECT($AC43&"!K26")/INDIRECT($AC43&"!K16")} -> 0.16121065 | AM43: {=INDIRECT($AC43&"!L26")/INDIRECT($AC43&"!L16")} -> 0.17624228
B44: Stellantis | F44: {=INDIRECT(B44&"!F9")} -> 8.778 | G44: {=INDIRECT(B44&"!R29")} -> 2888.724 | H44: =G44*F44 -> 25357.219 | I44: {=INDIRECT(B44&"!R26")} -> 32836 | J44: {=INDIRECT(B44&"!R27")} -> 40799 | K44: =H44-I44+J44 -> 33320.219 | L44: {=INDIRECT(B44&"!R30")} -> -0.05829118 | M44: {=INDIRECT(B44&"!R31")} -> 0.01005186 | N44: {=INDIRECT($B44&"!M16")} -> 152552.69 | O44: {=INDIRECT($B44&"!N16")} -> 160481.22 | P44: {=INDIRECT($B44&"!O16")} -> 166401.67 | Q44: {=INDIRECT($B44&"!M18")} -> 8945.5205 | R44: {=INDIRECT($B44&"!N18")} -> 13659.609 | S44: {=INDIRECT($B44&"!O18")} -> 16062.637 | T44: {=INDIRECT($B44&"!M22")} -> 2086.0842 | U44: {=INDIRECT($B44&"!N22")} -> 4879.009 | V44: {=INDIRECT($B44&"!O22")} -> 6472.0327 | W44: =SQRT(P44/N44)-1 -> 0.044404911 | X44: =IFERROR(SQRT(S44/Q44)-1,"N/A") -> 0.34000252 | Y44: =Q44/N44 -> 0.058638891 | Z44: =R44/O44 -> 0.085116558 | AA44: =S44/P44 -> 0.096529302 | AC44: BMW | AF44: {=INDIRECT($AC44&"!E26")/INDIRECT($AC44&"!E16")} -> 0.091970045 | AG44: {=INDIRECT($AC44&"!F26")/INDIRECT($AC44&"!F16")} -> 0.11335502 | AH44: {=INDIRECT($AC44&"!G26")/INDIRECT($AC44&"!G16")} -> 0.11549755 | AI44: {=INDIRECT($AC44&"!H26")/INDIRECT($AC44&"!H16")} -> 0.13675119 | AJ44: {=INDIRECT($AC44&"!I26")/INDIRECT($AC44&"!I16")} -> 0.14391535 | AK44: {=INDIRECT($AC44&"!J26")/INDIRECT($AC44&"!J16")} -> 0.11829465 | AL44: {=INDIRECT($AC44&"!K26")/INDIRECT($AC44&"!K16")} -> 0.11142909 | AM44: {=INDIRECT($AC44&"!L26")/INDIRECT($AC44&"!L16")} -> 0.13546144
B45: Volkswagen | F45: {=INDIRECT(B45&"!F9")} -> 91.35 | G45: {=INDIRECT(B45&"!R29")} -> 501.29526 | H45: =G45*F45 -> 45793.322 | I45: {=INDIRECT(B45&"!R26")} -> 65550 | J45: {=INDIRECT(B45&"!R27")} -> 271470 | K45: =H45-I45+J45 -> 251713.32 | L45: {=INDIRECT(B45&"!R30")} -> 0.040037059 | M45: {=INDIRECT(B45&"!R31")} -> 0.021366767 | N45: {=INDIRECT($B45&"!M16")} -> 324823.84 | O45: {=INDIRECT($B45&"!N16")} -> 331772.66 | P45: {=INDIRECT($B45&"!O16")} -> 340765.84 | Q45: {=INDIRECT($B45&"!M18")} -> 38573.105 | R45: {=INDIRECT($B45&"!N18")} -> 46299.426 | S45: {=INDIRECT($B45&"!O18")} -> 50404.945 | T45: {=INDIRECT($B45&"!M22")} -> 4917.487 | U45: {=INDIRECT($B45&"!N22")} -> 10889.342 | V45: {=INDIRECT($B45&"!O22")} -> 13216.16 | W45: =SQRT(P45/N45)-1 -> 0.024245532 | X45: =IFERROR(SQRT(S45/Q45)-1,"N/A") -> 0.14312645 | Y45: =Q45/N45 -> 0.11875084 | Z45: =R45/O45 -> 0.13955166 | AA45: =S45/P45 -> 0.14791666 | AC45: MercedesBenz | AF45: {=INDIRECT($AC45&"!E26")/INDIRECT($AC45&"!E16")} -> 0.12881197 | AG45: {=INDIRECT($AC45&"!F26")/INDIRECT($AC45&"!F16")} -> 0.14763208 | AH45: {=INDIRECT($AC45&"!G26")/INDIRECT($AC45&"!G16")} -> 0.15495673 | AI45: {=INDIRECT($AC45&"!H26")/INDIRECT($AC45&"!H16")} -> 0.2332441 | AJ45: {=INDIRECT($AC45&"!I26")/INDIRECT($AC45&"!I16")} -> 0.22275997 | AK45: {=INDIRECT($AC45&"!J26")/INDIRECT($AC45&"!J16")} -> 0.15942193 | AL45: {=INDIRECT($AC45&"!K26")/INDIRECT($AC45&"!K16")} -> 0.14516044 | AM45: {=INDIRECT($AC45&"!L26")/INDIRECT($AC45&"!L16")} -> 0.14833716
B46: Nissan | F46: {=INDIRECT(B46&"!F9")} -> 1.9880741 | G46: {=INDIRECT(B46&"!R29")} -> 3495.7389 | H46: =F46*G46 -> 6949.788 | I46: {=INDIRECT(B46&"!R26")} -> 13094.437 | J46: {=INDIRECT(B46&"!R27")} -> 51122.825 | K46: =H46-I46+J46 -> 44978.175 | L46: {=INDIRECT(B46&"!R30")} -> -0.17337875 | M46: {=INDIRECT(B46&"!R31")} -> -0.088023497 | N46: {=INDIRECT($B46&"!M16")} -> 66804.76 | O46: {=INDIRECT($B46&"!N16")} -> 68423.05 | P46: {=INDIRECT($B46&"!O16")} -> 69745.555 | Q46: {=INDIRECT($B46&"!M18")} -> 1382.472 | R46: {=INDIRECT($B46&"!N18")} -> 2853.257 | S46: {=INDIRECT($B46&"!O18")} -> 3462.0366 | T46: {=INDIRECT($B46&"!M22")} -> -1686.8341 | U46: {=INDIRECT($B46&"!N22")} -> 75.53421 | V46: {=INDIRECT($B46&"!O22")} -> 773.1631 | W46: =SQRT(P46/N46)-1 -> 0.021773331 | X46: =IFERROR(SQRT(S46/Q46)-1,"N/A") -> 0.58247791 | Y46: =Q46/N46 -> 0.020694214 | Z46: =R46/O46 -> 0.041700231 | AA46: =S46/P46 -> 0.049638097 | AC46: Ford | AF46: {=INDIRECT($AC46&"!E26")/INDIRECT($AC46&"!E16")} -> 0.2332301 | AG46: {=INDIRECT($AC46&"!F26")/INDIRECT($AC46&"!F16")} -> 0.21852582 | AH46: {=INDIRECT($AC46&"!G26")/INDIRECT($AC46&"!G16")} -> 0.22162048 | AI46: {=INDIRECT($AC46&"!H26")/INDIRECT($AC46&"!H16")} -> 0.36610752 | AJ46: {=INDIRECT($AC46&"!I26")/INDIRECT($AC46&"!I16")} -> 0.37806592 | AK46: {=INDIRECT($AC46&"!J26")/INDIRECT($AC46&"!J16")} -> 0.27457137 | AL46: {=INDIRECT($AC46&"!K26")/INDIRECT($AC46&"!K16")} -> 0.22313946 | AM46: {=INDIRECT($AC46&"!L26")/INDIRECT($AC46&"!L16")} -> 0.21654231
B47: BMW | F47: {=INDIRECT(B47&"!F9")} -> 80.72 | G47: {=INDIRECT(B47&"!R29")} -> 609.81512 | H47: =F47*G47 -> 49224.277 | I47: {=INDIRECT(B47&"!R26")} -> 19257 | J47: {=INDIRECT(B47&"!R27")} -> 107748 | K47: =H47-I47+J47 -> 137715.28 | L47: {=INDIRECT(B47&"!R30")} -> 0.076269943 | M47: {=INDIRECT(B47&"!R31")} -> 0.045064564 | N47: {=INDIRECT($B47&"!M16")} -> 138715.39 | O47: {=INDIRECT($B47&"!N16")} -> 142726.48 | P47: {=INDIRECT($B47&"!O16")} -> 147509.86 | Q47: {=INDIRECT($B47&"!M18")} -> 19217.615 | R47: {=INDIRECT($B47&"!N18")} -> 20805.014 | S47: {=INDIRECT($B47&"!O18")} -> 22766.3 | T47: {=INDIRECT($B47&"!M22")} -> 6489.721 | U47: {=INDIRECT($B47&"!N22")} -> 6961.953 | V47: {=INDIRECT($B47&"!O22")} -> 7871.975 | W47: =SQRT(P47/N47)-1 -> 0.031212578 | X47: =IFERROR(SQRT(S47/Q47)-1,"N/A") -> 0.088419923 | Y47: =Q47/N47 -> 0.13853989 | Z47: =R47/O47 -> 0.14576842 | AA47: =S47/P47 -> 0.15433748 | AC47: Toyota | AF47: {=INDIRECT($AC47&"!E26")/INDIRECT($AC47&"!E16")} -> 0.19282519 | AG47: {=INDIRECT($AC47&"!F26")/INDIRECT($AC47&"!F16")} -> 0.19914121 | AH47: {=INDIRECT($AC47&"!G26")/INDIRECT($AC47&"!G16")} -> 0.1399382 | AI47: {=INDIRECT($AC47&"!H26")/INDIRECT($AC47&"!H16")} -> 0.17835929 | AJ47: {=INDIRECT($AC47&"!I26")/INDIRECT($AC47&"!I16")} -> 0.18828154 | AK47: {=INDIRECT($AC47&"!J26")/INDIRECT($AC47&"!J16")} -> 0.19719277 | AL47: {=INDIRECT($AC47&"!K26")/INDIRECT($AC47&"!K16")} -> 0.20019118 | AM47: {=INDIRECT($AC47&"!L26")/INDIRECT($AC47&"!L16")} -> 0.18945754
B48: Mercedes Benz | F48: =MercedesBenz!F9 -> 56.21 | G48: =MercedesBenz!R29 -> 962.9037 | H48: =F48*G48 -> 54124.817 | I48: =MercedesBenz!R26 -> 22496 | J48: =MercedesBenz!R27 -> 102343 | K48: =H48-I48+J48 -> 133971.82 | L48: =MercedesBenz!R30 -> 0.068815547 | M48: =MercedesBenz!R31 -> 0.039276434 | N48: =MercedesBenz!M16 -> 134542.77 | O48: =MercedesBenz!N16 -> 135827.06 | P48: =MercedesBenz!O16 -> 140007.02 | Q48: =MercedesBenz!M18 -> 14753.084 | R48: =MercedesBenz!N18 -> 16532.469 | S48: =MercedesBenz!O18 -> 18476.857 | T48: =MercedesBenz!M22 -> 5118.2974 | U48: =MercedesBenz!N22 -> 6663.537 | V48: =MercedesBenz!O22 -> 7813.5654 | W48: =SQRT(P48/N48)-1 -> 0.020104641 | X48: =IFERROR(SQRT(S48/Q48)-1,"N/A") -> 0.11910965 | Y48: =Q48/N48 -> 0.10965349 | Z48: =R48/O48 -> 0.12171705 | AA48: =S48/P48 -> 0.13197093 | AC48: GeneralMotors | AF48: {=INDIRECT($AC48&"!E26")/INDIRECT($AC48&"!E16")} -> 0.16497509 | AG48: {=INDIRECT($AC48&"!F26")/INDIRECT($AC48&"!F16")} -> 0.20277631 | AH48: {=INDIRECT($AC48&"!G26")/INDIRECT($AC48&"!G16")} -> 0.19322753 | AI48: {=INDIRECT($AC48&"!H26")/INDIRECT($AC48&"!H16")} -> 0.24051304 | AJ48: {=INDIRECT($AC48&"!I26")/INDIRECT($AC48&"!I16")} -> 0.25869883 | AK48: {=INDIRECT($AC48&"!J26")/INDIRECT($AC48&"!J16")} -> 0.21147604 | AL48: {=INDIRECT($AC48&"!K26")/INDIRECT($AC48&"!K16")} -> 0.16556296 | AM48: {=INDIRECT($AC48&"!L26")/INDIRECT($AC48&"!L16")} -> 0.16576776
B49: Toyota | F49: {=INDIRECT(B49&"!F9")} -> 17.648024 | G49: {=INDIRECT(B49&"!R29")} -> 13033.389 | H49: =F49*G49 -> 230013.57 | I49: {=INDIRECT(B49&"!R26")} -> 46752.309 | J49: {=INDIRECT(B49&"!R27")} -> 229725.74 | K49: =H49-I49+J49 -> 412987 | L49: {=INDIRECT(B49&"!R30")} -> 0.12889945 | M49: {=INDIRECT(B49&"!R31")} -> 0.079094679 | N49: {=INDIRECT(B49&"!M16")} -> 274892 | O49: {=INDIRECT($B49&"!N16")} -> 283138.38 | P49: {=INDIRECT($B49&"!O16")} -> 290642.16 | Q49: {=INDIRECT($B49&"!M18")} -> 31747.256 | R49: {=INDIRECT($B49&"!N18")} -> 35426.26 | S49: {=INDIRECT($B49&"!O18")} -> 37506.48 | T49: {=INDIRECT($B49&"!M22")} -> 18217.3 | U49: {=INDIRECT($B49&"!N22")} -> 21142.232 | V49: {=INDIRECT($B49&"!O22")} -> 22701.158 | W49: =SQRT(P49/N49)-1 -> 0.028248905 | X49: =IFERROR(SQRT(S49/Q49)-1,"N/A") -> 0.086926198 | Y49: =Q49/N49 -> 0.11548992 | Z49: =R49/O49 -> 0.12511995 | AA49: =S49/P49 -> 0.12904694 | AC49: Honda | AF49: {=INDIRECT($AC49&"!E26")/INDIRECT($AC49&"!E16")} -> 0.14546115 | AG49: {=INDIRECT($AC49&"!F26")/INDIRECT($AC49&"!F16")} -> 0.162112 | AH49: {=INDIRECT($AC49&"!G26")/INDIRECT($AC49&"!G16")} -> 0.18251826 | AI49: {=INDIRECT($AC49&"!H26")/INDIRECT($AC49&"!H16")} -> 0.19927324 | AJ49: {=INDIRECT($AC49&"!I26")/INDIRECT($AC49&"!I16")} -> 0.24403868 | AK49: {=INDIRECT($AC49&"!J26")/INDIRECT($AC49&"!J16")} -> 0.21923011 | AL49: {=INDIRECT($AC49&"!K26")/INDIRECT($AC49&"!K16")} -> 0.23262394 | AM49: {=INDIRECT($AC49&"!L26")/INDIRECT($AC49&"!L16")} -> 0.21156329
B50: Honda | F50: {=INDIRECT(B50&"!F9")} -> 8.7733965 | G50: {=INDIRECT(B50&"!R29")} -> 3892.5506 | H50: =F50*G50 -> 34150.89 | I50: {=INDIRECT(B50&"!R26")} -> 26711.673 | J50: {=INDIRECT(B50&"!R27")} -> 72636.764 | K50: =H50-I50+J50 -> 80075.981 | L50: {=INDIRECT(B50&"!R30")} -> 0.053634847 | M50: {=INDIRECT(B50&"!R31")} -> 0.033711155 | N50: {=INDIRECT(B50&"!M16")} -> 117737.17 | O50: {=INDIRECT($B50&"!N16")} -> 120500.61 | P50: {=INDIRECT($B50&"!O16")} -> 124229.95 | Q50: {=INDIRECT($B50&"!M18")} -> 7197.0063 | R50: {=INDIRECT($B50&"!N18")} -> 8883.085 | S50: {=INDIRECT($B50&"!O18")} -> 9717.526 | T50: {=INDIRECT($B50&"!M22")} -> 3089.569 | U50: {=INDIRECT($B50&"!N22")} -> 4107.7305 | V50: {=INDIRECT($B50&"!O22")} -> 4521.1167 | W50: =SQRT(P50/N50)-1 -> 0.027203168 | X50: =IFERROR(SQRT(S50/Q50)-1,"N/A") -> 0.16198873 | Y50: =Q50/N50 -> 0.061127733 | Z50: =R50/O50 -> 0.073718175 | AA50: =S50/P50 -> 0.07822209 | AC50: Average | AF50: =AVERAGE(AF41:AF49) -> 0.14928595 | AG50: =AVERAGE(AG41:AG49) -> 0.16521453 | AH50: =AVERAGE(AH41:AH49) -> 0.16570215 | AI50: =AVERAGE(AI41:AI49) -> 0.26083427 | AJ50: =AVERAGE(AJ41:AJ49) -> 0.24829666 | AK50: =AVERAGE(AK41:AK49) -> 0.20926063 | AL50: =AVERAGE(AL41:AL49) -> 0.1903282 | AM50: =AVERAGE(AM41:AM49) -> 0.18763165
B51: Ford | F51: {=INDIRECT(B51&"!F9")} -> 11.375845 | G51: {=INDIRECT(B51&"!R29")} -> 4203 | H51: =F51*G51 -> 47812.677 | I51: {=INDIRECT(B51&"!R26")} -> 35904.682 | J51: {=INDIRECT(B51&"!R27")} -> 139899.58 | K51: =H51-I51+J51 -> 151807.57 | L51: {=INDIRECT(B51&"!R30")} -> 0.10263121 | M51: {=INDIRECT(B51&"!R31")} -> 0.031048975 | N51: {=INDIRECT(B51&"!M16")} -> 157610.4 | O51: {=INDIRECT($B51&"!N16")} -> 160697.72 | P51: {=INDIRECT($B51&"!O16")} -> 166121.98 | Q51: {=INDIRECT($B51&"!M18")} -> 10222.399 | R51: {=INDIRECT($B51&"!N18")} -> 10873.805 | S51: {=INDIRECT($B51&"!O18")} -> 11867.49 | T51: {=INDIRECT($B51&"!M22")} -> 3627.7937 | U51: {=INDIRECT($B51&"!N22")} -> 5049.9395 | V51: {=INDIRECT($B51&"!O22")} -> 5677.459 | W51: =SQRT(P51/N51)-1 -> 0.026646932 | X51: =IFERROR(SQRT(S51/Q51)-1,"N/A") -> 0.077464632 | Y51: =Q51/N51 -> 0.064858658 | Z51: =R51/O51 -> 0.067666206 | AA51: =S51/P51 -> 0.071438409
B52: General Motors | F52: =GeneralMotors!F9 -> 59.85964 | G52: =GeneralMotors!R29 -> 933 | H52: =F52*G52 -> 55849.044 | I52: =GeneralMotors!R26 -> 27699.575 | J52: =GeneralMotors!R27 -> 112768.51 | K52: =H52-I52+J52 -> 140917.98 | L52: =GeneralMotors!R30 -> 0.044367084 | M52: =GeneralMotors!R31 -> 0.018743231 | N52: =GeneralMotors!M16 -> 160977.55 | O52: =GeneralMotors!N16 -> 162207.69 | P52: =GeneralMotors!O16 -> 164368.53 | Q52: =GeneralMotors!M18 -> 15075.114 | R52: =GeneralMotors!N18 -> 17256.457 | S52: =GeneralMotors!O18 -> 17556.89 | T52: =GeneralMotors!M22 -> 8722.873 | U52: =GeneralMotors!N22 -> 9215.48 | V52: =GeneralMotors!O22 -> 9843.179 | W52: =SQRT(P52/N52)-1 -> 0.010477573 | X52: =IFERROR(SQRT(S52/Q52)-1,"N/A") -> 0.079179015 | Y52: =Q52/N52 -> 0.093647307 | Z52: =R52/O52 -> 0.10638495 | AA52: =S52/P52 -> 0.10681418 | AC52: Total Average (excl. covid) | AF52: =(AF50+AG50+AH50+AL50+AM50)/5 -> 0.1716325
B54: Renault | F54: 33.79 | G54: 273.46 | H54: =G54*F54 -> 9240.2134 | I54: 19302 | J54: =64053+6025 -> 70078 | K54: =H54+J54-I54 -> 60016.213 | N54: ='Main Financials'!O8 -> 57595.111 | O54: ='Main Financials'!P8 -> 60205.87 | P54: ='Main Financials'!Q8 -> 62404 | Q54: ='Main Financials'!O12 -> 6856.9353 | R54: ='Main Financials'!P12 -> 7221.7443 | S54: ='Main Financials'!Q12 -> 7444.0856 | T54: -9811 | U54: 2031 | V54: 2052 | W54: =SQRT(P54/N54)-1 -> 0.040910536 | X54: =IFERROR(SQRT(S54/Q54)-1,"N/A") -> 0.041935059 | Y54: =Q54/N54 -> 0.11905412 | Z54: =R54/O54 -> 0.11995083 | AA54: =S54/P54 -> 0.1192886
AC55: Market Value of equity to Book value of equity ratio
D56: Quartile | AC56: Market to Book | AF56: 2017 | AG56: =+AF56+1 -> 2018 | AH56: =+AG56+1 -> 2019 | AI56: =+AH56+1 -> 2020 | AJ56: =+AI56+1 -> 2021 | AK56: =+AJ56+1 -> 2022 | AL56: =+AK56+1 -> 2023 | AM56: =+AL56+1 -> 2024
C57: Maximum | D57: 4 | F57: =_xlfn.QUARTILE.INC(F$44:F$52,$D57) -> 91.35 | G57: =_xlfn.QUARTILE.INC(G$44:G$52,$D57) -> 13033.389 | H57: =_xlfn.QUARTILE.INC(H$44:H$52,$D57) -> 230013.57 | I57: =_xlfn.QUARTILE.INC(I$44:I$52,$D57) -> 65550 | J57: =_xlfn.QUARTILE.INC(J$44:J$52,$D57) -> 271470 | K57: =_xlfn.QUARTILE.INC(K$44:K$52,$D57) -> 412987 | L57: =_xlfn.QUARTILE.INC(L$44:L$52,$D57) -> 0.12889945 | M57: =_xlfn.QUARTILE.INC(M$44:M$52,$D57) -> 0.079094679 | ... AA57: =_xlfn.QUARTILE.INC(AA$44:AA$52,$D57) -> 0.15433748 | AC57: Stellantis | AF57: 1.1029703 | AG57: 0.79608663 | AH57: 0.72473806 | AI57: 1.0837878 | AJ57: 0.93456104 | AK57: 0.57924811 | AL57: 0.78266861 | AM57: 0.4533506
C58: 75th Percentile | D58: =D57-1 -> 3 | F58: =_xlfn.QUARTILE.INC(F$44:F$52,$D58) -> 59.85964 | G58: =_xlfn.QUARTILE.INC(G$44:G$52,$D58) -> 3892.5506 | H58: =_xlfn.QUARTILE.INC(H$44:H$52,$D58) -> 54124.817 | I58: =_xlfn.QUARTILE.INC(I$44:I$52,$D58) -> 35904.682 | J58: =_xlfn.QUARTILE.INC(J$44:J$52,$D58) -> 139899.58 | K58: =_xlfn.QUARTILE.INC(K$44:K$52,$D58) -> 151807.57 | L58: =_xlfn.QUARTILE.INC(L$44:L$52,$D58) -> 0.076269943 | M58: =_xlfn.QUARTILE.INC(M$44:M$52,$D58) -> 0.039276434 | ... AA58: =_xlfn.QUARTILE.INC(AA$44:AA$52,$D58) -> 0.13197093 | AC58: Volkswagen | AF58: 0.86505365 | AG58: 0.66714029 | AH58: 0.79592194 | AI58: 0.76588282 | AJ58: 0.99634409 | AK58: 0.48934739 | AL58: 0.37154937 | AM58: 0.27430679
C59: Median | D59: =D58-1 -> 2 | F59: =_xlfn.QUARTILE.INC(F$44:F$52,$D59) -> 17.648024 | G59: =_xlfn.QUARTILE.INC(G$44:G$52,$D59) -> 2888.724 | H59: =_xlfn.QUARTILE.INC(H$44:H$52,$D59) -> 47812.677 | I59: =_xlfn.QUARTILE.INC(I$44:I$52,$D59) -> 27699.575 | J59: =_xlfn.QUARTILE.INC(J$44:J$52,$D59) -> 107748 | K59: =_xlfn.QUARTILE.INC(K$44:K$52,$D59) -> 137715.28 | L59: =_xlfn.QUARTILE.INC(L$44:L$52,$D59) -> 0.053634847 | M59: =_xlfn.QUARTILE.INC(M$44:M$52,$D59) -> 0.031048975 | ... AA59: =_xlfn.QUARTILE.INC(AA$44:AA$52,$D59) -> 0.10681418 | AC59: Nissan | AF59: 0.79977705 | AG59: 0.67017111 | AH59: 0.34323064 | AI59: 0.61113332 | AJ59: 0.46813573 | AK59: 0.38228178 | AL59: 0.38033835 | AM59: 0.26671614
C60: 25th Percentile | D60: =D59-1 -> 1 | F60: =_xlfn.QUARTILE.INC(F$44:F$52,$D60) -> 8.778 | G60: =_xlfn.QUARTILE.INC(G$44:G$52,$D60) -> 933 | H60: =_xlfn.QUARTILE.INC(H$44:H$52,$D60) -> 34150.89 | I60: =_xlfn.QUARTILE.INC(I$44:I$52,$D60) -> 22496 | J60: =_xlfn.QUARTILE.INC(J$44:J$52,$D60) -> 72636.764 | K60: =_xlfn.QUARTILE.INC(K$44:K$52,$D60) -> 80075.981 | L60: =_xlfn.QUARTILE.INC(L$44:L$52,$D60) -> 0.040037059 | M60: =_xlfn.QUARTILE.INC(M$44:M$52,$D60) -> 0.018743231 | ... AA60: =_xlfn.QUARTILE.INC(AA$44:AA$52,$D60) -> 0.07822209 | AC60: BMW | AF60: 1.0638792 | AG60: 0.80773398 | AH60: 0.81139247 | AI60: 0.78155458 | AJ60: 0.78569797 | AK60: 0.61844104 | AL60: 0.71285697 | AM60: 0.53247479
C61: Minimum | D61: =D60-1 -> 0 | F61: =_xlfn.QUARTILE.INC(F$44:F$52,$D61) -> 1.9880741 | G61: =_xlfn.QUARTILE.INC(G$44:G$52,$D61) -> 501.29526 | H61: =_xlfn.QUARTILE.INC(H$44:H$52,$D61) -> 6949.788 | I61: =_xlfn.QUARTILE.INC(I$44:I$52,$D61) -> 13094.437 | J61: =_xlfn.QUARTILE.INC(J$44:J$52,$D61) -> 40799 | K61: =_xlfn.QUARTILE.INC(K$44:K$52,$D61) -> 33320.219 | L61: =_xlfn.QUARTILE.INC(L$44:L$52,$D61) -> -0.17337875 | M61: =_xlfn.QUARTILE.INC(M$44:M$52,$D61) -> -0.088023497 | ... AA61: =_xlfn.QUARTILE.INC(AA$44:AA$52,$D61) -> 0.049638097 | AC61: MercedesBenz | AF61: 1.1859351 | AG61: 0.75949897 | AH61: 0.86098114 | AI61: 1.0186642 | AJ61: 1.0049587 | AK61: 0.76904544 | AL61: 0.7094749 | AM61: 0.60461472
AC62: Ford | AF62: 1.4245999 | AG62: 0.86672465 | AH62: 1.140886 | AI62: 1.1731456 | AJ62: 1.7141372 | AK62: 1.0720868 | AL62: 1.1324545 | AM62: 0.87528934
B63: Valuation Statistics | I63: Enterprise Value / Revenue | L63: Enterprise Value / EBITDA | O63: P/E Ratio | R63: Price / Sales | W63: Renault | AC63: Toyota | AF63: 1.032883 | AG63: 0.92582004 | AH63: 0.87214972 | AI63: 1.0292826 | AJ63: 1.1667421 | AK63: 0.89991897 | AL63: 1.4930619 | AM63: 0.95020651
F64: Equity Value € | W64: Key Financials | AC64: GeneralMotors | AF64: 1.6395533 | AG64: 1.2050953 | AH64: 1.2260719 | AI64: 1.2946037 | AJ64: 1.4720308 | AK64: 0.69471324 | AL64: 0.67050366 | AM64: 0.84459032
B65: Company Name | F65: Millions | G65: Enterprise Value | I65: 2025 | J65: 2026 | K65: 2027 | L65: 2025 | M65: 2026 | N65: 2027 | O65: 2025 | P65: 2026 | Q65: 2027 | R65: 2025 | S65: 2026 | T65: 2027 | U65: Weight | W65: Share Count | X65: Cash | Y65: Debt | AC65: Honda | AF65: 0.82037761 | AG65: 0.63740504 | AH65: 0.52365528 | AI65: 0.63098167 | AJ65: 0.56955635 | AK65: 0.52232694 | AL65: 0.71918307 | AM65: 0.47338462
B66: Stellantis | F66: =H44 -> 25357.219 | H66: =K44 -> 33320.219 | I66: =IF($H66/N44<0,"NM",$H66/N44) -> 0.21841778 | J66: =IF($H66/O44<0,"NM",$H66/O44) -> 0.20762691 | K66: =IF($H66/P44<0,"NM",$H66/P44) -> 0.20023969 | L66: =IF($H66/Q44<0,"NM",$H66/Q44) -> 3.7247938 | M66: =IF($H66/R44<0,"NM",$H66/R44) -> 2.4393245 | N66: =IF($H66/S44<0,"NM",$H66/S44) -> 2.0743929 | O66: =IF($F66/T44<0,"MN",$F66/T44) -> 12.155415 | P66: =IF($F66/U44<0,"MN",$F66/U44) -> 5.1972069 | Q66: =IF($F66/V44<0,"MN",$F66/V44) -> 3.9179684 | R66: =IF($F66/N44<0,"MN",$F66/N44) -> 0.16621942 | S66: =IF($F66/O44<0,"MN",$F66/O44) -> 0.15800739 | T66: =IF($F66/P44<0,"MN",$F66/P44) -> 0.15238561 | U66: =F66/SUM(F$66:F$74) -> 0.046164839 | W66: =G54 -> 273.46 | X66: =I54 -> 19302 | Y66: =J54 -> 70078 | AC66: Average | AF66: =AVERAGE(AF57:AF65) -> 1.1038921 | AG66: =AVERAGE(AG57:AG65) -> 0.81507511 | AH66: =AVERAGE(AH57:AH65) -> 0.81100302 | AI66: =AVERAGE(AI57:AI65) -> 0.93211514 | AJ66: =AVERAGE(AJ57:AJ65) -> 1.0124627 | AK66: =AVERAGE(AK57:AK65) -> 0.66971219 | AL66: =AVERAGE(AL57:AL65) -> 0.77467682 | AM66: =AVERAGE(AM57:AM65) -> 0.58610376
B67: Volkswagen | F67: =H45 -> 45793.322 | H67: =K45 -> 251713.32 | I67: =IF($H67/N45<0,"NM",$H67/N45) -> 0.77492256 | J67: =IF($H67/O45<0,"NM",$H67/O45) -> 0.75869218 | K67: =IF($H67/P45<0,"NM",$H67/P45) -> 0.73866947 | L67: =IF($H67/Q45<0,"NM",$H67/Q45) -> 6.5256173 | M67: =IF($H67/R45<0,"NM",$H67/R45) -> 5.4366402 | N67: =IF($H67/S45<0,"NM",$H67/S45) -> 4.993822 | O67: =IF($F67/T45<0,"MN",$F67/T45) -> 9.3123423 | P67: =IF($F67/U45<0,"MN",$F67/U45) -> 4.2053342 | Q67: =IF($F67/V45<0,"MN",$F67/V45) -> 3.4649491 | R67: =IF($F67/N45<0,"MN",$F67/N45) -> 0.14097895 | S67: =IF($F67/O45<0,"MN",$F67/O45) -> 0.13802621 | T67: =IF($F67/P45<0,"MN",$F67/P45) -> 0.13438355 | U67: =F67/SUM(F$66:F$74) -> 0.083370392
B68: Nissan | F68: =H46 -> 6949.788 | H68: =K46 -> 44978.175 | I68: =IF($H68/N46<0,"NM",$H68/N46) -> 0.673278 | J68: =IF($H68/O46<0,"NM",$H68/O46) -> 0.65735414 | K68: =IF($H68/P46<0,"NM",$H68/P46) -> 0.64488949 | L68: =IF($H68/Q46<0,"NM",$H68/Q46) -> 32.534601 | M68: =IF($H68/R46<0,"NM",$H68/R46) -> 15.763801 | N68: =IF($H68/S46<0,"NM",$H68/S46) -> 12.991825 | O68: =IF($F68/T46<0,"MN",$F68/T46) -> MN | P68: =IF($F68/U46<0,"MN",$F68/U46) -> 92.008482 | Q68: =IF($F68/V46<0,"MN",$F68/V46) -> 8.9887735 | R68: =IF($F68/N46<0,"MN",$F68/N46) -> 0.10403133 | S68: =IF($F68/O46<0,"MN",$F68/O46) -> 0.10157086 | T68: =IF($F68/P46<0,"MN",$F68/P46) -> 0.099644888 | U68: =F68/SUM(F$66:F$74) -> 0.012652643 | AC68: Total Average | AF68: =AVERAGE(AF66:AM66) -> 0.8381301
B69: BMW | F69: =H47 -> 49224.277 | H69: =K47 -> 137715.28 | I69: =IF($H69/N47<0,"NM",$H69/N47) -> 0.99279018 | J69: =IF($H69/O47<0,"NM",$H69/O47) -> 0.96488946 | K69: =IF($H69/P47<0,"NM",$H69/P47) -> 0.93360049 | L69: =IF($H69/Q47<0,"NM",$H69/Q47) -> 7.1660961 | M69: =IF($H69/R47<0,"NM",$H69/R47) -> 6.6193311 | N69: =IF($H69/S47<0,"NM",$H69/S47) -> 6.0490847 | O69: =IF($F69/T47<0,"MN",$F69/T47) -> 7.5849604 | P69: =IF($F69/U47<0,"MN",$F69/U47) -> 7.0704696 | Q69: =IF($F69/V47<0,"MN",$F69/V47) -> 6.2531038 | R69: =IF($F69/N47<0,"MN",$F69/N47) -> 0.35485808 | S69: =IF($F69/O47<0,"MN",$F69/O47) -> 0.34488538 | T69: =IF($F69/P47<0,"MN",$F69/P47) -> 0.3337016 | U69: =F69/SUM(F$66:F$74) -> 0.089616719
B70: Mercedes Benz | F70: =H48 -> 54124.817 | H70: =K48 -> 133971.82 | I70: =IF($H70/N48<0,"NM",$H70/N48) -> 0.99575635 | J70: =IF($H70/O48<0,"NM",$H70/O48) -> 0.98634114 | K70: =IF($H70/P48<0,"NM",$H70/P48) -> 0.95689357 | L70: =IF($H70/Q48<0,"NM",$H70/Q48) -> 9.0809364 | M70: =IF($H70/R48<0,"NM",$H70/R48) -> 8.1035577 | N70: =IF($H70/S48<0,"NM",$H70/S48) -> 7.2507904 | O70: =IF($F70/T48<0,"MN",$F70/T48) -> 10.57477 | P70: =IF($F70/U48<0,"MN",$F70/U48) -> 8.1225357 | Q70: =IF($F70/V48<0,"MN",$F70/V48) -> 6.9270319 | R70: =IF($F70/N48<0,"MN",$F70/N48) -> 0.40228707 | S70: =IF($F70/O48<0,"MN",$F70/O48) -> 0.39848332 | T70: =IF($F70/P48<0,"MN",$F70/P48) -> 0.38658645 | U70: =F70/SUM(F$66:F$74) -> 0.098538543 | AC70: All values of market and book equity taken from FactSet for each given year.
B71: Toyota | F71: =H49 -> 230013.57 | H71: =K49 -> 412987 | I71: =IF($H71/N49<0,"NM",$H71/N49) -> 1.5023609 | J71: =IF($H71/O49<0,"NM",$H71/O49) -> 1.4586048 | K71: =IF($H71/P49<0,"NM",$H71/P49) -> 1.4209466 | L71: =IF($H71/Q49<0,"NM",$H71/Q49) -> 13.008589 | M71: =IF($H71/R49<0,"NM",$H71/R49) -> 11.657652 | N71: =IF($H71/S49<0,"NM",$H71/S49) -> 11.011084 | O71: =IF($F71/T49<0,"MN",$F71/T49) -> 12.626106 | P71: =IF($F71/U49<0,"MN",$F71/U49) -> 10.879342 | Q71: =IF($F71/V49<0,"MN",$F71/V49) -> 10.132239 | R71: =IF($F71/N49<0,"MN",$F71/N49) -> 0.83674158 | S71: =IF($F71/O49<0,"MN",$F71/O49) -> 0.81237155 | T71: =IF($F71/P49<0,"MN",$F71/P49) -> 0.7913978 | U71: =F71/SUM(F$66:F$74) -> 0.41875803
B72: Honda | F72: =H50 -> 34150.89 | H72: =K50 -> 80075.981 | I72: =IF($H72/N50<0,"NM",$H72/N50) -> 0.6801249 | J72: =IF($H72/O50<0,"NM",$H72/O50) -> 0.6645276 | K72: =IF($H72/P50<0,"NM",$H72/P50) -> 0.64457874 | L72: =IF($H72/Q50<0,"NM",$H72/Q50) -> 11.12629 | M72: =IF($H72/R50<0,"NM",$H72/R50) -> 9.0144337 | N72: =IF($H72/S50<0,"NM",$H72/S50) -> 8.2403671 | O72: =IF($F72/T50<0,"MN",$F72/T50) -> 11.05361 | P72: =IF($F72/U50<0,"MN",$F72/U50) -> 8.3138098 | Q72: =IF($F72/V50<0,"MN",$F72/V50) -> 7.5536404 | R72: =IF($F72/N50<0,"MN",$F72/N50) -> 0.29006039 | S72: =IF($F72/O50<0,"MN",$F72/O50) -> 0.28340844 | T72: =IF($F72/P50<0,"MN",$F72/P50) -> 0.27490063 | U72: =F72/SUM(F$66:F$74) -> 0.062174417
B73: Ford | F73: =H51 -> 47812.677 | H73: =K51 -> 151807.57 | I73: =IF($H73/N51<0,"NM",$H73/N51) -> 0.96318246 | J73: =IF($H73/O51<0,"NM",$H73/O51) -> 0.94467782 | K73: =IF($H73/P51<0,"NM",$H73/P51) -> 0.91383195 | L73: =IF($H73/Q51<0,"NM",$H73/Q51) -> 14.850484 | M73: =IF($H73/R51<0,"NM",$H73/R51) -> 13.960851 | N73: =IF($H73/S51<0,"NM",$H73/S51) -> 12.791885 | O73: =IF($F73/T51<0,"MN",$F73/T51) -> 13.179547 | P73: =IF($F73/U51<0,"MN",$F73/U51) -> 9.4679702 | Q73: =IF($F73/V51<0,"MN",$F73/V51) -> 8.4214922 | R73: =IF($F73/N51<0,"MN",$F73/N51) -> 0.30335991 | S73: =IF($F73/O51<0,"MN",$F73/O51) -> 0.29753177 | T73: =IF($F73/P51<0,"MN",$F73/P51) -> 0.28781668 | U73: =F73/SUM(F$66:F$74) -> 0.087046788
B74: General Motors | F74: =H52 -> 55849.044 | H74: =K52 -> 140917.98 | I74: =IF($H74/N52<0,"NM",$H74/N52) -> 0.87538903 | J74: =IF($H74/O52<0,"NM",$H74/O52) -> 0.86875032 | K74: =IF($H74/P52<0,"NM",$H74/P52) -> 0.85732945 | L74: =IF($H74/Q52<0,"NM",$H74/Q52) -> 9.3477225 | M74: =IF($H74/R52<0,"NM",$H74/R52) -> 8.1661017 | N74: =IF($H74/S52<0,"NM",$H74/S52) -> 8.0263636 | O74: =IF($F74/T52<0,"MN",$F74/T52) -> 6.4025974 | P74: =IF($F74/U52<0,"MN",$F74/U52) -> 6.0603511 | Q74: =IF($F74/V52<0,"MN",$F74/V52) -> 5.6738828 | R74: =IF($F74/N52<0,"MN",$F74/N52) -> 0.34693685 | S74: =IF($F74/O52<0,"MN",$F74/O52) -> 0.34430577 | T74: =IF($F74/P52<0,"MN",$F74/P52) -> 0.33977942 | U74: =F74/SUM(F$66:F$74) -> 0.10167764
B76: Renault | F76: =H54 -> 9240.2134 | H76: =K54 -> 60016.213 | I76: =$H76/N54 -> 1.0420366 | J76: =$H76/O54 -> 0.99684987 | K76: =$H76/P54 -> 0.96173663 | L76: =$H76/Q54 -> 8.7526294 | M76: =$H76/R54 -> 8.3104872 | N76: =$H76/S54 -> 8.0622681 | O76: =$F76/T54 -> -0.94182177 | P76: =$F76/U54 -> 4.5495881 | Q76: =$F76/V54 -> 4.503028 | R76: =$F76/N54 -> 0.16043399 | S76: =$F76/O54 -> 0.15347695 | T76: =$F76/P54 -> 0.14807085
D78: Quartile
C79: Maximum | D79: 4 | F79: =_xlfn.QUARTILE.INC(F$66:F$74,$D79) -> 230013.57 | H79: =_xlfn.QUARTILE.INC(H$66:H$74,$D79) -> 412987 | I79: =_xlfn.QUARTILE.INC(I$66:I$74,$D79) -> 1.5023609 | J79: =_xlfn.QUARTILE.INC(J$66:J$74,$D79) -> 1.4586048 | K79: =_xlfn.QUARTILE.INC(K$66:K$74,$D79) -> 1.4209466 | L79: =_xlfn.QUARTILE.INC(L$66:L$74,$D79) -> 32.534601 | M79: =_xlfn.QUARTILE.INC(M$66:M$74,$D79) -> 15.763801 | N79: =_xlfn.QUARTILE.INC(N$66:N$74,$D79) -> 12.991825 | O79: =_xlfn.QUARTILE.INC(O$66:O$74,$D79) -> 13.179547 | ... T79: =_xlfn.QUARTILE.INC(T$66:T$74,$D79) -> 0.7913978
C80: 75th Percentile | D80: =D79-1 -> 3 | F80: =_xlfn.QUARTILE.INC(F$66:F$74,$D80) -> 54124.817 | H80: =_xlfn.QUARTILE.INC(H$66:H$74,$D80) -> 151807.57 | I80: =_xlfn.QUARTILE.INC(I$66:I$74,$D80) -> 0.99279018 | J80: =_xlfn.QUARTILE.INC(J$66:J$74,$D80) -> 0.96488946 | K80: =_xlfn.QUARTILE.INC(K$66:K$74,$D80) -> 0.93360049 | L80: =_xlfn.QUARTILE.INC(L$66:L$74,$D80) -> 13.008589 | M80: =_xlfn.QUARTILE.INC(M$66:M$74,$D80) -> 11.657652 | N80: =_xlfn.QUARTILE.INC(N$66:N$74,$D80) -> 11.011084 | O80: =_xlfn.QUARTILE.INC(O$66:O$74,$D80) -> 12.273088 | ... T80: =_xlfn.QUARTILE.INC(T$66:T$74,$D80) -> 0.33977942
C81: Median | D81: =D80-1 -> 2 | F81: =_xlfn.QUARTILE.INC(F$66:F$74,$D81) -> 47812.677 | H81: =_xlfn.QUARTILE.INC(H$66:H$74,$D81) -> 137715.28 | I81: =_xlfn.QUARTILE.INC(I$66:I$74,$D81) -> 0.87538903 | J81: =_xlfn.QUARTILE.INC(J$66:J$74,$D81) -> 0.86875032 | K81: =_xlfn.QUARTILE.INC(K$66:K$74,$D81) -> 0.85732945 | L81: =_xlfn.QUARTILE.INC(L$66:L$74,$D81) -> 9.3477225 | M81: =_xlfn.QUARTILE.INC(M$66:M$74,$D81) -> 8.1661017 | N81: =_xlfn.QUARTILE.INC(N$66:N$74,$D81) -> 8.0263636 | O81: =_xlfn.QUARTILE.INC(O$66:O$74,$D81) -> 10.81419 | ... T81: =_xlfn.QUARTILE.INC(T$66:T$74,$D81) -> 0.28781668
C82: 25th Percentile | D82: =D81-1 -> 1 | F82: =_xlfn.QUARTILE.INC(F$66:F$74,$D82) -> 34150.89 | H82: =_xlfn.QUARTILE.INC(H$66:H$74,$D82) -> 80075.981 | I82: =_xlfn.QUARTILE.INC(I$66:I$74,$D82) -> 0.6801249 | J82: =_xlfn.QUARTILE.INC(J$66:J$74,$D82) -> 0.6645276 | K82: =_xlfn.QUARTILE.INC(K$66:K$74,$D82) -> 0.64488949 | L82: =_xlfn.QUARTILE.INC(L$66:L$74,$D82) -> 7.1660961 | M82: =_xlfn.QUARTILE.INC(M$66:M$74,$D82) -> 6.6193311 | N82: =_xlfn.QUARTILE.INC(N$66:N$74,$D82) -> 6.0490847 | O82: =_xlfn.QUARTILE.INC(O$66:O$74,$D82) -> 8.8804968 | ... T82: =_xlfn.QUARTILE.INC(T$66:T$74,$D82) -> 0.15238561
C83: Minimum | D83: =D82-1 -> 0 | F83: =_xlfn.QUARTILE.INC(F$66:F$74,$D83) -> 6949.788 | H83: =_xlfn.QUARTILE.INC(H$66:H$74,$D83) -> 33320.219 | I83: =_xlfn.QUARTILE.INC(I$66:I$74,$D83) -> 0.21841778 | J83: =_xlfn.QUARTILE.INC(J$66:J$74,$D83) -> 0.20762691 | K83: =_xlfn.QUARTILE.INC(K$66:K$74,$D83) -> 0.20023969 | L83: =_xlfn.QUARTILE.INC(L$66:L$74,$D83) -> 3.7247938 | M83: =_xlfn.QUARTILE.INC(M$66:M$74,$D83) -> 2.4393245 | N83: =_xlfn.QUARTILE.INC(N$66:N$74,$D83) -> 2.0743929 | O83: =_xlfn.QUARTILE.INC(O$66:O$74,$D83) -> 6.4025974 | ... T83: =_xlfn.QUARTILE.INC(T$66:T$74,$D83) -> 0.099644888
B87: Valuation Summary - Renault | E87: Implied EV or Equity Value at a Range of Multiples | N87: Valuation Summary - Renault | S87: Implied Per Share Multiples Value Range
F88: Applicable | I88: 25th | K88: 75th | R88: 25th | T88: 75th
B89: Comparables | F89: Company Figure | H89: Minimum | I89: Percentile | J89: Median | K89: Percentile | L89: Maximum | N89: Comparables | Q89: Minimum | R89: Percentile | S89: Median | T89: Percentile | U89: Maximum
B90: 2027E Enterprise Value / Revenue | F90: =P54 -> 62404 | H90: =IF($F90<0,$F90*$K$79,$F90*$K$83) -> 12495.758 | I90: =IF($F90<0,$F90*$K$80,$F90*$K$82) -> 40243.684 | J90: =$F90*$K$81 -> 53500.788 | K90: =IF($F90>0,$F90*$K$80,$F90*$K$82) -> 58260.405 | L90: =IF($F90>0,$F90*$K$79,$F90*$K$83) -> 88672.754 | N90: 2027E Enterprise Value / Revenue | Q90: =IF(((H90+$X$66-$Y$66)/$W$66) < 0, "", (H90+$X$66-$Y$66)/$W$66) | R90: =IF(((I90+$X$66-$Y$66)/$W$66) < 0, "", (I90+$X$66-$Y$66)/$W$66) | S90: =IF(((J90+$X$66-$Y$66)/$W$66) < 0, "", (J90+$X$66-$Y$66)/$W$66) -> 9.9641178 | T90: =IF(((K90+$X$66-$Y$66)/$W$66) < 0, "", (K90+$X$66-$Y$66)/$W$66) -> 27.369287 | U90: =IF(((L90+$X$66-$Y$66)/$W$66) < 0, "", (L90+$X$66-$Y$66)/$W$66) -> 138.58244
B91: 2026E Enterprise Value / Revenue | F91: =O54 -> 60205.87 | H91: =IF($F91<0,$F91*$J$79,$F91*$J$83) -> 12500.359 | I91: =IF($F91<0,$F91*$J$80,$F91*$J$82) -> 40008.462 | J91: =$F91*$J$81 -> 52303.868 | K91: =IF($F91>0,$F91*$J$80,$F91*$J$82) -> 58092.009 | L91: =IF($F91>0,$F91*$J$79,$F91*$J$83) -> 87816.57 | N91: 2026E Enterprise Value / Revenue | Q91: =IF(((H91+$X$66-$Y$66)/$W$66) < 0, "", (H91+$X$66-$Y$66)/$W$66) | R91: =IF(((I91+$X$66-$Y$66)/$W$66) < 0, "", (I91+$X$66-$Y$66)/$W$66) | S91: =IF(((J91+$X$66-$Y$66)/$W$66) < 0, "", (J91+$X$66-$Y$66)/$W$66) -> 5.5871732 | T91: =IF(((K91+$X$66-$Y$66)/$W$66) < 0, "", (K91+$X$66-$Y$66)/$W$66) -> 26.75349 | U91: =IF(((L91+$X$66-$Y$66)/$W$66) < 0, "", (L91+$X$66-$Y$66)/$W$66) -> 135.45151
B92: 2025E Enterprise Value / Revenue | F92: =N54 -> 57595.111 | H92: =IF($F92<0,$F92*$I$79,$F92*$I$83) -> 12579.796 | I92: =IF($F92<0,$F92*$I$80,$F92*$I$82) -> 39171.869 | J92: =$F92*$I$81 -> 50418.129 | K92: =IF($F92>0,$F92*$I$80,$F92*$I$82) -> 57179.861 | L92: =IF($F92>0,$F92*$I$79,$F92*$I$83) -> 86528.644 | N92: 2025E Enterprise Value / Revenue | Q92: =IF(((H92+$X$66-$Y$66)/$W$66) < 0, "", (H92+$X$66-$Y$66)/$W$66) | R92: =IF(((I92+$X$66-$Y$66)/$W$66) < 0, "", (I92+$X$66-$Y$66)/$W$66) | S92: =IF(((J92+$X$66-$Y$66)/$W$66) < 0, "", (J92+$X$66-$Y$66)/$W$66) | T92: =IF(((K92+$X$66-$Y$66)/$W$66) < 0, "", (K92+$X$66-$Y$66)/$W$66) -> 23.417907 | U92: =IF(((L92+$X$66-$Y$66)/$W$66) < 0, "", (L92+$X$66-$Y$66)/$W$66) -> 130.74177
Q93: =IF(((H93+$X$66-$Y$66)/$W$66) < 0, "", (H93+$X$66-$Y$66)/$W$66) | R93: =IF(((I93+$X$66-$Y$66)/$W$66) < 0, "", (I93+$X$66-$Y$66)/$W$66) | S93: =IF(((J93+$X$66-$Y$66)/$W$66) < 0, "", (J93+$X$66-$Y$66)/$W$66) | T93: =IF(((K93+$X$66-$Y$66)/$W$66) < 0, "", (K93+$X$66-$Y$66)/$W$66) | U93: =IF(((L93+$X$66-$Y$66)/$W$66) < 0, "", (L93+$X$66-$Y$66)/$W$66)
B94: 2027E Enterprise Value / EBITDA | F94: =S54 -> 7444.0856 | H94: =IF($F94<0,$F94*$N$79,$F94*$N$83) -> 15441.958 | I94: =IF($F94<0,$F94*$N$80,$F94*$N$82) -> 45029.904 | J94: =$F94*$N$81 -> 59748.937 | K94: =IF($F94>0,$F94*$N$80,$F94*$N$82) -> 81967.45 | L94: =IF($F94>0,$F94*$N$79,$F94*$N$83) -> 96712.26 | N94: 2027E Enterprise Value / EBITDA | Q94: =IF(((H94+$X$66-$Y$66)/$W$66) < 0, "", (H94+$X$66-$Y$66)/$W$66) | R94: =IF(((I94+$X$66-$Y$66)/$W$66) < 0, "", (I94+$X$66-$Y$66)/$W$66) | S94: =IF(((J94+$X$66-$Y$66)/$W$66) < 0, "", (J94+$X$66-$Y$66)/$W$66) -> 32.812612 | T94: =IF(((K94+$X$66-$Y$66)/$W$66) < 0, "", (K94+$X$66-$Y$66)/$W$66) -> 114.0622 | U94: =IF(((L94+$X$66-$Y$66)/$W$66) < 0, "", (L94+$X$66-$Y$66)/$W$66) -> 167.98164
B95: 2026E Enterprise Value / EBITDA | F95: =R54 -> 7221.7443 | H95: =IF($F95<0,$F95*$M$79,$F95*$M$83) -> 17616.178 | I95: =IF($F95<0,$F95*$M$80,$F95*$M$82) -> 47803.117 | J95: =$F95*$M$81 -> 58973.498 | K95: =IF($F95>0,$F95*$M$80,$F95*$M$82) -> 84188.579 | L95: =IF($F95>0,$F95*$M$79,$F95*$M$83) -> 113842.14 | N95: 2026E Enterprise Value / EBITDA | Q95: =IF(((H95+$X$66-$Y$66)/$W$66) < 0, "", (H95+$X$66-$Y$66)/$W$66) | R95: =IF(((I95+$X$66-$Y$66)/$W$66) < 0, "", (I95+$X$66-$Y$66)/$W$66) | S95: =IF(((J95+$X$66-$Y$66)/$W$66) < 0, "", (J95+$X$66-$Y$66)/$W$66) -> 29.976955 | T95: =IF(((K95+$X$66-$Y$66)/$W$66) < 0, "", (K95+$X$66-$Y$66)/$W$66) -> 122.18452 | U95: =IF(((L95+$X$66-$Y$66)/$W$66) < 0, "", (L95+$X$66-$Y$66)/$W$66) -> 230.6229
B96: 2025E Enterprise Value / EBITDA | F96: =Q54 -> 6856.9353 | H96: =IF($F96<0,$F96*$L$79,$F96*$L$83) -> 25540.67 | I96: =IF($F96<0,$F96*$L$80,$F96*$L$82) -> 49137.458 | J96: =$F96*$L$81 -> 64096.728 | K96: =IF($F96>0,$F96*$L$80,$F96*$L$82) -> 89199.051 | L96: =IF($F96>0,$F96*$L$79,$F96*$L$83) -> 223087.66 | N96: 2025E Enterprise Value / EBITDA | Q96: =IF(((H96+$X$66-$Y$66)/$W$66) < 0, "", (H96+$X$66-$Y$66)/$W$66) | R96: =IF(((I96+$X$66-$Y$66)/$W$66) < 0, "", (I96+$X$66-$Y$66)/$W$66) | S96: =IF(((J96+$X$66-$Y$66)/$W$66) < 0, "", (J96+$X$66-$Y$66)/$W$66) -> 48.711798 | T96: =IF(((K96+$X$66-$Y$66)/$W$66) < 0, "", (K96+$X$66-$Y$66)/$W$66) -> 140.50703 | U96: =IF(((L96+$X$66-$Y$66)/$W$66) < 0, "", (L96+$X$66-$Y$66)/$W$66) -> 630.11649
B98: 2027E P/E Ratio | F98: =V54 -> 2052 | H98: =IF($F98<0,$F98*$Q$79,$F98*$Q$83) -> 7110.0756 | I98: =IF($F98<0,$F98*$Q$80,$F98*$Q$82) -> 11642.808 | J98: =$F98*$Q$81 -> 14214.27 | K98: =IF($F98>0,$F98*$Q$80,$F98*$Q$82) -> 17280.902 | L98: =IF($F98>0,$F98*$Q$79,$F98*$Q$83) -> 20791.355 | N98: 2027E P/E Ratio | Q98: =H98/$W$66 -> 26.000423 | R98: =I98/$W$66 -> 42.575907 | S98: =J98/$W$66 -> 51.979337 | T98: =K98/$W$66 -> 63.193527 | U98: =L98/$W$66 -> 76.0307
B99: 2026E P/E Ratio | F99: =U54 -> 2031 | H99: =IF($F99<0,$F99*$P$79,$F99*$P$83) -> 8541.0338 | I99: =IF($F99<0,$F99*$P$80,$F99*$P$82) -> 12308.573 | J99: =$F99*$P$81 -> 16496.87 | K99: =IF($F99>0,$F99*$P$80,$F99*$P$82) -> 19229.447 | L99: =IF($F99>0,$F99*$P$79,$F99*$P$83) -> 186869.23 | N99: 2026E P/E Ratio | Q99: =H99/$W$66 -> 31.233211 | R99: =I99/$W$66 -> 45.010506 | S99: =J99/$W$66 -> 60.326446 | T99: =K99/$W$66 -> 70.31905 | U99: =L99/$W$66 -> 683.35123
B100: 2025E P/E Ratio | F100: =IF(T54<0,0, T54) -> 0 | N100: 2025E P/E Ratio
B102: 2027E Price / Sales | F102: =P54 -> 62404 | H102: =IF($F102<0,$F102*$T$79,$F102*$T$83) -> 6218.2396 | I102: =IF($F102<0,$F102*$T$80,$F102*$T$82) -> 9509.4715 | J102: =$F102*$T$81 -> 17960.912 | K102: =IF($F102>0,$F102*$T$80,$F102*$T$82) -> 21203.595 | L102: =IF($F102>0,$F102*$T$79,$F102*$T$83) -> 49386.389 | N102: 2027E Price / Sales | Q102: =H102/$W$66 -> 22.739119 | R102: =I102/$W$66 -> 34.774634 | S102: =J102/$W$66 -> 65.680217 | T102: =K102/$W$66 -> 77.538196 | U102: =L102/$W$66 -> 180.59822
B103: 2026E Price / Sales | F103: =O54 -> 60205.87 | H103: =IF($F103<0,$F103*$S$79,$F103*$S$83) -> 6115.1619 | I103: =IF($F103<0,$F103*$S$80,$F103*$S$82) -> 9512.9726 | J103: =$F103*$S$81 -> 17913.159 | K103: =IF($F103>0,$F103*$S$80,$F103*$S$82) -> 20764.124 | L103: =IF($F103>0,$F103*$S$79,$F103*$S$83) -> 48909.536 | N103: 2026E Price / Sales | Q103: =H103/$W$66 -> 22.362181 | R103: =I103/$W$66 -> 34.787437 | S103: =J103/$W$66 -> 65.505591 | T103: =K103/$W$66 -> 75.931122 | U103: =L103/$W$66 -> 178.85444
B104: 2025E Price / Sales | F104: =N54 -> 57595.111 | H104: =IF($F104<0,$F104*$R$79,$F104*$R$83) -> 5991.696 | I104: =IF($F104<0,$F104*$R$80,$F104*$R$82) -> 9573.4259 | J104: =$F104*$R$81 -> 17472.048 | K104: =IF($F104>0,$F104*$R$80,$F104*$R$82) -> 20438.091 | L104: =IF($F104>0,$F104*$R$79,$F104*$R$83) -> 48192.224 | N104: 2025E Price / Sales | Q104: =H104/$W$66 -> 21.910685 | R104: =I104/$W$66 -> 35.008505 | S104: =J104/$W$66 -> 63.892517 | T104: =K104/$W$66 -> 74.738867 | U104: =L104/$W$66 -> 176.23135
B107: CCA Charts - Renault | H107: Implied Per Share DCF Value Range | N107: Implied Per Share DCF Value Points
G108: 25th | I108: 75th | M108: 25th | O108: 75th
B109: Comparables | F109: Minimum | G109: Percentile | H109: Median | I109: Percentile | J109: Maximum | L109: Minimum | M109: Percentile | N109: Median | O109: Percentile | P109: Maximum
B111: 2027E Enterprise Value / Revenue | F111: =Q90 | G111: =R90 | H111: =S90 -> 9.9641178 | I111: =T90 -> 27.369287 | J111: =U90 -> 138.58244 | L111: =N111 -> 9.9641178 | M111: =IFERROR(G111-F111,G111) | N111: =IFERROR(H111-G111,H111) -> 9.9641178 | O111: =I111-H111 -> 17.405169 | P111: =J111-I111 -> 111.21315
B112: 2027E Enterprise Value / EBITDA | F112: =Q94 | G112: =R94 | H112: =S94 -> 32.812612 | I112: =T94 -> 114.0622 | J112: =U94 -> 167.98164 | L112: =N112 -> 32.812612 | M112: =IFERROR(G112-F112,G112) | N112: =IFERROR(H112-G112,H112) -> 32.812612 | O112: =I112-H112 -> 81.249591 | P112: =J112-I112 -> 53.91944
B113: 2027E P/E Ratio | F113: =Q98 -> 26.000423 | G113: =R98 -> 42.575907 | H113: =S98 -> 51.979337 | I113: =T98 -> 63.193527 | J113: =U98 -> 76.0307 | L113: =MIN(F113) -> 26.000423 | M113: =IFERROR(G113-F113,G113) -> 16.575484 | N113: =IFERROR(H113-G113,H113) -> 9.4034302 | O113: =I113-H113 -> 11.21419 | P113: =J113-I113 -> 12.837172
B114: 2027E Price / Sales | F114: =Q102 -> 22.739119 | G114: =R102 -> 34.774634 | H114: =S102 -> 65.680217 | I114: =T102 -> 77.538196 | J114: =U102 -> 180.59822 | L114: =MIN(F114) -> 22.739119 | M114: =IFERROR(G114-F114,G114) -> 12.035515 | N114: =IFERROR(H114-G114,H114) -> 30.905583 | O114: =I114-H114 -> 11.857979 | P114: =J114-I114 -> 103.06002
B116: 2026E Enterprise Value / Revenue | F116: =Q91 | G116: =R91 | H116: =S91 -> 5.5871732 | I116: =T91 -> 26.75349 | J116: =U91 -> 135.45151 | L116: =N116 -> 5.5871732 | M116: =IFERROR(G116-F116,G116) | N116: =IFERROR(H116-G116,H116) -> 5.5871732 | O116: =I116-H116 -> 21.166317 | P116: =J116-I116 -> 108.69802
B117: 2026E Enterprise Value / EBITDA | F117: =Q95 | G117: =R95 | H117: =S95 -> 29.976955 | I117: =T95 -> 122.18452 | J117: =U95 -> 230.6229 | L117: =N117 -> 29.976955 | M117: =IFERROR(G117-F117,G117) | N117: =IFERROR(H117-G117,H117) -> 29.976955 | O117: =I117-H117 -> 92.207565 | P117: =J117-I117 -> 108.43838
B118: 2026E P/E Ratio | F118: =Q99 -> 31.233211 | G118: =R99 -> 45.010506 | H118: =S99 -> 60.326446 | I118: =T99 -> 70.31905 | J118: =U99 -> 683.35123 | L118: =MIN(F118) -> 31.233211 | M118: =IFERROR(G118-F118,G118) -> 13.777296 | N118: =IFERROR(H118-G118,H118) -> 15.31594 | O118: =I118-H118 -> 9.9926037 | P118: =J118-I118 -> 613.03218
B119: 2026E Price / Sales | F119: =Q103 -> 22.362181 | G119: =R103 -> 34.787437 | H119: =S103 -> 65.505591 | I119: =T103 -> 75.931122 | J119: =U103 -> 178.85444 | L119: =MIN(F119) -> 22.362181 | M119: =IFERROR(G119-F119,G119) -> 12.425257 | N119: =IFERROR(H119-G119,H119) -> 30.718153 | O119: =I119-H119 -> 10.425531 | P119: =J119-I119 -> 102.92332
B121: 2025E Enterprise Value / Revenue | F121: =Q92 | G121: =R92 | H121: =S90 -> 9.9641178 | I121: =T92 -> 23.417907 | J121: =U92 -> 130.74177 | L121: =N121 -> 9.9641178 | M121: =IFERROR(G121-F121,G121) | N121: =IFERROR(H121-G121,H121) -> 9.9641178 | O121: =I121-H121 -> 13.45379 | P121: =J121-I121 -> 107.32386
B122: 2025E Enterprise Value / EBITDA | F122: =Q96 | G122: =R96 | H122: =S96 -> 48.711798 | I122: =T96 -> 140.50703 | J122: =U96 -> 630.11649 | L122: =N122 -> 48.711798 | M122: =IFERROR(G122-F122,G122) | N122: =IFERROR(H122-G122,H122) -> 48.711798 | O122: =I122-H122 -> 91.795227 | P122: =J122-I122 -> 489.60947
...

Sheet Valuation
B2: Financial Model
B4: Assumptions & Drivers
B6: Date | D6: =DATE(2025,11,1) -> 45962 | H6: TGR Assumptions:
B7: FYE | D7: =DATE(2025,12,31) -> 46022 | H7: Conservative Est | L7: 0.01
H8: European Union | L8: 0.015
B9: WACC Case | D9: {=INDEX(WACC!F33:F35,Valuation!$E$9)} -> Worst Case | E9: 3 | H9: NOPAT | L9: =L114 -> 0.029709657
B10: TGR | D10: =MIN(MAX(INDEX(L7:L10,Valuation!$E$10),0),L129-0.01%) -> 0.02 | E10: 4 | H10: Custom | L10: 0.02
B12: Supporting Schedules
B14: Income Statement Adjusted and Reorganized
B15: All figures in EUR(€) millions unless stated
E16: 2024 | F16: 2025 | G16: 2026 | H16: 2027 | I16: 2028 | J16: 2029 | K16: 2030 | L16: =+K16+1 -> 2031
E17: 2024 | F17: 2025 | G17: 2026 | H17: 2027 | I17: 2028 | J17: 2029 | K17: 2030 | L17: =+K17+1 -> 2031
B18: Revenues | E18: ='Main Financials'!N8 -> 56232 | F18: ='Main Financials'!O8 -> 57595.111 | G18: ='Main Financials'!P8 -> 60205.87 | H18: ='Main Financials'!Q8 -> 62404 | I18: ='Main Financials'!R8 -> 63485.794 | J18: ='Main Financials'!S8 -> 66042.052 | K18: ='Main Financials'!T8 -> 63615.972 | L18: ='Main Financials'!U8 -> 65725.275
B19: Cost of sales (excl. D&A exp.) | E19: ='Main Financials'!N9 -> -41332 | F19: ='Main Financials'!O9 -> -40730.819 | G19: ='Main Financials'!P9 -> -42301.955 | H19: ='Main Financials'!Q9 -> -43958.884 | I19: ='Main Financials'!R9 -> -44767.303 | J19: ='Main Financials'!S9 -> -46492.074 | K19: ='Main Financials'!T9 -> -44247.227 | L19: ='Main Financials'!U9 -> -45576.103
B20: Gross profit | E20: =SUM(E18:E19) -> 14900 | F20: =SUM(F18:F19) -> 16864.293 | G20: =SUM(G18:G19) -> 17903.915 | H20: =SUM(H18:H19) -> 18445.116 | I20: =SUM(I18:I19) -> 18718.491 | J20: =SUM(J18:J19) -> 19549.978 | K20: =SUM(K18:K19) -> 19368.746 | L20: =SUM(L18:L19) -> 20149.172
B21: Total SGA + other operating expenses (excl. D&A) | E21: ='Main Financials'!N11 -> -9154 | F21: ='Main Financials'!O11 -> -10007.358 | G21: ='Main Financials'!P11 -> -10682.17 | H21: ='Main Financials'!Q11 -> -11001.03 | I21: ='Main Financials'!R11 -> -11083.06 | J21: ='Main Financials'!S11 -> -11632.474 | K21: ='Main Financials'!T11 -> -11583.787 | L21: ='Main Financials'!U11 -> -12050.705
B22: EBITDA | E22: =SUM(E20:E21) -> 5746 | F22: =SUM(F20:F21) -> 6856.9353 | G22: =SUM(G20:G21) -> 7221.7443 | H22: =SUM(H20:H21) -> 7444.0856 | I22: =SUM(I20:I21) -> 7635.4309 | J22: =SUM(J20:J21) -> 7917.5036 | K22: =SUM(K20:K21) -> 7784.9587 | L22: =SUM(L20:L21) -> 8098.4674
B23: Depreciation expenses | E23: ='Main Financials'!N13 -> -2120 | F23: ='Main Financials'!O13 -> -2303.8045 | G23: ='Main Financials'!P13 -> -2408.2348 | H23: ='Main Financials'!Q13 -> -2496.16 | I23: ='Main Financials'!R13 -> -2539.4318 | J23: ='Main Financials'!S13 -> -2641.6821 | K23: ='Main Financials'!T13 -> -2544.6389 | L23: ='Main Financials'!U13 -> -2629.011
B24: Depreciation on right-of-use assets (i.e., operating lease assets) | E24: ='Main Financials'!N14 -> 0 | F24: ='Main Financials'!O14 -> 0 | G24: ='Main Financials'!P14 -> 0 | H24: ='Main Financials'!Q14 -> 0 | I24: ='Main Financials'!R14 -> 0 | J24: ='Main Financials'!S14 -> 0 | K24: ='Main Financials'!T14 -> 0 | L24: ='Main Financials'!U14 -> 0
B25: EBITA | E25: =SUM(E22:E24) -> 3626 | F25: =SUM(F22:F24) -> 4553.1309 | G25: =SUM(G22:G24) -> 4813.5095 | H25: =SUM(H22:H24) -> 4947.9255 | I25: =SUM(I22:I24) -> 5095.9991 | J25: =SUM(J22:J24) -> 5275.8216 | K25: =SUM(K22:K24) -> 5240.3198 | L25: =SUM(L22:L24) -> 5469.4564
B26: Amortization expenses | E26: ='Main Financials'!N16 -> -1048 | F26: ='Main Financials'!O16 -> -1439.8778 | G26: ='Main Financials'!P16 -> -1505.1467 | H26: ='Main Financials'!Q16 -> -1560.1 | I26: ='Main Financials'!R16 -> -1587.1449 | J26: ='Main Financials'!S16 -> -1651.0513 | K26: ='Main Financials'!T16 -> -1590.3993 | L26: ='Main Financials'!U16 -> -1643.1319
B27: EBIT before non-recurring items | E27: =SUM(E25:E26) -> 2578 | F27: =SUM(F25:F26) -> 3113.2531 | G27: =SUM(G25:G26) -> 3308.3628 | H27: =SUM(H25:H26) -> 3387.8255 | I27: =SUM(I25:I26) -> 3508.8543 | J27: =SUM(J25:J26) -> 3624.7703 | K27: =SUM(K25:K26) -> 3649.9205 | L27: =SUM(L25:L26) -> 3826.3245
B29: Reorganized Balance Sheet
B30: All figures in EUR(€) millions unless stated
E31: 2024 | F31: 2025 | G31: 2026 | H31: 2027 | I31: 2028 | J31: 2029 | K31: 2030 | L31: =+K31+1 -> 2031
E32: 2024 | F32: 2025 | G32: 2026 | H32: 2027 | I32: 2028 | J32: 2029 | K32: 2030 | L32: =+K32+1 -> 2031
B33: Operating fixed assets | E33: =SUM(E34:E36) -> 20078 | F33: =SUM(F34:F36) -> 21987.818 | G33: =SUM(G34:G36) -> 23917.111 | H33: =SUM(H34:H36) -> 25948.689 | I33: =SUM(I34:I36) -> 28011.956 | J33: =SUM(J34:J36) -> 30215.56 | K33: =SUM(K34:K36) -> 32290.498 | L33: =SUM(L34:L36) -> 34530.454
B34: Intangible assets and goodwill | E34: ='Main Financials'!N93 -> 5164 | F34: ='Main Financials'!O93 -> 5798.7009 | G34: ='Main Financials'!P93 -> 6460.8188 | H34: ='Main Financials'!Q93 -> 7161.8147 | I34: ='Main Financials'!R93 -> 7883.3701 | J34: ='Main Financials'!S93 -> 8645.0337 | K34: ='Main Financials'!T93 -> 9396.0973 | L34: ='Main Financials'!U93 -> 10175.547
B35: Property, plant and equipment | E35: ='Main Financials'!N94 -> 13861 | F35: ='Main Financials'!O94 -> 15037.215 | G35: ='Main Financials'!P94 -> 16252.175 | H35: ='Main Financials'!Q94 -> 17538.794 | I35: ='Main Financials'!R94 -> 18858.87 | J35: ='Main Financials'!S94 -> 20249.686 | K35: ='Main Financials'!T94 -> 21622.081 | L35: ='Main Financials'!U94 -> 23040.402
B36: Other non-current assets | E36: ='Main Financials'!N95 -> 1053 | F36: ='Main Financials'!O95 -> 1151.9022 | G36: ='Main Financials'!P95 -> 1204.1174 | H36: ='Main Financials'!Q95 -> 1248.08 | I36: ='Main Financials'!R95 -> 1269.7159 | J36: ='Main Financials'!S95 -> 1320.841 | K36: ='Main Financials'!T95 -> 1272.3194 | L36: ='Main Financials'!U95 -> 1314.5055
B38: Operating net working capital | E38: =SUM(E39:E45) -> 18272.41 | F38: =SUM(F39:F45) -> 18047.101 | G38: =SUM(G39:G45) -> 18880.6 | H38: =SUM(H39:H45) -> 19545.751 | I38: =SUM(I39:I45) -> 19873.87 | J38: =SUM(J39:J45) -> 20669.538 | K38: =SUM(K39:K45) -> 19981.01 | L38: =SUM(L39:L45) -> 20647.895
B39: Inventories | E39: ='Main Financials'!N98 -> 5468 | F39: ='Main Financials'!O98 -> 5579.5642 | G39: ='Main Financials'!P98 -> 5794.7884 | H39: ='Main Financials'!Q98 -> 6021.765 | I39: ='Main Financials'!R98 -> 6132.5072 | J39: ='Main Financials'!S98 -> 6368.7772 | K39: ='Main Financials'!T98 -> 6061.2639 | L39: ='Main Financials'!U98 -> 6243.3018
B40: Sales financing recievables | E40: ='Main Financials'!N99 -> 54355 | F40: ='Main Financials'!O99 -> 53650.241 | G40: ='Main Financials'!P99 -> 56082.18 | H40: ='Main Financials'!Q99 -> 58129.754 | I40: ='Main Financials'!R99 -> 59137.452 | J40: ='Main Financials'!S99 -> 61518.624 | K40: ='Main Financials'!T99 -> 59258.714 | L40: ='Main Financials'!U99 -> 61223.544
B41: Automotive recivable & other current assets (excl. tax and current tax due) | E41: ='Main Financials'!N100 -> 6137 | F41: ='Main Financials'!O100 -> 6311.793 | G41: ='Main Financials'!P100 -> 6597.9035 | H41: ='Main Financials'!Q100 -> 6838.7946 | I41: ='Main Financials'!R100 -> 6957.3473 | J41: ='Main Financials'!S100 -> 7237.4851 | K41: ='Main Financials'!T100 -> 6971.6134 | L41: ='Main Financials'!U100 -> 7202.7699
B42: Derivatives of financing operations by the Automotive segment | E42: ='Main Financials'!N101 -> 356 | F42: ='Main Financials'!O101 -> 324.8 | G42: ='Main Financials'!P101 -> 324.8 | H42: ='Main Financials'!Q101 -> 324.8 | I42: ='Main Financials'!R101 -> 324.8 | J42: ='Main Financials'!S101 -> 324.8 | K42: ='Main Financials'!T101 -> 324.8 | L42: ='Main Financials'!U101 -> 324.8
B43: Operating Cash | E43: ='Main Financials'!N102 -> 22203.41 | F43: ='Main Financials'!O102 -> 22185.952 | G43: ='Main Financials'!P102 -> 23191.631 | H43: ='Main Financials'!Q102 -> 24038.363 | I43: ='Main Financials'!R102 -> 24455.076 | J43: ='Main Financials'!S102 -> 25439.76 | K43: ='Main Financials'!T102 -> 24505.221 | L43: ='Main Financials'!U102 -> 25317.736
B44: Sales financing debts | E44: ='Main Financials'!N103 -> -60438 | F44: ='Main Financials'!O103 -> -59962.034 | G44: ='Main Financials'!P103 -> -62680.084 | H44: ='Main Financials'!Q103 -> -64968.548 | I44: ='Main Financials'!R103 -> -66094.799 | J44: ='Main Financials'!S103 -> -68756.109 | K44: ='Main Financials'!T103 -> -66230.327 | L44: ='Main Financials'!U103 -> -68426.314
B45: Trade payables (current) | E45: ='Main Financials'!N104 -> -9809 | F45: ='Main Financials'!O104 -> -10043.216 | G45: ='Main Financials'!P104 -> -10430.619 | H45: ='Main Financials'!Q104 -> -10839.177 | I45: ='Main Financials'!R104 -> -11038.513 | J45: ='Main Financials'!S104 -> -11463.799 | K45: ='Main Financials'!T104 -> -10910.275 | L45: ='Main Financials'!U104 -> -11237.943
B47: Operating Liabilities | E47: =SUM(E48:E51) -> -15980 | F47: =SUM(F48:F51) -> -16239.518 | G47: =SUM(G48:G51) -> -16975.647 | H47: =SUM(H48:H51) -> -17595.432 | I47: =SUM(I48:I51) -> -17900.455 | J47: =SUM(J48:J51) -> -18621.217 | K47: =SUM(K48:K51) -> -17937.16 | L47: =SUM(L48:L51) -> -18531.899
B48: Net deferred tax liabilities associated with operating ítems | E48: ='Main Financials'!N107 -> -1269 | F48: ='Main Financials'!O107 -> -1290.1305 | G48: ='Main Financials'!P107 -> -1348.6115 | H48: ='Main Financials'!Q107 -> -1397.8496 | I48: ='Main Financials'!R107 -> -1422.0818 | J48: ='Main Financials'!S107 -> -1479.342 | K48: ='Main Financials'!T107 -> -1424.9978 | L48: ='Main Financials'!U107 -> -1472.2462
B49: Tax Liabilitity | E49: ='Main Financials'!N108 -> -370 | F49: ='Main Financials'!O108 -> -354.78589 | G49: ='Main Financials'!P108 -> -370.86816 | H49: ='Main Financials'!Q108 -> -384.40864 | I49: ='Main Financials'!R108 -> -391.07249 | J49: ='Main Financials'!S108 -> -406.81904 | K49: ='Main Financials'!T108 -> -391.87439 | L49: ='Main Financials'!U108 -> -404.8677
B50: Operating provisions (non-current + current) | E50: ='Main Financials'!N109 -> -2630 | F50: ='Main Financials'!O109 -> -2741.5273 | G50: ='Main Financials'!P109 -> -2865.7994 | H50: ='Main Financials'!Q109 -> -2970.4304 | I50: ='Main Financials'!R109 -> -3021.9238 | J50: ='Main Financials'!S109 -> -3143.6017 | K50: ='Main Financials'!T109 -> -3028.1203 | L50: ='Main Financials'!U109 -> -3128.5231
B51: Other liabilities (non-current + current) | E51: ='Main Financials'!N110 -> -11711 | F51: ='Main Financials'!O110 -> -11853.074 | G51: ='Main Financials'!P110 -> -12390.368 | H51: ='Main Financials'!Q110 -> -12842.743 | I51: ='Main Financials'!R110 -> -13065.376 | J51: ='Main Financials'!S110 -> -13591.454 | K51: ='Main Financials'!T110 -> -13092.167 | L51: ='Main Financials'!U110 -> -13526.262
B53: Operating Capital | E53: =SUM(E47,E38,E33,) -> 22370.41 | F53: =SUM(F47,F38,F33,) -> 23795.402 | G53: =SUM(G47,G38,G33,) -> 25822.064 | H53: =SUM(H47,H38,H33,) -> 27899.008 | I53: =SUM(I47,I38,I33,) -> 29985.371 | J53: =SUM(J47,J38,J33,) -> 32263.882 | K53: =SUM(K47,K38,K33,) -> 34334.349 | L53: =SUM(L47,L38,L33,) -> 36646.451
B55: Reinvestment Schedules
E57: 2024 | F57: 2025 | G57: 2026 | H57: 2027 | I57: 2028 | J57: 2029 | K57: 2030 | L57: =+K57+1 -> 2031
E58: 2024 | F58: 2025 | G58: 2026 | H58: 2027 | I58: 2028 | J58: 2029 | K58: 2030 | L58: =+K58+1 -> 2031
B59: CapEx PPE (Reinvestments in tangible assets) | E59: ='Main Financials'!N411 -> 3412 | F59: ='Main Financials'!O411 -> 3167.7311 | G59: ='Main Financials'!P411 -> 3311.3228 | H59: ='Main Financials'!Q411 -> 3432.22 | I59: ='Main Financials'!R411 -> 3491.7187 | J59: ='Main Financials'!S411 -> 3632.3129 | K59: ='Main Financials'!T411 -> 3498.8785 | L59: ='Main Financials'!U411 -> 3614.8901
B60: CapEx Intangibles (Reinvestments in intangible assets) | E60: ='Main Financials'!N438 -> 1514 | F60: ='Main Financials'!O438 -> 1958.2338 | G60: ='Main Financials'!P438 -> 2046.9996 | H60: ='Main Financials'!Q438 -> 2121.736 | I60: ='Main Financials'!R438 -> 2158.517 | J60: ='Main Financials'!S438 -> 2245.4298 | K60: ='Main Financials'!T438 -> 2162.9431 | L60: ='Main Financials'!U438 -> 2234.6594
B62: Calculation Accounts
E64: 2024 | F64: 2025 | G64: 2026 | H64: 2027 | I64: 2028 | J64: 2029 | K64: 2030 | L64: =+K64+1 -> 2031
E65: 2024 | F65: 2025 | G65: 2026 | H65: 2027 | I65: 2028 | J65: 2029 | K65: 2030 | L65: =+K65+1 -> 2031
B66: Adjusted EBIT | E66: =E27 -> 2578 | F66: =F27 -> 3113.2531 | G66: =G27 -> 3308.3628 | H66: =H27 -> 3387.8255 | I66: =I27 -> 3508.8543 | J66: =J27 -> 3624.7703 | K66: =K27 -> 3649.9205 | L66: =L27 -> 3826.3245
B67: Tax rate % | E67: =Macro!N17 -> 0.2583 | F67: =Macro!O17 -> 0.25 | G67: =Macro!P17 -> 0.25 | H67: =Macro!Q17 -> 0.25 | I67: =Macro!R17 -> 0.25 | J67: =Macro!S17 -> 0.25 | K67: =Macro!T17 -> 0.25 | L67: =Macro!U17 -> 0.25
B68: - Statutory taxes | E68: =E66*E67 -> 665.8974 | F68: =F66*F67 -> 778.31327 | G68: =G66*G67 -> 827.09069 | H68: =H66*H67 -> 846.95638 | I68: =I66*I67 -> 877.21356 | J68: =J66*J67 -> 906.19256 | K68: =K66*K67 -> 912.48011 | L68: =L66*L67 -> 956.58112
B70: + Depreciation of tangible assets | E70: =ABS(E23) -> 2120 | F70: =ABS(F23) -> 2303.8045 | G70: =ABS(G23) -> 2408.2348 | H70: =ABS(H23) -> 2496.16 | I70: =ABS(I23) -> 2539.4318 | J70: =ABS(J23) -> 2641.6821 | K70: =ABS(K23) -> 2544.6389 | L70: =ABS(L23) -> 2629.011
B71: + Amortization intangible assets | E71: =ABS(E26) -> 1048 | F71: =ABS(F26) -> 1439.8778 | G71: =ABS(G26) -> 1505.1467 | H71: =ABS(H26) -> 1560.1 | I71: =ABS(I26) -> 1587.1449 | J71: =ABS(J26) -> 1651.0513 | K71: =ABS(K26) -> 1590.3993 | L71: =ABS(L26) -> 1643.1319
B72: - Reinvestments in tangible assets | E72: =E59 -> 3412 | F72: =F59 -> 3167.7311 | G72: =G59 -> 3311.3228 | H72: =H59 -> 3432.22 | I72: =I59 -> 3491.7187 | J72: =J59 -> 3632.3129 | K72: =K59 -> 3498.8785 | L72: =L59 -> 3614.8901
B73: - Reinvestments in intangible assets | E73: =E60 -> 1514 | F73: =F60 -> 1958.2338 | G73: =G60 -> 2046.9996 | H73: =H60 -> 2121.736 | I73: =I60 -> 2158.517 | J73: =J60 -> 2245.4298 | K73: =K60 -> 2162.9431 | L73: =L60 -> 2234.6594
B75: Operating net working capital | E75: =E38 -> 18272.41 | F75: =F38 -> 18047.101 | G75: =G38 -> 18880.6 | H75: =H38 -> 19545.751 | I75: =I38 -> 19873.87 | J75: =J38 -> 20669.538 | K75: =K38 -> 19981.01 | L75: =L38 -> 20647.895
B76: - Investments in operating NWC | F76: =F75-E75 -> -225.30847 | G76: =G75-F75 -> 833.49906 | H76: =H75-G75 -> 665.15072 | I76: =I75-H75 -> 328.11906 | J76: =J75-I75 -> 795.6685 | K76: =K75-J75 -> -688.52855 | L76: =L75-K75 -> 666.88485
B78: Other non-current assets | E78: =E36 -> 1053 | F78: =F36 -> 1151.9022 | G78: =G36 -> 1204.1174 | H78: =H36 -> 1248.08 | I78: =I36 -> 1269.7159 | J78: =J36 -> 1320.841 | K78: =K36 -> 1272.3194 | L78: =L36 -> 1314.5055
B79: - Changes in non-current operating assets | F79: =F78-E78 -> 98.902228 | G79: =G78-F78 -> 52.215166 | H79: =H78-G78 -> 43.962615 | I79: =I78-H78 -> 21.635874 | J79: =J78-I78 -> 51.125156 | K79: =K78-J78 -> -48.521595 | L79: =L78-K78 -> 42.186063
B81: Operating provisions (non-current + current) | E81: =E50 -> -2630 | F81: =F50 -> -2741.5273 | G81: =G50 -> -2865.7994 | H81: =H50 -> -2970.4304 | I81: =I50 -> -3021.9238 | J81: =J50 -> -3143.6017 | K81: =K50 -> -3028.1203 | L81: =L50 -> -3128.5231
B82: + Change in operating provisions | F82: =ABS(F81)-ABS(E81) -> 111.5273 | G82: =ABS(G81)-ABS(F81) -> 124.2721 | H82: =ABS(H81)-ABS(G81) -> 104.63102 | I82: =ABS(I81)-ABS(H81) -> 51.493379 | J82: =ABS(J81)-ABS(I81) -> 121.67787 | K82: =ABS(K81)-ABS(J81) -> -115.4814 | L82: =ABS(L81)-ABS(K81) -> 100.40283
B84: Net deferred tax liabilities associated with operating ítems | E84: =E48 -> -1269 | F84: =F48 -> -1290.1305 | G84: =G48 -> -1348.6115 | H84: =H48 -> -1397.8496 | I84: =I48 -> -1422.0818 | J84: =J48 -> -1479.342 | K84: =K48 -> -1424.9978 | L84: =L48 -> -1472.2462
B85: + Change in net operating DTL | F85: =(-1*F84)-(-1*E84) -> 21.130495 | G85: =(-1*G84)-(-1*F84) -> 58.480986 | H85: =(-1*H84)-(-1*G84) -> 49.238129 | I85: =(-1*I84)-(-1*H84) -> 24.232179 | J85: =(-1*J84)-(-1*I84) -> 57.260174 | K85: =(-1*K84)-(-1*J84) -> -54.344186 | L85: =(-1*L84)-(-1*K84) -> 47.248391
B87: Other liabilities (non-current + current) | E87: =E51 -> -11711 | F87: =F51 -> -11853.074 | G87: =G51 -> -12390.368 | H87: =H51 -> -12842.743 | I87: =I51 -> -13065.376 | J87: =J51 -> -13591.454 | K87: =K51 -> -13092.167 | L87: =L51 -> -13526.262
B88: Tax Liabilitity | E88: =E49 -> -370 | F88: =F49 -> -354.78589 | G88: =G49 -> -370.86816 | H88: =H49 -> -384.40864 | I88: =I49 -> -391.07249 | J88: =J49 -> -406.81904 | K88: =K49 -> -391.87439 | L88: =L49 -> -404.8677
B89: + Change in other non-current operating liabilities | F89: =ABS(F88)-ABS(E88)+ABS(F87)-ABS(E87) -> 126.85981 | G89: =ABS(G88)-ABS(F88)+ABS(G87)-ABS(F87) -> 553.37633 | H89: =ABS(H88)-ABS(G88)+ABS(H87)-ABS(G87) -> 465.9158 | I89: =ABS(I88)-ABS(H88)+ABS(I87)-ABS(H87) -> 229.29699 | J89: =ABS(J88)-ABS(I88)+ABS(J87)-ABS(I87) -> 541.8244 | K89: =ABS(K88)-ABS(J88)+ABS(K87)-ABS(J87) -> -514.23186 | L89: =ABS(L88)-ABS(K88)+ABS(L87)-ABS(K87) -> 447.0879
B92: FCF Forecast
F94: 2025 | G94: 2026 | H94: 2027 | I94: 2028 | J94: 2029 | K94: 2030 | L94: =+K94+1 -> 2031
F95: 2025 | G95: 2026 | H95: 2027 | I95: 2028 | J95: 2029 | K95: 2030 | L95: =+K95+1 -> 2031
B96: Adjusted EBIT | F96: =F66 -> 3113.2531 | G96: =G66 -> 3308.3628 | H96: =H66 -> 3387.8255 | I96: =I66 -> 3508.8543 | J96: =J66 -> 3624.7703 | K96: =K66 -> 3649.9205 | L96: =L66 -> 3826.3245
B97: - Statutory taxes | F97: =F68 -> 778.31327 | G97: =G68 -> 827.09069 | H97: =H68 -> 846.95638 | I97: =I68 -> 877.21356 | J97: =J68 -> 906.19256 | K97: =K68 -> 912.48011 | L97: =L68 -> 956.58112
B98: NOPAT | F98: =F96-F97 -> 2334.9398 | G98: =G96-G97 -> 2481.2721 | H98: =H96-H97 -> 2540.8691 | I98: =I96-I97 -> 2631.6407 | J98: =J96-J97 -> 2718.5777 | K98: =K96-K97 -> 2737.4403 | L98: =L96-L97 -> 2869.7434
B99: + Depreciation of tangible assets | F99: =F70 -> 2303.8045 | G99: =G70 -> 2408.2348 | H99: =H70 -> 2496.16 | I99: =I70 -> 2539.4318 | J99: =J70 -> 2641.6821 | K99: =K70 -> 2544.6389 | L99: =L70 -> 2629.011
B100: + Amortization intangible assets | F100: =F71 -> 1439.8778 | G100: =G71 -> 1505.1467 | H100: =H71 -> 1560.1 | I100: =I71 -> 1587.1449 | J100: =J71 -> 1651.0513 | K100: =K71 -> 1590.3993 | L100: =L71 -> 1643.1319
B101: - Reinvestments in tangible assets | F101: =F72 -> 3167.7311 | G101: =G72 -> 3311.3228 | H101: =H72 -> 3432.22 | I101: =I72 -> 3491.7187 | J101: =J72 -> 3632.3129 | K101: =K72 -> 3498.8785 | L101: =L72 -> 3614.8901
B102: - Reinvestments in intangible assets | F102: =F73 -> 1958.2338 | G102: =G73 -> 2046.9996 | H102: =H73 -> 2121.736 | I102: =I73 -> 2158.517 | J102: =J73 -> 2245.4298 | K102: =K73 -> 2162.9431 | L102: =L73 -> 2234.6594
B103: - Investments in operating NWC | F103: =F76 -> -225.30847 | G103: =G76 -> 833.49906 | H103: =H76 -> 665.15072 | I103: =I76 -> 328.11906 | J103: =J76 -> 795.6685 | K103: =K76 -> -688.52855 | L103: =L76 -> 666.88485
B104: - Changes in non-current operating assets | F104: =F79 -> 98.902228 | G104: =G79 -> 52.215166 | H104: =H79 -> 43.962615 | I104: =I79 -> 21.635874 | J104: =J79 -> 51.125156 | K104: =K79 -> -48.521595 | L104: =L79 -> 42.186063
B105: + Change in operating provisions | F105: =F82 -> 111.5273 | G105: =G82 -> 124.2721 | H105: =H82 -> 104.63102 | I105: =I82 -> 51.493379 | J105: =J82 -> 121.67787 | K105: =K82 -> -115.4814 | L105: =L82 -> 100.40283
B106: + Change in net operating DTL | F106: =F85 -> 21.130495 | G106: =G85 -> 58.480986 | H106: =H85 -> 49.238129 | I106: =I85 -> 24.232179 | J106: =J85 -> 57.260174 | K106: =K85 -> -54.344186 | L106: =L85 -> 47.248391
B107: + Change in other non-current operating liabilities | F107: =F89 -> 126.85981 | G107: =G89 -> 553.37633 | H107: =H89 -> 465.9158 | I107: =I89 -> 229.29699 | J107: =J89 -> 541.8244 | K107: =K89 -> -514.23186 | L107: =L89 -> 447.0879
B108: Free cash flow | F108: =F98+SUM(F99:F100)-SUM(F101:F104)+SUM(F105:F107) -> 1338.581 | G108: =G98+SUM(G99:G100)-SUM(G101:G104)+SUM(G105:G107) -> 886.7464 | H108: =H98+SUM(H99:H100)-SUM(H101:H104)+SUM(H105:H107) -> 953.84475 | I108: =I98+SUM(I99:I100)-SUM(I101:I104)+SUM(I105:I107) -> 1063.2492 | J108: =J98+SUM(J99:J100)-SUM(J101:J104)+SUM(J105:J107) -> 1007.5372 | K108: =K98+SUM(K99:K100)-SUM(K101:K104)+SUM(K105:K107) -> 1263.6497 | L108: =L98+SUM(L99:L100)-SUM(L101:L104)+SUM(L105:L107) -> 1178.005
B111: New investment | F111: =F98-F108 -> 996.35882 | G111: =G98-G108 -> 1594.5257 | H111: =H98-H108 -> 1587.0244 | I111: =I98-I108 -> 1568.3915 | J111: =J98-J108 -> 1711.0405 | K111: =K98-K108 -> 1473.7906 | L111: =L98-L108 -> 1691.7384
B112: Reinvestment rate | F112: =F111/F98 -> 0.42671713 | G112: =G111/G98 -> 0.64262428 | H112: =H111/H98 -> 0.62459903 | I112: =I111/I98 -> 0.59597477 | J112: =J111/J98 -> 0.6293881 | K112: =K111/K98 -> 0.53838274 | L112: =L111/L98 -> 0.5895086
B113: RONIC | F113: =(G98-F98)/F111 -> 0.14686705 | G113: =(H98-G98)/G111 -> 0.037376041 | H113: =(I98-H98)/H111 -> 0.057196064 | I113: =(J98-I98)/I111 -> 0.055430679 | J113: =(K98-J98)/J111 -> 0.011024083 | K113: =(L98-K98)/K111 -> 0.089770569 | L113: =AVERAGE(J113:K113) -> 0.050397326
B114: NOPAT growth rate | F114: =F113*F112 -> 0.062670685 | G114: =G113*G112 -> 0.024018752 | H114: =H113*H112 -> 0.035724606 | I114: =I113*I112 -> 0.033035286 | J114: =J113*J112 -> 0.0069384266 | K114: =K113*K112 -> 0.048330925 | L114: =L113*L112 -> 0.029709657
B115: ROIC | F115: =F98/AVERAGE(E53:F53) -> 0.1011545 | G115: =G98/AVERAGE(F53:G53) -> 0.10001607 | H115: =H98/AVERAGE(G53:H53) -> 0.094594878 | I115: =I98/AVERAGE(H53:I53) -> 0.090927491 | J115: =J98/AVERAGE(I53:J53) -> 0.08734491 | K115: =K98/AVERAGE(J53:K53) -> 0.0822076 | L115: =L98/AVERAGE(K53:L53) -> 0.080859709
G116: =G96/F96-1 -> 0.062670685 | H116: =H96/G96-1 -> 0.024018752 | I116: =I96/H96-1 -> 0.035724606 | J116: =J96/I96-1 -> 0.033035286 | K116: =K96/J96-1 -> 0.0069384266 | L116: =L96/K96-1 -> 0.048330925
B119: DCF
F121: 2025 | G121: 2026 | H121: 2027 | I121: 2028 | J121: 2029 | K121: 2030 | L121: =+K121+1 -> 2031
F122: 2025 | G122: 2026 | H122: 2027 | I122: 2028 | J122: 2029 | K122: 2030 | L122: =+K122+1 -> 2031
B123: Free cash flow | F123: =F108 -> 1338.581 | G123: =G108 -> 886.7464 | H123: =H108 -> 953.84475 | I123: =I108 -> 1063.2492 | J123: =J108 -> 1007.5372 | K123: =K108 -> 1263.6497 | L123: =L108 -> 1178.005
B124: PV of Operating FCF | F124: =(F126*F123)/(1+F129)^F127 -> 222.23127 | G124: =(G123)/(1+G129)^G127 -> 863.45839 | H124: =(H123)/(1+H129)^H127 -> 885.98317 | I124: =(I123)/(1+I129)^I127 -> 936.12792 | J124: =(J123)/(1+J129)^J127 -> 839.3325 | K124: =(K123)/(1+K129)^K127 -> 988.46523 | L124: =(L123)/(1+L129)^L127 -> 861.28344
B126: Stub | F126: =YEARFRAC(D6,D7) -> 0.16666667
B127: Discount rate | F127: =F126/2 -> 0.083333333 | G127: =F127+0.5 -> 0.58333333 | H127: =G127+1 -> 1.5833333 | I127: =H127+1 -> 2.5833333 | J127: =I127+1 -> 3.5833333 | K127: =J127+1 -> 4.5833333 | L127: =K127+1 -> 5.5833333
B129: Weighted average cost of capital | F129: =WACC!I31 -> 0.047752691 | G129: =WACC!J31 -> 0.046679585 | H129: =WACC!K31 -> 0.047715836 | I129: =WACC!L31 -> 0.050525036 | J129: =WACC!M31 -> 0.052295677 | K129: =WACC!N31 -> 0.055048514 | L129: =WACC!O31 -> 0.057689985
...

Sheet Macro
B2: Inflation Input
E4: 2015 | F4: 2016 | G4: 2017 | H4: 2018 | I4: 2019 | J4: 2020 | K4: 2021 | L4: 2022 | M4: 2023 | N4: 2024 | O4: 2025 | P4: 2026 | Q4: 2027 | R4: 2028 | S4: 2029 | T4: 2030 | U4: =+T4+1 -> 2031
B6: European Union | E6: 0.03 | F6: 0.011 | G6: 0.01499 | H6: 0.01695 | I6: 0.01559 | J6: 0.00157 | K6: 0.05346 | L6: 0.10762 | M6: 0.03215 | N6: 0.02655 | O6: 0.02253 | P6: 0.02074 | Q6: 0.02157 | R6: 0.02097 | S6: 0.02122 | T6: 0.02065 | U6: 0.02
B8: Compounded inflation multiple | E8: =F8*(1+F6) -> 1.3123329 | F8: =G8*(1+G6) -> 1.2980543 | G8: =H8*(1+H6) -> 1.2788838 | H8: =I8*(1+I6) -> 1.257568 | I8: =J8*(1+J6) -> 1.2382635 | J8: =K8*(1+K6) -> 1.2363225 | K8: =L8*(1+L6) -> 1.1735827 | L8: =M8*(1+M6) -> 1.0595536 | M8: =N8*(1+N6) -> 1.02655 | N8: 1 | O8: =N8*(1+O6) -> 1.02253 | P8: =O8*(1+P6) -> 1.0437373 | Q8: =P8*(1+Q6) -> 1.0662507 | R8: =Q8*(1+R6) -> 1.08861 | S8: =R8*(1+S6) -> 1.1117103 | T8: =S8*(1+T6) -> 1.1346671 | U8: =T8*(1+U6) -> 1.1573604
B11: Tax Rates
B13: Renault | E13: 2015 | F13: 2016 | G13: 2017 | H13: 2018 | I13: 2019 | J13: 2020 | K13: 2021 | L13: 2022 | M13: 2023 | N13: 2024 | O13: 2025 | P13: 2026 | Q13: 2027 | R13: 2028 | S13: 2029 | T13: 2030 | U13: =+T13+1 -> 2031
B14: Renault Effective Tax | E14: ='Main Financials'!E66/-'Main Financials'!E65 -> 0.095077958 | F14: ='Main Financials'!F66/-'Main Financials'!F65 -> 0.22944759 | G14: ='Main Financials'!G66/-'Main Financials'!G65 -> 0.14604163 | H14: ='Main Financials'!H66/-'Main Financials'!H65 -> 0.17321514 | I14: ='Main Financials'!I66/-'Main Financials'!I65 -> 0.98710115 | J14: ='Main Financials'!J66/-'Main Financials'!J65 -> -0.055074744 | K14: ='Main Financials'!K66/-'Main Financials'!K65 -> 0.38131798 | L14: ='Main Financials'!L66/-'Main Financials'!L65 -> 0.24756154 | ... N14: ='Main Financials'!N66/-'Main Financials'!N65 -> 0.4206762
B15: Average | D15: =AVERAGE(E14:N14) -> 0.28096492
B17: FR nominal/statutory tax rate | E17: 0.38 | F17: 0.3443 | G17: 0.3443 | H17: 0.3443 | I17: 0.3443 | J17: 0.3202 | K17: 0.2841 | L17: 0.2583 | M17: 0.2583 | N17: 0.2583 | O17: 0.25 | P17: 0.25 | Q17: 0.25 | R17: 0.25 | S17: 0.25 | T17: 0.25 | U17: 0.25
O20: Country Corporate Tax Rates
B21: Competitors | E21: Country of Origin | K21: 10 Year Aver Effective Tax | N21: =N4 -> 2024 | O21: =O4 -> 2025 | P21: =P4 -> 2026 | Q21: =Q4 -> 2027
B22: Stellantis | E22: Italy | M22: {=AVERAGE(INDIRECT(B22&"!E21:P21")/INDIRECT(B22&"!E20:P20"))} -> 0.12625534 | N22: 0.24 | O22: 0.24 | P22: 0.24 | Q22: 0.24
B23: Volkswagen | E23: Germany | M23: {=AVERAGE(INDIRECT(B23&"!E21:P21")/INDIRECT(B23&"!E20:P20"))} -> 0.2399952 | N23: 0.15825 | O23: 0.15825 | P23: 0.15825 | Q23: 0.15825
B24: Nissan | E24: Japan | M24: {=AVERAGE(INDIRECT(B24&"!E21:P21")/INDIRECT(B24&"!E20:P20"))} -> 0.30429663 | N24: 0.232 | O24: 0.232 | P24: 0.232 | Q24: 0.232
B25: BMW | E25: Germany | M25: {=AVERAGE(INDIRECT(B25&"!E21:P21")/INDIRECT(B25&"!E20:P20"))} -> 0.2829796 | N25: 0.15825 | O25: 0.15825 | P25: 0.15825 | Q25: 0.15825
B26: MercedesBenz | E26: Germany | M26: {=AVERAGE(INDIRECT(B26&"!E21:P21")/INDIRECT(B26&"!E20:P20"))} -> 0.3942979 | N26: 0.15825 | O26: 0.15825 | P26: 0.15825 | Q26: 0.15825
B27: Toyota | E27: Japan | M27: {=AVERAGE(INDIRECT(B27&"!E21:P21")/INDIRECT(B27&"!E20:P20"))} -> 0.32947895 | N27: 0.232 | O27: 0.232 | P27: 0.232 | Q27: 0.232
B28: Honda | E28: Japan | M28: {=AVERAGE(INDIRECT(B28&"!E21:P21")/INDIRECT(B28&"!E20:P20"))} -> 0.30704153 | N28: 0.232 | O28: 0.232 | P28: 0.232 | Q28: 0.232
B29: Ford | E29: United States | M29: {=AVERAGE(INDIRECT(B29&"!E21:P21")/INDIRECT(B29&"!E20:P20"))} -> -0.032402271 | N29: 0.21 | O29: 0.21 | P29: 0.21 | Q29: 0.21
B30: GeneralMotors | E30: United States | M30: {=AVERAGE(INDIRECT(B30&"!E21:P21")/INDIRECT(B30&"!E20:P20"))} -> 0.27553668 | N30: 0.21 | O30: 0.21 | P30: 0.21 | Q30: 0.21
N31: https://taxsummaries.pwc.com/quick-charts/corporate-income-tax-cit-rates

Sheet Ratio's
B2: Financial Ratios
B3: All figures in EUR(€) millions unless stated
D4: 2017 | E4: 2018 | F4: 2019 | G4: 2020 | H4: 2021 | I4: 2022 | J4: 2023 | K4: 2024
D5: 2017 | E5: 2018 | F5: 2019 | G5: 2020 | H5: 2021 | I5: 2022 | J5: 2023 | K5: 2024
B6: Operating costs
B7: Cost of sales (excl. D&A) as % of net sales | D7: =ABS(D61/D60) -> 0.7735526 | E7: =ABS(E61/E60) -> 0.77071884 | F7: =ABS(F61/F60) -> 0.77773759 | G7: =ABS(G61/G60) -> 0.76807567 | H7: =ABS(H61/H60) -> 0.76791284 | I7: =ABS(I61/I60) -> 0.67573452 | J7: =ABS(J61/J60) -> 0.72989537 | K7: =ABS(K61/K60) -> 0.73502632
B8: Total SGA + other operating expenses (excl. D&A) as % of net sales | D8: =ABS(D63/D60) -> 0.10691494 | E8: =ABS(E63/E60) -> 0.11538698 | F8: =ABS(F63/F60) -> 0.10822849 | G8: =ABS(G63/G60) -> 0.16496027 | H8: =ABS(H63/H60) -> 0.10724771 | I8: =ABS(I63/I60) -> 0.15155957 | J8: =ABS(J63/J60) -> 0.16186803 | K8: =ABS(K63/K60) -> 0.16278987
B10: Profit margin
B11: Gross margin | D11: =ABS(D62/D60) -> 0.2264474 | E11: =ABS(E62/E60) -> 0.22928116 | F11: =ABS(F62/F60) -> 0.22226241 | G11: =ABS(G62/G60) -> 0.23192433 | H11: =ABS(H62/H60) -> 0.23208716 | I11: =ABS(I62/I60) -> 0.32426548 | J11: =ABS(J62/J60) -> 0.27010463 | K11: =ABS(K62/K60) -> 0.26497368
B12: EBITDA margin | D12: =ABS(D64/D60) -> 0.11953246 | E12: =ABS(E64/E60) -> 0.11389418 | F12: =ABS(F64/F60) -> 0.11403392 | G12: =ABS(G64/G60) -> 0.066964068 | H12: =ABS(H64/H60) -> 0.12483945 | I12: =ABS(I64/I60) -> 0.17270591 | J12: =ABS(J64/J60) -> 0.1082366 | K12: =ABS(K64/K60) -> 0.10218381
B13: EBITA margin | D13: =ABS(D67/D60) -> 0.081421896 | E13: =ABS(E67/E60) -> 0.070235217 | F13: =ABS(F67/F60) -> 0.065515732 | G13: =ABS(G67/G60) -> 0.0029740139 | H13: =ABS(H67/H60) -> 0.060802752 | I13: =ABS(I67/I60) -> 0.096786015 | J13: =ABS(J67/J60) -> 0.07104399 | K13: =ABS(K67/K60) -> 0.064482857
B15: Profitability ratios
B16: Return on invested capital (ROIC) | E16: =E69*(1-Macro!H17)/AVERAGE('Ratio''s'!D95:E95) -> 0.093039787 | F16: =F69*(1-Macro!I17)/AVERAGE('Ratio''s'!E95:F95) -> 0.06630041 | G16: =G69*(1-Macro!J17)/AVERAGE('Ratio''s'!F95:G95) -> -0.058526796 | H16: =H69*(1-Macro!K17)/AVERAGE('Ratio''s'!G95:H95) -> 0.041626845 | I16: =I69*(1-Macro!L17)/AVERAGE('Ratio''s'!H95:I95) -> 0.073430941 | J16: =J69*(1-Macro!M17)/AVERAGE('Ratio''s'!I95:J95) -> 0.087363538 | K16: =K69*(1-Macro!N17)/AVERAGE('Ratio''s'!J95:K95) -> 0.087055398
B17: Return on invested capital excluding goodwill (ROIC excluding goowill) | E17: =E69*(1-Macro!H17)/AVERAGE('Ratio''s'!D95-D76,E95-E76) -> 0.13319989 | F17: =F69*(1-Macro!I17)/AVERAGE('Ratio''s'!E95-E76,F95-F76) -> 0.09628591 | G17: =G69*(1-Macro!J17)/AVERAGE('Ratio''s'!F95-F76,G95-G76) -> -0.081957795 | H17: =H69*(1-Macro!K17)/AVERAGE('Ratio''s'!G95-G76,H95-H76) -> 0.056638827 | I17: =I69*(1-Macro!L17)/AVERAGE('Ratio''s'!H95-H76,I95-I76) -> 0.097650503 | J17: =J69*(1-Macro!M17)/AVERAGE('Ratio''s'!I95-I76,J95-J76) -> 0.11216469 | K17: =K69*(1-Macro!N17)/AVERAGE('Ratio''s'!J95-J76,K95-K76) -> 0.1120206
B19: Net working capital
B20: Operaing NWC as a % net sales | D20: =ABS(D80/D60) -> 0.25773196 | E20: =ABS(E80/E60) -> 0.26157764 | F20: =ABS(F80/F60) -> 0.27875592 | G20: =ABS(G80/G60) -> 0.37985058 | H20: =ABS(H80/H60) -> 0.35253395 | I20: =ABS(I80/I60) -> 0.38516922 | J20: =ABS(J80/J60) -> 0.36127234 | K20: =ABS(K80/K60) -> 0.32494682
B22: Inventory days | D22: =ABS(D81/D61)*365 -> 53.256168 | E22: =ABS(E81/E61)*365 -> 51.003874 | F22: =ABS(F81/F61)*365 -> 51.632403 | G22: =ABS(G81/G61)*365 -> 65.335788 | H22: =ABS(H81/H61)*365 -> 52.240972 | I22: =ABS(I81/I61)*365 -> 60.697493 | J22: =ABS(J81/J61)*365 -> 47.013001 | K22: =ABS(K81/K61)*365 -> 48.287525
B23: Trade and other receivables days - Automotive | D23: =(D83/'Main Financials'!G32)*365 -> 39.306015 | E23: =(E83/'Main Financials'!H32)*365 -> 36.784157 | F23: =(F83/'Main Financials'!I32)*365 -> 39.670683 | G23: =(G83/'Main Financials'!J32)*365 -> 46.11541 | H23: =(H83/'Main Financials'!K32)*365 -> 40.199306 | I23: =(I83/'Main Financials'!L32)*365 -> 43.126899 | J23: =(J83/'Main Financials'!M32)*365 -> 42.806957 | K23: =(K83/'Main Financials'!N32)*365 -> 44.339852
B24: Trade and other accounts payable days | D24: =(D87/D61)*365 -> 83.351626 | E24: =(E87/E61)*365 -> 82.461613 | F24: =(F87/F61)*365 -> 85.595448 | G24: =(G87/G61)*365 -> 95.883744 | H24: =(H87/H61)*365 -> 86.941101 | I24: =(I87/I61)*365 -> 97.8635 | J24: =(J87/J61)*365 -> 76.047634 | K24: =(K87/K61)*365 -> 86.622593
B25: Trade and other accounts payable days (as a % of net sales) | D25: =(ABS(D87/D60))*365 -> 64.476867 | E25: =(ABS(E87/E60))*365 -> 63.554719 | F25: =(ABS(F87/F60))*365 -> 66.570798 | G25: =(ABS(G87/G60))*365 -> 73.64597 | H25: =(ABS(H87/H60))*365 -> 66.763188 | I25: =(ABS(I87/I60))*365 -> 66.129745 | J25: =(ABS(J87/J60))*365 -> 55.506816 | K25: =(ABS(K87/K60))*365 -> 63.669885
B27: Capital reinvestments
B28: Reinvestment in tangibles as a % of net sales | D28: =ABS(D152/D60) -> 0.052652231 | E28: =ABS(E152/E60) -> 0.058987323 | F28: =ABS(F152/F60) -> 0.079334564 | G28: =ABS(G152/G60) -> 0.087050851 | H28: =ABS(H152/H60) -> 0.039816514 | I28: =ABS(I152/I60) -> 0.03511457 | J28: =ABS(J152/J60) -> 0.043206812 | K28: =ABS(K152/K60) -> 0.045756864
B29: Reinvestment in tangibles as a % of BOP tangibles | D29: =ABS(D152/D134) -> 0.21811733 | E29: =ABS(E152/E134) -> 0.22607597 | F29: =ABS(F152/F134) -> 0.29138702 | G29: =ABS(G152/G134) -> 0.21130178 | H29: =ABS(H152/H134) -> 0.1013131 | I29: =ABS(I152/I134) -> 0.10076081 | J29: =ABS(J152/J134) -> 0.19333618 | K29: =ABS(K152/K134) -> 0.21002367
B31: Reinvestment in intangibles and goodwill as a % of net sales | D31: =ABS(D153/D60) -> 0.023293975 | E31: =ABS(E153/E60) -> 0.032461347 | F31: =ABS(F153/F60) -> 0.039705351 | G31: =ABS(G153/G60) -> 0.036565745 | H31: =ABS(H153/H60) -> 0.026788991 | I31: =ABS(I153/I60) -> 0.030889612 | J31: =ABS(J153/J60) -> 0.026042462 | K31: =ABS(K153/K60) -> 0.026675203
B32: Reinvestment in intangibles and goodwill as a % of BOP intangibles and goodwill | D32: =ABS(D153/D142) -> 0.24662717 | E32: =ABS(E153/E142) -> 0.30872373 | F32: =ABS(F153/F142) -> 0.32011782 | G32: =ABS(G153/G142) -> 0.2158584 | H32: =ABS(H153/H142) -> 0.18402395 | I32: =ABS(I153/I142) -> 0.22397624 | J32: =ABS(J153/J142) -> 0.29021277 | K32: =ABS(K153/K142) -> 0.32425422
B34: Depreciation as a % of net sales | D34: =ABS(SUM(D65:D66)/D60) -> 0.038110562 | E34: =ABS(SUM(E65:E66)/E60) -> 0.043658966 | F34: =ABS(SUM(F65:F66)/F60) -> 0.048518187 | G34: =ABS(SUM(G65:G66)/G60) -> 0.069938082 | H34: =ABS(SUM(H65:H66)/H60) -> 0.064036697 | I34: =ABS(SUM(I65:I66)/I60) -> 0.075919898 | J34: =ABS(SUM(J65:J66)/J60) -> 0.037192607 | K34: =ABS(SUM(K65:K66)/K60) -> 0.037700953
B35: Depreciation as a % of BOP tangibles | D35: =ABS(SUM(D65:D66)/D134) -> 0.15787696 | E35: =ABS(SUM(E65:E66)/E134) -> 0.16732821 | F35: =ABS(SUM(F65:F66)/F134) -> 0.1782019 | G35: =ABS(SUM(G65:G66)/G134) -> 0.16976331 | H35: =ABS(SUM(H65:H66)/H134) -> 0.16294135 | I35: =ABS(SUM(I65:I66)/I134) -> 0.21785118 | J35: =ABS(SUM(J65:J66)/J134) -> 0.1664246 | K35: =ABS(SUM(K65:K66)/K134) -> 0.1730471
B37: Amortization as a % of net sales | D37: =ABS(D68/D60) -> 0.017140513 | E37: =ABS(E68/E60) -> 0.017403092 | F37: =ABS(F68/F60) -> 0.023906961 | G37: =ABS(G68/G60) -> 0.045829067 | H37: =ABS(H68/H60) -> 0.028738532 | I37: =ABS(I68/I60) -> 0.049039684 | J37: =ABS(J68/J60) -> 0.023617687 | K37: =ABS(K68/K60) -> 0.018637075
B38: Amortization as a% of BOP intangibles | D38: =ABS(D68/D142) -> 0.18147681 | E38: =ABS(E68/E142) -> 0.16551216 | F38: =ABS(F68/F142) -> 0.19274592 | G38: =ABS(G68/G142) -> 0.27054252 | H38: =ABS(H68/H142) -> 0.1974161 | I38: =ABS(I68/I142) -> 0.35557987 | J38: =ABS(J68/J142) -> 0.26319149 | K38: =ABS(K68/K142) -> 0.22654561
B40: Other operating ratios
B41: Other non-current assets (including trade receivables) as a % of net sales | D41: =ABS(D78/D60) -> 0.025594835 | E41: =ABS(E78/E60) -> 0.027203781 | F41: =ABS(F78/F60) -> 0.023297866 | G41: =ABS(G78/G60) -> 0.023304568 | H41: =ABS(H78/H60) -> 0.022155963 | I41: =ABS(I78/I60) -> 0.020219439 | J41: =ABS(J78/J60) -> 0.014968688 | K41: =ABS(K78/K60) -> 0.018725992
B43: Income tax liabilities (non-current + current) as a %net sales | D43: =ABS(D91/D60) -> 0.0043876859 | E43: =ABS(E91/E60) -> 0.0052942039 | F43: =ABS(F91/F60) -> 0.0042446276 | G43: =ABS(G91/G60) -> 0.0053873531 | H43: =ABS(H91/H60) -> 0.0061009174 | I43: =ABS(I91/I60) -> 0.0067254424 | J43: =ABS(J91/J60) -> 0.0068542844 | K43: =ABS(K91/K60) -> 0.0065798833
B44: Operating provisions (non-current + current) as a % of net sales | D44: =ABS(D92/D60) -> 0.04332394 | E44: =ABS(E92/E60) -> 0.048875211 | F44: =ABS(F92/F60) -> 0.051715934 | G44: =ABS(G92/G60) -> 0.075837356 | H44: =ABS(H92/H60) -> 0.070275229 | I44: =ABS(I92/I60) -> 0.057834494 | J44: =ABS(J92/J60) -> 0.049831984 | K44: =ABS(K92/K60) -> 0.046770522
B45: Trade and other accounts payable (non-current) as a % of net sales | D45: =ABS('Main Financials'!G210/D60) -> 0.028163236 | E45: =ABS('Main Financials'!H210/E60) -> 0.028797538 | F45: =ABS('Main Financials'!I210/F60) -> 0.033005311 | G45: =ABS('Main Financials'!J210/G60) -> 0.04107552 | H45: =ABS('Main Financials'!K210/H60) -> 0.033417431 | I45: =ABS('Main Financials'!L210/I60) -> 0.029574702 | J45: =ABS('Main Financials'!M210/J60) -> 0.017985337 | K45: =ABS('Main Financials'!N210/K60) -> 0.0153827
B46: Net deferred tax liabilities associated with operating ítems as a % of net sales | D46: =ABS(D90/D60) -> 0.018781436 | E46: =ABS(E90/E60) -> 0.026324467 | F46: =ABS(F90/F60) -> 0.032262977 | G46: =ABS(G90/G60) -> 0.034176783 | H46: =ABS(H90/H60) -> 0.034288991 | I46: =ABS(I90/I60) -> 0.032915867 | J46: =ABS(J90/J60) -> 0.026920727 | K46: =ABS(K90/K60) -> 0.022567222
B47: Net deferred tax liabilities associated with operating ítems as a % BOP operating capital | E47: =ABS(E90/D95) -> 0.071994855 | F47: =ABS(F90/E95) -> 0.081922246 | G47: =ABS(G90/F95) -> 0.062178464 | H47: =ABS(H90/G95) -> 0.062397664 | I47: =ABS(I90/H95) -> 0.063291453 | J47: =ABS(J90/I95) -> 0.068382252 | K47: =ABS(K90/J95) -> 0.058864459
B49: Capital structure
B50: (Adjusted) Debt / EBITDA | D50: =ABS(D124/D64) -> 1.4463121 | E50: =ABS(E124/E64) -> 1.4918722 | F50: =ABS(F124/F64) -> 1.9318978 | G50: =ABS(G124/G64) -> 6.314889 | H50: =ABS(H124/H64) -> 3.0933309 | I50: =ABS(I124/I64) -> 1.9150025 | J50: =ABS(J124/J64) -> 2.1880402 | K50: =ABS(K124/K64) -> 1.9582318
B51: (Adj. Debt - excess cash) / EBITDA | D51: =ABS((D124-D102)/D64) -> 1.4463121 | E51: =ABS((E124-E102)/E64) -> 1.4918722 | F51: =ABS((F124-F102)/F64) -> 1.9318978 | G51: =ABS((G124-G102)/G64) -> 5.6476994 | H51: =ABS((H124-H102)/H64) -> 2.6511997 | I51: =ABS((I124-I102)/I64) -> 1.7319503 | J51: =ABS((J124-J102)/J64) -> 2.1880402 | K51: =ABS((K124-K102)/K64) -> 1.8993055
B52: Book value of (adj.) debt/Total capital | D52: =ABS(D124/D128) -> 0.22470879 | E52: =ABS(E124/E128) -> 0.20421134 | F52: =ABS(F124/F128) -> 0.24675408 | G52: =ABS(G124/G128) -> 0.40639569 | H52: =ABS(H124/H128) -> 0.37640562 | I52: =ABS(I124/I128) -> 0.34185197 | J52: =ABS(J124/J128) -> 0.28821042 | K52: =ABS(K124/K128) -> 0.26566558
B53: Book value of debt/Book value of equity | D53: =ABS(D124/D114) -> 0.29240858 | E53: =ABS(E124/E114) -> 0.26093937 | F53: =ABS(F124/F114) -> 0.33485708 | G53: =ABS(G124/G114) -> 0.70026643 | H53: =ABS(H124/H114) -> 0.61628843 | I53: =ABS(I124/I114) -> 0.53278005 | J53: =ABS(J124/J114) -> 0.41691315 | K53: =ABS(K124/K114) -> 0.37124287
B55: Financial Data for Input
B57: Income Statement Adjusted and Reorganized
B58: All figures in EUR(€) millions unless stated | D58: ='Main Financials'!G6 -> 2017 | E58: ='Main Financials'!H6 -> 2018 | F58: ='Main Financials'!I6 -> 2019 | G58: ='Main Financials'!J6 -> 2020 | H58: ='Main Financials'!K6 -> 2021 | I58: ='Main Financials'!L6 -> 2022 | J58: ='Main Financials'!M6 -> 2023 | K58: ='Main Financials'!N6 -> 2024
D59: ='Main Financials'!G7 -> 2017 | E59: ='Main Financials'!H7 -> 2018 | F59: ='Main Financials'!I7 -> 2019 | G59: ='Main Financials'!J7 -> 2020 | H59: ='Main Financials'!K7 -> 2021 | I59: ='Main Financials'!L7 -> 2022 | J59: ='Main Financials'!M7 -> 2023 | K59: ='Main Financials'!N7 -> 2024
B60: ='Main Financials'!B8 -> Revenues | D60: ='Main Financials'!G8 -> 56066 | E60: ='Main Financials'!H8 -> 54588 | F60: ='Main Financials'!I8 -> 52537 | G60: ='Main Financials'!J8 -> 41022 | H60: ='Main Financials'!K8 -> 43600 | I60: ='Main Financials'!L8 -> 46391 | J60: ='Main Financials'!M8 -> 52376 | K60: ='Main Financials'!N8 -> 56232
B61: ='Main Financials'!B9 -> Cost of sales (excl. D&A exp.) | D61: ='Main Financials'!G9 -> -43370 | E61: ='Main Financials'!H9 -> -42072 | F61: ='Main Financials'!I9 -> -40860 | G61: ='Main Financials'!J9 -> -31508 | H61: ='Main Financials'!K9 -> -33481 | I61: ='Main Financials'!L9 -> -31348 | J61: ='Main Financials'!M9 -> -38229 | K61: ='Main Financials'!N9 -> -41332
B62: ='Main Financials'!B10 -> Gross profit | D62: ='Main Financials'!G10 -> 12696 | E62: ='Main Financials'!H10 -> 12516 | F62: ='Main Financials'!I10 -> 11677 | G62: ='Main Financials'!J10 -> 9514 | H62: ='Main Financials'!K10 -> 10119 | I62: ='Main Financials'!L10 -> 15043 | J62: ='Main Financials'!M10 -> 14147 | K62: ='Main Financials'!N10 -> 14900
B63: ='Main Financials'!B11 -> Total SGA + other operating expenses (excl. D&A) | D63: ='Main Financials'!G11 -> -5994.2932 | E63: ='Main Financials'!H11 -> -6298.7443 | F63: ='Main Financials'!I11 -> -5686 | G63: ='Main Financials'!J11 -> -6767 | H63: ='Main Financials'!K11 -> -4676 | I63: ='Main Financials'!L11 -> -7031 | J63: ='Main Financials'!M11 -> -8478 | K63: ='Main Financials'!N11 -> -9154
B64: ='Main Financials'!B12 -> EBITDA | D64: ='Main Financials'!G12 -> 6701.7068 | E64: ='Main Financials'!H12 -> 6217.2557 | F64: ='Main Financials'!I12 -> 5991 | G64: ='Main Financials'!J12 -> 2747 | H64: ='Main Financials'!K12 -> 5443 | I64: ='Main Financials'!L12 -> 8012 | J64: ='Main Financials'!M12 -> 5669 | K64: ='Main Financials'!N12 -> 5746
B65: ='Main Financials'!B13 -> Depreciation expenses | D65: ='Main Financials'!G13 -> -2061 | E65: ='Main Financials'!H13 -> -2294 | F65: ='Main Financials'!I13 -> -2549 | G65: ='Main Financials'!J13 -> -2869 | H65: ='Main Financials'!K13 -> -2792 | I65: ='Main Financials'!L13 -> -3522 | J65: ='Main Financials'!M13 -> -1948 | K65: ='Main Financials'!N13 -> -2120
B66: ='Main Financials'!B14 -> Depreciation on right-of-use assets (i.e., operating lease assets) | D66: ='Main Financials'!G14 -> -75.706794 | E66: ='Main Financials'!H14 -> -89.25565 | F66: ='Main Financials'!I14 -> 0 | G66: ='Main Financials'!J14 -> 0 | H66: ='Main Financials'!K14 -> 0 | I66: ='Main Financials'!L14 -> 0 | J66: ='Main Financials'!M14 -> 0 | K66: ='Main Financials'!N14 -> 0
B67: ='Main Financials'!B15 -> EBITA | D67: ='Main Financials'!G15 -> 4565 | E67: ='Main Financials'!H15 -> 3834 | F67: ='Main Financials'!I15 -> 3442 | G67: ='Main Financials'!J15 -> -122 | H67: ='Main Financials'!K15 -> 2651 | I67: ='Main Financials'!L15 -> 4490 | J67: ='Main Financials'!M15 -> 3721 | K67: ='Main Financials'!N15 -> 3626
B68: ='Main Financials'!B16 -> Amortization expenses | D68: ='Main Financials'!G16 -> -961 | E68: ='Main Financials'!H16 -> -950 | F68: ='Main Financials'!I16 -> -1256 | G68: ='Main Financials'!J16 -> -1880 | H68: ='Main Financials'!K16 -> -1253 | I68: ='Main Financials'!L16 -> -2275 | J68: ='Main Financials'!M16 -> -1237 | K68: ='Main Financials'!N16 -> -1048
B69: ='Main Financials'!B17 -> EBIT before non-recurring items | D69: ='Main Financials'!G17 -> 3604 | E69: ='Main Financials'!H17 -> 2884 | F69: ='Main Financials'!I17 -> 2186 | G69: ='Main Financials'!J17 -> -2002 | H69: ='Main Financials'!K17 -> 1398 | I69: ='Main Financials'!L17 -> 2215 | J69: ='Main Financials'!M17 -> 2484 | K69: ='Main Financials'!N17 -> 2578
B71: Balance Sheet Adjusted and Reorganized
B72: All figures in EUR(€) millions unless stated
D73: ='Main Financials'!G90 -> 2017 | E73: ='Main Financials'!H90 -> 2018 | F73: ='Main Financials'!I90 -> 2019 | G73: ='Main Financials'!J90 -> 2020 | H73: ='Main Financials'!K90 -> 2021 | I73: ='Main Financials'!L90 -> 2022 | J73: ='Main Financials'!M90 -> 2023 | K73: ='Main Financials'!N90 -> 2024
D74: ='Main Financials'!G91 -> 2017 | E74: ='Main Financials'!H91 -> 2018 | F74: ='Main Financials'!I91 -> 2019 | G74: ='Main Financials'!J91 -> 2020 | H74: ='Main Financials'!K91 -> 2021 | I74: ='Main Financials'!L91 -> 2022 | J74: ='Main Financials'!M91 -> 2023 | K74: ='Main Financials'!N91 -> 2024
B75: ='Main Financials'!B92 -> Operating fixed assets | D75: ='Main Financials'!G92 -> 20756.76 | E75: ='Main Financials'!H92 -> 22305.351 | F75: ='Main Financials'!I92 -> 25073 | G75: ='Main Financials'!J92 -> 24438 | H75: ='Main Financials'!K92 -> 23531 | I75: ='Main Financials'!L92 -> 17343 | J75: ='Main Financials'!M92 -> 17661 | K75: ='Main Financials'!N92 -> 20078
B76: ='Main Financials'!B93 -> Intangible assets and goodwill | D76: ='Main Financials'!G93 -> 5739.7596 | E76: ='Main Financials'!H93 -> 6516.3507 | F76: ='Main Financials'!I93 -> 6949 | G76: ='Main Financials'!J93 -> 6347 | H76: ='Main Financials'!K93 -> 6398 | I76: ='Main Financials'!L93 -> 4700 | J76: ='Main Financials'!M93 -> 4626 | K76: ='Main Financials'!N93 -> 5164
B77: ='Main Financials'!B94 -> Property, plant and equipment | D77: ='Main Financials'!G94 -> 13582 | E77: ='Main Financials'!H94 -> 14304 | F77: ='Main Financials'!I94 -> 16900 | G77: ='Main Financials'!J94 -> 17135 | H77: ='Main Financials'!K94 -> 16167 | I77: ='Main Financials'!L94 -> 11705 | J77: ='Main Financials'!M94 -> 12251 | K77: ='Main Financials'!N94 -> 13861
B78: ='Main Financials'!B95 -> Other non-current assets | D78: ='Main Financials'!G95 -> 1435 | E78: ='Main Financials'!H95 -> 1485 | F78: ='Main Financials'!I95 -> 1224 | G78: ='Main Financials'!J95 -> 956 | H78: ='Main Financials'!K95 -> 966 | I78: ='Main Financials'!L95 -> 938 | J78: ='Main Financials'!M95 -> 784 | K78: ='Main Financials'!N95 -> 1053
B80: ='Main Financials'!B97 -> Operating net working capital | D80: ='Main Financials'!G97 -> 14450 | E80: ='Main Financials'!H97 -> 14279 | F80: ='Main Financials'!I97 -> 14645 | G80: ='Main Financials'!J97 -> 15582.23 | H80: ='Main Financials'!K97 -> 15370.48 | I80: ='Main Financials'!L97 -> 17868.385 | J80: ='Main Financials'!M97 -> 18922 | K80: ='Main Financials'!N97 -> 18272.41
B81: ='Main Financials'!B98 -> Inventories | D81: ='Main Financials'!G98 -> 6328 | E81: ='Main Financials'!H98 -> 5879 | F81: ='Main Financials'!I98 -> 5780 | G81: ='Main Financials'!J98 -> 5640 | H81: ='Main Financials'!K98 -> 4792 | I81: ='Main Financials'!L98 -> 5213 | J81: ='Main Financials'!M98 -> 4924 | K81: ='Main Financials'!N98 -> 5468
B82: ='Main Financials'!B99 -> Sales financing recievables | D82: ='Main Financials'!G99 -> 39334 | E82: ='Main Financials'!H99 -> 42067 | F82: ='Main Financials'!I99 -> 45374 | G82: ='Main Financials'!J99 -> 40820 | H82: ='Main Financials'!K99 -> 39498 | I82: ='Main Financials'!L99 -> 44247 | J82: ='Main Financials'!M99 -> 49615 | K82: ='Main Financials'!N99 -> 54355
B83: ='Main Financials'!B100 -> Automotive recivable & other current assets (excl. tax and current tax due) | D83: ='Main Financials'!G100 -> 5767 | E83: ='Main Financials'!H100 -> 5178 | F83: ='Main Financials'!I100 -> 5340 | G83: ='Main Financials'!J100 -> 4784 | H83: ='Main Financials'!K100 -> 4476 | I83: ='Main Financials'!L100 -> 5095 | J83: ='Main Financials'!M100 -> 5647 | K83: ='Main Financials'!N100 -> 6137
B84: ='Main Financials'!B101 -> Derivatives of financing operations by the Automotive segment | D84: ='Main Financials'!G101 -> 263 | E84: ='Main Financials'!H101 -> 378 | F84: ='Main Financials'!I101 -> 216 | G84: ='Main Financials'!J101 -> 298 | H84: ='Main Financials'!K101 -> 181 | I84: ='Main Financials'!L101 -> 410 | J84: ='Main Financials'!M101 -> 119 | K84: ='Main Financials'!N101 -> 356
B85: ='Main Financials'!B102 -> Operating Cash | D85: ='Main Financials'!G102 -> 14057 | E85: ='Main Financials'!H102 -> 14777 | F85: ='Main Financials'!I102 -> 14982 | G85: ='Main Financials'!J102 -> 19864.23 | H85: ='Main Financials'!K102 -> 19521.48 | I85: ='Main Financials'!L102 -> 20307.385 | J85: ='Main Financials'!M102 -> 20677 | K85: ='Main Financials'!N102 -> 22203.41
B86: ='Main Financials'!B103 -> Sales financing debts | D86: ='Main Financials'!G103 -> -41395 | E86: ='Main Financials'!H103 -> -44495 | F86: ='Main Financials'!I103 -> -47465 | G86: ='Main Financials'!J103 -> -47547 | H86: ='Main Financials'!K103 -> -45123 | I86: ='Main Financials'!L103 -> -48999 | J86: ='Main Financials'!M103 -> -54095 | K86: ='Main Financials'!N103 -> -60438
B87: ='Main Financials'!B104 -> Trade payables (current) | D87: ='Main Financials'!G104 -> -9904 | E87: ='Main Financials'!H104 -> -9505 | F87: ='Main Financials'!I104 -> -9582 | G87: ='Main Financials'!J104 -> -8277 | H87: ='Main Financials'!K104 -> -7975 | I87: ='Main Financials'!L104 -> -8405 | J87: ='Main Financials'!M104 -> -7965 | K87: ='Main Financials'!N104 -> -9809
... B103: ='Main Financials'!B120 -> Assets held for sale | D103: ='Main Financials'!G120 -> 0 | E103: ='Main Financials'!H120 -> 0 | F103: ='Main Financials'!I120 -> 0 | G103: ='Main Financials'!J120 -> 0 | H103: ='Main Financials'!K120 -> 129 | I103: ='Main Financials'!L120 -> 3861 | J103: ='Main Financials'!M120 -> 4022 | K103: ='Main Financials'!N120 -> 0
D104: ='Main Financials'!G121 -> 0 | E104: ='Main Financials'!H121 -> 0 | F104: ='Main Financials'!I121 -> 0 | G104: ='Main Financials'!J121 -> 0 | H104: ='Main Financials'!K121 -> 0 | I104: ='Main Financials'!L121 -> 0 | J104: ='Main Financials'!M121 -> 0 | K104: ='Main Financials'!N121 -> 0
B105: ='Main Financials'!B122 -> Non-operating liabilities | D105: ='Main Financials'!G122 -> -1198 | E105: ='Main Financials'!H122 -> -1117 | F105: ='Main Financials'!I122 -> -1208 | G105: ='Main Financials'!J122 -> -1252 | H105: ='Main Financials'!K122 -> -1341 | I105: ='Main Financials'!L122 -> -1765 | J105: ='Main Financials'!M122 -> -1854 | K105: ='Main Financials'!N122 -> -846
B106: ='Main Financials'!B123 -> Pension provisions (non-current + current) | D106: ='Main Financials'!G123 -> -1635 | E106: ='Main Financials'!H123 -> -1587 | F106: ='Main Financials'!I123 -> -1700 | G106: ='Main Financials'!J123 -> -1647 | H106: ='Main Financials'!K123 -> -1440 | I106: ='Main Financials'!L123 -> -1074 | J106: ='Main Financials'!M123 -> -1208 | K106: ='Main Financials'!N123 -> -1130
B107: ='Main Financials'!B124 -> Liabilities related to assets held for sales | D107: ='Main Financials'!G124 -> 0 | E107: ='Main Financials'!H124 -> 0 | F107: ='Main Financials'!I124 -> 0 | G107: ='Main Financials'!J124 -> 0 | H107: ='Main Financials'!K124 -> -182 | I107: ='Main Financials'!L124 -> -873 | J107: ='Main Financials'!M124 -> -1075 | K107: ='Main Financials'!N124 -> 0
B108: ='Main Financials'!B125 -> Net deferred tax liabilities with non-operating items | D108: ='Main Financials'!G125 -> 437 | E108: ='Main Financials'!H125 -> 470 | F108: ='Main Financials'!I125 -> 492 | G108: ='Main Financials'!J125 -> 395 | H108: ='Main Financials'!K125 -> 281 | I108: ='Main Financials'!L125 -> 182 | J108: ='Main Financials'!M125 -> 429 | K108: ='Main Financials'!N125 -> 284
D109: ='Main Financials'!G126 -> 0 | E109: ='Main Financials'!H126 -> 0 | F109: ='Main Financials'!I126 -> 0 | G109: ='Main Financials'!J126 -> 0 | H109: ='Main Financials'!K126 -> 0 | I109: ='Main Financials'!L126 -> 0 | J109: ='Main Financials'!M126 -> 0 | K109: ='Main Financials'!N126 -> 0
B110: ='Main Financials'!B127 -> Total capital | D110: ='Main Financials'!G127 -> 43134.76 | E110: ='Main Financials'!H127 -> 45420.351 | F110: ='Main Financials'!I127 -> 46905 | G110: ='Main Financials'!J127 -> 42685 | H110: ='Main Financials'!K127 -> 44731 | I110: ='Main Financials'!L127 -> 44882 | J110: ='Main Financials'!M127 -> 43038 | K110: ='Main Financials'!N127 -> 42354
D111: ='Main Financials'!G128 -> 0 | E111: ='Main Financials'!H128 -> 0 | F111: ='Main Financials'!I128 -> 0 | G111: ='Main Financials'!J128 -> 0 | H111: ='Main Financials'!K128 -> 0 | I111: ='Main Financials'!L128 -> 0 | J111: ='Main Financials'!M128 -> 0 | K111: ='Main Financials'!N128 -> 0
B112: ='Main Financials'!B129 -> Equity & other financial liabilities
B113: ='Main Financials'!B130 -> Equity | D113: ='Main Financials'!G130 -> 33442 | E113: ='Main Financials'!H130 -> 36145 | F113: ='Main Financials'!I130 -> 35331 | G113: ='Main Financials'!J130 -> 25338 | H113: ='Main Financials'!K130 -> 27894 | I113: ='Main Financials'!L130 -> 29539 | J113: ='Main Financials'!M130 -> 30634 | K113: ='Main Financials'!N130 -> 31102
B114: ='Main Financials'!B131 -> Shareholders' equity - parent-company shareholders' share | D114: ='Main Financials'!G131 -> 33148 | E114: ='Main Financials'!H131 -> 35546 | F114: ='Main Financials'!I131 -> 34564 | G114: ='Main Financials'!J131 -> 24772 | H114: ='Main Financials'!K131 -> 27320 | I114: ='Main Financials'!L131 -> 28798 | J114: ='Main Financials'!M131 -> 29752 | K114: ='Main Financials'!N131 -> 30309
B115: ='Main Financials'!B132 -> Share capital | D115: ='Main Financials'!G132 -> 1127 | E115: ='Main Financials'!H132 -> 1127 | F115: ='Main Financials'!I132 -> 1127 | G115: ='Main Financials'!J132 -> 1127 | H115: ='Main Financials'!K132 -> 1127 | I115: ='Main Financials'!L132 -> 1127 | J115: ='Main Financials'!M132 -> 1127 | K115: ='Main Financials'!N132 -> 1127
B116: ='Main Financials'!B133 -> Share premium | D116: ='Main Financials'!G133 -> 3785 | E116: ='Main Financials'!H133 -> 3785 | F116: ='Main Financials'!I133 -> 3785 | G116: ='Main Financials'!J133 -> 3785 | H116: ='Main Financials'!K133 -> 3785 | I116: ='Main Financials'!L133 -> 3785 | J116: ='Main Financials'!M133 -> 3785 | K116: ='Main Financials'!N133 -> 3785
B117: ='Main Financials'!B134 -> Treasury shares | D117: ='Main Financials'!G134 -> -494 | E117: ='Main Financials'!H134 -> -400 | F117: ='Main Financials'!I134 -> -344 | G117: ='Main Financials'!J134 -> -284 | H117: ='Main Financials'!K134 -> -237 | I117: ='Main Financials'!L134 -> -208 | J117: ='Main Financials'!M134 -> -212 | K117: ='Main Financials'!N134 -> -281
B118: ='Main Financials'!B135 -> Revaluation of financial instruments | D118: ='Main Financials'!G135 -> 809 | E118: ='Main Financials'!H135 -> 236 | F118: ='Main Financials'!I135 -> 232 | G118: ='Main Financials'!J135 -> 384 | H118: ='Main Financials'!K135 -> 5 | I118: ='Main Financials'!L135 -> 208 | J118: ='Main Financials'!M135 -> -111 | K118: ='Main Financials'!N135 -> -93
B119: ='Main Financials'!B136 -> Translation adjustment | D119: ='Main Financials'!G136 -> -3376 | E119: ='Main Financials'!H136 -> -2826 | F119: ='Main Financials'!I136 -> -2584 | G119: ='Main Financials'!J136 -> -4108 | H119: ='Main Financials'!K136 -> -3407 | I119: ='Main Financials'!L136 -> -2146 | J119: ='Main Financials'!M136 -> -3140 | K119: ='Main Financials'!N136 -> -2833
B120: ='Main Financials'!B137 -> Reserves | D120: ='Main Financials'!G137 -> 26183 | E120: ='Main Financials'!H137 -> 30322 | F120: ='Main Financials'!I137 -> 32489 | G120: ='Main Financials'!J137 -> 31876 | H120: ='Main Financials'!K137 -> 25159 | I120: ='Main Financials'!L137 -> 26370 | J120: ='Main Financials'!M137 -> 26105 | K120: ='Main Financials'!N137 -> 27852
B121: ='Main Financials'!B138 -> Net income - parent-company shareholders' share | D121: ='Main Financials'!G138 -> 5114 | E121: ='Main Financials'!H138 -> 3302 | F121: ='Main Financials'!I138 -> -141 | G121: ='Main Financials'!J138 -> -8008 | H121: ='Main Financials'!K138 -> 888 | I121: ='Main Financials'!L138 -> -338 | J121: ='Main Financials'!M138 -> 2198 | K121: ='Main Financials'!N138 -> 752
B122: ='Main Financials'!B139 -> Shareholders' equity - non-controlling interests' share | D122: ='Main Financials'!G139 -> 294 | E122: ='Main Financials'!H139 -> 599 | F122: ='Main Financials'!I139 -> 767 | G122: ='Main Financials'!J139 -> 566 | H122: ='Main Financials'!K139 -> 574 | I122: ='Main Financials'!L139 -> 741 | J122: ='Main Financials'!M139 -> 882 | K122: ='Main Financials'!N139 -> 793
D123: ='Main Financials'!G140 -> 0 | E123: ='Main Financials'!H140 -> 0 | F123: ='Main Financials'!I140 -> 0 | G123: ='Main Financials'!J140 -> 0 | H123: ='Main Financials'!K140 -> 0 | I123: ='Main Financials'!L140 -> 0 | J123: ='Main Financials'!M140 -> 0 | K123: ='Main Financials'!N140 -> 0
B124: ='Main Financials'!B141 -> Other financial liabilities | D124: ='Main Financials'!G141 -> 9692.7596 | E124: ='Main Financials'!H141 -> 9275.3507 | F124: ='Main Financials'!I141 -> 11574 | G124: ='Main Financials'!J141 -> 17347 | H124: ='Main Financials'!K141 -> 16837 | I124: ='Main Financials'!L141 -> 15343 | J124: ='Main Financials'!M141 -> 12404 | K124: ='Main Financials'!N141 -> 11252
B125: ='Main Financials'!B142 -> Financial liabilities (non-current + current) | D125: ='Main Financials'!G142 -> 9692.7596 | E125: ='Main Financials'!H142 -> 9275.3507 | F125: ='Main Financials'!I142 -> 11574 | G125: ='Main Financials'!J142 -> 17347 | H125: ='Main Financials'!K142 -> 16837 | I125: ='Main Financials'!L142 -> 15343 | J125: ='Main Financials'!M142 -> 12404 | K125: ='Main Financials'!N142 -> 11252
B128: ='Main Financials'!B145 -> Total capital | D128: ='Main Financials'!G145 -> 43134.76 | E128: ='Main Financials'!H145 -> 45420.351 | F128: ='Main Financials'!I145 -> 46905 | G128: ='Main Financials'!J145 -> 42685 | H128: ='Main Financials'!K145 -> 44731 | I128: ='Main Financials'!L145 -> 44882 | J128: ='Main Financials'!M145 -> 43038 | K128: ='Main Financials'!N145 -> 42354
B130: Fixed Assets
B131: All figures in EUR(€) millions unless stated
D132: ='Main Financials'!G408 -> 2017 | E132: ='Main Financials'!H408 -> 2018 | F132: ='Main Financials'!I408 -> 2019 | G132: ='Main Financials'!J408 -> 2020 | H132: ='Main Financials'!K408 -> 2021 | I132: ='Main Financials'!L408 -> 2022 | J132: ='Main Financials'!M408 -> 2023 | K132: ='Main Financials'!N408 -> 2024
B133: Property plan and equipment | D133: ='Main Financials'!G409 -> 2017 | E133: ='Main Financials'!H409 -> 2018 | F133: ='Main Financials'!I409 -> 2019 | G133: ='Main Financials'!J409 -> 2020 | H133: ='Main Financials'!K409 -> 2021 | I133: ='Main Financials'!L409 -> 2022 | J133: ='Main Financials'!M409 -> 2023 | K133: ='Main Financials'!N409 -> 2024
B134: ='Main Financials'!B410 -> Beginning of period | D134: ='Main Financials'!G410 -> 13534 | E134: ='Main Financials'!H410 -> 14243 | F134: ='Main Financials'!I410 -> 14304 | G134: ='Main Financials'!J410 -> 16900 | H134: ='Main Financials'!K410 -> 17135 | I134: ='Main Financials'!L410 -> 16167 | J134: ='Main Financials'!M410 -> 11705 | K134: ='Main Financials'!N410 -> 12251
...

Sheet Peer Group>>>

Sheet Stellantis
B2: Company Data Inputs
B4: FactSet Inputs | E4: Reporting Information
B5: Name | C5: Stellantis | E5: Last FY | F5: 2024 | H5: Last Quarter | I5: 2
B6: Identifier | C6: STLAM-IT | E6: Ended | F6: 12/31/2024 | H6: Ended | I6: 45838
B7: Start Date | C7: -7
B8: End Date | C8: 0 | E8: Date | F8: 45962
B9: Report Basis | C9: ANN_R | E9: €/Share | F9: 8.778
B10: Currency | C10: EUR
B13: Key Financial Items and Forecast
B14: All values in € (FactSet currency adjusted) million except for shares outstanding in millions.
E15: 2017 | F15: 2018 | G15: 2019 | H15: 2020 | I15: 2021 | J15: 2022 | K15: 2023 | L15: 2024 | M15: 2025 | N15: 2026 | O15: 2027 | P15: 2028 | R15: Current Q
B16: Revenue | E16: 105730 | F16: 110412 | G16: 108187 | H16: 47656 | I16: 149419 | J16: 179592 | K16: 189544 | L16: 156878 | M16: 152552.69 | N16: 160481.22 | O16: 166401.67 | P16: 175903.67
B17: COGS | E17: 91004 | F17: 96467 | G17: 94522 | H17: 39072 | I17: 121518 | J17: 146216 | K17: 153593 | L17: 138509 | M17: 141293.67 | N17: 145042 | O17: 146393.95 | P17: 152166
B18: EBITDA | E18: 11414 | F18: 10539 | G18: 10401 | H18: 5628 | I18: 21730 | J18: 27881 | K18: 30533 | L18: 12661 | M18: 8945.5205 | N18: 13659.609 | O18: 16062.637 | P18: 18389.607
B19: D&A | E19: 5474 | F19: 5507 | G19: 5445 | H19: 2376 | I19: 5871 | J19: 6797 | K19: 7549 | L19: 7226 | M19: 7130.467 | N19: 7387.1 | O19: 7648.7285 | P19: 8600.5
B20: EBIT | E20: 5940 | F20: 5032 | G20: 4956 | H20: 3252 | I20: 15859 | J20: 21084 | K20: 22984 | L20: 5435 | M20: 2720.6702 | N20: 6286.8486 | O20: 8583.423 | P20: 8843
B21: Taxes | E21: 2588 | F21: 778 | G21: 1321 | H21: 504 | I21: 1911 | J21: 2729 | K21: 3793 | L21: -1488 | M21: -367.99124 | N21: 916.8716 | O21: 1602.1273 | P21: 1457.5
B22: Net Income | E22: 3281 | F22: 3323 | G22: 2694 | H22: 2488 | I22: 13210 | J22: 16799 | K22: 18596 | L22: 5473 | M22: 2086.0842 | N22: 4879.009 | O22: 6472.0327 | P22: 6979
B24: Free Cash Flow | E24: 2280 | F24: 4556 | G24: 2077 | H24: 3291 | I24: 8533 | J24: 10945 | K24: 12292 | L24: -7052 | M24: -4564.9575 | N24: 1483.3606 | O24: 3114.2896 | P24: 5879.7593 | R24: -8658
B26: Cash and ST Investments | E26: 13125 | F26: 13065 | G26: 15684 | H26: 23828 | I26: 51467 | J26: 50287 | K26: 48476 | L26: 37184 | R26: 32836
B27: Total Debt | E27: 17971 | F27: 14528 | G27: 12901 | H27: 13703 | I27: 33582 | J27: 27153 | K27: 29463 | L27: 37227 | R27: 40799
B29: Total Common Stock FD | R29: 2888.724
B30: ROE (LTM) | R30: -0.05829118
B31: ROIC (LTM) | R31: 0.01005186
B33: Source: FactSet Standardized Financials

Sheet Nissan
B2: Company Data Inputs
B4: FactSet Inputs | E4: Reporting Information
B5: Name | C5: Nissan | E5: Last FY | F5: 2024 | H5: Last Quarter | I5: 2
B6: Identifier | C6: 7201-JP | E6: Ended | F6: 03/31/2025 | H6: Ended | I6: 09/30/2025
B7: Start Date | C7: -7
B8: End Date | C8: 0 | E8: Date | F8: 45962
B9: Report Basis | C9: ANN_R | E9: €/Share | F9: 1.9880741
B10: Currency | C10: EUR
B13: Key Financial Items and Forecast
B14: All values in € (FactSet currency adjusted) million except for shares outstanding in millions.
E15: 2017 | F15: 2018 | G15: 2019 | H15: 2020 | I15: 2021 | J15: 2022 | K15: 2023 | L15: 2024 | M15: 2025 | N15: 2026 | O15: 2027 | P15: 2028 | R15: Current Q
B16: Revenue | E16: 92272.615 | F16: 90177.566 | G16: 81781.882 | H16: 63620.807 | I16: 64551.714 | J16: 75189.608 | K16: 80913.628 | L16: 77189.784 | M16: 66804.76 | N16: 68423.05 | O16: 69745.555 | P16: 73847.02
B17: COGS | E17: 76196.491 | F17: 75786.846 | G17: 70433.633 | H17: 55564.759 | I17: 54616.283 | J17: 63452.248 | K17: 68140.016 | L17: 67273.616 | M17: 60348.582 | N17: 61463.797 | O17: 62330.297 | P17: 64030.965
B18: EBITDA | E18: 11311.346 | F18: 9496.5921 | G18: 6847.3449 | H18: 4524.1201 | I18: 7182.1208 | J18: 7607.6519 | K18: 7959.5955 | L18: 4691.5539 | M18: 1382.472 | N18: 2853.257 | O18: 3462.0366 | P18: 4690.603
B19: D&A | E19: 6873.7378 | F19: 7017.2372 | G19: 7182.3663 | H19: 5743.1281 | I19: 5287.1799 | J19: 4931.848 | K19: 4332.1269 | L19: 4265.0834 | M19: 2207.3872 | N19: 2288.666 | O19: 2344.5256 | P19: 2091.009
B20: EBIT | E20: 4437.6084 | F20: 2479.3549 | G20: -335.02134 | H20: -1219.008 | I20: 1894.9409 | J20: 2675.8039 | K20: 3627.4686 | L20: 426.47045 | M20: -1043.1133 | N20: 409.94443 | O20: 1159.4227 | P20: 1587.6959
B21: Taxes | E21: -408.53854 | F21: 1057.9939 | G21: 771.18902 | H21: 749.24193 | I21: 1114.4052 | J21: 1144.0687 | K21: 954.66313 | L21: 1505.9299 | M21: 128.6108 | N21: 361.9056 | O21: 408.1405 | P21: 495.23898
B22: Net Income | E22: 5766.6056 | F22: 2486.4761 | G22: -5556.6406 | H22: -3630.6778 | I22: 1651.4789 | J22: 1574.5073 | K22: 2721.3063 | L22: -4099.2317 | M22: -1686.8341 | N22: 75.53421 | O22: 773.1631 | P22: 1054.753
B24: Free Cash Flow | E24: -5853.2021 | F24: -2106.6149 | G24: -3255.218 | H24: 1136.7407 | I24: -2120.1513 | J24: 621.2102 | K24: -4253.5714 | L24: -7075.7876 | M24: -3121.3655 | N24: -105.39995 | O24: 460.951 | P24: 3012.166 | R24: -1793.4639
B26: Cash and ST Investments | E26: 9220.6393 | F26: 10935.219 | G26: 13870.247 | H26: 15661.938 | I26: 13274.491 | J26: 13931.175 | K26: 13044.139 | L26: 13604.104 | R26: 13094.437
B27: Total Debt | E27: 59162.804 | F27: 64608.262 | G27: 66760.136 | H27: 58513.853 | I27: 52813.294 | J27: 48681.023 | K27: 47788.891 | L27: 50143.662 | R27: 51122.825
B29: Total Common Stock FD | R29: 3495.7389
B30: ROE (LTM) | R30: -0.17337875
B31: ROIC (LTM) | R31: -0.088023497
B33: Source: FactSet Standardized Financials

Sheet Volkswagen
B2: Company Data Inputs
B4: FactSet Inputs | E4: Reporting Information
B5: Name | C5: Volkswagen | E5: Last FY | F5: 2024 | H5: Last Quarter | I5: 3
B6: Identifier | C6: VOW-DE | E6: Ended | F6: 12/31/2024 | H6: Ended | I6: 09/30/2025
B7: Start Date | C7: -7
B8: End Date | C8: 0 | E8: Date | F8: 45962
B9: Report Basis | C9: ANN_R | E9: €/Share | F9: 91.35
B10: Currency | C10: EUR
B13: Key Financial Items and Forecast
B14: All values in € (FactSet currency adjusted) million except for shares outstanding in millions.
E15: 2017 | F15: 2018 | G15: 2019 | H15: 2020 | I15: 2021 | J15: 2022 | K15: 2023 | L15: 2024 | M15: 2025 | N15: 2026 | O15: 2027 | P15: 2028 | R15: Current Q
B16: Revenue | E16: 229550 | F16: 235849 | G16: 252632 | H16: 222884 | I16: 250200 | J16: 279050 | K16: 322284 | L16: 324656 | M16: 324823.84 | N16: 331772.66 | O16: 340765.84 | P16: 348319.9
B17: COGS | E17: 184816 | F17: 188335 | G17: 203317 | H17: 183758 | I17: 203139 | J17: 226480 | K17: 260256 | L17: 263621 | M17: 259587.75 | N17: 253605.75 | O17: 270546.5 | P17: 279929
B18: EBITDA | E18: 36857 | F18: 39612 | G18: 42748 | H18: 36111 | I18: 45454 | J18: 44466 | K18: 54079 | L18: 54320 | M18: 38573.105 | N18: 46299.426 | O18: 50404.945 | P18: 49948.914
B19: D&A | E19: 20926 | F19: 21495 | G19: 24390 | H19: 25732 | I19: 27263 | J19: 28230 | K19: 26761 | L19: 29929 | M19: 27499.256 | N19: 26700.8 | O19: 27464.738 | P19: 22816.5
B20: EBIT | E20: 15931 | F20: 18117 | G20: 18358 | H20: 10379 | I20: 18191 | J20: 16236 | K20: 27318 | L20: 24391 | M20: 9667.638 | N20: 17560.557 | O20: 20718.305 | P20: 23554.36
B21: Taxes | E21: 2210 | F21: 3490 | G21: 4327 | H21: 2843 | I21: 4698 | J21: 6218 | K21: 5238 | L21: 4412 | M21: 2315.4128 | N21: 4626.1943 | O21: 5419.217 | P21: 6138
B22: Net Income | E22: 11179 | F22: 11827 | G22: 13346 | H22: 8334 | I22: 14843 | J22: 14881 | K22: 15946 | L22: 10721 | M22: 4917.487 | N22: 10889.342 | O22: 13216.16 | P22: 15885.937
B24: Free Cash Flow | E24: -14237 | F24: -6457 | G24: -1418 | H24: 7155 | I24: 20135 | J24: 5825 | K24: -6439 | L24: -10295 | M24: 1503.4125 | N24: 5282.5234 | O24: 8102.409 | P24: 9952.663 | R24: 1263
B26: Cash and ST Investments | E26: 37241 | F26: 48065 | G26: 42692 | H26: 55071 | I26: 62255 | J26: 66378 | K26: 70221 | L26: 67622 | R26: 65550
B27: Total Debt | E27: 174560 | F27: 203479 | G27: 214131 | H27: 219170 | I27: 224641 | J27: 219306 | K27: 247954 | L27: 267971 | R27: 271470
B29: Total Common Stock FD | R29: 501.29526
B30: ROE (LTM) | R30: 0.040037059
B31: ROIC (LTM) | R31: 0.021366767
B33: Source: FactSet Standardized Financials

Sheet BMW
B2: Company Data Inputs
B4: FactSet Inputs | E4: Reporting Information
B5: Name | C5: BMW | E5: Last FY | F5: 2024 | H5: Last Quarter | I5: 3
B6: Identifier | C6: BMW-DE | E6: Ended | F6: 12/31/2024 | H6: Ended | I6: 09/30/2025
B7: Start Date | C7: -7
B8: End Date | C8: 0 | E8: Date | F8: 45962
B9: Report Basis | C9: ANN_R | E9: €/Share | F9: 80.72
B10: Currency | C10: EUR
B13: Key Financial Items and Forecast
B14: All values in € (FactSet currency adjusted) million except for shares outstanding in millions.
E15: 2017 | F15: 2018 | G15: 2019 | H15: 2020 | I15: 2021 | J15: 2022 | K15: 2023 | L15: 2024 | M15: 2025 | N15: 2026 | O15: 2027 | P15: 2028 | R15: Current Q
B16: Revenue | E16: 98282 | F16: 96855 | G16: 104210 | H16: 98990 | I16: 111239 | J16: 142610 | K16: 155498 | L16: 142380 | M16: 138715.39 | N16: 142726.48 | O16: 147509.86 | P16: 151737.19
B17: COGS | E17: 73409 | F17: 73157 | G17: 80195 | H17: 79719 | I17: 82954 | J17: 111418 | K17: 118271 | L17: 111843 | M17: 113391.57 | N17: 114671.71 | O17: 118492.95 | P17: 120825
B18: EBITDA | E18: 18385 | F18: 17401 | G18: 17981 | H18: 11004 | I18: 19939 | J18: 22551 | K18: 27466 | L18: 20239 | M18: 19217.615 | N18: 20805.014 | O18: 22766.3 | P18: 21656.938
B19: D&A | E19: 8455 | F19: 8601 | G19: 10749 | H19: 6143 | I19: 6495 | J19: 8566 | K19: 8974 | L19: 8650 | M19: 9871.21 | N19: 10231.11 | O19: 10821.388 | P19: 12147.5
B20: EBIT | E20: 9930 | F20: 8800 | G20: 7232 | H20: 4861 | I20: 13444 | J20: 13985 | K20: 18492 | L20: 11589 | M20: 10039.378 | N20: 10719.96 | O20: 12163.138 | P20: 13251.419
B21: Taxes | E21: 2000 | F21: 2530 | G21: 2140 | H21: 1365 | I21: 3597 | J21: 4927 | K21: 4931 | L21: 3293 | M21: 2877.5354 | N21: 3067.6953 | O21: 3475.33 | P21: 3988
B22: Net Income | E22: 8589 | F22: 7007 | G22: 4871 | H22: 3775 | I22: 12382 | J22: 17941 | K22: 11290 | L22: 7290 | M22: 6489.721 | N22: 6961.953 | O22: 7871.975 | P22: 8768.83
B24: Free Cash Flow | E24: -1368 | F24: -2862 | G24: -3439 | H24: 6826 | I24: 9067 | J24: 14251 | K24: 6475 | L24: -4835 | M24: 3839.6692 | N24: 5261.009 | O24: 5685.784 | P24: 7093.672 | R24: -839
B26: Cash and ST Investments | E26: 9039 | F26: 10979 | G26: 12036 | H26: 13537 | I26: 16009 | J26: 16870 | K26: 17327 | L26: 19287 | R26: 19257
B27: Total Debt | E27: 78854 | F27: 86357 | G27: 113317 | H27: 104048 | I27: 100435 | J27: 88072 | K27: 89564 | L27: 104943 | R27: 107748
B29: Total Common Stock FD | R29: 609.81512
B30: ROE (LTM) | R30: 0.076269943
B31: ROIC (LTM) | R31: 0.045064564
B33: Source: FactSet Standardized Financials

Sheet MercedesBenz
B2: Company Data Inputs
B4: FactSet Inputs | E4: Reporting Information
B5: Name | C5: Mercedes-Benz | E5: Last FY | F5: 2024 | H5: Last Quarter | I5: 3
B6: Identifier | C6: MBG-DE | E6: Ended | F6: 12/31/2024 | H6: Ended | I6: 09/30/2025
B7: Start Date | C7: -7
B8: End Date | C8: 0 | E8: Date | F8: 45962
B9: Report Basis | C9: ANN_R | E9: €/Share | F9: 56.21
B10: Currency | C10: EUR
B13: Key Financial Items and Forecast
B14: All values in € (FactSet currency adjusted) million except for shares outstanding in millions.
E15: 2017 | F15: 2018 | G15: 2019 | H15: 2020 | I15: 2021 | J15: 2022 | K15: 2023 | L15: 2024 | M15: 2025 | N15: 2026 | O15: 2027 | P15: 2028 | R15: Current Q
B16: Revenue | E16: 164154 | F16: 167362 | G16: 172745 | H16: 121778 | I16: 133893 | J16: 150017 | K16: 152390 | L16: 145594 | M16: 134542.77 | N16: 135827.06 | O16: 140007.02 | P16: 143087.64
B17: COGS | E17: 129809 | F17: 134504 | G17: 143224 | H17: 100722 | I17: 103191 | J17: 115605 | K17: 117136 | L17: 116615 | M17: 106778.84 | N17: 106884.16 | O17: 113059.03 | P17: 116963.5
B18: EBITDA | E18: 25456 | F18: 24270 | G18: 28545 | H18: 23891 | I18: 18099 | J18: 29612 | K18: 29547 | L18: 24804 | M18: 14753.084 | N18: 16532.469 | O18: 18476.857 | P18: 21577.664
B19: D&A | E19: 13625 | F19: 14887 | G19: 16136 | H19: 17843 | I19: 15066 | J19: 13891 | K19: 13697 | L19: 14680 | M19: 8395.57 | N19: 7936.56 | O19: 8340.532 | P19: 10865.5
B20: EBIT | E20: 11831 | F20: 9383 | G20: 12409 | H20: 6048 | I20: 3033 | J20: 15721 | K20: 15850 | L20: 10124 | M20: 7220.623 | N20: 8871.206 | O20: 10437.339 | P20: 11410.503
B21: Taxes | E21: 3350 | F21: 3013 | G21: 1121 | H21: 1926 | I21: 4761 | J21: 5495 | K21: 5553 | L21: 3738 | M21: 1615.7935 | N21: 2512.7302 | O21: 2870.7139 | P21: 3396
B22: Net Income | E22: 10278 | F22: 7249 | G22: 2377 | H22: 3649 | I22: 10660 | J22: 14501 | K22: 14261 | L22: 10207 | M22: 5118.2974 | N22: 6663.537 | O22: 7813.5654 | P22: 8203.428
B24: Free Cash Flow | E24: -11810 | F24: -10358 | G24: 689 | H24: 16591 | I24: 19970 | J24: 13413 | K24: 10725 | L24: 13696 | M24: 5340.1396 | N24: 4707.801 | O24: 5821.9165 | P24: 4594.8984 | R24: 3589
B26: Cash and ST Investments | E26: 21145 | F26: 24708 | G26: 26768 | H26: 28404 | I26: 29826 | J26: 23916 | K26: 22121 | L26: 21597 | R26: 22496
B27: Total Debt | E27: 127124 | F27: 144902 | G27: 161780 | H27: 145842 | I27: 125843 | J27: 111837 | K27: 109431 | L27: 112798 | R27: 102343
B29: Total Common Stock FD | R29: 962.9037
B30: ROE (LTM) | R30: 0.068815547
B31: ROIC (LTM) | R31: 0.039276434
B33: Source: FactSet Standardized Financials

Sheet Toyota
B2: Company Data Inputs
B4: FactSet Inputs | E4: Reporting Information
B5: Name | C5: Toyota | E5: Last FY | F5: 2024 | H5: Last Quarter | I5: 2
B6: Identifier | C6: 7203-JP | E6: Ended | F6: 03/31/2025 | H6: Ended | I6: 09/30/2025
B7: Start Date | C7: -7
B8: End Date | C8: 0 | E8: Date | F8: 45962
B9: Report Basis | C9: ANN_R | E9: €/Share | F9: 17.648024
B10: Currency | C10: EUR
B13: Key Financial Items and Forecast
B14: All values in € (FactSet currency adjusted) million except for shares outstanding in millions.
E15: 2017 | F15: 2018 | G15: 2019 | H15: 2020 | I15: 2021 | J15: 2022 | K15: 2023 | L15: 2024 | M15: 2025 | N15: 2026 | O15: 2027 | P15: 2028 | R15: Current Q
B16: Revenue | E16: 226868.65 | F16: 235485.41 | G16: 247249.27 | H16: 220209.68 | I16: 240439.26 | J16: 263630.98 | K16: 287632.67 | L16: 293507.48 | M16: 274892 | N16: 283138.38 | O16: 290642.16 | P16: 300070.13
B17: COGS | E17: 184823.43 | F17: 193206.81 | G17: 202701.21 | H17: 181108.03 | I17: 194682.49 | J17: 218836.52 | K17: 227878.48 | L17: 234985.03 | M17: 222018.53 | N17: 225093.98 | O17: 230229.44 | P17: 244985.3
B18: EBITDA | E18: 31572.253 | F18: 33053.97 | G18: 33068.989 | H18: 31088.252 | I18: 36913.722 | J18: 33809.902 | K18: 47454.749 | L18: 44046.783 | M18: 31747.256 | N18: 35426.26 | O18: 37506.48 | P18: 37944.605
B19: D&A | E19: 13388.126 | F19: 13964.798 | G19: 13207.03 | H19: 13304.941 | I19: 13959.795 | J19: 14474.285 | K19: 13311.987 | L19: 14745.431 | M19: 9020.376 | N19: 9768.076 | O19: 10402.503 | P19: 9327.001
B20: EBIT | E20: 18184.127 | F20: 19089.172 | G20: 19861.959 | H20: 17783.311 | I20: 22953.927 | J20: 19335.617 | K20: 34142.763 | L20: 29301.352 | M20: 21309.92 | N20: 24447.715 | O20: 26236.025 | P20: 25518.342
B21: Taxes | E21: 3894.4191 | F21: 5141.7724 | G21: 5644.4006 | H21: 5259.3474 | I21: 8550.5006 | J21: 8342.7248 | K21: 12078.412 | L21: 9927.8507 | M21: 7342.747 | N21: 8331.811 | O21: 8868.219 | P21: 9450.811
B22: Net Income | E22: 19255.55 | F22: 14669.888 | G22: 16856.121 | H22: 18167.751 | I22: 21838.403 | J22: 17393.495 | K22: 31540.393 | L22: 29114.989 | M22: 18217.3 | N22: 21142.232 | O22: 22701.158 | P22: 22678.734
B24: Free Cash Flow | E24: 4719.742 | F24: 215.89485 | G24: -8635.1713 | H24: -6168.5199 | I24: 1827.1219 | J24: -2855.7973 | K24: -3238.4928 | L24: -7373.6105 | M24: 12674.911 | N24: 8773.261 | O24: 9346.489 | P24: 13434.681 | R24: -707.72607
B26: Cash and ST Investments | E26: 43745.991 | F26: 46894.848 | G26: 34599.617 | H26: 39276.442 | I26: 45270.273 | J26: 51986.123 | K26: 57581.524 | L26: 55607.205 | R26: 46752.309
B27: Total Debt | E27: 147919.81 | F27: 162131.87 | G27: 180163.12 | H27: 197578.4 | I27: 196199.71 | J27: 203189.22 | K27: 223679.3 | L27: 240154.37 | R27: 229725.74
B29: Total Common Stock FD | R29: 13033.389
B30: ROE (LTM) | R30: 0.12889945
B31: ROIC (LTM) | R31: 0.079094679
B33: Source: FactSet Standardized Financials

Sheet Honda
B2: Company Data Inputs
B4: FactSet Inputs | E4: Reporting Information
B5: Name | C5: Honda | E5: Last FY | F5: 2024 | H5: Last Quarter | I5: 2
B6: Identifier | C6: 7267-JP | E6: Ended | F6: 03/31/2025 | H6: Ended | I6: 09/30/2025
B7: Start Date | C7: -7
B8: End Date | C8: 0 | E8: Date | F8: 45962
B9: Report Basis | C9: ANN_R | E9: €/Share | F9: 8.7733965
B10: Currency | C10: EUR
B13: Key Financial Items and Forecast
B14: All values in € (FactSet currency adjusted) million except for shares outstanding in millions.
E15: 2017 | F15: 2018 | G15: 2019 | H15: 2020 | I15: 2021 | J15: 2022 | K15: 2023 | L15: 2024 | M15: 2025 | N15: 2026 | O15: 2027 | P15: 2028 | R15: Current Q
B16: Revenue | E16: 118600.37 | F16: 123791.8 | G16: 123605.89 | H16: 106570.6 | I16: 111507.15 | J16: 119969.97 | K16: 130301.55 | L16: 132519.82 | M16: 117737.17 | N16: 120500.61 | O16: 124229.95 | P16: 125972.59
B17: COGS | E17: 93842.516 | F17: 99174.889 | G17: 99243.664 | H17: 85645.437 | I17: 89628.297 | J17: 97392.34 | K17: 103146.7 | L17: 105097.72 | M17: 93464.484 | N17: 95480.46 | O17: 97692.44 | P17: 100254.6
B18: EBITDA | E18: 17662.679 | F18: 17102.168 | G18: 17343.723 | H18: 16873.629 | I18: 17992.158 | J18: 16870.75 | K18: 18889.175 | L18: 17268.827 | M18: 7197.0063 | N18: 8883.085 | O18: 9717.526 | P18: 10091.87
B19: D&A | E19: 11226.942 | F19: 11442.856 | G19: 12098.179 | H19: 11531.488 | I19: 11316.515 | J19: 11330.748 | K19: 10074.476 | L19: 9854.3466 | M19: 3078.9573 | N19: 3460.7869 | O19: 3616.1497 | P19: 2586.248
B20: EBIT | E20: 6435.7366 | F20: 5659.3123 | G20: 5245.544 | H20: 5342.1407 | I20: 6675.6426 | J20: 5540.0023 | K20: 8814.6993 | L20: 7414.4808 | M20: 4491.1504 | N20: 5852.801 | O20: 6462.6543 | P20: 6332.5957
B21: Taxes | E21: -105.51249 | F21: 2361.4347 | G21: 2317.8553 | H21: 1768.8971 | I21: 2371.3981 | J21: 1151.2991 | K21: 2932.7159 | L21: 2533.2704 | M21: 1398.4604 | N21: 1716.8285 | O21: 1849.3868 | P21: 2421.1685
B22: Net Income | E22: 8178.9317 | F22: 4755.1095 | G22: 3772.879 | H22: 5319.6218 | I22: 5417.7608 | J22: 4622.1689 | K22: 7061.9163 | L22: 5107.0201 | M22: 3089.569 | N22: 4107.7305 | O22: 4521.1167 | P22: 4521.675
B24: Free Cash Flow | E24: 4417.1328 | F24: 2767.5991 | G24: 5043.4087 | H24: 6100.8174 | I24: 10815.178 | J24: 11735.891 | K24: 2542.3878 | L24: -1335.9723 | M24: -336.0547 | N24: 1580.8635 | O24: 456.1939 | P24: 7433.224 | R24: 1013.7414
B26: Cash and ST Investments | E26: 17251.747 | F26: 20068.135 | G26: 22560.331 | H26: 21236.669 | I26: 27212.057 | J26: 26301.03 | K26: 30311.26 | L26: 28036.329 | R26: 26711.673
B27: Total Debt | E27: 51981.131 | F27: 58987.477 | G27: 65846.242 | H27: 61895.54 | I27: 63417.013 | J27: 55196.178 | K27: 64212.674 | L27: 72890.264 | R27: 72636.764
B29: Total Common Stock FD | R29: 3892.5506
B30: ROE (LTM) | R30: 0.053634847
B31: ROIC (LTM) | R31: 0.033711155
B33: Source: FactSet Standardized Financials

Sheet GeneralMotors
B2: Company Data Inputs
B4: FactSet Inputs | E4: Reporting Information
B5: Name | C5: General Motors | E5: Last FY | F5: 2024 | H5: Last Quarter | I5: 3
B6: Identifier | C6: GM-US | E6: Ended | F6: 12/31/2024 | H6: Ended | I6: 09/30/2025
B7: Start Date | C7: -7
B8: End Date | C8: 0 | E8: Date | F8: 45962
B9: Report Basis | C9: ANN_R | E9: €/Share | F9: 59.85964
B10: Currency | C10: EUR
B13: Key Financial Items and Forecast
B14: All values in € (FactSet currency adjusted) million except for shares outstanding in millions.
E15: 2017 | F15: 2018 | G15: 2019 | H15: 2020 | I15: 2021 | J15: 2022 | K15: 2023 | L15: 2024 | M15: 2025 | N15: 2026 | O15: 2027 | P15: 2028 | R15: Current Q
B16: Revenue | E16: 129074.86 | F16: 124644.23 | G16: 122615.29 | H16: 107445.39 | I16: 107450.12 | J16: 149133.04 | K16: 158948.77 | L16: 173286.13 | M16: 160977.55 | N16: 162207.69 | O16: 164368.53 | P16: 167007.11
B17: COGS | E17: 106439.68 | F17: 106085.21 | G17: 105271.51 | H17: 90013.421 | I17: 85640.975 | J17: 119844.98 | K17: 132089.48 | L17: 143143.5 | M17: 133904.83 | N17: 133405.94 | O17: 137880.53 | P17: 136838.66
B18: EBITDA | E18: 18389.364 | F18: 15280.36 | G18: 16243.933 | H18: 16938.976 | I18: 18080.664 | J18: 20542.842 | K18: 19456.753 | L18: 22409.362 | M18: 15075.114 | N18: 17256.457 | O18: 17556.89 | P18: 19956.453
B19: D&A | E19: 10609.658 | F19: 11139.651 | G19: 12561.999 | H19: 11119.547 | I19: 10192.212 | J19: 10729.092 | K19: 10856.378 | L19: 10590.827 | M19: 7591.445 | N19: 7868.9937 | O19: 8641.932 | P19: 6297.3247
B20: EBIT | E20: 7779.7065 | F20: 4140.7088 | G20: 3681.9343 | H20: 5819.4287 | I20: 7888.452 | J20: 9813.7507 | K20: 8600.3752 | L20: 11818.535 | M20: 10889.222 | N20: 11581.482 | O20: 12457.239 | P20: 13364.911
B21: Taxes | E21: 10224.884 | F21: 401.78013 | G21: 687.06806 | H21: 1556.1752 | I21: 2344.3694 | J21: 1797.3798 | K21: 520.75836 | L21: 2362.9674 | M21: 1887.5278 | N21: 2145.603 | O21: 2373.3323 | P21: 2020.0358
B22: Net Income | E22: 308.52853 | F22: 6852.3009 | G22: 6014.7493 | H22: 5637.8457 | I22: 8476.448 | J22: 9452.1814 | K22: 9367.1757 | L22: 5554.2677 | M22: 8722.873 | N22: 9215.48 | O22: 9843.179 | P22: 11031.131
B24: Free Cash Flow | E24: -9136.1681 | F24: -8680.6548 | G24: -8018.7722 | H24: -3388.6724 | I24: -5857.1164 | J24: -4894.5059 | K24: -3403.8913 | L24: -5528.3823 | M24: 8010.505 | N24: 8761.326 | O24: 9293.281 | P24: 9702.061 | R24: 647.81256
B26: Cash and ST Investments | E26: 21294.137 | F26: 25274.898 | G26: 23692.651 | H26: 25842.017 | I26: 27797.222 | J26: 31538.065 | K26: 26316.029 | L26: 28725.253 | R26: 27699.575
B27: Total Debt | E27: 78463.525 | F27: 91808.598 | G27: 93160.803 | H27: 90778.473 | I27: 97252.024 | J27: 108609.04 | K27: 111267.83 | L27: 126457.75 | R27: 112768.51
B29: Total Common Stock FD | R29: 933
B30: ROE (LTM) | R30: 0.044367084
B31: ROIC (LTM) | R31: 0.018743231
B33: Source: FactSet Standardized Financials

Sheet Ford
B2: Company Data Inputs
B4: FactSet Inputs | E4: Reporting Information
B5: Name | C5: Ford | E5: Last FY | F5: 2024 | H5: Last Quarter | I5: 3
B6: Identifier | C6: F-US | E6: Ended | F6: 12/31/2024 | H6: Ended | I6: 09/30/2025
B7: Start Date | C7: -7
B8: End Date | C8: 0 | E8: Date | F8: 45962
B9: Report Basis | C9: ANN_R | E9: €/Share | F9: 11.375845
B10: Currency | C10: EUR
B13: Key Financial Items and Forecast
B14: All values in € (FactSet currency adjusted) million except for shares outstanding in millions.
E15: 2017 | F15: 2018 | G15: 2019 | H15: 2020 | I15: 2021 | J15: 2022 | K15: 2023 | L15: 2024 | M15: 2025 | N15: 2026 | O15: 2027 | P15: 2028 | R15: Current Q
B16: Revenue | E16: 138993.88 | F16: 135908.49 | G16: 139289.87 | H16: 111532.32 | I16: 115349.58 | J16: 150390.92 | K16: 162971.47 | L16: 171021.15 | M16: 157610.4 | N16: 160697.72 | O16: 166121.98 | P16: 172878.31
B17: COGS | E17: 117758.6 | F17: 116619.65 | G17: 122215.92 | H17: 100377.69 | I17: 94581.051 | J17: 126511.18 | K17: 140485.44 | L17: 149383.73 | M17: 136034.64 | N17: 129520.28 | O17: 127938.17 | P17: 141145.77
B18: EBITDA | E18: 11417.329 | F18: 9714.7724 | G18: 8075.9535 | H18: 2526.3724 | I18: 9300.4883 | J18: 12276.228 | K18: 11008.073 | L18: 10134.135 | M18: 10222.399 | N18: 10873.805 | O18: 11867.49 | P18: 14546.648
B19: D&A | E19: 7494.2289 | F19: 7042.1716 | G19: 7585.4458 | H19: 6541.3747 | I19: 5042.3825 | J19: 6178.0767 | K19: 6033.5822 | L19: 5423.9162 | M19: 5692.1816 | N19: 6024.026 | O19: 6303.179 | P19: 4770.372
B20: EBIT | E20: 3923.0998 | F20: 2672.6008 | G20: 490.50763 | H20: -4015.0023 | I20: 4258.1059 | J20: 6098.1509 | K20: 4974.4911 | L20: 4710.2187 | M20: 5600.745 | N20: 7469.647 | O20: 8475.115 | P20: 8912.0625
B21: Taxes | E21: 356.40365 | F21: 550.96432 | G21: -646.86252 | H21: 140.35402 | I21: -109.98485 | J21: -822.0943 | K21: -334.8393 | L21: 1237.8769 | M21: 820.6775 | N21: 1295.245 | O21: 1326.4688 | P21: 1395.5507
B22: Net Income | E22: 6854.1209 | F22: 3116.7628 | G22: 41.992456 | H22: -1121.955 | I22: 15175.372 | J22: -1884.9176 | K22: 4020.8465 | L22: 5435.01 | M22: 3627.7937 | N22: 5049.9395 | O22: 5677.459 | P22: 6284.284
B24: Free Cash Flow | E24: 9794.0077 | F24: 6134.352 | G24: 8940.8194 | H24: 16252.119 | I24: 8088.1169 | J24: -12.36947 | K24: 6180.6525 | L24: 6230.0616 | M24: 2002.9093 | N24: 2397.3325 | O24: 2408.2559 | P24: 2749.2969 | R24: 4004.9707
B26: Cash and ST Investments | E26: 32417.555 | F26: 29699.514 | G26: 30869.488 | H26: 40832.823 | I26: 43609.744 | J26: 41293.043 | K26: 36365.366 | L26: 37033.316 | R26: 35904.682
B27: Total Debt | E27: 128486.84 | F27: 134901.8 | G27: 139617.82 | H27: 133217.28 | I27: 122656.53 | J27: 131622.39 | K27: 136791.75 | L27: 155347.17 | R27: 139899.58
B29: Total Common Stock FD | R29: 4203
B30: ROE (LTM) | R30: 0.10263121
B31: ROIC (LTM) | R31: 0.031048975
B33: Source: FactSet Standardized Financials
