Workbook
Name Cash_to_sales_ratio: #REF!
Name cs_fd_outstanding: #REF!
Name MarginalTax: #REF!
Name TGR: #REF!

Sheet __FDSCACHE__
B1: This sheet contains FactSet XML data for use with this workbook's =FDS codes. Modifying the worksheet's contents may damage the workbook's =FDS functionality.

Sheet Assignment Manager
B2: Basics
B4: Company | E4: Renault SA
B5: $/Share Estimate Deadline | E5: 45962
B6: Final Document Deadline | E6: 45989
B7: OUR DEADLINE | E7: 45983
B9: Grading Rubric
B11: Team Members | E11: ID | G11: Abbreviation
B12: Jordy Dikken | E12: 673670 | G12: JD
B13: Jorick Stoel | E13: 694007 | G13: JS
B14: Rikus van der Vegt | E14: 666665 | G14: RV
B15: Theodor Hogan | E15: 754441 | G15: TH
B17: Grading Rubric
B19: Evaluation Criterion | H19: Weight
B20: Reorganizing balancsheet and income statement | H20: 0.1 | I20: TH
B21: Adjustments to income statement and balancesheet; calculating key ratios | H21: 0.1 | I21: JD
B22: Projections of future cash cashflows and continuing (i.e. stable) growth rate | H22: 0.2 | I22: TH, RV
B23: Estimating the cost of debt, cost of equity, cost of capital | H23: 0.2 | I23: JD, JS
B24: Implemeting WACC; appropriate post DCF value adj. to estime $/shr | H24: 0.15 | I24: TH, RV
B25: Sensititivity analysis | H25: 0.05 | I25: RV
B26: Correctly identifiying peers and implementing multiples valuation | H26: 0.15 | I26: JD, JS
B27: General presentation and readability of Excel file | H27: 0.05 | I27: JD, JS, RV, TH
B28: Total | H28: =SUM(H20:H27) -> 1

Sheet Cover
C3: Kion Recapitalization Proposal
C5: Rotterdam School of Management
C6: Msc. Finance & Investment
C8: Last Update: | D8: 46011
C10: Authors: Jordy Dikken (673670), Jorick Stoel (694007),
C11: Rikus van der Vegt (666665) & Theodor Hogan (754441)
C15: #VALUE!
C21: Format: | E21: =D2*1.1+25*A2 -> 0
C22: Hardcode | D22: XXX
C23: Sheet Link | D23: XXX
C24: Ext. Link | D24: XXX | E24: Note: FactSet live links have been broken for compatability.
C25: Mixed Formula | D25: XXX | E25: =_xlfn.FORMULATEXT(E21) -> =D2*1.1+25*A2
C26: Assumptions | D26: XXX
C28: Font | D28: Arial
C29: Default | D29: 10 pt
C31: Input Field | D31: [Input]

Sheet Recapitalization
B2: Recapitalization Summary
B4: Active Scenario | C4: =IF(C27 = 1, "Base", "Adverse") -> Base
B6: Summary and Forecast | E6: =2019 -> 2019 | F6: =E6+1 -> 2020 | G6: =F6+1 -> 2021 | H6: =G6+1 -> 2022 | I6: =H6+1 -> 2023 | J6: =I6+1 -> 2024 | K6: =J6+1 -> 2025 | L6: =K6+1 -> 2026 | M6: =L6+1 -> 2027
B7: Key Figures
B8: Revenue | E8: =I30 -> 8806.5 | F8: =J30 -> 8341.6 | G8: =K30 -> 10294.3 | H8: =L30 -> 11135.6 | I8: =M30 -> 11433.7 | J8: =N30 -> 11503.2 | K8: =R30 -> 12653.52 | L8: =S30 -> 13792.337 | M8: =T30 -> 14895.724
B9: EBITDA | E9: =I40 -> 1646.7 | F9: =J40 -> 1413.8 | G9: =K40 -> 1845.7 | H9: =L40 -> 1306.1 | I9: =M40 -> 1833 | J9: =N40 -> 2037.5 | K9: =R40 -> 2277.6336 | L9: =S40 -> 2482.6206 | M9: =T40 -> 2681.2303
B10: EBIT | E10: =I43 -> 755.7 | F10: =J43 -> 497.7 | G10: =K43 -> 906.8 | H10: =L43 -> 292.8 | I10: =M43 -> 786.5 | J10: =N43 -> 926.7 | K10: =R43 -> 1025.8198 | L10: =S43 -> 1118.1435 | M10: =T43 -> 1207.595
B11: Net income | E11: =I50 -> 454.8 | F11: =J50 -> 215.3 | G11: =K50 -> 568.3 | H11: =L50 -> 98 | I11: =M50 -> 305.8 | J11: =N50 -> 360.4 | K11: =R50 -> 405.21254 | L11: =S50 -> 469.93151 | M11: =T50 -> 532.637 | W11: =2019 -> 2019 | X11: =W11+1 -> 2020 | Y11: =X11+1 -> 2021 | Z11: =Y11+1 -> 2022 | AA11: =Z11+1 -> 2023 | AB11: =AA11+1 -> 2024 | AC11: =AB11+1 -> 2025 | AD11: =AC11+1 -> 2026 | AE11: =AD11+1 -> 2027
B12: Free cashflow to equity holders | E12: =I62 -> 184.7 | F12: =J62 -> -538.4 | G12: =K62 -> 244.4 | H12: =L62 -> 48.8 | I12: =M62 -> 26.8 | J12: =N62 -> 659.5 | K12: =R62 -> 2084.7488 | L12: =S62 -> 129.10099 | M12: =T62 -> 172.07333 | V12: Payout ratio | W12: 0.82620466 | X12: 1.4114042 | Y12: 0.80482815 | Z12: 0.5102459 | AA12: 3.4253731 | AB12: 0.16300227 | AC12: 0.95934819 | AD12: 0.8 | AE12: 0.8
B13: Payouts to equity holders | E13: =I66 -> 152.6 | F13: =J66 -> -759.9 | G13: =K66 -> 196.7 | H13: =L66 -> 24.9 | I13: =M66 -> 91.8 | J13: =N66 -> 107.5 | K13: =R66 -> 2000 | L13: =S66 -> 103.28079 | M13: =T66 -> 137.65866 | V13: Net Leverage Ratio | W13: 3.1386409 | X13: 3.2583109 | Y13: 2.5120009 | Z13: 4.5756833 | AA13: 3.4259684 | AB13: 3.363092 | AC13: 3.8866216 | AD13: 3.5657079 | AE13: 3.3015814
B14: Retained cashflow | E14: =I56-I66 -> 542 | F14: =J56-J66 -> 1109.1 | G14: =K56-K66 -> 513.5 | H14: =L56-L66 -> -543.3 | I14: =M56-M66 -> 836.8 | J14: =N56-N66 -> 982.1 | K14: =R56-R66 -> -1473.2237 | L14: =S56-S66 -> 507.63017 | M14: =T56-T66 -> 554.76944 | V14: Interest Coverage Ratio | W14: 14.046468 | X14: 12.198529 | Y14: 57.757962 | Z14: 8.5865103 | AA14: 5.6664265 | AB14: 5.3566474 | AC14: 4.2452838 | AD14: 4.6273593 | AE14: 4.9975481
B16: Ratios
B17: EPS | E17: =I53 -> 3.8240982 | F17: =J53 -> 1.6410061 | G17: =K53 -> 4.3315549 | H17: =L53 -> 0.74695122 | I17: =M53 -> 2.3307927 | J17: =N53 -> 2.7469512 | K17: =R53 -> 3.0885102 | L17: =S53 -> 3.581795 | M17: =T53 -> 4.0597332
B18: Interest coverage ratio | E18: =I43/ABS(I44) -> 14.046468 | F18: =J43/ABS(J44) -> 12.198529 | G18: =K43/ABS(K44) -> 57.757962 | H18: =L43/ABS(L44) -> 8.5865103 | I18: =M43/ABS(M44) -> 5.6664265 | J18: =N43/ABS(N44) -> 5.3566474 | K18: =R43/ABS(R44) -> 4.2452838 | L18: =S43/ABS(S44) -> 4.6273593 | M18: =T43/ABS(T44) -> 4.9975481
B19: Net leverage ratio | E19: =I83/I40 -> 3.1386409 | F19: =J83/J40 -> 3.2583109 | G19: =K83/K40 -> 2.5120009 | H19: =L83/L40 -> 4.5756833 | I19: =M83/M40 -> 3.4259684 | J19: =N83/N40 -> 3.363092 | K19: =R83/R40 -> 3.8866216 | L19: =S83/S40 -> 3.5657079 | M19: =T83/T40 -> 3.3015814
B20: Payout ratio | E20: =I67 -> 0.82620466 | F20: =J67 -> 1.4114042 | G20: =K67 -> 0.80482815 | H20: =L67 -> 0.5102459 | I20: =M67 -> 3.4253731 | J20: =N67 -> 0.16300227 | K20: =R67 -> 0.95934819 | L20: =S67 -> 0.8 | M20: =T67 -> 0.8
B21: Retained cashflow/ net debt | E21: =E14/I83 -> 0.10486804 | F21: =F14/J83 -> 0.24076325 | G21: =G14/K83 -> 0.11075403 | H21: =H14/L83 -> -0.090909091 | I21: =I14/M83 -> 0.13325265 | J21: =J14/N83 -> 0.14332414 | K21: =K14/R83 -> -0.1664227 | L21: =L14/S83 -> 0.057344438 | M21: =M14/T83 -> 0.062669525 | W21: 2019 | X21: 2020 | Y21: 2021 | Z21: 2022 | AA21: 2023 | AB21: 2024 | AC21: 2025 | AD21: 2026 | AE21: 2027
B22: EBITDA Margin | E22: =E9/E$8 -> 0.18698688 | F22: =F9/F$8 -> 0.16948787 | G22: =G9/G$8 -> 0.1792934 | H22: =H9/H$8 -> 0.11729049 | I22: =I9/I$8 -> 0.16031556 | J22: =J9/J$8 -> 0.17712463 | K22: =K9/K$8 -> 0.18 | L22: =L9/L$8 -> 0.18 | M22: =M9/M$8 -> 0.18 | V22: EBITDA | W22: =E9 -> 1646.7 | X22: =F9 -> 1413.8 | Y22: =G9 -> 1845.7 | Z22: =H9 -> 1306.1 | AA22: =I9 -> 1833 | AB22: =J9 -> 2037.5 | AC22: =K9 -> 2277.6336 | AD22: =L9 -> 2482.6206 | AE22: =M9 -> 2681.2303
B23: EBIT Margin | E23: =E10/E$8 -> 0.085811616 | F23: =F10/F$8 -> 0.059664813 | G23: =G10/G$8 -> 0.088087582 | H23: =H10/H$8 -> 0.026294048 | I23: =I10/I$8 -> 0.068787881 | J23: =J10/J$8 -> 0.080560192 | K23: =K10/K$8 -> 0.081069913 | L23: =L10/L$8 -> 0.081069913 | M23: =M10/M$8 -> 0.081069913 | V23: EBIT | W23: =E10 -> 755.7 | X23: =F10 -> 497.7 | Y23: =G10 -> 906.8 | Z23: =H10 -> 292.8 | AA23: =I10 -> 786.5 | AB23: =J10 -> 926.7 | AC23: =K10 -> 1025.8198 | AD23: =L10 -> 1118.1435 | AE23: =M10 -> 1207.595
V24: EBITDA Margin | W24: 0.18698688 | X24: 0.16948787 | Y24: 0.1792934 | Z24: 0.11729049 | AA24: 0.16031556 | AB24: 0.17712463 | AC24: 0.18 | AD24: 0.18 | AE24: 0.18
B25: Forecast | V25: EBIT Margin | W25: 0.085811616 | X25: 0.059664813 | Y25: 0.088087582 | Z25: 0.026294048 | AA25: 0.068787881 | AB25: 0.080560192 | AC25: 0.081069913 | AD25: 0.081069913 | AE25: 0.081069913
B27: Scenario Switch | C27: 1 | D27: 1 is Base Case, 2 is Adverse scenario
B29: Income Statement | E29: 2015 | F29: =+E29+1 -> 2016 | G29: =+F29+1 -> 2017 | H29: =+G29+1 -> 2018 | I29: =+H29+1 -> 2019 | J29: =+I29+1 -> 2020 | K29: =+J29+1 -> 2021 | L29: =+K29+1 -> 2022 | M29: =+L29+1 -> 2023 | N29: =+M29+1 -> 2024 | P29: Avg/CAGR | R29: =N29+1 -> 2025 | S29: =R29+1 -> 2026 | T29: =S29+1 -> 2027
B30: Revenue | E30: =Financials!E5 -> 5097.9 | F30: =Financials!F5 -> 5587.2 | G30: =Financials!G5 -> 7653.6 | H30: =Financials!H5 -> 7995.7 | I30: =Financials!I5 -> 8806.5 | J30: =Financials!J5 -> 8341.6 | K30: =Financials!K5 -> 10294.3 | L30: =Financials!L5 -> 11135.6 | ... N30: =Financials!N5 -> 11503.2 | P30: =(N30/E30)^(1/(N29-E29))-1 -> 0.094635948 | R30: =N30*(1+R31) -> 12653.52 | S30: =R30*(1+S31) -> 13792.337 | T30: =S30*(1+T31) -> 14895.724
B31: % growth | F31: =F30/E30-1 -> 0.095980698 | G31: =G30/F30-1 -> 0.36984536 | H31: =H30/G30-1 -> 0.04469792 | I31: =I30/H30-1 -> 0.1014045 | J31: =J30/I30-1 -> -0.052790552 | K31: =K30/J30-1 -> 0.23409178 | L31: =L30/K30-1 -> 0.081724838 | M31: =M30/L30-1 -> 0.026769999 | N31: =N30/M30-1 -> 0.0060785223 | P31: =AVERAGE(E31:N31) -> 0.10086701 | R31: =CHOOSE($C$27,R32,R33) -> 0.1 | S31: =CHOOSE($C$27,S32,S33) -> 0.09 | T31: =CHOOSE($C$27,T32,T33) -> 0.08
B32: Based Case | R32: 0.1 | S32: 0.09 | T32: 0.08
B33: Adverse Case | R33: -0.15 | S33: 0 | T33: 0.15
B34: GOGS | E34: =Financials!E6 -> -3601.7 | F34: =Financials!F6 -> -4091.6 | G34: =Financials!G6 -> -5768.1 | H34: =Financials!H6 -> -5974.7 | I34: =Financials!I6 -> -6474.6 | J34: =Financials!J6 -> -6296.8 | K34: =Financials!K6 -> -7870.6 | L34: =Financials!L6 -> -9124.1 | ... N34: =Financials!N6 -> -8525.9 | R34: =-R30*R35 -> -9490.14 | S34: =-S30*S35 -> -10344.253 | T34: =-T30*T35 -> -11171.793
B35: % revenue | E35: =ABS(E34)/E30 -> 0.7065066 | F35: =ABS(F34)/F30 -> 0.73231672 | G35: =ABS(G34)/G30 -> 0.75364534 | H35: =ABS(H34)/H30 -> 0.74723914 | I35: =ABS(I34)/I30 -> 0.73520695 | J35: =ABS(J34)/J30 -> 0.75486717 | K35: =ABS(K34)/K30 -> 0.76455903 | L35: =ABS(L34)/L30 -> 0.81936312 | ... N35: =ABS(N34)/N30 -> 0.74117637 | P35: =AVERAGE(E35:N35) -> 0.752192 | R35: =CHOOSE($C$27,R36,R37) -> 0.75 | S35: =CHOOSE($C$27,S36,S37) -> 0.75 | T35: =CHOOSE($C$27,T36,T37) -> 0.75
B36: Based Case | R36: 0.75 | S36: 0.75 | T36: 0.75
B37: Adverse Case | R37: =R36*1.2 -> 0.9 | S37: =S36*1.2 -> 0.9 | T37: 0.75
B38: OpEx | E38: =Financials!E8+Financials!E9 -> -647.2 | F38: =Financials!F8+Financials!F9 -> -450.5 | G38: =Financials!G8+Financials!G9 -> -423.8 | H38: =Financials!H8+Financials!H9 -> -391.5 | I38: =Financials!I8+Financials!I9 -> -685.2 | J38: =Financials!J8+Financials!J9 -> -631 | K38: =Financials!K8+Financials!K9 -> -578 | L38: =Financials!L8+Financials!L9 -> -705.4 | ... N38: =Financials!N8+Financials!N9 -> -939.8 | R38: =-R39*R30 -> -885.7464 | S38: =-S39*S30 -> -965.46358 | T38: =-T39*T30 -> -1042.7007
B39: % revenue | E39: =ABS(E38)/E30 -> 0.12695424 | F39: =ABS(F38)/F30 -> 0.080630727 | G39: =ABS(G38)/G30 -> 0.055372635 | H39: =ABS(H38)/H30 -> 0.048963818 | I39: =ABS(I38)/I30 -> 0.077806166 | J39: =ABS(J38)/J30 -> 0.07564496 | K39: =ABS(K38)/K30 -> 0.056147577 | L39: =ABS(L38)/L30 -> 0.063346385 | ... N39: =ABS(N38)/N30 -> 0.081699005 | P39: =AVERAGE(E39:N39) -> 0.073921041 | R39: 0.07 | S39: 0.07 | T39: 0.07
B40: EBITDA | E40: =E30+E34+E38 -> 849 | F40: =F30+F34+F38 -> 1045.1 | G40: =G30+G34+G38 -> 1461.7 | H40: =H30+H34+H38 -> 1629.5 | I40: =I30+I34+I38 -> 1646.7 | J40: =J30+J34+J38 -> 1413.8 | K40: =K30+K34+K38 -> 1845.7 | L40: =L30+L34+L38 -> 1306.1 | ... N40: =N30+N34+N38 -> 2037.5 | R40: =R30+R34+R38 -> 2277.6336 | S40: =S30+S34+S38 -> 2482.6206 | T40: =T30+T34+T38 -> 2681.2303
B41: Depreciation & amortization | E41: =Financials!E13+Financials!E11 -> -397.3 | F41: =Financials!F13+Financials!F11 -> -511.7 | G41: =Financials!G13+Financials!G11 -> -690.4 | H41: =Financials!H13+Financials!H11 -> -968.1 | I41: =Financials!I13+Financials!I11 -> -891 | J41: =Financials!J13+Financials!J11 -> -916.1 | K41: =Financials!K13+Financials!K11 -> -938.9 | L41: =Financials!L13+Financials!L11 -> -1013.3 | ... N41: =Financials!N13+Financials!N11 -> -1110.8 | R41: =R42*R58 -> -1251.8138 | S41: =S42*S58 -> -1364.4771 | T41: =T42*T58 -> -1473.6352
B42: % capital expenditure | E42: =ABS(E41)/ABS(E58) -> 3.0918288 | F42: =ABS(F41)/ABS(F58) -> 3.1921397 | G42: =ABS(G41)/ABS(G58) -> 3.2216519 | H42: =ABS(H41)/ABS(H58) -> 3.820442 | I42: =ABS(I41)/ABS(I58) -> 3.1395349 | J42: =ABS(J41)/ABS(J58) -> 3.2941388 | K42: =ABS(K41)/ABS(K58) -> 2.9618297 | L42: =ABS(L41)/ABS(L58) -> 2.700693 | ... N42: =ABS(N41)/ABS(N58) -> 2.4483139 | P42: =AVERAGE(E42:N42) -> 3.0317953 | R42: =AVERAGE(I42:N42) -> 2.8319818 | S42: =R42 -> 2.8319818 | T42: =S42 -> 2.8319818
B43: EBIT | E43: =E40+E41 -> 451.7 | F43: =F40+F41 -> 533.4 | G43: =G40+G41 -> 771.3 | H43: =H40+H41 -> 661.4 | I43: =I40+I41 -> 755.7 | J43: =J40+J41 -> 497.7 | K43: =K40+K41 -> 906.8 | L43: =L40+L41 -> 292.8 | ... N43: =N40+N41 -> 926.7 | R43: =R40+R41 -> 1025.8198 | S43: =S40+S41 -> 1118.1435 | T43: =T40+T41 -> 1207.595
B44: Interest expense | E44: =Financials!E15 -> -45.7 | F44: =Financials!F15 -> -50.9 | G44: =Financials!G15 -> -53.2 | H44: =Financials!H15 -> -63.6 | I44: =Financials!I15 -> -53.8 | J44: =Financials!J15 -> -40.8 | K44: =Financials!K15 -> -15.7 | L44: =Financials!L15 -> -34.1 | ... N44: =Financials!N15 -> -173 | R44: =R89 -> -241.6375 | S44: =S89 -> -241.6375 | T44: =T89 -> -241.6375
B45: % of net debt | E45: =ABS(E44)/E82 -> 0.024964493 | F45: =ABS(F44)/F82 -> 0.011724329 | G45: =ABS(G44)/G82 -> 0.014340782 | H45: =ABS(H44)/H82 -> 0.013366961 | I45: =ABS(I44)/I82 -> 0.010409411 | J45: =ABS(J44)/J82 -> 0.0088568576 | K45: =ABS(K44)/K82 -> 0.003386248 | L45: =ABS(L44)/L82 -> 0.0057058715 | ... N45: =ABS(N44)/N82 -> 0.025246997 | P45: =AVERAGE(E45:N45) -> 0.014010456 | R45: =ABS(R44)/R83 -> 0.027296578 | S45: =ABS(S44)/S83 -> 0.027296578 | T45: =ABS(T44)/T83 -> 0.027296578
B46: Taxes | E46: =Financials!E17 -> -109.2 | F46: =Financials!F17 -> -93.1 | G46: =Financials!G17 -> -41.9 | H46: =Financials!H17 -> -143.7 | I46: =Financials!I17 -> -176.8 | J46: =Financials!J17 -> -90.7 | K46: =Financials!K17 -> -191.7 | L46: =Financials!L17 -> -32.2 | ... N46: =Financials!N17 -> -220.5 | R46: =-R47*(R43-R44) -> -378.96972 | S46: =-S47*(S43-S44) -> -406.57453 | T46: =-T47*(T43-T44) -> -433.32052
B47: % Effective tax | E47: =ABS(E46)/(E43+E44) -> 0.26896552 | F47: =ABS(F46)/(F43+F44) -> 0.19295337 | G47: =ABS(G46)/(G43+G44) -> 0.058348419 | H47: =ABS(H46)/(H43+H44) -> 0.2403814 | I47: =ABS(I46)/(I43+I44) -> 0.25188773 | J47: =ABS(J46)/(J43+J44) -> 0.19851171 | K47: =ABS(K46)/(K43+K44) -> 0.21512737 | L47: =ABS(L46)/(L43+L44) -> 0.1244685 | ... N47: =ABS(N46)/(N43+N44) -> 0.29255672 | P47: =AVERAGE(E47:N47) -> 0.20676874 | R47: 0.299 | S47: 0.299 | T47: 0.299
B48: Adj. net income | E48: =E46+E44+E43 -> 296.8 | F48: =F46+F44+F43 -> 389.4 | G48: =G46+G44+G43 -> 676.2 | H48: =H46+H44+H43 -> 454.1 | I48: =I46+I44+I43 -> 525.1 | J48: =J46+J44+J43 -> 366.2 | K48: =K46+K44+K43 -> 699.4 | L48: =L46+L44+L43 -> 226.5 | ... N48: =N46+N44+N43 -> 533.2 | R48: =R46+R44+R43 -> 405.21254 | S48: =S46+S44+S43 -> 469.93151 | T48: =T46+T44+T43 -> 532.637
B49: Exceptional items, net | E49: =Financials!E19 -> -79.8 | F49: =Financials!F19 -> -143.8 | G49: =Financials!G19 -> -251.4 | H49: =Financials!H19 -> -54.3 | I49: =Financials!I19 -> -70.3 | J49: =Financials!J19 -> -150.9 | K49: =Financials!K19 -> -131.1 | L49: =Financials!L19 -> -128.5 | ... N49: =Financials!N19 -> -172.8 | R49: 0 | S49: 0 | T49: 0
B50: Net income | E50: =E48+E49 -> 217 | F50: =F48+F49 -> 245.6 | G50: =G48+G49 -> 424.8 | H50: =H48+H49 -> 399.8 | I50: =I48+I49 -> 454.8 | J50: =J48+J49 -> 215.3 | K50: =K48+K49 -> 568.3 | L50: =L48+L49 -> 98 | ... N50: =N48+N49 -> 360.4 | R50: =R48+R49 -> 405.21254 | S50: =S48+S49 -> 469.93151 | T50: =T48+T49 -> 532.637
B52: Shares Outstanding | E52: =BS!D159 -> 99.6 | F52: =BS!E159 -> 109.56 | G52: =BS!F159 -> 118.93 | H52: =BS!G159 -> 118.93 | I52: =BS!H159 -> 118.93 | J52: =BS!I159 -> 131.2 | K52: =BS!J159 -> 131.2 | L52: =BS!K159 -> 131.2 | ... N52: =BS!M159 -> 131.2 | R52: =$N$52 -> 131.2 | S52: =$N$52 -> 131.2 | T52: =$N$52 -> 131.2
B53: EPS | E53: =E50/E52 -> 2.1787149 | F53: =F50/F52 -> 2.241694 | G53: =G50/G52 -> 3.571849 | H53: =H50/H52 -> 3.3616413 | I53: =I50/I52 -> 3.8240982 | J53: =J50/J52 -> 1.6410061 | K53: =K50/K52 -> 4.3315549 | L53: =L50/L52 -> 0.74695122 | ... N53: =N50/N52 -> 2.7469512 | R53: =R50/R52 -> 3.0885102 | S53: =S50/S52 -> 3.581795 | T53: =T50/T52 -> 4.0597332
B55: Free Cashflow Items | E55: 2015 | F55: =+E55+1 -> 2016 | G55: =+F55+1 -> 2017 | H55: =+G55+1 -> 2018 | I55: =+H55+1 -> 2019 | J55: =+I55+1 -> 2020 | K55: =+J55+1 -> 2021 | L55: =+K55+1 -> 2022 | M55: =+L55+1 -> 2023 | N55: =+M55+1 -> 2024 | P55: Avg/CAGR | R55: =N55+1 -> 2025 | S55: =R55+1 -> 2026 | T55: =S55+1 -> 2027
B56: Cashflow from operations | E56: =Financials!E25 -> 424.3 | F56: =Financials!F25 -> 332.4 | G56: =Financials!G25 -> 554.2 | H56: =Financials!H25 -> 620.3 | I56: =Financials!I25 -> 694.6 | J56: =Financials!J25 -> 349.2 | K56: =Financials!K25 -> 710.2 | L56: =Financials!L25 -> -518.4 | ... N56: =Financials!N25 -> 1089.6 | R56: =R57*R48 -> 526.7763 | S56: =S57*S48 -> 610.91096 | T56: =T57*T48 -> 692.4281
B57: % of adj net income | E57: =E56/E48 -> 1.4295822 | F57: =F56/F48 -> 0.85362096 | G57: =G56/G48 -> 0.81958001 | H57: =H56/H48 -> 1.3659987 | I57: =I56/I48 -> 1.3227957 | J57: =J56/J48 -> 0.95357728 | K57: =K56/K48 -> 1.0154418 | L57: =L56/L48 -> -2.2887417 | ... N57: =N56/N48 -> 2.0435109 | P57: =(N57+M57+K57+J57+I57+H57+G57+F57+E57)/9 -> 1.2947559 | R57: 1.3 | S57: 1.3 | T57: 1.3
B58: Capital expenditures | E58: =Financials!E26 -> -128.5 | F58: =Financials!F26 -> -160.3 | G58: =Financials!G26 -> -214.3 | H58: =Financials!H26 -> -253.4 | I58: =Financials!I26 -> -283.8 | J58: =Financials!J26 -> -278.1 | K58: =Financials!K26 -> -317 | L58: =Financials!L26 -> -375.2 | ... N58: =Financials!N26 -> -453.7 | R58: =-R59*R30 -> -442.0275 | S58: =-S59*S30 -> -481.80997 | T58: =-T59*T30 -> -520.35477
B59: % of revenue | E59: =ABS(E58)/E30 -> 0.025206458 | F59: =ABS(F58)/F30 -> 0.028690578 | G59: =ABS(G58)/G30 -> 0.027999895 | H59: =ABS(H58)/H30 -> 0.031692034 | I59: =ABS(I58)/I30 -> 0.032226197 | J59: =ABS(J58)/J30 -> 0.033338928 | K59: =ABS(K58)/K30 -> 0.03079374 | L59: =ABS(L58)/L30 -> 0.033693739 | ... N59: =ABS(N58)/N30 -> 0.039441199 | P59: =AVERAGE(E59:N59) -> 0.032048099 | R59: =AVERAGE(J59:N59) -> 0.034933165 | S59: =R59 -> 0.034933165 | T59: =S59 -> 0.034933165
B60: Principal payments | E60: =Financials!E27 -> -223.9 | F60: =Financials!F27 -> 1744 | G60: =Financials!G27 -> -914.7 | H60: =Financials!H27 -> -230.9 | I60: =Financials!I27 -> -226.1 | J60: =Financials!J27 -> -609.5 | K60: =Financials!K27 -> -148.8 | L60: =Financials!L27 -> 942.4 | ... N60: =Financials!N27 -> 23.6 | R60: =P81 -> 2000 | S60: 0 | T60: 0
B61: % of Net debt | E61: =E60/E82 -> -0.12230963 | F61: =F60/F82 -> 0.40171373 | G61: =G60/G82 -> -0.2465698 | H61: =H60/H82 -> -0.048528794 | I61: =I60/I82 -> -0.043746614 | J61: =J60/J82 -> -0.13231016 | K61: =K60/K82 -> -0.032093866 | L61: =L60/L82 -> 0.15768954 | ... N61: =N60/N82 -> 0.0034440991 | P61: =AVERAGE(E61:N61) -> -0.013822345
B62: Free cashflow to equity holders | E62: =E56+E58+E60 -> 71.9 | F62: =F56+F58+F60 -> 1916.1 | G62: =G56+G58+G60 -> -574.8 | H62: =H56+H58+H60 -> 136 | I62: =I56+I58+I60 -> 184.7 | J62: =J56+J58+J60 -> -538.4 | K62: =K56+K58+K60 -> 244.4 | L62: =L56+L58+L60 -> 48.8 | ... N62: =N56+N58+N60 -> 659.5 | R62: =R56+R58+R60 -> 2084.7488 | S62: =S56+S58+S60 -> 129.10099 | T62: =T56+T58+T60 -> 172.07333
B64: Cash paid out to equity holders - dividends | E64: =CF!B81 -> 76 | F64: =CF!C81 -> 86.9 | G64: =CF!D81 -> 116.7 | H64: =CF!E81 -> 141.5 | I64: =CF!F81 -> 153.4 | J64: =CF!G81 -> 53.7 | K64: =CF!H81 -> 196.7 | L64: =CF!I81 -> 24.9 | ... N64: =CF!K81 -> 107.5 | R64: 2000 | S64: =S62*S67 -> 103.28079 | T64: =T62*T67 -> 137.65866
B65: Cash paid out to equity holders - buybacks, net | E65: =CF!B77 -> -0.4 | F65: =CF!C77 -> -457.1 | G65: =CF!D77 -> -596.6 | H65: =CF!E77 -> 1.9 | I65: =CF!F77 -> -0.8 | J65: =CF!G77 -> -813.6 | K65: =CF!H77 -> 0 | L65: =CF!I77 -> 0 | ... N65: =CF!K77 -> 0 | R65: 0 | S65: 0 | T65: 0
B66: Total cash paid out to equity holders | E66: =E64+E65 -> 75.6 | F66: =F64+F65 -> -370.2 | G66: =G64+G65 -> -479.9 | H66: =H64+H65 -> 143.4 | I66: =I64+I65 -> 152.6 | J66: =J64+J65 -> -759.9 | K66: =K64+K65 -> 196.7 | L66: =L64+L65 -> 24.9 | ... N66: =N64+N65 -> 107.5 | R66: =R64+R65 -> 2000 | S66: =S64+S65 -> 103.28079 | T66: =T64+T65 -> 137.65866
B67: % payout ratio | E67: =E66/E62 -> 1.0514604 | F67: =F66/F62 -> -0.19320495 | G67: =G66/G62 -> 0.8348991 | H67: =H66/H62 -> 1.0544118 | I67: =I66/I62 -> 0.82620466 | J67: =J66/J62 -> 1.4114042 | K67: =K66/K62 -> 0.80482815 | L67: =L66/L62 -> 0.5102459 | ... N67: =N66/N62 -> 0.16300227 | P67: =AVERAGE(K67:N67) -> 1.2258624 | R67: =R66/R62 -> 0.95934819 | S67: 0.8 | T67: 0.8
B69: Debt and Recapitalization | P69: Issuance | R69: 2025 | S69: 2026 | T69: 2027
B70: Recapitalization
B71: New issue | E71: 2000
B72: Date | E72: 45992
B73: Term | E73: 5
B74: Type | E74: Fixed
B75: Credit Rating | E75: BB+
B76: DE 10yr bond | E76: 0.027487 | F76: As of Dec-1: https://www.cnbc.com/quotes/DE10Y-DE | W76: =W21 -> 2019 | X76: =X21 -> 2020 | Y76: =Y21 -> 2021 | Z76: =Z21 -> 2022 | AA76: =AA21 -> 2023 | AB76: =AB21 -> 2024 | AC76: =AC21 -> 2025 | AD76: =AD21 -> 2026 | AE76: =AE21 -> 2027
B77: Bond spread | E77: 76.78 | F77: Current spread on their 5 year bond maturing in 2029 | V77: Old Debt | W77: =I82 -> 5168.4 | X77: =J82 -> 4606.6 | Y77: =K82 -> 4636.4 | Z77: =L82 -> 5976.3 | AA77: =M82 -> 6279.8 | AB77: =N82 -> 6852.3 | AC77: =R82 -> 6852.3 | AD77: =S82 -> 6852.3 | AE77: =T82 -> 6852.3
B78: Interest rate | E78: =E76+E77*0.0001 -> 0.035165 | V78: New Debt | W78: =I81 -> 0 | X78: =J81 -> 0 | Y78: =K81 -> 0 | Z78: =L81 -> 0 | AA78: =M81 -> 0 | AB78: =N81 -> 0 | AC78: =R81 -> 2000 | AD78: =S81 -> 2000 | AE78: =T81 -> 2000
B81: New debt, balance | E81: 0 | F81: 0 | G81: 0 | H81: 0 | I81: 0 | J81: 0 | K81: 0 | L81: 0 | M81: 0 | N81: 0 | P81: =E71 -> 2000 | R81: =P81 -> 2000 | S81: =R81 -> 2000 | T81: =S81 -> 2000
B82: Old net debt, balance | E82: =Financials!E94 -> 1830.6 | F82: =Financials!F94 -> 4341.4 | G82: =Financials!G94 -> 3709.7 | H82: =Financials!H94 -> 4758 | I82: =Financials!I94 -> 5168.4 | J82: =Financials!J94 -> 4606.6 | K82: =Financials!K94 -> 4636.4 | L82: =Financials!L94 -> 5976.3 | ... N82: =Financials!N94 -> 6852.3 | R82: =N82 -> 6852.3 | S82: =R82 -> 6852.3 | T82: =R82 -> 6852.3
B83: Net debt | E83: =E81+E82 -> 1830.6 | F83: =F81+F82 -> 4341.4 | G83: =G81+G82 -> 3709.7 | H83: =H81+H82 -> 4758 | I83: =I81+I82 -> 5168.4 | J83: =J81+J82 -> 4606.6 | K83: =K81+K82 -> 4636.4 | L83: =L81+L82 -> 5976.3 | ... N83: =N81+N82 -> 6852.3 | R83: =R81+R82 -> 8852.3 | S83: =S81+S82 -> 8852.3 | T83: =T81+T82 -> 8852.3
B85: Interest expense new debt | E85: 0 | F85: 0 | G85: 0 | H85: 0 | I85: 0 | J85: 0 | K85: 0 | L85: 0 | M85: 0 | N85: 0 | R85: =-P81*R86 -> -70.33 | S85: =-R81*S86 -> -70.33 | T85: =-S81*T86 -> -70.33
B86: % rate | E86: 0 | F86: 0 | G86: 0 | H86: 0 | I86: 0 | J86: 0 | K86: 0 | L86: 0 | M86: 0 | N86: 0 | R86: =E78 -> 0.035165 | S86: =R86 -> 0.035165 | T86: =S86 -> 0.035165
B87: Interest expense old debt | E87: =E44 -> -45.7 | F87: =F44 -> -50.9 | G87: =G44 -> -53.2 | H87: =H44 -> -63.6 | I87: =I44 -> -53.8 | J87: =J44 -> -40.8 | K87: =K44 -> -15.7 | L87: =L44 -> -34.1 | ... N87: =N44 -> -173 | R87: =-N82*R88 -> -171.3075 | S87: =-R82*S88 -> -171.3075 | T87: =-S82*T88 -> -171.3075
B88: % rate | E88: =E45 -> 0.024964493 | F88: =F45 -> 0.011724329 | G88: =G45 -> 0.014340782 | H88: =H45 -> 0.013366961 | I88: =I45 -> 0.010409411 | J88: =J45 -> 0.0088568576 | K88: =K45 -> 0.003386248 | L88: =L45 -> 0.0057058715 | ... N88: =N45 -> 0.025246997 | R88: 0.025 | S88: =R88 -> 0.025 | T88: =S88 -> 0.025
B89: Total interest expense | E89: =E87+E85 -> -45.7 | F89: =F87+F85 -> -50.9 | G89: =G87+G85 -> -53.2 | H89: =H87+H85 -> -63.6 | I89: =I87+I85 -> -53.8 | J89: =J87+J85 -> -40.8 | K89: =K87+K85 -> -15.7 | L89: =L87+L85 -> -34.1 | ... N89: =N87+N85 -> -173 | R89: =R87+R85 -> -241.6375 | S89: =S87+S85 -> -241.6375 | T89: =T87+T85 -> -241.6375
W91: 2019 | X91: 2020 | Y91: 2021 | Z91: 2022 | AA91: 2023 | AB91: 2024 | AC91: 2025 | AD91: 2026 | AE91: 2027
V92: Basic Interest Expense | W92: =ABS(I87) -> 53.8 | X92: =ABS(J87) -> 40.8 | Y92: =ABS(K87) -> 15.7 | Z92: =ABS(L87) -> 34.1 | AA92: =ABS(M87) -> 138.8 | AB92: =ABS(N87) -> 173 | AC92: =ABS(R87) -> 171.3075 | AD92: =ABS(S87) -> 171.3075 | AE92: =ABS(T87) -> 171.3075
V93: Recap. Interest Expense | W93: 0 | X93: 0 | Y93: 0 | Z93: 0 | AA93: 0 | AB93: 0 | AC93: =ABS(R85) -> 70.33 | AD93: =ABS(S85) -> 70.33 | AE93: =ABS(T85) -> 70.33

Sheet Peer Analysis
B2: Comparables
B4: Year Ended | E4: 2019 | F4: 2020 | G4: 2021 | H4: 2022 | I4: 2023 | J4: 2024 | K4: LTM/Cur. Q
B6: Profitability Ratios
B8: Gross Profit Margin
B9: Honeywell_International | E9: =INDEX(INDIRECT($B9&"!C53:N78"),MATCH($B$8,INDIRECT($B9&"!B53:B78"),0),MATCH(E$4,INDIRECT($B9&"!C52:N52"),0)) -> 0.38503242 | F9: =INDEX(INDIRECT($B9&"!C53:N78"),MATCH($B$8,INDIRECT($B9&"!B53:B78"),0),MATCH(F$4,INDIRECT($B9&"!C52:N52"),0)) -> 0.3723652 | G9: =INDEX(INDIRECT($B9&"!C53:N78"),MATCH($B$8,INDIRECT($B9&"!B53:B78"),0),MATCH(G$4,INDIRECT($B9&"!C52:N52"),0)) -> 0.37144851 | H9: =INDEX(INDIRECT($B9&"!C53:N78"),MATCH($B$8,INDIRECT($B9&"!B53:B78"),0),MATCH(H$4,INDIRECT($B9&"!C52:N52"),0)) -> 0.38400135 | I9: =INDEX(INDIRECT($B9&"!C53:N78"),MATCH($B$8,INDIRECT($B9&"!B53:B78"),0),MATCH(I$4,INDIRECT($B9&"!C52:N52"),0)) -> 0.39004557 | J9: =INDEX(INDIRECT($B9&"!C53:N78"),MATCH($B$8,INDIRECT($B9&"!B53:B78"),0),MATCH(J$4,INDIRECT($B9&"!C52:N52"),0)) -> 0.38336451 | K9: =INDEX(INDIRECT($B9&"!C53:N78"),MATCH($B$8,INDIRECT($B9&"!B53:B78"),0),MATCH(K$4,INDIRECT($B9&"!C52:N52"),0)) -> 0.38066436 | P9: Kion | Q9: Honeywell International | R9: Daifuku | S9: Hyster Yale | T9: Mitsubishi Logisnext | U9: Toyota Industries | V9: Symbotic | W9: KENGIC | X9: Jungheinrich | Y9: ManitouBF
B10: Daifuku | E10: =INDEX(INDIRECT($B10&"!C53:N78"),MATCH($B$8,INDIRECT($B10&"!B53:B78"),0),MATCH(E$4,INDIRECT($B10&"!C52:N52"),0)) -> 0.20153078 | F10: =INDEX(INDIRECT($B10&"!C53:N78"),MATCH($B$8,INDIRECT($B10&"!B53:B78"),0),MATCH(F$4,INDIRECT($B10&"!C52:N52"),0)) -> 0.19341974 | G10: =INDEX(INDIRECT($B10&"!C53:N78"),MATCH($B$8,INDIRECT($B10&"!B53:B78"),0),MATCH(G$4,INDIRECT($B10&"!C52:N52"),0)) -> 0.19238758 | H10: =INDEX(INDIRECT($B10&"!C53:N78"),MATCH($B$8,INDIRECT($B10&"!B53:B78"),0),MATCH(H$4,INDIRECT($B10&"!C52:N52"),0)) -> 0.18782666 | I10: =INDEX(INDIRECT($B10&"!C53:N78"),MATCH($B$8,INDIRECT($B10&"!B53:B78"),0),MATCH(I$4,INDIRECT($B10&"!C52:N52"),0)) -> - | J10: =INDEX(INDIRECT($B10&"!C53:N78"),MATCH($B$8,INDIRECT($B10&"!B53:B78"),0),MATCH(J$4,INDIRECT($B10&"!C52:N52"),0)) -> 0.22661871 | K10: =INDEX(INDIRECT($B10&"!C53:N78"),MATCH($B$8,INDIRECT($B10&"!B53:B78"),0),MATCH(K$4,INDIRECT($B10&"!C52:N52"),0)) -> 0.2399198 | O10: EBITDA Margin | P10: =M222 -> 0.17712463 | Q10: =INDEX(INDIRECT($B23&"!C53:N78"),MATCH($B$22,INDIRECT($B23&"!B53:B78"),0),MATCH(K$4,INDIRECT($B23&"!C52:N52"),0)) -> 0.24140051 | R10: =INDEX(INDIRECT($B24&"!C53:N78"),MATCH($B$22,INDIRECT($B24&"!B53:B78"),0),MATCH(K$4,INDIRECT($B24&"!C52:N52"),0)) -> 0.1585306 | S10: =INDEX(INDIRECT($B25&"!C53:N78"),MATCH($B$22,INDIRECT($B25&"!B53:B78"),0),MATCH(K$4,INDIRECT($B25&"!C52:N52"),0)) -> 0.051895954 | T10: =INDEX(INDIRECT($B26&"!C53:N78"),MATCH($B$22,INDIRECT($B26&"!B53:B78"),0),MATCH(K$4,INDIRECT($B26&"!C52:N52"),0)) -> 0.083073068 | U10: =INDEX(INDIRECT($B27&"!C53:N78"),MATCH($B$22,INDIRECT($B27&"!B53:B78"),0),MATCH(K$4,INDIRECT($B27&"!C52:N52"),0)) -> 0.125042 | V10: =INDEX(INDIRECT($B28&"!C53:N78"),MATCH($B$22,INDIRECT($B28&"!B53:B78"),0),MATCH(K$4,INDIRECT($B28&"!C52:N52"),0)) -> -0.0017771358 | W10: =INDEX(INDIRECT($B29&"!C53:N78"),MATCH($B$22,INDIRECT($B29&"!B53:B78"),0),MATCH(K$4,INDIRECT($B29&"!C52:N52"),0)) -> - | X10: =INDEX(INDIRECT($B30&"!C53:N78"),MATCH($B$22,INDIRECT($B30&"!B53:B78"),0),MATCH(K$4,INDIRECT($B30&"!C52:N52"),0)) -> 0.16530251 | Y10: =INDEX(INDIRECT($B31&"!C53:N78"),MATCH($B$22,INDIRECT($B31&"!B53:B78"),0),MATCH(K$4,INDIRECT($B31&"!C52:N52"),0)) -> 0.086141812
B11: Hyster_Yale | E11: =INDEX(INDIRECT($B11&"!C53:N78"),MATCH($B$8,INDIRECT($B11&"!B53:B78"),0),MATCH(E$4,INDIRECT($B11&"!C52:N52"),0)) -> 0.17176013 | F11: =INDEX(INDIRECT($B11&"!C53:N78"),MATCH($B$8,INDIRECT($B11&"!B53:B78"),0),MATCH(F$4,INDIRECT($B11&"!C52:N52"),0)) -> 0.17012197 | G11: =INDEX(INDIRECT($B11&"!C53:N78"),MATCH($B$8,INDIRECT($B11&"!B53:B78"),0),MATCH(G$4,INDIRECT($B11&"!C52:N52"),0)) -> 0.11955002 | H11: =INDEX(INDIRECT($B11&"!C53:N78"),MATCH($B$8,INDIRECT($B11&"!B53:B78"),0),MATCH(H$4,INDIRECT($B11&"!C52:N52"),0)) -> 0.14122256 | I11: =INDEX(INDIRECT($B11&"!C53:N78"),MATCH($B$8,INDIRECT($B11&"!B53:B78"),0),MATCH(I$4,INDIRECT($B11&"!C52:N52"),0)) -> 0.20085958 | J11: =INDEX(INDIRECT($B11&"!C53:N78"),MATCH($B$8,INDIRECT($B11&"!B53:B78"),0),MATCH(J$4,INDIRECT($B11&"!C52:N52"),0)) -> 0.21779397 | K11: =INDEX(INDIRECT($B11&"!C53:N78"),MATCH($B$8,INDIRECT($B11&"!B53:B78"),0),MATCH(K$4,INDIRECT($B11&"!C52:N52"),0)) -> 0.19904947 | O11: EBIT Margin | P11: =M223 -> 0.080560192 | Q11: =INDEX(INDIRECT($B37&"!C53:N78"),MATCH($B$36,INDIRECT($B37&"!B53:B78"),0),MATCH(K$4,INDIRECT($B37&"!C52:N52"),0)) -> 0.20324064 | R11: =INDEX(INDIRECT($B38&"!C53:N78"),MATCH($B$36,INDIRECT($B38&"!B53:B78"),0),MATCH(K$4,INDIRECT($B38&"!C52:N52"),0)) -> 0.14606494 | S11: =INDEX(INDIRECT($B39&"!C53:N78"),MATCH($B$36,INDIRECT($B39&"!B53:B78"),0),MATCH(K$4,INDIRECT($B39&"!C52:N52"),0)) -> 0.040167621 | T11: =INDEX(INDIRECT($B40&"!C53:N78"),MATCH($B$36,INDIRECT($B40&"!B53:B78"),0),MATCH(K$4,INDIRECT($B40&"!C52:N52"),0)) -> 0.020403643 | U11: =INDEX(INDIRECT($B41&"!C53:N78"),MATCH($B$36,INDIRECT($B41&"!B53:B78"),0),MATCH(K$4,INDIRECT($B41&"!C52:N52"),0)) -> 0.043718371 | V11: =INDEX(INDIRECT($B42&"!C53:N78"),MATCH($B$36,INDIRECT($B42&"!B53:B78"),0),MATCH(K$4,INDIRECT($B42&"!C52:N52"),0)) -> -0.020168845 | W11: =INDEX(INDIRECT($B43&"!C53:N78"),MATCH($B$36,INDIRECT($B43&"!B53:B78"),0),MATCH(K$4,INDIRECT($B43&"!C52:N52"),0)) -> -0.075104141 | X11: =INDEX(INDIRECT($B44&"!C53:N78"),MATCH($B$36,INDIRECT($B44&"!B53:B78"),0),MATCH(K$4,INDIRECT($B44&"!C52:N52"),0)) -> 0.077929765 | Y11: =INDEX(INDIRECT($B45&"!C53:N78"),MATCH($B$36,INDIRECT($B45&"!B53:B78"),0),MATCH(K$4,INDIRECT($B45&"!C52:N52"),0)) -> 0.053908518
B12: Mitsubishi_Logisnext | E12: =INDEX(INDIRECT($B12&"!C53:N78"),MATCH($B$8,INDIRECT($B12&"!B53:B78"),0),MATCH(E$4,INDIRECT($B12&"!C52:N52"),0)) -> 0.22745802 | F12: =INDEX(INDIRECT($B12&"!C53:N78"),MATCH($B$8,INDIRECT($B12&"!B53:B78"),0),MATCH(F$4,INDIRECT($B12&"!C52:N52"),0)) -> 0.22136114 | G12: =INDEX(INDIRECT($B12&"!C53:N78"),MATCH($B$8,INDIRECT($B12&"!B53:B78"),0),MATCH(G$4,INDIRECT($B12&"!C52:N52"),0)) -> 0.21082023 | H12: =INDEX(INDIRECT($B12&"!C53:N78"),MATCH($B$8,INDIRECT($B12&"!B53:B78"),0),MATCH(H$4,INDIRECT($B12&"!C52:N52"),0)) -> 0.21488217 | I12: =INDEX(INDIRECT($B12&"!C53:N78"),MATCH($B$8,INDIRECT($B12&"!B53:B78"),0),MATCH(I$4,INDIRECT($B12&"!C52:N52"),0)) -> 0.24655086 | J12: =INDEX(INDIRECT($B12&"!C53:N78"),MATCH($B$8,INDIRECT($B12&"!B53:B78"),0),MATCH(J$4,INDIRECT($B12&"!C52:N52"),0)) -> 0.23027251 | K12: =INDEX(INDIRECT($B12&"!C53:N78"),MATCH($B$8,INDIRECT($B12&"!B53:B78"),0),MATCH(K$4,INDIRECT($B12&"!C52:N52"),0)) -> 0.23149125 | O12: EBITDA Mean | P12: =$J$33 -> 0.097115411 | Q12: =$J$33 -> 0.097115411 | R12: =$J$33 -> 0.097115411 | S12: =$J$33 -> 0.097115411 | T12: =$J$33 -> 0.097115411 | U12: =$J$33 -> 0.097115411 | V12: =$J$33 -> 0.097115411 | W12: =$J$33 -> 0.097115411 | ... Y12: =$J$33 -> 0.097115411
B13: Toyota_Industries | E13: =INDEX(INDIRECT($B13&"!C53:N78"),MATCH($B$8,INDIRECT($B13&"!B53:B78"),0),MATCH(E$4,INDIRECT($B13&"!C52:N52"),0)) -> 0.23290618 | F13: =INDEX(INDIRECT($B13&"!C53:N78"),MATCH($B$8,INDIRECT($B13&"!B53:B78"),0),MATCH(F$4,INDIRECT($B13&"!C52:N52"),0)) -> 0.23118469 | G13: =INDEX(INDIRECT($B13&"!C53:N78"),MATCH($B$8,INDIRECT($B13&"!B53:B78"),0),MATCH(G$4,INDIRECT($B13&"!C52:N52"),0)) -> 0.22436819 | H13: =INDEX(INDIRECT($B13&"!C53:N78"),MATCH($B$8,INDIRECT($B13&"!B53:B78"),0),MATCH(H$4,INDIRECT($B13&"!C52:N52"),0)) -> 0.2234788 | I13: =INDEX(INDIRECT($B13&"!C53:N78"),MATCH($B$8,INDIRECT($B13&"!B53:B78"),0),MATCH(I$4,INDIRECT($B13&"!C52:N52"),0)) -> 0.23461959 | J13: =INDEX(INDIRECT($B13&"!C53:N78"),MATCH($B$8,INDIRECT($B13&"!B53:B78"),0),MATCH(J$4,INDIRECT($B13&"!C52:N52"),0)) -> 0.23236835 | K13: =INDEX(INDIRECT($B13&"!C53:N78"),MATCH($B$8,INDIRECT($B13&"!B53:B78"),0),MATCH(K$4,INDIRECT($B13&"!C52:N52"),0)) -> 0.22392472 | O13: EBIT Mean | P13: =$J$47 -> 0.058723411 | Q13: =$J$47 -> 0.058723411 | R13: =$J$47 -> 0.058723411 | S13: =$J$47 -> 0.058723411 | T13: =$J$47 -> 0.058723411 | U13: =$J$47 -> 0.058723411 | V13: =$J$47 -> 0.058723411 | W13: =$J$47 -> 0.058723411 | ... Y13: =$J$47 -> 0.058723411
B14: Symbotic | E14: =INDEX(INDIRECT($B14&"!C53:N78"),MATCH($B$8,INDIRECT($B14&"!B53:B78"),0),MATCH(E$4,INDIRECT($B14&"!C52:N52"),0)) -> - | F14: =INDEX(INDIRECT($B14&"!C53:N78"),MATCH($B$8,INDIRECT($B14&"!B53:B78"),0),MATCH(F$4,INDIRECT($B14&"!C52:N52"),0)) -> - | G14: =INDEX(INDIRECT($B14&"!C53:N78"),MATCH($B$8,INDIRECT($B14&"!B53:B78"),0),MATCH(G$4,INDIRECT($B14&"!C52:N52"),0)) -> 0.16795042 | H14: =INDEX(INDIRECT($B14&"!C53:N78"),MATCH($B$8,INDIRECT($B14&"!B53:B78"),0),MATCH(H$4,INDIRECT($B14&"!C52:N52"),0)) -> 0.16122054 | I14: =INDEX(INDIRECT($B14&"!C53:N78"),MATCH($B$8,INDIRECT($B14&"!B53:B78"),0),MATCH(I$4,INDIRECT($B14&"!C52:N52"),0)) -> 0.13738334 | J14: =INDEX(INDIRECT($B14&"!C53:N78"),MATCH($B$8,INDIRECT($B14&"!B53:B78"),0),MATCH(J$4,INDIRECT($B14&"!C52:N52"),0)) -> 0.17480091 | K14: =INDEX(INDIRECT($B14&"!C53:N78"),MATCH($B$8,INDIRECT($B14&"!B53:B78"),0),MATCH(K$4,INDIRECT($B14&"!C52:N52"),0)) -> 0.17898562
B15: KENGIC | E15: =INDEX(INDIRECT($B15&"!C53:N78"),MATCH($B$8,INDIRECT($B15&"!B53:B78"),0),MATCH(E$4,INDIRECT($B15&"!C52:N52"),0)) -> 0.23852087 | F15: =INDEX(INDIRECT($B15&"!C53:N78"),MATCH($B$8,INDIRECT($B15&"!B53:B78"),0),MATCH(F$4,INDIRECT($B15&"!C52:N52"),0)) -> 0.23207883 | G15: =INDEX(INDIRECT($B15&"!C53:N78"),MATCH($B$8,INDIRECT($B15&"!B53:B78"),0),MATCH(G$4,INDIRECT($B15&"!C52:N52"),0)) -> 0.20948648 | H15: =INDEX(INDIRECT($B15&"!C53:N78"),MATCH($B$8,INDIRECT($B15&"!B53:B78"),0),MATCH(H$4,INDIRECT($B15&"!C52:N52"),0)) -> 0.19963167 | I15: =INDEX(INDIRECT($B15&"!C53:N78"),MATCH($B$8,INDIRECT($B15&"!B53:B78"),0),MATCH(I$4,INDIRECT($B15&"!C52:N52"),0)) -> 0.095067994 | J15: =INDEX(INDIRECT($B15&"!C53:N78"),MATCH($B$8,INDIRECT($B15&"!B53:B78"),0),MATCH(J$4,INDIRECT($B15&"!C52:N52"),0)) -> 0.12347494 | K15: =INDEX(INDIRECT($B15&"!C53:N78"),MATCH($B$8,INDIRECT($B15&"!B53:B78"),0),MATCH(K$4,INDIRECT($B15&"!C52:N52"),0)) -> 0.14822545
B16: Jungheinrich | E16: =INDEX(INDIRECT($B16&"!C53:N78"),MATCH($B$8,INDIRECT($B16&"!B53:B78"),0),MATCH(E$4,INDIRECT($B16&"!C52:N52"),0)) -> 0.2919199 | F16: =INDEX(INDIRECT($B16&"!C53:N78"),MATCH($B$8,INDIRECT($B16&"!B53:B78"),0),MATCH(F$4,INDIRECT($B16&"!C52:N52"),0)) -> 0.30405805 | G16: =INDEX(INDIRECT($B16&"!C53:N78"),MATCH($B$8,INDIRECT($B16&"!B53:B78"),0),MATCH(G$4,INDIRECT($B16&"!C52:N52"),0)) -> 0.31403163 | H16: =INDEX(INDIRECT($B16&"!C53:N78"),MATCH($B$8,INDIRECT($B16&"!B53:B78"),0),MATCH(H$4,INDIRECT($B16&"!C52:N52"),0)) -> 0.31209705 | I16: =INDEX(INDIRECT($B16&"!C53:N78"),MATCH($B$8,INDIRECT($B16&"!B53:B78"),0),MATCH(I$4,INDIRECT($B16&"!C52:N52"),0)) -> 0.31189619 | J16: =INDEX(INDIRECT($B16&"!C53:N78"),MATCH($B$8,INDIRECT($B16&"!B53:B78"),0),MATCH(J$4,INDIRECT($B16&"!C52:N52"),0)) -> 0.319837 | K16: =INDEX(INDIRECT($B16&"!C53:N78"),MATCH($B$8,INDIRECT($B16&"!B53:B78"),0),MATCH(K$4,INDIRECT($B16&"!C52:N52"),0)) -> 0.32620149
B17: Manitou_BF | E17: =INDEX(INDIRECT($B17&"!C53:N78"),MATCH($B$8,INDIRECT($B17&"!B53:B78"),0),MATCH(E$4,INDIRECT($B17&"!C52:N52"),0)) -> 0.16019521 | F17: =INDEX(INDIRECT($B17&"!C53:N78"),MATCH($B$8,INDIRECT($B17&"!B53:B78"),0),MATCH(F$4,INDIRECT($B17&"!C52:N52"),0)) -> 0.1510329 | G17: =INDEX(INDIRECT($B17&"!C53:N78"),MATCH($B$8,INDIRECT($B17&"!B53:B78"),0),MATCH(G$4,INDIRECT($B17&"!C52:N52"),0)) -> 0.16465102 | H17: =INDEX(INDIRECT($B17&"!C53:N78"),MATCH($B$8,INDIRECT($B17&"!B53:B78"),0),MATCH(H$4,INDIRECT($B17&"!C52:N52"),0)) -> 0.12831366 | I17: =INDEX(INDIRECT($B17&"!C53:N78"),MATCH($B$8,INDIRECT($B17&"!B53:B78"),0),MATCH(I$4,INDIRECT($B17&"!C52:N52"),0)) -> 0.16513601 | J17: =INDEX(INDIRECT($B17&"!C53:N78"),MATCH($B$8,INDIRECT($B17&"!B53:B78"),0),MATCH(J$4,INDIRECT($B17&"!C52:N52"),0)) -> 0.1823467 | K17: =INDEX(INDIRECT($B17&"!C53:N78"),MATCH($B$8,INDIRECT($B17&"!B53:B78"),0),MATCH(K$4,INDIRECT($B17&"!C52:N52"),0)) -> 0.17579505
B19: Mean | E19: =IFERROR(AVERAGE(E9:E17),"-") -> 0.23866544 | F19: =IFERROR(AVERAGE(F9:F17),"-") -> 0.23445281 | G19: =IFERROR(AVERAGE(G9:G17),"-") -> 0.21941045 | H19: =IFERROR(AVERAGE(H9:H17),"-") -> 0.21696383 | I19: =IFERROR(AVERAGE(I9:I17),"-") -> 0.22269489 | J19: =IFERROR(AVERAGE(J9:J17),"-") -> 0.23231973 | K19: =IFERROR(AVERAGE(K9:K17),"-") -> 0.23380636
B20: Median | E20: =IFERROR(MEDIAN(E9:E17),"-") -> 0.2301821 | F20: =IFERROR(MEDIAN(F9:F17),"-") -> 0.22627292 | G20: =IFERROR(MEDIAN(G9:G17),"-") -> 0.20948648 | H20: =IFERROR(MEDIAN(H9:H17),"-") -> 0.19963167 | I20: =IFERROR(MEDIAN(I9:I17),"-") -> 0.21773959 | J20: =IFERROR(MEDIAN(J9:J17),"-") -> 0.22661871 | K20: =IFERROR(MEDIAN(K9:K17),"-") -> 0.22392472
B22: EBITDA Margin
B23: Honeywell_International | E23: =INDEX(INDIRECT($B23&"!C53:N78"),MATCH($B$22,INDIRECT($B23&"!B53:B78"),0),MATCH(E$4,INDIRECT($B23&"!C52:N52"),0)) -> 0.22925407 | F23: =INDEX(INDIRECT($B23&"!C53:N78"),MATCH($B$22,INDIRECT($B23&"!B53:B78"),0),MATCH(F$4,INDIRECT($B23&"!C52:N52"),0)) -> 0.22340686 | G23: =INDEX(INDIRECT($B23&"!C53:N78"),MATCH($B$22,INDIRECT($B23&"!B53:B78"),0),MATCH(G$4,INDIRECT($B23&"!C52:N52"),0)) -> 0.23171547 | H23: =INDEX(INDIRECT($B23&"!C53:N78"),MATCH($B$22,INDIRECT($B23&"!B53:B78"),0),MATCH(H$4,INDIRECT($B23&"!C52:N52"),0)) -> 0.23800525 | I23: =INDEX(INDIRECT($B23&"!C53:N78"),MATCH($B$22,INDIRECT($B23&"!B53:B78"),0),MATCH(I$4,INDIRECT($B23&"!C52:N52"),0)) -> 0.24692335 | J23: =INDEX(INDIRECT($B23&"!C53:N78"),MATCH($B$22,INDIRECT($B23&"!B53:B78"),0),MATCH(J$4,INDIRECT($B23&"!C52:N52"),0)) -> 0.23908978 | K23: =INDEX(INDIRECT($B23&"!C53:N78"),MATCH($B$22,INDIRECT($B23&"!B53:B78"),0),MATCH(K$4,INDIRECT($B23&"!C52:N52"),0)) -> 0.24140051
B24: Daifuku | E24: =INDEX(INDIRECT($B24&"!C53:N78"),MATCH($B$22,INDIRECT($B24&"!B53:B78"),0),MATCH(E$4,INDIRECT($B24&"!C52:N52"),0)) -> 0.10591083 | F24: =INDEX(INDIRECT($B24&"!C53:N78"),MATCH($B$22,INDIRECT($B24&"!B53:B78"),0),MATCH(F$4,INDIRECT($B24&"!C52:N52"),0)) -> 0.10901621 | G24: =INDEX(INDIRECT($B24&"!C53:N78"),MATCH($B$22,INDIRECT($B24&"!B53:B78"),0),MATCH(G$4,INDIRECT($B24&"!C52:N52"),0)) -> 0.1136495 | H24: =INDEX(INDIRECT($B24&"!C53:N78"),MATCH($B$22,INDIRECT($B24&"!B53:B78"),0),MATCH(H$4,INDIRECT($B24&"!C52:N52"),0)) -> 0.11311765 | I24: =INDEX(INDIRECT($B24&"!C53:N78"),MATCH($B$22,INDIRECT($B24&"!B53:B78"),0),MATCH(I$4,INDIRECT($B24&"!C52:N52"),0)) -> - | J24: =INDEX(INDIRECT($B24&"!C53:N78"),MATCH($B$22,INDIRECT($B24&"!B53:B78"),0),MATCH(J$4,INDIRECT($B24&"!C52:N52"),0)) -> 0.14252487 | K24: =INDEX(INDIRECT($B24&"!C53:N78"),MATCH($B$22,INDIRECT($B24&"!B53:B78"),0),MATCH(K$4,INDIRECT($B24&"!C52:N52"),0)) -> 0.1585306
B25: Hyster_Yale | E25: =INDEX(INDIRECT($B25&"!C53:N78"),MATCH($B$22,INDIRECT($B25&"!B53:B78"),0),MATCH(E$4,INDIRECT($B25&"!C52:N52"),0)) -> 0.036818762 | F25: =INDEX(INDIRECT($B25&"!C53:N78"),MATCH($B$22,INDIRECT($B25&"!B53:B78"),0),MATCH(F$4,INDIRECT($B25&"!C52:N52"),0)) -> 0.039187794 | G25: =INDEX(INDIRECT($B25&"!C53:N78"),MATCH($B$22,INDIRECT($B25&"!B53:B78"),0),MATCH(G$4,INDIRECT($B25&"!C52:N52"),0)) -> -0.010371626 | H25: =INDEX(INDIRECT($B25&"!C53:N78"),MATCH($B$22,INDIRECT($B25&"!B53:B78"),0),MATCH(H$4,INDIRECT($B25&"!C52:N52"),0)) -> 0.021024151 | I25: =INDEX(INDIRECT($B25&"!C53:N78"),MATCH($B$22,INDIRECT($B25&"!B53:B78"),0),MATCH(I$4,INDIRECT($B25&"!C52:N52"),0)) -> 0.072189983 | J25: =INDEX(INDIRECT($B25&"!C53:N78"),MATCH($B$22,INDIRECT($B25&"!B53:B78"),0),MATCH(J$4,INDIRECT($B25&"!C52:N52"),0)) -> 0.083213405 | K25: =INDEX(INDIRECT($B25&"!C53:N78"),MATCH($B$22,INDIRECT($B25&"!B53:B78"),0),MATCH(K$4,INDIRECT($B25&"!C52:N52"),0)) -> 0.051895954
B26: Mitsubishi_Logisnext | E26: =INDEX(INDIRECT($B26&"!C53:N78"),MATCH($B$22,INDIRECT($B26&"!B53:B78"),0),MATCH(E$4,INDIRECT($B26&"!C52:N52"),0)) -> 0.087987115 | F26: =INDEX(INDIRECT($B26&"!C53:N78"),MATCH($B$22,INDIRECT($B26&"!B53:B78"),0),MATCH(F$4,INDIRECT($B26&"!C52:N52"),0)) -> 0.082358441 | G26: =INDEX(INDIRECT($B26&"!C53:N78"),MATCH($B$22,INDIRECT($B26&"!B53:B78"),0),MATCH(G$4,INDIRECT($B26&"!C52:N52"),0)) -> 0.07429857 | H26: =INDEX(INDIRECT($B26&"!C53:N78"),MATCH($B$22,INDIRECT($B26&"!B53:B78"),0),MATCH(H$4,INDIRECT($B26&"!C52:N52"),0)) -> 0.07845036 | I26: =INDEX(INDIRECT($B26&"!C53:N78"),MATCH($B$22,INDIRECT($B26&"!B53:B78"),0),MATCH(I$4,INDIRECT($B26&"!C52:N52"),0)) -> 0.11373812 | J26: =INDEX(INDIRECT($B26&"!C53:N78"),MATCH($B$22,INDIRECT($B26&"!B53:B78"),0),MATCH(J$4,INDIRECT($B26&"!C52:N52"),0)) -> 0.093244531 | K26: =INDEX(INDIRECT($B26&"!C53:N78"),MATCH($B$22,INDIRECT($B26&"!B53:B78"),0),MATCH(K$4,INDIRECT($B26&"!C52:N52"),0)) -> 0.083073068 | P26: Kion | Q26: Honeywell International | R26: Daifuku | S26: Hyster Yale | T26: Mitsubishi Logisnext | U26: Toyota Industries | V26: Symbotic | W26: KENGIC | X26: Jungheinrich | Y26: ManitouBF
B27: Toyota_Industries | E27: =INDEX(INDIRECT($B27&"!C53:N78"),MATCH($B$22,INDIRECT($B27&"!B53:B78"),0),MATCH(E$4,INDIRECT($B27&"!C52:N52"),0)) -> 0.15315828 | F27: =INDEX(INDIRECT($B27&"!C53:N78"),MATCH($B$22,INDIRECT($B27&"!B53:B78"),0),MATCH(F$4,INDIRECT($B27&"!C52:N52"),0)) -> 0.15338228 | G27: =INDEX(INDIRECT($B27&"!C53:N78"),MATCH($B$22,INDIRECT($B27&"!B53:B78"),0),MATCH(G$4,INDIRECT($B27&"!C52:N52"),0)) -> 0.13881834 | H27: =INDEX(INDIRECT($B27&"!C53:N78"),MATCH($B$22,INDIRECT($B27&"!B53:B78"),0),MATCH(H$4,INDIRECT($B27&"!C52:N52"),0)) -> 0.12624135 | I27: =INDEX(INDIRECT($B27&"!C53:N78"),MATCH($B$22,INDIRECT($B27&"!B53:B78"),0),MATCH(I$4,INDIRECT($B27&"!C52:N52"),0)) -> 0.13762243 | J27: =INDEX(INDIRECT($B27&"!C53:N78"),MATCH($B$22,INDIRECT($B27&"!B53:B78"),0),MATCH(J$4,INDIRECT($B27&"!C52:N52"),0)) -> 0.1344982 | K27: =INDEX(INDIRECT($B27&"!C53:N78"),MATCH($B$22,INDIRECT($B27&"!B53:B78"),0),MATCH(K$4,INDIRECT($B27&"!C52:N52"),0)) -> 0.125042 | O27: EBITDA Margin | P27: =K222 -> 0.17388696 | Q27: =AVERAGE(E23:J23) -> 0.23473246 | R27: =AVERAGE(E24:J24) -> 0.11684381 | S27: =AVERAGE(E25:J25) -> 0.040343745 | T27: =AVERAGE(E26:J26) -> 0.08834619 | U27: =AVERAGE(E27:J27) -> 0.14062015 | V27: =AVERAGE(E28:J28) -> -0.10921565 | W27: =AVERAGE(E29:J29) -> 0.011587778 | X27: =AVERAGE(E30:J30) -> 0.16509884 | Y27: =AVERAGE(E31:J31) -> 0.088549726
B28: Symbotic | E28: =INDEX(INDIRECT($B28&"!C53:N78"),MATCH($B$22,INDIRECT($B28&"!B53:B78"),0),MATCH(E$4,INDIRECT($B28&"!C52:N52"),0)) -> - | F28: =INDEX(INDIRECT($B28&"!C53:N78"),MATCH($B$22,INDIRECT($B28&"!B53:B78"),0),MATCH(F$4,INDIRECT($B28&"!C52:N52"),0)) -> - | G28: =INDEX(INDIRECT($B28&"!C53:N78"),MATCH($B$22,INDIRECT($B28&"!B53:B78"),0),MATCH(G$4,INDIRECT($B28&"!C52:N52"),0)) -> -0.2265014 | H28: =INDEX(INDIRECT($B28&"!C53:N78"),MATCH($B$22,INDIRECT($B28&"!B53:B78"),0),MATCH(H$4,INDIRECT($B28&"!C52:N52"),0)) -> -0.16044816 | I28: =INDEX(INDIRECT($B28&"!C53:N78"),MATCH($B$22,INDIRECT($B28&"!B53:B78"),0),MATCH(I$4,INDIRECT($B28&"!C52:N52"),0)) -> -0.033268484 | J28: =INDEX(INDIRECT($B28&"!C53:N78"),MATCH($B$22,INDIRECT($B28&"!B53:B78"),0),MATCH(J$4,INDIRECT($B28&"!C52:N52"),0)) -> -0.016644548 | K28: =INDEX(INDIRECT($B28&"!C53:N78"),MATCH($B$22,INDIRECT($B28&"!B53:B78"),0),MATCH(K$4,INDIRECT($B28&"!C52:N52"),0)) -> -0.0017771358 | O28: EBIT Margin | P28: =K223 -> 0.077677502 | Q28: =AVERAGE(E37:J37) -> 0.20196437 | R28: =AVERAGE(E38:J38) -> 0.10164539 | S28: =AVERAGE(E39:J39) -> 0.027400179 | T28: =AVERAGE(E40:J40) -> 0.02439985 | U28: =AVERAGE(E41:J41) -> 0.056015256 | V28: =AVERAGE(E42:J42) -> -0.12194452 | W28: =AVERAGE(E43:J43) -> 0.0070461438 | X28: =AVERAGE(E44:J44) -> 0.076874602 | Y28: =AVERAGE(E45:J45) -> 0.062353465
B29: KENGIC | E29: =INDEX(INDIRECT($B29&"!C53:N78"),MATCH($B$22,INDIRECT($B29&"!B53:B78"),0),MATCH(E$4,INDIRECT($B29&"!C52:N52"),0)) -> 0.024125615 | F29: =INDEX(INDIRECT($B29&"!C53:N78"),MATCH($B$22,INDIRECT($B29&"!B53:B78"),0),MATCH(F$4,INDIRECT($B29&"!C52:N52"),0)) -> 0.082948008 | G29: =INDEX(INDIRECT($B29&"!C53:N78"),MATCH($B$22,INDIRECT($B29&"!B53:B78"),0),MATCH(G$4,INDIRECT($B29&"!C52:N52"),0)) -> 0.066231477 | H29: =INDEX(INDIRECT($B29&"!C53:N78"),MATCH($B$22,INDIRECT($B29&"!B53:B78"),0),MATCH(H$4,INDIRECT($B29&"!C52:N52"),0)) -> 0.057992202 | I29: =INDEX(INDIRECT($B29&"!C53:N78"),MATCH($B$22,INDIRECT($B29&"!B53:B78"),0),MATCH(I$4,INDIRECT($B29&"!C52:N52"),0)) -> -0.090891504 | J29: =INDEX(INDIRECT($B29&"!C53:N78"),MATCH($B$22,INDIRECT($B29&"!B53:B78"),0),MATCH(J$4,INDIRECT($B29&"!C52:N52"),0)) -> -0.07087913 | K29: =INDEX(INDIRECT($B29&"!C53:N78"),MATCH($B$22,INDIRECT($B29&"!B53:B78"),0),MATCH(K$4,INDIRECT($B29&"!C52:N52"),0)) -> - | O29: EBITDA Mean | P29: =AVERAGE(E33:J33) -> 0.094075953 | Q29: =P29 -> 0.094075953 | R29: =Q29 -> 0.094075953 | S29: =R29 -> 0.094075953 | T29: =S29 -> 0.094075953 | U29: =T29 -> 0.094075953 | V29: =U29 -> 0.094075953 | W29: =V29 -> 0.094075953 | X29: =W29 -> 0.094075953 | Y29: =X29 -> 0.094075953
B30: Jungheinrich | E30: =INDEX(INDIRECT($B30&"!C53:N78"),MATCH($B$22,INDIRECT($B30&"!B53:B78"),0),MATCH(E$4,INDIRECT($B30&"!C52:N52"),0)) -> 0.16383182 | F30: =INDEX(INDIRECT($B30&"!C53:N78"),MATCH($B$22,INDIRECT($B30&"!B53:B78"),0),MATCH(F$4,INDIRECT($B30&"!C52:N52"),0)) -> 0.16752208 | G30: =INDEX(INDIRECT($B30&"!C53:N78"),MATCH($B$22,INDIRECT($B30&"!B53:B78"),0),MATCH(G$4,INDIRECT($B30&"!C52:N52"),0)) -> 0.17313491 | H30: =INDEX(INDIRECT($B30&"!C53:N78"),MATCH($B$22,INDIRECT($B30&"!B53:B78"),0),MATCH(H$4,INDIRECT($B30&"!C52:N52"),0)) -> 0.16327378 | I30: =INDEX(INDIRECT($B30&"!C53:N78"),MATCH($B$22,INDIRECT($B30&"!B53:B78"),0),MATCH(I$4,INDIRECT($B30&"!C52:N52"),0)) -> 0.15761735 | J30: =INDEX(INDIRECT($B30&"!C53:N78"),MATCH($B$22,INDIRECT($B30&"!B53:B78"),0),MATCH(J$4,INDIRECT($B30&"!C52:N52"),0)) -> 0.16521312 | K30: =INDEX(INDIRECT($B30&"!C53:N78"),MATCH($B$22,INDIRECT($B30&"!B53:B78"),0),MATCH(K$4,INDIRECT($B30&"!C52:N52"),0)) -> 0.16530251 | O30: EBIT Mean | P30: =AVERAGE(E47:K47) -> 0.054580909 | Q30: =P30 -> 0.054580909 | R30: =Q30 -> 0.054580909 | S30: =R30 -> 0.054580909 | T30: =S30 -> 0.054580909 | U30: =T30 -> 0.054580909 | V30: =U30 -> 0.054580909 | W30: =V30 -> 0.054580909 | X30: =W30 -> 0.054580909 | Y30: =X30 -> 0.054580909
B31: Manitou_BF | E31: =INDEX(INDIRECT($B31&"!C53:N78"),MATCH($B$22,INDIRECT($B31&"!B53:B78"),0),MATCH(E$4,INDIRECT($B31&"!C52:N52"),0)) -> 0.0915973 | F31: =INDEX(INDIRECT($B31&"!C53:N78"),MATCH($B$22,INDIRECT($B31&"!B53:B78"),0),MATCH(F$4,INDIRECT($B31&"!C52:N52"),0)) -> 0.086563982 | G31: =INDEX(INDIRECT($B31&"!C53:N78"),MATCH($B$22,INDIRECT($B31&"!B53:B78"),0),MATCH(G$4,INDIRECT($B31&"!C52:N52"),0)) -> 0.094522889 | H31: =INDEX(INDIRECT($B31&"!C53:N78"),MATCH($B$22,INDIRECT($B31&"!B53:B78"),0),MATCH(H$4,INDIRECT($B31&"!C52:N52"),0)) -> 0.059263381 | I31: =INDEX(INDIRECT($B31&"!C53:N78"),MATCH($B$22,INDIRECT($B31&"!B53:B78"),0),MATCH(I$4,INDIRECT($B31&"!C52:N52"),0)) -> 0.095572338 | J31: =INDEX(INDIRECT($B31&"!C53:N78"),MATCH($B$22,INDIRECT($B31&"!B53:B78"),0),MATCH(J$4,INDIRECT($B31&"!C52:N52"),0)) -> 0.10377847 | K31: =INDEX(INDIRECT($B31&"!C53:N78"),MATCH($B$22,INDIRECT($B31&"!B53:B78"),0),MATCH(K$4,INDIRECT($B31&"!C52:N52"),0)) -> 0.086141812
B33: Mean | E33: =IFERROR(AVERAGE(E23:E31),"-") -> 0.11158547 | F33: =IFERROR(AVERAGE(F23:F31),"-") -> 0.11804821 | G33: =IFERROR(AVERAGE(G23:G31),"-") -> 0.072833125 | H33: =IFERROR(AVERAGE(H23:H31),"-") -> 0.07743555 | I33: =IFERROR(AVERAGE(I23:I31),"-") -> 0.087437948 | J33: =IFERROR(AVERAGE(J23:J31),"-") -> 0.097115411 | K33: =IFERROR(AVERAGE(K23:K31),"-") -> 0.11370116
B34: Median | E34: =IFERROR(MEDIAN(E23:E31),"-") -> 0.098754065 | F34: =IFERROR(MEDIAN(F23:F31),"-") -> 0.097790096 | G34: =IFERROR(MEDIAN(G23:G31),"-") -> 0.094522889 | H34: =IFERROR(MEDIAN(H23:H31),"-") -> 0.07845036 | I34: =IFERROR(MEDIAN(I23:I31),"-") -> 0.10465523 | J34: =IFERROR(MEDIAN(J23:J31),"-") -> 0.10377847 | K34: =IFERROR(MEDIAN(K23:K31),"-") -> 0.1055919
B36: EBIT Margin (Operating Margin)
B37: Honeywell_International | E37: =INDEX(INDIRECT($B37&"!C53:N78"),MATCH($B$36,INDIRECT($B37&"!B53:B78"),0),MATCH(E$4,INDIRECT($B37&"!C52:N52"),0)) -> 0.19961314 | F37: =INDEX(INDIRECT($B37&"!C53:N78"),MATCH($B$36,INDIRECT($B37&"!B53:B78"),0),MATCH(F$4,INDIRECT($B37&"!C52:N52"),0)) -> 0.19270833 | G37: =INDEX(INDIRECT($B37&"!C53:N78"),MATCH($B$36,INDIRECT($B37&"!B53:B78"),0),MATCH(G$4,INDIRECT($B37&"!C52:N52"),0)) -> 0.19614971 | H37: =INDEX(INDIRECT($B37&"!C53:N78"),MATCH($B$36,INDIRECT($B37&"!B53:B78"),0),MATCH(H$4,INDIRECT($B37&"!C52:N52"),0)) -> 0.20404479 | I37: =INDEX(INDIRECT($B37&"!C53:N78"),MATCH($B$36,INDIRECT($B37&"!B53:B78"),0),MATCH(I$4,INDIRECT($B37&"!C52:N52"),0)) -> 0.21483341 | J37: =INDEX(INDIRECT($B37&"!C53:N78"),MATCH($B$36,INDIRECT($B37&"!B53:B78"),0),MATCH(J$4,INDIRECT($B37&"!C52:N52"),0)) -> 0.20443682 | K37: =INDEX(INDIRECT($B37&"!C53:N78"),MATCH($B$36,INDIRECT($B37&"!B53:B78"),0),MATCH(K$4,INDIRECT($B37&"!C52:N52"),0)) -> 0.20324064
B38: Daifuku | E38: =INDEX(INDIRECT($B38&"!C53:N78"),MATCH($B$36,INDIRECT($B38&"!B53:B78"),0),MATCH(E$4,INDIRECT($B38&"!C52:N52"),0)) -> 0.091274617 | F38: =INDEX(INDIRECT($B38&"!C53:N78"),MATCH($B$36,INDIRECT($B38&"!B53:B78"),0),MATCH(F$4,INDIRECT($B38&"!C52:N52"),0)) -> 0.094042651 | G38: =INDEX(INDIRECT($B38&"!C53:N78"),MATCH($B$36,INDIRECT($B38&"!B53:B78"),0),MATCH(G$4,INDIRECT($B38&"!C52:N52"),0)) -> 0.098100994 | H38: =INDEX(INDIRECT($B38&"!C53:N78"),MATCH($B$36,INDIRECT($B38&"!B53:B78"),0),MATCH(H$4,INDIRECT($B38&"!C52:N52"),0)) -> 0.09777845 | I38: =INDEX(INDIRECT($B38&"!C53:N78"),MATCH($B$36,INDIRECT($B38&"!B53:B78"),0),MATCH(I$4,INDIRECT($B38&"!C52:N52"),0)) -> - | J38: =INDEX(INDIRECT($B38&"!C53:N78"),MATCH($B$36,INDIRECT($B38&"!B53:B78"),0),MATCH(J$4,INDIRECT($B38&"!C52:N52"),0)) -> 0.12703026 | K38: =INDEX(INDIRECT($B38&"!C53:N78"),MATCH($B$36,INDIRECT($B38&"!B53:B78"),0),MATCH(K$4,INDIRECT($B38&"!C52:N52"),0)) -> 0.14606494
B39: Hyster_Yale | E39: =INDEX(INDIRECT($B39&"!C53:N78"),MATCH($B$36,INDIRECT($B39&"!B53:B78"),0),MATCH(E$4,INDIRECT($B39&"!C52:N52"),0)) -> 0.023664863 | F39: =INDEX(INDIRECT($B39&"!C53:N78"),MATCH($B$36,INDIRECT($B39&"!B53:B78"),0),MATCH(F$4,INDIRECT($B39&"!C52:N52"),0)) -> 0.023932292 | G39: =INDEX(INDIRECT($B39&"!C53:N78"),MATCH($B$36,INDIRECT($B39&"!B53:B78"),0),MATCH(G$4,INDIRECT($B39&"!C52:N52"),0)) -> -0.025392595 | H39: =INDEX(INDIRECT($B39&"!C53:N78"),MATCH($B$36,INDIRECT($B39&"!B53:B78"),0),MATCH(H$4,INDIRECT($B39&"!C52:N52"),0)) -> 0.0087929435 | I39: =INDEX(INDIRECT($B39&"!C53:N78"),MATCH($B$36,INDIRECT($B39&"!B53:B78"),0),MATCH(I$4,INDIRECT($B39&"!C52:N52"),0)) -> 0.061238861 | J39: =INDEX(INDIRECT($B39&"!C53:N78"),MATCH($B$36,INDIRECT($B39&"!B53:B78"),0),MATCH(J$4,INDIRECT($B39&"!C52:N52"),0)) -> 0.072164709 | K39: =INDEX(INDIRECT($B39&"!C53:N78"),MATCH($B$36,INDIRECT($B39&"!B53:B78"),0),MATCH(K$4,INDIRECT($B39&"!C52:N52"),0)) -> 0.040167621
B40: Mitsubishi_Logisnext | E40: =INDEX(INDIRECT($B40&"!C53:N78"),MATCH($B$36,INDIRECT($B40&"!B53:B78"),0),MATCH(E$4,INDIRECT($B40&"!C52:N52"),0)) -> 0.018794078 | F40: =INDEX(INDIRECT($B40&"!C53:N78"),MATCH($B$36,INDIRECT($B40&"!B53:B78"),0),MATCH(F$4,INDIRECT($B40&"!C52:N52"),0)) -> 0.004074117 | G40: =INDEX(INDIRECT($B40&"!C53:N78"),MATCH($B$36,INDIRECT($B40&"!B53:B78"),0),MATCH(G$4,INDIRECT($B40&"!C52:N52"),0)) -> 0.0077201409 | H40: =INDEX(INDIRECT($B40&"!C53:N78"),MATCH($B$36,INDIRECT($B40&"!B53:B78"),0),MATCH(H$4,INDIRECT($B40&"!C52:N52"),0)) -> 0.023900711 | I40: =INDEX(INDIRECT($B40&"!C53:N78"),MATCH($B$36,INDIRECT($B40&"!B53:B78"),0),MATCH(I$4,INDIRECT($B40&"!C52:N52"),0)) -> 0.06070935 | J40: =INDEX(INDIRECT($B40&"!C53:N78"),MATCH($B$36,INDIRECT($B40&"!B53:B78"),0),MATCH(J$4,INDIRECT($B40&"!C52:N52"),0)) -> 0.031200702 | K40: =INDEX(INDIRECT($B40&"!C53:N78"),MATCH($B$36,INDIRECT($B40&"!B53:B78"),0),MATCH(K$4,INDIRECT($B40&"!C52:N52"),0)) -> 0.020403643
B41: Toyota_Industries | E41: =INDEX(INDIRECT($B41&"!C53:N78"),MATCH($B$36,INDIRECT($B41&"!B53:B78"),0),MATCH(E$4,INDIRECT($B41&"!C52:N52"),0)) -> 0.057221873 | F41: =INDEX(INDIRECT($B41&"!C53:N78"),MATCH($B$36,INDIRECT($B41&"!B53:B78"),0),MATCH(F$4,INDIRECT($B41&"!C52:N52"),0)) -> 0.054322283 | G41: =INDEX(INDIRECT($B41&"!C53:N78"),MATCH($B$36,INDIRECT($B41&"!B53:B78"),0),MATCH(G$4,INDIRECT($B41&"!C52:N52"),0)) -> 0.056111546 | H41: =INDEX(INDIRECT($B41&"!C53:N78"),MATCH($B$36,INDIRECT($B41&"!B53:B78"),0),MATCH(H$4,INDIRECT($B41&"!C52:N52"),0)) -> 0.049977943 | I41: =INDEX(INDIRECT($B41&"!C53:N78"),MATCH($B$36,INDIRECT($B41&"!B53:B78"),0),MATCH(I$4,INDIRECT($B41&"!C52:N52"),0)) -> 0.063288032 | J41: =INDEX(INDIRECT($B41&"!C53:N78"),MATCH($B$36,INDIRECT($B41&"!B53:B78"),0),MATCH(J$4,INDIRECT($B41&"!C52:N52"),0)) -> 0.055169861 | K41: =INDEX(INDIRECT($B41&"!C53:N78"),MATCH($B$36,INDIRECT($B41&"!B53:B78"),0),MATCH(K$4,INDIRECT($B41&"!C52:N52"),0)) -> 0.043718371
B42: Symbotic | E42: =INDEX(INDIRECT($B42&"!C53:N78"),MATCH($B$36,INDIRECT($B42&"!B53:B78"),0),MATCH(E$4,INDIRECT($B42&"!C52:N52"),0)) -> - | F42: =INDEX(INDIRECT($B42&"!C53:N78"),MATCH($B$36,INDIRECT($B42&"!B53:B78"),0),MATCH(F$4,INDIRECT($B42&"!C52:N52"),0)) -> - | G42: =INDEX(INDIRECT($B42&"!C53:N78"),MATCH($B$36,INDIRECT($B42&"!B53:B78"),0),MATCH(G$4,INDIRECT($B42&"!C52:N52"),0)) -> -0.23659558 | H42: =INDEX(INDIRECT($B42&"!C53:N78"),MATCH($B$36,INDIRECT($B42&"!B53:B78"),0),MATCH(H$4,INDIRECT($B42&"!C52:N52"),0)) -> -0.16849903 | I42: =INDEX(INDIRECT($B42&"!C53:N78"),MATCH($B$36,INDIRECT($B42&"!B53:B78"),0),MATCH(I$4,INDIRECT($B42&"!C52:N52"),0)) -> -0.046399159 | J42: =INDEX(INDIRECT($B42&"!C53:N78"),MATCH($B$36,INDIRECT($B42&"!B53:B78"),0),MATCH(J$4,INDIRECT($B42&"!C52:N52"),0)) -> -0.036284304 | K42: =INDEX(INDIRECT($B42&"!C53:N78"),MATCH($B$36,INDIRECT($B42&"!B53:B78"),0),MATCH(K$4,INDIRECT($B42&"!C52:N52"),0)) -> -0.020168845
B43: KENGIC | E43: =INDEX(INDIRECT($B43&"!C53:N78"),MATCH($B$36,INDIRECT($B43&"!B53:B78"),0),MATCH(E$4,INDIRECT($B43&"!C52:N52"),0)) -> 0.020460619 | F43: =INDEX(INDIRECT($B43&"!C53:N78"),MATCH($B$36,INDIRECT($B43&"!B53:B78"),0),MATCH(F$4,INDIRECT($B43&"!C52:N52"),0)) -> 0.081390825 | G43: =INDEX(INDIRECT($B43&"!C53:N78"),MATCH($B$36,INDIRECT($B43&"!B53:B78"),0),MATCH(G$4,INDIRECT($B43&"!C52:N52"),0)) -> 0.063192723 | H43: =INDEX(INDIRECT($B43&"!C53:N78"),MATCH($B$36,INDIRECT($B43&"!B53:B78"),0),MATCH(H$4,INDIRECT($B43&"!C52:N52"),0)) -> 0.053584208 | I43: =INDEX(INDIRECT($B43&"!C53:N78"),MATCH($B$36,INDIRECT($B43&"!B53:B78"),0),MATCH(I$4,INDIRECT($B43&"!C52:N52"),0)) -> -0.098653914 | J43: =INDEX(INDIRECT($B43&"!C53:N78"),MATCH($B$36,INDIRECT($B43&"!B53:B78"),0),MATCH(J$4,INDIRECT($B43&"!C52:N52"),0)) -> -0.077697599 | K43: =INDEX(INDIRECT($B43&"!C53:N78"),MATCH($B$36,INDIRECT($B43&"!B53:B78"),0),MATCH(K$4,INDIRECT($B43&"!C52:N52"),0)) -> -0.075104141
B44: Jungheinrich | E44: =INDEX(INDIRECT($B44&"!C53:N78"),MATCH($B$36,INDIRECT($B44&"!B53:B78"),0),MATCH(E$4,INDIRECT($B44&"!C52:N52"),0)) -> 0.070211496 | F44: =INDEX(INDIRECT($B44&"!C53:N78"),MATCH($B$36,INDIRECT($B44&"!B53:B78"),0),MATCH(F$4,INDIRECT($B44&"!C52:N52"),0)) -> 0.070510104 | G44: =INDEX(INDIRECT($B44&"!C53:N78"),MATCH($B$36,INDIRECT($B44&"!B53:B78"),0),MATCH(G$4,INDIRECT($B44&"!C52:N52"),0)) -> 0.084779171 | H44: =INDEX(INDIRECT($B44&"!C53:N78"),MATCH($B$36,INDIRECT($B44&"!B53:B78"),0),MATCH(H$4,INDIRECT($B44&"!C52:N52"),0)) -> 0.079458039 | I44: =INDEX(INDIRECT($B44&"!C53:N78"),MATCH($B$36,INDIRECT($B44&"!B53:B78"),0),MATCH(I$4,INDIRECT($B44&"!C52:N52"),0)) -> 0.077777099 | J44: =INDEX(INDIRECT($B44&"!C53:N78"),MATCH($B$36,INDIRECT($B44&"!B53:B78"),0),MATCH(J$4,INDIRECT($B44&"!C52:N52"),0)) -> 0.078511704 | K44: =INDEX(INDIRECT($B44&"!C53:N78"),MATCH($B$36,INDIRECT($B44&"!B53:B78"),0),MATCH(K$4,INDIRECT($B44&"!C52:N52"),0)) -> 0.077929765
B45: Manitou_BF | E45: =INDEX(INDIRECT($B45&"!C53:N78"),MATCH($B$36,INDIRECT($B45&"!B53:B78"),0),MATCH(E$4,INDIRECT($B45&"!C52:N52"),0)) -> 0.069332535 | F45: =INDEX(INDIRECT($B45&"!C53:N78"),MATCH($B$36,INDIRECT($B45&"!B53:B78"),0),MATCH(F$4,INDIRECT($B45&"!C52:N52"),0)) -> 0.054552853 | G45: =INDEX(INDIRECT($B45&"!C53:N78"),MATCH($B$36,INDIRECT($B45&"!B53:B78"),0),MATCH(G$4,INDIRECT($B45&"!C52:N52"),0)) -> 0.065827973 | H45: =INDEX(INDIRECT($B45&"!C53:N78"),MATCH($B$36,INDIRECT($B45&"!B53:B78"),0),MATCH(H$4,INDIRECT($B45&"!C52:N52"),0)) -> 0.036012037 | I45: =INDEX(INDIRECT($B45&"!C53:N78"),MATCH($B$36,INDIRECT($B45&"!B53:B78"),0),MATCH(I$4,INDIRECT($B45&"!C52:N52"),0)) -> 0.074416852 | J45: =INDEX(INDIRECT($B45&"!C53:N78"),MATCH($B$36,INDIRECT($B45&"!B53:B78"),0),MATCH(J$4,INDIRECT($B45&"!C52:N52"),0)) -> 0.073978537 | K45: =INDEX(INDIRECT($B45&"!C53:N78"),MATCH($B$36,INDIRECT($B45&"!B53:B78"),0),MATCH(K$4,INDIRECT($B45&"!C52:N52"),0)) -> 0.053908518
B47: Mean | E47: =IFERROR(AVERAGE(E37:E45),"-") -> 0.068821653 | F47: =IFERROR(AVERAGE(F37:F45),"-") -> 0.071941682 | G47: =IFERROR(AVERAGE(G37:G45),"-") -> 0.034432675 | H47: =IFERROR(AVERAGE(H37:H45),"-") -> 0.042783344 | I47: =IFERROR(AVERAGE(I37:I45),"-") -> 0.050901317 | J47: =IFERROR(AVERAGE(J37:J45),"-") -> 0.058723411 | K47: =IFERROR(AVERAGE(K37:K45),"-") -> 0.054462279
B48: Median | E48: =IFERROR(MEDIAN(E37:E45),"-") -> 0.063277204 | F48: =IFERROR(MEDIAN(F37:F45),"-") -> 0.062531479 | G48: =IFERROR(MEDIAN(G37:G45),"-") -> 0.063192723 | H48: =IFERROR(MEDIAN(H37:H45),"-") -> 0.049977943 | I48: =IFERROR(MEDIAN(I37:I45),"-") -> 0.062263447 | J48: =IFERROR(MEDIAN(J37:J45),"-") -> 0.072164709 | K48: =IFERROR(MEDIAN(K37:K45),"-") -> 0.043718371
B50: Profit Margin
B51: Honeywell_International | E51: =INDEX(INDIRECT($B51&"!C53:N78"),MATCH($B$50,INDIRECT($B51&"!B53:B78"),0),MATCH(E$4,INDIRECT($B51&"!C52:N52"),0)) -> 0.16735684 | F51: =INDEX(INDIRECT($B51&"!C53:N78"),MATCH($B$50,INDIRECT($B51&"!B53:B78"),0),MATCH(F$4,INDIRECT($B51&"!C52:N52"),0)) -> 0.14641544 | G51: =INDEX(INDIRECT($B51&"!C53:N78"),MATCH($B$50,INDIRECT($B51&"!B53:B78"),0),MATCH(G$4,INDIRECT($B51&"!C52:N52"),0)) -> 0.16116556 | H51: =INDEX(INDIRECT($B51&"!C53:N78"),MATCH($B$50,INDIRECT($B51&"!B53:B78"),0),MATCH(H$4,INDIRECT($B51&"!C52:N52"),0)) -> 0.14007277 | I51: =INDEX(INDIRECT($B51&"!C53:N78"),MATCH($B$50,INDIRECT($B51&"!B53:B78"),0),MATCH(I$4,INDIRECT($B51&"!C52:N52"),0)) -> 0.1543919 | J51: =INDEX(INDIRECT($B51&"!C53:N78"),MATCH($B$50,INDIRECT($B51&"!B53:B78"),0),MATCH(J$4,INDIRECT($B51&"!C52:N52"),0)) -> 0.14819722 | K51: =INDEX(INDIRECT($B51&"!C53:N78"),MATCH($B$50,INDIRECT($B51&"!B53:B78"),0),MATCH(K$4,INDIRECT($B51&"!C52:N52"),0)) -> 0.15069706
B52: Daifuku | E52: =INDEX(INDIRECT($B52&"!C53:N78"),MATCH($B$50,INDIRECT($B52&"!B53:B78"),0),MATCH(E$4,INDIRECT($B52&"!C52:N52"),0)) -> 0.063248545 | F52: =INDEX(INDIRECT($B52&"!C53:N78"),MATCH($B$50,INDIRECT($B52&"!B53:B78"),0),MATCH(F$4,INDIRECT($B52&"!C52:N52"),0)) -> 0.068347464 | G52: =INDEX(INDIRECT($B52&"!C53:N78"),MATCH($B$50,INDIRECT($B52&"!B53:B78"),0),MATCH(G$4,INDIRECT($B52&"!C52:N52"),0)) -> 0.070037558 | H52: =INDEX(INDIRECT($B52&"!C53:N78"),MATCH($B$50,INDIRECT($B52&"!B53:B78"),0),MATCH(H$4,INDIRECT($B52&"!C52:N52"),0)) -> 0.068527151 | I52: =INDEX(INDIRECT($B52&"!C53:N78"),MATCH($B$50,INDIRECT($B52&"!B53:B78"),0),MATCH(I$4,INDIRECT($B52&"!C52:N52"),0)) -> - | J52: =INDEX(INDIRECT($B52&"!C53:N78"),MATCH($B$50,INDIRECT($B52&"!B53:B78"),0),MATCH(J$4,INDIRECT($B52&"!C52:N52"),0)) -> 0.10135682 | K52: =INDEX(INDIRECT($B52&"!C53:N78"),MATCH($B$50,INDIRECT($B52&"!B53:B78"),0),MATCH(K$4,INDIRECT($B52&"!C52:N52"),0)) -> 0.11846653
B53: Hyster_Yale | E53: =INDEX(INDIRECT($B53&"!C53:N78"),MATCH($B$50,INDIRECT($B53&"!B53:B78"),0),MATCH(E$4,INDIRECT($B53&"!C52:N52"),0)) -> 0.010875509 | F53: =INDEX(INDIRECT($B53&"!C53:N78"),MATCH($B$50,INDIRECT($B53&"!B53:B78"),0),MATCH(F$4,INDIRECT($B53&"!C52:N52"),0)) -> 0.013192987 | G53: =INDEX(INDIRECT($B53&"!C53:N78"),MATCH($B$50,INDIRECT($B53&"!B53:B78"),0),MATCH(G$4,INDIRECT($B53&"!C52:N52"),0)) -> -0.056247358 | H53: =INDEX(INDIRECT($B53&"!C53:N78"),MATCH($B$50,INDIRECT($B53&"!B53:B78"),0),MATCH(H$4,INDIRECT($B53&"!C52:N52"),0)) -> -0.02088324 | I53: =INDEX(INDIRECT($B53&"!C53:N78"),MATCH($B$50,INDIRECT($B53&"!B53:B78"),0),MATCH(I$4,INDIRECT($B53&"!C52:N52"),0)) -> 0.030570867 | J53: =INDEX(INDIRECT($B53&"!C53:N78"),MATCH($B$50,INDIRECT($B53&"!B53:B78"),0),MATCH(J$4,INDIRECT($B53&"!C52:N52"),0)) -> 0.033030036 | K53: =INDEX(INDIRECT($B53&"!C53:N78"),MATCH($B$50,INDIRECT($B53&"!B53:B78"),0),MATCH(K$4,INDIRECT($B53&"!C52:N52"),0)) -> 0.00068990188
B54: Mitsubishi_Logisnext | E54: =INDEX(INDIRECT($B54&"!C53:N78"),MATCH($B$50,INDIRECT($B54&"!B53:B78"),0),MATCH(E$4,INDIRECT($B54&"!C52:N52"),0)) -> -0.011676966 | F54: =INDEX(INDIRECT($B54&"!C53:N78"),MATCH($B$50,INDIRECT($B54&"!B53:B78"),0),MATCH(F$4,INDIRECT($B54&"!C52:N52"),0)) -> -0.0068506447 | G54: =INDEX(INDIRECT($B54&"!C53:N78"),MATCH($B$50,INDIRECT($B54&"!B53:B78"),0),MATCH(G$4,INDIRECT($B54&"!C52:N52"),0)) -> 0.0015405904 | H54: =INDEX(INDIRECT($B54&"!C53:N78"),MATCH($B$50,INDIRECT($B54&"!B53:B78"),0),MATCH(H$4,INDIRECT($B54&"!C52:N52"),0)) -> 0.011232961 | I54: =INDEX(INDIRECT($B54&"!C53:N78"),MATCH($B$50,INDIRECT($B54&"!B53:B78"),0),MATCH(I$4,INDIRECT($B54&"!C52:N52"),0)) -> 0.039215127 | J54: =INDEX(INDIRECT($B54&"!C53:N78"),MATCH($B$50,INDIRECT($B54&"!B53:B78"),0),MATCH(J$4,INDIRECT($B54&"!C52:N52"),0)) -> 0.013018447 | K54: =INDEX(INDIRECT($B54&"!C53:N78"),MATCH($B$50,INDIRECT($B54&"!B53:B78"),0),MATCH(K$4,INDIRECT($B54&"!C52:N52"),0)) -> -0.0030804004
B55: Toyota_Industries | E55: =INDEX(INDIRECT($B55&"!C53:N78"),MATCH($B$50,INDIRECT($B55&"!B53:B78"),0),MATCH(E$4,INDIRECT($B55&"!C52:N52"),0)) -> 0.067184776 | F55: =INDEX(INDIRECT($B55&"!C53:N78"),MATCH($B$50,INDIRECT($B55&"!B53:B78"),0),MATCH(F$4,INDIRECT($B55&"!C52:N52"),0)) -> 0.064532819 | G55: =INDEX(INDIRECT($B55&"!C53:N78"),MATCH($B$50,INDIRECT($B55&"!B53:B78"),0),MATCH(G$4,INDIRECT($B55&"!C52:N52"),0)) -> 0.066652422 | H55: =INDEX(INDIRECT($B55&"!C53:N78"),MATCH($B$50,INDIRECT($B55&"!B53:B78"),0),MATCH(H$4,INDIRECT($B55&"!C52:N52"),0)) -> 0.057061308 | I55: =INDEX(INDIRECT($B55&"!C53:N78"),MATCH($B$50,INDIRECT($B55&"!B53:B78"),0),MATCH(I$4,INDIRECT($B55&"!C52:N52"),0)) -> 0.059683215 | J55: =INDEX(INDIRECT($B55&"!C53:N78"),MATCH($B$50,INDIRECT($B55&"!B53:B78"),0),MATCH(J$4,INDIRECT($B55&"!C52:N52"),0)) -> 0.06421396 | K55: =INDEX(INDIRECT($B55&"!C53:N78"),MATCH($B$50,INDIRECT($B55&"!B53:B78"),0),MATCH(K$4,INDIRECT($B55&"!C52:N52"),0)) -> 0.049902947
B56: Symbotic | E56: =INDEX(INDIRECT($B56&"!C53:N78"),MATCH($B$50,INDIRECT($B56&"!B53:B78"),0),MATCH(E$4,INDIRECT($B56&"!C52:N52"),0)) -> - | F56: =INDEX(INDIRECT($B56&"!C53:N78"),MATCH($B$50,INDIRECT($B56&"!B53:B78"),0),MATCH(F$4,INDIRECT($B56&"!C52:N52"),0)) -> - | G56: =INDEX(INDIRECT($B56&"!C53:N78"),MATCH($B$50,INDIRECT($B56&"!B53:B78"),0),MATCH(G$4,INDIRECT($B56&"!C52:N52"),0)) -> -0.01156727 | H56: =INDEX(INDIRECT($B56&"!C53:N78"),MATCH($B$50,INDIRECT($B56&"!B53:B78"),0),MATCH(H$4,INDIRECT($B56&"!C52:N52"),0)) -> -0.020278853 | I56: =INDEX(INDIRECT($B56&"!C53:N78"),MATCH($B$50,INDIRECT($B56&"!B53:B78"),0),MATCH(I$4,INDIRECT($B56&"!C52:N52"),0)) -> -0.0075439875 | J56: =INDEX(INDIRECT($B56&"!C53:N78"),MATCH($B$50,INDIRECT($B56&"!B53:B78"),0),MATCH(J$4,INDIRECT($B56&"!C52:N52"),0)) -> -0.0075378674 | K56: =INDEX(INDIRECT($B56&"!C53:N78"),MATCH($B$50,INDIRECT($B56&"!B53:B78"),0),MATCH(K$4,INDIRECT($B56&"!C52:N52"),0)) -> -0.0037732974
B57: KENGIC | E57: =INDEX(INDIRECT($B57&"!C53:N78"),MATCH($B$50,INDIRECT($B57&"!B53:B78"),0),MATCH(E$4,INDIRECT($B57&"!C52:N52"),0)) -> 0.027732493 | F57: =INDEX(INDIRECT($B57&"!C53:N78"),MATCH($B$50,INDIRECT($B57&"!B53:B78"),0),MATCH(F$4,INDIRECT($B57&"!C52:N52"),0)) -> 0.070255435 | G57: =INDEX(INDIRECT($B57&"!C53:N78"),MATCH($B$50,INDIRECT($B57&"!B53:B78"),0),MATCH(G$4,INDIRECT($B57&"!C52:N52"),0)) -> 0.067827181 | H57: =INDEX(INDIRECT($B57&"!C53:N78"),MATCH($B$50,INDIRECT($B57&"!B53:B78"),0),MATCH(H$4,INDIRECT($B57&"!C52:N52"),0)) -> 0.053486468 | I57: =INDEX(INDIRECT($B57&"!C53:N78"),MATCH($B$50,INDIRECT($B57&"!B53:B78"),0),MATCH(I$4,INDIRECT($B57&"!C52:N52"),0)) -> -0.068399806 | J57: =INDEX(INDIRECT($B57&"!C53:N78"),MATCH($B$50,INDIRECT($B57&"!B53:B78"),0),MATCH(J$4,INDIRECT($B57&"!C52:N52"),0)) -> -0.042205297 | K57: =INDEX(INDIRECT($B57&"!C53:N78"),MATCH($B$50,INDIRECT($B57&"!B53:B78"),0),MATCH(K$4,INDIRECT($B57&"!C52:N52"),0)) -> -0.041782054
B58: Jungheinrich | E58: =INDEX(INDIRECT($B58&"!C53:N78"),MATCH($B$50,INDIRECT($B58&"!B53:B78"),0),MATCH(E$4,INDIRECT($B58&"!C52:N52"),0)) -> 0.043470479 | F58: =INDEX(INDIRECT($B58&"!C53:N78"),MATCH($B$50,INDIRECT($B58&"!B53:B78"),0),MATCH(F$4,INDIRECT($B58&"!C52:N52"),0)) -> 0.039719073 | G58: =INDEX(INDIRECT($B58&"!C53:N78"),MATCH($B$50,INDIRECT($B58&"!B53:B78"),0),MATCH(G$4,INDIRECT($B58&"!C52:N52"),0)) -> 0.06279708 | H58: =INDEX(INDIRECT($B58&"!C53:N78"),MATCH($B$50,INDIRECT($B58&"!B53:B78"),0),MATCH(H$4,INDIRECT($B58&"!C52:N52"),0)) -> 0.056508794 | I58: =INDEX(INDIRECT($B58&"!C53:N78"),MATCH($B$50,INDIRECT($B58&"!B53:B78"),0),MATCH(I$4,INDIRECT($B58&"!C52:N52"),0)) -> 0.053963415 | J58: =INDEX(INDIRECT($B58&"!C53:N78"),MATCH($B$50,INDIRECT($B58&"!B53:B78"),0),MATCH(J$4,INDIRECT($B58&"!C52:N52"),0)) -> 0.053597778 | K58: =INDEX(INDIRECT($B58&"!C53:N78"),MATCH($B$50,INDIRECT($B58&"!B53:B78"),0),MATCH(K$4,INDIRECT($B58&"!C52:N52"),0)) -> 0.052497575
B59: Manitou_BF | E59: =INDEX(INDIRECT($B59&"!C53:N78"),MATCH($B$50,INDIRECT($B59&"!B53:B78"),0),MATCH(E$4,INDIRECT($B59&"!C52:N52"),0)) -> 0.045675416 | F59: =INDEX(INDIRECT($B59&"!C53:N78"),MATCH($B$50,INDIRECT($B59&"!B53:B78"),0),MATCH(F$4,INDIRECT($B59&"!C52:N52"),0)) -> 0.024971847 | G59: =INDEX(INDIRECT($B59&"!C53:N78"),MATCH($B$50,INDIRECT($B59&"!B53:B78"),0),MATCH(G$4,INDIRECT($B59&"!C52:N52"),0)) -> 0.046280693 | H59: =INDEX(INDIRECT($B59&"!C53:N78"),MATCH($B$50,INDIRECT($B59&"!B53:B78"),0),MATCH(H$4,INDIRECT($B59&"!C52:N52"),0)) -> 0.023172584 | I59: =INDEX(INDIRECT($B59&"!C53:N78"),MATCH($B$50,INDIRECT($B59&"!B53:B78"),0),MATCH(I$4,INDIRECT($B59&"!C52:N52"),0)) -> 0.049939192 | J59: =INDEX(INDIRECT($B59&"!C53:N78"),MATCH($B$50,INDIRECT($B59&"!B53:B78"),0),MATCH(J$4,INDIRECT($B59&"!C52:N52"),0)) -> 0.045888358 | K59: =INDEX(INDIRECT($B59&"!C53:N78"),MATCH($B$50,INDIRECT($B59&"!B53:B78"),0),MATCH(K$4,INDIRECT($B59&"!C52:N52"),0)) -> 0.028842713
B61: Mean | E61: =IFERROR(AVERAGE(E51:E59),"-") -> 0.051733386 | F61: =IFERROR(AVERAGE(F51:F59),"-") -> 0.052573053 | G61: =IFERROR(AVERAGE(G51:G59),"-") -> 0.045387384 | H61: =IFERROR(AVERAGE(H51:H59),"-") -> 0.040988883 | I61: =IFERROR(AVERAGE(I51:I59),"-") -> 0.03897749 | J61: =IFERROR(AVERAGE(J51:J59),"-") -> 0.045506606 | K61: =IFERROR(AVERAGE(K51:K59),"-") -> 0.039162331
B62: Median | E62: =IFERROR(MEDIAN(E51:E59),"-") -> 0.044572947 | F62: =IFERROR(MEDIAN(F51:F59),"-") -> 0.052125946 | G62: =IFERROR(MEDIAN(G51:G59),"-") -> 0.06279708 | H62: =IFERROR(MEDIAN(H51:H59),"-") -> 0.053486468 | I62: =IFERROR(MEDIAN(I51:I59),"-") -> 0.04457716 | J62: =IFERROR(MEDIAN(J51:J59),"-") -> 0.045888358 | K62: =IFERROR(MEDIAN(K51:K59),"-") -> 0.028842713
B64: Liquidity Ratios
B66: Current Ratio
B67: Honeywell_International | E67: =INDEX(INDIRECT($B67&"!C53:N78"),MATCH($B$66,INDIRECT($B67&"!B53:B78"),0),MATCH(E$4,INDIRECT($B67&"!C52:N52"),0)) -> 1.3428556 | F67: =INDEX(INDIRECT($B67&"!C53:N78"),MATCH($B$66,INDIRECT($B67&"!B53:B78"),0),MATCH(F$4,INDIRECT($B67&"!C52:N52"),0)) -> 1.4676772 | G67: =INDEX(INDIRECT($B67&"!C53:N78"),MATCH($B$66,INDIRECT($B67&"!B53:B78"),0),MATCH(G$4,INDIRECT($B67&"!C52:N52"),0)) -> 1.3005946 | H67: =INDEX(INDIRECT($B67&"!C53:N78"),MATCH($B$66,INDIRECT($B67&"!B53:B78"),0),MATCH(H$4,INDIRECT($B67&"!C52:N52"),0)) -> 1.2529843 | I67: =INDEX(INDIRECT($B67&"!C53:N78"),MATCH($B$66,INDIRECT($B67&"!B53:B78"),0),MATCH(I$4,INDIRECT($B67&"!C52:N52"),0)) -> 1.2677059 | J67: =INDEX(INDIRECT($B67&"!C53:N78"),MATCH($B$66,INDIRECT($B67&"!B53:B78"),0),MATCH(J$4,INDIRECT($B67&"!C52:N52"),0)) -> 1.3129469 | K67: =INDEX(INDIRECT($B67&"!C53:N78"),MATCH($B$66,INDIRECT($B67&"!B53:B78"),0),MATCH(K$4,INDIRECT($B67&"!C52:N52"),0)) -> 1.358143
B68: Daifuku | E68: =INDEX(INDIRECT($B68&"!C53:N78"),MATCH($B$66,INDIRECT($B68&"!B53:B78"),0),MATCH(E$4,INDIRECT($B68&"!C52:N52"),0)) -> 2.3049353 | F68: =INDEX(INDIRECT($B68&"!C53:N78"),MATCH($B$66,INDIRECT($B68&"!B53:B78"),0),MATCH(F$4,INDIRECT($B68&"!C52:N52"),0)) -> 2.3502393 | G68: =INDEX(INDIRECT($B68&"!C53:N78"),MATCH($B$66,INDIRECT($B68&"!B53:B78"),0),MATCH(G$4,INDIRECT($B68&"!C52:N52"),0)) -> 2.195917 | H68: =INDEX(INDIRECT($B68&"!C53:N78"),MATCH($B$66,INDIRECT($B68&"!B53:B78"),0),MATCH(H$4,INDIRECT($B68&"!C52:N52"),0)) -> 2.13565 | I68: =INDEX(INDIRECT($B68&"!C53:N78"),MATCH($B$66,INDIRECT($B68&"!B53:B78"),0),MATCH(I$4,INDIRECT($B68&"!C52:N52"),0)) -> - | J68: =INDEX(INDIRECT($B68&"!C53:N78"),MATCH($B$66,INDIRECT($B68&"!B53:B78"),0),MATCH(J$4,INDIRECT($B68&"!C52:N52"),0)) -> 2.4812083 | K68: =INDEX(INDIRECT($B68&"!C53:N78"),MATCH($B$66,INDIRECT($B68&"!B53:B78"),0),MATCH(K$4,INDIRECT($B68&"!C52:N52"),0)) -> 2.595098
B69: Hyster_Yale | E69: =INDEX(INDIRECT($B69&"!C53:N78"),MATCH($B$66,INDIRECT($B69&"!B53:B78"),0),MATCH(E$4,INDIRECT($B69&"!C52:N52"),0)) -> 1.4146879 | F69: =INDEX(INDIRECT($B69&"!C53:N78"),MATCH($B$66,INDIRECT($B69&"!B53:B78"),0),MATCH(F$4,INDIRECT($B69&"!C52:N52"),0)) -> 1.4945099 | G69: =INDEX(INDIRECT($B69&"!C53:N78"),MATCH($B$66,INDIRECT($B69&"!B53:B78"),0),MATCH(G$4,INDIRECT($B69&"!C52:N52"),0)) -> 1.2221619 | H69: =INDEX(INDIRECT($B69&"!C53:N78"),MATCH($B$66,INDIRECT($B69&"!B53:B78"),0),MATCH(H$4,INDIRECT($B69&"!C52:N52"),0)) -> 1.0862313 | I69: =INDEX(INDIRECT($B69&"!C53:N78"),MATCH($B$66,INDIRECT($B69&"!B53:B78"),0),MATCH(I$4,INDIRECT($B69&"!C52:N52"),0)) -> 1.2227967 | J69: =INDEX(INDIRECT($B69&"!C53:N78"),MATCH($B$66,INDIRECT($B69&"!B53:B78"),0),MATCH(J$4,INDIRECT($B69&"!C52:N52"),0)) -> 1.354854 | K69: =INDEX(INDIRECT($B69&"!C53:N78"),MATCH($B$66,INDIRECT($B69&"!B53:B78"),0),MATCH(K$4,INDIRECT($B69&"!C52:N52"),0)) -> 1.3922854
B70: Mitsubishi_Logisnext | E70: =INDEX(INDIRECT($B70&"!C53:N78"),MATCH($B$66,INDIRECT($B70&"!B53:B78"),0),MATCH(E$4,INDIRECT($B70&"!C52:N52"),0)) -> 1.2532617 | F70: =INDEX(INDIRECT($B70&"!C53:N78"),MATCH($B$66,INDIRECT($B70&"!B53:B78"),0),MATCH(F$4,INDIRECT($B70&"!C52:N52"),0)) -> 1.2944427 | G70: =INDEX(INDIRECT($B70&"!C53:N78"),MATCH($B$66,INDIRECT($B70&"!B53:B78"),0),MATCH(G$4,INDIRECT($B70&"!C52:N52"),0)) -> 1.3147357 | H70: =INDEX(INDIRECT($B70&"!C53:N78"),MATCH($B$66,INDIRECT($B70&"!B53:B78"),0),MATCH(H$4,INDIRECT($B70&"!C52:N52"),0)) -> 1.2676071 | I70: =INDEX(INDIRECT($B70&"!C53:N78"),MATCH($B$66,INDIRECT($B70&"!B53:B78"),0),MATCH(I$4,INDIRECT($B70&"!C52:N52"),0)) -> 1.3631277 | J70: =INDEX(INDIRECT($B70&"!C53:N78"),MATCH($B$66,INDIRECT($B70&"!B53:B78"),0),MATCH(J$4,INDIRECT($B70&"!C52:N52"),0)) -> 1.4715446 | K70: =INDEX(INDIRECT($B70&"!C53:N78"),MATCH($B$66,INDIRECT($B70&"!B53:B78"),0),MATCH(K$4,INDIRECT($B70&"!C52:N52"),0)) -> 1.4994428
B71: Toyota_Industries | E71: =INDEX(INDIRECT($B71&"!C53:N78"),MATCH($B$66,INDIRECT($B71&"!B53:B78"),0),MATCH(E$4,INDIRECT($B71&"!C52:N52"),0)) -> 1.7857518 | F71: =INDEX(INDIRECT($B71&"!C53:N78"),MATCH($B$66,INDIRECT($B71&"!B53:B78"),0),MATCH(F$4,INDIRECT($B71&"!C52:N52"),0)) -> 1.639469 | G71: =INDEX(INDIRECT($B71&"!C53:N78"),MATCH($B$66,INDIRECT($B71&"!B53:B78"),0),MATCH(G$4,INDIRECT($B71&"!C52:N52"),0)) -> 1.6433252 | H71: =INDEX(INDIRECT($B71&"!C53:N78"),MATCH($B$66,INDIRECT($B71&"!B53:B78"),0),MATCH(H$4,INDIRECT($B71&"!C52:N52"),0)) -> 1.7645527 | I71: =INDEX(INDIRECT($B71&"!C53:N78"),MATCH($B$66,INDIRECT($B71&"!B53:B78"),0),MATCH(I$4,INDIRECT($B71&"!C52:N52"),0)) -> 1.9091854 | J71: =INDEX(INDIRECT($B71&"!C53:N78"),MATCH($B$66,INDIRECT($B71&"!B53:B78"),0),MATCH(J$4,INDIRECT($B71&"!C52:N52"),0)) -> 1.9166965 | K71: =INDEX(INDIRECT($B71&"!C53:N78"),MATCH($B$66,INDIRECT($B71&"!B53:B78"),0),MATCH(K$4,INDIRECT($B71&"!C52:N52"),0)) -> 1.7292143
B72: Symbotic | E72: =INDEX(INDIRECT($B72&"!C53:N78"),MATCH($B$66,INDIRECT($B72&"!B53:B78"),0),MATCH(E$4,INDIRECT($B72&"!C52:N52"),0)) -> 0.048552268 | F72: =INDEX(INDIRECT($B72&"!C53:N78"),MATCH($B$66,INDIRECT($B72&"!B53:B78"),0),MATCH(F$4,INDIRECT($B72&"!C52:N52"),0)) -> - | G72: =INDEX(INDIRECT($B72&"!C53:N78"),MATCH($B$66,INDIRECT($B72&"!B53:B78"),0),MATCH(G$4,INDIRECT($B72&"!C52:N52"),0)) -> 1.1019032 | H72: =INDEX(INDIRECT($B72&"!C53:N78"),MATCH($B$66,INDIRECT($B72&"!B53:B78"),0),MATCH(H$4,INDIRECT($B72&"!C52:N52"),0)) -> 0.93345321 | I72: =INDEX(INDIRECT($B72&"!C53:N78"),MATCH($B$66,INDIRECT($B72&"!B53:B78"),0),MATCH(I$4,INDIRECT($B72&"!C52:N52"),0)) -> 1.3316466 | J72: =INDEX(INDIRECT($B72&"!C53:N78"),MATCH($B$66,INDIRECT($B72&"!B53:B78"),0),MATCH(J$4,INDIRECT($B72&"!C52:N52"),0)) -> 1.0811675 | K72: =INDEX(INDIRECT($B72&"!C53:N78"),MATCH($B$66,INDIRECT($B72&"!B53:B78"),0),MATCH(K$4,INDIRECT($B72&"!C52:N52"),0)) -> 1.055603
B73: KENGIC | E73: =INDEX(INDIRECT($B73&"!C53:N78"),MATCH($B$66,INDIRECT($B73&"!B53:B78"),0),MATCH(E$4,INDIRECT($B73&"!C52:N52"),0)) -> 1.0747159 | F73: =INDEX(INDIRECT($B73&"!C53:N78"),MATCH($B$66,INDIRECT($B73&"!B53:B78"),0),MATCH(F$4,INDIRECT($B73&"!C52:N52"),0)) -> 1.2205577 | G73: =INDEX(INDIRECT($B73&"!C53:N78"),MATCH($B$66,INDIRECT($B73&"!B53:B78"),0),MATCH(G$4,INDIRECT($B73&"!C52:N52"),0)) -> 1.2008068 | H73: =INDEX(INDIRECT($B73&"!C53:N78"),MATCH($B$66,INDIRECT($B73&"!B53:B78"),0),MATCH(H$4,INDIRECT($B73&"!C52:N52"),0)) -> 1.9719743 | I73: =INDEX(INDIRECT($B73&"!C53:N78"),MATCH($B$66,INDIRECT($B73&"!B53:B78"),0),MATCH(I$4,INDIRECT($B73&"!C52:N52"),0)) -> 1.6092714 | J73: =INDEX(INDIRECT($B73&"!C53:N78"),MATCH($B$66,INDIRECT($B73&"!B53:B78"),0),MATCH(J$4,INDIRECT($B73&"!C52:N52"),0)) -> 1.2934924 | K73: =INDEX(INDIRECT($B73&"!C53:N78"),MATCH($B$66,INDIRECT($B73&"!B53:B78"),0),MATCH(K$4,INDIRECT($B73&"!C52:N52"),0)) -> 1.1377357
B74: Jungheinrich | E74: =INDEX(INDIRECT($B74&"!C53:N78"),MATCH($B$66,INDIRECT($B74&"!B53:B78"),0),MATCH(E$4,INDIRECT($B74&"!C52:N52"),0)) -> 1.5235372 | F74: =INDEX(INDIRECT($B74&"!C53:N78"),MATCH($B$66,INDIRECT($B74&"!B53:B78"),0),MATCH(F$4,INDIRECT($B74&"!C52:N52"),0)) -> 1.5162501 | G74: =INDEX(INDIRECT($B74&"!C53:N78"),MATCH($B$66,INDIRECT($B74&"!B53:B78"),0),MATCH(G$4,INDIRECT($B74&"!C52:N52"),0)) -> 1.3555452 | H74: =INDEX(INDIRECT($B74&"!C53:N78"),MATCH($B$66,INDIRECT($B74&"!B53:B78"),0),MATCH(H$4,INDIRECT($B74&"!C52:N52"),0)) -> 1.4688519 | I74: =INDEX(INDIRECT($B74&"!C53:N78"),MATCH($B$66,INDIRECT($B74&"!B53:B78"),0),MATCH(I$4,INDIRECT($B74&"!C52:N52"),0)) -> 1.255719 | J74: =INDEX(INDIRECT($B74&"!C53:N78"),MATCH($B$66,INDIRECT($B74&"!B53:B78"),0),MATCH(J$4,INDIRECT($B74&"!C52:N52"),0)) -> 1.4295947 | K74: =INDEX(INDIRECT($B74&"!C53:N78"),MATCH($B$66,INDIRECT($B74&"!B53:B78"),0),MATCH(K$4,INDIRECT($B74&"!C52:N52"),0)) -> 1.4325139
B75: Manitou_BF | E75: =INDEX(INDIRECT($B75&"!C53:N78"),MATCH($B$66,INDIRECT($B75&"!B53:B78"),0),MATCH(E$4,INDIRECT($B75&"!C52:N52"),0)) -> 2.0778055 | F75: =INDEX(INDIRECT($B75&"!C53:N78"),MATCH($B$66,INDIRECT($B75&"!B53:B78"),0),MATCH(F$4,INDIRECT($B75&"!C52:N52"),0)) -> 2.3593258 | G75: =INDEX(INDIRECT($B75&"!C53:N78"),MATCH($B$66,INDIRECT($B75&"!B53:B78"),0),MATCH(G$4,INDIRECT($B75&"!C52:N52"),0)) -> 2.0629274 | H75: =INDEX(INDIRECT($B75&"!C53:N78"),MATCH($B$66,INDIRECT($B75&"!B53:B78"),0),MATCH(H$4,INDIRECT($B75&"!C52:N52"),0)) -> 1.7706085 | I75: =INDEX(INDIRECT($B75&"!C53:N78"),MATCH($B$66,INDIRECT($B75&"!B53:B78"),0),MATCH(I$4,INDIRECT($B75&"!C52:N52"),0)) -> 1.6259339 | J75: =INDEX(INDIRECT($B75&"!C53:N78"),MATCH($B$66,INDIRECT($B75&"!B53:B78"),0),MATCH(J$4,INDIRECT($B75&"!C52:N52"),0)) -> 1.70353 | K75: =INDEX(INDIRECT($B75&"!C53:N78"),MATCH($B$66,INDIRECT($B75&"!B53:B78"),0),MATCH(K$4,INDIRECT($B75&"!C52:N52"),0)) -> 1.6371404
B77: Mean | E77: =IFERROR(AVERAGE(E67:E75),"-") -> 1.4251226 | F77: =IFERROR(AVERAGE(F67:F75),"-") -> 1.667809 | G77: =IFERROR(AVERAGE(G67:G75),"-") -> 1.4886574 | H77: =IFERROR(AVERAGE(H67:H75),"-") -> 1.5168793 | I77: =IFERROR(AVERAGE(I67:I75),"-") -> 1.4481733 | J77: =IFERROR(AVERAGE(J67:J75),"-") -> 1.5605594 | K77: =IFERROR(AVERAGE(K67:K75),"-") -> 1.5374641
B78: Median | E78: =IFERROR(MEDIAN(E67:E75),"-") -> 1.4146879 | F78: =IFERROR(MEDIAN(F67:F75),"-") -> 1.50538 | G78: =IFERROR(MEDIAN(G67:G75),"-") -> 1.3147357 | H78: =IFERROR(MEDIAN(H67:H75),"-") -> 1.4688519 | I78: =IFERROR(MEDIAN(I67:I75),"-") -> 1.3473871 | J78: =IFERROR(MEDIAN(J67:J75),"-") -> 1.4295947 | K78: =IFERROR(MEDIAN(K67:K75),"-") -> 1.4325139
B80: Quick Ratio
B81: Honeywell_International | E81: =INDEX(INDIRECT($B81&"!C53:N78"),MATCH($B$80,INDIRECT($B81&"!B53:B78"),0),MATCH(E$4,INDIRECT($B81&"!C52:N52"),0)) -> 1.0985744 | F81: =INDEX(INDIRECT($B81&"!C53:N78"),MATCH($B$80,INDIRECT($B81&"!B53:B78"),0),MATCH(F$4,INDIRECT($B81&"!C52:N52"),0)) -> 1.2338386 | G81: =INDEX(INDIRECT($B81&"!C53:N78"),MATCH($B$80,INDIRECT($B81&"!B53:B78"),0),MATCH(G$4,INDIRECT($B81&"!C52:N52"),0)) -> 1.0372155 | H81: =INDEX(INDIRECT($B81&"!C53:N78"),MATCH($B$80,INDIRECT($B81&"!B53:B78"),0),MATCH(H$4,INDIRECT($B81&"!C52:N52"),0)) -> 0.97522319 | I81: =INDEX(INDIRECT($B81&"!C53:N78"),MATCH($B$80,INDIRECT($B81&"!B53:B78"),0),MATCH(I$4,INDIRECT($B81&"!C52:N52"),0)) -> 0.93446248 | J81: =INDEX(INDIRECT($B81&"!C53:N78"),MATCH($B$80,INDIRECT($B81&"!B53:B78"),0),MATCH(J$4,INDIRECT($B81&"!C52:N52"),0)) -> 1.0098796 | K81: =INDEX(INDIRECT($B81&"!C53:N78"),MATCH($B$80,INDIRECT($B81&"!B53:B78"),0),MATCH(K$4,INDIRECT($B81&"!C52:N52"),0)) -> 1.0437298
B82: Daifuku | E82: =INDEX(INDIRECT($B82&"!C53:N78"),MATCH($B$80,INDIRECT($B82&"!B53:B78"),0),MATCH(E$4,INDIRECT($B82&"!C52:N52"),0)) -> 2.0645373 | F82: =INDEX(INDIRECT($B82&"!C53:N78"),MATCH($B$80,INDIRECT($B82&"!B53:B78"),0),MATCH(F$4,INDIRECT($B82&"!C52:N52"),0)) -> 2.1065707 | G82: =INDEX(INDIRECT($B82&"!C53:N78"),MATCH($B$80,INDIRECT($B82&"!B53:B78"),0),MATCH(G$4,INDIRECT($B82&"!C52:N52"),0)) -> 1.9583461 | H82: =INDEX(INDIRECT($B82&"!C53:N78"),MATCH($B$80,INDIRECT($B82&"!B53:B78"),0),MATCH(H$4,INDIRECT($B82&"!C52:N52"),0)) -> 1.8099558 | I82: =INDEX(INDIRECT($B82&"!C53:N78"),MATCH($B$80,INDIRECT($B82&"!B53:B78"),0),MATCH(I$4,INDIRECT($B82&"!C52:N52"),0)) -> - | J82: =INDEX(INDIRECT($B82&"!C53:N78"),MATCH($B$80,INDIRECT($B82&"!B53:B78"),0),MATCH(J$4,INDIRECT($B82&"!C52:N52"),0)) -> 2.1874125 | K82: =INDEX(INDIRECT($B82&"!C53:N78"),MATCH($B$80,INDIRECT($B82&"!B53:B78"),0),MATCH(K$4,INDIRECT($B82&"!C52:N52"),0)) -> 2.3145515
B83: Hyster_Yale | E83: =INDEX(INDIRECT($B83&"!C53:N78"),MATCH($B$80,INDIRECT($B83&"!B53:B78"),0),MATCH(E$4,INDIRECT($B83&"!C52:N52"),0)) -> 0.72937576 | F83: =INDEX(INDIRECT($B83&"!C53:N78"),MATCH($B$80,INDIRECT($B83&"!B53:B78"),0),MATCH(F$4,INDIRECT($B83&"!C52:N52"),0)) -> 0.82061119 | G83: =INDEX(INDIRECT($B83&"!C53:N78"),MATCH($B$80,INDIRECT($B83&"!B53:B78"),0),MATCH(G$4,INDIRECT($B83&"!C52:N52"),0)) -> 0.51511859 | H83: =INDEX(INDIRECT($B83&"!C53:N78"),MATCH($B$80,INDIRECT($B83&"!B53:B78"),0),MATCH(H$4,INDIRECT($B83&"!C52:N52"),0)) -> 0.49087795 | I83: =INDEX(INDIRECT($B83&"!C53:N78"),MATCH($B$80,INDIRECT($B83&"!B53:B78"),0),MATCH(I$4,INDIRECT($B83&"!C52:N52"),0)) -> 0.55342196 | J83: =INDEX(INDIRECT($B83&"!C53:N78"),MATCH($B$80,INDIRECT($B83&"!B53:B78"),0),MATCH(J$4,INDIRECT($B83&"!C52:N52"),0)) -> 0.6418376 | K83: =INDEX(INDIRECT($B83&"!C53:N78"),MATCH($B$80,INDIRECT($B83&"!B53:B78"),0),MATCH(K$4,INDIRECT($B83&"!C52:N52"),0)) -> 0.67839923
B84: Mitsubishi_Logisnext | E84: =INDEX(INDIRECT($B84&"!C53:N78"),MATCH($B$80,INDIRECT($B84&"!B53:B78"),0),MATCH(E$4,INDIRECT($B84&"!C52:N52"),0)) -> 0.85210269 | F84: =INDEX(INDIRECT($B84&"!C53:N78"),MATCH($B$80,INDIRECT($B84&"!B53:B78"),0),MATCH(F$4,INDIRECT($B84&"!C52:N52"),0)) -> 0.88318036 | G84: =INDEX(INDIRECT($B84&"!C53:N78"),MATCH($B$80,INDIRECT($B84&"!B53:B78"),0),MATCH(G$4,INDIRECT($B84&"!C52:N52"),0)) -> 0.77949022 | H84: =INDEX(INDIRECT($B84&"!C53:N78"),MATCH($B$80,INDIRECT($B84&"!B53:B78"),0),MATCH(H$4,INDIRECT($B84&"!C52:N52"),0)) -> 0.74874586 | I84: =INDEX(INDIRECT($B84&"!C53:N78"),MATCH($B$80,INDIRECT($B84&"!B53:B78"),0),MATCH(I$4,INDIRECT($B84&"!C52:N52"),0)) -> 0.77472888 | J84: =INDEX(INDIRECT($B84&"!C53:N78"),MATCH($B$80,INDIRECT($B84&"!B53:B78"),0),MATCH(J$4,INDIRECT($B84&"!C52:N52"),0)) -> 0.83119942 | K84: =INDEX(INDIRECT($B84&"!C53:N78"),MATCH($B$80,INDIRECT($B84&"!B53:B78"),0),MATCH(K$4,INDIRECT($B84&"!C52:N52"),0)) -> 0.84493738
B85: Toyota_Industries | E85: =INDEX(INDIRECT($B85&"!C53:N78"),MATCH($B$80,INDIRECT($B85&"!B53:B78"),0),MATCH(E$4,INDIRECT($B85&"!C52:N52"),0)) -> 1.5232718 | F85: =INDEX(INDIRECT($B85&"!C53:N78"),MATCH($B$80,INDIRECT($B85&"!B53:B78"),0),MATCH(F$4,INDIRECT($B85&"!C52:N52"),0)) -> 1.3933392 | G85: =INDEX(INDIRECT($B85&"!C53:N78"),MATCH($B$80,INDIRECT($B85&"!B53:B78"),0),MATCH(G$4,INDIRECT($B85&"!C52:N52"),0)) -> 1.3271932 | H85: =INDEX(INDIRECT($B85&"!C53:N78"),MATCH($B$80,INDIRECT($B85&"!B53:B78"),0),MATCH(H$4,INDIRECT($B85&"!C52:N52"),0)) -> 1.4189058 | I85: =INDEX(INDIRECT($B85&"!C53:N78"),MATCH($B$80,INDIRECT($B85&"!B53:B78"),0),MATCH(I$4,INDIRECT($B85&"!C52:N52"),0)) -> 1.5315115 | J85: =INDEX(INDIRECT($B85&"!C53:N78"),MATCH($B$80,INDIRECT($B85&"!B53:B78"),0),MATCH(J$4,INDIRECT($B85&"!C52:N52"),0)) -> 1.5346401 | K85: =INDEX(INDIRECT($B85&"!C53:N78"),MATCH($B$80,INDIRECT($B85&"!B53:B78"),0),MATCH(K$4,INDIRECT($B85&"!C52:N52"),0)) -> 1.3671297
B86: Symbotic | E86: =INDEX(INDIRECT($B86&"!C53:N78"),MATCH($B$80,INDIRECT($B86&"!B53:B78"),0),MATCH(E$4,INDIRECT($B86&"!C52:N52"),0)) -> 0.048552268 | F86: =INDEX(INDIRECT($B86&"!C53:N78"),MATCH($B$80,INDIRECT($B86&"!B53:B78"),0),MATCH(F$4,INDIRECT($B86&"!C52:N52"),0)) -> - | G86: =INDEX(INDIRECT($B86&"!C53:N78"),MATCH($B$80,INDIRECT($B86&"!B53:B78"),0),MATCH(G$4,INDIRECT($B86&"!C52:N52"),0)) -> 0.92617175 | H86: =INDEX(INDIRECT($B86&"!C53:N78"),MATCH($B$80,INDIRECT($B86&"!B53:B78"),0),MATCH(H$4,INDIRECT($B86&"!C52:N52"),0)) -> 0.80071168 | I86: =INDEX(INDIRECT($B86&"!C53:N78"),MATCH($B$80,INDIRECT($B86&"!B53:B78"),0),MATCH(I$4,INDIRECT($B86&"!C52:N52"),0)) -> 1.2272997 | J86: =INDEX(INDIRECT($B86&"!C53:N78"),MATCH($B$80,INDIRECT($B86&"!B53:B78"),0),MATCH(J$4,INDIRECT($B86&"!C52:N52"),0)) -> 0.98611271 | K86: =INDEX(INDIRECT($B86&"!C53:N78"),MATCH($B$80,INDIRECT($B86&"!B53:B78"),0),MATCH(K$4,INDIRECT($B86&"!C52:N52"),0)) -> 0.95016817
B87: KENGIC | E87: =INDEX(INDIRECT($B87&"!C53:N78"),MATCH($B$80,INDIRECT($B87&"!B53:B78"),0),MATCH(E$4,INDIRECT($B87&"!C52:N52"),0)) -> 0.74707164 | F87: =INDEX(INDIRECT($B87&"!C53:N78"),MATCH($B$80,INDIRECT($B87&"!B53:B78"),0),MATCH(F$4,INDIRECT($B87&"!C52:N52"),0)) -> 0.81269658 | G87: =INDEX(INDIRECT($B87&"!C53:N78"),MATCH($B$80,INDIRECT($B87&"!B53:B78"),0),MATCH(G$4,INDIRECT($B87&"!C52:N52"),0)) -> 0.73711637 | H87: =INDEX(INDIRECT($B87&"!C53:N78"),MATCH($B$80,INDIRECT($B87&"!B53:B78"),0),MATCH(H$4,INDIRECT($B87&"!C52:N52"),0)) -> 1.553504 | I87: =INDEX(INDIRECT($B87&"!C53:N78"),MATCH($B$80,INDIRECT($B87&"!B53:B78"),0),MATCH(I$4,INDIRECT($B87&"!C52:N52"),0)) -> 1.1292783 | J87: =INDEX(INDIRECT($B87&"!C53:N78"),MATCH($B$80,INDIRECT($B87&"!B53:B78"),0),MATCH(J$4,INDIRECT($B87&"!C52:N52"),0)) -> 0.8831345 | K87: =INDEX(INDIRECT($B87&"!C53:N78"),MATCH($B$80,INDIRECT($B87&"!B53:B78"),0),MATCH(K$4,INDIRECT($B87&"!C52:N52"),0)) -> 0.56281467
B88: Jungheinrich | E88: =INDEX(INDIRECT($B88&"!C53:N78"),MATCH($B$80,INDIRECT($B88&"!B53:B78"),0),MATCH(E$4,INDIRECT($B88&"!C52:N52"),0)) -> 1.1258902 | F88: =INDEX(INDIRECT($B88&"!C53:N78"),MATCH($B$80,INDIRECT($B88&"!B53:B78"),0),MATCH(F$4,INDIRECT($B88&"!C52:N52"),0)) -> 1.197037 | G88: =INDEX(INDIRECT($B88&"!C53:N78"),MATCH($B$80,INDIRECT($B88&"!B53:B78"),0),MATCH(G$4,INDIRECT($B88&"!C52:N52"),0)) -> 0.97069268 | H88: =INDEX(INDIRECT($B88&"!C53:N78"),MATCH($B$80,INDIRECT($B88&"!B53:B78"),0),MATCH(H$4,INDIRECT($B88&"!C52:N52"),0)) -> 0.96757146 | I88: =INDEX(INDIRECT($B88&"!C53:N78"),MATCH($B$80,INDIRECT($B88&"!B53:B78"),0),MATCH(I$4,INDIRECT($B88&"!C52:N52"),0)) -> 0.87773456 | J88: =INDEX(INDIRECT($B88&"!C53:N78"),MATCH($B$80,INDIRECT($B88&"!B53:B78"),0),MATCH(J$4,INDIRECT($B88&"!C52:N52"),0)) -> 1.0199399 | K88: =INDEX(INDIRECT($B88&"!C53:N78"),MATCH($B$80,INDIRECT($B88&"!B53:B78"),0),MATCH(K$4,INDIRECT($B88&"!C52:N52"),0)) -> 0.99040483
B89: Manitou_BF | E89: =INDEX(INDIRECT($B89&"!C53:N78"),MATCH($B$80,INDIRECT($B89&"!B53:B78"),0),MATCH(E$4,INDIRECT($B89&"!C52:N52"),0)) -> 0.90860212 | F89: =INDEX(INDIRECT($B89&"!C53:N78"),MATCH($B$80,INDIRECT($B89&"!B53:B78"),0),MATCH(F$4,INDIRECT($B89&"!C52:N52"),0)) -> 1.2101433 | G89: =INDEX(INDIRECT($B89&"!C53:N78"),MATCH($B$80,INDIRECT($B89&"!B53:B78"),0),MATCH(G$4,INDIRECT($B89&"!C52:N52"),0)) -> 1.0935478 | H89: =INDEX(INDIRECT($B89&"!C53:N78"),MATCH($B$80,INDIRECT($B89&"!B53:B78"),0),MATCH(H$4,INDIRECT($B89&"!C52:N52"),0)) -> 0.83092332 | I89: =INDEX(INDIRECT($B89&"!C53:N78"),MATCH($B$80,INDIRECT($B89&"!B53:B78"),0),MATCH(I$4,INDIRECT($B89&"!C52:N52"),0)) -> 0.7732071 | J89: =INDEX(INDIRECT($B89&"!C53:N78"),MATCH($B$80,INDIRECT($B89&"!B53:B78"),0),MATCH(J$4,INDIRECT($B89&"!C52:N52"),0)) -> 0.7123204 | K89: =INDEX(INDIRECT($B89&"!C53:N78"),MATCH($B$80,INDIRECT($B89&"!B53:B78"),0),MATCH(K$4,INDIRECT($B89&"!C52:N52"),0)) -> 0.74908359
B91: Mean | E91: =IFERROR(AVERAGE(E81:E89),"-") -> 1.0108865 | F91: =IFERROR(AVERAGE(F81:F89),"-") -> 1.2071771 | G91: =IFERROR(AVERAGE(G81:G89),"-") -> 1.0383214 | H91: =IFERROR(AVERAGE(H81:H89),"-") -> 1.0662688 | I91: =IFERROR(AVERAGE(I81:I89),"-") -> 0.97520555 | J91: =IFERROR(AVERAGE(J81:J89),"-") -> 1.0896085 | K91: =IFERROR(AVERAGE(K81:K89),"-") -> 1.055691
B92: Median | E92: =IFERROR(MEDIAN(E81:E89),"-") -> 0.90860212 | F92: =IFERROR(MEDIAN(F81:F89),"-") -> 1.2035901 | G92: =IFERROR(MEDIAN(G81:G89),"-") -> 0.97069268 | H92: =IFERROR(MEDIAN(H81:H89),"-") -> 0.96757146 | I92: =IFERROR(MEDIAN(I81:I89),"-") -> 0.90609852 | J92: =IFERROR(MEDIAN(J81:J89),"-") -> 0.98611271 | K92: =IFERROR(MEDIAN(K81:K89),"-") -> 0.95016817
B94: Cash Ratio
B95: Honeywell_International | E95: =INDEX(INDIRECT($B95&"!C53:N78"),MATCH($B$94,INDIRECT($B95&"!B53:B78"),0),MATCH(E$4,INDIRECT($B95&"!C52:N52"),0)) -> 0.57553321 | F95: =INDEX(INDIRECT($B95&"!C53:N78"),MATCH($B$94,INDIRECT($B95&"!B53:B78"),0),MATCH(F$4,INDIRECT($B95&"!C52:N52"),0)) -> 0.79283221 | G95: =INDEX(INDIRECT($B95&"!C53:N78"),MATCH($B$94,INDIRECT($B95&"!B53:B78"),0),MATCH(G$4,INDIRECT($B95&"!C52:N52"),0)) -> 0.59068075 | H95: =INDEX(INDIRECT($B95&"!C53:N78"),MATCH($B$94,INDIRECT($B95&"!B53:B78"),0),MATCH(H$4,INDIRECT($B95&"!C52:N52"),0)) -> 0.50707192 | I95: =INDEX(INDIRECT($B95&"!C53:N78"),MATCH($B$94,INDIRECT($B95&"!B53:B78"),0),MATCH(I$4,INDIRECT($B95&"!C52:N52"),0)) -> 0.43664707 | J95: =INDEX(INDIRECT($B95&"!C53:N78"),MATCH($B$94,INDIRECT($B95&"!B53:B78"),0),MATCH(J$4,INDIRECT($B95&"!C52:N52"),0)) -> 0.5152898 | K95: =INDEX(INDIRECT($B95&"!C53:N78"),MATCH($B$94,INDIRECT($B95&"!B53:B78"),0),MATCH(K$4,INDIRECT($B95&"!C52:N52"),0)) -> 0.5900879
B96: Daifuku | E96: =INDEX(INDIRECT($B96&"!C53:N78"),MATCH($B$94,INDIRECT($B96&"!B53:B78"),0),MATCH(E$4,INDIRECT($B96&"!C52:N52"),0)) -> 0.5112441 | F96: =INDEX(INDIRECT($B96&"!C53:N78"),MATCH($B$94,INDIRECT($B96&"!B53:B78"),0),MATCH(F$4,INDIRECT($B96&"!C52:N52"),0)) -> 0.63123919 | G96: =INDEX(INDIRECT($B96&"!C53:N78"),MATCH($B$94,INDIRECT($B96&"!B53:B78"),0),MATCH(G$4,INDIRECT($B96&"!C52:N52"),0)) -> 0.68397593 | H96: =INDEX(INDIRECT($B96&"!C53:N78"),MATCH($B$94,INDIRECT($B96&"!B53:B78"),0),MATCH(H$4,INDIRECT($B96&"!C52:N52"),0)) -> 0.50659711 | I96: =INDEX(INDIRECT($B96&"!C53:N78"),MATCH($B$94,INDIRECT($B96&"!B53:B78"),0),MATCH(I$4,INDIRECT($B96&"!C52:N52"),0)) -> - | J96: =INDEX(INDIRECT($B96&"!C53:N78"),MATCH($B$94,INDIRECT($B96&"!B53:B78"),0),MATCH(J$4,INDIRECT($B96&"!C52:N52"),0)) -> 1.0339659 | K96: =INDEX(INDIRECT($B96&"!C53:N78"),MATCH($B$94,INDIRECT($B96&"!B53:B78"),0),MATCH(K$4,INDIRECT($B96&"!C52:N52"),0)) -> 1.0883004
B97: Hyster_Yale | E97: =INDEX(INDIRECT($B97&"!C53:N78"),MATCH($B$94,INDIRECT($B97&"!B53:B78"),0),MATCH(E$4,INDIRECT($B97&"!C52:N52"),0)) -> 0.079069767 | F97: =INDEX(INDIRECT($B97&"!C53:N78"),MATCH($B$94,INDIRECT($B97&"!B53:B78"),0),MATCH(F$4,INDIRECT($B97&"!C52:N52"),0)) -> 0.20029104 | G97: =INDEX(INDIRECT($B97&"!C53:N78"),MATCH($B$94,INDIRECT($B97&"!B53:B78"),0),MATCH(G$4,INDIRECT($B97&"!C52:N52"),0)) -> 0.059297483 | H97: =INDEX(INDIRECT($B97&"!C53:N78"),MATCH($B$94,INDIRECT($B97&"!B53:B78"),0),MATCH(H$4,INDIRECT($B97&"!C52:N52"),0)) -> 0.043934768 | I97: =INDEX(INDIRECT($B97&"!C53:N78"),MATCH($B$94,INDIRECT($B97&"!B53:B78"),0),MATCH(I$4,INDIRECT($B97&"!C52:N52"),0)) -> 0.064664369 | J97: =INDEX(INDIRECT($B97&"!C53:N78"),MATCH($B$94,INDIRECT($B97&"!B53:B78"),0),MATCH(J$4,INDIRECT($B97&"!C52:N52"),0)) -> 0.091312979 | K97: =INDEX(INDIRECT($B97&"!C53:N78"),MATCH($B$94,INDIRECT($B97&"!B53:B78"),0),MATCH(K$4,INDIRECT($B97&"!C52:N52"),0)) -> 0.068563163
B98: Mitsubishi_Logisnext | E98: =INDEX(INDIRECT($B98&"!C53:N78"),MATCH($B$94,INDIRECT($B98&"!B53:B78"),0),MATCH(E$4,INDIRECT($B98&"!C52:N52"),0)) -> 0.09929101 | F98: =INDEX(INDIRECT($B98&"!C53:N78"),MATCH($B$94,INDIRECT($B98&"!B53:B78"),0),MATCH(F$4,INDIRECT($B98&"!C52:N52"),0)) -> 0.10071237 | G98: =INDEX(INDIRECT($B98&"!C53:N78"),MATCH($B$94,INDIRECT($B98&"!B53:B78"),0),MATCH(G$4,INDIRECT($B98&"!C52:N52"),0)) -> 0.069517 | H98: =INDEX(INDIRECT($B98&"!C53:N78"),MATCH($B$94,INDIRECT($B98&"!B53:B78"),0),MATCH(H$4,INDIRECT($B98&"!C52:N52"),0)) -> 0.063461566 | I98: =INDEX(INDIRECT($B98&"!C53:N78"),MATCH($B$94,INDIRECT($B98&"!B53:B78"),0),MATCH(I$4,INDIRECT($B98&"!C52:N52"),0)) -> 0.094510109 | J98: =INDEX(INDIRECT($B98&"!C53:N78"),MATCH($B$94,INDIRECT($B98&"!B53:B78"),0),MATCH(J$4,INDIRECT($B98&"!C52:N52"),0)) -> 0.085745717 | K98: =INDEX(INDIRECT($B98&"!C53:N78"),MATCH($B$94,INDIRECT($B98&"!B53:B78"),0),MATCH(K$4,INDIRECT($B98&"!C52:N52"),0)) -> 0.10158671
B99: Toyota_Industries | E99: =INDEX(INDIRECT($B99&"!C53:N78"),MATCH($B$94,INDIRECT($B99&"!B53:B78"),0),MATCH(E$4,INDIRECT($B99&"!C52:N52"),0)) -> 0.54742106 | F99: =INDEX(INDIRECT($B99&"!C53:N78"),MATCH($B$94,INDIRECT($B99&"!B53:B78"),0),MATCH(F$4,INDIRECT($B99&"!C52:N52"),0)) -> 0.49831053 | G99: =INDEX(INDIRECT($B99&"!C53:N78"),MATCH($B$94,INDIRECT($B99&"!B53:B78"),0),MATCH(G$4,INDIRECT($B99&"!C52:N52"),0)) -> 0.419429 | H99: =INDEX(INDIRECT($B99&"!C53:N78"),MATCH($B$94,INDIRECT($B99&"!B53:B78"),0),MATCH(H$4,INDIRECT($B99&"!C52:N52"),0)) -> 0.41058538 | I99: =INDEX(INDIRECT($B99&"!C53:N78"),MATCH($B$94,INDIRECT($B99&"!B53:B78"),0),MATCH(I$4,INDIRECT($B99&"!C52:N52"),0)) -> 0.45156683 | J99: =INDEX(INDIRECT($B99&"!C53:N78"),MATCH($B$94,INDIRECT($B99&"!B53:B78"),0),MATCH(J$4,INDIRECT($B99&"!C52:N52"),0)) -> 0.28860668 | K99: =INDEX(INDIRECT($B99&"!C53:N78"),MATCH($B$94,INDIRECT($B99&"!B53:B78"),0),MATCH(K$4,INDIRECT($B99&"!C52:N52"),0)) -> 0.27366343
B100: Symbotic | E100: =INDEX(INDIRECT($B100&"!C53:N78"),MATCH($B$94,INDIRECT($B100&"!B53:B78"),0),MATCH(E$4,INDIRECT($B100&"!C52:N52"),0)) -> 0 | F100: =INDEX(INDIRECT($B100&"!C53:N78"),MATCH($B$94,INDIRECT($B100&"!B53:B78"),0),MATCH(F$4,INDIRECT($B100&"!C52:N52"),0)) -> - | G100: =INDEX(INDIRECT($B100&"!C53:N78"),MATCH($B$94,INDIRECT($B100&"!B53:B78"),0),MATCH(G$4,INDIRECT($B100&"!C52:N52"),0)) -> 0.67588157 | H100: =INDEX(INDIRECT($B100&"!C53:N78"),MATCH($B$94,INDIRECT($B100&"!B53:B78"),0),MATCH(H$4,INDIRECT($B100&"!C52:N52"),0)) -> 0.53196276 | I100: =INDEX(INDIRECT($B100&"!C53:N78"),MATCH($B$94,INDIRECT($B100&"!B53:B78"),0),MATCH(I$4,INDIRECT($B100&"!C52:N52"),0)) -> 0.71590509 | J100: =INDEX(INDIRECT($B100&"!C53:N78"),MATCH($B$94,INDIRECT($B100&"!B53:B78"),0),MATCH(J$4,INDIRECT($B100&"!C52:N52"),0)) -> 0.71988923 | K100: =INDEX(INDIRECT($B100&"!C53:N78"),MATCH($B$94,INDIRECT($B100&"!B53:B78"),0),MATCH(K$4,INDIRECT($B100&"!C52:N52"),0)) -> 0.59089077
B101: KENGIC | E101: =INDEX(INDIRECT($B101&"!C53:N78"),MATCH($B$94,INDIRECT($B101&"!B53:B78"),0),MATCH(E$4,INDIRECT($B101&"!C52:N52"),0)) -> 0.15113165 | F101: =INDEX(INDIRECT($B101&"!C53:N78"),MATCH($B$94,INDIRECT($B101&"!B53:B78"),0),MATCH(F$4,INDIRECT($B101&"!C52:N52"),0)) -> 0.36730172 | G101: =INDEX(INDIRECT($B101&"!C53:N78"),MATCH($B$94,INDIRECT($B101&"!B53:B78"),0),MATCH(G$4,INDIRECT($B101&"!C52:N52"),0)) -> 0.4011849 | H101: =INDEX(INDIRECT($B101&"!C53:N78"),MATCH($B$94,INDIRECT($B101&"!B53:B78"),0),MATCH(H$4,INDIRECT($B101&"!C52:N52"),0)) -> 0.95508927 | I101: =INDEX(INDIRECT($B101&"!C53:N78"),MATCH($B$94,INDIRECT($B101&"!B53:B78"),0),MATCH(I$4,INDIRECT($B101&"!C52:N52"),0)) -> 0.76198294 | J101: =INDEX(INDIRECT($B101&"!C53:N78"),MATCH($B$94,INDIRECT($B101&"!B53:B78"),0),MATCH(J$4,INDIRECT($B101&"!C52:N52"),0)) -> 0.47219098 | K101: =INDEX(INDIRECT($B101&"!C53:N78"),MATCH($B$94,INDIRECT($B101&"!B53:B78"),0),MATCH(K$4,INDIRECT($B101&"!C52:N52"),0)) -> 0.22995525
B102: Jungheinrich | E102: =INDEX(INDIRECT($B102&"!C53:N78"),MATCH($B$94,INDIRECT($B102&"!B53:B78"),0),MATCH(E$4,INDIRECT($B102&"!C52:N52"),0)) -> 0.38547131 | F102: =INDEX(INDIRECT($B102&"!C53:N78"),MATCH($B$94,INDIRECT($B102&"!B53:B78"),0),MATCH(F$4,INDIRECT($B102&"!C52:N52"),0)) -> 0.56445093 | G102: =INDEX(INDIRECT($B102&"!C53:N78"),MATCH($B$94,INDIRECT($B102&"!B53:B78"),0),MATCH(G$4,INDIRECT($B102&"!C52:N52"),0)) -> 0.36285529 | H102: =INDEX(INDIRECT($B102&"!C53:N78"),MATCH($B$94,INDIRECT($B102&"!B53:B78"),0),MATCH(H$4,INDIRECT($B102&"!C52:N52"),0)) -> 0.25507208 | I102: =INDEX(INDIRECT($B102&"!C53:N78"),MATCH($B$94,INDIRECT($B102&"!B53:B78"),0),MATCH(I$4,INDIRECT($B102&"!C52:N52"),0)) -> 0.26581017 | J102: =INDEX(INDIRECT($B102&"!C53:N78"),MATCH($B$94,INDIRECT($B102&"!B53:B78"),0),MATCH(J$4,INDIRECT($B102&"!C52:N52"),0)) -> 0.32712726 | K102: =INDEX(INDIRECT($B102&"!C53:N78"),MATCH($B$94,INDIRECT($B102&"!B53:B78"),0),MATCH(K$4,INDIRECT($B102&"!C52:N52"),0)) -> 0.2907338
B103: Manitou_BF | E103: =INDEX(INDIRECT($B103&"!C53:N78"),MATCH($B$94,INDIRECT($B103&"!B53:B78"),0),MATCH(E$4,INDIRECT($B103&"!C52:N52"),0)) -> 0.045269717 | F103: =INDEX(INDIRECT($B103&"!C53:N78"),MATCH($B$94,INDIRECT($B103&"!B53:B78"),0),MATCH(F$4,INDIRECT($B103&"!C52:N52"),0)) -> 0.3097794 | G103: =INDEX(INDIRECT($B103&"!C53:N78"),MATCH($B$94,INDIRECT($B103&"!B53:B78"),0),MATCH(G$4,INDIRECT($B103&"!C52:N52"),0)) -> 0.35466712 | H103: =INDEX(INDIRECT($B103&"!C53:N78"),MATCH($B$94,INDIRECT($B103&"!B53:B78"),0),MATCH(H$4,INDIRECT($B103&"!C52:N52"),0)) -> 0.087986637 | I103: =INDEX(INDIRECT($B103&"!C53:N78"),MATCH($B$94,INDIRECT($B103&"!B53:B78"),0),MATCH(I$4,INDIRECT($B103&"!C52:N52"),0)) -> 0.059598782 | J103: =INDEX(INDIRECT($B103&"!C53:N78"),MATCH($B$94,INDIRECT($B103&"!B53:B78"),0),MATCH(J$4,INDIRECT($B103&"!C52:N52"),0)) -> 0.054654465 | K103: =INDEX(INDIRECT($B103&"!C53:N78"),MATCH($B$94,INDIRECT($B103&"!B53:B78"),0),MATCH(K$4,INDIRECT($B103&"!C52:N52"),0)) -> 0.062717428
B105: Mean | E105: =IFERROR(AVERAGE(E95:E103),"-") -> 0.26604798 | F105: =IFERROR(AVERAGE(F95:F103),"-") -> 0.43311467 | G105: =IFERROR(AVERAGE(G95:G103),"-") -> 0.40194323 | H105: =IFERROR(AVERAGE(H95:H103),"-") -> 0.37352905 | I105: =IFERROR(AVERAGE(I95:I103),"-") -> 0.35633567 | J105: =IFERROR(AVERAGE(J95:J103),"-") -> 0.39875367 | K105: =IFERROR(AVERAGE(K95:K103),"-") -> 0.36627765
B106: Median | E106: =IFERROR(MEDIAN(E95:E103),"-") -> 0.15113165 | F106: =IFERROR(MEDIAN(F95:F103),"-") -> 0.43280612 | G106: =IFERROR(MEDIAN(G95:G103),"-") -> 0.4011849 | H106: =IFERROR(MEDIAN(H95:H103),"-") -> 0.41058538 | I106: =IFERROR(MEDIAN(I95:I103),"-") -> 0.35122862 | J106: =IFERROR(MEDIAN(J95:J103),"-") -> 0.32712726 | K106: =IFERROR(MEDIAN(K95:K103),"-") -> 0.27366343
B108: Solvency & Leverage Ratios
B110: Debt to Equity | P110: Kion | Q110: Honeywell International | R110: Daifuku | S110: Hyster Yale | T110: Mitsubishi Logisnext | U110: Toyota Industries | V110: Symbotic | W110: KENGIC | X110: Jungheinrich | Y110: ManitouBF
B111: Honeywell_International | E111: =INDEX(INDIRECT($B111&"!C53:N78"),MATCH($B$110,INDIRECT($B111&"!B53:B78"),0),MATCH(E$4,INDIRECT($B111&"!C52:N52"),0)) -> 0.90337407 | F111: =INDEX(INDIRECT($B111&"!C53:N78"),MATCH($B$110,INDIRECT($B111&"!B53:B78"),0),MATCH(F$4,INDIRECT($B111&"!C52:N52"),0)) -> 1.3226964 | G111: =INDEX(INDIRECT($B111&"!C53:N78"),MATCH($B$110,INDIRECT($B111&"!B53:B78"),0),MATCH(G$4,INDIRECT($B111&"!C52:N52"),0)) -> 1.1110453 | H111: =INDEX(INDIRECT($B111&"!C53:N78"),MATCH($B$110,INDIRECT($B111&"!B53:B78"),0),MATCH(H$4,INDIRECT($B111&"!C52:N52"),0)) -> 1.2299814 | I111: =INDEX(INDIRECT($B111&"!C53:N78"),MATCH($B$110,INDIRECT($B111&"!B53:B78"),0),MATCH(I$4,INDIRECT($B111&"!C52:N52"),0)) -> 1.358224 | J111: =INDEX(INDIRECT($B111&"!C53:N78"),MATCH($B$110,INDIRECT($B111&"!B53:B78"),0),MATCH(J$4,INDIRECT($B111&"!C52:N52"),0)) -> 1.7307589 | K111: =INDEX(INDIRECT($B111&"!C53:N78"),MATCH($B$110,INDIRECT($B111&"!B53:B78"),0),MATCH(K$4,INDIRECT($B111&"!C52:N52"),0)) -> 2.2771422 | O111: Debt to Equity | P111: =K241 -> 3.2041782 | Q111: =AVERAGE($E$112:$J$112) -> 0.12922607 | R111: 0.12922607 | S111: 1.4214476 | T111: 2.760737 | U111: 0.43730903 | V111: 33.886875 | W111: 0.60002537 | X111: 0.3855768 | Y111: 0.37677101
B112: Daifuku | E112: =INDEX(INDIRECT($B112&"!C53:N78"),MATCH($B$110,INDIRECT($B112&"!B53:B78"),0),MATCH(E$4,INDIRECT($B112&"!C52:N52"),0)) -> 0.15993166 | F112: =INDEX(INDIRECT($B112&"!C53:N78"),MATCH($B$110,INDIRECT($B112&"!B53:B78"),0),MATCH(F$4,INDIRECT($B112&"!C52:N52"),0)) -> 0.15405742 | G112: =INDEX(INDIRECT($B112&"!C53:N78"),MATCH($B$110,INDIRECT($B112&"!B53:B78"),0),MATCH(G$4,INDIRECT($B112&"!C52:N52"),0)) -> 0.10504522 | H112: =INDEX(INDIRECT($B112&"!C53:N78"),MATCH($B$110,INDIRECT($B112&"!B53:B78"),0),MATCH(H$4,INDIRECT($B112&"!C52:N52"),0)) -> 0.053225068 | I112: =INDEX(INDIRECT($B112&"!C53:N78"),MATCH($B$110,INDIRECT($B112&"!B53:B78"),0),MATCH(I$4,INDIRECT($B112&"!C52:N52"),0)) -> - | J112: =INDEX(INDIRECT($B112&"!C53:N78"),MATCH($B$110,INDIRECT($B112&"!B53:B78"),0),MATCH(J$4,INDIRECT($B112&"!C52:N52"),0)) -> 0.173871 | K112: =INDEX(INDIRECT($B112&"!C53:N78"),MATCH($B$110,INDIRECT($B112&"!B53:B78"),0),MATCH(K$4,INDIRECT($B112&"!C52:N52"),0)) -> 0.14762246 | O112: Net Leverage Ratio Median | P112: =K247 -> 14.887343 | Q112: 1.339916 | R112: -1.2656098 | S112: -0.43394968 | T112: 4.1183155 | U112: 2.5657269 | V112: 9.3887156 | W112: -0.26044674 | X112: 0.033100502 | Y112: 1.0246915
B113: Hyster_Yale | E113: =INDEX(INDIRECT($B113&"!C53:N78"),MATCH($B$110,INDIRECT($B113&"!B53:B78"),0),MATCH(E$4,INDIRECT($B113&"!C52:N52"),0)) -> 0.67481168 | F113: =INDEX(INDIRECT($B113&"!C53:N78"),MATCH($B$110,INDIRECT($B113&"!B53:B78"),0),MATCH(F$4,INDIRECT($B113&"!C52:N52"),0)) -> 0.59085751 | G113: =INDEX(INDIRECT($B113&"!C53:N78"),MATCH($B$110,INDIRECT($B113&"!B53:B78"),0),MATCH(G$4,INDIRECT($B113&"!C52:N52"),0)) -> 1.6558387 | H113: =INDEX(INDIRECT($B113&"!C53:N78"),MATCH($B$110,INDIRECT($B113&"!B53:B78"),0),MATCH(H$4,INDIRECT($B113&"!C52:N52"),0)) -> 3 | I113: =INDEX(INDIRECT($B113&"!C53:N78"),MATCH($B$110,INDIRECT($B113&"!B53:B78"),0),MATCH(I$4,INDIRECT($B113&"!C52:N52"),0)) -> 1.4667864 | J113: =INDEX(INDIRECT($B113&"!C53:N78"),MATCH($B$110,INDIRECT($B113&"!B53:B78"),0),MATCH(J$4,INDIRECT($B113&"!C52:N52"),0)) -> 1.1403915 | K113: =INDEX(INDIRECT($B113&"!C53:N78"),MATCH($B$110,INDIRECT($B113&"!B53:B78"),0),MATCH(K$4,INDIRECT($B113&"!C52:N52"),0)) -> 0.87276119 | O113: Debt to Equity Median | P113: =AVERAGE(E122:J122) -> 0.50388531 | Q113: =P113 -> 0.50388531 | R113: =Q113 -> 0.50388531 | S113: =R113 -> 0.50388531 | T113: =S113 -> 0.50388531 | U113: =T113 -> 0.50388531 | V113: =U113 -> 0.50388531 | W113: =V113 -> 0.50388531 | X113: =W113 -> 0.50388531 | Y113: =X113 -> 0.50388531
B114: Mitsubishi_Logisnext | E114: =INDEX(INDIRECT($B114&"!C53:N78"),MATCH($B$110,INDIRECT($B114&"!B53:B78"),0),MATCH(E$4,INDIRECT($B114&"!C52:N52"),0)) -> 3.3326376 | F114: =INDEX(INDIRECT($B114&"!C53:N78"),MATCH($B$110,INDIRECT($B114&"!B53:B78"),0),MATCH(F$4,INDIRECT($B114&"!C52:N52"),0)) -> 3.3154399 | G114: =INDEX(INDIRECT($B114&"!C53:N78"),MATCH($B$110,INDIRECT($B114&"!B53:B78"),0),MATCH(G$4,INDIRECT($B114&"!C52:N52"),0)) -> 2.9679673 | H114: =INDEX(INDIRECT($B114&"!C53:N78"),MATCH($B$110,INDIRECT($B114&"!B53:B78"),0),MATCH(H$4,INDIRECT($B114&"!C52:N52"),0)) -> 3.032641 | I114: =INDEX(INDIRECT($B114&"!C53:N78"),MATCH($B$110,INDIRECT($B114&"!B53:B78"),0),MATCH(I$4,INDIRECT($B114&"!C52:N52"),0)) -> 2.059626 | J114: =INDEX(INDIRECT($B114&"!C53:N78"),MATCH($B$110,INDIRECT($B114&"!B53:B78"),0),MATCH(J$4,INDIRECT($B114&"!C52:N52"),0)) -> 1.8561103 | K114: =INDEX(INDIRECT($B114&"!C53:N78"),MATCH($B$110,INDIRECT($B114&"!B53:B78"),0),MATCH(K$4,INDIRECT($B114&"!C52:N52"),0)) -> 1.9034642 | O114: Net Leverage Ratio Median | P114: =AVERAGE(E150:J150) -> 1.2371118 | Q114: =P114 -> 1.2371118 | R114: =Q114 -> 1.2371118 | S114: =R114 -> 1.2371118 | T114: =S114 -> 1.2371118 | U114: =T114 -> 1.2371118 | V114: =U114 -> 1.2371118 | W114: =V114 -> 1.2371118 | X114: =W114 -> 1.2371118 | Y114: =X114 -> 1.2371118
B115: Toyota_Industries | E115: =INDEX(INDIRECT($B115&"!C53:N78"),MATCH($B$110,INDIRECT($B115&"!B53:B78"),0),MATCH(E$4,INDIRECT($B115&"!C52:N52"),0)) -> 0.59860825 | F115: =INDEX(INDIRECT($B115&"!C53:N78"),MATCH($B$110,INDIRECT($B115&"!B53:B78"),0),MATCH(F$4,INDIRECT($B115&"!C52:N52"),0)) -> 0.45395511 | G115: =INDEX(INDIRECT($B115&"!C53:N78"),MATCH($B$110,INDIRECT($B115&"!B53:B78"),0),MATCH(G$4,INDIRECT($B115&"!C52:N52"),0)) -> 0.38774289 | H115: =INDEX(INDIRECT($B115&"!C53:N78"),MATCH($B$110,INDIRECT($B115&"!B53:B78"),0),MATCH(H$4,INDIRECT($B115&"!C52:N52"),0)) -> 0.47950835 | I115: =INDEX(INDIRECT($B115&"!C53:N78"),MATCH($B$110,INDIRECT($B115&"!B53:B78"),0),MATCH(I$4,INDIRECT($B115&"!C52:N52"),0)) -> 0.31200731 | J115: =INDEX(INDIRECT($B115&"!C53:N78"),MATCH($B$110,INDIRECT($B115&"!B53:B78"),0),MATCH(J$4,INDIRECT($B115&"!C52:N52"),0)) -> 0.39203223 | K115: =INDEX(INDIRECT($B115&"!C53:N78"),MATCH($B$110,INDIRECT($B115&"!B53:B78"),0),MATCH(K$4,INDIRECT($B115&"!C52:N52"),0)) -> 0.32934751
B116: Symbotic | E116: =INDEX(INDIRECT($B116&"!C53:N78"),MATCH($B$110,INDIRECT($B116&"!B53:B78"),0),MATCH(E$4,INDIRECT($B116&"!C52:N52"),0)) -> 2.8843029 | F116: =INDEX(INDIRECT($B116&"!C53:N78"),MATCH($B$110,INDIRECT($B116&"!B53:B78"),0),MATCH(F$4,INDIRECT($B116&"!C52:N52"),0)) -> - | G116: =INDEX(INDIRECT($B116&"!C53:N78"),MATCH($B$110,INDIRECT($B116&"!B53:B78"),0),MATCH(G$4,INDIRECT($B116&"!C52:N52"),0)) -> 0 | H116: =INDEX(INDIRECT($B116&"!C53:N78"),MATCH($B$110,INDIRECT($B116&"!B53:B78"),0),MATCH(H$4,INDIRECT($B116&"!C52:N52"),0)) -> 166.31707 | I116: =INDEX(INDIRECT($B116&"!C53:N78"),MATCH($B$110,INDIRECT($B116&"!B53:B78"),0),MATCH(I$4,INDIRECT($B116&"!C52:N52"),0)) -> 0.089858188 | J116: =INDEX(INDIRECT($B116&"!C53:N78"),MATCH($B$110,INDIRECT($B116&"!B53:B78"),0),MATCH(J$4,INDIRECT($B116&"!C52:N52"),0)) -> 0.14314245 | K116: =INDEX(INDIRECT($B116&"!C53:N78"),MATCH($B$110,INDIRECT($B116&"!B53:B78"),0),MATCH(K$4,INDIRECT($B116&"!C52:N52"),0)) -> 0.13080715
B117: KENGIC | E117: =INDEX(INDIRECT($B117&"!C53:N78"),MATCH($B$110,INDIRECT($B117&"!B53:B78"),0),MATCH(E$4,INDIRECT($B117&"!C52:N52"),0)) -> 0.85791027 | F117: =INDEX(INDIRECT($B117&"!C53:N78"),MATCH($B$110,INDIRECT($B117&"!B53:B78"),0),MATCH(F$4,INDIRECT($B117&"!C52:N52"),0)) -> 0.681658 | G117: =INDEX(INDIRECT($B117&"!C53:N78"),MATCH($B$110,INDIRECT($B117&"!B53:B78"),0),MATCH(G$4,INDIRECT($B117&"!C52:N52"),0)) -> 1.0390329 | H117: =INDEX(INDIRECT($B117&"!C53:N78"),MATCH($B$110,INDIRECT($B117&"!B53:B78"),0),MATCH(H$4,INDIRECT($B117&"!C52:N52"),0)) -> 0.23420695 | I117: =INDEX(INDIRECT($B117&"!C53:N78"),MATCH($B$110,INDIRECT($B117&"!B53:B78"),0),MATCH(I$4,INDIRECT($B117&"!C52:N52"),0)) -> 0.30204485 | J117: =INDEX(INDIRECT($B117&"!C53:N78"),MATCH($B$110,INDIRECT($B117&"!B53:B78"),0),MATCH(J$4,INDIRECT($B117&"!C52:N52"),0)) -> 0.48529919 | K117: =INDEX(INDIRECT($B117&"!C53:N78"),MATCH($B$110,INDIRECT($B117&"!B53:B78"),0),MATCH(K$4,INDIRECT($B117&"!C52:N52"),0)) -> 0.96643873
B118: Jungheinrich | E118: =INDEX(INDIRECT($B118&"!C53:N78"),MATCH($B$110,INDIRECT($B118&"!B53:B78"),0),MATCH(E$4,INDIRECT($B118&"!C52:N52"),0)) -> 0.51599392 | F118: =INDEX(INDIRECT($B118&"!C53:N78"),MATCH($B$110,INDIRECT($B118&"!B53:B78"),0),MATCH(F$4,INDIRECT($B118&"!C52:N52"),0)) -> 0.50916177 | G118: =INDEX(INDIRECT($B118&"!C53:N78"),MATCH($B$110,INDIRECT($B118&"!B53:B78"),0),MATCH(G$4,INDIRECT($B118&"!C52:N52"),0)) -> 0.29586527 | H118: =INDEX(INDIRECT($B118&"!C53:N78"),MATCH($B$110,INDIRECT($B118&"!B53:B78"),0),MATCH(H$4,INDIRECT($B118&"!C52:N52"),0)) -> 0.29730162 | I118: =INDEX(INDIRECT($B118&"!C53:N78"),MATCH($B$110,INDIRECT($B118&"!B53:B78"),0),MATCH(I$4,INDIRECT($B118&"!C52:N52"),0)) -> 0.41567694 | J118: =INDEX(INDIRECT($B118&"!C53:N78"),MATCH($B$110,INDIRECT($B118&"!B53:B78"),0),MATCH(J$4,INDIRECT($B118&"!C52:N52"),0)) -> 0.27946125 | K118: =INDEX(INDIRECT($B118&"!C53:N78"),MATCH($B$110,INDIRECT($B118&"!B53:B78"),0),MATCH(K$4,INDIRECT($B118&"!C52:N52"),0)) -> 0.27414922
B119: Manitou_BF | E119: =INDEX(INDIRECT($B119&"!C53:N78"),MATCH($B$110,INDIRECT($B119&"!B53:B78"),0),MATCH(E$4,INDIRECT($B119&"!C52:N52"),0)) -> 0.35262306 | F119: =INDEX(INDIRECT($B119&"!C53:N78"),MATCH($B$110,INDIRECT($B119&"!B53:B78"),0),MATCH(F$4,INDIRECT($B119&"!C52:N52"),0)) -> 0.2704824 | G119: =INDEX(INDIRECT($B119&"!C53:N78"),MATCH($B$110,INDIRECT($B119&"!B53:B78"),0),MATCH(G$4,INDIRECT($B119&"!C52:N52"),0)) -> 0.26637734 | H119: =INDEX(INDIRECT($B119&"!C53:N78"),MATCH($B$110,INDIRECT($B119&"!B53:B78"),0),MATCH(H$4,INDIRECT($B119&"!C52:N52"),0)) -> 0.38233684 | I119: =INDEX(INDIRECT($B119&"!C53:N78"),MATCH($B$110,INDIRECT($B119&"!B53:B78"),0),MATCH(I$4,INDIRECT($B119&"!C52:N52"),0)) -> 0.53081123 | J119: =INDEX(INDIRECT($B119&"!C53:N78"),MATCH($B$110,INDIRECT($B119&"!B53:B78"),0),MATCH(J$4,INDIRECT($B119&"!C52:N52"),0)) -> 0.45799522 | K119: =INDEX(INDIRECT($B119&"!C53:N78"),MATCH($B$110,INDIRECT($B119&"!B53:B78"),0),MATCH(K$4,INDIRECT($B119&"!C52:N52"),0)) -> 0.41794742
B121: Mean | E121: =IFERROR(AVERAGE(E111:E119),"-") -> 1.1422437 | F121: =IFERROR(AVERAGE(F111:F119),"-") -> 0.91228857 | G121: =IFERROR(AVERAGE(G111:G119),"-") -> 0.86987944 | H121: =IFERROR(AVERAGE(H111:H119),"-") -> 19.447364 | I121: =IFERROR(AVERAGE(I111:I119),"-") -> 0.81687936 | J121: =IFERROR(AVERAGE(J111:J119),"-") -> 0.73989578 | K121: =IFERROR(AVERAGE(K111:K119),"-") -> 0.81329779
...

Sheet Financials
B2: Income Statement Standardized | P2: Year | Q2: 2019 | R2: 2020 | S2: 2021 | T2: 2022 | U2: 2023 | V2: 2024
P3: Revenue | Q3: =I5 -> 8806.5 | R3: =J5 -> 8341.6 | S3: =K5 -> 10294.3 | T3: =L5 -> 11135.6 | U3: =M5 -> 11433.7 | V3: =N5 -> 11503.2 | W3: CAGR
B4: Year Ended | E4: 2015 | F4: =+E4+1 -> 2016 | G4: =+F4+1 -> 2017 | H4: =+G4+1 -> 2018 | I4: =+H4+1 -> 2019 | J4: =+I4+1 -> 2020 | K4: =+J4+1 -> 2021 | L4: =+K4+1 -> 2022 | M4: =+L4+1 -> 2023 | N4: =+M4+1 -> 2024 | P4: Growth | Q4: =I5/H5-1 -> 0.1014045 | R4: =J5/I5-1 -> -0.052790552 | S4: =K5/J5-1 -> 0.23409178 | T4: =L5/K5-1 -> 0.081724838 | U4: =M5/L5-1 -> 0.026769999 | V4: =N5/M5-1 -> 0.0060785223 | W4: =(V3/Q3)^(1/(V2-Q2))-1 -> 0.054880019
B5: Revenue from Goods & Services | E5: =IS!B19 -> 5097.9 | F5: =IS!C19 -> 5587.2 | G5: =IS!D19 -> 7653.6 | H5: =IS!E19 -> 7995.7 | I5: =IS!F19 -> 8806.5 | J5: =IS!G19 -> 8341.6 | K5: =IS!H19 -> 10294.3 | L5: =IS!I19 -> 11135.6 | ... N5: =IS!K19 -> 11503.2
B6: Cost of Revenue (excl. D&A) | E6: =-IS!B22-IS!B24 -> -3601.7 | F6: =-IS!C22-IS!C24 -> -4091.6 | G6: =-IS!D22-IS!D24 -> -5768.1 | H6: =-IS!E22-IS!E24 -> -5974.7 | I6: =-IS!F22-IS!F24 -> -6474.6 | J6: =-IS!G22-IS!G24 -> -6296.8 | K6: =-IS!H22-IS!H24 -> -7870.6 | L6: =-IS!I22-IS!I24 -> -9124.1 | ... N6: =-IS!K22-IS!K24 -> -8525.9
B7: Gross Profit | E7: =E5+E6 -> 1496.2 | F7: =F5+F6 -> 1495.6 | G7: =G5+G6 -> 1885.5 | H7: =H5+H6 -> 2021 | I7: =I5+I6 -> 2331.9 | J7: =J5+J6 -> 2044.8 | K7: =K5+K6 -> 2423.7 | L7: =L5+L6 -> 2011.5 | ... N7: =N5+N6 -> 2977.3
B8: SG&A (excl. D&A) | E8: =-IS!B26+IS!B129+IS!B24 -> -719.6 | F8: =-IS!C26+IS!C129+IS!C24 -> -580.5 | G8: =-IS!D26+IS!D129+IS!D24 -> -664 | H8: =-IS!E26+IS!E129+IS!E24 -> -445.6 | I8: =-IS!F26+IS!F129+IS!F24 -> -751.4 | J8: =-IS!G26+IS!G129+IS!G24 -> -710.9 | K8: =-IS!H26+IS!H129+IS!H24 -> -721.1 | L8: =-IS!I26+IS!I129+IS!I24 -> -852 | ... N8: =-IS!K26+IS!K129+IS!K24 -> -1074
B9: Other Operating Expenses | E9: =-IS!B29 -> 72.4 | F9: =-IS!C29 -> 130 | G9: =-IS!D29 -> 240.2 | H9: =-IS!E29 -> 54.1 | I9: =-IS!F29 -> 66.2 | J9: =-IS!G29 -> 79.9 | K9: =-IS!H29 -> 143.1 | L9: =-IS!I29 -> 146.6 | ... N9: =-IS!K29 -> 134.2
B10: EBITDA | E10: =E7+E8+E9 -> 849 | F10: =F7+F8+F9 -> 1045.1 | G10: =G7+G8+G9 -> 1461.7 | H10: =H7+H8+H9 -> 1629.5 | I10: =I7+I8+I9 -> 1646.7 | J10: =J7+J8+J9 -> 1413.8 | K10: =K7+K8+K9 -> 1845.7 | L10: =L7+L8+L9 -> 1306.1 | ... N10: =N7+N8+N9 -> 2037.5
B11: Depreciation Expense | E11: =-IS!B130 -> -310.4 | F11: =-IS!C130 -> -339.5 | G11: =-IS!D130 -> -404 | H11: =-IS!E130 -> -708.7 | I11: =-IS!F130 -> -733.2 | J11: =-IS!G130 -> -743.7 | K11: =-IS!H130 -> -768.4 | L11: =-IS!I130 -> -824.4 | ... N11: =-IS!K130 -> -917.5
B12: EBITA | E12: =E10+E11 -> 538.6 | F12: =F10+F11 -> 705.6 | G12: =G10+G11 -> 1057.7 | H12: =H10+H11 -> 920.8 | I12: =I10+I11 -> 913.5 | J12: =J10+J11 -> 670.1 | K12: =K10+K11 -> 1077.3 | L12: =L10+L11 -> 481.7 | ... N12: =N10+N11 -> 1120
B13: Amortization Expense | E13: =-IS!B132 -> -86.9 | F13: =-IS!C132 -> -172.2 | G13: =-IS!D132 -> -286.4 | H13: =-IS!E132 -> -259.4 | I13: =-IS!F132 -> -157.8 | J13: =-IS!G132 -> -172.4 | K13: =-IS!H132 -> -170.5 | L13: =-IS!I132 -> -188.9 | ... N13: =-IS!K132 -> -193.3
B14: EBIT | E14: =E12+E13 -> 451.7 | F14: =F12+F13 -> 533.4 | G14: =G12+G13 -> 771.3 | H14: =H12+H13 -> 661.4 | I14: =I12+I13 -> 755.7 | J14: =J12+J13 -> 497.7 | K14: =K12+K13 -> 906.8 | L14: =L12+L13 -> 292.8 | ... N14: =N12+N13 -> 926.7
B15: Interest Expense, Net | E15: =-IS!B39 -> -45.7 | F15: =-IS!C39 -> -50.9 | G15: =-IS!D39 -> -53.2 | H15: =-IS!E39 -> -63.6 | I15: =-IS!F39 -> -53.8 | J15: =-IS!G39 -> -40.8 | K15: =-IS!H39 -> -15.7 | L15: =-IS!I39 -> -34.1 | ... N15: =-IS!K39 -> -173 | P15: GOGS % | Q15: =ABS(N6)/N5 -> 0.74117637
B16: EBT | E16: =SUM(E14:E15) -> 406 | F16: =SUM(F14:F15) -> 482.5 | G16: =SUM(G14:G15) -> 718.1 | H16: =SUM(H14:H15) -> 597.8 | I16: =SUM(I14:I15) -> 701.9 | J16: =SUM(J14:J15) -> 456.9 | K16: =SUM(K14:K15) -> 891.1 | L16: =SUM(L14:L15) -> 258.7 | ... N16: =SUM(N14:N15) -> 753.7 | P16: OpEx % | Q16: =ABS(SUM(N8:N9))/N5 -> 0.081699005
B17: Taxes | E17: =-IS!B63 -> -109.2 | F17: =-IS!C63 -> -93.1 | G17: =-IS!D63 -> -41.9 | H17: =-IS!E63 -> -143.7 | I17: =-IS!F63 -> -176.8 | J17: =-IS!G63 -> -90.7 | K17: =-IS!H63 -> -191.7 | L17: =-IS!I63 -> -32.2 | ... N17: =-IS!K63 -> -220.5 | P17: Dep. % | Q17: =ABS(N11)/N5 -> 0.079760414
B18: Adj. NI | E18: =SUM(E16:E17) -> 296.8 | F18: =SUM(F16:F17) -> 389.4 | G18: =SUM(G16:G17) -> 676.2 | H18: =SUM(H16:H17) -> 454.1 | I18: =SUM(I16:I17) -> 525.1 | J18: =SUM(J16:J17) -> 366.2 | K18: =SUM(K16:K17) -> 699.4 | L18: =SUM(L16:L17) -> 226.5 | ... N18: =SUM(N16:N17) -> 533.2 | P18: Amort. % | Q18: =ABS(N13)/N5 -> 0.01680402
B19: Exceptional Items, Net | E19: =IS!B37+IS!B52-E15-SUM(IS!B73,IS!B70) -> -79.8 | F19: =IS!C37+IS!C52-F15-SUM(IS!C73,IS!C70) -> -143.8 | G19: =IS!D37+IS!D52-G15-SUM(IS!D73,IS!D70) -> -251.4 | H19: =IS!E37+IS!E52-H15-SUM(IS!E73,IS!E70) -> -54.3 | I19: =IS!F37+IS!F52-I15-SUM(IS!F73,IS!F70) -> -70.3 | J19: =IS!G37+IS!G52-J15-SUM(IS!G73,IS!G70) -> -150.9 | K19: =IS!H37+IS!H52-K15-SUM(IS!H73,IS!H70) -> -131.1 | L19: =IS!I37+IS!I52-L15-SUM(IS!I73,IS!I70) -> -128.5 | ... N19: =IS!K37+IS!K52-N15-SUM(IS!K73,IS!K70) -> -172.8 | P19: Int. Exp. % | Q19: =ABS(N15)/N5 -> 0.015039293
B20: NI | E20: =SUM(E18:E19) -> 217 | F20: =SUM(F18:F19) -> 245.6 | G20: =SUM(G18:G19) -> 424.8 | H20: =SUM(H18:H19) -> 399.8 | I20: =SUM(I18:I19) -> 454.8 | J20: =SUM(J18:J19) -> 215.3 | K20: =SUM(K18:K19) -> 568.3 | L20: =SUM(L18:L19) -> 98 | ... N20: =SUM(N18:N19) -> 360.4 | P20: Tax % | Q20: =ABS(N17)/N5 -> 0.019168579
P21: Ex. Item % | Q21: =ABS(N19)/N5 -> 0.015021907
B22: Free Cash Flow to Equity Holders | P22: NI % | Q22: =N20/N5 -> 0.031330412
P23: Revenue | Q23: =SUM(Q15:Q22) -> 1
B24: Year Ended | E24: 2015 | F24: =+E24+1 -> 2016 | G24: =+F24+1 -> 2017 | H24: =+G24+1 -> 2018 | I24: =+H24+1 -> 2019 | J24: =+I24+1 -> 2020 | K24: =+J24+1 -> 2021 | L24: =+K24+1 -> 2022 | M24: =+L24+1 -> 2023 | N24: =+M24+1 -> 2024
B25: CFO | E25: =CF!B32 -> 424.3 | F25: =CF!C32 -> 332.4 | G25: =CF!D32 -> 554.2 | H25: =CF!E32 -> 620.3 | I25: =CF!F32 -> 694.6 | J25: =CF!G32 -> 349.2 | K25: =CF!H32 -> 710.2 | L25: =CF!I32 -> -518.4 | ... N25: =CF!K32 -> 1089.6
B26: CapEx | E26: =-CF!B34 -> -128.5 | F26: =-CF!C34 -> -160.3 | G26: =-CF!D34 -> -214.3 | H26: =-CF!E34 -> -253.4 | I26: =-CF!F34 -> -283.8 | J26: =-CF!G34 -> -278.1 | K26: =-CF!H34 -> -317 | L26: =-CF!I34 -> -375.2 | ... N26: =-CF!K34 -> -453.7 | P26: EBITDA | Q26: =I10 -> 1646.7 | R26: =J10 -> 1413.8 | S26: =K10 -> 1845.7 | T26: =L10 -> 1306.1 | U26: =M10 -> 1833 | V26: =N10 -> 2037.5 | W26: Average
B27: Debt Payment | E27: =CF!B51 -> -223.9 | F27: =CF!C51 -> 1744 | G27: =CF!D51 -> -914.7 | H27: =CF!E51 -> -230.9 | I27: =CF!F51 -> -226.1 | J27: =CF!G51 -> -609.5 | K27: =CF!H51 -> -148.8 | L27: =CF!I51 -> 942.4 | ... N27: =CF!K51 -> 23.6 | P27: EBITDA Margin | Q27: =Q26/Q3 -> 0.18698688 | R27: =R26/R3 -> 0.16948787 | S27: =S26/S3 -> 0.1792934 | T27: =T26/T3 -> 0.11729049 | U27: =U26/U3 -> 0.16031556 | V27: =V26/V3 -> 0.17712463 | W27: =AVERAGE(Q27:V27) -> 0.16508314
B28: FCFE | E28: =E25+E26+E27 -> 71.9 | F28: =F25+F26+F27 -> 1916.1 | G28: =G25+G26+G27 -> -574.8 | H28: =H25+H26+H27 -> 136 | I28: =I25+I26+I27 -> 184.7 | J28: =J25+J26+J27 -> -538.4 | K28: =K25+K26+K27 -> 244.4 | L28: =L25+L26+L27 -> 48.8 | ... N28: =N25+N26+N27 -> 659.5
B30: Balancesheet
B32: Year Ended | E32: 2015 | F32: =+E32+1 -> 2016 | G32: =+F32+1 -> 2017 | H32: =+G32+1 -> 2018 | I32: =+H32+1 -> 2019 | J32: =+I32+1 -> 2020 | K32: =+J32+1 -> 2021 | L32: =+K32+1 -> 2022 | M32: =+L32+1 -> 2023 | N32: =+M32+1 -> 2024
B33: Current Assets
B34: Cash & Short-Term Investments | E34: =BS!D17 -> 140.5 | F34: =BS!E17 -> 326.5 | G34: =BS!F17 -> 231.5 | H34: =BS!G17 -> 211.4 | I34: =BS!H17 -> 249 | J34: =BS!I17 -> 359.8 | K34: =BS!J17 -> 517.6 | L34: =BS!K17 -> 355.9 | ... N34: =BS!M17 -> 839.8
B35: Derivative Financial Instruments - ST | E35: =BS!D21 -> 5.3 | F35: =BS!E21 -> 10.3 | G35: =BS!F21 -> 30 | H35: =BS!G21 -> 8.9 | I35: =BS!H21 -> 9.4 | J35: =BS!I21 -> 15 | K35: =BS!J21 -> 8.9 | L35: =BS!K21 -> 20.5 | ... N35: =BS!M21 -> 12.7
B36: Loans & Receivables - ST | E36: =BS!D22 -> 898.3 | F36: =BS!E22 -> 1292.3 | G36: =BS!F22 -> 1410.8 | H36: =BS!G22 -> 1550.3 | I36: =BS!H22 -> 1666.3 | J36: =BS!I22 -> 1861.7 | K36: =BS!J22 -> 2481.6 | L36: =BS!K22 -> 2846.3 | ... N36: =BS!M22 -> 2884.9
B37: Inventories | E37: =BS!D29 -> 553.5 | F37: =BS!E29 -> 672.4 | G37: =BS!F29 -> 768.6 | H37: =BS!G29 -> 994.8 | I37: =BS!H29 -> 1085.3 | J37: =BS!I29 -> 1101 | K37: =BS!J29 -> 1632.1 | L37: =BS!K29 -> 1804.6 | ... N37: =BS!M29 -> 1748.6
B38: Assets Held for Sale/Discontinued Operations - ST | E38: =BS!D34 -> 0 | F38: =BS!E34 -> 0 | G38: =BS!F34 -> 0 | H38: =BS!G34 -> 0 | I38: =BS!H34 -> 0 | J38: =BS!I34 -> 0 | K38: =BS!J34 -> 0 | L38: =BS!K34 -> 27.4 | ... N38: =BS!M34 -> 0
B39: Other Current Assets - Total | E39: =BS!D35 -> 32.3 | F39: =BS!E35 -> 53.1 | G39: =BS!F35 -> 40.6 | H39: =BS!G35 -> 52.8 | I39: =BS!H35 -> 58.8 | J39: =BS!I35 -> 51.9 | K39: =BS!J35 -> 57.7 | L39: =BS!K35 -> 61.1 | ... N39: =BS!M35 -> 83 | P39: Net Income | Q39: =I20 -> 454.8 | R39: =J20 -> 215.3 | S39: =K20 -> 568.3 | T39: =L20 -> 98 | U39: =M20 -> 305.8 | V39: =N20 -> 360.4 | W39: Average
B40: Total Current Assets | E40: =SUM(E34:E39) -> 1629.9 | F40: =SUM(F34:F39) -> 2354.6 | G40: =SUM(G34:G39) -> 2481.5 | H40: =SUM(H34:H39) -> 2818.2 | I40: =SUM(I34:I39) -> 3068.8 | J40: =SUM(J34:J39) -> 3389.4 | K40: =SUM(K34:K39) -> 4697.9 | L40: =SUM(L34:L39) -> 5115.8 | ... N40: =SUM(N34:N39) -> 5569 | P40: Net Income Margin | Q40: =Q39/Q3 -> 0.051643672 | R40: =R39/R3 -> 0.025810396 | S40: =S39/S3 -> 0.055205308 | T40: =T39/T3 -> 0.0088006035 | U40: =U39/U3 -> 0.026745498 | V40: =V39/V3 -> 0.031330412 | W40: =AVERAGE(Q40:V40) -> 0.033255982
B42: Non-Current Assets
B43: Investments - LT | E43: =BS!D41 -> 43.2 | F43: =BS!E41 -> 42.9 | G43: =BS!F41 -> 54.9 | H43: =BS!G41 -> 51.8 | I43: =BS!H41 -> 60.8 | J43: =BS!I41 -> 80 | K43: =BS!J41 -> 95 | L43: =BS!K41 -> 106.3 | ... N43: =BS!M41 -> 161.5
B44: Investments in J&V, Associates | E44: =BS!D43 -> 73.6 | F44: =BS!E43 -> 72.7 | G44: =BS!F43 -> 80.3 | H44: =BS!G43 -> 82.3 | I44: =BS!H43 -> 84.5 | J44: =BS!I43 -> 78.8 | K44: =BS!J43 -> 84.3 | L44: =BS!K43 -> 94.7 | ... N44: =BS!M43 -> 110.3
B45: Receivables & Loans - LT | E45: =BS!D44 -> 474.7 | F45: =BS!E44 -> 535.9 | G45: =BS!F44 -> 650 | H45: =BS!G44 -> 826.2 | I45: =BS!H44 -> 1080.9 | J45: =BS!I44 -> 1208.7 | K45: =BS!J44 -> 1326.9 | L45: =BS!K44 -> 1383.8 | ... N45: =BS!M44 -> 2090.1
B46: Derivative Financial Instruments - LT | E46: =BS!D48 -> 0 | F46: =BS!E48 -> 0 | G46: =BS!F48 -> 0 | H46: =BS!G48 -> 1 | I46: =BS!H48 -> 2.6 | J46: =BS!I48 -> 2.5 | K46: =BS!J48 -> 4.2 | L46: =BS!K48 -> 78.1 | ... N46: =BS!M48 -> 17.6
B47: Property, Plant & Equipment | E47: =BS!D49 -> 1387.2 | F47: =BS!E49 -> 1684.1 | G47: =BS!F49 -> 1850.6 | H47: =BS!G49 -> 3010.1 | I47: =BS!H49 -> 3230.4 | J47: =BS!I49 -> 3179.5 | K47: =BS!J49 -> 3381.8 | L47: =BS!K49 -> 3555 | ... N47: =BS!M49 -> 4422.8
B48: Other Non-Current Assets | E48: =BS!D78 -> 379.1 | F48: =BS!E78 -> 432.3 | G48: =BS!F78 -> 394.7 | H48: =BS!G78 -> 457.6 | I48: =BS!H78 -> 504.8 | J48: =BS!I78 -> 557.2 | K48: =BS!J78 -> 550.1 | L48: =BS!K78 -> 413.2 | ... N48: =BS!M78 -> 619.2
B49: Intangible Assets | E49: =BS!D82 -> 2452.5 | F49: =BS!E82 -> 6236.7 | G49: =BS!F82 -> 5716.4 | H49: =BS!G82 -> 5721.6 | I49: =BS!H82 -> 5732.4 | J49: =BS!I82 -> 5559.6 | K49: =BS!J82 -> 5710.7 | L49: =BS!K82 -> 5781.5 | ... N49: =BS!M82 -> 5814.9
B50: Total Non-Current Assets | E50: =SUM(E43:E49) -> 4810.3 | F50: =SUM(F43:F49) -> 9004.6 | G50: =SUM(G43:G49) -> 8746.9 | H50: =SUM(H43:H49) -> 10150.6 | I50: =SUM(I43:I49) -> 10696.4 | J50: =SUM(J43:J49) -> 10666.3 | K50: =SUM(K43:K49) -> 11153 | L50: =SUM(L43:L49) -> 11412.6 | ... N50: =SUM(N43:N49) -> 13236.4
B52: Total Assets | E52: =E40+E50 -> 6440.2 | F52: =F40+F50 -> 11359.2 | G52: =G40+G50 -> 11228.4 | H52: =H40+H50 -> 12968.8 | I52: =I40+I50 -> 13765.2 | J52: =J40+J50 -> 14055.7 | K52: =K40+K50 -> 15850.9 | L52: =L40+L50 -> 16528.4 | ... N52: =N40+N50 -> 18805.4
B54: Current Liabilities
B55: Trade Accounts Payable & Accruals - ST | E55: =BS!D104 -> 797.4 | F55: =BS!E104 -> 1103.4 | G55: =BS!F104 -> 1225.1 | H55: =BS!G104 -> 1222.6 | I55: =BS!H104 -> 1325.6 | J55: =BS!I104 -> 1234.2 | K55: =BS!J104 -> 1858.3 | L55: =BS!K104 -> 1533.9 | ... N55: =BS!M104 -> 1686.7
B56: ST Debt & Current Portion of LT Debt | E56: =BS!D107 -> 484.6 | F56: =BS!E107 -> 715.1 | G56: =BS!F107 -> 735.9 | H56: =BS!G107 -> 1224.9 | I56: =BS!H107 -> 1407.6 | J56: =BS!I107 -> 1362.5 | K56: =BS!J107 -> 1712.9 | L56: =BS!K107 -> 1835.1 | ... N56: =BS!M107 -> 2258.1
B57: Derivative Liabilities - ST | E57: =BS!D111 -> 12.4 | F57: =BS!E111 -> 22.4 | G57: =BS!F111 -> 3.3 | H57: =BS!G111 -> 6.4 | I57: =BS!H111 -> 12.8 | J57: =BS!I111 -> 6.9 | K57: =BS!J111 -> 15.2 | L57: =BS!K111 -> 11.5 | ... N57: =BS!M111 -> 41
B58: Liabilities Held for Sale/Discontinued Operations - ST | E58: =BS!D112 -> 0 | F58: =BS!E112 -> 0 | G58: =BS!F112 -> 0 | H58: =BS!G112 -> 0 | I58: =BS!H112 -> 0 | J58: =BS!I112 -> 0 | K58: =BS!J112 -> 0 | L58: =BS!K112 -> 27.2 | ... N58: =BS!M112 -> 0
B59: Income Taxes - Payable - ST | E59: =BS!D113 -> 144.5 | F59: =BS!E113 -> 155.7 | G59: =BS!F113 -> 193.4 | H59: =BS!G113 -> 180.2 | I59: =BS!H113 -> 195.9 | J59: =BS!I113 -> 168.9 | K59: =BS!J113 -> 170.2 | L59: =BS!K113 -> 181.3 | ... N59: =BS!M113 -> 210.5
B60: Other Current Liabilities | E60: =BS!D114 -> 292.6 | F60: =BS!E114 -> 675.9 | G60: =BS!F114 -> 691.9 | H60: =BS!G114 -> 1030.5 | I60: =BS!H114 -> 987.1 | J60: =BS!I114 -> 1045.8 | K60: =BS!J114 -> 1348.7 | L60: =BS!K114 -> 1290.9 | ... N60: =BS!M114 -> 1313.9
B61: Total Current Liabilities | E61: =SUM(E55:E60) -> 1731.5 | F61: =SUM(F55:F60) -> 2672.5 | G61: =SUM(G55:G60) -> 2849.6 | H61: =SUM(H55:H60) -> 3664.6 | I61: =SUM(I55:I60) -> 3929 | J61: =SUM(J55:J60) -> 3818.3 | K61: =SUM(K55:K60) -> 5105.3 | L61: =SUM(L55:L60) -> 4879.9 | ... N61: =SUM(N55:N60) -> 5510.2
B63: Non-Current Liabilities
B64: Debt - Long-Term - Total | E64: =BS!D121 -> 1486.5 | F64: =BS!E121 -> 3952.8 | G64: =BS!F121 -> 3205.3 | H64: =BS!G121 -> 3744.5 | I64: =BS!H121 -> 4009.8 | J64: =BS!I121 -> 3603.9 | K64: =BS!J121 -> 3441.1 | L64: =BS!K121 -> 4497.1 | ... N64: =BS!M121 -> 5434
B65: Derivative Liabilities - Hedging - Long-Term | E65: =BS!D125 -> 0 | F65: =BS!E125 -> 0 | G65: =BS!F125 -> 1.9 | H65: =BS!G125 -> 7.9 | I65: =BS!H125 -> 11.4 | J65: =BS!I125 -> 9.7 | K65: =BS!J125 -> 1.4 | L65: =BS!K125 -> 5.4 | ... N65: =BS!M125 -> 7.1
B66: Deferred Tax & Investment Tax Credits - Long-Term | E66: =BS!D126 -> 302.7 | F66: =BS!E126 -> 905.3 | G66: =BS!F126 -> 665.2 | H66: =BS!G126 -> 626.7 | I66: =BS!H126 -> 570.9 | J66: =BS!I126 -> 511.1 | K66: =BS!J126 -> 523.5 | L66: =BS!K126 -> 492.8 | ... N66: =BS!M126 -> 446.7
B67: Other Non-Current Liabilities - Total | E67: =BS!D128 -> 1070.8 | F67: =BS!E128 -> 1293.5 | G67: =BS!F128 -> 1357.6 | H67: =BS!G128 -> 1620 | I67: =BS!H128 -> 1685.7 | J67: =BS!I128 -> 1841.9 | K67: =BS!J128 -> 1610.7 | L67: =BS!K128 -> 1045.4 | ... N67: =BS!M128 -> 1200.3
B68: Total Non-Current Liabilities | E68: =SUM(E64:E67) -> 2860 | F68: =SUM(F64:F67) -> 6151.6 | G68: =SUM(G64:G67) -> 5230 | H68: =SUM(H64:H67) -> 5999.1 | I68: =SUM(I64:I67) -> 6277.8 | J68: =SUM(J64:J67) -> 5966.6 | K68: =SUM(K64:K67) -> 5576.7 | L68: =SUM(L64:L67) -> 6040.7 | ... N68: =SUM(N64:N67) -> 7088.1
B70: Shareholders' Equity
B71: Common Equity | E71: =BS!D152 -> 1841 | F71: =BS!E152 -> 2529.4 | G71: =BS!F152 -> 3144.4 | H71: =BS!G152 -> 3301.8 | I71: =BS!H152 -> 3567.6 | J71: =BS!I152 -> 4283.9 | K71: =BS!J152 -> 5177.2 | L71: =BS!K152 -> 5608.7 | ... N71: =BS!M152 -> 6189.4
B72: Mintority Interest | E72: =BS!D153 -> 7.7 | F72: =BS!E153 -> 5.7 | G72: =BS!F153 -> 4.4 | H72: =BS!G153 -> 3.3 | I72: =BS!H153 -> -9.2 | J72: =BS!I153 -> -13.1 | K72: =BS!J153 -> -8.3 | L72: =BS!K153 -> -0.9 | ... N72: =BS!M153 -> 17.7
B74: Total Liabilities and Shareholder's Equity | E74: =E68+E71+E72+E61 -> 6440.2 | F74: =F68+F71+F72+F61 -> 11359.2 | G74: =G68+G71+G72+G61 -> 11228.4 | H74: =H68+H71+H72+H61 -> 12968.8 | I74: =I68+I71+I72+I61 -> 13765.2 | J74: =J68+J71+J72+J61 -> 14055.7 | K74: =K68+K71+K72+K61 -> 15850.9 | L74: =L68+L71+L72+L61 -> 16528.4 | ... N74: =N68+N71+N72+N61 -> 18805.4
B75: check | E75: =E74-E52 -> 0 | F75: =F74-F52 -> 0 | G75: =G74-G52 -> 0 | H75: =H74-H52 -> 0 | I75: =I74-I52 -> 0 | J75: =J74-J52 -> 0 | K75: =K74-K52 -> 0 | L75: =L74-L52 -> 0 | ... N75: =N74-N52 -> 0
B77: Financial Ratios
B79: Year Ended | E79: 2015 | F79: =+E79+1 -> 2016 | G79: =+F79+1 -> 2017 | H79: =+G79+1 -> 2018 | I79: =+H79+1 -> 2019 | J79: =+I79+1 -> 2020 | K79: =+J79+1 -> 2021 | L79: =+K79+1 -> 2022 | M79: =+L79+1 -> 2023 | N79: =+M79+1 -> 2024
B81: Profitability Ratios
B82: Gross Profit Margin | E82: =E7/E5 -> 0.2934934 | F82: =F7/F5 -> 0.26768328 | G82: =G7/G5 -> 0.24635466 | H82: =H7/H5 -> 0.25276086 | I82: =I7/I5 -> 0.26479305 | J82: =J7/J5 -> 0.24513283 | K82: =K7/K5 -> 0.23544097 | L82: =L7/L5 -> 0.18063688 | ... N82: =N7/N5 -> 0.25882363
B83: EBITDA Margin | E83: =E10/E5 -> 0.16653916 | F83: =F10/F5 -> 0.18705255 | G83: =G10/G5 -> 0.19098202 | H83: =H10/H5 -> 0.20379704 | I83: =I10/I5 -> 0.18698688 | J83: =J10/J5 -> 0.16948787 | K83: =K10/K5 -> 0.1792934 | L83: =L10/L5 -> 0.11729049 | ... N83: =N10/N5 -> 0.17712463
B84: EBIT Margin (Operating Margin) | E84: =E14/E5 -> 0.088605112 | F84: =F14/F5 -> 0.095468213 | G84: =G14/G5 -> 0.10077611 | H84: =H14/H5 -> 0.082719462 | I84: =I14/I5 -> 0.085811616 | J84: =J14/J5 -> 0.059664813 | K84: =K14/K5 -> 0.088087582 | L84: =L14/L5 -> 0.026294048 | ... N84: =N14/N5 -> 0.080560192
B85: Profit Margin | E85: =E20/E5 -> 0.042566547 | F85: =F20/F5 -> 0.043957617 | G85: =G20/G5 -> 0.055503293 | H85: =H20/H5 -> 0.050001876 | I85: =I20/I5 -> 0.051643672 | J85: =J20/J5 -> 0.025810396 | K85: =K20/K5 -> 0.055205308 | L85: =L20/L5 -> 0.0088006035 | ... N85: =N20/N5 -> 0.031330412
B87: Liquidity Ratios | P87: Year | Q87: 2019 | R87: 2020 | S87: 2021 | T87: 2022 | U87: 2023 | V87: 2024
B88: Current Ratio | E88: =E40/E61 -> 0.94132255 | F88: =F40/F61 -> 0.88104771 | G88: =G40/G61 -> 0.87082398 | H88: =H40/H61 -> 0.76903346 | I88: =I40/I61 -> 0.78106388 | J88: =J40/J61 -> 0.88767252 | K88: =K40/K61 -> 0.92020058 | L88: =L40/L61 -> 1.0483412 | ... N88: =N40/N61 -> 1.0106711 | P88: =B88 -> Current Ratio | Q88: =I88 -> 0.78106388 | R88: =J88 -> 0.88767252 | S88: =K88 -> 0.92020058 | T88: =L88 -> 1.0483412 | U88: =M88 -> 1.050374 | V88: =N88 -> 1.0106711
B89: Quick Ratio | E89: =(E40-E37)/E61 -> 0.62165752 | F89: =(F40-F37)/F61 -> 0.62944808 | G89: =(G40-G37)/G61 -> 0.60110191 | H89: =(H40-H37)/H61 -> 0.49757136 | I89: =(I40-I37)/I61 -> 0.50483584 | J89: =(J40-J37)/J61 -> 0.59932431 | K89: =(K40-K37)/K61 -> 0.60051319 | L89: =(L40-L37)/L61 -> 0.67853849 | ... N89: =(N40-N37)/N61 -> 0.69333237 | P89: =B89 -> Quick Ratio | Q89: =I89 -> 0.50483584 | R89: =J89 -> 0.59932431 | S89: =K89 -> 0.60051319 | T89: =L89 -> 0.67853849 | U89: =M89 -> 0.68496622 | V89: =N89 -> 0.69333237
B90: Cash Ratio | E90: =E34/E61 -> 0.081143517 | F90: =F34/F61 -> 0.12217025 | G90: =G34/G61 -> 0.081239472 | H90: =H34/H61 -> 0.05768706 | I90: =I34/I61 -> 0.063374905 | J90: =J34/J61 -> 0.094230417 | K90: =K34/K61 -> 0.10138484 | L90: =L34/L61 -> 0.072931822 | ... N90: =N34/N61 -> 0.15240826 | P90: =B90 -> Cash Ratio | Q90: =I90 -> 0.063374905 | R90: =J90 -> 0.094230417 | S90: =K90 -> 0.10138484 | T90: =L90 -> 0.072931822 | U90: =M90 -> 0.071287806 | V90: =N90 -> 0.15240826
B92: Solvency & Leverage Ratios | P92: Year | Q92: 2019 | R92: 2020 | S92: 2021 | T92: 2022 | U92: 2023 | V92: 2024
B93: Debt to Equity | E93: =(E64+E56)/(E71+E72) -> 1.0662087 | F93: =(F64+F56)/(F71+F72) -> 1.841308 | G93: =(G64+G56)/(G71+G72) -> 1.2516514 | H93: =(H64+H56)/(H71+H72) -> 1.5035551 | I93: =(I64+I56)/(I71+I72) -> 1.5224258 | J93: =(J64+J56)/(J71+J72) -> 1.1628735 | K93: =(K64+K56)/(K71+K72) -> 0.99711738 | L93: =(L64+L56)/(L71+L72) -> 1.1291772 | ... N93: =(N64+N56)/(N71+N72) -> 1.2392422 | P93: Net Debt | Q93: =I94 -> 5168.4 | R93: =J94 -> 4606.6 | S93: =K94 -> 4636.4 | T93: =L94 -> 5976.3 | U93: =M94 -> 6279.8 | V93: =N94 -> 6852.3
B94: Net Debt | E94: =SUM(E56,E64)-E34 -> 1830.6 | F94: =SUM(F56,F64)-F34 -> 4341.4 | G94: =SUM(G56,G64)-G34 -> 3709.7 | H94: =SUM(H56,H64)-H34 -> 4758 | I94: =SUM(I56,I64)-I34 -> 5168.4 | J94: =SUM(J56,J64)-J34 -> 4606.6 | K94: =SUM(K56,K64)-K34 -> 4636.4 | L94: =SUM(L56,L64)-L34 -> 5976.3 | ... N94: =SUM(N56,N64)-N34 -> 6852.3 | P94: Debt to Equity | Q94: =I93 -> 1.5224258 | R94: =J93 -> 1.1628735 | S94: =K93 -> 0.99711738 | T94: =L93 -> 1.1291772 | U94: =M93 -> 1.1492542 | V94: =N93 -> 1.2392422
B95: Net Leverage Ratio | E95: =E94/E10 -> 2.1561837 | F95: =F94/F10 -> 4.1540522 | G95: =G94/G10 -> 2.5379353 | H95: =H94/H10 -> 2.9199141 | I95: =I94/I10 -> 3.1386409 | J95: =J94/J10 -> 3.2583109 | K95: =K94/K10 -> 2.5120009 | L95: =L94/L10 -> 4.5756833 | ... N95: =N94/N10 -> 3.363092 | P95: Net Lev. Ratio | Q95: =I95 -> 3.1386409 | R95: =J95 -> 3.2583109 | S95: =K95 -> 2.5120009 | T95: =L95 -> 4.5756833 | U95: =M95 -> 3.4259684 | V95: =N95 -> 3.363092
P96: Int. Cov. Ratio | Q96: =I98 -> 14.046468 | R96: =J98 -> 12.198529 | S96: =K98 -> 57.757962 | T96: =L98 -> 8.5865103 | U96: =M98 -> 5.6664265 | V96: =N98 -> 5.3566474
B97: Coverage Ratios
B98: Interest Coverage Ratio | E98: =E14/(-E15) -> 9.8840263 | F98: =F14/(-F15) -> 10.479371 | G98: =G14/(-G15) -> 14.49812 | H98: =H14/(-H15) -> 10.399371 | I98: =I14/(-I15) -> 14.046468 | J98: =J14/(-J15) -> 12.198529 | K98: =K14/(-K15) -> 57.757962 | L98: =L14/(-L15) -> 8.5865103 | ... N98: =N14/(-N15) -> 5.3566474
B99: Debt Service Coverage Ratio | E99: - | F99: - | G99: - | H99: - | I99: - | J99: - | K99: - | L99: - | M99: - | N99: -
B101: Payout & Cash Flow Ratios
B102: Free Cash Flow | E102: =E28 -> 71.9 | F102: =F28 -> 1916.1 | G102: =G28 -> -574.8 | H102: =H28 -> 136 | I102: =I28 -> 184.7 | J102: =J28 -> -538.4 | K102: =K28 -> 244.4 | L102: =L28 -> 48.8 | ... N102: =N28 -> 659.5
B103: Dividend Payout Ratio - NI | E103: =IFERROR(CF!B$43/E$20,"-") -> 0.25023041 | F103: =IFERROR(CF!C$43/F$20,"-") -> 0.30944625 | G103: =IFERROR(CF!D$43/G$20,"-") -> 0.20456685 | H103: =IFERROR(CF!E$43/H$20,"-") -> 0.29214607 | I103: =IFERROR(CF!F$43/I$20,"-") -> 0.31112577 | J103: =IFERROR(CF!G$43/J$20,"-") -> 0.021830005 | K103: =IFERROR(CF!H$43/K$20,"-") -> 0.094492346 | L103: =IFERROR(CF!I$43/L$20,"-") -> 2.0071429 | ... N103: =IFERROR(CF!K$43/N$20,"-") -> 0.25471698
B104: Dividend Payout Ratio - FCF | E104: =IFERROR(CF!B$43/E102,"-") -> 0.75521558 | F104: =IFERROR(CF!C$43/F102,"-") -> 0.039663901 | G104: =IFERROR(CF!D$43/G102,"-") -> -0.15118302 | H104: =IFERROR(CF!E$43/H102,"-") -> 0.85882353 | I104: =IFERROR(CF!F$43/I102,"-") -> 0.7661072 | J104: =IFERROR(CF!G$43/J102,"-") -> -0.0087295691 | K104: =IFERROR(CF!H$43/K102,"-") -> 0.21972177 | L104: =IFERROR(CF!I$43/L102,"-") -> 4.0307377 | ... N104: =IFERROR(CF!K$43/N102,"-") -> 0.13919636

Sheet BS
A1: Company Fundamentals - Balance Sheet
A2: Company Name | D2: Kion Group AG (KGX.DE)
A3: Country of Exchange | D3: Germany
A4: Country of Headquarters | D4: Germany
A5: TRBC Industry Group | D5: Machinery, Tools, Heavy Vehicles, Trains & Ships
A6: CF Template | D6: IND
A7: Consolidation Basis | D7: Consolidated
A8: Scaling | D8: Millions
A9: Period | D9: Annual
A10: Export Date | D10: 45993.357
A11: Statement Data | D11: 2015 | E11: 2016 | F11: 2017 | G11: 2018 | H11: 2019 | I11: 2020 | J11: 2021 | K11: 2022 | L11: 2023 | M11: 2024
A12: Period End Date | D12: 42369 | E12: 42735 | F12: 43100 | G12: 43465 | H12: 43830 | I12: 44196 | J12: 44561 | K12: 44926 | L12: 45291 | M12: 45657
A13: Standardized Currency | D13: EUR | E13: EUR | F13: EUR | G13: EUR | H13: EUR | I13: EUR | J13: EUR | K13: EUR | L13: EUR | M13: EUR
A14: Balance Sheet - Standardized (Currency: Euro)
A15: Field Name | D15: 31-12-2015 | E15: 31-12-2016 | F15: 31-12-2017 | G15: 31-12-2018 | H15: 31-12-2019 | I15: 31-12-2020 | J15: 31-12-2021 | K15: 31-12-2022 | L15: 31-12-2023 | M15: 31-12-2024
A16: Current Assets
A17: Cash & Short-Term Investments | D17: 140.5 | E17: 326.5 | F17: 231.5 | G17: 211.4 | H17: 249 | I17: 359.8 | J17: 517.6 | K17: 355.9 | L17: 354.5 | M17: 839.8
A18: Cash & Cash Equivalents | D18: 102.8 | E18: 276.1 | F18: 172.8 | G18: 171.6 | H18: 207.4 | I18: 307.2 | J18: 473.7 | K18: 306.2 | L18: 309.7 | M18: 786.5
A19: Short-Term Investments - Total | D19: 37.7 | E19: 50.4 | F19: 58.7 | G19: 39.8 | H19: 41.6 | I19: 52.6 | J19: 43.9 | K19: 49.7 | L19: 44.8 | M19: 53.3
A20: Financial Assets - Short-Term | D20: 37.7 | E20: 50.4 | F20: 58.7 | G20: 39.8 | H20: 41.6 | I20: 52.6 | J20: 43.9 | K20: 49.7 | L20: 44.8 | M20: 53.3
A21: Derivative Financial Instruments - Hedging - Short-Term | D21: 5.3 | E21: 10.3 | F21: 30 | G21: 8.9 | H21: 9.4 | I21: 15 | J21: 8.9 | K21: 20.5 | L21: 10.2 | M21: 12.7
A22: Loans & Receivables - Net - Short-Term | D22: 898.3 | E22: 1292.3 | F22: 1410.8 | G22: 1550.3 | H22: 1666.3 | I22: 1861.7 | J22: 2481.6 | K22: 2846.3 | L22: 2923.8 | M22: 2884.9
A23: Trade Accounts & Trade Notes Receivable - Net | D23: 670.5 | E23: 998.9 | F23: 1094.1 | G23: 1036.4 | H23: 1074.2 | I23: 1172.7 | J23: 1339.2 | K23: 1596.4 | L23: 1755.8 | M23: 1695.6
A24: Trade Accounts & Trade Notes Receivable - Gross | D24: 709 | E24: 1039.3 | F24: 1145.2 | G24: 1074.2 | H24: 1116.4 | I24: 1230.6 | J24: 1396.5 | K24: 1671.1 | L24: 1836.8 | M24: 1785.7
A25: Provision - Trade Accounts & Trade Notes Receivable | D25: 38.5 | E25: 40.4 | F25: 51.1 | G25: 37.8 | H25: 42.2 | I25: 57.9 | J25: 57.3 | K25: 74.7 | L25: 81 | M25: 90.1
A26: Loans - Short-Term | D26: 197.1 | E26: 221.6 | F26: 258.3 | G26: 305.9 | H26: 363.2 | I26: 405.9 | J26: 475.1 | K26: 529.9 | L26: 623 | M26: 734
A27: Income Tax - Receivables - Short-Term | D27: 7.9 | E27: 35.2 | F27: 14.4 | G27: 31.5 | H27: 78.7 | I27: 111 | J27: 148.2 | K27: 191.2 | L27: 141.7 | M27: 177.2
A28: Receivables - Other - Total | D28: 22.8 | E28: 36.6 | F28: 44 | G28: 176.5 | H28: 150.2 | I28: 172.1 | J28: 519.1 | K28: 528.8 | L28: 403.3 | M28: 278.1
... A33: Inventories - Other - Total | D33: 3.1 | E33: 12.6 | F33: 15.4 | G33: 27.7 | H33: 26.9 | I33: 39.6 | J33: 65.3 | K33: 62 | L33: 73.6 | M33: 54
A34: Assets Held for Sale/Discontinued Operations - Short-Term | K34: 27.4 | L34: 55.2 | M34: 0
A35: Other Current Assets - Total | D35: 32.3 | E35: 53.1 | F35: 40.6 | G35: 52.8 | H35: 58.8 | I35: 51.9 | J35: 57.7 | K35: 61.1 | L35: 62.5 | M35: 83
A36: Deferred Costs - Short-Term | D36: 32 | E36: 49.5 | F36: 40.2 | G36: 49 | H36: 55 | I36: 44.5 | J36: 48.1 | K36: 48.2 | L36: 60.4 | M36: 82.6
A37: Restricted Accounts - Short-Term | D37: 0.3 | E37: 3.5 | F37: 0.4 | G37: 3.7 | H37: 3.8 | I37: 7.2 | J37: 9.3 | K37: 11.9 | L37: 2.1 | M37: 0.5
A38: Other Current Assets | E38: 0.1 | F38: 0 | G38: 0.1 | I38: 0.2 | J38: 0.3 | K38: 1 | M38: -0.1
A39: Total Current Assets | D39: 1629.9 | E39: 2354.6 | F39: 2481.5 | G39: 2818.2 | H39: 3068.8 | I39: 3389.4 | J39: 4697.9 | K39: 5115.8 | L39: 5223.3 | M39: 5569
A40: Non-Current Assets
A41: Investments - Long-Term | D41: 43.2 | E41: 42.9 | F41: 54.9 | G41: 51.8 | H41: 60.8 | I41: 80 | J41: 95 | K41: 106.3 | L41: 123.3 | M41: 161.5
A42: Investments - Available for Sale/Held to Maturity - Long-Term | D42: 43.2 | E42: 42.9 | F42: 54.9 | G42: 51.8 | H42: 60.8 | I42: 80 | J42: 95 | K42: 106.3 | L42: 123.3 | M42: 161.5
A43: Investments in Associates, Joint Ventures and Unconsolidated Subsidiaries | D43: 73.6 | E43: 72.7 | F43: 80.3 | G43: 82.3 | H43: 84.5 | I43: 78.8 | J43: 84.3 | K43: 94.7 | L43: 103.6 | M43: 110.3
A44: Receivables & Loans - Long-Term | D44: 474.7 | E44: 535.9 | F44: 650 | G44: 826.2 | H44: 1080.9 | I44: 1208.7 | J44: 1326.9 | K44: 1383.8 | L44: 1705.5 | M44: 2090.1
A45: Loans - Long-Term | D45: 2.7 | E45: 4.6 | F45: 2.2 | G45: 0
A46: Finance Lease Receivables - Long-Term | D46: 472 | E46: 531.3 | F46: 647.8 | G46: 826.2 | H46: 1080.9 | I46: 1199.1 | J46: 1318.9 | K46: 1370.5 | L46: 1701.9 | M46: 2088.9
A47: Receivables - Other - Net - Long-Term | I47: 9.6 | J47: 8 | K47: 13.3 | L47: 3.6 | M47: 1.2
A48: Derivative Financial Instruments - Hedging - Long-Term | G48: 1 | H48: 2.6 | I48: 2.5 | J48: 4.2 | K48: 78.1 | L48: 36.9 | M48: 17.6
A49: Property, Plant & Equipment - Net - Total | D49: 1387.2 | E49: 1684.1 | F49: 1850.6 | G49: 3010.1 | H49: 3230.4 | I49: 3179.5 | J49: 3381.8 | K49: 3555 | L49: 3942.6 | M49: 4422.8
A50: Assets Leased Out under Operating Lease - Net | D50: 544 | E50: 575.3 | F50: 651.4
A51: Property, Plant & Equipment - excluding Assets Leased Out - Net - Total | D51: 843.2 | E51: 1108.8 | F51: 1199.2 | G51: 3010.1 | H51: 3230.4 | I51: 3179.5 | J51: 3381.8 | K51: 3555 | L51: 3942.6 | M51: 4422.8
A52: Land & Buildings - Net | D52: 305.7 | E52: 375.4 | F52: 355.9 | G52: 349.1 | H52: 375.7 | I52: 349.5 | J52: 385.3 | K52: 406.8 | L52: 417.1 | M52: 445.2
A53: Plant, Machinery & Equipment - Net | D53: 174.1 | E53: 266.3 | F53: 274.3 | G53: 267.7 | H53: 314.4 | I53: 374.9 | J53: 427 | K53: 491.4 | L53: 555 | M53: 615.3
A54: Construction in Progress - Net | D54: 29 | E54: 37.3 | F54: 46.7 | G54: 70.3 | H54: 93.5 | I54: 99.8 | J54: 121.7 | K54: 143.3 | L54: 188.6 | M54: 218.4
A55: Property, Plant & Equipment - Under Capital Lease - Net | D55: 334.4 | E55: 429.7 | F55: 522.3
A56: Right of Use Tangible Assets - Total - Net | G56: 2323 | H56: 2446.8 | I56: 2355.4 | J56: 2447.9 | K56: 2513.4 | L56: 2781.9 | M56: 3144
A57: Right of Use Tangible Assets - Capital/Finance Lease - Net | G57: 2323 | H57: 2446.8 | I57: 2355.4 | J57: 2447.9 | K57: 2513.4 | L57: 2781.9 | M57: 3144
A58: Property, Plant & Equipment - Other - Net | E58: 0.1 | I58: -0.1 | J58: -0.1 | K58: 0.1 | M58: -0.1
A59: Property, Plant & Equipment - Gross - Total | D59: 3308.5 | E59: 3562.8 | F59: 3864.7 | G59: 5579.5 | H59: 5922.9 | I59: 5971 | J59: 6346 | K59: 6755.8 | L59: 7232.2 | M59: 7579.5
A60: Assets Leased Out under Operating Lease - Gross | D60: 954.5 | E60: 989.9 | F60: 1114.7
A61: Property, Plant & Equipment - excluding Assets Leased Out - Gross | D61: 2354 | E61: 2572.9 | F61: 2750 | G61: 5579.5 | H61: 5922.9 | I61: 5971 | J61: 6346 | K61: 6755.8 | L61: 7232.2 | M61: 7579.5
A62: Land & Buildings - Gross | D62: 653 | E62: 729.1 | F62: 714.6 | G62: 740.6 | H62: 786.2 | I62: 781.9 | J62: 831.8 | K62: 872.7 | L62: 895.6 | M62: 931.1
A63: Plant, Machinery & Equipment - Gross | D63: 996.7 | E63: 1059.1 | F63: 1091.5 | G63: 1010.7 | H63: 1086.4 | I63: 1196 | J63: 1319.8 | K63: 1468.7 | L63: 1604.6 | M63: 1614.2
A64: Construction in Progress - Gross | D64: 29 | E64: 37.3 | F64: 46.7 | G64: 70.3 | H64: 93.5 | I64: 99.8 | J64: 121.7 | K64: 143.3 | L64: 188.6 | M64: 218.4
A65: Property, Plant & Equipment - Under Capital Lease - Gross | D65: 675.3 | E65: 747.3 | F65: 897.2
A66: Right of Use Tangible Assets - Total - Gross | G66: 3757.9 | H66: 3956.8 | I66: 3893.4 | J66: 4072.8 | K66: 4271 | L66: 4543.4 | M66: 4815.9
A67: Right of Use Tangible Assets - Capital/Finance Lease - Gross | G67: 3757.9 | H67: 3956.8 | I67: 3893.4 | J67: 4072.8 | K67: 4271 | L67: 4543.4 | M67: 4815.9
A68: Property, Plant & Equipment - Other - Gross | E68: 0.1 | I68: -0.1 | J68: -0.1 | K68: 0.1 | M68: -0.1
A69: Property, Plant & Equipment - Accumulated Depreciation & Impairment - Total | D69: 1921.3 | E69: 1878.7 | F69: 2014.1 | G69: 2569.4 | H69: 2692.5 | I69: 2791.5 | J69: 2964.2 | K69: 3200.8 | L69: 3289.6 | M69: 3156.7
A70: Assets Leased Out under Operating Lease - Accumulated Depreciation & Impairment | D70: 410.5 | E70: 414.6 | F70: 463.3
A71: Property, Plant & Equipment - excluding Assets Leased Out - Accumulated Depreciation & Impairment - Total | D71: 1510.8 | E71: 1464.1 | F71: 1550.8 | G71: 2569.4 | H71: 2692.5 | I71: 2791.5 | J71: 2964.2 | K71: 3200.8 | L71: 3289.6 | M71: 3156.7
A72: Land & Buildings - Accumulated Depreciation & Impairment | D72: 347.3 | E72: 353.7 | F72: 358.7 | G72: 391.5 | H72: 410.5 | I72: 432.4 | J72: 446.5 | K72: 465.9 | L72: 478.5 | M72: 485.9
A73: Plant, Machinery & Equipment - Accumulated Depreciation & Impairment | D73: 822.6 | E73: 792.8 | F73: 817.2 | G73: 743 | H73: 772 | I73: 821.1 | J73: 892.8 | K73: 977.3 | L73: 1049.6 | M73: 998.9
A74: Construction in Progress - Accumulated Depreciation & Impairment | D74: 0 | E74: 0 | F74: 0 | G74: 0 | H74: 0 | I74: 0 | J74: 0 | K74: 0 | L74: 0 | M74: 0
A75: Property, Plant & Equipment - Under Capital Lease - Accumulated Depreciation & Impairment | D75: 340.9 | E75: 317.6 | F75: 374.9
A76: Right of Use Tangible Assets - Total/Unspecified - Accumulated Depreciation | G76: 1434.9 | H76: 1510 | I76: 1538 | J76: 1624.9 | K76: 1757.6 | L76: 1761.5 | M76: 1671.9
A77: Right of Use Tangible Assets - Capital/Finance Lease - Accumulated Depreciation | G77: 1434.9 | H77: 1510 | I77: 1538 | J77: 1624.9 | K77: 1757.6 | L77: 1761.5 | M77: 1671.9
A78: Other Non-Current Assets - Total | D78: 379.1 | E78: 432.3 | F78: 394.7 | G78: 457.6 | H78: 504.8 | I78: 557.2 | J78: 550.1 | K78: 413.2 | L78: 588.3 | M78: 619.2
A79: Deferred Tax - Asset - Long-Term | D79: 349 | E79: 420.2 | F79: 370.5 | G79: 421.7 | H79: 449.7 | I79: 494.9 | J79: 449.3 | K79: 300.8 | L79: 443.2 | M79: 489.3
A80: Pension Assets - Long-Term | D80: 30.2 | E80: 12.3 | F80: 24.2 | G80: 33.3 | H80: 51.7 | I80: 50.4 | J80: 79.7 | K80: 94 | L80: 100.9 | M80: 80.6
A81: Other Non-Current Assets | D81: -0.1 | E81: -0.2 | G81: 2.6 | H81: 3.4 | I81: 11.9 | J81: 21.1 | K81: 18.4 | L81: 44.2 | M81: 49.3
A82: Intangible Assets - Total - Net | D82: 2452.5 | E82: 6236.7 | F82: 5716.4 | G82: 5721.6 | H82: 5732.4 | I82: 5559.6 | J82: 5710.7 | K82: 5781.5 | L82: 5664.9 | M82: 5814.9
A83: Goodwill/Cost in Excess of Assets Purchased - Net | D83: 1548.1 | E83: 3605.8 | F83: 3382.5 | G83: 3424.8 | H83: 3475.8 | I83: 3407.6 | J83: 3544.8 | K83: 3619.4 | L83: 3558 | M83: 3648.2
A84: Intangible Assets - excluding Goodwill - Net - Total | D84: 904.4 | E84: 2630.9 | F84: 2333.9 | G84: 2296.8 | H84: 2256.6 | I84: 2152 | J84: 2165.9 | K84: 2162.1 | L84: 2106.9 | M84: 2166.7
A85: Research & Development Costs - Net | D85: 194.1 | E85: 729.2 | F85: 670.3 | G85: 689.7 | H85: 697.9 | I85: 656.5 | J85: 680.6 | K85: 706.3 | L85: 692.6 | M85: 726.5
A86: Brands, Patents, Trademarks, Marketing & Artistic Intangibles - Net | D86: 604.1 | E86: 972.2 | F86: 944.6 | G86: 944.3 | H86: 939.8 | I86: 939.1 | J86: 939.7 | K86: 939.4 | L86: 938.9 | M86: 939.3
A87: Intangible Assets - Other - Net | D87: 106.2 | E87: 929.5 | F87: 719 | G87: 662.8 | H87: 618.9 | I87: 556.4 | J87: 545.6 | K87: 516.4 | L87: 475.4 | M87: 500.9
A88: Intangible Assets - Gross - Total | D88: 2902.1 | E88: 6677.9 | F88: 6304.4 | G88: 6372.2 | H88: 6464.7 | I88: 6401 | J88: 6717.2 | K88: 6979.3 | L88: 6989.3 | M88: 7312.9
A89: Goodwill/Cost in Excess of Assets Purchased - Gross | D89: 1548.1 | E89: 3605.8 | F89: 3382.5 | G89: 3424.8 | H89: 3475.8 | I89: 3407.6 | J89: 3544.8 | K89: 3619.6 | L89: 3558.1 | M89: 3671.5
A90: Intangible Assets - excluding Goodwill - Gross | D90: 1354 | E90: 3072.1 | F90: 2921.9 | G90: 2947.4 | H90: 2988.9 | I90: 2993.4 | J90: 3172.4 | K90: 3359.7 | L90: 3431.2 | M90: 3641.4
A91: Research & Development Costs - Gross | D91: 451.4 | E91: 938.5 | F91: 917.2 | G91: 992.4 | H91: 1042.6 | I91: 1063.8 | J91: 1173.4 | K91: 1301.7 | L91: 1363.7 | M91: 1493.8
A92: Brands, Patents, Trademarks, Marketing & Artistic Intangibles - Gross | D92: 605.6 | E92: 974.1 | F92: 955.2 | G92: 954.9 | H92: 946.4 | I92: 945.7 | J92: 946.7 | K92: 946.4 | L92: 945.8 | M92: 946.4
A93: Intangible Assets - Other - Gross - Total | D93: 297 | E93: 1159.5 | F93: 1049.5 | G93: 1000.1 | H93: 999.9 | I93: 983.9 | J93: 1052.3 | K93: 1111.6 | L93: 1121.7 | M93: 1201.2
... A100: Total Non-Current Assets | D100: 4810.3 | E100: 9004.6 | F100: 8746.9 | G100: 10150.6 | H100: 10696.4 | I100: 10666.3 | J100: 11153 | K100: 11412.6 | L100: 12165.1 | M100: 13236.4
A101: Total Assets
A102: Total Assets | D102: 6440.2 | E102: 11359.2 | F102: 11228.4 | G102: 12968.8 | H102: 13765.2 | I102: 14055.7 | J102: 15850.9 | K102: 16528.4 | L102: 17388.4 | M102: 18805.4
A103: Current Liabilities
A104: Trade Accounts Payable & Accruals - Short-Term | D104: 797.4 | E104: 1103.4 | F104: 1225.1 | G104: 1222.6 | H104: 1325.6 | I104: 1234.2 | J104: 1858.3 | K104: 1533.9 | L104: 1700.5 | M104: 1686.7
A105: Trade Accounts & Trade Notes Payable - Short-Term | D105: 574.6 | E105: 802.2 | F105: 923.9 | G105: 904.2 | H105: 975.9 | I105: 910.5 | J105: 1443.7 | K105: 1124.3 | L105: 1194 | M105: 1160.4
A106: Accrued Expenses - Short-Term | D106: 222.8 | E106: 301.2 | F106: 301.2 | G106: 318.4 | H106: 349.7 | I106: 323.7 | J106: 414.6 | K106: 409.6 | L106: 506.5 | M106: 526.3
A107: Short-Term Debt & Current Portion of Long-Term Debt | D107: 484.6 | E107: 715.1 | F107: 735.9 | G107: 1224.9 | H107: 1407.6 | I107: 1362.5 | J107: 1712.9 | K107: 1835.1 | L107: 1607.4 | M107: 2258.1
A108: Current Portion of Long-Term Debt including Capitalized Leases | D108: 484.6 | E108: 715.1 | F108: 735.9 | G108: 1224.9 | H108: 1407.6 | I108: 1362.5 | J108: 1712.9 | K108: 1835.1 | L108: 1607.4 | M108: 2258.1
A109: Current Portion of Long-Term Debt excluding Capitalized Leases | D109: 119.3 | E109: 293.9 | F109: 243.9 | G109: 226.5 | H109: 103.7 | I109: 77.1 | J109: 151.9 | K109: 626.7 | L109: 236.8 | M109: 698.3
A110: Capitalized Leases - Current Portion | D110: 365.3 | E110: 421.2 | F110: 492 | G110: 998.4 | H110: 1303.9 | I110: 1285.4 | J110: 1561 | K110: 1208.4 | L110: 1370.6 | M110: 1559.8
...

Sheet IS
A1: Company Fundamentals - Income Statement
A2: Company Name | B2: Kion Group AG (KGX.DE)
A3: Country of Exchange | B3: Germany
A4: Country of Headquarters | B4: Germany
A5: TRBC Industry Group | B5: Machinery, Tools, Heavy Vehicles, Trains & Ships
A6: CF Template | B6: IND
A7: Consolidation Basis | B7: Consolidated
A8: Scaling | B8: Millions
A9: Period | B9: Annual
A10: Export Date | B10: 45993.357
A11: Statement Data | B11: 2015 | C11: 2016 | D11: 2017 | E11: 2018 | F11: 2019 | G11: 2020 | H11: 2021 | I11: 2022 | J11: 2023 | K11: 2024
A12: Period End Date | B12: 42369 | C12: 42735 | D12: 43100 | E12: 43465 | F12: 43830 | G12: 44196 | H12: 44561 | I12: 44926 | J12: 45291 | K12: 45657
A13: Standardized Currency | B13: EUR | C13: EUR | D13: EUR | E13: EUR | F13: EUR | G13: EUR | H13: EUR | I13: EUR | J13: EUR | K13: EUR
A14: Income Statement - Standardized (Currency: Euro)
A15: Field Name | B15: 31-12-2015 | C15: 31-12-2016 | D15: 31-12-2017 | E15: 31-12-2018 | F15: 31-12-2019 | G15: 31-12-2020 | H15: 31-12-2021 | I15: 31-12-2022 | J15: 31-12-2023 | K15: 31-12-2024
A16: Revenues
A17: Revenue from Goods & Services | B17: 5097.9 | C17: 5587.2 | D17: 7653.6 | E17: 7995.7 | F17: 8806.5 | G17: 8341.6 | H17: 10294.3 | I17: 11135.6 | J17: 11433.7 | K17: 11503.2
A18: Sales of Goods & Services - Net - Unclassified | B18: 5097.9 | C18: 5587.2 | D18: 7653.6 | E18: 7995.7 | F18: 8806.5 | G18: 8341.6 | H18: 10294.3 | I18: 11135.6 | J18: 11433.7 | K18: 11503.2
A19: Revenue from Business Activities - Total | B19: 5097.9 | C19: 5587.2 | D19: 7653.6 | E19: 7995.7 | F19: 8806.5 | G19: 8341.6 | H19: 10294.3 | I19: 11135.6 | J19: 11433.7 | K19: 11503.2
A20: Operating Expenses
A21: Cost of Operating Revenue | B21: 3601.7 | C21: 4034.6 | D21: 5699.1 | E21: 5898.1 | F21: 6474.6 | G21: 6296.8 | H21: 7770.7 | I21: 9011.5 | J21: 8652.5 | K21: 8409.7
A22: Cost of Revenues - Total | B22: 3601.7 | C22: 4034.6 | D22: 5699.1 | E22: 5898.1 | F22: 6474.6 | G22: 6296.8 | H22: 7770.7 | I22: 9011.5 | J22: 8652.5 | K22: 8409.7
A23: Cost of Revenues - Unclassified | C23: 3977.6 | D23: 5630.1 | E23: 5821.5 | H23: 7670.8 | I23: 8898.9 | J23: 8534.9 | K23: 8293.5
A24: Amortization in Cost of Revenues | C24: 57 | D24: 69 | E24: 76.6 | H24: 99.9 | I24: 112.6 | J24: 117.6 | K24: 116.2
A25: Gross Profit - Industrials/Property - Total | B25: 1496.2 | C25: 1552.6 | D25: 1954.5 | E25: 2097.6 | F25: 2331.9 | G25: 2044.8 | H25: 2523.6 | I25: 2124.1 | J25: 2781.2 | K25: 3093.5
A26: Selling, General & Administrative Expenses - Total | B26: 1116.9 | C26: 1149.2 | D26: 1423.4 | E26: 1490.3 | F26: 1642.4 | G26: 1627 | H26: 1759.9 | I26: 1977.9 | J26: 2139.3 | K26: 2301
A27: Selling, General & Administrative Expenses - Unclassified | B27: 973.9 | C27: 1052.7 | D27: 1286.4 | E27: 1352.6 | F27: 1487.1 | G27: 1470.2 | H27: 1585.2 | I27: 1774.6 | J27: 1904.2 | K27: 2041.4
A28: Research & Development Expense | B28: 143 | C28: 96.5 | D28: 137 | E28: 137.7 | F28: 155.3 | G28: 156.8 | H28: 174.7 | I28: 203.3 | J28: 235.1 | K28: 259.6
A29: Other Operating Expense/(Income) - Net | B29: -72.4 | C29: -130 | D29: -240.2 | E29: -54.1 | F29: -66.2 | G29: -79.9 | H29: -143.1 | I29: -146.6 | J29: -144.6 | K29: -134.2
A30: Other Operating Income - Total | B30: 63.8 | C30: 56.1 | D30: 34.3 | E30: 36.4 | F30: 28.7 | G30: 24.8 | H30: 28.4 | I30: 28.5 | J30: 24.8 | K30: 33.9
A31: Other Operating Expense | B31: 23.7 | C31: 13.8 | D31: 12.9 | E31: 5.7 | F31: 7.3 | G31: 13.4 | H31: 11.7 | I31: 14.8 | J31: 18.3 | K31: 44.2
A32: Operating Provisions - Increase/(Decrease) | B32: -5.3 | C32: -6 | D32: -2.5 | E32: -2.4 | F32: -1.9 | G32: -3.4 | H32: -3.8 | I32: -8.7 | J32: -8.2 | K32: -5.1
A33: Non-Recurring Adjustments - Operating - Decrease/(Increase) | B33: 27 | C33: 81.7 | D33: 216.3 | E33: 21 | F33: 42.9 | G33: 65.1 | H33: 122.6 | I33: 124.2 | J33: 129.9 | K33: 139.4
A34: Operating Expenses - Total | B34: 4646.2 | C34: 5053.8 | D34: 6882.3 | E34: 7334.3 | F34: 8050.8 | G34: 7843.9 | H34: 9387.5 | I34: 10842.8 | J34: 10647.2 | K34: 10576.5
A35: Operating Profit
A36: Operating Profit before Non-Recurring Income/Expense | B36: 451.7 | C36: 533.4 | D36: 771.3 | E36: 661.4 | F36: 755.7 | G36: 497.7 | H36: 906.8 | I36: 292.8 | J36: 786.5 | K36: 926.7
A37: Non-Operating Expenses | B37: =SUM(B38,B45,B46,B47) -> -57.4 | C37: =SUM(C38,C45,C46,C47) -> -65.9 | D37: =SUM(D38,D45,D46,D47) -> -71.9 | E37: =SUM(E38,E45,E46,E47) -> -88.7 | F37: =SUM(F38,F45,F46,F47) -> -84.3 | G37: =SUM(G38,G45,G46,G47) -> -107.8 | H37: =SUM(H38,H45,H46,H47) -> -28.1 | I37: =SUM(I38,I45,I46,I47) -> 24.1 | ... K37: =SUM(K38,K45,K46,K47) -> -121.7
A38: Financing Income/(Expense) - Net - Total | B38: -104.6 | C38: -73 | D38: -86.7 | E38: -103.2 | F38: -100.9 | G38: -110.6 | H38: -46.5 | I38: 4.4 | J38: -129.2 | K38: -142.7
A39: Interest Expense - Net of (Interest Income) | B39: 45.7 | C39: 50.9 | D39: 53.2 | E39: 63.6 | F39: 53.8 | G39: 40.8 | H39: 15.7 | I39: 34.1 | J39: 138.8 | K39: 173
A40: Interest Income - Non-Bank | B40: 44.8 | C40: 36.4 | D40: 36.2 | E40: 43.8 | F40: 51.9 | G40: 58.8 | H40: 71.8 | I40: 80.6 | J40: 102 | K40: 140.2
A41: Interest Expense - Net of Capitalized Interest | B41: 90.5 | C41: 87.3 | D41: 89.4 | E41: 107.4 | F41: 105.7 | G41: 99.6 | H41: 87.5 | I41: 114.7 | J41: 240.8 | K41: 313.2
A42: Non-Interest Financial Income/(Expense) - Total | B42: -58.9 | C42: -22.1 | D42: -33.5 | E42: -39.6 | F42: -47.1 | G42: -69.8 | H42: -30.8 | I42: 38.5 | J42: 9.6 | K42: 30.3
A43: Foreign Exchange Gain/(Loss) - Non-Business | B43: -13.2 | C43: -6.5 | D43: 15.3 | E43: -12.1 | F43: -14 | G43: -35.7 | H43: -17.3 | I43: -22.3 | J43: -37.9 | K43: -13.2
A44: Non-Interest Financial Income/(Expense) - Other - Net | B44: -45.7 | C44: -15.6 | D44: -48.8 | E44: -27.5 | F44: -33.1 | G44: -34.1 | H44: -13.5 | I44: 60.8 | J44: 47.5 | K44: 43.5
A45: Sale of Tangible & Intangible Fixed Assets - Gain/(Loss) | B45: 2.3 | C45: -0.6 | E45: 1.2 | F45: 3.6 | G45: 5 | H45: 5.3 | I45: 5.7 | J45: 6 | K45: 5.6
A46: Equity Earnings/(Loss) - before Taxes including Non-Recurring | B46: 10.6 | C46: 6.5 | D46: 13.6 | E46: 12.2 | F46: 12.1 | G46: -2.2 | H46: 13.1 | I46: 14.1 | J46: 12.8 | K46: 15.4
A47: Other Non-Operating Income/(Expense) - Total | B47: 34.3 | C47: 1.2 | D47: 1.2 | E47: 1.1 | F47: 0.9 | I47: -0.1
A48: Non-Operating Rental Income | B48: 1.3 | C48: 1.2 | D48: 1.2 | E48: 1.2 | F48: 0.8
A49: Non-Recurring Adjustments - Non-Operating- Decrease/(Increase) | B49: 33
A50: Normalized Pre-tax Profit | B50: 394.3 | C50: 467.5 | D50: 699.4 | E50: 572.7 | F50: 671.4 | G50: 389.9 | H50: 878.7 | I50: 316.9 | J50: 676.1 | K50: 805
A51: Non-Recurring Income/Expense
A52: Non-Recurring Income/(Expense) - Total | B52: -64.1 | C52: -128.3 | D52: -231.1 | E52: -27.4 | F52: -49.8 | G52: -88.3 | H52: -119 | I52: -178.9 | J52: -216.3 | K52: -215.2
A53: Impairment - Tangible & Intangible Fixed Assets | B53: 4.1 | D53: 14.8 | E53: 6.4 | F53: 6.9 | G53: 21.6 | H53: 2.3 | I53: 20.2 | J53: 6.7 | K53: 30
A54: Impairment - Fixed Assets | D54: 6.2 | E54: 1.3 | F54: 1.2 | G54: 16.2 | H54: 1.2 | I54: 17.8 | J54: 5.6 | K54: 1.1
A55: Impairment - Goodwill | K55: 22.4
A56: Impairment - Intangibles excluding Goodwill | B56: 4.1 | D56: 8.6 | E56: 5.1 | F56: 5.7 | G56: 5.4 | H56: 1.1 | I56: 2.4 | J56: 1.1 | K56: 6.5
A57: Derivatives - Hedging - Gain/(Loss) | H57: 5.9 | I57: -34.5 | J57: -79.7 | K57: -45.8
A58: Sale & Acquisition of Group Companies - Gain/(Loss) | B58: -27 | C58: -81.3 | D58: -176.2 | G58: -1.6
A59: Non-Recurring Income/(Expense) - Other - Total | B59: -33 | C59: -47 | D59: -40.1 | E59: -21 | F59: -42.9 | G59: -65.1 | H59: -122.6 | I59: -124.2 | J59: -129.9 | K59: -139.4
A60: Pre-Tax Income
A61: Income before Taxes | B61: 330.2 | C61: 339.2 | D61: 468.3 | E61: 545.3 | F61: 621.6 | G61: 301.6 | H61: 759.7 | I61: 138 | J61: 459.8 | K61: 589.8
A62: Taxes
A63: Income Taxes | B63: 109.2 | C63: 93.1 | D63: 41.9 | E63: 143.7 | F63: 176.8 | G63: 90.7 | H63: 191.7 | I63: 32.2 | J63: 145.4 | K63: 220.5
A64: Income Taxes for the Year - Current | B64: 132.5 | C64: 86.2 | D64: 184.9 | E64: 166.5 | F64: 212.8 | G64: 145.2 | H64: 203.8 | I64: 107.2 | J64: 286.6 | K64: 265.6
A65: Income Taxes - Deferred | B65: -23.3 | C65: 6.9 | D65: -143 | E65: -22.9 | F65: -36 | G65: -54.5 | H65: -12.1 | I65: -75 | J65: -141.2 | K65: -45.1
A66: Income Taxes - Other (by Type) | E66: 0.1
A67: Net Income After Tax
A68: Net Income after Tax | B68: 221 | C68: 246.1 | D68: 426.4 | E68: 401.6 | F68: 444.8 | G68: 210.9 | H68: 568 | I68: 105.8 | J68: 314.4 | K68: 369.3
A69: After Tax Income/Expense
A70: After-Tax Adjustments - Other - Income/(Expense) - Total | B70: 0.1
A71: Income before Discontinued Operations & Extraordinary Items | B71: 221.1 | C71: 246.1 | D71: 426.4 | E71: 401.6 | F71: 444.8 | G71: 210.9 | H71: 568 | I71: 105.8 | J71: 314.4 | K71: 369.3
A72: Net Income before Minority Interest | B72: 221.1 | C72: 246.1 | D72: 426.4 | E72: 401.6 | F72: 444.8 | G72: 210.9 | H72: 568 | I72: 105.8 | J72: 314.4 | K72: 369.3
A73: Minority Interest | B73: 3.9 | C73: 0.5 | D73: 1.6 | E73: 1.8 | F73: -10 | G73: -4.4 | H73: -0.3 | I73: 7.8 | J73: 8.6 | K73: 8.9
A74: Net Income after Minority Interest | B74: 217.2 | C74: 245.6 | D74: 424.8 | E74: 399.8 | F74: 454.8 | G74: 215.3 | H74: 568.3 | I74: 98 | J74: 305.8 | K74: 360.4
A75: Net Income
A76: Earnings Adjustments to Net Income - Other Expense/(Income) | B76: 0.1 | C76: 0.1 | E76: -0.1 | K76: 0.1
A77: Income Available to Common Shares | B77: 217.1 | C77: 245.5 | D77: 424.8 | E77: 399.9 | F77: 454.8 | G77: 215.3 | H77: 568.3 | I77: 98 | J77: 305.8 | K77: 360.3
A78: Other Comprehensive Income
A79: Other Comprehensive Income - Starting Line | D79: 426.4 | E79: 401.6 | F79: 444.8 | G79: 210.9 | H79: 568 | I79: 105.8 | J79: 314.4 | K79: 369.2
A80: Other Comprehensive Income - Foreign Currency | F80: 76.1 | G80: -204.4 | H80: 234.5 | I80: 92.6 | J80: -79 | K80: 151.5
A81: Other Comprehensive Income - Unrealized Investment Gain/(Loss) | D81: -306.8 | E81: 29.1 | F81: -1.9 | G81: 1.6 | H81: 2.2 | I81: 14.4 | J81: 31.2 | K81: 27
A82: Other Comprehensive Income - Hedging Gain/(Loss) | D82: 3.7 | E82: -12.2 | F82: -6.3 | G82: 15.6 | H82: -3.3 | I82: 7 | J82: 1.9 | K82: -14.5
A83: Other Comprehensive Income - Other | E83: -0.1 | F83: -0.2 | G83: -0.1 | H83: 0.2 | J83: -0.1
A84: Other Comprehensive Income - Associated Companies | D84: 1.6 | E84: 0.2 | F84: -0.3 | G84: -2 | H84: -0.4 | I84: 5.1 | J84: 0.7 | K84: -0.4
A85: Other Comprehensive Income - Pension Related | D85: 18.7 | E85: -0.2 | F85: -168.1 | G85: -151.3 | H85: 212.5 | I85: 587.7 | J85: -84.7 | K85: -22
A86: Other Comprehensive Income - Income Tax | F86: 52.3 | G86: 45.8 | H86: -61.6 | I86: -177.1 | J86: 26 | K86: 6.8
A87: Other Comprehensive Income - Net of Tax - Total | D87: -282.8 | E87: 16.8 | F87: -48.4 | G87: -294.8 | H87: 384.1 | I87: 529.7 | J87: -104 | K87: 148.4
A88: Comprehensive Income before Minority Interest - Total | D88: 143.6 | E88: 418.4 | F88: 396.4 | G88: -83.9 | H88: 952.1 | I88: 635.5 | J88: 210.4 | K88: 517.6
A89: Comprehensive Income - Attributable to Minority Interest - Total | D89: 1.1 | E89: 1.5 | F89: -9.4 | G89: -1.9 | H89: 5.8 | I89: 7.6 | J89: 8.4 | K89: 9.1
A90: Comprehensive Income - Attributable to Parent Company Equity Holders - Total | D90: 142.5 | E90: 416.9 | F90: 405.9 | G90: -81.9 | H90: 946.3 | I90: 627.9 | J90: 202 | K90: 508.5
A91: Share/Per Share - Basic
A92: Net Income - Basic - including Extraordinary Items Applicable to Common - Total | B92: 217.1 | C92: 245.5 | D92: 424.8 | E92: 399.9 | F92: 454.8 | G92: 215.3 | H92: 568.3 | I92: 98 | J92: 305.8 | K92: 360.3
A93: Income available to Common excluding Extraordinary Items | B93: 217.1 | C93: 245.5 | D93: 424.8 | E93: 399.9 | F93: 454.8 | G93: 215.3 | H93: 568.3 | I93: 98 | J93: 305.8 | K93: 360.3
A94: Shares used to calculate Basic EPS - Total | B94: 99.42 | C94: 103.97 | D94: 115.14 | E94: 118.75 | F94: 118.74 | G94: 118.9 | H94: 131.09 | I94: 131.11 | J94: 131.11 | K94: 131.11
A95: EPS - Basic - including Extraordinary Items Applicable to Common - Total | B95: 2.18 | C95: 2.36 | D95: 3.69 | E95: 3.37 | F95: 3.83 | G95: 1.81 | H95: 4.34 | I95: 0.75 | J95: 2.33 | K95: 2.75
A96: EPS - Basic - excluding Extraordinary Items Applicable to Common - Total | B96: 2.18 | C96: 2.36 | D96: 3.69 | E96: 3.37 | F96: 3.83 | G96: 1.81 | H96: 4.34 | I96: 0.75 | J96: 2.33 | K96: 2.75
A97: EPS - Basic - excluding Extraordinary Items - Normalized - Total | B97: 2.83 | C97: 3.6 | D97: 5.7 | E97: 3.6 | F97: 4.25 | G97: 2.55 | H97: 5.24 | I97: 2.11 | J97: 3.98 | K97: 4.39
A98: Allocated Net Income including Extraordinary Items Applicable to Common - Issue Specific | B98: 217.1 | C98: 245.5 | D98: 424.8 | E98: 399.9 | F98: 454.8 | G98: 215.3 | H98: 568.3 | I98: 98 | J98: 305.8 | K98: 360.3
A99: Earnings Allocation Factor - Basic - Issue Specific | B99: 1 | C99: 1 | D99: 1 | E99: 1 | F99: 1 | G99: 1 | H99: 1 | I99: 1 | J99: 1 | K99: 1
A100: Shares used to calculate Basic EPS - Issue Specific | B100: 99.42 | C100: 103.97 | D100: 115.14 | E100: 118.75 | F100: 118.74 | G100: 118.9 | H100: 131.09 | I100: 131.11 | J100: 131.11 | K100: 131.11
...

Sheet CF
A1: Company Fundamentals - Cash Flow
A2: Company Name | B2: Kion Group AG (KGX.DE)
A3: Country of Exchange | B3: Germany
A4: Country of Headquarters | B4: Germany
A5: TRBC Industry Group | B5: Machinery, Tools, Heavy Vehicles, Trains & Ships
A6: CF Template | B6: IND
A7: Consolidation Basis | B7: Consolidated
A8: Scaling | B8: Millions
A9: Period | B9: Annual
A10: Export Date | B10: 46010.541
A11: Statement Data | B11: 2015 | C11: 2016 | D11: 2017 | E11: 2018 | F11: 2019 | G11: 2020 | H11: 2021 | I11: 2022 | J11: 2023 | K11: 2024
A12: Period End Date | B12: 42369 | C12: 42735 | D12: 43100 | E12: 43465 | F12: 43830 | G12: 44196 | H12: 44561 | I12: 44926 | J12: 45291 | K12: 45657
A13: Standardized Currency | B13: EUR | C13: EUR | D13: EUR | E13: EUR | F13: EUR | G13: EUR | H13: EUR | I13: EUR | J13: EUR | K13: EUR
A14: Cash Flow - Standardized (Currency: Standardized)
A15: Field Name | B15: 31-12-2015 | C15: 31-12-2016 | D15: 31-12-2017 | E15: 31-12-2018 | F15: 31-12-2019 | G15: 31-12-2020 | H15: 31-12-2021 | I15: 31-12-2022 | J15: 31-12-2023 | K15: 31-12-2024
A16: Operating Cash Flow - Indirect
A17: Profit/(Loss) - Starting Line - Cash Flow | B17: 422.8 | C17: 434.8 | D17: 561 | E17: 642.8 | F17: 716.6 | G17: 389.9 | H17: 794.8 | I17: 168.3 | J17: 660.6 | K17: 777.8
A18: Non-cash Items & Reconciliation Adjustments - Cash Flow | B18: 387.6 | C18: 480.7 | D18: 636.9 | E18: 649.8 | F18: 687 | G18: 776 | H18: 759 | I18: 904.3 | J18: 886.2 | K18: 896.4
A19: Financial Income/(Expense) - Cash Flow - to Reconcile | K19: -86.4
A20: Other Non-Cash Items & Reconciliation Adjustments - Cash Flow - to Reconcile | B20: -11.4 | C20: 24.3 | D20: -259.5 | E20: -246.9 | F20: -207.4 | G20: -156.9 | H20: -176.6 | I20: -124.3 | J20: -160.9 | K20: -150.8
A21: Depreciation, Depletion & Amortization including Impairment - Cash Flow - to Reconcile | B21: 401.4 | C21: 454.7 | D21: 896.6 | E21: 897.9 | F21: 898 | G21: 937.8 | H21: 940.9 | I21: 1033.5 | J21: 1053 | K21: 1139.2
A22: Assets Sale - Gain/(Loss) - Cash Flow - to Reconcile | B22: -2.4 | C22: 1.7 | D22: -0.2 | E22: -1.2 | F22: -3.6 | G22: -4.9 | H22: -5.3 | I22: -4.9 | J22: -5.9 | K22: -5.6
A23: Income Taxes - Paid/(Reimbursed) - Cash Flow | B23: 84.8 | C23: 108.7 | D23: 136.3 | E23: 193.2 | F23: 191.6 | G23: 216.8 | H23: 201.4 | I23: 160 | J23: 180 | K23: 302.9
A24: Interest Paid - Cash | B24: 56 | C24: 99.5 | D24: 174.5 | E24: 161.9 | F24: 167 | G24: 185.1 | H24: 182.2 | I24: 187.5 | J24: 295.9 | K24: 103.9
A25: Interest & Dividends - Received - Total - Cash Flow | B25: 25.3 | C25: 17.6 | D25: 16.8 | E25: 16.7 | F25: 15.3 | G25: 7.1 | H25: 10.8 | I25: 15 | J25: 19.6 | K25: 22.9
A26: Cash Flow from Operating Activities before Changes in Working Capital | B26: 694.9 | C26: 724.9 | D26: 903.9 | E26: 954.2 | F26: 1060.3 | G26: 771.1 | H26: 1181 | I26: 740.1 | J26: 1090.5 | K26: 1290.3
A27: Working Capital - Increase/(Decrease) - Cash Flow | B27: -270.6 | C27: -392.5 | D27: -349.7 | E27: -333.9 | F27: -365.7 | G27: -421.9 | H27: -470.8 | I27: -1258.5 | J27: -161.9 | K27: -200.7
A28: Accounts Receivables - Decrease/(Increase) - Cash Flow | B28: -60.9 | C28: -78.8 | H28: 356.4 | I28: -590.9 | J28: -22.3 | K28: 34.2
A29: Inventories - Decrease/(Increase) - Cash Flow | B29: -22.1 | C29: -31.2 | H29: -490.1 | I29: -163.2 | J29: -31.7 | K29: 93.8
A30: Other Liabilities - Increase/(Decrease) -Total - Cash Flow | B30: 23.6 | C30: 4.7 | D30: -4 | E30: -19 | F30: 22.5 | G30: 59.8 | H30: 36.6 | I30: 30.9 | J30: 81.1 | K30: 19.3
A31: Other Assets & Liabilities - Increase/(Decrease) - Net - Cash Flow | B31: -211.2 | C31: -287.2 | D31: -345.7 | E31: -314.9 | F31: -388.2 | G31: -481.7 | H31: -373.7 | I31: -535.3 | J31: -189 | K31: -348
A32: Net Cash Flow from Operating Activities | B32: 424.3 | C32: 332.4 | D32: 554.2 | E32: 620.3 | F32: 694.6 | G32: 349.2 | H32: 710.2 | I32: -518.4 | J32: 928.6 | K32: 1089.6
A33: Investing Cash Flow
A34: Capital Expenditures - Net - Cash Flow | B34: 128.5 | C34: 160.3 | D34: 214.3 | E34: 253.4 | F34: 283.8 | G34: 278.1 | H34: 317 | I34: 375.2 | J34: 427.6 | K34: 453.7
A35: Capital Expenditures - Total | B35: 142.6 | C35: 166.7 | D35: 218.3 | E35: 258.5 | F35: 287.4 | G35: 283.8 | H35: 333.8 | I35: 382.7 | J35: 442.8 | K35: 462.9
A36: Acquisition & Disposals of Business - Assets - Sold/(Acquired) - Net - Cash Flow | B36: -84.9 | C36: -2118.7 | D36: -13.3 | E36: -1.6 | F36: -10 | G36: -133.5 | H36: -17 | I36: -4.9 | J36: -2.8 | K36: -26.4
A37: Acquisition of Business - Cash Flow | B37: 84.9 | C37: 2118.7 | D37: 13.3 | E37: 1.6 | F37: 10 | G37: 133.5 | H37: 17 | I37: 4.9 | J37: 2.8 | K37: 36.7
A38: Business - Sold - Cash Flow | K38: 10.3
A39: Investments - Associated Companies & Joint Ventures - Sold/(Purchased) - Cash Flow | B39: 77.4 | C39: 0
A40: Other Investing Cash Flow - Decrease/(Increase) | B40: -4.5 | C40: 5.1 | D40: -19.3 | E40: -4.8 | F40: 3.7 | G40: -0.3 | H40: -12 | I40: -0.1 | J40: -8.3 | K40: -0.1
A41: Net Cash Flow from Investing Activities | B41: -140.5 | C41: -2273.9 | D41: -246.9 | E41: -259.8 | F41: -290.1 | G41: -411.9 | H41: -346 | I41: -380.2 | J41: -438.7 | K41: -480.2
A42: Financing Cash Flow
A43: Dividends Paid - Cash - Total - Cash Flow | B43: 54.3 | C43: 76 | D43: 86.9 | E43: 116.8 | F43: 141.5 | G43: 4.7 | H43: 53.7 | I43: 196.7 | J43: 24.9 | K43: 91.8
A44: Dividends - Common - Cash Paid | B44: 54.3 | C44: 76 | D44: 86.9 | E44: 116.8 | F44: 141.5 | G44: 4.7 | H44: 53.7 | I44: 196.7 | J44: 24.9 | K44: 91.8
A45: Stock - Total - Issuance/(Retirement) - Net - Cash Flow | B45: 0.4 | C45: 457.1 | D45: 596.6 | E45: -1.9 | F45: 0.8 | G45: 813.6 | H45: 0
A46: Stock - Issuance/(Retirement) - Net - Excluding Options/Warrants - Cash Flow | B46: 0.4 | C46: 457.1 | D46: 596.6 | E46: -1.9 | F46: 0.8 | G46: 813.6 | H46: 0
A47: Stock - Common - Issuance/(Retirement) - Net - Cash Flow | B47: 0.4 | C47: 457.1 | D47: 596.6 | E47: -1.9 | F47: 0.8 | G47: 813.6 | H47: 0
A48: Stock - Common - Issued/Sold - Cash Flow | B48: 3.1 | C48: 459.9 | D48: 600.9 | E48: 1.7 | F48: 3.7 | G48: 813.6 | H48: 0
A49: Stock - Common - Repurchased/Retired - Cash Flow | B49: 2.7 | C49: 2.8 | D49: 4.3 | E49: 3.6 | F49: 2.9 | G49: 0
A50: Minority Interests & Joint Ventures - Net - Cash Flow | B50: 0.5 | C50: 0.3 | D50: 0.5 | E50: 0.6 | F50: 0 | G50: -7.5 | H50: 0
A51: Debt - Long-Term & Short-Term - Issuance/(Retirement) - Total - Cash Flow | B51: -223.9 | C51: 1744 | D51: -914.7 | E51: -230.9 | F51: -226.1 | G51: -609.5 | H51: -148.8 | I51: 942.4 | J51: -474.2 | K51: 23.6
A52: Debt - Issued/(Reduced) - Long-Term - Cash Flow | B52: -223.9 | C52: 1744 | D52: -914.7 | E52: -230.9 | F52: -226.1 | G52: -609.5 | H52: -148.8 | I52: 942.4 | J52: -474.2 | K52: 23.6
A53: Lease liabilities - Issued/(Reduced) - Cash Flow | K53: -147.3
A54: Debt - Issued - Long-Term - Cash Flow | B54: 911 | C54: 4362.5 | D54: 2425.3 | E54: 1811.7 | F54: 2940.1 | G54: 3650.5 | H54: 623.9 | I54: 2699.7 | J54: 1147.5 | K54: 1016.6
A55: Debt - Reduced - Long-Term - Cash Flow | B55: 1134.9 | C55: 2618.5 | D55: 3340 | E55: 2042.6 | F55: 3166.2 | G55: 4260 | H55: 772.7 | I55: 1757.3 | J55: 1621.7 | K55: 993
A56: Lease liabilities - Reduced - Cash flow | K56: 147.3
A57: Other Financing Cash Flow - Increase/(Decrease) | B57: -2.9 | C57: -7.6 | D57: 3 | E57: -6.1 | F57: -4.2 | G57: -12.8 | H57: -4 | I57: 0.1 | J57: 2.7 | K57: -63.9
A58: Net Cash Flow from Financing Activities | B58: -280.2 | C58: 2117.8 | D58: -401.5 | E58: -355.1 | F58: -371 | G58: 179.1 | H58: -206.5 | I58: 745.8 | J58: -496.4 | K58: -132.1
A59: Non classified Cash Flow
A60: Non-Classified Cash Flows | I60: -14.1 | J60: 5.2
A61: Foreign Exchange Effects
A62: Foreign Exchange Effects - Cash Flow | B62: 0.5 | C62: 0.2 | D62: -12.2 | E62: -3.2 | F62: 2.4 | G62: -13.1 | H62: 10.8 | I62: 2.1 | J62: -5 | K62: -2.1
A63: Change in Cash
A64: Net Change in Cash - Total | B64: 4.1 | C64: 176.5 | D64: -106.4 | E64: 2.2 | F64: 35.9 | G64: 103.3 | H64: 168.5 | I64: -164.8 | J64: -6.3 | K64: 475.2
A65: Net Cash from Continuing Operations | B65: 4.1 | C65: 176.5 | D65: -106.4 | E65: 2.2 | F65: 35.9 | G65: 103.3 | H65: 168.5 | I65: -150.7 | J65: -11.5 | K65: 475.2
A66: Net Cash - Beginning Balance | B66: 98.9 | C66: 103.1 | D66: 279.6 | E66: 173.2 | F66: 175.3 | G66: 211.2 | H66: 314.4 | I66: 483 | J66: 318.1 | K66: 311.8
A67: Net Cash - Ending Balance | B67: 103.1 | C67: 279.6 | D67: 173.2 | E67: 175.3 | F67: 211.2 | G67: 314.4 | H67: 483 | I67: 318.1 | J67: 311.8 | K67: 787
A68: Supplemental
A69: Income Taxes - Paid/(Reimbursed) - Cash Flow - Supplemental | B69: 84.8 | C69: 108.7 | D69: 136.3 | E69: 193.2 | F69: 191.6 | G69: 216.8 | H69: 201.4 | I69: 160 | J69: 180 | K69: 302.9
A70: Interest Paid - Cash Flow - Supplemental | B70: 56 | C70: 99.5 | D70: 174.5 | E70: 161.9 | F70: 167 | G70: 185.1 | H70: 182.2 | I70: 187.5 | J70: 295.9 | K70: 103.9
A71: Interest on Financial Leases Paid - Cash Flow - Supplemental | D71: 109 | E71: 114 | F71: 126.5 | G71: 133.3 | H71: 145.1 | I71: 151.7 | J71: 218.8 | K71: 27.8
A72: Interest & Dividends - Received - Cash Flow - Supplemental | B72: 25.3 | C72: 17.6 | D72: 16.8 | E72: 16.7 | F72: 15.3 | G72: 7.1 | H72: 10.8 | I72: 15 | J72: 19.6 | K72: 22.9
A73: CF from Optg Activities before Change in WC & Int Payments | B73: 750.9 | C73: 824.4 | D73: 1078.4 | E73: 1116.1 | F73: 1227.3 | G73: 956.2 | H73: 1363.2 | I73: 927.6 | J73: 1386.4 | K73: 1394.2
A74: Non-GAAP Free Cash Flow - Company Reported | E74: 519.9 | F74: 568.4 | G74: 120.9 | H74: 543.8 | I74: -715.6 | J74: 715.2 | K74: 702
A75: Contract Assets/Liabilities – Net – Cash Flow | H75: -68.2 | I75: -50.3 | J75: 81.4 | K75: 115
A76: Cash Dividends Paid & Common Stock Buyback - Net | B76: 53.9 | C76: -381.1 | D76: -509.7 | E76: 118.7 | F76: 140.7 | G76: -808.9 | H76: 53.7
A77: Common Stock Buyback - Net | B77: -0.4 | C77: -457.1 | D77: -596.6 | E77: 1.9 | F77: -0.8 | G77: -813.6 | H77: 0
A78: Free Cash Flow to Equity | B78: 71.9 | C78: 1916.1 | D78: -574.8 | E78: 136 | F78: 184.7 | G78: -538.4 | H78: 244.4 | I78: 48.8 | J78: 26.8 | K78: 659.5
A79: Free Cash Flow Net of Dividends | B79: 227.4 | C79: 89.7 | D79: 249 | E79: 245 | F79: 265.7 | G79: 60.7 | H79: 322.7 | I79: -1097.8 | J79: 460.9 | K79: 534.9
A80: Free Cash Flow | B80: 281.7 | C80: 165.7 | D80: 335.9 | E80: 361.8 | F80: 407.2 | G80: 65.4 | H80: 376.4 | I80: -901.1 | J80: 485.8 | K80: 626.7
A81: Dividends Provided/Paid - Common | B81: 76 | C81: 86.9 | D81: 116.7 | E81: 141.5 | F81: 153.4 | G81: 53.7 | H81: 196.7 | I81: 24.9 | J81: 91.8 | K81: 107.5

Sheet Peer Group>>>

Sheet Honeywell_International
B2: Company Data Inputs
B4: FactSet Inputs | E4: Reporting Information
B5: Name | C5: Honeywell International | E5: Last FY | F5: 2024 | H5: Last Quarter | I5: 3
B6: Identifier | C6: HON-US | E6: Ended | F6: 12/31/2024 | H6: Ended | I6: 09/30/2025 | V6: HON-US | W6: Honeywell_International
B7: Start Date | C7: -5 | V7: 6383-JP | W7: Daifuku
B8: End Date | C8: 0 | E8: €/Shr | F8: 163.55975 | V8: JUN3-DE | W8: Jungheinrich
B9: Report Basis | C9: ANN_R | V9: HY-US | W9: Hyster-Yale
B10: Currency | C10: EUR | V10: 7105-JP | W10: Mitsubishi Logisnext
B11: Share Date | C11: 45992 | V11: 6201-JP | W11: Toyota Industries
V12: SYM-US | W12: Symbotic
B13: Key Financial Items and Forecast | V13: 688455-CN | W13: KENGIC
B14: All values in € (FactSet currency adjusted) million except for shares outstanding in millions. | V14: MTU-FR | W14: Manitou BF
E15: 2019 | F15: 2020 | G15: 2021 | H15: 2022 | I15: 2023 | J15: 2024 | L15: LTM/Cur. Q
B16: Revenue | E16: 32795.215 | F16: 28632.221 | G16: 29092.686 | H16: 33733.46 | I16: 33897.392 | J16: 35588.73 | L16: 36839.905
B17: COGS | E17: 20167.994 | F17: 17970.578 | G17: 18286.251 | H17: 20779.766 | I17: 20675.864 | J17: 21945.274 | L17: 22816.266
B18: EBITDA | E18: 7518.4366 | F18: 6396.6346 | G18: 6741.2254 | H18: 8028.7404 | I18: 8370.0576 | J18: 8508.9015 | L18: 8893.1717
B19: D&A | E19: 972.08069 | F19: 878.96707 | G19: 1034.7037 | H19: 1145.6036 | I19: 1087.7652 | J19: 1233.2545 | L19: 1405.8059
B20: EBIT | E20: 6546.3559 | F20: 5517.6675 | G20: 5706.5218 | H20: 6883.1368 | I20: 7282.2923 | J20: 7275.647 | L20: 7487.3658
B21: Interest | E21: 381.50593 | F21: 314.91934 | G21: 290.1908 | H21: 393.92019 | I21: 707.60239 | J21: 978.09841 | L21: 1142.2173
B22: Taxes | E22: 1187.4037 | F22: 1006.1629 | G22: 1374.8107 | H22: 1343.5152 | I22: 1375.4311 | J22: 1361.7571 | L22: 1210.1525
B23: Net Income | E23: 5488.5034 | F23: 4192.1992 | G23: 4688.7389 | H23: 4725.1392 | I23: 5233.4828 | J23: 5274.1507 | L23: 5551.6653
B25: Free Cash Flow | E25: 5412.5596 | F25: 4650.9814 | G25: 4351.17 | H25: 4289.3531 | I25: 3978.2979 | J25: 4560.4532 | L25: 1864.7075
B27: Cash and ST Investments | E27: 9279.2874 | F27: 12439.214 | G27: 10132.782 | H27: 9472.9444 | I27: 7328.1132 | J27: 10577.498 | L27: 11369.362
B28: Inventory | E28: 3938.5301 | F28: 3668.8325 | G28: 4518.1147 | H28: 5189.0372 | I28: 5592.7219 | J28: 6221.149 | L28: 6057.8725
B29: Current Assets | E29: 21650.78 | F29: 23027.257 | G29: 22310.939 | H29: 23407.824 | I29: 21275.518 | J29: 26951.231 | L29: 26167.66
... B34: Total Common Stock FD | E34: 711.1 | F34: 696.8 | G34: 684.8 | H34: 668.14025 | I34: 652.18181 | J34: 649.8 | L34: 634.88721
B38: Source: FactSet Standardized Financials
B50: Financial Ratios
B52: Year Ended | E52: 2019 | F52: 2020 | G52: 2021 | H52: 2022 | I52: 2023 | J52: 2024 | K52: LTM/Cur. Q
B54: Profitability Ratios
B55: Gross Profit Margin | E55: =IFERROR((E16-E17)/E16,"-") -> 0.38503242 | F55: =IFERROR((F16-F17)/F16,"-") -> 0.3723652 | G55: =IFERROR((G16-G17)/G16,"-") -> 0.37144851 | H55: =IFERROR((H16-H17)/H16,"-") -> 0.38400135 | I55: =IFERROR((I16-I17)/I16,"-") -> 0.39004557 | J55: =IFERROR((J16-J17)/J16,"-") -> 0.38336451 | K55: =IFERROR((L16-L17)/L16,"-") -> 0.38066436
B56: EBITDA Margin | E56: =IFERROR(E18/E16,"-") -> 0.22925407 | F56: =IFERROR(F18/F16,"-") -> 0.22340686 | G56: =IFERROR(G18/G16,"-") -> 0.23171547 | H56: =IFERROR(H18/H16,"-") -> 0.23800525 | I56: =IFERROR(I18/I16,"-") -> 0.24692335 | J56: =IFERROR(J18/J16,"-") -> 0.23908978 | K56: =IFERROR(L18/L16,"-") -> 0.24140051
B57: EBIT Margin (Operating Margin) | E57: =IFERROR(E20/E16,"-") -> 0.19961314 | F57: =IFERROR(F20/F16,"-") -> 0.19270833 | G57: =IFERROR(G20/G16,"-") -> 0.19614971 | H57: =IFERROR(H20/H16,"-") -> 0.20404479 | I57: =IFERROR(I20/I16,"-") -> 0.21483341 | J57: =IFERROR(J20/J16,"-") -> 0.20443682 | K57: =IFERROR(L20/L16,"-") -> 0.20324064
B58: Profit Margin | E58: =IFERROR(E23/E16,"-") -> 0.16735684 | F58: =IFERROR(F23/F16,"-") -> 0.14641544 | G58: =IFERROR(G23/G16,"-") -> 0.16116556 | H58: =IFERROR(H23/H16,"-") -> 0.14007277 | I58: =IFERROR(I23/I16,"-") -> 0.1543919 | J58: =IFERROR(J23/J16,"-") -> 0.14819722 | K58: =IFERROR(L23/L16,"-") -> 0.15069706
B60: Liquidity Ratios
B61: Current Ratio | E61: =IFERROR(E29/E30,"-") -> 1.3428556 | F61: =IFERROR(F29/F30,"-") -> 1.4676772 | G61: =IFERROR(G29/G30,"-") -> 1.3005946 | H61: =IFERROR(H29/H30,"-") -> 1.2529843 | I61: =IFERROR(I29/I30,"-") -> 1.2677059 | J61: =IFERROR(J29/J30,"-") -> 1.3129469 | K61: =IFERROR(L29/L30,"-") -> 1.358143
B62: Quick Ratio | E62: =IFERROR((E29-E28)/E30,"-") -> 1.0985744 | F62: =IFERROR((F29-F28)/F30,"-") -> 1.2338386 | G62: =IFERROR((G29-G28)/G30,"-") -> 1.0372155 | H62: =IFERROR((H29-H28)/H30,"-") -> 0.97522319 | I62: =IFERROR((I29-I28)/I30,"-") -> 0.93446248 | J62: =IFERROR((J29-J28)/J30,"-") -> 1.0098796 | K62: =IFERROR((L29-L28)/L30,"-") -> 1.0437298
B63: Cash Ratio | E63: =IFERROR(E27/E30,"-") -> 0.57553321 | F63: =IFERROR(F27/F30,"-") -> 0.79283221 | G63: =IFERROR(G27/G30,"-") -> 0.59068075 | H63: =IFERROR(H27/H30,"-") -> 0.50707192 | I63: =IFERROR(I27/I30,"-") -> 0.43664707 | J63: =IFERROR(J27/J30,"-") -> 0.5152898 | K63: =IFERROR(L27/L30,"-") -> 0.5900879
B65: Solvency & Leverage Ratios
B66: Debt to Equity | E66: =IFERROR(E31/E32,"-") -> 0.90337407 | F66: =IFERROR(F31/F32,"-") -> 1.3226964 | G66: =IFERROR(G31/G32,"-") -> 1.1110453 | H66: =IFERROR(H31/H32,"-") -> 1.2299814 | I66: =IFERROR(I31/I32,"-") -> 1.358224 | J66: =IFERROR(J31/J32,"-") -> 1.7307589 | K66: =IFERROR(L31/L32,"-") -> 2.2771422
B67: Net Debt | E67: =IFERROR(E31-E27,"-") -> 5604.4544 | F67: =IFERROR(F31-F27,"-") -> 6531.8132 | G67: =IFERROR(G31-G27,"-") -> 8009.1454 | H67: =IFERROR(H31-H27,"-") -> 9769.9695 | I67: =IFERROR(I31-I27,"-") -> 12167.655 | J67: =IFERROR(J31-J27,"-") -> 20542.732 | K67: =IFERROR(L31-L27,"-") -> 21154.043
B68: Net Leverage Ratio | E68: =IFERROR(E67/E18,"-") -> 0.74542816 | F68: =IFERROR(F67/F18,"-") -> 1.0211328 | G68: =IFERROR(G67/G18,"-") -> 1.1880845 | H68: =IFERROR(H67/H18,"-") -> 1.2168745 | I68: =IFERROR(I67/I18,"-") -> 1.4537123 | J68: =IFERROR(J67/J18,"-") -> 2.4142637 | K68: =IFERROR(K67/L18,"-") -> 2.3786837
B70: Coverage Ratios
B71: Interest Coverage Ratio | E71: =IFERROR(E20/E21,"-") -> 17.159251 | F71: =IFERROR(F20/F21,"-") -> 17.520891 | G71: =IFERROR(G20/G21,"-") -> 19.664723 | H71: =IFERROR(H20/H21,"-") -> 17.47343 | I71: =IFERROR(I20/I21,"-") -> 10.291503 | J71: =IFERROR(J20/J21,"-") -> 7.4385633 | K71: =IFERROR(L20/L21,"-") -> 6.555115

Sheet Daifuku
B2: Company Data Inputs
B4: FactSet Inputs | E4: Reporting Information
B5: Name | C5: Daifuku | E5: Last FY | F5: 2024 | H5: Last Quarter | I5: 3
B6: Identifier | C6: 6383-JP | E6: Ended | F6: 12/31/2024 | H6: Ended | I6: 09/30/2025 | V6: HON-US | W6: Honeywell_International
B7: Start Date | C7: -5 | V7: 6383-JP | W7: Daifuku
B8: End Date | C8: 0 | E8: €/Shr | F8: 27.697777 | V8: JUN3-DE | W8: Jungheinrich
B9: Report Basis | C9: ANN_R | V9: HY-US | W9: Hyster-Yale
B10: Currency | C10: EUR | V10: 7105-JP | W10: Mitsubishi Logisnext
B11: Share Date | C11: 45992 | V11: 6201-JP | W11: Toyota Industries
V12: SYM-US | W12: Symbotic
B13: Key Financial Items and Forecast | V13: 688455-CN | W13: KENGIC
B14: All values in € (FactSet currency adjusted) million except for shares outstanding in millions. | V14: MTU-FR | W14: Manitou BF
E15: 2019 | F15: 2020 | G15: 2021 | H15: 2022 | I15: 2023 | J15: 2024 | L15: LTM/Cur. Q
B16: Revenue | E16: 3673.1069 | F16: 3834.6266 | G16: 3925.1521 | H16: 4270.9807 | I16: #N/A | J16: 3437.0283 | L16: 3476.493
B17: COGS | E17: 2932.8628 | F17: 3092.9341 | G17: 3170.0016 | H17: 3468.7766 | I17: #N/A | J17: 2658.1334 | L17: 2642.4135
B18: EBITDA | E18: 389.0218 | F18: 418.03646 | G18: 446.09155 | H18: 483.12328 | I18: #N/A | J18: 489.86203 | L18: 551.13052
B19: D&A | E19: 53.760375 | F19: 57.418011 | G19: 61.030234 | H19: 65.513413 | I19: #N/A | J19: 53.255424 | L19: 43.336769
B20: EBIT | E20: 335.26142 | F20: 360.61845 | G20: 385.06132 | H20: 417.60987 | I20: #N/A | J20: 436.60661 | L20: 507.79375
B21: Interest | E21: 6.2750792 | F21: 5.210992 | G21: 2.6971303 | H21: 2.2705829 | I21: #N/A | J21: 1.0435061 | L21: #N/A
B22: Taxes | E22: 92.0069 | F22: 99.737092 | G22: 111.3639 | H22: 97.897601 | I22: #N/A | J22: 105.70534 | L22: 151.17774
B23: Net Income | E23: 232.31866 | F23: 262.087 | G23: 274.90807 | H23: 292.67814 | I23: #N/A | J23: 348.36627 | L23: 411.84807
B25: Free Cash Flow | E25: 7.37612 | F25: 248.80059 | G25: 354.22822 | H25: 44.82982 | I25: #N/A | J25: 636.15426 | L25: -82.49386
B27: Cash and ST Investments | E27: 598.60558 | F27: 725.083 | G27: 879.45837 | H27: 710.57474 | I27: #N/A | J27: 1361.2026 | L27: 1312.4023
B28: Inventory | E28: 281.47725 | F28: 279.89388 | G28: 305.46941 | H28: 456.83263 | I28: #N/A | J28: 386.77839 | L28: 338.3164
B29: Current Assets | E29: 2698.803 | F29: 2699.64 | G29: 2823.5168 | H29: 2995.5539 | I29: #N/A | J29: 3266.4782 | L29: 3129.4786
B30: Current Liabilities | E30: 1170.8802 | F30: 1148.666 | G30: 1285.8031 | H30: 1402.6427 | I30: #N/A | J30: 1316.4869 | L30: 1205.9192
B31: Total Debt | E31: 314.5366 | F31: 304.93418 | G31: 226.17162 | H31: 122.2167 | I31: #N/A | J31: 425.32473 | L31: 358.59533
B32: Total Shareholders Equity | E32: 1966.6937 | F32: 1979.3541 | G32: 2153.088 | H32: 2296.2243 | I32: #N/A | J32: 2446.2087 | L32: 2429.138
B34: Total Common Stock FD | E34: 377.71919 | F34: 378.01841 | G34: 378.052 | H34: 378.05653 | I34: #N/A | J34: 367.68462 | L34: 367.70049
B38: Source: FactSet Standardized Financials
B50: Financial Ratios
B52: Year Ended | E52: 2019 | F52: 2020 | G52: 2021 | H52: 2022 | I52: 2023 | J52: 2024 | K52: LTM/Cur. Q
B54: Profitability Ratios
B55: Gross Profit Margin | E55: =IFERROR((E16-E17)/E16,"-") -> 0.20153078 | F55: =IFERROR((F16-F17)/F16,"-") -> 0.19341974 | G55: =IFERROR((G16-G17)/G16,"-") -> 0.19238758 | H55: =IFERROR((H16-H17)/H16,"-") -> 0.18782666 | I55: =IFERROR((I16-I17)/I16,"-") -> - | J55: =IFERROR((J16-J17)/J16,"-") -> 0.22661871 | K55: =IFERROR((L16-L17)/L16,"-") -> 0.2399198
B56: EBITDA Margin | E56: =IFERROR(E18/E16,"-") -> 0.10591083 | F56: =IFERROR(F18/F16,"-") -> 0.10901621 | G56: =IFERROR(G18/G16,"-") -> 0.1136495 | H56: =IFERROR(H18/H16,"-") -> 0.11311765 | I56: =IFERROR(I18/I16,"-") -> - | J56: =IFERROR(J18/J16,"-") -> 0.14252487 | K56: =IFERROR(L18/L16,"-") -> 0.1585306
B57: EBIT Margin (Operating Margin) | E57: =IFERROR(E20/E16,"-") -> 0.091274617 | F57: =IFERROR(F20/F16,"-") -> 0.094042651 | G57: =IFERROR(G20/G16,"-") -> 0.098100994 | H57: =IFERROR(H20/H16,"-") -> 0.09777845 | I57: =IFERROR(I20/I16,"-") -> - | J57: =IFERROR(J20/J16,"-") -> 0.12703026 | K57: =IFERROR(L20/L16,"-") -> 0.14606494
B58: Profit Margin | E58: =IFERROR(E23/E16,"-") -> 0.063248545 | F58: =IFERROR(F23/F16,"-") -> 0.068347464 | G58: =IFERROR(G23/G16,"-") -> 0.070037558 | H58: =IFERROR(H23/H16,"-") -> 0.068527151 | I58: =IFERROR(I23/I16,"-") -> - | J58: =IFERROR(J23/J16,"-") -> 0.10135682 | K58: =IFERROR(L23/L16,"-") -> 0.11846653
B60: Liquidity Ratios
B61: Current Ratio | E61: =IFERROR(E29/E30,"-") -> 2.3049353 | F61: =IFERROR(F29/F30,"-") -> 2.3502393 | G61: =IFERROR(G29/G30,"-") -> 2.195917 | H61: =IFERROR(H29/H30,"-") -> 2.13565 | I61: =IFERROR(I29/I30,"-") -> - | J61: =IFERROR(J29/J30,"-") -> 2.4812083 | K61: =IFERROR(L29/L30,"-") -> 2.595098
B62: Quick Ratio | E62: =IFERROR((E29-E28)/E30,"-") -> 2.0645373 | F62: =IFERROR((F29-F28)/F30,"-") -> 2.1065707 | G62: =IFERROR((G29-G28)/G30,"-") -> 1.9583461 | H62: =IFERROR((H29-H28)/H30,"-") -> 1.8099558 | I62: =IFERROR((I29-I28)/I30,"-") -> - | J62: =IFERROR((J29-J28)/J30,"-") -> 2.1874125 | K62: =IFERROR((L29-L28)/L30,"-") -> 2.3145515
B63: Cash Ratio | E63: =IFERROR(E27/E30,"-") -> 0.5112441 | F63: =IFERROR(F27/F30,"-") -> 0.63123919 | G63: =IFERROR(G27/G30,"-") -> 0.68397593 | H63: =IFERROR(H27/H30,"-") -> 0.50659711 | I63: =IFERROR(I27/I30,"-") -> - | J63: =IFERROR(J27/J30,"-") -> 1.0339659 | K63: =IFERROR(L27/L30,"-") -> 1.0883004
B65: Solvency & Leverage Ratios
B66: Debt to Equity | E66: =IFERROR(E31/E32,"-") -> 0.15993166 | F66: =IFERROR(F31/F32,"-") -> 0.15405742 | G66: =IFERROR(G31/G32,"-") -> 0.10504522 | H66: =IFERROR(H31/H32,"-") -> 0.053225068 | I66: =IFERROR(I31/I32,"-") -> - | J66: =IFERROR(J31/J32,"-") -> 0.173871 | K66: =IFERROR(L31/L32,"-") -> 0.14762246
B67: Net Debt | E67: =IFERROR(E31-E27,"-") -> -284.06898 | F67: =IFERROR(F31-F27,"-") -> -420.14882 | G67: =IFERROR(G31-G27,"-") -> -653.28676 | H67: =IFERROR(H31-H27,"-") -> -588.35804 | I67: =IFERROR(I31-I27,"-") -> - | J67: =IFERROR(J31-J27,"-") -> -935.87787 | K67: =IFERROR(L31-L27,"-") -> -953.80699
B68: Net Leverage Ratio | E68: =IFERROR(E67/E18,"-") -> -0.73021352 | F68: =IFERROR(F67/F18,"-") -> -1.0050531 | G68: =IFERROR(G67/G18,"-") -> -1.4644679 | H68: =IFERROR(H67/H18,"-") -> -1.2178218 | I68: =IFERROR(I67/I18,"-") -> - | J68: =IFERROR(J67/J18,"-") -> -1.9104928 | K68: =IFERROR(K67/L18,"-") -> -1.7306372
B70: Coverage Ratios
B71: Interest Coverage Ratio | E71: =IFERROR(E20/E21,"-") -> 53.42744 | F71: =IFERROR(F20/F21,"-") -> 69.203417 | G71: =IFERROR(G20/G21,"-") -> 142.76705 | H71: =IFERROR(H20/H21,"-") -> 183.92188 | I71: =IFERROR(I20/I21,"-") -> - | J71: =IFERROR(J20/J21,"-") -> 418.40351 | K71: =IFERROR(L20/L21,"-") -> -

Sheet Hyster_Yale
B2: Company Data Inputs
B4: FactSet Inputs | E4: Reporting Information
B5: Name | C5: Hyster-Yale | E5: Last FY | F5: 2024 | H5: Last Quarter | I5: 3
B6: Identifier | C6: HY-US | E6: Ended | F6: 12/31/2024 | H6: Ended | I6: 09/30/2025 | V6: HON-US | W6: Honeywell_International
B7: Start Date | C7: -5 | V7: 6383-JP | W7: Daifuku
B8: End Date | C8: 0 | E8: €/Shr | F8: 24.60877 | V8: JUN3-DE | W8: Jungheinrich
B9: Report Basis | C9: ANN_R | V9: HY-US | W9: Hyster-Yale
B10: Currency | C10: EUR | V10: 7105-JP | W10: Mitsubishi Logisnext
B11: Share Date | C11: 45992 | V11: 6201-JP | W11: Toyota Industries
V12: SYM-US | W12: Symbotic
B13: Key Financial Items and Forecast | V13: 688455-CN | W13: KENGIC
B14: All values in € (FactSet currency adjusted) million except for shares outstanding in millions. | V14: MTU-FR | W14: Manitou BF
E15: 2019 | F15: 2020 | G15: 2021 | H15: 2022 | I15: 2023 | J15: 2024 | L15: LTM/Cur. Q
B16: Revenue | E16: 2941.0802 | F16: 2466.8097 | G16: 2602.157 | H16: 3376.2005 | I16: 3809.3058 | J16: 3982.8389 | L16: 3544.9498
B17: COGS | E17: 2435.9199 | F17: 2047.1511 | G17: 2291.0691 | H17: 2899.4048 | I17: 3044.1702 | J17: 3115.4006 | L17: 2839.3294
B18: EBITDA | E18: 108.28693 | F18: 96.66883 | G18: -26.9886 | H18: 70.98175 | I18: 274.99372 | J18: 331.42559 | L18: 183.96855
B19: D&A | E19: 38.686667 | F19: 37.632422 | G19: 39.086925 | H19: 41.295015 | I19: 41.716167 | J19: 44.005184 | L19: 41.576348
B20: EBIT | E20: 69.60026 | F20: 59.03641 | G20: -66.07552 | H20: 29.68674 | I20: 233.27755 | J20: 287.42041 | L20: 142.3922
B21: Interest | E21: 17.422402 | F21: 13.684517 | G21: 15.820898 | H21: 28.164342 | I21: 40.328712 | J21: 5.8242155 | L21: 27.536405
B22: Taxes | E22: 10.096059 | F22: 3.2456868 | G22: 23.942856 | H22: 8.7537819 | I22: 48.930937 | J22: 69.151003 | L22: 16.938512
B23: Net Income | E23: 31.985743 | F23: 32.544589 | G23: -146.36446 | H23: -70.506004 | I23: 116.45378 | J23: 131.55331 | L23: 2.4456675
B25: Free Cash Flow | E25: 24.12333 | F25: 101.0549 | G25: -251.94992 | H25: 11.22768 | I25: 106.64909 | J25: 113.61843 | L25: 13.94894
B27: Cash and ST Investments | E27: 57.550112 | F27: 123.7383 | G27: 57.597609 | H27: 55.282267 | I27: 71.334814 | J27: 93.288264 | L27: 60.51064
B28: Inventory | E28: 498.79733 | F28: 416.32953 | G28: 686.77454 | H28: 749.12157 | I28: 738.42396 | J28: 728.44035 | L28: 630.04257
B29: Current Assets | E29: 1029.6659 | F29: 923.29697 | G29: 1187.1263 | H29: 1366.7838 | I29: 1348.9341 | J29: 1384.1622 | L29: 1228.766
... B34: Total Common Stock FD | E34: 16.666917 | F34: 16.805437 | G34: 16.8269 | H34: 16.938515 | I34: 17.18563 | J34: 17.41897 | L34: 17.720627
B38: Source: FactSet Standardized Financials
B50: Financial Ratios
B52: Year Ended | E52: 2019 | F52: 2020 | G52: 2021 | H52: 2022 | I52: 2023 | J52: 2024 | K52: LTM/Cur. Q
B54: Profitability Ratios
B55: Gross Profit Margin | E55: =IFERROR((E16-E17)/E16,"-") -> 0.17176013 | F55: =IFERROR((F16-F17)/F16,"-") -> 0.17012197 | G55: =IFERROR((G16-G17)/G16,"-") -> 0.11955002 | H55: =IFERROR((H16-H17)/H16,"-") -> 0.14122256 | I55: =IFERROR((I16-I17)/I16,"-") -> 0.20085958 | J55: =IFERROR((J16-J17)/J16,"-") -> 0.21779397 | K55: =IFERROR((L16-L17)/L16,"-") -> 0.19904947
B56: EBITDA Margin | E56: =IFERROR(E18/E16,"-") -> 0.036818762 | F56: =IFERROR(F18/F16,"-") -> 0.039187794 | G56: =IFERROR(G18/G16,"-") -> -0.010371626 | H56: =IFERROR(H18/H16,"-") -> 0.021024151 | I56: =IFERROR(I18/I16,"-") -> 0.072189983 | J56: =IFERROR(J18/J16,"-") -> 0.083213405 | K56: =IFERROR(L18/L16,"-") -> 0.051895954
B57: EBIT Margin (Operating Margin) | E57: =IFERROR(E20/E16,"-") -> 0.023664863 | F57: =IFERROR(F20/F16,"-") -> 0.023932292 | G57: =IFERROR(G20/G16,"-") -> -0.025392595 | H57: =IFERROR(H20/H16,"-") -> 0.0087929435 | I57: =IFERROR(I20/I16,"-") -> 0.061238861 | J57: =IFERROR(J20/J16,"-") -> 0.072164709 | K57: =IFERROR(L20/L16,"-") -> 0.040167621
B58: Profit Margin | E58: =IFERROR(E23/E16,"-") -> 0.010875509 | F58: =IFERROR(F23/F16,"-") -> 0.013192987 | G58: =IFERROR(G23/G16,"-") -> -0.056247358 | H58: =IFERROR(H23/H16,"-") -> -0.02088324 | I58: =IFERROR(I23/I16,"-") -> 0.030570867 | J58: =IFERROR(J23/J16,"-") -> 0.033030036 | K58: =IFERROR(L23/L16,"-") -> 0.00068990188
B60: Liquidity Ratios
B61: Current Ratio | E61: =IFERROR(E29/E30,"-") -> 1.4146879 | F61: =IFERROR(F29/F30,"-") -> 1.4945099 | G61: =IFERROR(G29/G30,"-") -> 1.2221619 | H61: =IFERROR(H29/H30,"-") -> 1.0862313 | I61: =IFERROR(I29/I30,"-") -> 1.2227967 | J61: =IFERROR(J29/J30,"-") -> 1.354854 | K61: =IFERROR(L29/L30,"-") -> 1.3922854
B62: Quick Ratio | E62: =IFERROR((E29-E28)/E30,"-") -> 0.72937576 | F62: =IFERROR((F29-F28)/F30,"-") -> 0.82061119 | G62: =IFERROR((G29-G28)/G30,"-") -> 0.51511859 | H62: =IFERROR((H29-H28)/H30,"-") -> 0.49087795 | I62: =IFERROR((I29-I28)/I30,"-") -> 0.55342196 | J62: =IFERROR((J29-J28)/J30,"-") -> 0.6418376 | K62: =IFERROR((L29-L28)/L30,"-") -> 0.67839923
B63: Cash Ratio | E63: =IFERROR(E27/E30,"-") -> 0.079069767 | F63: =IFERROR(F27/F30,"-") -> 0.20029104 | G63: =IFERROR(G27/G30,"-") -> 0.059297483 | H63: =IFERROR(H27/H30,"-") -> 0.043934768 | I63: =IFERROR(I27/I30,"-") -> 0.064664369 | J63: =IFERROR(J27/J30,"-") -> 0.091312979 | K63: =IFERROR(L27/L30,"-") -> 0.068563163
B65: Solvency & Leverage Ratios
B66: Debt to Equity | E66: =IFERROR(E31/E32,"-") -> 0.67481168 | F66: =IFERROR(F31/F32,"-") -> 0.59085751 | G66: =IFERROR(G31/G32,"-") -> 1.6558387 | H66: =IFERROR(H31/H32,"-") -> 3 | I66: =IFERROR(I31/I32,"-") -> 1.4667864 | J66: =IFERROR(J31/J32,"-") -> 1.1403915 | K66: =IFERROR(L31/L32,"-") -> 0.87276119
B67: Net Debt | E67: =IFERROR(E31-E27,"-") -> 269.66593 | F67: =IFERROR(F31-F27,"-") -> 174.16534 | G67: =IFERROR(G31-G27,"-") -> 462.36371 | H67: =IFERROR(H31-H27,"-") -> 519.27852 | I67: =IFERROR(I31-I27,"-") -> 446.38575 | J67: =IFERROR(J31-J27,"-") -> 429.93722 | K67: =IFERROR(L31-L27,"-") -> 337.61703
B68: Net Leverage Ratio | E68: =IFERROR(E67/E18,"-") -> 2.4902906 | F68: =IFERROR(F67/F18,"-") -> 1.8016701 | G68: =IFERROR(G67/G18,"-") -> -17.131815 | H68: =IFERROR(H67/H18,"-") -> 7.3156624 | I68: =IFERROR(I67/I18,"-") -> 1.623258 | J68: =IFERROR(J67/J18,"-") -> 1.297236 | K68: =IFERROR(K67/L18,"-") -> 1.8351888
B70: Coverage Ratios
B71: Interest Coverage Ratio | E71: =IFERROR(E20/E21,"-") -> 3.9948716 | F71: =IFERROR(F20/F21,"-") -> 4.3141025 | G71: =IFERROR(G20/G21,"-") -> -4.1764709 | H71: =IFERROR(H20/H21,"-") -> 1.0540541 | I71: =IFERROR(I20/I21,"-") -> 5.7844037 | J71: =IFERROR(J20/J21,"-") -> 49.349206 | K71: =IFERROR(L20/L21,"-") -> 5.1710527

Sheet Mitsubishi_Logisnext
B2: Company Data Inputs
B4: FactSet Inputs | E4: Reporting Information
B5: Name | C5: Mitsubishi_Logisnext | E5: Last FY | F5: 2024 | H5: Last Quarter | I5: 2
B6: Identifier | C6: 7105-JP | E6: Ended | F6: 03/31/2025 | H6: Ended | I6: 09/30/2025 | V6: HON-US | W6: Honeywell_International
B7: Start Date | C7: -5 | V7: 6383-JP | W7: Daifuku
B8: End Date | C8: 0 | E8: €/Shr | F8: 8.532202 | V8: JUN3-DE | W8: Jungheinrich
B9: Report Basis | C9: ANN_R | V9: HY-US | W9: Hyster-Yale
B10: Currency | C10: EUR | V10: 7105-JP | W10: Mitsubishi_Logisnext
B11: Share Date | C11: 45992 | V11: 6201-JP | W11: Toyota_Industries
V12: SYM-US | W12: Symbotic
B13: Key Financial Items and Forecast | V13: 688455-CN | W13: KENGIC
B14: All values in € (FactSet currency adjusted) million except for shares outstanding in millions. | V14: MTU-FR | W14: Manitou_BF
E15: 2019 | F15: 2020 | G15: 2021 | H15: 2022 | I15: 2023 | J15: 2024 | L15: LTM/Cur. Q
B16: Revenue | E16: 3716.3536 | F16: 3167.83 | G16: 3566.0813 | H16: 4366.7638 | I16: 4476.1176 | J16: 4066.8239 | L16: 3975.9375
B17: COGS | E17: 2871.0391 | F17: 2466.5955 | G17: 2814.2792 | H17: 3428.4241 | I17: 3372.5269 | J17: 3130.3462 | L17: 3055.5428
B18: EBITDA | E18: 326.99123 | F18: 260.89754 | G18: 264.95474 | H18: 342.57419 | I18: 509.1052 | J18: 379.20909 | L18: 330.29333
B19: D&A | E19: 257.14579 | F19: 247.99143 | G19: 237.42409 | H19: 238.20543 | I19: 237.36301 | J19: 252.32133 | L19: 249.16972
B20: EBIT | E20: 69.84544 | F20: 12.90611 | G20: 27.53065 | H20: 104.36876 | I20: 271.74219 | J20: 126.88776 | L20: 81.12361
B21: Interest | E21: 14.3797 | F21: 11.51435 | G21: 11.378518 | H21: 27.481149 | I21: 43.908394 | J21: 47.359129 | L21: 47.872648
B22: Taxes | E22: 45.167325 | F22: 13.6829 | G22: 15.991224 | H22: 38.117411 | I22: 57.896062 | J22: 44.352976 | L22: 23.420193
B23: Net Income | E23: -43.395733 | F23: -21.701678 | G23: 5.4938705 | H23: 49.051687 | I23: 175.53152 | J23: 52.943731 | L23: -12.24748
B25: Free Cash Flow | E25: 140.67602 | F25: 129.12579 | G25: -41.53734 | H25: -114.41609 | I25: 72.94253 | J25: 37.68689 | L25: #N/A
B27: Cash and ST Investments | E27: 129.45995 | F27: 115.49954 | G27: 93.018852 | H27: 91.60028 | I27: 123.37246 | J27: 102.7777 | L27: 110.3153
B28: Inventory | E28: 523.04858 | F28: 471.64621 | G28: 716.19777 | H28: 748.92306 | I28: 768.08932 | J28: 767.53931 | L28: 710.7422
B29: Current Assets | E29: 1634.0572 | F29: 1484.5002 | G29: 1759.2129 | H29: 1829.6611 | I29: 1779.4119 | J29: 1763.8429 | L29: 1628.2788
B30: Current Liabilities | E30: 1303.8436 | F30: 1146.8257 | G30: 1338.0735 | H30: 1443.3977 | I30: 1305.389 | J30: 1198.6336 | L30: 1085.9226
B31: Total Debt | E31: 1550.1847 | F31: 1406.7382 | G31: 1393.439 | H31: 1588.3675 | I31: 1474.2049 | J31: 1424.4078 | L31: 1332.7331
B32: Total Shareholders Equity | E32: 465.15251 | F32: 424.2991 | G32: 469.4927 | H32: 523.75719 | I32: 715.76339 | J32: 767.41549 | L32: 700.16189
B34: Total Common Stock FD | E34: 106.52891 | F34: 106.5728 | G34: 106.6378 | H34: 106.6978 | I34: 106.65774 | J34: 106.6644 | L34: 106.74125
B38: Source: FactSet Standardized Financials
B50: Financial Ratios
B52: Year Ended | E52: 2019 | F52: 2020 | G52: 2021 | H52: 2022 | I52: 2023 | J52: 2024 | K52: LTM/Cur. Q
B54: Profitability Ratios
B55: Gross Profit Margin | E55: =IFERROR((E16-E17)/E16,"-") -> 0.22745802 | F55: =IFERROR((F16-F17)/F16,"-") -> 0.22136114 | G55: =IFERROR((G16-G17)/G16,"-") -> 0.21082023 | H55: =IFERROR((H16-H17)/H16,"-") -> 0.21488217 | I55: =IFERROR((I16-I17)/I16,"-") -> 0.24655086 | J55: =IFERROR((J16-J17)/J16,"-") -> 0.23027251 | K55: =IFERROR((L16-L17)/L16,"-") -> 0.23149125
B56: EBITDA Margin | E56: =IFERROR(E18/E16,"-") -> 0.087987115 | F56: =IFERROR(F18/F16,"-") -> 0.082358441 | G56: =IFERROR(G18/G16,"-") -> 0.07429857 | H56: =IFERROR(H18/H16,"-") -> 0.07845036 | I56: =IFERROR(I18/I16,"-") -> 0.11373812 | J56: =IFERROR(J18/J16,"-") -> 0.093244531 | K56: =IFERROR(L18/L16,"-") -> 0.083073068
B57: EBIT Margin (Operating Margin) | E57: =IFERROR(E20/E16,"-") -> 0.018794078 | F57: =IFERROR(F20/F16,"-") -> 0.004074117 | G57: =IFERROR(G20/G16,"-") -> 0.0077201409 | H57: =IFERROR(H20/H16,"-") -> 0.023900711 | I57: =IFERROR(I20/I16,"-") -> 0.06070935 | J57: =IFERROR(J20/J16,"-") -> 0.031200702 | K57: =IFERROR(L20/L16,"-") -> 0.020403643
B58: Profit Margin | E58: =IFERROR(E23/E16,"-") -> -0.011676966 | F58: =IFERROR(F23/F16,"-") -> -0.0068506447 | G58: =IFERROR(G23/G16,"-") -> 0.0015405904 | H58: =IFERROR(H23/H16,"-") -> 0.011232961 | I58: =IFERROR(I23/I16,"-") -> 0.039215127 | J58: =IFERROR(J23/J16,"-") -> 0.013018447 | K58: =IFERROR(L23/L16,"-") -> -0.0030804004
B60: Liquidity Ratios
B61: Current Ratio | E61: =IFERROR(E29/E30,"-") -> 1.2532617 | F61: =IFERROR(F29/F30,"-") -> 1.2944427 | G61: =IFERROR(G29/G30,"-") -> 1.3147357 | H61: =IFERROR(H29/H30,"-") -> 1.2676071 | I61: =IFERROR(I29/I30,"-") -> 1.3631277 | J61: =IFERROR(J29/J30,"-") -> 1.4715446 | K61: =IFERROR(L29/L30,"-") -> 1.4994428
B62: Quick Ratio | E62: =IFERROR((E29-E28)/E30,"-") -> 0.85210269 | F62: =IFERROR((F29-F28)/F30,"-") -> 0.88318036 | G62: =IFERROR((G29-G28)/G30,"-") -> 0.77949022 | H62: =IFERROR((H29-H28)/H30,"-") -> 0.74874586 | I62: =IFERROR((I29-I28)/I30,"-") -> 0.77472888 | J62: =IFERROR((J29-J28)/J30,"-") -> 0.83119942 | K62: =IFERROR((L29-L28)/L30,"-") -> 0.84493738
B63: Cash Ratio | E63: =IFERROR(E27/E30,"-") -> 0.09929101 | F63: =IFERROR(F27/F30,"-") -> 0.10071237 | G63: =IFERROR(G27/G30,"-") -> 0.069517 | H63: =IFERROR(H27/H30,"-") -> 0.063461566 | I63: =IFERROR(I27/I30,"-") -> 0.094510109 | J63: =IFERROR(J27/J30,"-") -> 0.085745717 | K63: =IFERROR(L27/L30,"-") -> 0.10158671
B65: Solvency & Leverage Ratios
B66: Debt to Equity | E66: =IFERROR(E31/E32,"-") -> 3.3326376 | F66: =IFERROR(F31/F32,"-") -> 3.3154399 | G66: =IFERROR(G31/G32,"-") -> 2.9679673 | H66: =IFERROR(H31/H32,"-") -> 3.032641 | I66: =IFERROR(I31/I32,"-") -> 2.059626 | J66: =IFERROR(J31/J32,"-") -> 1.8561103 | K66: =IFERROR(L31/L32,"-") -> 1.9034642
B67: Net Debt | E67: =IFERROR(E31-E27,"-") -> 1420.7248 | F67: =IFERROR(F31-F27,"-") -> 1291.2386 | G67: =IFERROR(G31-G27,"-") -> 1300.4201 | H67: =IFERROR(H31-H27,"-") -> 1496.7673 | I67: =IFERROR(I31-I27,"-") -> 1350.8324 | J67: =IFERROR(J31-J27,"-") -> 1321.6301 | K67: =IFERROR(L31-L27,"-") -> 1222.4178
B68: Net Leverage Ratio | E68: =IFERROR(E67/E18,"-") -> 4.3448407 | F68: =IFERROR(F67/F18,"-") -> 4.9492174 | G68: =IFERROR(G67/G18,"-") -> 4.9080841 | H68: =IFERROR(H67/H18,"-") -> 4.3691769 | I68: =IFERROR(I67/I18,"-") -> 2.6533463 | J68: =IFERROR(J67/J18,"-") -> 3.4852279 | K68: =IFERROR(K67/L18,"-") -> 3.7010066
B70: Coverage Ratios
B71: Interest Coverage Ratio | E71: =IFERROR(E20/E21,"-") -> 4.8572251 | F71: =IFERROR(F20/F21,"-") -> 1.1208718 | G71: =IFERROR(G20/G21,"-") -> 2.4195286 | H71: =IFERROR(H20/H21,"-") -> 3.797831 | I71: =IFERROR(I20/I21,"-") -> 6.1888438 | J71: =IFERROR(J20/J21,"-") -> 2.6792672 | K71: =IFERROR(L20/L21,"-") -> 1.6945712

Sheet Toyota_Industries
B2: Company Data Inputs
B4: FactSet Inputs | E4: Reporting Information
B5: Name | C5: Toyota_Industries | E5: Last FY | F5: 2024 | H5: Last Quarter | I5: 2
B6: Identifier | C6: 6201-JP | E6: Ended | F6: 03/31/2025 | H6: Ended | I6: 09/30/2025 | V6: HON-US | W6: Honeywell_International
B7: Start Date | C7: -5 | V7: 6383-JP | W7: Daifuku
B8: End Date | C8: 0 | E8: €/Shr | F8: 96.21596 | V8: JUN3-DE | W8: Jungheinrich
B9: Report Basis | C9: ANN_R | V9: HY-US | W9: Hyster-Yale
B10: Currency | C10: EUR | V10: 7105-JP | W10: Mitsubishi_Logisnext
B11: Share Date | C11: 45992 | V11: 6201-JP | W11: Toyota_Industries
V12: SYM-US | W12: Symbotic
B13: Key Financial Items and Forecast | V13: 688455-CN | W13: KENGIC
B14: All values in € (FactSet currency adjusted) million except for shares outstanding in millions. | V14: MTU-FR | W14: Manitou_BF
E15: 2019 | F15: 2020 | G15: 2021 | H15: 2022 | I15: 2023 | J15: 2024 | L15: LTM/Cur. Q
B16: Revenue | E16: 17975.494 | F16: 17140.458 | G16: 20727.929 | H16: 23982.259 | I16: 24449.43 | J16: 24959.526 | L16: 25066.79
B17: COGS | E17: 13788.891 | F17: 13177.846 | G17: 16077.241 | H17: 18622.732 | I17: 18713.114 | J17: 19159.722 | L17: 19453.716
B18: EBITDA | E18: 2753.0958 | F18: 2629.0426 | G18: 2877.4166 | H18: 3027.5527 | I18: 3364.79 | J18: 3357.0114 | L18: 3134.4015
B19: D&A | E19: 1724.5044 | F19: 1697.9338 | G19: 1714.3404 | H19: 1828.9687 | I19: 1817.4337 | J19: 1979.9978 | L19: 2038.5223
B20: EBIT | E20: 1028.5914 | F20: 931.10879 | G20: 1163.0761 | H20: 1198.584 | I20: 1547.3563 | J20: 1377.0136 | L20: 1095.8792
B21: Interest | E21: 66.823799 | F21: 48.217859 | G21: 45.123296 | H21: 99.160613 | I21: 136.43876 | J21: 84.648868 | L21: #N/A
B22: Taxes | E22: 381.64568 | F22: 344.50807 | G22: 465.66107 | H22: 455.89048 | I22: 461.37618 | J22: 490.11903 | L22: 314.78513
B23: Net Income | E23: 1207.6796 | F23: 1106.1221 | G23: 1381.5667 | H23: 1368.459 | I23: 1459.2206 | J23: 1602.75 | L23: 1250.9067
B25: Free Cash Flow | E25: 804.64231 | F25: 1294.8668 | G25: 641.44194 | H25: -674.15026 | I25: 603.79782 | J25: -241.06658 | L25: 347.12879
B27: Cash and ST Investments | E27: 4502.6905 | F27: 4559.2442 | G27: 4263.369 | H27: 4307.9034 | I27: 4528.4717 | J27: 2898.4896 | L27: 2879.2796
B28: Inventory | E28: 2158.9715 | F28: 2251.9407 | G28: 3213.3859 | H28: 3626.5619 | I28: 3787.4477 | J28: 3837.0094 | L28: 3809.5805
B29: Current Assets | E29: 14688.305 | F29: 15000.164 | G29: 16703.904 | H29: 18513.866 | I29: 19145.985 | J29: 19249.467 | L29: 18193.485
B30: Current Liabilities | E30: 8225.2781 | F30: 9149.4037 | G30: 10164.698 | H30: 10492.102 | I30: 10028.353 | J30: 10043.044 | L30: 10521.244
B31: Total Debt | E31: 12324.57 | F31: 11311.378 | G31: 11279.354 | H31: 12725.648 | I31: 11540.219 | J31: 11903.412 | L31: 10172.9
B32: Total Shareholders Equity | E32: 20588.707 | F32: 24917.393 | G32: 29089.776 | H32: 26538.949 | I32: 36987.016 | J32: 30363.351 | L32: 30888.043
B34: Total Common Stock FD | E34: 310.48361 | F34: 310.48178 | G34: 310.47985 | H34: 310.47812 | I34: 310.47704 | J34: 301.40031 | L34: 300.47387
B38: Source: FactSet Standardized Financials
B50: Financial Ratios
B52: Year Ended | E52: 2019 | F52: 2020 | G52: 2021 | H52: 2022 | I52: 2023 | J52: 2024 | K52: LTM/Cur. Q
B54: Profitability Ratios
B55: Gross Profit Margin | E55: =IFERROR((E16-E17)/E16,"-") -> 0.23290618 | F55: =IFERROR((F16-F17)/F16,"-") -> 0.23118469 | G55: =IFERROR((G16-G17)/G16,"-") -> 0.22436819 | H55: =IFERROR((H16-H17)/H16,"-") -> 0.2234788 | I55: =IFERROR((I16-I17)/I16,"-") -> 0.23461959 | J55: =IFERROR((J16-J17)/J16,"-") -> 0.23236835 | K55: =IFERROR((L16-L17)/L16,"-") -> 0.22392472
B56: EBITDA Margin | E56: =IFERROR(E18/E16,"-") -> 0.15315828 | F56: =IFERROR(F18/F16,"-") -> 0.15338228 | G56: =IFERROR(G18/G16,"-") -> 0.13881834 | H56: =IFERROR(H18/H16,"-") -> 0.12624135 | I56: =IFERROR(I18/I16,"-") -> 0.13762243 | J56: =IFERROR(J18/J16,"-") -> 0.1344982 | K56: =IFERROR(L18/L16,"-") -> 0.125042
B57: EBIT Margin (Operating Margin) | E57: =IFERROR(E20/E16,"-") -> 0.057221873 | F57: =IFERROR(F20/F16,"-") -> 0.054322283 | G57: =IFERROR(G20/G16,"-") -> 0.056111546 | H57: =IFERROR(H20/H16,"-") -> 0.049977943 | I57: =IFERROR(I20/I16,"-") -> 0.063288032 | J57: =IFERROR(J20/J16,"-") -> 0.055169861 | K57: =IFERROR(L20/L16,"-") -> 0.043718371
B58: Profit Margin | E58: =IFERROR(E23/E16,"-") -> 0.067184776 | F58: =IFERROR(F23/F16,"-") -> 0.064532819 | G58: =IFERROR(G23/G16,"-") -> 0.066652422 | H58: =IFERROR(H23/H16,"-") -> 0.057061308 | I58: =IFERROR(I23/I16,"-") -> 0.059683215 | J58: =IFERROR(J23/J16,"-") -> 0.06421396 | K58: =IFERROR(L23/L16,"-") -> 0.049902947
B60: Liquidity Ratios
B61: Current Ratio | E61: =IFERROR(E29/E30,"-") -> 1.7857518 | F61: =IFERROR(F29/F30,"-") -> 1.639469 | G61: =IFERROR(G29/G30,"-") -> 1.6433252 | H61: =IFERROR(H29/H30,"-") -> 1.7645527 | I61: =IFERROR(I29/I30,"-") -> 1.9091854 | J61: =IFERROR(J29/J30,"-") -> 1.9166965 | K61: =IFERROR(L29/L30,"-") -> 1.7292143
