Workbook
Name estimate_start: model!$D$73
Name scenario_name: 'Scenario Manager'!$D$10
Name scenario_number: 'Scenario Manager'!$D$11

Sheet Financial Valuation
C2: Financial Output
C4: Live Scenario | D4: =scenario_number -> 2
C5: Scenario Name | D5: =scenario_name -> Street

Sheet Financial Output
C2: Financial Output
C4: Live Scenario | D4: =scenario_number -> 2
C5: Scenario Name | D5: =scenario_name -> Street
B8: 1 | C8: Income Statement | E8: Units
C10: Year Ended | G10: =H10-1 -> 2020 | H10: =I10-1 -> 2021 | I10: =J10-1 -> 2022 | J10: =K10-1 -> 2023 | K10: =L10-1 -> 2024 | L10: =estimate_start -> 2025 | M10: =+L10+1 -> 2026 | N10: =+M10+1 -> 2027 | O10: =+N10+1 -> 2028 | P10: =+O10+1 -> 2029
C12: Revenue | E12: (US$m) | G12: {=INDEX(model!$N3:$AZ3,,MATCH('Financial Output'!G$10,model!$N$2:$AZ$2,0))} -> 3532.157 | H12: {=INDEX(model!$N3:$AZ3,,MATCH('Financial Output'!H$10,model!$N$2:$AZ$2,0))} -> 3620.684 | I12: {=INDEX(model!$N3:$AZ3,,MATCH('Financial Output'!I$10,model!$N$2:$AZ$2,0))} -> 3632.661 | J12: {=INDEX(model!$N3:$AZ3,,MATCH('Financial Output'!J$10,model!$N$2:$AZ$2,0))} -> 4386.549 | K12: {=INDEX(model!$N3:$AZ3,,MATCH('Financial Output'!K$10,model!$N$2:$AZ$2,0))} -> 4014.955 | L12: {=INDEX(model!$N3:$AZ3,,MATCH('Financial Output'!L$10,model!$N$2:$AZ$2,0))} -> 4577.0487 | M12: {=INDEX(model!$N3:$AZ3,,MATCH('Financial Output'!M$10,model!$N$2:$AZ$2,0))} -> 5034.7536 | N12: {=INDEX(model!$N3:$AZ3,,MATCH('Financial Output'!N$10,model!$N$2:$AZ$2,0))} -> 5487.8814 | ... P12: {=INDEX(model!$N3:$AZ3,,MATCH('Financial Output'!P$10,model!$N$2:$AZ$2,0))} -> 6640.3365
C13: Cost of Goods Sold | E13: (US$m) | G13: {=INDEX(model!$N4:$AZ4,,MATCH('Financial Output'!G$10,model!$N$2:$AZ$2,0))} -> -1879.266 | H13: {=INDEX(model!$N4:$AZ4,,MATCH('Financial Output'!H$10,model!$N$2:$AZ$2,0))} -> -1898.705 | I13: {=INDEX(model!$N4:$AZ4,,MATCH('Financial Output'!I$10,model!$N$2:$AZ$2,0))} -> -2072.317 | J13: {=INDEX(model!$N4:$AZ4,,MATCH('Financial Output'!J$10,model!$N$2:$AZ$2,0))} -> -2507.698 | K13: {=INDEX(model!$N4:$AZ4,,MATCH('Financial Output'!K$10,model!$N$2:$AZ$2,0))} -> -2295.365 | L13: {=INDEX(model!$N4:$AZ4,,MATCH('Financial Output'!L$10,model!$N$2:$AZ$2,0))} -> -2654.6882 | M13: {=INDEX(model!$N4:$AZ4,,MATCH('Financial Output'!M$10,model!$N$2:$AZ$2,0))} -> -2819.462 | N13: {=INDEX(model!$N4:$AZ4,,MATCH('Financial Output'!N$10,model!$N$2:$AZ$2,0))} -> -3018.3348 | ... P13: {=INDEX(model!$N4:$AZ4,,MATCH('Financial Output'!P$10,model!$N$2:$AZ$2,0))} -> -3320.1682
C15: Gross Profit | E15: (US$m) | G15: =+G12+G13 -> 1652.891 | H15: =+H12+H13 -> 1721.979 | I15: =+I12+I13 -> 1560.344 | J15: =+J12+J13 -> 1878.851 | K15: =+K12+K13 -> 1719.59 | L15: =+L12+L13 -> 1922.3605 | M15: =+M12+M13 -> 2215.2916 | N15: =+N12+N13 -> 2469.5466 | ... P15: =+P12+P13 -> 3320.1682
C16: Gross Margin | E16: (%) | G16: =G15/G12 -> 0.46795513 | H16: =H15/H12 -> 0.47559494 | I16: =I15/I12 -> 0.42953196 | J16: =J15/J12 -> 0.42832099 | K16: =K15/K12 -> 0.42829621 | L16: =L15/L12 -> 0.42 | M16: =M15/M12 -> 0.44 | N16: =N15/N12 -> 0.45 | ... P16: =P15/P12 -> 0.5
C18: Sales and Marketing | E18: (US$m) | G18: {=INDEX(model!$N6:$AZ6,,MATCH('Financial Output'!G$10,model!$N$2:$AZ$2,0))} -> -416.425 | H18: {=INDEX(model!$N6:$AZ6,,MATCH('Financial Output'!H$10,model!$N$2:$AZ$2,0))} -> -452.214 | I18: {=INDEX(model!$N6:$AZ6,,MATCH('Financial Output'!I$10,model!$N$2:$AZ$2,0))} -> -466.565 | J18: {=INDEX(model!$N6:$AZ6,,MATCH('Financial Output'!J$10,model!$N$2:$AZ$2,0))} -> -490.804 | K18: {=INDEX(model!$N6:$AZ6,,MATCH('Financial Output'!K$10,model!$N$2:$AZ$2,0))} -> -510.668 | L18: {=INDEX(model!$N6:$AZ6,,MATCH('Financial Output'!L$10,model!$N$2:$AZ$2,0))} -> -543.33617 | M18: {=INDEX(model!$N6:$AZ6,,MATCH('Financial Output'!M$10,model!$N$2:$AZ$2,0))} -> -597.66979 | N18: {=INDEX(model!$N6:$AZ6,,MATCH('Financial Output'!N$10,model!$N$2:$AZ$2,0))} -> -651.46007 | ... P18: {=INDEX(model!$N6:$AZ6,,MATCH('Financial Output'!P$10,model!$N$2:$AZ$2,0))} -> -695.52943
C19: Research and Development | E19: (US$m) | G19: {=INDEX(model!$N7:$AZ7,,MATCH('Financial Output'!G$10,model!$N$2:$AZ$2,0))} -> -529.888 | H19: {=INDEX(model!$N7:$AZ7,,MATCH('Financial Output'!H$10,model!$N$2:$AZ$2,0))} -> -536.666 | I19: {=INDEX(model!$N7:$AZ7,,MATCH('Financial Output'!I$10,model!$N$2:$AZ$2,0))} -> -624.656 | J19: {=INDEX(model!$N7:$AZ7,,MATCH('Financial Output'!J$10,model!$N$2:$AZ$2,0))} -> -750.559 | K19: {=INDEX(model!$N7:$AZ7,,MATCH('Financial Output'!K$10,model!$N$2:$AZ$2,0))} -> -767.497 | L19: {=INDEX(model!$N7:$AZ7,,MATCH('Financial Output'!L$10,model!$N$2:$AZ$2,0))} -> -778.09828 | M19: {=INDEX(model!$N7:$AZ7,,MATCH('Financial Output'!M$10,model!$N$2:$AZ$2,0))} -> -855.90811 | N19: {=INDEX(model!$N7:$AZ7,,MATCH('Financial Output'!N$10,model!$N$2:$AZ$2,0))} -> -932.93984 | ... P19: {=INDEX(model!$N7:$AZ7,,MATCH('Financial Output'!P$10,model!$N$2:$AZ$2,0))} -> -1128.8572
C20: General and Administrative | E20: (US$m) | G20: {=INDEX(model!$N8:$AZ8,,MATCH('Financial Output'!G$10,model!$N$2:$AZ$2,0))} -> -173.579 | H20: {=INDEX(model!$N8:$AZ8,,MATCH('Financial Output'!H$10,model!$N$2:$AZ$2,0))} -> -184.446 | I20: {=INDEX(model!$N8:$AZ8,,MATCH('Financial Output'!I$10,model!$N$2:$AZ$2,0))} -> -179.98 | J20: {=INDEX(model!$N8:$AZ8,,MATCH('Financial Output'!J$10,model!$N$2:$AZ$2,0))} -> -218.758 | K20: {=INDEX(model!$N8:$AZ8,,MATCH('Financial Output'!K$10,model!$N$2:$AZ$2,0))} -> -220.647 | L20: {=INDEX(model!$N8:$AZ8,,MATCH('Financial Output'!L$10,model!$N$2:$AZ$2,0))} -> -234.76211 | M20: {=INDEX(model!$N8:$AZ8,,MATCH('Financial Output'!M$10,model!$N$2:$AZ$2,0))} -> -258.23832 | N20: {=INDEX(model!$N8:$AZ8,,MATCH('Financial Output'!N$10,model!$N$2:$AZ$2,0))} -> -281.47977 | ... P20: {=INDEX(model!$N8:$AZ8,,MATCH('Financial Output'!P$10,model!$N$2:$AZ$2,0))} -> -300.52105
C22: EBITDA | E22: (US$m) | G22: =G15+G18+G19+G20-G25 -> 665.526 | H22: =H15+H18+H19+H20-H25 -> 680.919 | I22: =I15+I18+I19+I20-I25 -> 429.346 | J22: =J15+J18+J19+J20-J25 -> 560.91 | K22: =K15+K18+K19+K20-K25 -> 354.248 | L22: =L15+L18+L19+L20-L25 -> 480.59011 | M22: =M15+M18+M19+M20-M25 -> 604.17043 | N22: =N15+N18+N19+N20-N25 -> 713.42458 | ... P22: =P15+P18+P19+P20-P25 -> 1328.0673
C23: EBITDA Margin | E23: (%)
C25: Depreciation and Amortization | E25: (US$m) | G25: {=-INDEX(model!$N50:$AZ50,,MATCH('Financial Output'!G$10,model!$N$2:$AZ$2,0))} -> -132.527 | H25: {=-INDEX(model!$N50:$AZ50,,MATCH('Financial Output'!H$10,model!$N$2:$AZ$2,0))} -> -132.266 | I25: {=-INDEX(model!$N50:$AZ50,,MATCH('Financial Output'!I$10,model!$N$2:$AZ$2,0))} -> -140.203 | J25: {=-INDEX(model!$N50:$AZ50,,MATCH('Financial Output'!J$10,model!$N$2:$AZ$2,0))} -> -142.18 | K25: {=-INDEX(model!$N50:$AZ50,,MATCH('Financial Output'!K$10,model!$N$2:$AZ$2,0))} -> -133.47 | L25: {=-INDEX(model!$N50:$AZ50,,MATCH('Financial Output'!L$10,model!$N$2:$AZ$2,0))} -> -114.42622 | M25: {=-INDEX(model!$N50:$AZ50,,MATCH('Financial Output'!M$10,model!$N$2:$AZ$2,0))} -> -100.69507 | N25: {=-INDEX(model!$N50:$AZ50,,MATCH('Financial Output'!N$10,model!$N$2:$AZ$2,0))} -> -109.75763 | ... P25: {=-INDEX(model!$N50:$AZ50,,MATCH('Financial Output'!P$10,model!$N$2:$AZ$2,0))} -> -132.80673
C27: EBIT | E27: (US$m) | G27: =+G15+G18+G19+G20 -> 532.999 | H27: =+H15+H18+H19+H20 -> 548.653 | I27: =+I15+I18+I19+I20 -> 289.143 | J27: =+J15+J18+J19+J20 -> 418.73 | K27: =+K15+K18+K19+K20 -> 220.778 | L27: =+L15+L18+L19+L20 -> 366.1639 | M27: =+M15+M18+M19+M20 -> 503.47536 | N27: =+N15+N18+N19+N20 -> 603.66695 | ... P27: =+P15+P18+P19+P20 -> 1195.2606
C28: EBIT Margin | E28: (%) | G28: =G27/G12 -> 0.15089901 | H28: =H27/H12 -> 0.15153297 | I28: =I27/I12 -> 0.079595371 | J28: =J27/J12 -> 0.095457728 | K28: =K27/K12 -> 0.05498891 | L28: =L27/L12 -> 0.08 | M28: =M27/M12 -> 0.1 | N28: =N27/N12 -> 0.11 | ... P28: =P27/P12 -> 0.18
C30: Interest Expense | E30: (US$m) | G30: {=INDEX(model!$N11:$AZ11,,MATCH('Financial Output'!G$10,model!$N$2:$AZ$2,0))} -> -31.003 | H30: {=INDEX(model!$N11:$AZ11,,MATCH('Financial Output'!H$10,model!$N$2:$AZ$2,0))} -> -32.605 | I30: {=INDEX(model!$N11:$AZ11,,MATCH('Financial Output'!I$10,model!$N$2:$AZ$2,0))} -> -40.303 | J30: {=INDEX(model!$N11:$AZ11,,MATCH('Financial Output'!J$10,model!$N$2:$AZ$2,0))} -> -33.892 | K30: {=INDEX(model!$N11:$AZ11,,MATCH('Financial Output'!K$10,model!$N$2:$AZ$2,0))} -> -46.767 | L30: {=INDEX(model!$N11:$AZ11,,MATCH('Financial Output'!L$10,model!$N$2:$AZ$2,0))} -> -38.460574 | M30: {=INDEX(model!$N11:$AZ11,,MATCH('Financial Output'!M$10,model!$N$2:$AZ$2,0))} -> -36.328192 | N30: {=INDEX(model!$N11:$AZ11,,MATCH('Financial Output'!N$10,model!$N$2:$AZ$2,0))} -> -28.363881 | ... P30: {=INDEX(model!$N11:$AZ11,,MATCH('Financial Output'!P$10,model!$N$2:$AZ$2,0))} -> 6.0653429
C32: Pre-Tax Income | E32: (US$m) | G32: =G27+G30 -> 501.996 | H32: =H27+H30 -> 516.048 | I32: =I27+I30 -> 248.84 | J32: =J27+J30 -> 384.838 | K32: =K27+K30 -> 174.011 | L32: =L27+L30 -> 327.70332 | M32: =M27+M30 -> 467.14717 | N32: =N27+N30 -> 575.30307 | ... P32: =P27+P30 -> 1201.3259
C33: Pre-Tax Margin | E33: (%) | G33: =G32/G12 -> 0.14212166 | H33: =H32/H12 -> 0.14252777 | I33: =I32/I12 -> 0.068500749 | J33: =J32/J12 -> 0.087731381 | K33: =K32/K12 -> 0.04334071 | L33: =L32/L12 -> 0.07159708 | M33: =M32/M12 -> 0.092784514 | N33: =N32/N12 -> 0.10483154 | ... P33: =P32/P12 -> 0.18091341
C35: Net Tax Expense | E35: (US$m) | G35: {=INDEX(model!$N13:$AZ13,,MATCH('Financial Output'!G$10,model!$N$2:$AZ$2,0))} -> -94.67 | H35: {=INDEX(model!$N13:$AZ13,,MATCH('Financial Output'!H$10,model!$N$2:$AZ$2,0))} -> 37.445 | I35: {=INDEX(model!$N13:$AZ13,,MATCH('Financial Output'!I$10,model!$N$2:$AZ$2,0))} -> -29.603 | J35: {=INDEX(model!$N13:$AZ13,,MATCH('Financial Output'!J$10,model!$N$2:$AZ$2,0))} -> -68.826 | K35: {=INDEX(model!$N13:$AZ13,,MATCH('Financial Output'!K$10,model!$N$2:$AZ$2,0))} -> -35.894 | L35: {=INDEX(model!$N13:$AZ13,,MATCH('Financial Output'!L$10,model!$N$2:$AZ$2,0))} -> -81.92583 | M35: {=INDEX(model!$N13:$AZ13,,MATCH('Financial Output'!M$10,model!$N$2:$AZ$2,0))} -> -116.78679 | N35: {=INDEX(model!$N13:$AZ13,,MATCH('Financial Output'!N$10,model!$N$2:$AZ$2,0))} -> -143.82577 | ... P35: {=INDEX(model!$N13:$AZ13,,MATCH('Financial Output'!P$10,model!$N$2:$AZ$2,0))} -> -300.33148
C36: Effective Tax Rate | E36: (%) | G36: =-G35/G32 -> 0.18858716 | H36: =-H35/H32 -> -0.07256108 | I36: =-I35/I32 -> 0.11896399 | J36: =-J35/J32 -> 0.17884409 | K36: =-K35/K32 -> 0.20627432 | L36: =-L35/L32 -> 0.25 | M36: =-M35/M32 -> 0.25 | N36: =-N35/N32 -> 0.25 | ... P36: =-P35/P32 -> 0.25
C38: Net Income | E38: (US$m) | G38: =G32+G35 -> 407.326 | H38: =H32+H35 -> 553.493 | I38: =I32+I35 -> 219.237 | J38: =J32+J35 -> 316.012 | K38: =K32+K35 -> 138.117 | L38: =L32+L35 -> 245.77749 | M38: =M32+M35 -> 350.36037 | N38: =N32+N35 -> 431.4773 | ... P38: =P32+P35 -> 900.99443
C39: Net Margin | G39: =G38/G12 -> 0.11531934 | H39: =H38/H12 -> 0.15286973 | I39: =I38/I12 -> 0.060351627 | J39: =J38/J12 -> 0.072041142 | K39: =K38/K12 -> 0.034400635 | L39: =L38/L12 -> 0.05369781 | M39: =M38/M12 -> 0.069588386 | N39: =N38/N12 -> 0.078623657 | ... P39: =P38/P12 -> 0.13568506
C41: Shares Outstanding (f.d.) | E41: (millions) | G41: {=INDEX(model!$N16:$AZ16,,MATCH('Financial Output'!G$10,model!$N$2:$AZ$2,0))} -> 155.955 | H41: {=INDEX(model!$N16:$AZ16,,MATCH('Financial Output'!H$10,model!$N$2:$AZ$2,0))} -> 156.743 | I41: {=INDEX(model!$N16:$AZ16,,MATCH('Financial Output'!I$10,model!$N$2:$AZ$2,0))} -> 152.193 | J41: {=INDEX(model!$N16:$AZ16,,MATCH('Financial Output'!J$10,model!$N$2:$AZ$2,0))} -> 149.38 | K41: {=INDEX(model!$N16:$AZ16,,MATCH('Financial Output'!K$10,model!$N$2:$AZ$2,0))} -> 145.964 | L41: {=INDEX(model!$N16:$AZ16,,MATCH('Financial Output'!L$10,model!$N$2:$AZ$2,0))} -> 146 | M41: {=INDEX(model!$N16:$AZ16,,MATCH('Financial Output'!M$10,model!$N$2:$AZ$2,0))} -> 146 | N41: {=INDEX(model!$N16:$AZ16,,MATCH('Financial Output'!N$10,model!$N$2:$AZ$2,0))} -> 146 | ... P41: {=INDEX(model!$N16:$AZ16,,MATCH('Financial Output'!P$10,model!$N$2:$AZ$2,0))} -> 146
C43: Earnings per Share (diluted) | E43: (US$/share) | G43: =G38/G41 -> 2.6118175 | H43: =H38/H41 -> 3.5312135 | I43: =I38/I41 -> 1.4405196 | J43: =J38/J41 -> 2.1154907 | K43: =K38/K41 -> 0.94624017 | L43: =L38/L41 -> 1.6834075 | M43: =M38/M41 -> 2.3997286 | N43: =N38/N41 -> 2.955324 | ... P43: =P38/P41 -> 6.1711947
C45: Imprield Forward Price-to-Earnings | E45: (x)
B47: 2 | C47: Balance Sheet | E47: Units
C49: Year Ended | G49: =H49-1 -> 2020 | H49: =I49-1 -> 2021 | I49: =J49-1 -> 2022 | J49: =K49-1 -> 2023 | K49: =L49-1 -> 2024 | L49: =estimate_start -> 2025 | M49: =+L49+1 -> 2026 | N49: =+M49+1 -> 2027 | O49: =+N49+1 -> 2028 | P49: =+O49+1 -> 2029
C51: Current Assets
C52: Cash & Cash Eqivalents | E52: (US$m) | G52: {=INDEX(model!$N23:$AZ23,,MATCH('Financial Output'!G$10,model!$N$2:$AZ$2,0))} -> 1239.291 | H52: {=INDEX(model!$N23:$AZ23,,MATCH('Financial Output'!H$10,model!$N$2:$AZ$2,0))} -> 1604.029 | I52: {=INDEX(model!$N23:$AZ23,,MATCH('Financial Output'!I$10,model!$N$2:$AZ$2,0))} -> 1148.341 | J52: {=INDEX(model!$N23:$AZ23,,MATCH('Financial Output'!J$10,model!$N$2:$AZ$2,0))} -> 1115.371 | K52: {=INDEX(model!$N23:$AZ23,,MATCH('Financial Output'!K$10,model!$N$2:$AZ$2,0))} -> 1251.206 | L52: {=INDEX(model!$N23:$AZ23,,MATCH('Financial Output'!L$10,model!$N$2:$AZ$2,0))} -> 1283.1276 | M52: {=INDEX(model!$N23:$AZ23,,MATCH('Financial Output'!M$10,model!$N$2:$AZ$2,0))} -> 1426.7348 | N52: {=INDEX(model!$N23:$AZ23,,MATCH('Financial Output'!N$10,model!$N$2:$AZ$2,0))} -> 1744.4763 | ... P52: {=INDEX(model!$N23:$AZ23,,MATCH('Financial Output'!P$10,model!$N$2:$AZ$2,0))} -> 2747.696
C53: Accounts Recievable | E53: (US$m) | G53: {=INDEX(model!$N24:$AZ24,,MATCH('Financial Output'!G$10,model!$N$2:$AZ$2,0))} -> 719.405 | H53: {=INDEX(model!$N24:$AZ24,,MATCH('Financial Output'!H$10,model!$N$2:$AZ$2,0))} -> 884.958 | I53: {=INDEX(model!$N24:$AZ24,,MATCH('Financial Output'!I$10,model!$N$2:$AZ$2,0))} -> 920.772 | J53: {=INDEX(model!$N24:$AZ24,,MATCH('Financial Output'!J$10,model!$N$2:$AZ$2,0))} -> 1003.876 | K53: {=INDEX(model!$N24:$AZ24,,MATCH('Financial Output'!K$10,model!$N$2:$AZ$2,0))} -> 908.597 | L53: {=INDEX(model!$N24:$AZ24,,MATCH('Financial Output'!L$10,model!$N$2:$AZ$2,0))} -> 1144.2622 | M53: {=INDEX(model!$N24:$AZ24,,MATCH('Financial Output'!M$10,model!$N$2:$AZ$2,0))} -> 1195.754 | N53: {=INDEX(model!$N24:$AZ24,,MATCH('Financial Output'!N$10,model!$N$2:$AZ$2,0))} -> 1238.2032 | ... P53: {=INDEX(model!$N24:$AZ24,,MATCH('Financial Output'!P$10,model!$N$2:$AZ$2,0))} -> 1352.1489
C54: % of Revenue | G54: =G53/G12 -> 0.203673 | H54: =H53/H12 -> 0.24441735 | I54: =I53/I12 -> 0.25347039 | J54: =J53/J12 -> 0.22885325 | K54: =K53/K12 -> 0.22630316 | L54: =L53/L12 -> 0.25 | M54: =M53/M12 -> 0.2375 | N54: =N53/N12 -> 0.225625 | ... P54: =P53/P12 -> 0.20362656
C56: Inventories | E56: (US$m) | G56: {=INDEX(model!$N25:$AZ25,,MATCH('Financial Output'!G$10,model!$N$2:$AZ$2,0))} -> 344.379 | H56: {=INDEX(model!$N25:$AZ25,,MATCH('Financial Output'!H$10,model!$N$2:$AZ$2,0))} -> 374.265 | I56: {=INDEX(model!$N25:$AZ25,,MATCH('Financial Output'!I$10,model!$N$2:$AZ$2,0))} -> 946.73 | J56: {=INDEX(model!$N25:$AZ25,,MATCH('Financial Output'!J$10,model!$N$2:$AZ$2,0))} -> 1050.838 | K56: {=INDEX(model!$N25:$AZ25,,MATCH('Financial Output'!K$10,model!$N$2:$AZ$2,0))} -> 820.43 | L56: {=INDEX(model!$N25:$AZ25,,MATCH('Financial Output'!L$10,model!$N$2:$AZ$2,0))} -> 915.40974 | M56: {=INDEX(model!$N25:$AZ25,,MATCH('Financial Output'!M$10,model!$N$2:$AZ$2,0))} -> 1006.9507 | N56: {=INDEX(model!$N25:$AZ25,,MATCH('Financial Output'!N$10,model!$N$2:$AZ$2,0))} -> 1097.5763 | ... P56: {=INDEX(model!$N25:$AZ25,,MATCH('Financial Output'!P$10,model!$N$2:$AZ$2,0))} -> 1328.0673
C57: Prepaid Expenses and Other | E57: (US$m) | G57: {=INDEX(model!$N26:$AZ26,,MATCH('Financial Output'!G$10,model!$N$2:$AZ$2,0))} -> 308.084 | H57: {=INDEX(model!$N26:$AZ26,,MATCH('Financial Output'!H$10,model!$N$2:$AZ$2,0))} -> 325.654 | I57: {=INDEX(model!$N26:$AZ26,,MATCH('Financial Output'!I$10,model!$N$2:$AZ$2,0))} -> 370.053 | J57: {=INDEX(model!$N26:$AZ26,,MATCH('Financial Output'!J$10,model!$N$2:$AZ$2,0))} -> 405.694 | K57: {=INDEX(model!$N26:$AZ26,,MATCH('Financial Output'!K$10,model!$N$2:$AZ$2,0))} -> 564.183 | L57: {=INDEX(model!$N26:$AZ26,,MATCH('Financial Output'!L$10,model!$N$2:$AZ$2,0))} -> 643.43465 | M57: {=INDEX(model!$N26:$AZ26,,MATCH('Financial Output'!M$10,model!$N$2:$AZ$2,0))} -> 707.77812 | N57: {=INDEX(model!$N26:$AZ26,,MATCH('Financial Output'!N$10,model!$N$2:$AZ$2,0))} -> 771.47815 | ... P57: {=INDEX(model!$N26:$AZ26,,MATCH('Financial Output'!P$10,model!$N$2:$AZ$2,0))} -> 933.48856
C59: Total Current Assets | E59: (US$m) | G59: =G52+G53+G56+G57 -> 2611.159 | H59: =H52+H53+H56+H57 -> 3188.906 | I59: =I52+I53+I56+I57 -> 3385.896 | J59: =J52+J53+J56+J57 -> 3575.779 | K59: =K52+K53+K56+K57 -> 3544.416 | L59: =L52+L53+L56+L57 -> 3986.2342 | M59: =M52+M53+M56+M57 -> 4337.2176 | N59: =N52+N53+N56+N57 -> 4851.734 | ... P59: =P52+P53+P56+P57 -> 6361.4007
C61: Non-Current Assets
C62: Investments | E62: (US$m) | G62: {=INDEX(model!$N27:$AZ27,,MATCH('Financial Output'!G$10,model!$N$2:$AZ$2,0))} -> 82.226 | H62: {=INDEX(model!$N27:$AZ27,,MATCH('Financial Output'!H$10,model!$N$2:$AZ$2,0))} -> 70.038 | I62: {=INDEX(model!$N27:$AZ27,,MATCH('Financial Output'!I$10,model!$N$2:$AZ$2,0))} -> 35.385 | J62: {=INDEX(model!$N27:$AZ27,,MATCH('Financial Output'!J$10,model!$N$2:$AZ$2,0))} -> 134.278 | K62: {=INDEX(model!$N27:$AZ27,,MATCH('Financial Output'!K$10,model!$N$2:$AZ$2,0))} -> 80.92 | L62: {=INDEX(model!$N27:$AZ27,,MATCH('Financial Output'!L$10,model!$N$2:$AZ$2,0))} -> 81 | M62: {=INDEX(model!$N27:$AZ27,,MATCH('Financial Output'!M$10,model!$N$2:$AZ$2,0))} -> 81 | N62: {=INDEX(model!$N27:$AZ27,,MATCH('Financial Output'!N$10,model!$N$2:$AZ$2,0))} -> 81 | ... P62: {=INDEX(model!$N27:$AZ27,,MATCH('Financial Output'!P$10,model!$N$2:$AZ$2,0))} -> 81
C64: Leases | E64: (US$m) | G64: {=INDEX(model!$N29:$AZ29,,MATCH('Financial Output'!G$10,model!$N$2:$AZ$2,0))} -> 57.026 | H64: {=INDEX(model!$N29:$AZ29,,MATCH('Financial Output'!H$10,model!$N$2:$AZ$2,0))} -> 44.285 | I64: {=INDEX(model!$N29:$AZ29,,MATCH('Financial Output'!I$10,model!$N$2:$AZ$2,0))} -> 45.108 | J64: {=INDEX(model!$N29:$AZ29,,MATCH('Financial Output'!J$10,model!$N$2:$AZ$2,0))} -> 35.14 | K64: {=INDEX(model!$N29:$AZ29,,MATCH('Financial Output'!K$10,model!$N$2:$AZ$2,0))} -> 27.417 | L64: {=INDEX(model!$N29:$AZ29,,MATCH('Financial Output'!L$10,model!$N$2:$AZ$2,0))} -> 35 | M64: {=INDEX(model!$N29:$AZ29,,MATCH('Financial Output'!M$10,model!$N$2:$AZ$2,0))} -> 35 | N64: {=INDEX(model!$N29:$AZ29,,MATCH('Financial Output'!N$10,model!$N$2:$AZ$2,0))} -> 35 | ... P64: {=INDEX(model!$N29:$AZ29,,MATCH('Financial Output'!P$10,model!$N$2:$AZ$2,0))} -> 35
C65: Property, Plant and Equipment | E65: (US$m) | G65: {=INDEX(model!$N28:$AZ28,,MATCH('Financial Output'!G$10,model!$N$2:$AZ$2,0))} -> 272.377 | H65: {=INDEX(model!$N28:$AZ28,,MATCH('Financial Output'!H$10,model!$N$2:$AZ$2,0))} -> 284.968 | I65: {=INDEX(model!$N28:$AZ28,,MATCH('Financial Output'!I$10,model!$N$2:$AZ$2,0))} -> 267.779 | J65: {=INDEX(model!$N28:$AZ28,,MATCH('Financial Output'!J$10,model!$N$2:$AZ$2,0))} -> 280.147 | K65: {=INDEX(model!$N28:$AZ28,,MATCH('Financial Output'!K$10,model!$N$2:$AZ$2,0))} -> 337.722 | L65: {=INDEX(model!$N28:$AZ28,,MATCH('Financial Output'!L$10,model!$N$2:$AZ$2,0))} -> 360.60724 | M65: {=INDEX(model!$N28:$AZ28,,MATCH('Financial Output'!M$10,model!$N$2:$AZ$2,0))} -> 410.95478 | N65: {=INDEX(model!$N28:$AZ28,,MATCH('Financial Output'!N$10,model!$N$2:$AZ$2,0))} -> 465.83359 | ... P65: {=INDEX(model!$N28:$AZ28,,MATCH('Financial Output'!P$10,model!$N$2:$AZ$2,0))} -> 592.60365
C67: Goodwill | E67: (US$m) | G67: {=INDEX(model!$N30:$AZ30,,MATCH('Financial Output'!G$10,model!$N$2:$AZ$2,0))} -> 310.847 | H67: {=INDEX(model!$N30:$AZ30,,MATCH('Financial Output'!H$10,model!$N$2:$AZ$2,0))} -> 311.645 | I67: {=INDEX(model!$N30:$AZ30,,MATCH('Financial Output'!I$10,model!$N$2:$AZ$2,0))} -> 328.322 | J67: {=INDEX(model!$N30:$AZ30,,MATCH('Financial Output'!J$10,model!$N$2:$AZ$2,0))} -> 444.765 | K67: {=INDEX(model!$N30:$AZ30,,MATCH('Financial Output'!K$10,model!$N$2:$AZ$2,0))} -> 444.707 | L67: {=INDEX(model!$N30:$AZ30,,MATCH('Financial Output'!L$10,model!$N$2:$AZ$2,0))} -> 445 | M67: {=INDEX(model!$N30:$AZ30,,MATCH('Financial Output'!M$10,model!$N$2:$AZ$2,0))} -> 445 | N67: {=INDEX(model!$N30:$AZ30,,MATCH('Financial Output'!N$10,model!$N$2:$AZ$2,0))} -> 445 | ... P67: {=INDEX(model!$N30:$AZ30,,MATCH('Financial Output'!P$10,model!$N$2:$AZ$2,0))} -> 445
C68: Other Intangible Assets | E68: (US$m) | G68: {=INDEX(model!$N31:$AZ31,,MATCH('Financial Output'!G$10,model!$N$2:$AZ$2,0))} -> 96.647 | H68: {=INDEX(model!$N31:$AZ31,,MATCH('Financial Output'!H$10,model!$N$2:$AZ$2,0))} -> 65.314 | I68: {=INDEX(model!$N31:$AZ31,,MATCH('Financial Output'!I$10,model!$N$2:$AZ$2,0))} -> 69.517 | J68: {=INDEX(model!$N31:$AZ31,,MATCH('Financial Output'!J$10,model!$N$2:$AZ$2,0))} -> 205.627 | K68: {=INDEX(model!$N31:$AZ31,,MATCH('Financial Output'!K$10,model!$N$2:$AZ$2,0))} -> 165.02 | L68: {=INDEX(model!$N31:$AZ31,,MATCH('Financial Output'!L$10,model!$N$2:$AZ$2,0))} -> 165 | M68: {=INDEX(model!$N31:$AZ31,,MATCH('Financial Output'!M$10,model!$N$2:$AZ$2,0))} -> 165 | N68: {=INDEX(model!$N31:$AZ31,,MATCH('Financial Output'!N$10,model!$N$2:$AZ$2,0))} -> 165 | ... P68: {=INDEX(model!$N31:$AZ31,,MATCH('Financial Output'!P$10,model!$N$2:$AZ$2,0))} -> 165
C69: Deferred Tax Asset | E69: (US$m) | G69: {=INDEX(model!$N32:$AZ32,,MATCH('Financial Output'!G$10,model!$N$2:$AZ$2,0))} -> 647.805 | H69: {=INDEX(model!$N32:$AZ32,,MATCH('Financial Output'!H$10,model!$N$2:$AZ$2,0))} -> 800.18 | I69: {=INDEX(model!$N32:$AZ32,,MATCH('Financial Output'!I$10,model!$N$2:$AZ$2,0))} -> 824.008 | J69: {=INDEX(model!$N32:$AZ32,,MATCH('Financial Output'!J$10,model!$N$2:$AZ$2,0))} -> 809.306 | K69: {=INDEX(model!$N32:$AZ32,,MATCH('Financial Output'!K$10,model!$N$2:$AZ$2,0))} -> 886.441 | L69: {=INDEX(model!$N32:$AZ32,,MATCH('Financial Output'!L$10,model!$N$2:$AZ$2,0))} -> 1010.9607 | M69: {=INDEX(model!$N32:$AZ32,,MATCH('Financial Output'!M$10,model!$N$2:$AZ$2,0))} -> 1112.0568 | N69: {=INDEX(model!$N32:$AZ32,,MATCH('Financial Output'!N$10,model!$N$2:$AZ$2,0))} -> 1212.1419 | ... P69: {=INDEX(model!$N32:$AZ32,,MATCH('Financial Output'!P$10,model!$N$2:$AZ$2,0))} -> 1466.6917
C70: Other Long-Term Assets | E70: (US$m) | G70: {=INDEX(model!$N33:$AZ33,,MATCH('Financial Output'!G$10,model!$N$2:$AZ$2,0))} -> 102.83 | H70: {=INDEX(model!$N33:$AZ33,,MATCH('Financial Output'!H$10,model!$N$2:$AZ$2,0))} -> 99.891 | I70: {=INDEX(model!$N33:$AZ33,,MATCH('Financial Output'!I$10,model!$N$2:$AZ$2,0))} -> 113.617 | J70: {=INDEX(model!$N33:$AZ33,,MATCH('Financial Output'!J$10,model!$N$2:$AZ$2,0))} -> 116.453 | K70: {=INDEX(model!$N33:$AZ33,,MATCH('Financial Output'!K$10,model!$N$2:$AZ$2,0))} -> 154.694 | L70: {=INDEX(model!$N33:$AZ33,,MATCH('Financial Output'!L$10,model!$N$2:$AZ$2,0))} -> 176.4241 | M70: {=INDEX(model!$N33:$AZ33,,MATCH('Financial Output'!M$10,model!$N$2:$AZ$2,0))} -> 194.06651 | N70: {=INDEX(model!$N33:$AZ33,,MATCH('Financial Output'!N$10,model!$N$2:$AZ$2,0))} -> 211.5325 | ... P70: {=INDEX(model!$N33:$AZ33,,MATCH('Financial Output'!P$10,model!$N$2:$AZ$2,0))} -> 255.95432
C72: Total Assets | E72: (US$m) | G72: =+G70+G69+G68+G67+G65+G64+G62+G59 -> 4180.917 | H72: =+H70+H69+H68+H67+H65+H64+H62+H59 -> 4865.227 | I72: =+I70+I69+I68+I67+I65+I64+I62+I59 -> 5069.632 | J72: =+J70+J69+J68+J67+J65+J64+J62+J59 -> 5601.495 | K72: =+K70+K69+K68+K67+K65+K64+K62+K59 -> 5641.337 | L72: =+L70+L69+L68+L67+L65+L64+L62+L59 -> 6260.2262 | M72: =+M70+M69+M68+M67+M65+M64+M62+M59 -> 6780.2957 | N72: =+N70+N69+N68+N67+N65+N64+N62+N59 -> 7467.242 | ... P72: =+P70+P69+P68+P67+P65+P64+P62+P59 -> 9402.6504
C74: Current Liabilities
C75: Accounts Payable | E75: (US$m) | G75: {=INDEX(model!$N36:$AZ36,,MATCH('Financial Output'!G$10,model!$N$2:$AZ$2,0))} -> 291.904 | H75: {=INDEX(model!$N36:$AZ36,,MATCH('Financial Output'!H$10,model!$N$2:$AZ$2,0))} -> 356.176 | I75: {=INDEX(model!$N36:$AZ36,,MATCH('Financial Output'!I$10,model!$N$2:$AZ$2,0))} -> 516.047 | J75: {=INDEX(model!$N36:$AZ36,,MATCH('Financial Output'!J$10,model!$N$2:$AZ$2,0))} -> 317.828 | K75: {=INDEX(model!$N36:$AZ36,,MATCH('Financial Output'!K$10,model!$N$2:$AZ$2,0))} -> 423.401 | L75: {=INDEX(model!$N36:$AZ36,,MATCH('Financial Output'!L$10,model!$N$2:$AZ$2,0))} -> 265.46882 | M75: {=INDEX(model!$N36:$AZ36,,MATCH('Financial Output'!M$10,model!$N$2:$AZ$2,0))} -> 281.9462 | N75: {=INDEX(model!$N36:$AZ36,,MATCH('Financial Output'!N$10,model!$N$2:$AZ$2,0))} -> 301.83348 | ... P75: {=INDEX(model!$N36:$AZ36,,MATCH('Financial Output'!P$10,model!$N$2:$AZ$2,0))} -> 332.01682
C76: % of Cost of Goods Sold
C78: Accurred Liabilities | E78: (US$m) | G78: {=INDEX(model!$N37:$AZ37,,MATCH('Financial Output'!G$10,model!$N$2:$AZ$2,0))} -> 334.132 | H78: {=INDEX(model!$N37:$AZ37,,MATCH('Financial Output'!H$10,model!$N$2:$AZ$2,0))} -> 409.285 | I78: {=INDEX(model!$N37:$AZ37,,MATCH('Financial Output'!I$10,model!$N$2:$AZ$2,0))} -> 360.782 | J78: {=INDEX(model!$N37:$AZ37,,MATCH('Financial Output'!J$10,model!$N$2:$AZ$2,0))} -> 431.419 | K78: {=INDEX(model!$N37:$AZ37,,MATCH('Financial Output'!K$10,model!$N$2:$AZ$2,0))} -> 393.905 | L78: {=INDEX(model!$N37:$AZ37,,MATCH('Financial Output'!L$10,model!$N$2:$AZ$2,0))} -> 389.04914 | M78: {=INDEX(model!$N37:$AZ37,,MATCH('Financial Output'!M$10,model!$N$2:$AZ$2,0))} -> 427.95405 | N78: {=INDEX(model!$N37:$AZ37,,MATCH('Financial Output'!N$10,model!$N$2:$AZ$2,0))} -> 466.46992 | ... P78: {=INDEX(model!$N37:$AZ37,,MATCH('Financial Output'!P$10,model!$N$2:$AZ$2,0))} -> 531.22692
C79: Deferred Revenue | E79: (US$m) | G79: {=INDEX(model!$N39:$AZ39,,MATCH('Financial Output'!G$10,model!$N$2:$AZ$2,0))} -> 158.363 | H79: {=INDEX(model!$N39:$AZ39,,MATCH('Financial Output'!H$10,model!$N$2:$AZ$2,0))} -> 175.464 | I79: {=INDEX(model!$N39:$AZ39,,MATCH('Financial Output'!I$10,model!$N$2:$AZ$2,0))} -> 200.235 | J79: {=INDEX(model!$N39:$AZ39,,MATCH('Financial Output'!J$10,model!$N$2:$AZ$2,0))} -> 228.46 | K79: {=INDEX(model!$N39:$AZ39,,MATCH('Financial Output'!K$10,model!$N$2:$AZ$2,0))} -> 237.619 | L79: {=INDEX(model!$N39:$AZ39,,MATCH('Financial Output'!L$10,model!$N$2:$AZ$2,0))} -> 200 | M79: {=INDEX(model!$N39:$AZ39,,MATCH('Financial Output'!M$10,model!$N$2:$AZ$2,0))} -> 200 | N79: {=INDEX(model!$N39:$AZ39,,MATCH('Financial Output'!N$10,model!$N$2:$AZ$2,0))} -> 200 | ... P79: {=INDEX(model!$N39:$AZ39,,MATCH('Financial Output'!P$10,model!$N$2:$AZ$2,0))} -> 200
C81: Total Current Liabilities | E81: (US$m) | G81: =G75+G78+G79 -> 784.399 | H81: =H75+H78+H79 -> 940.925 | I81: =I75+I78+I79 -> 1077.064 | J81: =J75+J78+J79 -> 977.707 | K81: =K75+K78+K79 -> 1054.925 | L81: =L75+L78+L79 -> 854.51796 | M81: =M75+M78+M79 -> 909.90025 | N81: =N75+N78+N79 -> 968.30339 | ... P81: =P75+P78+P79 -> 1063.2437
C83: Non-Current Liabilities
C84: Leases | E84: (US$m) | G84: {=INDEX(model!$N40:$AZ40,,MATCH('Financial Output'!G$10,model!$N$2:$AZ$2,0))} -> 80.45 | H84: {=INDEX(model!$N40:$AZ40,,MATCH('Financial Output'!H$10,model!$N$2:$AZ$2,0))} -> 60.196 | I84: {=INDEX(model!$N40:$AZ40,,MATCH('Financial Output'!I$10,model!$N$2:$AZ$2,0))} -> 61.317 | J84: {=INDEX(model!$N40:$AZ40,,MATCH('Financial Output'!J$10,model!$N$2:$AZ$2,0))} -> 49.914 | K84: {=INDEX(model!$N40:$AZ40,,MATCH('Financial Output'!K$10,model!$N$2:$AZ$2,0))} -> 39.562 | L84: {=INDEX(model!$N40:$AZ40,,MATCH('Financial Output'!L$10,model!$N$2:$AZ$2,0))} -> 50 | M84: {=INDEX(model!$N40:$AZ40,,MATCH('Financial Output'!M$10,model!$N$2:$AZ$2,0))} -> 50 | N84: {=INDEX(model!$N40:$AZ40,,MATCH('Financial Output'!N$10,model!$N$2:$AZ$2,0))} -> 50 | ... P84: {=INDEX(model!$N40:$AZ40,,MATCH('Financial Output'!P$10,model!$N$2:$AZ$2,0))} -> 50
C85: Debt | E85: (US$m) | G85: {=INDEX(model!$N38:$AZ38,,MATCH('Financial Output'!G$10,model!$N$2:$AZ$2,0))} -> 683.286 | H85: {=INDEX(model!$N38:$AZ38,,MATCH('Financial Output'!H$10,model!$N$2:$AZ$2,0))} -> 677.285 | I85: {=INDEX(model!$N38:$AZ38,,MATCH('Financial Output'!I$10,model!$N$2:$AZ$2,0))} -> 1068.055 | J85: {=INDEX(model!$N38:$AZ38,,MATCH('Financial Output'!J$10,model!$N$2:$AZ$2,0))} -> 1555.106 | K85: {=INDEX(model!$N38:$AZ38,,MATCH('Financial Output'!K$10,model!$N$2:$AZ$2,0))} -> 1544.774 | L85: {=INDEX(model!$N38:$AZ38,,MATCH('Financial Output'!L$10,model!$N$2:$AZ$2,0))} -> 1558.3 | M85: {=INDEX(model!$N38:$AZ38,,MATCH('Financial Output'!M$10,model!$N$2:$AZ$2,0))} -> 1558.3 | N85: {=INDEX(model!$N38:$AZ38,,MATCH('Financial Output'!N$10,model!$N$2:$AZ$2,0))} -> 1558.3 | ... P85: {=INDEX(model!$N38:$AZ38,,MATCH('Financial Output'!P$10,model!$N$2:$AZ$2,0))} -> 1558.3
C86: Other Liabilities | E86: (US$m) | G86: {=INDEX(model!$N41:$AZ41,,MATCH('Financial Output'!G$10,model!$N$2:$AZ$2,0))} -> 123.185 | H86: {=INDEX(model!$N41:$AZ41,,MATCH('Financial Output'!H$10,model!$N$2:$AZ$2,0))} -> 166.803 | I86: {=INDEX(model!$N41:$AZ41,,MATCH('Financial Output'!I$10,model!$N$2:$AZ$2,0))} -> 150.335 | J86: {=INDEX(model!$N41:$AZ41,,MATCH('Financial Output'!J$10,model!$N$2:$AZ$2,0))} -> 170.407 | K86: {=INDEX(model!$N41:$AZ41,,MATCH('Financial Output'!K$10,model!$N$2:$AZ$2,0))} -> 185.938 | L86: {=INDEX(model!$N41:$AZ41,,MATCH('Financial Output'!L$10,model!$N$2:$AZ$2,0))} -> 183.08195 | M86: {=INDEX(model!$N41:$AZ41,,MATCH('Financial Output'!M$10,model!$N$2:$AZ$2,0))} -> 201.39014 | N86: {=INDEX(model!$N41:$AZ41,,MATCH('Financial Output'!N$10,model!$N$2:$AZ$2,0))} -> 219.51526 | ... P86: {=INDEX(model!$N41:$AZ41,,MATCH('Financial Output'!P$10,model!$N$2:$AZ$2,0))} -> 265.61346
C88: Total Liablities | E88: (US$m) | G88: =G84+G85+G86+G81 -> 1671.32 | H88: =H84+H85+H86+H81 -> 1845.209 | I88: =I84+I85+I86+I81 -> 2356.771 | J88: =J84+J85+J86+J81 -> 2753.134 | K88: =K84+K85+K86+K81 -> 2825.199 | L88: =L84+L85+L86+L81 -> 2645.8999 | M88: =M84+M85+M86+M81 -> 2719.5904 | N88: =N84+N85+N86+N81 -> 2796.1187 | ... P88: =P84+P85+P86+P81 -> 2937.1572
C90: Shareholder's Equity
C91: Total Paid in Capital | E91: (US$m) | G91: {=INDEX(model!$N43:$AZ43,,MATCH('Financial Output'!G$10,model!$N$2:$AZ$2,0))} -> 6828.077 | H91: {=INDEX(model!$N43:$AZ43,,MATCH('Financial Output'!H$10,model!$N$2:$AZ$2,0))} -> 6804.711 | I91: {=INDEX(model!$N43:$AZ43,,MATCH('Financial Output'!I$10,model!$N$2:$AZ$2,0))} -> 6391.736 | J91: {=INDEX(model!$N43:$AZ43,,MATCH('Financial Output'!J$10,model!$N$2:$AZ$2,0))} -> 6263.531 | K91: {=INDEX(model!$N43:$AZ43,,MATCH('Financial Output'!K$10,model!$N$2:$AZ$2,0))} -> 6156.296 | L91: {=INDEX(model!$N43:$AZ43,,MATCH('Financial Output'!L$10,model!$N$2:$AZ$2,0))} -> 5983.2243 | M91: {=INDEX(model!$N43:$AZ43,,MATCH('Financial Output'!M$10,model!$N$2:$AZ$2,0))} -> 5829.6317 | N91: {=INDEX(model!$N43:$AZ43,,MATCH('Financial Output'!N$10,model!$N$2:$AZ$2,0))} -> 5692.2157 | ... P91: {=INDEX(model!$N43:$AZ43,,MATCH('Financial Output'!P$10,model!$N$2:$AZ$2,0))} -> 5604.2184
C92: Retained Earnings | E92: (US$m) | G92: {=INDEX(model!$N42:$AZ42,,MATCH('Financial Output'!G$10,model!$N$2:$AZ$2,0))} -> -4283.122 | H92: {=INDEX(model!$N42:$AZ42,,MATCH('Financial Output'!H$10,model!$N$2:$AZ$2,0))} -> -3785.132 | I92: {=INDEX(model!$N42:$AZ42,,MATCH('Financial Output'!I$10,model!$N$2:$AZ$2,0))} -> -3632.23 | J92: {=INDEX(model!$N42:$AZ42,,MATCH('Financial Output'!J$10,model!$N$2:$AZ$2,0))} -> -3377.403 | K92: {=INDEX(model!$N42:$AZ42,,MATCH('Financial Output'!K$10,model!$N$2:$AZ$2,0))} -> -3293.447 | L92: {=INDEX(model!$N42:$AZ42,,MATCH('Financial Output'!L$10,model!$N$2:$AZ$2,0))} -> -3047.6695 | M92: {=INDEX(model!$N42:$AZ42,,MATCH('Financial Output'!M$10,model!$N$2:$AZ$2,0))} -> -2697.3091 | N92: {=INDEX(model!$N42:$AZ42,,MATCH('Financial Output'!N$10,model!$N$2:$AZ$2,0))} -> -2265.8318 | ... P92: {=INDEX(model!$N42:$AZ42,,MATCH('Financial Output'!P$10,model!$N$2:$AZ$2,0))} -> -605.49187
C93: Accumulated Other Comprehensive Income | E93: (US$m) | G93: {=INDEX(model!$N44:$AZ44,,MATCH('Financial Output'!G$10,model!$N$2:$AZ$2,0))} -> -35.358 | H93: {=INDEX(model!$N44:$AZ44,,MATCH('Financial Output'!H$10,model!$N$2:$AZ$2,0))} -> 0.439 | I93: {=INDEX(model!$N44:$AZ44,,MATCH('Financial Output'!I$10,model!$N$2:$AZ$2,0))} -> -46.645 | J93: {=INDEX(model!$N44:$AZ44,,MATCH('Financial Output'!J$10,model!$N$2:$AZ$2,0))} -> -37.767 | K93: {=INDEX(model!$N44:$AZ44,,MATCH('Financial Output'!K$10,model!$N$2:$AZ$2,0))} -> -46.711 | L93: {=INDEX(model!$N44:$AZ44,,MATCH('Financial Output'!L$10,model!$N$2:$AZ$2,0))} -> -20 | M93: {=INDEX(model!$N44:$AZ44,,MATCH('Financial Output'!M$10,model!$N$2:$AZ$2,0))} -> -20 | N93: {=INDEX(model!$N44:$AZ44,,MATCH('Financial Output'!N$10,model!$N$2:$AZ$2,0))} -> -20 | ... P93: {=INDEX(model!$N44:$AZ44,,MATCH('Financial Output'!P$10,model!$N$2:$AZ$2,0))} -> -20
C95: Total Liabilities and Shareholders' Equity | E95: (US$m) | G95: =G88+G91+G92+G93 -> 4180.917 | H95: =H88+H91+H92+H93 -> 4865.227 | I95: =I88+I91+I92+I93 -> 5069.632 | J95: =J88+J91+J92+J93 -> 5601.495 | K95: =K88+K91+K92+K93 -> 5641.337 | L95: =L88+L91+L92+L93 -> 5561.4547 | M95: =M88+M91+M92+M93 -> 5831.9129 | N95: =N88+N91+N92+N93 -> 6202.5025 | ... P95: =P88+P91+P92+P93 -> 7915.8837
C97: Balance Check | E97: (US$m) | G97: =G72-G95 -> 0 | H97: =H72-H95 -> 0 | I97: =I72-I95 -> 0 | J97: =J72-J95 -> 0 | K97: =K72-K95 -> 0 | L97: =L72-L95 -> 698.77154 | M97: =M72-M95 -> 948.38273 | N97: =N72-N95 -> 1264.7395 | ... P97: =P72-P95 -> 1486.7667
B99: 3 | C99: Cash Flow Statement | E99: Units
C101: Year Ended | G101: =H101-1 -> 2020 | H101: =I101-1 -> 2021 | I101: =J101-1 -> 2022 | J101: =K101-1 -> 2023 | K101: =L101-1 -> 2024 | L101: =estimate_start -> 2025 | M101: =+L101+1 -> 2026 | N101: =+M101+1 -> 2027 | O101: =+N101+1 -> 2028 | P101: =+O101+1 -> 2029
C103: Cash Generated from Operating Activities
C104: Net Income | E104: (US$m) | L104: =L38 -> 245.77749 | M104: =M38 -> 350.36037 | N104: =N38 -> 431.4773 | O104: =O38 -> 759.34553 | P104: =P38 -> 900.99443
C105: Depreciation & Armortization | E105: (US$m) | L105: {=INDEX(model!$N50:$AZ50,,MATCH('Financial Output'!L$10,model!$N$2:$AZ$2,0))} -> 114.42622 | M105: {=INDEX(model!$N50:$AZ50,,MATCH('Financial Output'!M$10,model!$N$2:$AZ$2,0))} -> 100.69507 | N105: {=INDEX(model!$N50:$AZ50,,MATCH('Financial Output'!N$10,model!$N$2:$AZ$2,0))} -> 109.75763 | O105: {=INDEX(model!$N50:$AZ50,,MATCH('Financial Output'!O$10,model!$N$2:$AZ$2,0))} -> 120.73339 | P105: {=INDEX(model!$N50:$AZ50,,MATCH('Financial Output'!P$10,model!$N$2:$AZ$2,0))} -> 132.80673
C106: Other Non-Cash Adjustments | E106: (US$m) | L106: =SUM(INDEX(model!$N51:$AZ54,,MATCH('Financial Output'!L$10,model!$N$2:$AZ$2,0))) -> 502.55114 | M106: =SUM(INDEX(model!$N51:$AZ54,,MATCH('Financial Output'!M$10,model!$N$2:$AZ$2,0))) -> 272.63973 | N106: =SUM(INDEX(model!$N51:$AZ54,,MATCH('Financial Output'!N$10,model!$N$2:$AZ$2,0))) -> 364.83845 | O106: =SUM(INDEX(model!$N51:$AZ54,,MATCH('Financial Output'!O$10,model!$N$2:$AZ$2,0))) -> 166.43723 | P106: =SUM(INDEX(model!$N51:$AZ54,,MATCH('Financial Output'!P$10,model!$N$2:$AZ$2,0))) -> 88.692423
C107: Change in Working Capital | E107: (US$m) | L107: {=INDEX(model!$N55:$AZ55,,MATCH('Financial Output'!L$10,model!$N$2:$AZ$2,0))} -> -364.20043 | M107: {=INDEX(model!$N55:$AZ55,,MATCH('Financial Output'!M$10,model!$N$2:$AZ$2,0))} -> -100.50215 | N107: {=INDEX(model!$N55:$AZ55,,MATCH('Financial Output'!N$10,model!$N$2:$AZ$2,0))} -> -95.922453 | O107: {=INDEX(model!$N55:$AZ55,,MATCH('Financial Output'!O$10,model!$N$2:$AZ$2,0))} -> -155.35012 | P107: {=INDEX(model!$N55:$AZ55,,MATCH('Financial Output'!P$10,model!$N$2:$AZ$2,0))} -> -142.21096
C109: Cash Generated from Operating Activities | E109: (US$m) | L109: =L104+L105+L106+L107 -> 498.55442 | M109: =M104+M105+M106+M107 -> 623.19303 | N109: =N104+N105+N106+N107 -> 810.15093 | O109: =O104+O105+O106+O107 -> 891.16603 | P109: =P104+P105+P106+P107 -> 980.28263
C111: Cash Generated from Investing Activities
C112: Capital Expenditure | E112: (US$m) | L112: {=INDEX(model!$N60:$AZ60,,MATCH('Financial Output'!L$10,model!$N$2:$AZ$2,0))} -> -137.31146 | M112: {=INDEX(model!$N60:$AZ60,,MATCH('Financial Output'!M$10,model!$N$2:$AZ$2,0))} -> -151.04261 | N112: {=INDEX(model!$N60:$AZ60,,MATCH('Financial Output'!N$10,model!$N$2:$AZ$2,0))} -> -164.63644 | O112: {=INDEX(model!$N60:$AZ60,,MATCH('Financial Output'!O$10,model!$N$2:$AZ$2,0))} -> -181.10009 | P112: {=INDEX(model!$N60:$AZ60,,MATCH('Financial Output'!P$10,model!$N$2:$AZ$2,0))} -> -199.21009
C113: Investments | E113: (US$m) | L113: {=INDEX(model!$N58:$AZ58,,MATCH('Financial Output'!L$10,model!$N$2:$AZ$2,0))} -> 0 | M113: {=INDEX(model!$N58:$AZ58,,MATCH('Financial Output'!M$10,model!$N$2:$AZ$2,0))} -> 0 | N113: {=INDEX(model!$N58:$AZ58,,MATCH('Financial Output'!N$10,model!$N$2:$AZ$2,0))} -> 0 | O113: {=INDEX(model!$N58:$AZ58,,MATCH('Financial Output'!O$10,model!$N$2:$AZ$2,0))} -> 0 | P113: {=INDEX(model!$N58:$AZ58,,MATCH('Financial Output'!P$10,model!$N$2:$AZ$2,0))} -> 0
C114: Other | E114: (US$m) | L114: {=INDEX(model!$N59:$AZ59,,MATCH('Financial Output'!L$10,model!$N$2:$AZ$2,0))} -> 0 | M114: {=INDEX(model!$N59:$AZ59,,MATCH('Financial Output'!M$10,model!$N$2:$AZ$2,0))} -> 0 | N114: {=INDEX(model!$N59:$AZ59,,MATCH('Financial Output'!N$10,model!$N$2:$AZ$2,0))} -> 0 | O114: {=INDEX(model!$N59:$AZ59,,MATCH('Financial Output'!O$10,model!$N$2:$AZ$2,0))} -> 0 | P114: {=INDEX(model!$N59:$AZ59,,MATCH('Financial Output'!P$10,model!$N$2:$AZ$2,0))} -> 0
C116: Cash Generated from Investing Activities | E116: (US$m) | L116: =L112+L113+L114 -> -137.31146 | M116: =M112+M113+M114 -> -151.04261 | N116: =N112+N113+N114 -> -164.63644 | O116: =O112+O113+O114 -> -181.10009 | P116: =P112+P113+P114 -> -199.21009
C118: Cash Generated from Financing Activities
C119: Debt Drawdowns and Repayments | E119: (US$m) | L119: {=INDEX(model!$N63:$AZ63,,MATCH('Financial Output'!L$10,model!$N$2:$AZ$2,0))} -> 0 | M119: {=INDEX(model!$N63:$AZ63,,MATCH('Financial Output'!M$10,model!$N$2:$AZ$2,0))} -> 0 | N119: {=INDEX(model!$N63:$AZ63,,MATCH('Financial Output'!N$10,model!$N$2:$AZ$2,0))} -> 0 | O119: {=INDEX(model!$N63:$AZ63,,MATCH('Financial Output'!O$10,model!$N$2:$AZ$2,0))} -> 0 | P119: {=INDEX(model!$N63:$AZ63,,MATCH('Financial Output'!P$10,model!$N$2:$AZ$2,0))} -> 0
C120: Accrued Interest | E120: (US$m) | L120: =SUM(INDEX(model!$N65:$AZ66,,MATCH('Financial Output'!L$10,model!$N$2:$AZ$2,0))) -> -50.454897 | M120: =SUM(INDEX(model!$N65:$AZ66,,MATCH('Financial Output'!M$10,model!$N$2:$AZ$2,0))) -> -55.123486 | N120: =SUM(INDEX(model!$N65:$AZ66,,MATCH('Financial Output'!N$10,model!$N$2:$AZ$2,0))) -> -59.74539 | O120: =SUM(INDEX(model!$N65:$AZ66,,MATCH('Financial Output'!O$10,model!$N$2:$AZ$2,0))) -> -61.721027 | P120: =SUM(INDEX(model!$N65:$AZ66,,MATCH('Financial Output'!P$10,model!$N$2:$AZ$2,0))) -> -63.532028
C121: Equity Issuance | E121: (US$m) | L121: {=INDEX(model!$N64:$AZ64,,MATCH('Financial Output'!L$10,model!$N$2:$AZ$2,0))} -> -278.86645 | M121: {=INDEX(model!$N64:$AZ64,,MATCH('Financial Output'!M$10,model!$N$2:$AZ$2,0))} -> -273.41977 | N121: {=INDEX(model!$N64:$AZ64,,MATCH('Financial Output'!N$10,model!$N$2:$AZ$2,0))} -> -268.02754 | O121: {=INDEX(model!$N64:$AZ64,,MATCH('Financial Output'!O$10,model!$N$2:$AZ$2,0))} -> -182.3893 | P121: {=INDEX(model!$N64:$AZ64,,MATCH('Financial Output'!P$10,model!$N$2:$AZ$2,0))} -> -180.27647
C123: Cash Generaded from Financing Activities | E123: (US$m) | L123: =L119+L120+L121 -> -329.32135 | M123: =M119+M120+M121 -> -328.54325 | N123: =N119+N120+N121 -> -327.77293 | O123: =O119+O120+O121 -> -244.11033 | P123: =P119+P120+P121 -> -243.8085
C125: Change in Cash | E125: (US$m) | L125: =L123+L116+L109 -> 31.921608 | M125: =M123+M116+M109 -> 143.60717 | N125: =N123+N116+N109 -> 317.74156 | O125: =O123+O116+O109 -> 465.95561 | P125: =P123+P116+P109 -> 537.26404
B127: 4 | C127: Charts | E127: Units
C129: Revenues
C146: EPS (Diluted) and Net Margin

Sheet Scenario Manager
B3: Market Rates | F3: =estimate_start -> 2025 | G3: =F3+1 -> 2026 | H3: =G3+1 -> 2027 | I3: =H3+1 -> 2028 | J3: =I3+1 -> 2029
C4: SOFR | F4: 0.0411 | G4: 0.0336 | H4: 0.0341 | I4: 0.0356 | J4: 0.0371
B9: Live Scenario
B10: Scenario Name | D10: Street
B11: # | D11: =IF(scenario_name = "Bear", 1, IF(scenario_name = "Street", 2, IF(scenario_name = "Bull", 3, ""))) -> 2
C14: Revenue Growth | F14: =CHOOSE(scenario_number,F39,F61,F83) -> 0.14 | G14: =CHOOSE(scenario_number,G39,G61,G83) -> 0.1 | H14: =CHOOSE(scenario_number,H39,H61,H83) -> 0.09 | I14: =CHOOSE(scenario_number,I39,I61,I83) -> 0.1 | J14: =CHOOSE(scenario_number,J39,J61,J83) -> 0.1
C15: COGS % of Rev | F15: =CHOOSE(scenario_number,F40,F62,F84) -> 0.58 | G15: =CHOOSE(scenario_number,G40,G62,G84) -> 0.56 | H15: =CHOOSE(scenario_number,H40,H62,H84) -> 0.55 | I15: =CHOOSE(scenario_number,I40,I62,I84) -> 0.5 | J15: =CHOOSE(scenario_number,J40,J62,J84) -> 0.5
C16: R&D % of Rev | F16: =CHOOSE(scenario_number,F41,F63,F85) -> 0.17 | G16: =CHOOSE(scenario_number,G41,G63,G85) -> 0.17 | H16: =CHOOSE(scenario_number,H41,H63,H85) -> 0.17 | I16: =CHOOSE(scenario_number,I41,I63,I85) -> 0.17 | J16: =CHOOSE(scenario_number,J41,J63,J85) -> 0.17
C17: SG&A % of Rev | F17: =CHOOSE(scenario_number,F42,F64,F86) -> 0.17 | G17: =CHOOSE(scenario_number,G42,G64,G86) -> 0.17 | H17: =CHOOSE(scenario_number,H42,H64,H86) -> 0.17 | I17: =CHOOSE(scenario_number,I42,I64,I86) -> 0.16 | J17: =CHOOSE(scenario_number,J42,J64,J86) -> 0.15
C18: D&A % of Rev | F18: =CHOOSE(scenario_number,F43,F65,F87) -> 0.025 | G18: =CHOOSE(scenario_number,G43,G65,G87) -> 0.02 | H18: =CHOOSE(scenario_number,H43,H65,H87) -> 0.02 | I18: =CHOOSE(scenario_number,I43,I65,I87) -> 0.02 | J18: =CHOOSE(scenario_number,J43,J65,J87) -> 0.02
C19: D&A % of CapEx | F19: =CHOOSE(scenario_number,F44,F66,F88) -> 1.2 | G19: =CHOOSE(scenario_number,G44,G66,G88) -> 1.2 | H19: =CHOOSE(scenario_number,H44,H66,H88) -> 1.2 | I19: =CHOOSE(scenario_number,I44,I66,I88) -> 1.2 | J19: =CHOOSE(scenario_number,J44,J66,J88) -> 1.2
C20: Int Exp % of Debt | F20: =CHOOSE(scenario_number,F45,F67,F89) -> 0.05 | G20: =CHOOSE(scenario_number,G45,G67,G89) -> 0.05 | H20: =CHOOSE(scenario_number,H45,H67,H89) -> 0.05 | I20: =CHOOSE(scenario_number,I45,I67,I89) -> 0.05 | J20: =CHOOSE(scenario_number,J45,J67,J89) -> 0.05
C21: Taxes % of EBIT | F21: =CHOOSE(scenario_number,F46,F68,F90) -> 0.25 | G21: =CHOOSE(scenario_number,G46,G68,G90) -> 0.25 | H21: =CHOOSE(scenario_number,H46,H68,H90) -> 0.25 | I21: =CHOOSE(scenario_number,I46,I68,I90) -> 0.25 | J21: =CHOOSE(scenario_number,J46,J68,J90) -> 0.25
C23: AR % of Rev | F23: =CHOOSE(scenario_number,F48,F70,F92) -> 0.25 | G23: =CHOOSE(scenario_number,G48,G70,G92) -> 0.2375 | H23: =CHOOSE(scenario_number,H48,H70,H92) -> 0.225625 | I23: =CHOOSE(scenario_number,I48,I70,I92) -> 0.21434375 | J23: =CHOOSE(scenario_number,J48,J70,J92) -> 0.20362656
C24: Inv % of Rev | F24: =CHOOSE(scenario_number,F49,F71,F93) -> 0.2 | G24: =CHOOSE(scenario_number,G49,G71,G93) -> 0.2 | H24: =CHOOSE(scenario_number,H49,H71,H93) -> 0.2 | I24: =CHOOSE(scenario_number,I49,I71,I93) -> 0.2 | J24: =CHOOSE(scenario_number,J49,J71,J93) -> 0.2
C25: OA % of Rev | F25: =CHOOSE(scenario_number,F50,F72,F94) -> 0.4 | G25: =CHOOSE(scenario_number,G50,G72,G94) -> 0.4 | H25: =CHOOSE(scenario_number,H50,H72,H94) -> 0.4 | I25: =CHOOSE(scenario_number,I50,I72,I94) -> 0.4 | J25: =CHOOSE(scenario_number,J50,J72,J94) -> 0.4
C26: CapEx | F26: =CHOOSE(scenario_number,F51,F73,F95) -> 0 | G26: =CHOOSE(scenario_number,G51,G73,G95) -> 0 | H26: =CHOOSE(scenario_number,H51,H73,H95) -> 0 | I26: =CHOOSE(scenario_number,I51,I73,I95) -> 0 | J26: =CHOOSE(scenario_number,J51,J73,J95) -> 0
... C33: SBC % of SG&A | F33: =CHOOSE(scenario_number,F58,F80,F102) -> 0.2 | G33: =CHOOSE(scenario_number,G58,G80,G102) -> 0.2 | H33: =CHOOSE(scenario_number,H58,H80,H102) -> 0.2 | I33: =CHOOSE(scenario_number,I58,I80,I102) -> 0.2 | J33: =CHOOSE(scenario_number,J58,J80,J102) -> 0.2
B38: Bear Case | D38: 1 | F38: =estimate_start -> 2025 | G38: =+F38+1 -> 2026 | H38: =+G38+1 -> 2027 | I38: =+H38+1 -> 2028 | J38: =+I38+1 -> 2029
C39: Revenue Growth | F39: 0.05 | G39: 0.05 | H39: 0.05 | I39: 0.05 | J39: 0.05
C40: COGS % of Rev | F40: 0.55 | G40: 0.55 | H40: 0.55 | I40: 0.55 | J40: 0.55
C41: R&D % of Rev | F41: 0.17 | G41: 0.17 | H41: 0.17 | I41: 0.17 | J41: 0.17
C42: SG&A % of Rev | F42: 0.2 | G42: 0.2 | H42: 0.2 | I42: 0.2 | J42: 0.2
C43: D&A % of Rev | F43: 0.04 | G43: 0.04 | H43: 0.04 | I43: 0.04 | J43: 0.04
C44: D&A % of CapEx | F44: 1.2 | G44: 1.2 | H44: 1.2 | I44: 1.2 | J44: 1.2
C45: Int Exp % of Debt | F45: 0.05 | G45: 0.05 | H45: 0.05 | I45: 0.05 | J45: 0.05
C46: Taxes % of EBIT | F46: 0.2 | G46: 0.2 | H46: 0.2 | I46: 0.2 | J46: 0.2
C48: AR % of Rev | F48: 0.25 | G48: 0.25 | H48: 0.25 | I48: 0.25 | J48: 0.25
C49: Inv % of Rev | F49: 0.2 | G49: 0.2 | H49: 0.2 | I49: 0.2 | J49: 0.2
C50: OA % of Rev | F50: 0.4 | G50: 0.4 | H50: 0.4 | I50: 0.4 | J50: 0.4
C51: CapEx
C52: CapEx % of Rev | F52: 0.03 | G52: 0.03 | H52: 0.03 | I52: 0.03 | J52: 0.03
C53: AP % of COGS | F53: 0.2 | G53: 0.2 | H53: 0.2 | I53: 0.2 | J53: 0.2
C54: AE % of OpEx | F54: 0.25 | G54: 0.25 | H54: 0.25 | I54: 0.25 | J54: 0.25
C55: OL % of Rev | F55: 0.04 | G55: 0.04 | H55: 0.04 | I55: 0.04 | J55: 0.04
C57: CFFO growth | F57: 0.03 | G57: 0.03 | H57: 0.03 | I57: 0.03 | J57: 0.03
C58: SBC % of SG&A | F58: 0.2 | G58: 0.2 | H58: 0.2 | I58: 0.2 | J58: 0.2
B60: Street Case | D60: 2 | F60: =estimate_start -> 2025 | G60: =+F60+1 -> 2026 | H60: =+G60+1 -> 2027 | I60: =+H60+1 -> 2028 | J60: =+I60+1 -> 2029
C61: Revenue Growth | F61: 0.14 | G61: 0.1 | H61: 0.09 | I61: 0.1 | J61: 0.1
C62: COGS % of Rev | F62: 0.58 | G62: 0.56 | H62: 0.55 | I62: 0.5 | J62: 0.5
C63: R&D % of Rev | F63: 0.17 | G63: 0.17 | H63: 0.17 | I63: 0.17 | J63: 0.17
C64: SG&A % of Rev | F64: 0.17 | G64: 0.17 | H64: 0.17 | I64: 0.16 | J64: 0.15
C65: D&A % of Rev | F65: 0.025 | G65: 0.02 | H65: 0.02 | I65: 0.02 | J65: 0.02
C66: D&A % of CapEx | F66: 1.2 | G66: 1.2 | H66: 1.2 | I66: 1.2 | J66: 1.2
C67: Int Exp % of Debt | F67: 0.05 | G67: 0.05 | H67: 0.05 | I67: 0.05 | J67: 0.05
C68: Taxes % of EBIT | F68: 0.25 | G68: 0.25 | H68: 0.25 | I68: 0.25 | J68: 0.25
C70: AR % of Rev | F70: 0.25 | G70: =F70*0.95 -> 0.2375 | H70: =G70*0.95 -> 0.225625 | I70: =H70*0.95 -> 0.21434375 | J70: =I70*0.95 -> 0.20362656
C71: Inv % of Rev | F71: 0.2 | G71: 0.2 | H71: 0.2 | I71: 0.2 | J71: 0.2
C72: OA % of Rev | F72: 0.4 | G72: 0.4 | H72: 0.4 | I72: 0.4 | J72: 0.4
C73: CapEx
C74: CapEx % of Rev | F74: 0.03 | G74: 0.03 | H74: 0.03 | I74: 0.03 | J74: 0.03
C75: AP % of COGS | F75: 0.1 | G75: 0.1 | H75: 0.1 | I75: 0.1 | J75: 0.1
C76: AE % of OpEx | F76: 0.25 | G76: 0.25 | H76: 0.25 | I76: 0.25 | J76: 0.25
C77: OL % of Rev | F77: 0.04 | G77: 0.04 | H77: 0.04 | I77: 0.04 | J77: 0.04
C79: CFFO growth | F79: -0.02 | G79: 0.25 | H79: 0.3 | I79: 0.1 | J79: 0.1
C80: SBC % of SG&A | F80: 0.2 | G80: 0.2 | H80: 0.2 | I80: 0.2 | J80: 0.2
B82: Bull Case | D82: 3 | F82: =estimate_start -> 2025 | G82: =+F82+1 -> 2026 | H82: =+G82+1 -> 2027 | I82: =+H82+1 -> 2028 | J82: =+I82+1 -> 2029
C83: Revenue Growth | F83: 0.05 | G83: 0.05 | H83: 0.05 | I83: 0.05 | J83: 0.05
C84: COGS % of Rev | F84: 0.55 | G84: 0.55 | H84: 0.55 | I84: 0.55 | J84: 0.55
C85: R&D % of Rev | F85: 0.17 | G85: 0.17 | H85: 0.17 | I85: 0.17 | J85: 0.17
C86: SG&A % of Rev | F86: 0.2 | G86: 0.2 | H86: 0.2 | I86: 0.2 | J86: 0.2
C87: D&A % of Rev | F87: 0.04 | G87: 0.04 | H87: 0.04 | I87: 0.04 | J87: 0.04
C88: D&A % of CapEx | F88: 1.2 | G88: 1.2 | H88: 1.2 | I88: 1.2 | J88: 1.2
C89: Int Exp % of Debt | F89: 0.05 | G89: 0.05 | H89: 0.05 | I89: 0.05 | J89: 0.05
C90: Taxes % of EBIT | F90: 0.2 | G90: 0.2 | H90: 0.2 | I90: 0.2 | J90: 0.2
C92: AR % of Rev | F92: 0.25 | G92: 0.25 | H92: 0.25 | I92: 0.25 | J92: 0.25
C93: Inv % of Rev | F93: 0.2 | G93: 0.2 | H93: 0.2 | I93: 0.2 | J93: 0.2
C94: OA % of Rev | F94: 0.4 | G94: 0.4 | H94: 0.4 | I94: 0.4 | J94: 0.4
C95: CapEx
C96: CapEx % of Rev | F96: 0.03 | G96: 0.03 | H96: 0.03 | I96: 0.03 | J96: 0.03
C97: AP % of COGS | F97: 0.1 | G97: 0.1 | H97: 0.1 | I97: 0.1 | J97: 0.1
C98: AE % of OpEx | F98: 0.25 | G98: 0.25 | H98: 0.25 | I98: 0.25 | J98: 0.25
C99: OL % of Rev | F99: 0.04 | G99: 0.04 | H99: 0.04 | I99: 0.04 | J99: 0.04
C101: CFFO growth | F101: 0.03 | G101: 0.03 | H101: 0.03 | I101: 0.03 | J101: 0.03
C102: SBC % of SG&A | F102: 0.2 | G102: 0.2 | H102: 0.2 | I102: 0.2 | J102: 0.2

Sheet model
B1: CIEN | N1: 42307 | O1: 42674 | P1: 43039 | Q1: 43404 | R1: 43769 | S1: 44134 | T1: 44498 | U1: 44865 | V1: 45230 | W1: 45596
N2: 2015 | O2: =N2+1 -> 2016 | P2: =O2+1 -> 2017 | Q2: =P2+1 -> 2018 | R2: =Q2+1 -> 2019 | S2: =R2+1 -> 2020 | T2: =S2+1 -> 2021 | U2: =T2+1 -> 2022 | V2: =U2+1 -> 2023 | ... AB2: =AA2+1 -> 2029
A3: x | B3: Revenue | N3: =IS_Static!D12 -> 2445.669 | O3: =IS_Static!E12 -> 2600.573 | P3: =IS_Static!F12 -> 2801.687 | Q3: =IS_Static!G12 -> 3094.286 | R3: =IS_Static!H12 -> 3572.131 | S3: =IS_Static!I12 -> 3532.157 | T3: =IS_Static!J12 -> 3620.684 | U3: =IS_Static!K12 -> 3632.661 | ... W3: =IS_Static!M12 -> 4014.955 | X3: =W3*(1+X77) -> 4577.0487 | Y3: =X3*(1+Y77) -> 5034.7536 | Z3: =Y3*(1+Z77) -> 5487.8814 | AA3: =Z3*(1+AA77) -> 6036.6695 | AB3: =AA3*(1+AB77) -> 6640.3365
B4: COGS | N4: =IS_Static!D15 -> -1370.106 | O4: =IS_Static!E15 -> -1438.997 | P4: =IS_Static!F15 -> -1555.901 | Q4: =IS_Static!G15 -> -1779.596 | R4: =IS_Static!H15 -> -2030.065 | S4: =IS_Static!I15 -> -1879.266 | T4: =IS_Static!J15 -> -1898.705 | U4: =IS_Static!K15 -> -2072.317 | ... W4: =IS_Static!M15 -> -2295.365 | X4: =-X3*X78 -> -2654.6882 | Y4: =-Y3*Y78 -> -2819.462 | Z4: =-Z3*Z78 -> -3018.3348 | AA4: =-AA3*AA78 -> -3018.3348 | AB4: =-AB3*AB78 -> -3320.1682
B5: Gross Profit | N5: =N3+N4 -> 1075.563 | O5: =O3+O4 -> 1161.576 | P5: =P3+P4 -> 1245.786 | Q5: =Q3+Q4 -> 1314.69 | R5: =R3+R4 -> 1542.066 | S5: =S3+S4 -> 1652.891 | T5: =T3+T4 -> 1721.979 | U5: =U3+U4 -> 1560.344 | ... AB5: =AB3+AB4 -> 3320.1682
B6: S&M | N6: =IS_Static!D21 -> -333.836 | O6: =IS_Static!E21 -> -349.731 | P6: =IS_Static!F21 -> -356.169 | Q6: =IS_Static!G21 -> -394.06 | R6: =IS_Static!H21 -> -423.046 | S6: =IS_Static!I21 -> -416.425 | T6: =IS_Static!J21 -> -452.214 | U6: =IS_Static!K21 -> -466.565 | ... W6: =IS_Static!M21 -> -510.668 | X6: =-X3*X80*(W6/(W6+W8)) -> -543.33617 | Y6: =-Y3*Y80*(X6/(X6+X8)) -> -597.66979 | Z6: =-Z3*Z80*(Y6/(Y6+Y8)) -> -651.46007 | AA6: =-AA3*AA80*(Z6/(Z6+Z8)) -> -674.45278 | AB6: =-AB3*AB80*(AA6/(AA6+AA8)) -> -695.52943
B7: R&D | N7: =IS_Static!D20 -> -414.201 | O7: =IS_Static!E20 -> -451.794 | P7: =IS_Static!F20 -> -475.329 | Q7: =IS_Static!G20 -> -491.564 | R7: =IS_Static!H20 -> -548.139 | S7: =IS_Static!I20 -> -529.888 | T7: =IS_Static!J20 -> -536.666 | U7: =IS_Static!K20 -> -624.656 | ... W7: =IS_Static!M20 -> -767.497 | X7: =-X79*X3 -> -778.09828 | Y7: =-Y79*Y3 -> -855.90811 | Z7: =-Z79*Z3 -> -932.93984 | AA7: =-AA79*AA3 -> -1026.2338 | AB7: =-AB79*AB3 -> -1128.8572
B8: G&A | N8: =IS_Static!D22 -> -148.941 | O8: =IS_Static!E22 -> -137.441 | P8: =IS_Static!F22 -> -142.604 | Q8: =IS_Static!G22 -> -165.244 | R8: =IS_Static!H22 -> -177.769 | S8: =IS_Static!I22 -> -173.579 | T8: =IS_Static!J22 -> -184.446 | U8: =IS_Static!K22 -> -179.98 | ... W8: =IS_Static!M22 -> -220.647 | X8: =-X3*X80*(W8/(W6+W8)) -> -234.76211 | Y8: =-Y3*Y80*(X8/(X6+X8)) -> -258.23832 | Z8: =-Z3*Z80*(Y8/(Y6+Y8)) -> -281.47977 | AA8: =-AA3*AA80*(Z8/(Z6+Z8)) -> -291.41435 | AB8: =-AB3*AB80*(AA8/(AA6+AA8)) -> -300.52105
B9: Operating Expenses | N9: =N8+N7+N6 -> -896.978 | O9: =O8+O7+O6 -> -938.966 | P9: =P8+P7+P6 -> -974.102 | Q9: =Q8+Q7+Q6 -> -1050.868 | R9: =R8+R7+R6 -> -1148.954 | S9: =S8+S7+S6 -> -1119.892 | T9: =T8+T7+T6 -> -1173.326 | U9: =U8+U7+U6 -> -1271.201 | ... W9: =W8+W7+W6 -> -1498.812 | X9: =+X8+X7+X6 -> -1556.1966 | Y9: =+Y8+Y7+Y6 -> -1711.8162 | Z9: =+Z8+Z7+Z6 -> -1865.8797 | AA9: =+AA8+AA7+AA6 -> -1992.1009 | AB9: =+AB8+AB7+AB6 -> -2124.9077
B10: Operating Income | N10: =N5+N9 -> 178.585 | O10: =O5+O9 -> 222.61 | P10: =P5+P9 -> 271.684 | Q10: =Q5+Q9 -> 263.822 | R10: =R5+R9 -> 393.112 | S10: =S5+S9 -> 532.999 | T10: =T5+T9 -> 548.653 | U10: =U5+U9 -> 289.143 | ... W10: =W5+W9 -> 220.778 | X10: =X9+X5 -> 366.1639 | Y10: =Y9+Y5 -> 503.47536 | Z10: =Z9+Z5 -> 603.66695 | AA10: =AA9+AA5 -> 1026.2338 | AB10: =AB9+AB5 -> 1195.2606
B11: Interest Exp, net | N11: =IS_Static!D33+IS_Static!D36 -> -76.684 | O11: =IS_Static!E33+IS_Static!E36 -> -69.451 | P11: =IS_Static!F33+IS_Static!F36 -> -58.596 | Q11: =IS_Static!G33+IS_Static!G36 -> -81.165 | R11: =IS_Static!H33+IS_Static!H36 -> -33.576 | S11: =IS_Static!I33+IS_Static!I36 -> -31.003 | T11: =IS_Static!J33+IS_Static!J36 -> -32.605 | U11: =IS_Static!K33+IS_Static!K36 -> -40.303 | ... W11: =IS_Static!M33+IS_Static!M36 -> -46.767 | X11: =X129+X107 -> -38.460574 | Y11: =Y129+Y107 -> -36.328192 | Z11: =Z129+Z107 -> -28.363881 | AA11: =AA129+AA107 -> -13.773113 | AB11: =AB129+AB107 -> 6.0653429
B12: Pretax Income | N12: =N10+N11 -> 101.901 | O12: =O10+O11 -> 153.159 | P12: =P10+P11 -> 213.088 | Q12: =Q10+Q11 -> 182.657 | R12: =R10+R11 -> 359.536 | S12: =S10+S11 -> 501.996 | T12: =T10+T11 -> 516.048 | U12: =U10+U11 -> 248.84 | ... AB12: =AB10+AB11 -> 1201.3259
B13: Taxes | N13: =IS_Static!D42 -> -12.097 | O13: =IS_Static!E42 -> -14.134 | P13: =IS_Static!F42 -> 1105.827 | Q13: =IS_Static!G42 -> -493.471 | R13: =IS_Static!H42 -> -59.756 | S13: =IS_Static!I42 -> -94.67 | T13: =IS_Static!J42 -> 37.445 | U13: =IS_Static!K42 -> -29.603 | ... W13: =IS_Static!M42 -> -35.894 | X13: =X12*-X84 -> -81.92583 | Y13: =Y12*-Y84 -> -116.78679 | Z13: =Z12*-Z84 -> -143.82577 | AA13: =AA12*-AA84 -> -253.11518 | AB13: =AB12*-AB84 -> -300.33148
B14: Net Income | N14: =N12+N13 -> 89.804 | O14: =O12+O13 -> 139.025 | P14: =P12+P13 -> 1318.915 | Q14: =Q12+Q13 -> -310.814 | R14: =R12+R13 -> 299.78 | S14: =S12+S13 -> 407.326 | T14: =T12+T13 -> 553.493 | U14: =U12+U13 -> 219.237 | ... AB14: =AB12+AB13 -> 900.99443
B15: EPS | N15: =N14/N16 -> 0.74773732 | O15: =O14/O16 -> 0.92250372 | P15: =P14/P16 -> 7.7620219 | Q15: =Q14/Q16 -> -2.1623649 | R15: =R14/R16 -> 1.9020125 | S15: =S14/S16 -> 2.6118175 | T15: =T14/T16 -> 3.5312135 | U15: =U14/U16 -> 1.4405196 | ... AB15: =AB14/AB16 -> 6.1711947
B16: Shares | N16: =IS_Static!D49 -> 120.101 | O16: =IS_Static!E49 -> 150.704 | P16: =IS_Static!F49 -> 169.919 | Q16: =IS_Static!G49 -> 143.738 | R16: =IS_Static!H49 -> 157.612 | S16: =IS_Static!I49 -> 155.955 | T16: =IS_Static!J49 -> 156.743 | U16: =IS_Static!K49 -> 152.193 | ... W16: =IS_Static!M49 -> 145.964 | X16: 146 | Y16: 146 | Z16: 146 | AA16: 146 | AB16: 146
B18: EBIT | N18: =N10 -> 178.585 | O18: =O10 -> 222.61 | P18: =P10 -> 271.684 | Q18: =Q10 -> 263.822 | R18: =R10 -> 393.112 | S18: =S10 -> 532.999 | T18: =T10 -> 548.653 | U18: =U10 -> 289.143 | ... AB18: =AB10 -> 1195.2606
B19: EBITDA | N19: =N18+N50 -> 314.352 | O19: =O18+O50 -> 364.302 | P19: =P18+P50 -> 394.586 | Q19: =Q18+Q50 -> 373.842 | R19: =R18+R50 -> 515.824 | S19: =S18+S50 -> 665.526 | T19: =T18+T50 -> 680.919 | U19: =U18+U50 -> 429.346 | ... AB19: =AB18+AB50 -> 1328.0673
B20: % of sales | N20: =N19/N3 -> 0.12853416 | O20: =O19/O3 -> 0.14008528 | P20: =P19/P3 -> 0.14083872 | Q20: =Q19/Q3 -> 0.12081689 | R20: =R19/R3 -> 0.14440232 | S20: =S19/S3 -> 0.18841914 | T20: =T19/T3 -> 0.18806364 | U20: =U19/U3 -> 0.11819049 | ... AB20: =AB19/AB3 -> 0.2
B22: Net Cash
B23: Cash | N23: =BS_Static!D14+BS_Static!D15 -> 926.078 | O23: =BS_Static!E14+BS_Static!E15 -> 1052.863 | P23: =BS_Static!F14+BS_Static!F15 -> 919.646 | Q23: =BS_Static!G14+BS_Static!G15 -> 894.404 | R23: =BS_Static!H14+BS_Static!H15 -> 1013.985 | S23: =BS_Static!I14+BS_Static!I15 -> 1239.291 | T23: =BS_Static!J14+BS_Static!J15 -> 1604.029 | U23: =BS_Static!K14+BS_Static!K15 -> 1148.341 | ... W23: =BS_Static!M14+BS_Static!M15 -> 1251.206 | X23: =W23+X69 -> 1283.1276 | Y23: =X23+Y69 -> 1426.7348 | Z23: =Y23+Z69 -> 1744.4763 | AA23: =Z23+AA69 -> 2210.4319 | AB23: =AA23+AB69 -> 2747.696
B24: AR | N24: =BS_Static!D16 -> 550.792 | O24: =BS_Static!E16 -> 576.235 | P24: =BS_Static!F16 -> 622.183 | Q24: =BS_Static!G16 -> 786.502 | R24: =BS_Static!H16 -> 724.854 | S24: =BS_Static!I16 -> 719.405 | T24: =BS_Static!J16 -> 884.958 | U24: =BS_Static!K16 -> 920.772 | ... W24: =BS_Static!M16 -> 908.597 | X24: =X87*X3 -> 1144.2622 | Y24: =Y87*Y3 -> 1195.754 | Z24: =Z87*Z3 -> 1238.2032 | AA24: =AA87*AA3 -> 1293.9224 | AB24: =AB87*AB3 -> 1352.1489
B25: Inventory | N25: =BS_Static!D17 -> 191.162 | O25: =BS_Static!E17 -> 211.251 | P25: =BS_Static!F17 -> 267.143 | Q25: =BS_Static!G17 -> 262.751 | R25: =BS_Static!H17 -> 345.049 | S25: =BS_Static!I17 -> 344.379 | T25: =BS_Static!J17 -> 374.265 | U25: =BS_Static!K17 -> 946.73 | ... W25: =BS_Static!M17 -> 820.43 | X25: =X3*X88 -> 915.40974 | Y25: =Y3*Y88 -> 1006.9507 | Z25: =Z3*Z88 -> 1097.5763 | AA25: =AA3*AA88 -> 1207.3339 | AB25: =AB3*AB88 -> 1328.0673
B26: Prepaids | N26: =BS_Static!D18 -> 196.178 | O26: =BS_Static!E18 -> 172.843 | P26: =BS_Static!F18 -> 197.339 | Q26: =BS_Static!G18 -> 198.945 | R26: =BS_Static!H18 -> 297.914 | S26: =BS_Static!I18 -> 308.084 | T26: =BS_Static!J18 -> 325.654 | U26: =BS_Static!K18 -> 370.053 | ... W26: =BS_Static!M18 -> 564.183 | X26: =X$89*X$3*(W26/(W$26+W$32+W$33)) -> 643.43465 | Y26: =Y$89*Y$3*(X26/(X$26+X$32+X$33)) -> 707.77812 | Z26: =Z$89*Z$3*(Y26/(Y$26+Y$32+Y$33)) -> 771.47815 | AA26: =AA$89*AA$3*(Z26/(Z$26+Z$32+Z$33)) -> 848.62596 | AB26: =AB$89*AB$3*(AA26/(AA$26+AA$32+AA$33)) -> 933.48856
B27: LT Investments | N27: =BS_Static!D19 -> 95.105 | O27: =BS_Static!E19 -> 90.172 | P27: =BS_Static!F19 -> 49.783 | Q27: =BS_Static!G19 -> 58.97 | R27: =BS_Static!H19 -> 10.014 | S27: =BS_Static!I19 -> 82.226 | T27: =BS_Static!J19 -> 70.038 | U27: =BS_Static!K19 -> 35.385 | ... W27: =BS_Static!M19 -> 80.92 | X27: 81 | Y27: 81 | Z27: 81 | AA27: 81 | AB27: 81
B28: PP&E | N28: =BS_Static!D20 -> 191.973 | O28: =BS_Static!E20 -> 288.406 | P28: =BS_Static!F20 -> 308.465 | Q28: =BS_Static!G20 -> 292.067 | R28: =BS_Static!H20 -> 286.884 | S28: =BS_Static!I20 -> 272.377 | T28: =BS_Static!J20 -> 284.968 | U28: =BS_Static!K20 -> 267.779 | ... W28: =BS_Static!M20 -> 337.722 | X28: =W28-X60-X50 -> 360.60724 | Y28: =X28-Y60-Y50 -> 410.95478 | Z28: =Y28-Z60-Z50 -> 465.83359 | AA28: =Z28-AA60-AA50 -> 526.20029 | AB28: =AA28-AB60-AB50 -> 592.60365
B29: Leases | N29: =BS_Static!D21 -> - | O29: =BS_Static!E21 -> - | P29: =BS_Static!F21 -> - | Q29: =BS_Static!G21 -> - | R29: =BS_Static!H21 -> 0 | S29: =BS_Static!I21 -> 57.026 | T29: =BS_Static!J21 -> 44.285 | U29: =BS_Static!K21 -> 45.108 | ... W29: =BS_Static!M21 -> 27.417 | X29: 35 | Y29: 35 | Z29: 35 | AA29: 35 | AB29: 35
B30: Goodwill | N30: =BS_Static!D22 -> 256.434 | O30: =BS_Static!E22 -> 266.974 | P30: =BS_Static!F22 -> 267.458 | Q30: =BS_Static!G22 -> 297.968 | R30: =BS_Static!H22 -> 297.937 | S30: =BS_Static!I22 -> 310.847 | T30: =BS_Static!J22 -> 311.645 | U30: =BS_Static!K22 -> 328.322 | ... W30: =BS_Static!M22 -> 444.707 | X30: 445 | Y30: 445 | Z30: 445 | AA30: 445 | AB30: 445
B31: Other Intangible | N31: =BS_Static!D23 -> 202.673 | O31: =BS_Static!E23 -> 146.711 | P31: =BS_Static!F23 -> 100.997 | Q31: =BS_Static!G23 -> 148.225 | R31: =BS_Static!H23 -> 112.781 | S31: =BS_Static!I23 -> 96.647 | T31: =BS_Static!J23 -> 65.314 | U31: =BS_Static!K23 -> 69.517 | ... W31: =BS_Static!M23 -> 165.02 | X31: 165 | Y31: 165 | Z31: 165 | AA31: 165 | AB31: 165
B32: Deferred Taxes | N32: =BS_Static!D25 -> 0 | O32: =BS_Static!E25 -> 1.116 | P32: =BS_Static!F25 -> 1155.104 | Q32: =BS_Static!G25 -> 745.039 | R32: =BS_Static!H25 -> 714.942 | S32: =BS_Static!I25 -> 647.805 | T32: =BS_Static!J25 -> 800.18 | U32: =BS_Static!K25 -> 824.008 | ... W32: =BS_Static!M25 -> 886.441 | X32: =X$89*X$3*(W32/(W$26+W$32+W$33)) -> 1010.9607 | Y32: =Y$89*Y$3*(X32/(X$26+X$32+X$33)) -> 1112.0568 | Z32: =Z$89*Z$3*(Y32/(Y$26+Y$32+Y$33)) -> 1212.1419 | AA32: =AA$89*AA$3*(Z32/(Z$26+Z$32+Z$33)) -> 1333.3561 | AB32: =AB$89*AB$3*(AA32/(AA$26+AA$32+AA$33)) -> 1466.6917
B33: Other Assets | N33: =BS_Static!D24 -> 84.656 | O33: =BS_Static!E26 -> 67.004 | P33: =BS_Static!F26 -> 63.593 | Q33: =BS_Static!G26 -> 71.652 | R33: =BS_Static!H26 -> 88.986 | S33: =BS_Static!I26 -> 102.83 | T33: =BS_Static!J26 -> 99.891 | U33: =BS_Static!K26 -> 113.617 | V33: =BS_Static!L26 -> 116.453 | W33: =BS_Static!M26 -> 154.694 | X33: =X$89*X$3*(W33/(W$26+W$32+W$33)) -> 176.4241 | Y33: =Y$89*Y$3*(X33/(X$26+X$32+X$33)) -> 194.06651 | Z33: =Z$89*Z$3*(Y33/(Y$26+Y$32+Y$33)) -> 211.5325 | AA33: =AA$89*AA$3*(Z33/(Z$26+Z$32+Z$33)) -> 232.68575 | AB33: =AB$89*AB$3*(AA33/(AA$26+AA$32+AA$33)) -> 255.95432
B34: Assets | N34: =SUM(N23:N33) -> 2695.051 | O34: =SUM(O23:O33) -> 2873.575 | P34: =SUM(P23:P33) -> 3951.711 | Q34: =SUM(Q23:Q33) -> 3756.523 | R34: =SUM(R23:R33) -> 3893.346 | S34: =SUM(S23:S33) -> 4180.917 | T34: =SUM(T23:T33) -> 4865.227 | U34: =SUM(U23:U33) -> 5069.632 | ... AB34: =SUM(AB23:AB33) -> 9402.6504
B36: AP | N36: =BS_Static!D30 -> 222.14 | O36: =BS_Static!E30 -> 235.942 | P36: =BS_Static!F30 -> 260.098 | Q36: =BS_Static!G30 -> 340.582 | R36: =BS_Static!H30 -> 344.819 | S36: =BS_Static!I30 -> 291.904 | T36: =BS_Static!J30 -> 356.176 | U36: =BS_Static!K30 -> 516.047 | ... W36: =BS_Static!M30 -> 423.401 | X36: =-X92*X4 -> 265.46882 | Y36: =-Y92*Y4 -> 281.9462 | Z36: =-Z92*Z4 -> 301.83348 | AA36: =-AA92*AA4 -> 301.83348 | AB36: =-AB92*AB4 -> 332.01682
B37: Accurred Expenses | N37: =BS_Static!D31 -> 316.283 | O37: =BS_Static!E31 -> 310.353 | P37: =BS_Static!F31 -> 322.934 | Q37: =BS_Static!G31 -> 340.075 | R37: =BS_Static!H31 -> 382.74 | S37: =BS_Static!I31 -> 334.132 | T37: =BS_Static!J31 -> 409.285 | U37: =BS_Static!K31 -> 360.782 | ... W37: =BS_Static!M31 -> 393.905 | X37: =X9*-X93 -> 389.04914 | Y37: =Y9*-Y93 -> 427.95405 | Z37: =Z9*-Z93 -> 466.46992 | AA37: =AA9*-AA93 -> 498.02524 | AB37: =AB9*-AB93 -> 531.22692
B38: Debt | N38: =BS_Static!D40+BS_Static!D49 -> 1274.139 | O38: =BS_Static!E40+BS_Static!E49 -> 1253.682 | P38: =BS_Static!F40+BS_Static!F49 -> 935.981 | Q38: =BS_Static!G40+BS_Static!G49+BS_Static!G41 -> 857.662 | R38: =BS_Static!H40+BS_Static!H49 -> 687.406 | S38: =BS_Static!I40+BS_Static!I49 -> 683.286 | T38: =BS_Static!J40+BS_Static!J49 -> 677.285 | U38: =BS_Static!K40+BS_Static!K49 -> 1068.055 | V38: =BS_Static!L40+BS_Static!L49 -> 1555.106 | W38: =BS_Static!M40+BS_Static!M49 -> 1544.774 | X38: =X123 -> 1558.3 | Y38: =Y123 -> 1558.3 | Z38: =Z123 -> 1558.3 | AA38: =AA123 -> 1558.3 | AB38: =AB123 -> 1558.3
B39: Deferred Rev | N39: =BS_Static!D36+BS_Static!D42 -> 189.073 | O39: =BS_Static!E36+BS_Static!E42 -> 182.863 | P39: =BS_Static!F36+BS_Static!F42 -> 185.007 | Q39: =BS_Static!G36+BS_Static!G42 -> 169.457 | R39: =BS_Static!H36+BS_Static!H42 -> 156.873 | S39: =BS_Static!I36+BS_Static!I42 -> 158.363 | T39: =BS_Static!J36+BS_Static!J42 -> 175.464 | U39: =BS_Static!K36+BS_Static!K42 -> 200.235 | ... W39: =BS_Static!M36+BS_Static!M42 -> 237.619 | X39: 200 | Y39: 200 | Z39: 200 | AA39: 200 | AB39: 200
B40: Lease | N40: =BS_Static!D39+BS_Static!D48 -> 0 | O40: =BS_Static!E39+BS_Static!E48 -> 0 | P40: =BS_Static!F39+BS_Static!F48 -> 0 | Q40: =BS_Static!G39+BS_Static!G48 -> 0 | R40: =BS_Static!H39+BS_Static!H48 -> 0 | S40: =BS_Static!I39+BS_Static!I48 -> 80.45 | T40: =BS_Static!J39+BS_Static!J48 -> 60.196 | U40: =BS_Static!K39+BS_Static!K48 -> 61.317 | ... W40: =BS_Static!M39+BS_Static!M48 -> 39.562 | X40: 50 | Y40: 50 | Z40: 50 | AA40: 50 | AB40: 50
B41: Other Liabilities | N41: =BS_Static!D44 -> 72.54 | O41: =BS_Static!E44 -> 124.394 | P41: =BS_Static!F44 -> 111.349 | Q41: =BS_Static!G44 -> 119.413 | R41: =BS_Static!H44 -> 148.747 | S41: =BS_Static!I44 -> 123.185 | T41: =BS_Static!J44 -> 166.803 | U41: =BS_Static!K44 -> 150.335 | ... W41: =BS_Static!M44 -> 185.938 | X41: =X94*X3 -> 183.08195 | Y41: =Y94*Y3 -> 201.39014 | Z41: =Z94*Z3 -> 219.51526 | AA41: =AA94*AA3 -> 241.46678 | AB41: =AB94*AB3 -> 265.61346
B42: Retained Earnings | N42: =BS_Static!D57 -> -5998.79 | O42: =BS_Static!E57 -> -5926.206 | P42: =BS_Static!F57 -> -4664.253 | Q42: =BS_Static!G57 -> -4947.652 | R42: =BS_Static!H57 -> -4644.413 | S42: =BS_Static!I57 -> -4283.122 | T42: =BS_Static!J57 -> -3785.132 | U42: =BS_Static!K57 -> -3632.23 | ... W42: =BS_Static!M57 -> -3293.447 | X42: =W42+X14 -> -3047.6695 | Y42: =X42+Y14 -> -2697.3091 | Z42: =Y42+Z14 -> -2265.8318 | AA42: =Z42+AA14 -> -1506.4863 | AB42: =AA42+AB14 -> -605.49187
B43: Total Paid in Capital | N43: =BS_Static!D51+BS_Static!D52+BS_Static!D53 -> 6641.792 | O43: =BS_Static!E51+BS_Static!E52+BS_Static!E53 -> 6716.876 | P43: =BS_Static!F51+BS_Static!F52+BS_Static!F53 -> 6811.612 | Q43: =BS_Static!G51+BS_Static!G52+BS_Static!G53 -> 6882.766 | R43: =BS_Static!H51+BS_Static!H52+BS_Static!H53 -> 6839.258 | S43: =BS_Static!I51+BS_Static!I52+BS_Static!I53 -> 6828.077 | T43: =BS_Static!J51+BS_Static!J52+BS_Static!J53 -> 6804.711 | U43: =BS_Static!K51+BS_Static!K52+BS_Static!K53 -> 6391.736 | ... W43: =BS_Static!M51+BS_Static!M52+BS_Static!M53 -> 6156.296 | X43: =X142 -> 5983.2243 | Y43: =Y142 -> 5829.6317 | Z43: =Z142 -> 5692.2157 | AA43: =AA142 -> 5645.0478 | AB43: =AB142 -> 5604.2184
B44: AOCI | N44: =BS_Static!D54 -> -22.126 | O44: =BS_Static!E54 -> -24.329 | P44: =BS_Static!F54 -> -11.017 | Q44: =BS_Static!G54 -> -5.78 | R44: =BS_Static!H54 -> -22.084 | S44: =BS_Static!I54 -> -35.358 | T44: =BS_Static!J54 -> 0.439 | U44: =BS_Static!K54 -> -46.645 | ... W44: =BS_Static!M54 -> -46.711 | X44: -20 | Y44: -20 | Z44: -20 | AA44: -20 | AB44: -20
B45: L+SE | N45: =SUM(N36:N44) -> 2695.051 | O45: =SUM(O36:O44) -> 2873.575 | P45: =SUM(P36:P44) -> 3951.711 | Q45: =SUM(Q36:Q44) -> 3756.523 | R45: =SUM(R36:R44) -> 3893.346 | S45: =SUM(S36:S44) -> 4180.917 | T45: =SUM(T36:T44) -> 4865.227 | U45: =SUM(U36:U44) -> 5069.632 | ... AB45: =SUM(AB36:AB44) -> 7915.8837
B46: check | N46: =N34-N45 -> 0 | O46: =O34-O45 -> 0 | P46: =P34-P45 -> 0 | Q46: =Q34-Q45 -> 0 | R46: =R34-R45 -> 0 | S46: =S34-S45 -> 0 | T46: =T34-T45 -> 0 | U46: =U34-U45 -> 0 | ... AB46: =AB34-AB45 -> 1486.7667
B48: Model NI | N48: =N14 -> 89.804 | O48: =O14 -> 139.025 | P48: =P14 -> 1318.915 | Q48: =Q14 -> -310.814 | R48: =R14 -> 299.78 | S48: =S14 -> 407.326 | T48: =T14 -> 553.493 | U48: =U14 -> 219.237 | ... AB48: =AB14 -> 900.99443
B49: Reported NI | N49: =IS_Static!D43 -> 11.667 | O49: =IS_Static!E43 -> 72.584 | P49: =IS_Static!F43 -> 1261.953 | Q49: =IS_Static!G43 -> -344.69 | R49: =IS_Static!H43 -> 253.434 | S49: =IS_Static!I43 -> 361.291 | T49: =IS_Static!J43 -> 500.196 | U49: =IS_Static!K43 -> 152.902 | ... W49: =IS_Static!M43 -> 83.956 | X49: 0 | Y49: 0 | Z49: 0 | AA49: 0 | AB49: 0
B50: D&A | N50: =CF_Static!D23+CF_Static!D20 -> 135.767 | O50: =CF_Static!E23+CF_Static!E20 -> 141.692 | P50: =CF_Static!F23+CF_Static!F20 -> 122.902 | Q50: =CF_Static!G23+CF_Static!G20 -> 110.02 | R50: =CF_Static!H23+CF_Static!H20 -> 122.712 | S50: =CF_Static!I23+CF_Static!I20 -> 132.527 | T50: =CF_Static!J23+CF_Static!J20 -> 132.266 | U50: =CF_Static!K23+CF_Static!K20 -> 140.203 | ... W50: =CF_Static!M23+CF_Static!M20 -> 133.47 | X50: =X3*X81 -> 114.42622 | Y50: =Y3*Y81 -> 100.69507 | Z50: =Z3*Z81 -> 109.75763 | AA50: =AA3*AA81 -> 120.73339 | AB50: =AB3*AB81 -> 132.80673
B51: Share Based Comp | N51: =CF_Static!D21 -> 55.34 | O51: =CF_Static!E21 -> 51.993 | P51: =CF_Static!F21 -> 48.36 | Q51: =CF_Static!G21 -> 52.972 | R51: =CF_Static!H21 -> 59.736 | S51: =CF_Static!I21 -> 67.758 | T51: =CF_Static!J21 -> 84.336 | U51: =CF_Static!K21 -> 105.131 | ... W51: =CF_Static!M21 -> 156.404 | X51: =X98*-(X6+X8) -> 155.61966 | Y51: =Y98*-(Y6+Y8) -> 171.18162 | Z51: =Z98*-(Z6+Z8) -> 186.58797 | AA51: =AA98*-(AA6+AA8) -> 193.17342 | AB51: =AB98*-(AB6+AB8) -> 199.21009
B52: Lease Adj. | N52: =CF_Static!D41+CF_Static!D46 -> 0 | O52: =CF_Static!E41+CF_Static!E46 -> 0 | P52: =CF_Static!F41+CF_Static!F46 -> 0 | Q52: =CF_Static!G41+CF_Static!G46 -> 0 | R52: =CF_Static!H41+CF_Static!H46 -> 0 | S52: =CF_Static!I41+CF_Static!I46 -> -3.109 | T52: =CF_Static!J41+CF_Static!J46 -> -5.472 | U52: =CF_Static!K41+CF_Static!K46 -> -3.643 | ... W52: =CF_Static!M41+CF_Static!M46 -> -5.803 | X52: -5 | Y52: -5 | Z52: -5 | AA52: -5 | AB52: -5
B53: Other | N53: =CF_Static!D24 -> 27.373 | O53: =CF_Static!E24 -> 25.514 | P53: =CF_Static!F24 -> -1086.094 | Q53: =CF_Static!G24 -> 488.016 | R53: =CF_Static!H24 -> 25.695 | S53: =CF_Static!I24 -> 84.822 | T53: =CF_Static!J24 -> -141.944 | U53: =CF_Static!K24 -> -27.502 | ... W53: =CF_Static!M24 -> -65.042 | X53: 0 | Y53: 0 | Z53: 0 | AA53: 0 | AB53: 0
B54: Provisions | N54: =CF_Static!D35+CF_Static!D36 -> 44.727 | O54: =CF_Static!E35+CF_Static!E36 -> 49.196 | P54: =CF_Static!F35+CF_Static!F36 -> 43.424 | Q54: =CF_Static!G35+CF_Static!G36 -> 51.607 | R54: =CF_Static!H35+CF_Static!H36 -> 51.19 | S54: =CF_Static!I35+CF_Static!I36 -> 47.118 | T54: =CF_Static!J35+CF_Static!J36 -> 34.943 | U54: =CF_Static!K35+CF_Static!K36 -> 33.624 | ... W54: =CF_Static!M35+CF_Static!M36 -> 102.984 | X54: =-(X48+X49+X50+X51+X52+X53+X55-X56) -> 351.93148 | Y54: =-(Y48+Y49+Y50+Y51+Y52+Y53+Y55-Y56) -> 106.45811 | Z54: =-(Z48+Z49+Z50+Z51+Z52+Z53+Z55-Z56) -> 183.25049 | AA54: =-(AA48+AA49+AA50+AA51+AA52+AA53+AA55-AA56) -> -21.736196 | AB54: =-(AB48+AB49+AB50+AB51+AB52+AB53+AB55-AB56) -> -105.51767
B55: WC | N55: =CF_Static!D37 -> -12.762 | O55: =CF_Static!E37 -> -51.459 | P55: =CF_Static!F37 -> -155.663 | Q55: =CF_Static!G37 -> -150.773 | R55: =CF_Static!H37 -> -99.627 | S55: =CF_Static!I37 -> -199.862 | T55: =CF_Static!J37 -> -68.151 | U55: =CF_Static!K37 -> -572.114 | ... W55: =CF_Static!M37 -> 102.76 | X55: =W25-X25+W26-X26+X36-W36+X37-W37+X39-W39+X40-W40 -> -364.20043 | Y55: =X25-Y25+X26-Y26+Y36-X36+Y37-X37+Y39-X39+Y40-X40 -> -100.50215 | Z55: =Y25-Z25+Y26-Z26+Z36-Y36+Z37-Y37+Z39-Y39+Z40-Y40 -> -95.922453 | AA55: =Z25-AA25+Z26-AA26+AA36-Z36+AA37-Z37+AA39-Z39+AA40-Z40 -> -155.35012 | AB55: =AA25-AB25+AA26-AB26+AB36-AA36+AB37-AA37+AB39-AA39+AB40-AA40 -> -142.21096
B56: CFFO | N56: =SUM(N49:N55) -> 262.112 | O56: =SUM(O49:O55) -> 289.52 | P56: =SUM(P49:P55) -> 234.882 | Q56: =SUM(Q49:Q55) -> 207.152 | R56: =SUM(R49:R55) -> 413.14 | S56: =SUM(S49:S55) -> 490.545 | T56: =SUM(T49:T55) -> 536.174 | U56: =SUM(U49:U55) -> -171.399 | ... W56: =SUM(W49:W55) -> 508.729 | X56: =W56*(1+X97) -> 498.55442 | Y56: =X56*(1+Y97) -> 623.19303 | Z56: =Y56*(1+Z97) -> 810.15093 | AA56: =Z56*(1+AA97) -> 891.16603 | AB56: =AA56*(1+AB97) -> 980.28263
B58: Investments | N58: =+CF_Static!D51+CF_Static!D52+CF_Static!D57+CF_Static!D58 -> -18.19 | O58: =+CF_Static!E51+CF_Static!E52+CF_Static!E57+CF_Static!E58 -> -157.085 | P58: =+CF_Static!F51+CF_Static!F52+CF_Static!F57+CF_Static!F58 -> 33.227 | Q58: =+CF_Static!G51+CF_Static!G52+CF_Static!G57+CF_Static!G58 -> 130.903 | R58: =+CF_Static!H51+CF_Static!H52+CF_Static!H57+CF_Static!H58 -> 86.656 | S58: =+CF_Static!I51+CF_Static!I52+CF_Static!I57+CF_Static!I58 -> -109.275 | T58: =+CF_Static!J51+CF_Static!J52+CF_Static!J57+CF_Static!J58 -> -11.167 | U58: =+CF_Static!K51+CF_Static!K52+CF_Static!K57+CF_Static!K58 -> 51.613 | ... W58: =+CF_Static!M51+CF_Static!M52+CF_Static!M57+CF_Static!M58 -> -169.836 | X58: 0 | Y58: 0 | Z58: 0 | AA58: 0 | AB58: 0
B59: Aqcuistions | N59: =CF_Static!D59 -> 37.212 | O59: =CF_Static!E59 -> -32 | P59: =CF_Static!F59 -> 0 | Q59: =CF_Static!G59 -> -82.67 | R59: =CF_Static!H59 -> 0 | S59: =CF_Static!I59 -> -28.3 | T59: =CF_Static!J59 -> 0 | U59: =CF_Static!K59 -> -62.043 | ... W59: =CF_Static!M59 -> 0 | X59: 0 | Y59: 0 | Z59: 0 | AA59: 0 | AB59: 0
B60: PPE | N60: =CF_Static!D48 -> -62.109 | O60: =CF_Static!E48 -> -107.185 | P60: =CF_Static!F48 -> -94.6 | Q60: =CF_Static!G48 -> -67.616 | R60: =CF_Static!H48 -> -62.579 | S60: =CF_Static!I48 -> -82.667 | T60: =CF_Static!J48 -> -79.55 | U60: =CF_Static!K48 -> -90.818 | ... W60: =CF_Static!M48 -> -136.641 | X60: =-X91*X3 -> -137.31146 | Y60: =-Y91*Y3 -> -151.04261 | Z60: =-Z91*Z3 -> -164.63644 | AA60: =-AA91*AA3 -> -181.10009 | AB60: =-AB91*AB3 -> -199.21009
B61: CFFI | N61: =SUM(N58:N60) -> -43.087 | O61: =SUM(O58:O60) -> -296.27 | P61: =SUM(P58:P60) -> -61.373 | Q61: =SUM(Q58:Q60) -> -19.383 | R61: =SUM(R58:R60) -> 24.077 | S61: =SUM(S58:S60) -> -220.242 | T61: =SUM(T58:T60) -> -90.717 | U61: =SUM(U58:U60) -> -101.248 | ... AB61: =SUM(AB58:AB60) -> -199.21009
B63: Debt PMT | N63: =CF_Static!D62+CF_Static!D63+CF_Static!D64+CF_Static!D65+CF_Static!D66+CF_Static!D70+CF_Static!D71 -> -30.288 | O63: =CF_Static!E62+CF_Static!E63+CF_Static!E64+CF_Static!E65+CF_Static!E66+CF_Static!E70+CF_Static!E71 -> -21.353 | P63: =CF_Static!F62+CF_Static!F63+CF_Static!F64+CF_Static!F65+CF_Static!F66+CF_Static!F70+CF_Static!F71 -> -327.901 | Q63: =CF_Static!G62+CF_Static!G63+CF_Static!G64+CF_Static!G65+CF_Static!G66+CF_Static!G70+CF_Static!G71 -> -2.994 | R63: =CF_Static!H62+CF_Static!H63+CF_Static!H64+CF_Static!H65+CF_Static!H66+CF_Static!H70+CF_Static!H71 -> -119.459 | S63: =CF_Static!I62+CF_Static!I63+CF_Static!I64+CF_Static!I65+CF_Static!I66+CF_Static!I70+CF_Static!I71 -> -5.58 | T63: =CF_Static!J62+CF_Static!J63+CF_Static!J64+CF_Static!J65+CF_Static!J66+CF_Static!J70+CF_Static!J71 -> -6.929 | U63: =CF_Static!K62+CF_Static!K63+CF_Static!K64+CF_Static!K65+CF_Static!K66+CF_Static!K70+CF_Static!K71 -> 389.319 | ... W63: =CF_Static!M62+CF_Static!M63+CF_Static!M64+CF_Static!M65+CF_Static!M66+CF_Static!M70+CF_Static!M71 -> -14.254
B64: Buyback and Issuance | N64: =+CF_Static!D80+CF_Static!D81 -> 30.275 | O64: =+CF_Static!E80+CF_Static!E81 -> 23.091 | P64: =+CF_Static!F80+CF_Static!F81 -> 20.412 | Q64: =+CF_Static!G80+CF_Static!G81 -> -87.854 | R64: =+CF_Static!H80+CF_Static!H81 -> -127.129 | S64: =+CF_Static!I80+CF_Static!I81 -> -46.467 | T64: =+CF_Static!J80+CF_Static!J81 -> -62.831 | U64: =+CF_Static!K80+CF_Static!K81 -> -470.452 | ... W64: =+CF_Static!M80+CF_Static!M81 -> -220.211 | X64: =X141 -> -278.86645 | Y64: =Y141 -> -273.41977 | Z64: =Z141 -> -268.02754 | AA64: =AA141 -> -182.3893 | AB64: =AB141 -> -180.27647
B65: Taxes for SBC | N65: =CF_Static!D79 -> 0 | O65: =CF_Static!E79 -> 0 | P65: =CF_Static!F79 -> 0 | Q65: =CF_Static!G79 -> -4.757 | R65: =CF_Static!H79 -> -29.059 | S65: =CF_Static!I79 -> -32.472 | T65: =CF_Static!J79 -> -44.071 | U65: =CF_Static!K79 -> -48.454 | ... W65: =CF_Static!M79 -> -46.567 | X65: =X136 -> -46.685897 | Y65: =Y136 -> -51.354486 | Z65: =Z136 -> -55.97639 | AA65: =AA136 -> -57.952027 | AB65: =AB136 -> -59.763028
B66: Financing Lease | N66: =CF_Static!D75 -> -8.038 | O66: =CF_Static!E75 -> -5.966 | P66: =CF_Static!F75 -> -3.562 | Q66: =CF_Static!G75 -> -3.624 | R66: =CF_Static!H75 -> -3.319 | S66: =CF_Static!I75 -> -2.703 | T66: =CF_Static!J75 -> -3.004 | U66: =CF_Static!K75 -> -3.468 | ... W66: =CF_Static!M75 -> -4.029 | X66: =-X127 -> -3.769 | Y66: =-Y127 -> -3.769 | Z66: =-Z127 -> -3.769 | AA66: =-AA127 -> -3.769 | AB66: =-AB127 -> -3.769
B67: CFFF | N67: =SUM(N63:N66) -> -8.051 | O67: =SUM(O63:O66) -> -4.228 | P67: =SUM(P63:P66) -> -311.051 | Q67: =SUM(Q63:Q66) -> -99.229 | R67: =SUM(R63:R66) -> -278.966 | S67: =SUM(S63:S66) -> -87.222 | T67: =SUM(T63:T66) -> -116.835 | U67: =SUM(U63:U66) -> -133.055 | ... AB67: =SUM(AB63:AB66) -> -243.8085
B68: FX | N68: =CF_Static!D84 -> -6.683 | O68: =CF_Static!E84 -> -2.389 | P68: =CF_Static!F84 -> 0.494 | Q68: =CF_Static!G84 -> -5.856 | R68: =CF_Static!H84 -> 0.476 | S68: =CF_Static!I84 -> -1.643 | T68: =CF_Static!J84 -> -0.198 | U68: =CF_Static!K84 -> -26.167 | ... W68: =CF_Static!M84 -> 1.246 | X68: 0 | Y68: 0 | Z68: 0 | AA68: 0 | AB68: 0
B69: Model CIC | N69: =N67+N68+N61+N56 -> 204.291 | O69: =O67+O68+O61+O56 -> -13.367 | P69: =P67+P68+P61+P56 -> -137.048 | Q69: =Q67+Q68+Q61+Q56 -> 82.684 | R69: =R67+R68+R61+R56 -> 158.727 | S69: =S67+S68+S61+S56 -> 181.438 | T69: =T67+T68+T61+T56 -> 328.424 | U69: =U67+U68+U61+U56 -> -431.869 | ... AB69: =AB67+AB68+AB61+AB56 -> 537.26404
B70: Reported CIC | N70: =CF_Static!D85 -> 204.251 | O70: =CF_Static!E85 -> -13.356 | P70: =CF_Static!F85 -> -137.048 | Q70: =CF_Static!G85 -> 104.793 | R70: =CF_Static!H85 -> 158.727 | S70: =CF_Static!I85 -> 184.547 | T70: =CF_Static!J85 -> 333.896 | U70: =CF_Static!K85 -> -428.226 | ... W70: =CF_Static!M85 -> -75.76
B71: ceck | N71: =N69-N70 -> 0.04 | O71: =O69-O70 -> -0.011 | P71: =P69-P70 -> 0 | Q71: =Q69-Q70 -> -22.109 | R71: =R69-R70 -> 0 | S71: =S69-S70 -> -3.109 | T71: =T69-T70 -> -5.472 | U71: =U69-U70 -> -3.643 | ... W71: =W69-W70 -> -5.803
A73: x | B73: Estimate Start Year | D73: 2025 | N73: =IF(N2<>"",N2,M73+1 ) -> 2015 | O73: =IF(O2<>"",O2,N73+1 ) -> 2016 | P73: =IF(P2<>"",P2,O73+1 ) -> 2017 | Q73: =IF(Q2<>"",Q2,P73+1 ) -> 2018 | R73: =IF(R2<>"",R2,Q73+1 ) -> 2019 | S73: =IF(S2<>"",S2,R73+1 ) -> 2020 | T73: =IF(T2<>"",T2,S73+1 ) -> 2021 | U73: =IF(U2<>"",U2,T73+1 ) -> 2022 | ... AB73: =IF(AB2<>"",AB2,AA73+1 ) -> 2029
B74: Model Dummy | N74: =IF(N2<>"","n","y" ) -> n | O74: =IF(O2<>"","n","y" ) -> n | P74: =IF(P2<>"","n","y" ) -> n | Q74: =IF(Q2<>"","n","y" ) -> n | R74: =IF(R2<>"","n","y" ) -> n | S74: =IF(S2<>"","n","y" ) -> n | T74: =IF(T2<>"","n","y" ) -> n | U74: =IF(U2<>"","n","y" ) -> n | ... AB74: =IF(AB2<>"","n","y" ) -> n
B76: IS Drivers | M76: AVG
B77: Revenue Growth | M77: =AVERAGE(O77:W77) -> 0.059948493 | N77: =IFERROR(N3/M3-1,0) -> 0 | O77: =IFERROR(O3/N3-1,0) -> 0.063338089 | P77: =IFERROR(P3/O3-1,0) -> 0.077334495 | Q77: =IFERROR(Q3/P3-1,0) -> 0.10443672 | R77: =IFERROR(R3/Q3-1,0) -> 0.15442819 | S77: =IFERROR(S3/R3-1,0) -> -0.011190519 | T77: =IFERROR(T3/S3-1,0) -> 0.025063155 | U77: =IFERROR(U3/T3-1,0) -> 0.0033079385 | ... W77: =IFERROR(W3/V3-1,0) -> -0.084712151 | X77: =INDEX('Scenario Manager'!$F$4:$J$33,MATCH(model!$B77,'Scenario Manager'!$C$4:$C$33,0),MATCH(model!X$73,'Scenario Manager'!$F$3:$J$3,0)) -> 0.14 | Y77: =INDEX('Scenario Manager'!$F$4:$J$33,MATCH(model!$B77,'Scenario Manager'!$C$4:$C$33,0),MATCH(model!Y$73,'Scenario Manager'!$F$3:$J$3,0)) -> 0.1 | Z77: =INDEX('Scenario Manager'!$F$4:$J$33,MATCH(model!$B77,'Scenario Manager'!$C$4:$C$33,0),MATCH(model!Z$73,'Scenario Manager'!$F$3:$J$3,0)) -> 0.09 | AA77: =INDEX('Scenario Manager'!$F$4:$J$33,MATCH(model!$B77,'Scenario Manager'!$C$4:$C$33,0),MATCH(model!AA$73,'Scenario Manager'!$F$3:$J$3,0)) -> 0.1 | AB77: =INDEX('Scenario Manager'!$F$4:$J$33,MATCH(model!$B77,'Scenario Manager'!$C$4:$C$33,0),MATCH(model!AB$73,'Scenario Manager'!$F$3:$J$3,0)) -> 0.1
B78: COGS % of Rev | M78: =AVERAGE(N78:W78) -> 0.55826305 | N78: =-N4/N3 -> 0.56021727 | O78: =-O4/O3 -> 0.55333844 | P78: =-P4/P3 -> 0.55534433 | Q78: =-Q4/Q3 -> 0.57512331 | R78: =-R4/R3 -> 0.56830643 | S78: =-S4/S3 -> 0.53204487 | T78: =-T4/T3 -> 0.52440506 | U78: =-U4/U3 -> 0.57046804 | ... W78: =-W4/W3 -> 0.57170379 | X78: =INDEX('Scenario Manager'!$F$4:$J$33,MATCH(model!$B78,'Scenario Manager'!$C$4:$C$33,0),MATCH(model!X$73,'Scenario Manager'!$F$3:$J$3,0)) -> 0.58 | Y78: =INDEX('Scenario Manager'!$F$4:$J$33,MATCH(model!$B78,'Scenario Manager'!$C$4:$C$33,0),MATCH(model!Y$73,'Scenario Manager'!$F$3:$J$3,0)) -> 0.56 | Z78: =INDEX('Scenario Manager'!$F$4:$J$33,MATCH(model!$B78,'Scenario Manager'!$C$4:$C$33,0),MATCH(model!Z$73,'Scenario Manager'!$F$3:$J$3,0)) -> 0.55 | AA78: =INDEX('Scenario Manager'!$F$4:$J$33,MATCH(model!$B78,'Scenario Manager'!$C$4:$C$33,0),MATCH(model!AA$73,'Scenario Manager'!$F$3:$J$3,0)) -> 0.5 | AB78: =INDEX('Scenario Manager'!$F$4:$J$33,MATCH(model!$B78,'Scenario Manager'!$C$4:$C$33,0),MATCH(model!AB$73,'Scenario Manager'!$F$3:$J$3,0)) -> 0.5
B79: R&D % of Rev | M79: =AVERAGE(N79:W79) -> 0.16575186 | N79: =-N7/N3 -> 0.16936102 | O79: =-O7/O3 -> 0.17372864 | P79: =-P7/P3 -> 0.16965814 | Q79: =-Q7/Q3 -> 0.15886185 | R79: =-R7/R3 -> 0.15344874 | S79: =-S7/S3 -> 0.15001825 | T79: =-T7/T3 -> 0.14822227 | U79: =-U7/U3 -> 0.17195549 | ... W79: =-W7/W3 -> 0.19115955 | X79: =INDEX('Scenario Manager'!$F$4:$J$33,MATCH(model!$B79,'Scenario Manager'!$C$4:$C$33,0),MATCH(model!X$73,'Scenario Manager'!$F$3:$J$3,0)) -> 0.17 | Y79: =INDEX('Scenario Manager'!$F$4:$J$33,MATCH(model!$B79,'Scenario Manager'!$C$4:$C$33,0),MATCH(model!Y$73,'Scenario Manager'!$F$3:$J$3,0)) -> 0.17 | Z79: =INDEX('Scenario Manager'!$F$4:$J$33,MATCH(model!$B79,'Scenario Manager'!$C$4:$C$33,0),MATCH(model!Z$73,'Scenario Manager'!$F$3:$J$3,0)) -> 0.17 | AA79: =INDEX('Scenario Manager'!$F$4:$J$33,MATCH(model!$B79,'Scenario Manager'!$C$4:$C$33,0),MATCH(model!AA$73,'Scenario Manager'!$F$3:$J$3,0)) -> 0.17 | AB79: =INDEX('Scenario Manager'!$F$4:$J$33,MATCH(model!$B79,'Scenario Manager'!$C$4:$C$33,0),MATCH(model!AB$73,'Scenario Manager'!$F$3:$J$3,0)) -> 0.17
B80: SG&A % of Rev | M80: =AVERAGE(N80:W80) -> 0.17764733 | N80: =-(N6+N8)/N3 -> 0.19740079 | O80: =-(O6+O8)/O3 -> 0.18733256 | P80: =-(P6+P8)/P3 -> 0.17802595 | Q80: =-(Q6+Q8)/Q3 -> 0.18075382 | R80: =-(R6+R8)/R3 -> 0.16819512 | S80: =-(S6+S8)/S3 -> 0.16703788 | T80: =-(T6+T8)/T3 -> 0.1758397 | U80: =-(U6+U8)/U3 -> 0.1779811 | ... W80: =-(W6+W8)/W3 -> 0.18214775 | X80: =INDEX('Scenario Manager'!$F$4:$J$33,MATCH(model!$B80,'Scenario Manager'!$C$4:$C$33,0),MATCH(model!X$73,'Scenario Manager'!$F$3:$J$3,0)) -> 0.17 | Y80: =INDEX('Scenario Manager'!$F$4:$J$33,MATCH(model!$B80,'Scenario Manager'!$C$4:$C$33,0),MATCH(model!Y$73,'Scenario Manager'!$F$3:$J$3,0)) -> 0.17 | Z80: =INDEX('Scenario Manager'!$F$4:$J$33,MATCH(model!$B80,'Scenario Manager'!$C$4:$C$33,0),MATCH(model!Z$73,'Scenario Manager'!$F$3:$J$3,0)) -> 0.17 | AA80: =INDEX('Scenario Manager'!$F$4:$J$33,MATCH(model!$B80,'Scenario Manager'!$C$4:$C$33,0),MATCH(model!AA$73,'Scenario Manager'!$F$3:$J$3,0)) -> 0.16 | AB80: =INDEX('Scenario Manager'!$F$4:$J$33,MATCH(model!$B80,'Scenario Manager'!$C$4:$C$33,0),MATCH(model!AB$73,'Scenario Manager'!$F$3:$J$3,0)) -> 0.15
B81: D&A % of Rev | M81: =AVERAGE(N81:W81) -> 0.040207561 | N81: =N50/N3 -> 0.055513236 | O81: =O50/O3 -> 0.054484915 | P81: =P50/P3 -> 0.043867141 | Q81: =Q50/Q3 -> 0.03555586 | R81: =R50/R3 -> 0.034352604 | S81: =S50/S3 -> 0.037520133 | T81: =T50/T3 -> 0.036530667 | U81: =U50/U3 -> 0.038595124 | ... W81: =W50/W3 -> 0.033243212 | X81: =INDEX('Scenario Manager'!$F$4:$J$33,MATCH(model!$B81,'Scenario Manager'!$C$4:$C$33,0),MATCH(model!X$73,'Scenario Manager'!$F$3:$J$3,0)) -> 0.025 | Y81: =INDEX('Scenario Manager'!$F$4:$J$33,MATCH(model!$B81,'Scenario Manager'!$C$4:$C$33,0),MATCH(model!Y$73,'Scenario Manager'!$F$3:$J$3,0)) -> 0.02 | Z81: =INDEX('Scenario Manager'!$F$4:$J$33,MATCH(model!$B81,'Scenario Manager'!$C$4:$C$33,0),MATCH(model!Z$73,'Scenario Manager'!$F$3:$J$3,0)) -> 0.02 | AA81: =INDEX('Scenario Manager'!$F$4:$J$33,MATCH(model!$B81,'Scenario Manager'!$C$4:$C$33,0),MATCH(model!AA$73,'Scenario Manager'!$F$3:$J$3,0)) -> 0.02 | AB81: =INDEX('Scenario Manager'!$F$4:$J$33,MATCH(model!$B81,'Scenario Manager'!$C$4:$C$33,0),MATCH(model!AB$73,'Scenario Manager'!$F$3:$J$3,0)) -> 0.02
B82: D&A % of CapEx | M82: =AVERAGE(N82:W82) -> 1.552033 | N82: =N50/-N60 -> 2.1859473 | O82: =O50/-O60 -> 1.3219387 | P82: =P50/-P60 -> 1.2991755 | Q82: =Q50/-Q60 -> 1.6271297 | R82: =R50/-R60 -> 1.9609134 | S82: =S50/-S60 -> 1.6031427 | T82: =T50/-T60 -> 1.6626776 | U82: =U50/-U60 -> 1.5437799 | ... W82: =W50/-W60 -> 0.9767932 | X82: =INDEX('Scenario Manager'!$F$4:$J$33,MATCH(model!$B82,'Scenario Manager'!$C$4:$C$33,0),MATCH(model!X$73,'Scenario Manager'!$F$3:$J$3,0)) -> 1.2 | Y82: =INDEX('Scenario Manager'!$F$4:$J$33,MATCH(model!$B82,'Scenario Manager'!$C$4:$C$33,0),MATCH(model!Y$73,'Scenario Manager'!$F$3:$J$3,0)) -> 1.2 | Z82: =INDEX('Scenario Manager'!$F$4:$J$33,MATCH(model!$B82,'Scenario Manager'!$C$4:$C$33,0),MATCH(model!Z$73,'Scenario Manager'!$F$3:$J$3,0)) -> 1.2 | AA82: =INDEX('Scenario Manager'!$F$4:$J$33,MATCH(model!$B82,'Scenario Manager'!$C$4:$C$33,0),MATCH(model!AA$73,'Scenario Manager'!$F$3:$J$3,0)) -> 1.2 | AB82: =INDEX('Scenario Manager'!$F$4:$J$33,MATCH(model!$B82,'Scenario Manager'!$C$4:$C$33,0),MATCH(model!AB$73,'Scenario Manager'!$F$3:$J$3,0)) -> 1.2
B83: Int Exp % of Debt | M83: =AVERAGE(N83:W83) -> 0.050498351 | N83: =-N11/N38 -> 0.060184956 | O83: =-O11/O38 -> 0.055397621 | P83: =-P11/P38 -> 0.062603835 | Q83: =-Q11/Q38 -> 0.094635183 | R83: =-R11/R38 -> 0.048844497 | S83: =-S11/S38 -> 0.045373387 | T83: =-T11/T38 -> 0.048140738 | U83: =-U11/U38 -> 0.037734948 | ... W83: =-W11/W38 -> 0.030274331 | X83: =INDEX('Scenario Manager'!$F$4:$J$33,MATCH(model!$B83,'Scenario Manager'!$C$4:$C$33,0),MATCH(model!X$73,'Scenario Manager'!$F$3:$J$3,0)) -> 0.05 | Y83: =INDEX('Scenario Manager'!$F$4:$J$33,MATCH(model!$B83,'Scenario Manager'!$C$4:$C$33,0),MATCH(model!Y$73,'Scenario Manager'!$F$3:$J$3,0)) -> 0.05 | Z83: =INDEX('Scenario Manager'!$F$4:$J$33,MATCH(model!$B83,'Scenario Manager'!$C$4:$C$33,0),MATCH(model!Z$73,'Scenario Manager'!$F$3:$J$3,0)) -> 0.05 | AA83: =INDEX('Scenario Manager'!$F$4:$J$33,MATCH(model!$B83,'Scenario Manager'!$C$4:$C$33,0),MATCH(model!AA$73,'Scenario Manager'!$F$3:$J$3,0)) -> 0.05 | AB83: =INDEX('Scenario Manager'!$F$4:$J$33,MATCH(model!$B83,'Scenario Manager'!$C$4:$C$33,0),MATCH(model!AB$73,'Scenario Manager'!$F$3:$J$3,0)) -> 0.05
B84: Taxes % of EBIT | M84: =AVERAGE(N84:W84) -> -0.13778633 | N84: =-N13/N18 -> 0.067738052 | O84: =-O13/O18 -> 0.063492206 | P84: =-P13/P18 -> -4.0702691 | Q84: =-Q13/Q18 -> 1.8704695 | R84: =-R13/R18 -> 0.15200757 | S84: =-S13/S18 -> 0.17761759 | T84: =-T13/T18 -> -0.068248966 | U84: =-U13/U18 -> 0.10238187 | ... W84: =-W13/W18 -> 0.1625796 | X84: =INDEX('Scenario Manager'!$F$4:$J$33,MATCH(model!$B84,'Scenario Manager'!$C$4:$C$33,0),MATCH(model!X$73,'Scenario Manager'!$F$3:$J$3,0)) -> 0.25 | Y84: =INDEX('Scenario Manager'!$F$4:$J$33,MATCH(model!$B84,'Scenario Manager'!$C$4:$C$33,0),MATCH(model!Y$73,'Scenario Manager'!$F$3:$J$3,0)) -> 0.25 | Z84: =INDEX('Scenario Manager'!$F$4:$J$33,MATCH(model!$B84,'Scenario Manager'!$C$4:$C$33,0),MATCH(model!Z$73,'Scenario Manager'!$F$3:$J$3,0)) -> 0.25 | AA84: =INDEX('Scenario Manager'!$F$4:$J$33,MATCH(model!$B84,'Scenario Manager'!$C$4:$C$33,0),MATCH(model!AA$73,'Scenario Manager'!$F$3:$J$3,0)) -> 0.25 | AB84: =INDEX('Scenario Manager'!$F$4:$J$33,MATCH(model!$B84,'Scenario Manager'!$C$4:$C$33,0),MATCH(model!AB$73,'Scenario Manager'!$F$3:$J$3,0)) -> 0.25
B86: BS Drivers
B87: AR % of Rev | M87: =AVERAGE(N87:W87) -> 0.22826808 | N87: =N24/N3 -> 0.22521118 | O87: =O24/O3 -> 0.22158001 | P87: =P24/P3 -> 0.22207441 | Q87: =Q24/Q3 -> 0.25417883 | R87: =R24/R3 -> 0.20291921 | S87: =S24/S3 -> 0.203673 | T87: =T24/T3 -> 0.24441735 | U87: =U24/U3 -> 0.25347039 | ... W87: =W24/W3 -> 0.22630316 | X87: =INDEX('Scenario Manager'!$F$4:$J$33,MATCH(model!$B87,'Scenario Manager'!$C$4:$C$33,0),MATCH(model!X$73,'Scenario Manager'!$F$3:$J$3,0)) -> 0.25 | Y87: =INDEX('Scenario Manager'!$F$4:$J$33,MATCH(model!$B87,'Scenario Manager'!$C$4:$C$33,0),MATCH(model!Y$73,'Scenario Manager'!$F$3:$J$3,0)) -> 0.2375 | Z87: =INDEX('Scenario Manager'!$F$4:$J$33,MATCH(model!$B87,'Scenario Manager'!$C$4:$C$33,0),MATCH(model!Z$73,'Scenario Manager'!$F$3:$J$3,0)) -> 0.225625 | AA87: =INDEX('Scenario Manager'!$F$4:$J$33,MATCH(model!$B87,'Scenario Manager'!$C$4:$C$33,0),MATCH(model!AA$73,'Scenario Manager'!$F$3:$J$3,0)) -> 0.21434375 | AB87: =INDEX('Scenario Manager'!$F$4:$J$33,MATCH(model!$B87,'Scenario Manager'!$C$4:$C$33,0),MATCH(model!AB$73,'Scenario Manager'!$F$3:$J$3,0)) -> 0.20362656
B88: Inv % of Rev | M88: =AVERAGE(N88:W88) -> 0.13416419 | N88: =N25/N3 -> 0.07816348 | O88: =O25/O3 -> 0.081232482 | P88: =P25/P3 -> 0.095350765 | Q88: =Q25/Q3 -> 0.084914904 | R88: =R25/R3 -> 0.096594722 | S88: =S25/S3 -> 0.097498214 | T88: =T25/T3 -> 0.10336859 | U88: =U25/U3 -> 0.26061612 | ... W88: =W25/W3 -> 0.20434351 | X88: =INDEX('Scenario Manager'!$F$4:$J$33,MATCH(model!$B88,'Scenario Manager'!$C$4:$C$33,0),MATCH(model!X$73,'Scenario Manager'!$F$3:$J$3,0)) -> 0.2 | Y88: =INDEX('Scenario Manager'!$F$4:$J$33,MATCH(model!$B88,'Scenario Manager'!$C$4:$C$33,0),MATCH(model!Y$73,'Scenario Manager'!$F$3:$J$3,0)) -> 0.2 | Z88: =INDEX('Scenario Manager'!$F$4:$J$33,MATCH(model!$B88,'Scenario Manager'!$C$4:$C$33,0),MATCH(model!Z$73,'Scenario Manager'!$F$3:$J$3,0)) -> 0.2 | AA88: =INDEX('Scenario Manager'!$F$4:$J$33,MATCH(model!$B88,'Scenario Manager'!$C$4:$C$33,0),MATCH(model!AA$73,'Scenario Manager'!$F$3:$J$3,0)) -> 0.2 | AB88: =INDEX('Scenario Manager'!$F$4:$J$33,MATCH(model!$B88,'Scenario Manager'!$C$4:$C$33,0),MATCH(model!AB$73,'Scenario Manager'!$F$3:$J$3,0)) -> 0.2
B89: OA % of Rev | M89: =AVERAGE(N89:W89) -> 0.30512088 | N89: =(N26+N32+N33)/N3 -> 0.11482911 | O89: =(O26+O32+O33)/O3 -> 0.092657657 | P89: =(P26+P32+P33)/P3 -> 0.50542263 | Q89: =(Q26+Q32+Q33)/Q3 -> 0.32822952 | R89: =(R26+R32+R33)/R3 -> 0.30845509 | S89: =(S26+S32+S33)/S3 -> 0.29973724 | T89: =(T26+T32+T33)/T3 -> 0.3385341 | U89: =(U26+U32+U33)/U3 -> 0.35997799 | ... W89: =(W26+W32+W33)/W3 -> 0.39983462 | X89: =INDEX('Scenario Manager'!$F$4:$J$33,MATCH(model!$B89,'Scenario Manager'!$C$4:$C$33,0),MATCH(model!X$73,'Scenario Manager'!$F$3:$J$3,0)) -> 0.4 | Y89: =INDEX('Scenario Manager'!$F$4:$J$33,MATCH(model!$B89,'Scenario Manager'!$C$4:$C$33,0),MATCH(model!Y$73,'Scenario Manager'!$F$3:$J$3,0)) -> 0.4 | Z89: =INDEX('Scenario Manager'!$F$4:$J$33,MATCH(model!$B89,'Scenario Manager'!$C$4:$C$33,0),MATCH(model!Z$73,'Scenario Manager'!$F$3:$J$3,0)) -> 0.4 | AA89: =INDEX('Scenario Manager'!$F$4:$J$33,MATCH(model!$B89,'Scenario Manager'!$C$4:$C$33,0),MATCH(model!AA$73,'Scenario Manager'!$F$3:$J$3,0)) -> 0.4 | AB89: =INDEX('Scenario Manager'!$F$4:$J$33,MATCH(model!$B89,'Scenario Manager'!$C$4:$C$33,0),MATCH(model!AB$73,'Scenario Manager'!$F$3:$J$3,0)) -> 0.4
B90: CapEx | M90: =AVERAGE(N90:W90) -> 88.9962 | N90: =-N60 -> 62.109 | O90: =-O60 -> 107.185 | P90: =-P60 -> 94.6 | Q90: =-Q60 -> 67.616 | R90: =-R60 -> 62.579 | S90: =-S60 -> 82.667 | T90: =-T60 -> 79.55 | U90: =-U60 -> 90.818 | ... W90: =-W60 -> 136.641 | X90: =INDEX('Scenario Manager'!$F$4:$J$33,MATCH(model!$B90,'Scenario Manager'!$C$4:$C$33,0),MATCH(model!X$73,'Scenario Manager'!$F$3:$J$3,0)) -> 0 | Y90: =INDEX('Scenario Manager'!$F$4:$J$33,MATCH(model!$B90,'Scenario Manager'!$C$4:$C$33,0),MATCH(model!Y$73,'Scenario Manager'!$F$3:$J$3,0)) -> 0 | Z90: =INDEX('Scenario Manager'!$F$4:$J$33,MATCH(model!$B90,'Scenario Manager'!$C$4:$C$33,0),MATCH(model!Z$73,'Scenario Manager'!$F$3:$J$3,0)) -> 0 | AA90: =INDEX('Scenario Manager'!$F$4:$J$33,MATCH(model!$B90,'Scenario Manager'!$C$4:$C$33,0),MATCH(model!AA$73,'Scenario Manager'!$F$3:$J$3,0)) -> 0 | AB90: =INDEX('Scenario Manager'!$F$4:$J$33,MATCH(model!$B90,'Scenario Manager'!$C$4:$C$33,0),MATCH(model!AB$73,'Scenario Manager'!$F$3:$J$3,0)) -> 0
B91: CapEx % of Rev | M91: =AVERAGE(N91:W91) -> 0.026836556 | N91: =N90/N3 -> 0.025395505 | O91: =O90/O3 -> 0.041215917 | P91: =P90/P3 -> 0.033765371 | Q91: =Q90/Q3 -> 0.021851891 | R91: =R90/R3 -> 0.017518674 | S91: =S90/S3 -> 0.023404113 | T91: =T90/T3 -> 0.021970987 | U91: =U90/U3 -> 0.025000406 | ... W91: =W90/W3 -> 0.034033009 | X91: =INDEX('Scenario Manager'!$F$4:$J$33,MATCH(model!$B91,'Scenario Manager'!$C$4:$C$33,0),MATCH(model!X$73,'Scenario Manager'!$F$3:$J$3,0)) -> 0.03 | Y91: =INDEX('Scenario Manager'!$F$4:$J$33,MATCH(model!$B91,'Scenario Manager'!$C$4:$C$33,0),MATCH(model!Y$73,'Scenario Manager'!$F$3:$J$3,0)) -> 0.03 | Z91: =INDEX('Scenario Manager'!$F$4:$J$33,MATCH(model!$B91,'Scenario Manager'!$C$4:$C$33,0),MATCH(model!Z$73,'Scenario Manager'!$F$3:$J$3,0)) -> 0.03 | AA91: =INDEX('Scenario Manager'!$F$4:$J$33,MATCH(model!$B91,'Scenario Manager'!$C$4:$C$33,0),MATCH(model!AA$73,'Scenario Manager'!$F$3:$J$3,0)) -> 0.03 | AB91: =INDEX('Scenario Manager'!$F$4:$J$33,MATCH(model!$B91,'Scenario Manager'!$C$4:$C$33,0),MATCH(model!AB$73,'Scenario Manager'!$F$3:$J$3,0)) -> 0.03
B92: AP % of COGS | M92: =AVERAGE(N92:W92) -> 0.17576398 | N92: =-N36/N4 -> 0.16213344 | O92: =-O36/O4 -> 0.16396282 | P92: =-P36/P4 -> 0.16716873 | Q92: =-Q36/Q4 -> 0.19138164 | R92: =-R36/R4 -> 0.16985614 | S92: =-S36/S4 -> 0.15532873 | T92: =-T36/T4 -> 0.18758891 | U92: =-U36/U4 -> 0.24901933 | ... W92: =-W36/W4 -> 0.18445912 | X92: =INDEX('Scenario Manager'!$F$4:$J$33,MATCH(model!$B92,'Scenario Manager'!$C$4:$C$33,0),MATCH(model!X$73,'Scenario Manager'!$F$3:$J$3,0)) -> 0.1 | Y92: =INDEX('Scenario Manager'!$F$4:$J$33,MATCH(model!$B92,'Scenario Manager'!$C$4:$C$33,0),MATCH(model!Y$73,'Scenario Manager'!$F$3:$J$3,0)) -> 0.1 | Z92: =INDEX('Scenario Manager'!$F$4:$J$33,MATCH(model!$B92,'Scenario Manager'!$C$4:$C$33,0),MATCH(model!Z$73,'Scenario Manager'!$F$3:$J$3,0)) -> 0.1 | AA92: =INDEX('Scenario Manager'!$F$4:$J$33,MATCH(model!$B92,'Scenario Manager'!$C$4:$C$33,0),MATCH(model!AA$73,'Scenario Manager'!$F$3:$J$3,0)) -> 0.1 | AB92: =INDEX('Scenario Manager'!$F$4:$J$33,MATCH(model!$B92,'Scenario Manager'!$C$4:$C$33,0),MATCH(model!AB$73,'Scenario Manager'!$F$3:$J$3,0)) -> 0.1
B93: AE % of OpEx | M93: =AVERAGE(N93:W93) -> 0.31606663 | N93: =N37/-N9 -> 0.35260954 | O93: =O37/-O9 -> 0.33052634 | P93: =P37/-P9 -> 0.3315197 | Q93: =Q37/-Q9 -> 0.32361343 | R93: =R37/-R9 -> 0.33312039 | S93: =S37/-S9 -> 0.29836091 | T93: =T37/-T9 -> 0.34882462 | U93: =U37/-U9 -> 0.28381192 | ... W93: =W37/-W9 -> 0.26281148 | X93: =INDEX('Scenario Manager'!$F$4:$J$33,MATCH(model!$B93,'Scenario Manager'!$C$4:$C$33,0),MATCH(model!X$73,'Scenario Manager'!$F$3:$J$3,0)) -> 0.25 | Y93: =INDEX('Scenario Manager'!$F$4:$J$33,MATCH(model!$B93,'Scenario Manager'!$C$4:$C$33,0),MATCH(model!Y$73,'Scenario Manager'!$F$3:$J$3,0)) -> 0.25 | Z93: =INDEX('Scenario Manager'!$F$4:$J$33,MATCH(model!$B93,'Scenario Manager'!$C$4:$C$33,0),MATCH(model!Z$73,'Scenario Manager'!$F$3:$J$3,0)) -> 0.25 | AA93: =INDEX('Scenario Manager'!$F$4:$J$33,MATCH(model!$B93,'Scenario Manager'!$C$4:$C$33,0),MATCH(model!AA$73,'Scenario Manager'!$F$3:$J$3,0)) -> 0.25 | AB93: =INDEX('Scenario Manager'!$F$4:$J$33,MATCH(model!$B93,'Scenario Manager'!$C$4:$C$33,0),MATCH(model!AB$73,'Scenario Manager'!$F$3:$J$3,0)) -> 0.25
B94: OL % of Rev | M94: =AVERAGE(N94:W94) -> 0.040495788 | N94: =N41/N3 -> 0.029660596 | O94: =O41/O3 -> 0.047833304 | P94: =P41/P3 -> 0.039743555 | Q94: =Q41/Q3 -> 0.038591455 | R94: =R41/R3 -> 0.04164097 | S94: =S41/S3 -> 0.03487529 | T94: =T41/T3 -> 0.046069472 | U94: =U41/U3 -> 0.041384263 | ... W94: =W41/W3 -> 0.046311353 | X94: =INDEX('Scenario Manager'!$F$4:$J$33,MATCH(model!$B94,'Scenario Manager'!$C$4:$C$33,0),MATCH(model!X$73,'Scenario Manager'!$F$3:$J$3,0)) -> 0.04 | Y94: =INDEX('Scenario Manager'!$F$4:$J$33,MATCH(model!$B94,'Scenario Manager'!$C$4:$C$33,0),MATCH(model!Y$73,'Scenario Manager'!$F$3:$J$3,0)) -> 0.04 | Z94: =INDEX('Scenario Manager'!$F$4:$J$33,MATCH(model!$B94,'Scenario Manager'!$C$4:$C$33,0),MATCH(model!Z$73,'Scenario Manager'!$F$3:$J$3,0)) -> 0.04 | AA94: =INDEX('Scenario Manager'!$F$4:$J$33,MATCH(model!$B94,'Scenario Manager'!$C$4:$C$33,0),MATCH(model!AA$73,'Scenario Manager'!$F$3:$J$3,0)) -> 0.04 | AB94: =INDEX('Scenario Manager'!$F$4:$J$33,MATCH(model!$B94,'Scenario Manager'!$C$4:$C$33,0),MATCH(model!AB$73,'Scenario Manager'!$F$3:$J$3,0)) -> 0.04
B96: CF Drivers
B97: CFFO growth | M97: =AVERAGE(O97:W97) -> 0.0004505635 | N97: =IFERROR(N56/M56-1,0) -> 0 | O97: =IFERROR(O56/N56-1,0) -> 0.10456599 | P97: =IFERROR(P56/O56-1,0) -> -0.18871926 | Q97: =IFERROR(Q56/P56-1,0) -> -0.11805928 | R97: =IFERROR(R56/Q56-1,0) -> 0.99438094 | S97: =IFERROR(S56/R56-1,0) -> 0.1873578 | T97: =IFERROR(T56/S56-1,0) -> 0.093016951 | U97: =IFERROR(U56/T56-1,0) -> -1.3196705 | ... W97: =IFERROR(W56/V56-1,0) -> 2.1835157 | X97: =INDEX('Scenario Manager'!$F$4:$J$33,MATCH(model!$B97,'Scenario Manager'!$C$4:$C$33,0),MATCH(model!X$73,'Scenario Manager'!$F$3:$J$3,0)) -> -0.02 | Y97: =INDEX('Scenario Manager'!$F$4:$J$33,MATCH(model!$B97,'Scenario Manager'!$C$4:$C$33,0),MATCH(model!Y$73,'Scenario Manager'!$F$3:$J$3,0)) -> 0.25 | Z97: =INDEX('Scenario Manager'!$F$4:$J$33,MATCH(model!$B97,'Scenario Manager'!$C$4:$C$33,0),MATCH(model!Z$73,'Scenario Manager'!$F$3:$J$3,0)) -> 0.3 | AA97: =INDEX('Scenario Manager'!$F$4:$J$33,MATCH(model!$B97,'Scenario Manager'!$C$4:$C$33,0),MATCH(model!AA$73,'Scenario Manager'!$F$3:$J$3,0)) -> 0.1 | AB97: =INDEX('Scenario Manager'!$F$4:$J$33,MATCH(model!$B97,'Scenario Manager'!$C$4:$C$33,0),MATCH(model!AB$73,'Scenario Manager'!$F$3:$J$3,0)) -> 0.1
B98: SBC % of SG&A | M98: =AVERAGE(N98:W98) -> 0.13200796 | N98: =N51/-(N6+N8) -> 0.11462849 | O98: =O51/-(O6+O8) -> 0.10672411 | P98: =P51/-(P6+P8) -> 0.096957935 | Q98: =Q51/-(Q6+Q8) -> 0.094710569 | R98: =R51/-(R6+R8) -> 0.099424948 | S98: =S51/-(S6+S8) -> 0.11484329 | T98: =T51/-(T6+T8) -> 0.13246631 | U98: =U51/-(U6+U8) -> 0.1626043 | ... W98: =W51/-(W6+W8) -> 0.2138668 | X98: =INDEX('Scenario Manager'!$F$4:$J$33,MATCH(model!$B98,'Scenario Manager'!$C$4:$C$33,0),MATCH(model!X$73,'Scenario Manager'!$F$3:$J$3,0)) -> 0.2 | Y98: =INDEX('Scenario Manager'!$F$4:$J$33,MATCH(model!$B98,'Scenario Manager'!$C$4:$C$33,0),MATCH(model!Y$73,'Scenario Manager'!$F$3:$J$3,0)) -> 0.2 | Z98: =INDEX('Scenario Manager'!$F$4:$J$33,MATCH(model!$B98,'Scenario Manager'!$C$4:$C$33,0),MATCH(model!Z$73,'Scenario Manager'!$F$3:$J$3,0)) -> 0.2 | AA98: =INDEX('Scenario Manager'!$F$4:$J$33,MATCH(model!$B98,'Scenario Manager'!$C$4:$C$33,0),MATCH(model!AA$73,'Scenario Manager'!$F$3:$J$3,0)) -> 0.2 | AB98: =INDEX('Scenario Manager'!$F$4:$J$33,MATCH(model!$B98,'Scenario Manager'!$C$4:$C$33,0),MATCH(model!AB$73,'Scenario Manager'!$F$3:$J$3,0)) -> 0.2
A101: x | B101: Debt Manager
B103: Cash
B104: Cash/Equiv | N104: =N23 -> 926.078 | O104: =O23 -> 1052.863 | P104: =P23 -> 919.646 | Q104: =Q23 -> 894.404 | R104: =R23 -> 1013.985 | S104: =S23 -> 1239.291 | T104: =T23 -> 1604.029 | U104: =U23 -> 1148.341 | ... AB104: =AB23 -> 2747.696
B105: Average Cash | O105: =+(N104+O104)/2 -> 989.4705 | P105: =+(O104+P104)/2 -> 986.2545 | Q105: =+(P104+Q104)/2 -> 907.025 | R105: =+(Q104+R104)/2 -> 954.1945 | S105: =+(R104+S104)/2 -> 1126.638 | T105: =+(S104+T104)/2 -> 1421.66 | U105: =+(T104+U104)/2 -> 1376.185 | V105: =+(U104+V104)/2 -> 1131.856 | ... AB105: =+(AA104+AB104)/2 -> 2479.064
B106: Interest Rate | M106: SOFR | O106: =O107/O105 -> -0.012702754 | P106: =P107/P105 -> 0.00092572455 | Q106: =Q107/Q105 -> -0.013262038 | R106: =R107/R105 -> 0.0040620649 | S106: =S107/S105 -> 0.00085564307 | T106: =T107/T105 -> -0.0012436166 | U106: =U107/U105 -> 0.0049026839 | V106: =V107/V105 -> 0.053017345 | W106: =W107/W105 -> 0.042475694 | X106: =INDEX('Scenario Manager'!$F$4:$J$33,MATCH(model!$M106,'Scenario Manager'!$C$4:$C$33,0),MATCH(model!X$73,'Scenario Manager'!$F$3:$J$3,0)) -> 0.0411 | Y106: =INDEX('Scenario Manager'!$F$4:$J$33,MATCH(model!$M106,'Scenario Manager'!$C$4:$C$33,0),MATCH(model!Y$73,'Scenario Manager'!$F$3:$J$3,0)) -> 0.0336 | Z106: =INDEX('Scenario Manager'!$F$4:$J$33,MATCH(model!$M106,'Scenario Manager'!$C$4:$C$33,0),MATCH(model!Z$73,'Scenario Manager'!$F$3:$J$3,0)) -> 0.0341 | AA106: =INDEX('Scenario Manager'!$F$4:$J$33,MATCH(model!$M106,'Scenario Manager'!$C$4:$C$33,0),MATCH(model!AA$73,'Scenario Manager'!$F$3:$J$3,0)) -> 0.0356 | AB106: =INDEX('Scenario Manager'!$F$4:$J$33,MATCH(model!$M106,'Scenario Manager'!$C$4:$C$33,0),MATCH(model!AB$73,'Scenario Manager'!$F$3:$J$3,0)) -> 0.0371
B107: Interest Income, Note 5 | O107: -12.569 | P107: 0.913 | Q107: -12.029 | R107: 3.876 | S107: 0.964 | T107: -1.768 | U107: 6.747 | V107: 60.008 | W107: 50.261 | X107: =X106*X105 -> 52.080556 | Y107: =Y106*Y105 -> 45.525688 | Z107: =Z106*Z105 -> 54.069149 | AA107: =AA106*AA105 -> 70.397367 | AB107: =AB106*AB105 -> 91.973273
B109: Debt
B110: Term Loans
B111: SOFR + 2%, Due Oct'30 | M111: 2030 | W111: 1158.3 | X111: =W111 -> 1158.3 | Y111: =X111 -> 1158.3 | Z111: =Y111 -> 1158.3 | AA111: =Z111 -> 1158.3 | AB111: =AA111 -> 1158.3 | AC111: =AB111 -> 1158.3
B112: Notes
B113: 4% Senior, Due 2030 | M113: 2030 | W113: 400 | X113: =W113 -> 400 | Y113: =X113 -> 400 | Z113: =Y113 -> 400 | AA113: =Z113 -> 400 | AB113: =AA113 -> 400 | AC113: =AB113 -> 400
B114: Interest Payments
...

Sheet historical>>>

Sheet IS_Static
I1: Next Report Date: | J1: 45904 | K1: Last Refresh: | L1: 45828
I2: FYE Date: | J2: 45598
K3: Identifier | L3: CIEN-US | M3: 1 | P3: original | Q3: restated | R3: Units | S3: M
K4: Start Date | L4: -9 | O4: 1 | P4: ANN | Q4: ANN_R | R4: Billions | S4: B
K5: End Date | L5: 0 | O5: 2 | P5: QTR | Q5: QTR_R | R5: Millions | S5: M
K6: Frequency | L6: Fiscal Years | M6: ANN | N6: ANN_R | O6: 3 | P6: SEMI | Q6: SEMI_R | R6: Thousands | S6: T
K7: Report Basis | L7: Restated | M7: ANN_R | O7: 4 | P7: YTD | Q7: YTD_R
K8: Units | L8: Millions
B9: Ciena Corporation
B11: Income Statement | D11: 42307 | E11: 42674 | F11: 43039 | G11: 43404 | H11: 43769 | I11: 44134 | J11: 44498 | K11: 44865 | L11: 45230 | M11: 45596
B12: Total revenue | C12: RV | D12: 2445.669 | E12: 2600.573 | F12: 2801.687 | G12: 3094.286 | H12: 3572.131 | I12: 3532.157 | J12: 3620.684 | K12: 3632.661 | L12: 4386.549 | M12: 4014.955
B13: Products | C13: PRODUCTS | D13: 2002.395 | E13: 2117.472 | F13: 2318.581 | G13: 2565.46 | H13: 2983.815 | I13: 2914.79 | J13: 2932.602 | K13: 2888.848 | L13: 3581.039 | M13: 3159.021
B14: Services | C14: SERVICES | D14: 443.274 | E14: 483.101 | F14: 483.106 | G14: 528.826 | H14: 588.316 | I14: 617.367 | J14: 688.082 | K14: 743.813 | L14: 805.51 | M14: 855.934
B15: Total cost of goods sold | C15: TOTAL COST OF GOODS SOLD | D15: -1370.106 | E15: -1438.997 | F15: -1555.901 | G15: -1779.596 | H15: -2030.065 | I15: -1879.266 | J15: -1898.705 | K15: -2072.317 | L15: -2507.698 | M15: -2295.365
B16: Products | C16: PRODUCTS2 | D16: -1120.373 | E16: -1176.304 | F16: -1308.295 | G16: -1507.157 | H16: -1716.358 | I16: -1573.791 | J16: -1545.269 | K16: -1699.631 | L16: -2088.44 | M16: -1861.317
B17: Services | C17: SERVICES2 | D17: -249.733 | E17: -262.693 | F17: -247.606 | G17: -272.439 | H17: -313.707 | I17: -305.475 | J17: -353.436 | K17: -372.686 | L17: -419.258 | M17: -434.048
B18: Gross profit | C18: GROSS PROFIT | D18: 1075.563 | E18: 1161.576 | F18: 1245.786 | G18: 1314.69 | H18: 1542.066 | I18: 1652.891 | J18: 1721.979 | K18: 1560.344 | L18: 1878.851 | M18: 1719.59
B19: Total operating expenses | C19: TOTAL OPERATING EXPENSES | D19: -975.115 | E19: -1005.407 | F19: -1031.064 | G19: -1084.744 | H19: -1195.3 | I19: -1165.927 | J19: -1226.623 | K19: -1337.536 | L19: -1521.306 | M19: -1552.973
B20: Research and development | C20: RESEARCH AND DEVELOPMENT | D20: -414.201 | E20: -451.794 | F20: -475.329 | G20: -491.564 | H20: -548.139 | I20: -529.888 | J20: -536.666 | K20: -624.656 | L20: -750.559 | M20: -767.497
B21: Selling and marketing | C21: SELLING AND MARKETING | D21: -333.836 | E21: -349.731 | F21: -356.169 | G21: -394.06 | H21: -423.046 | I21: -416.425 | J21: -452.214 | K21: -466.565 | L21: -490.804 | M21: -510.668
B22: General and administrative | C22: GENERAL AND ADMINISTRATIVE | D22: -148.941 | E22: -137.441 | F22: -142.604 | G22: -165.244 | H22: -177.769 | I22: -173.579 | J22: -184.446 | K22: -179.98 | L22: -218.758 | M22: -220.647
B23: General and administrative excluding provision for / recovery of doubtful accounts and acquisition and integration costs | C23: GENERAL AND ADMINISTRATIVE EXCLUDING PROVISION FOR / RECOVERY OF DOUBTFUL ACCOUNTS AND ACQUISITION AND INTEGRATION COSTS | D23: -123.402 | E23: -132.828 | F23: -142.604 | G23: -160.133 | H23: -174.399 | I23: -169.548 | J23: -181.874 | K23: -179.382 | L23: -215.284 | M23: -220.647
B24: Provision for / recovery of doubtful accounts | C24: PROVISION FOR / RECOVERY OF DOUBTFUL ACCOUNTS | D24: - | E24: - | F24: - | G24: - | H24: - | I24: - | J24: - | K24: - | L24: - | M24: -
B25: Acquisition and integration costs | C25: ACQUISITION AND INTEGRATION COSTS | D25: -25.539 | E25: -4.613 | F25: 0 | G25: -5.111 | H25: -3.37 | I25: -4.031 | J25: -2.572 | K25: -0.598 | L25: -3.474 | M25: 0
B26: Gain on lease settlement | C26: GAIN ON LEASE SETTLEMENT | D26: 0 | E26: 0 | F26: 0 | G26: 0 | H26: 0 | I26: 0 | J26: 0 | K26: 0 | L26: 0 | M26: 0
B27: Goodwill impairment | C27: GOODWILL IMPAIRMENT | D27: 0 | E27: 0 | F27: 0 | G27: 0 | H27: 0 | I27: 0 | J27: 0 | K27: 0 | L27: 0 | M27: 0
B28: Long-lived asset impairment | C28: LONG-LIVED ASSET IMPAIRMENT | D28: 0 | E28: 0 | F28: 0 | G28: 0 | H28: 0 | I28: 0 | J28: 0 | K28: 0 | L28: 0 | M28: 0
B29: Change in fair value of contingent consideration | C29: CHANGE IN FAIR VALUE OF CONTINGENT CONSIDERATION | D29: 0 | E29: 0 | F29: 0 | G29: 0 | H29: 0 | I29: 0 | J29: 0 | K29: 0 | L29: 0 | M29: 0
B30: Restructuring costs / recoveries | C30: RESTRUCTURING COSTS / RECOVERIES | D30: -8.626 | E30: -4.933 | F30: -23.933 | G30: -18.139 | H30: -24.538 | I30: -22.652 | J30: -29.565 | K30: -33.824 | L30: -23.834 | M30: -24.592
B31: Amortization of intangible assets | C31: AMORTIZATION OF INTANGIBLE ASSETS | D31: -69.511 | E31: -61.508 | F31: -33.029 | G31: -15.737 | H31: -21.808 | I31: -23.383 | J31: -23.732 | K31: -32.511 | L31: -37.351 | M31: -29.569
B32: Income / loss from operations | C32: INCOME / LOSS FROM OPERATIONS | D32: 100.448 | E32: 156.169 | F32: 214.722 | G32: 229.946 | H32: 346.766 | I32: 486.964 | J32: 495.356 | K32: 222.808 | L32: 357.545 | M32: 166.617
B33: Interest and other income / loss, net | C33: INTEREST AND OTHER INCOME / LOSS NET | D33: -25.505 | E33: -12.795 | F33: -2.744 | G33: -25.916 | H33: 3.876 | I33: 0.318 | J33: -1.768 | K33: 6.747 | L33: 54.134 | M33: 50.261
B34: Interest and other income / loss, net excluding loss on extinguishment and modification of debt | C34: INTEREST AND OTHER INCOME / LOSS NET EXCLUDING LOSS ON EXTINGUISHMENT AND MODIFICATION OF DEBT | D34: 0 | E34: -12.569 | F34: 0.913 | G34: -12.029 | H34: 3.876 | I34: 0.964 | J34: -1.768 | K34: 6.747 | L34: 62.008 | M34: 50.261
B35: Loss on extinguishment and modification of debt | C35: LOSS ON EXTINGUISHMENT AND MODIFICATION OF DEBT | D35: 0 | E35: -0.226 | F35: -3.657 | G35: -13.887 | H35: 0 | I35: -0.646 | J35: 0 | K35: 0 | L35: -7.874 | M35: 0
B36: Interest expense | C36: INTEREST EXPENSE | D36: -51.179 | E36: -56.656 | F36: -55.852 | G36: -55.249 | H36: -37.452 | I36: -31.321 | J36: -30.837 | K36: -47.05 | L36: -88.026 | M36: -97.028
... B43: Net loss / income | C43: NI | D43: 11.667 | E43: 72.584 | F43: 1261.953 | G43: -344.69 | H43: 253.434 | I43: 361.291 | J43: 500.196 | K43: 152.902 | L43: 254.827 | M43: 83.956
B44: Per share | C44: PER SHARE | D44: - | E44: - | F44: - | G44: - | H44: - | I44: - | J44: - | K44: - | L44: - | M44: -
B45: Basic | C45: BASIC | D45: 0.1 | E45: 0.52 | F45: 8.89 | G45: -2.4 | H45: 1.63 | I45: 2.34 | J45: 3.22 | K45: 1.01 | L45: 1.71 | M45: 0.58
B46: Diluted | C46: DILUTED | D46: 0.1 | E46: 0.51 | F46: 7.53 | G46: -2.49 | H46: 1.61 | I46: 2.32 | J46: 3.19 | K46: 1 | L46: 1.71 | M46: 0.58
B47: Weighted average shares | C47: WEIGHTED AVERAGE SHARES | D47: - | E47: - | F47: - | G47: - | H47: - | I47: - | J47: - | K47: - | L47: - | M47: -
B48: Basic | C48: BASIC2 | D48: 118.416 | E48: 138.312 | F48: 141.997 | G48: 143.738 | H48: 155.72 | I48: 154.287 | J48: 155.279 | K48: 151.208 | L48: 148.971 | M48: 144.715
B49: Diluted | C49: DILUTED2 | D49: 120.101 | E49: 150.704 | F49: 169.919 | G49: 143.738 | H49: 157.612 | I49: 155.955 | J49: 156.743 | K49: 152.193 | L49: 149.38 | M49: 145.964
D50: -
D51: -
D52: -
D53: -
D54: -
D55: -
D56: -
D57: -
D58: -
D59: -
D60: -
D61: -
D62: -

Sheet CF_Static
I1: Next Report Date: | J1: 45904 | K1: Last Refresh: | L1: 45828
I2: FYE Date: | J2: 45598
K3: Identifier | L3: CIEN-US | M3: 1 | P3: original | Q3: restated | R3: Units | S3: M
K4: Start Date | L4: -9 | O4: 1 | P4: ANN | Q4: ANN_R | R4: Billions | S4: B
K5: End Date | L5: 0 | O5: 2 | P5: QTR | Q5: QTR_R | R5: Millions | S5: M
K6: Frequency | L6: Fiscal Years | M6: ANN | N6: ANN_R | O6: 3 | P6: SEMI | Q6: SEMI_R | R6: Thousands | S6: T
K7: Report Basis | L7: Restated | M7: ANN_R | O7: 4 | P7: YTD | Q7: YTD_R
K8: Units | L8: Millions
B9: Ciena Corporation
B11: Cash Flow | D11: 42307 | E11: 42674 | F11: 43039 | G11: 43404 | H11: 43769 | I11: 44134 | J11: 44498 | K11: 44865 | L11: 45230 | M11: 45596
B12: Net cash provided by / used in operating activities | C12: NET CASH PROVIDED BY / USED IN OPERATING ACTIVITIES | D12: 262.112 | E12: 289.52 | F12: 234.882 | G12: 229.261 | H12: 413.14 | I12: 493.654 | J12: 541.646 | K12: -167.756 | L12: 168.332 | M12: 514.532
B13: Net loss / income | C13: NET LOSS / INCOME | D13: 11.667 | E13: 72.584 | F13: 1261.953 | G13: -344.69 | H13: 253.434 | I13: 361.291 | J13: 500.196 | K13: 152.902 | L13: 254.827 | M13: 83.956
B14: Adjustments to reconcile net loss / income to net cash provided by / used in operating activities | C14: ADJUSTMENTS TO RECONCILE NET LOSS / INCOME TO NET CASH PROVIDED BY / USED IN OPERATING ACTIVITIES | D14: 250.445 | E14: 216.936 | F14: -1027.071 | G14: 573.951 | H14: 159.706 | I14: 132.363 | J14: 41.45 | K14: -320.658 | L14: -86.495 | M14: 430.576
B15: Gain / loss on extinguishment of debt | C15: GAIN / LOSS ON EXTINGUISHMENT OF DEBT | D15: - | E15: 0 | F15: 0 | G15: 10.039 | H15: - | I15: - | J15: 0 | K15: 0 | L15: 1.864 | M15: 0
B16: Realized loss due to impairment of marketable debt investments | C16: REALIZED LOSS DUE TO IMPAIRMENT OF MARKETABLE DEBT INVESTMENTS | D16: - | E16: - | F16: - | G16: - | H16: - | I16: - | J16: - | K16: - | L16: - | M16: -
B17: Non-cash impairment of long-lived assets | C17: NON-CASH IMPAIRMENT OF LONG-LIVED ASSETS | D17: - | E17: - | F17: - | G17: - | H17: - | I17: - | J17: - | K17: - | L17: - | M17: -
B18: Change in fair value of contingent consideration | C18: CHANGE IN FAIR VALUE OF CONTINGENT CONSIDERATION | D18: - | E18: - | F18: - | G18: - | H18: - | I18: - | J18: - | K18: - | L18: - | M18: -
B19: Loss on fair value of debt conversion liability | C19: LOSS ON FAIR VALUE OF DEBT CONVERSION LIABILITY | D19: - | E19: 0 | F19: 0 | G19: 12.07 | H19: - | I19: - | J19: - | K19: - | L19: - | M19: -
B20: Depreciation of equipment, building, furniture and fixtures, and amortization of leasehold improvements | C20: DEPRECIATION OF EQUIPMENT BUILDING FURNITURE AND FIXTURES AND AMORTIZATION OF LEASEHOLD IMPROVEMENTS | D20: 55.901 | E20: 63.394 | F20: 77.189 | G20: 84.214 | H20: 87.576 | I20: 93.908 | J20: 96.233 | K20: 95.922 | L20: 92.564 | M20: 92.846
B21: Share-based compensation costs | C21: SHARE-BASED COMPENSATION COSTS | D21: 55.34 | E21: 51.993 | F21: 48.36 | G21: 52.972 | H21: 59.736 | I21: 67.758 | J21: 84.336 | K21: 105.131 | L21: 130.455 | M21: 156.404
B22: Impairment of goodwill | C22: IMPAIRMENT OF GOODWILL | D22: - | E22: - | F22: - | G22: - | H22: - | I22: - | J22: - | K22: - | L22: - | M22: -
B23: Amortization of intangible assets | C23: AMORTIZATION OF INTANGIBLE ASSETS | D23: 79.866 | E23: 78.298 | F23: 45.713 | G23: 25.806 | H23: 35.136 | I23: 38.619 | J23: 36.033 | K23: 44.281 | L23: 49.616 | M23: 40.624
B24: Other | C24: OTHER | D24: 27.373 | E24: 25.514 | F24: -1086.094 | G24: 488.016 | H24: 25.695 | I24: 84.822 | J24: -141.944 | K24: -27.502 | L24: -25.449 | M24: -65.042
B25: Change in fair value of embedded redemption feature | C25: CHANGE IN FAIR VALUE OF EMBEDDED REDEMPTION FEATURE | D25: 0 | E25: 0 | F25: 0 | G25: 0 | H25: 0 | I25: 0 | J25: 0 | K25: 0 | L25: 0 | M25: 0
B26: Other excluding change in fair value of embedded redemption feature | C26: OTHER EXCLUDING CHANGE IN FAIR VALUE OF EMBEDDED REDEMPTION FEATURE | D26: 27.373 | E26: 25.514 | F26: -1086.094 | G26: 488.016 | H26: 25.695 | I26: 84.822 | J26: -141.944 | K26: -27.502 | L26: -25.449 | M26: -65.042
B27: Amortization of discount / premium on marketable securities | C27: AMORTIZATION OF DISCOUNT / PREMIUM ON MARKETABLE SECURITIES | D27: - | E27: - | F27: - | G27: - | H27: - | I27: - | J27: - | K27: - | L27: - | M27: -
B28: Other excluding amortization of discount / premium on marketable securities | C28: OTHER EXCLUDING AMORTIZATION OF DISCOUNT / PREMIUM ON MARKETABLE SECURITIES | D28: 27.373 | E28: 25.514 | F28: -1086.094 | G28: 488.016 | H28: 25.695 | I28: 84.822 | J28: -141.944 | K28: -27.502 | L28: -25.449 | M28: -65.042
B29: Deferred tax provision / benefit | C29: DEFERRED TAX PROVISION / BENEFIT | D29: 0 | E29: -1.116 | F29: -1126.732 | G29: 463.631 | H29: 19.865 | I29: 64.339 | J29: -156.469 | K29: -27.502 | L29: -14.852 | M29: -76.81
B30: Other excluding deferred tax provision / benefit | C30: OTHER EXCLUDING DEFERRED TAX PROVISION / BENEFIT | D30: 27.373 | E30: 26.63 | F30: 40.638 | G30: 24.385 | H30: 5.83 | I30: 20.483 | J30: 14.525 | K30: 0 | L30: -10.597 | M30: 11.768
B31: Provision for doubtful accounts | C31: PROVISION FOR DOUBTFUL ACCOUNTS | D31: 1.576 | E31: 1.701 | F31: 18.221 | G31: 2.7 | H31: - | I31: - | J31: - | K31: - | L31: - | M31: -
B32: Gain on cost method equity investments, net | C32: GAIN ON COST METHOD EQUITY INVESTMENTS NET | D32: - | E32: - | F32: - | G32: - | H32: - | I32: - | J32: -0.164 | K32: -4.12 | L32: -26.368 | M32: 0
B33: Other excluding provision for doubtful accounts | C33: OTHER EXCLUDING PROVISION FOR DOUBTFUL ACCOUNTS | D33: 25.797 | E33: 24.929 | F33: 22.417 | G33: 21.685 | H33: - | I33: - | J33: 14.689 | K33: 4.12 | L33: 15.771 | M33: 11.768
B34: Gain / loss on cost method investments | C34: GAIN / LOSS ON COST METHOD INVESTMENTS | D34: - | E34: - | F34: - | G34: - | H34: - | I34: - | J34: - | K34: - | L34: - | M34: -
B35: Provision for inventory excess and obsolescence | C35: PROVISION FOR INVENTORY EXCESS AND OBSOLESCENCE | D35: 26.846 | E35: 33.713 | F35: 35.459 | G35: 30.615 | H35: 28.085 | I35: 24.701 | J35: 17.85 | K35: 16.184 | L35: 29.464 | M35: 77.341
B36: Provision for warranty | C36: PROVISION FOR WARRANTY | D36: 17.881 | E36: 15.483 | F36: 7.965 | G36: 20.992 | H36: 23.105 | I36: 22.417 | J36: 17.093 | K36: 17.44 | L36: 31.742 | M36: 25.643
B37: Changes in assets and liabilities | C37: CHANGES IN ASSETS AND LIABILITIES | D37: -12.762 | E37: -51.459 | F37: -155.663 | G37: -150.773 | H37: -99.627 | I37: -199.862 | J37: -68.151 | K37: -572.114 | L37: -396.751 | M37: 102.76
B38: Accounts receivable | C38: ACCOUNTS RECEIVABLE | D38: -37.297 | E38: -26.074 | F38: -66.123 | G38: -168.357 | H38: 65.712 | I38: -17.299 | J38: -174.377 | K38: -47.069 | L38: -94.565 | M38: 80.313
B39: Inventories | C39: INVENTORIES | D39: 46.898 | E39: -53 | F39: -91.567 | G39: -27.445 | H39: -112.941 | I39: -25.044 | J39: -47.567 | K39: -589.113 | L39: -132.497 | M39: 153.021
B40: Prepaid expenses and other | C40: PREPAID EXPENSES AND OTHER | D40: -46.383 | E40: 30.047 | F40: -33.834 | G40: -21.425 | H40: -96.618 | I40: -38.998 | J40: -19.691 | K40: -58.996 | L40: -51.965 | M40: -198.91
B41: Operating lease right-of-use assets | C41: OPERATING LEASE RIGHT-OF-USE ASSETS | D41: 0 | E41: 0 | F41: 0 | G41: 0 | H41: 0 | I41: 16.787 | J41: 16.632 | K41: 16.453 | L41: 14.19 | M41: 11.837
B42: Accounts payable, accruals and other obligations | C42: ACCOUNTS PAYABLE ACCRUALS AND OTHER OBLIGATIONS | D42: -10.505 | E42: 7.153 | F42: 33.897 | G42: 85.798 | H42: 27.74 | I42: -117.931 | J42: 162.134 | K42: 100.327 | L42: -138.469 | M42: 64.255
B43: Accounts payable, accruals and other obligations excluding income taxes payable | C43: ACCOUNTS PAYABLE ACCRUALS AND OTHER OBLIGATIONS EXCLUDING INCOME TAXES PAYABLE | D43: - | E43: - | F43: - | G43: - | H43: - | I43: - | J43: - | K43: - | L43: - | M43: -
B44: Income taxes payable | C44: INCOME TAXES PAYABLE | D44: - | E44: - | F44: - | G44: - | H44: - | I44: - | J44: - | K44: - | L44: - | M44: -
B45: Deferred revenue | C45: DEFERRED REVENUE | D45: 34.525 | E45: -9.585 | F45: 1.964 | G45: -19.344 | H45: 16.48 | I45: 2.519 | J45: 16.822 | K45: 26.38 | L45: 27.412 | M45: 9.884
B46: Short and long-term operating lease liabilities | C46: SHORT AND LONG-TERM OPERATING LEASE LIABILITIES | D46: 0 | E46: 0 | F46: 0 | G46: 0 | H46: 0 | I46: -19.896 | J46: -22.104 | K46: -20.096 | L46: -20.857 | M46: -17.64
B47: Net cash used in / provided by investing activities | C47: NET CASH USED IN / PROVIDED BY INVESTING ACTIVITIES | D47: -43.127 | E47: -296.259 | F47: -61.373 | G47: -19.383 | H47: 24.077 | I47: -220.242 | J47: -90.717 | K47: -101.248 | L47: -383.454 | M47: -306.477
B48: Payments for equipment, furniture, fixtures and intellectual property | C48: PAYMENTS FOR EQUIPMENT FURNITURE FIXTURES AND INTELLECTUAL PROPERTY | D48: -62.109 | E48: -107.185 | F48: -94.6 | G48: -67.616 | H48: -62.579 | I48: -82.667 | J48: -79.55 | K48: -90.818 | L48: -106.197 | M48: -136.641
B49: Proceeds from sale of equipment, furniture and fixtures | C49: PROCEEDS FROM SALE OF EQUIPMENT FURNITURE AND FIXTURES | D49: - | E49: - | F49: - | G49: - | H49: - | I49: - | J49: - | K49: - | L49: - | M49: -
B50: Restricted cash | C50: RESTRICTED CASH | D50: -0.04 | E50: 0.011 | F50: - | G50: - | H50: - | I50: - | J50: - | K50: - | L50: - | M50: -
B51: Purchase of available for sale securities | C51: PURCHASE OF AVAILABLE FOR SALE SECURITIES | D51: -245.323 | E51: -365.191 | F51: -299.038 | G51: -286.824 | H51: -158.074 | I51: -223.196 | J51: -170.525 | K51: -647.526 | L51: -252.329 | M51: -287.536
B52: Proceeds from maturities of available for sale securities | C52: PROCEEDS FROM MATURITIES OF AVAILABLE FOR SALE SECURITIES | D52: 229.133 | E52: 212.106 | F52: 332.265 | G52: 419.494 | H52: 247.397 | I52: 113.921 | J52: 154.68 | K52: 707.139 | L52: 205.12 | M52: 139.382
B53: Proceeds from maturities of available for sale securities excluding settlement of foreign currency forward contracts, net | C53: PROCEEDS FROM MATURITIES OF AVAILABLE FOR SALE SECURITIES EXCLUDING SETTLEMENT OF FOREIGN CURRENCY FORWARD CONTRACTS NET | D53: 205 | E53: 230.612 | F53: 335.075 | G53: 410.109 | H53: 248.748 | I53: 110.39 | J53: 150 | K53: 702.197 | L53: 208.104 | M53: 140.836
B54: Settlement of foreign currency forward contracts, net | C54: SETTLEMENT OF FOREIGN CURRENCY FORWARD CONTRACTS NET | D54: 24.133 | E54: -18.506 | F54: -2.81 | G54: 9.385 | H54: -1.351 | I54: 3.531 | J54: 4.68 | K54: 4.942 | L54: -2.984 | M54: -1.454
B55: Proceeds from sales of available for sale securities | C55: PROCEEDS FROM SALES OF AVAILABLE FOR SALE SECURITIES | D55: 0 | E55: 0 | F55: 0 | G55: 0 | H55: 0 | I55: 0 | J55: 0 | K55: 0 | L55: 0 | M55: 0
B56: Minority equity investments, net | C56: MINORITY EQUITY INVESTMENTS NET | D56: 0 | E56: 0 | F56: 0 | G56: 0 | H56: 0 | I56: 0 | J56: 0 | K56: 0 | L56: 0 | M56: 0
B57: Proceeds from sale of cost method investment | C57: PROCEEDS FROM SALE OF COST METHOD INVESTMENT | D57: 0 | E57: 0 | F57: 0 | G57: 0 | H57: 0 | I57: 0 | J57: 4.678 | K57: 0 | L57: 0 | M57: 0
B58: Purchase of cost method investment | C58: PURCHASE OF COST METHOD INVESTMENT | D58: -2 | E58: -4 | F58: 0 | G58: -1.767 | H58: -2.667 | I58: 0 | J58: 0 | K58: -8 | L58: 0 | M58: -21.682
B59: Acquisition of business, net of cash acquired | C59: ACQUISITION OF BUSINESS NET OF CASH ACQUIRED | D59: 37.212 | E59: -32 | F59: 0 | G59: -82.67 | H59: 0 | I59: -28.3 | J59: 0 | K59: -62.043 | L59: -230.048 | M59: 0
B60: Receipt of contingent consideration related to business acquisition | C60: RECEIPT OF CONTINGENT CONSIDERATION RELATED TO BUSINESS ACQUISITION | D60: - | E60: - | F60: - | G60: - | H60: - | I60: - | J60: - | K60: - | L60: - | M60: -
B61: Net cash provided by / used in financing activities | C61: NET CASH PROVIDED BY / USED IN FINANCING ACTIVITIES | D61: -8.051 | E61: -4.228 | F61: -311.051 | G61: -99.229 | H61: -278.966 | I61: -87.222 | J61: -116.835 | K61: -133.055 | L61: 229.38 | M61: -285.061
B62: Proceeds from issuance of senior convertible notes payable | C62: PROCEEDS FROM ISSUANCE OF SENIOR CONVERTIBLE NOTES PAYABLE | D62: 0 | E62: 0 | F62: 0 | G62: 0 | H62: 0 | I62: 0 | J62: 0 | K62: 400 | L62: 0 | M62: 0
B63: Proceeds from issuance of long-term debt, net | C63: PROCEEDS FROM ISSUANCE OF LONG-TERM DEBT NET | D63: 0 | E63: 248.75 | F63: 0 | G63: 305.125 | H63: 0 | I63: 0 | J63: 0 | K63: 0 | L63: 497.5 | M63: 0
B64: Payment for debt conversion liability | C64: PAYMENT FOR DEBT CONVERSION LIABILITY | D64: 0 | E64: 0 | F64: 0 | G64: 0 | H64: -111.268 | I64: 0 | J64: 0 | K64: 0 | L64: 0 | M64: 0
B65: Payment for make-whole provision upon conversion of long-term debt | C65: PAYMENT FOR MAKE-WHOLE PROVISION UPON CONVERSION OF LONG-TERM DEBT | D65: 0 | E65: 0 | F65: 0 | G65: -13.453 | H65: 0 | I65: 0 | J65: 0 | K65: 0 | L65: 0 | M65: 0
B66: Payment for modification of term loans | C66: PAYMENT FOR MODIFICATION OF TERM LOANS | D66: 0 | E66: 0 | F66: -93.625 | G66: 0 | H66: 0 | I66: 0 | J66: 0 | K66: 0 | L66: 0.83 | M66: 0
B67: Proceeds from modification of term loan | C67: PROCEEDS FROM MODIFICATION OF TERM LOAN | D67: 0 | E67: 0 | F67: 0 | G67: 0 | H67: 0 | I67: 0 | J67: 0 | K67: 0 | L67: 0.83 | M67: 0
B68: Payment for modification of term loans excluding payment for modification of term loans | C68: PAYMENT FOR MODIFICATION OF TERM LOANS EXCLUDING PAYMENT FOR MODIFICATION OF TERM LOANS | D68: 0 | E68: 0 | F68: 0 | G68: 0 | H68: 0 | I68: 0 | J68: 0 | K68: 0 | L68: 0 | M68: 0
B69: Cash paid for extinguishment of debt | C69: CASH PAID FOR EXTINGUISHMENT OF DEBT | D69: 0 | E69: 0 | F69: 0 | G69: 0 | H69: 0 | I69: 0 | J69: 0 | K69: 0 | L69: 0 | M69: 0
B70: Payment of long term debt | C70: PAYMENT OF LONG TERM DEBT | D70: -29.867 | E70: -266.116 | F70: -233.554 | G70: -292.73 | H70: -7 | I70: -5.198 | J70: -6.929 | K70: -5.197 | L70: -9.43 | M70: -11.7
B71: Payment for debt issuance costs | C71: PAYMENT FOR DEBT ISSUANCE COSTS | D71: -0.421 | E71: -3.987 | F71: -0.722 | G71: -1.936 | H71: -1.191 | I71: -0.382 | J71: 0 | K71: -5.484 | L71: -6.379 | M71: -2.554
B72: Purchase of call spread option | C72: PURCHASE OF CALL SPREAD OPTION | D72: 0 | E72: 0 | F72: 0 | G72: 0 | H72: 0 | I72: 0 | J72: 0 | K72: 0 | L72: 0 | M72: 0
... B87: Cash and cash equivalents at end of period | C87: CASH AND CASH EQUIVALENTS AT END OF PERIOD | D87: 790.971 | E87: 777.615 | F87: 640.641 | G87: 745.434 | H87: 904.161 | I87: 1088.708 | J87: 1422.604 | K87: 994.378 | L87: 1010.786 | M87: 935.026
B88: Supplemental disclosure | C88: SUPPLEMENTAL DISCLOSURE | D88: - | E88: - | F88: - | G88: - | H88: - | I88: - | J88: - | K88: - | L88: - | M88: -
B89: Cash paid during the period for interest | C89: CASH PAID DURING THE PERIOD FOR INTEREST | D89: -40.772 | E89: -46.897 | F89: -47.235 | G89: -44.75 | H89: -39.579 | I89: -32.837 | J89: -29.864 | K89: -42.812 | L89: -84.465 | M89: -92.515
B90: Cash paid / refunded during the period for income taxes, net | C90: CASH PAID / REFUNDED DURING THE PERIOD FOR INCOME TAXES NET | D90: -10.668 | E90: -15.268 | F90: -22.136 | G90: -26.9 | H90: -33.57 | I90: -53.076 | J90: -73.127 | K90: -34.967 | L90: -78.242 | M90: -54.956
B91: Operating lease payments | C91: OPERATING LEASE PAYMENTS | D91: - | E91: - | F91: - | G91: 0 | H91: 0 | I91: 22.089 | J91: 24.058 | K91: 21.661 | L91: 22.782 | M91: 19.452
B92: Non-cash investing and financing activities | C92: NON-CASH INVESTING AND FINANCING ACTIVITIES | D92: - | E92: - | F92: - | G92: - | H92: - | I92: - | J92: - | K92: - | L92: - | M92: -
B93: Purchase of equipment in accounts payable | C93: PURCHASE OF EQUIPMENT IN ACCOUNTS PAYABLE | D93: 20.922 | E93: 15.03 | F93: 6.214 | G93: 5.118 | H93: 16.549 | I93: 7.854 | J93: 10.138 | K93: 12.373 | L93: 6.99 | M93: 14.682
B94: Fair value of vested options assumed in acquisition | C94: FAIR VALUE OF VESTED OPTIONS ASSUMED IN ACQUISITION | D94: - | E94: - | F94: - | G94: - | H94: - | I94: - | J94: - | K94: - | L94: - | M94: -
B95: Construction in progress subject to build-to-suit lease | C95: CONSTRUCTION IN PROGRESS SUBJECT TO BUILD-TO-SUIT LEASE | D95: 18.663 | E95: 39.914 | F95: - | G95: - | H95: - | I95: - | J95: - | K95: - | L95: - | M95: -
B96: Building subject to capital lease | C96: BUILDING SUBJECT TO CAPITAL LEASE | D96: 14.939 | E96: 8.993 | F96: 50.37 | G96: - | H96: - | I96: - | J96: - | K96: - | L96: - | M96: -
B97: Contingent consideration for acquisition of business | C97: CONTINGENT CONSIDERATION FOR ACQUISITION OF BUSINESS | D97: - | E97: 0 | F97: 0 | G97: 10.9 | H97: - | I97: - | J97: - | K97: - | L97: - | M97: -
B98: Repurchase of common stock in accrued liabilities from repurchase program | C98: REPURCHASE OF COMMON STOCK IN ACCRUED LIABILITIES FROM REPURCHASE PROGRAM | D98: - | E98: - | F98: - | G98: - | H98: 0 | I98: 0 | J98: 0.8 | K98: 0 | L98: 9.31 | M98: 6.172
B99: Conversion of debt conversion liability | C99: CONVERSION OF DEBT CONVERSION LIABILITY | D99: - | E99: - | F99: 0 | G99: 0 | H99: 52.944 | I99: - | J99: - | K99: - | L99: - | M99: -
B100: Operating lease right-of-use assets subject to lease liability | C100: OPERATING LEASE RIGHT-OF-USE ASSETS SUBJECT TO LEASE LIABILITY | D100: - | E100: - | F100: - | G100: 0 | H100: 0 | I100: 24.16 | J100: 4.356 | K100: 23.242 | L100: 10.236 | M100: 6.912
B101: Unrealized gain on equity investment | C101: UNREALIZED GAIN ON EQUITY INVESTMENT | D101: - | E101: - | F101: - | G101: 0 | H101: 0 | I101: 2.681 | J101: 0.164 | K101: 4.12 | L101: 26.368 | M101: 0
B102: Conversion of 3.75% convertible senior notes | C102: CONVERSION OF 3.75% CONVERTIBLE SENIOR NOTES | D102: - | E102: 0 | F102: 0 | G102: 61.27 | H102: - | I102: - | J102: - | K102: - | L102: - | M102: -
B103: Conversion of 4.0% convertible senior notes | C103: CONVERSION OF 4.0% CONVERTIBLE SENIOR NOTES | D103: 180.645 | E103: 0 | F103: 0 | G103: 214.286 | H103: - | I103: - | J103: - | K103: - | L103: - | M103: -
B104: Equipment acquired under capital lease | C104: EQUIPMENT ACQUIRED UNDER CAPITAL LEASE | D104: 0.464 | E104: 5.322 | F104: - | G104: - | H104: - | I104: - | J104: - | K104: - | L104: - | M104: -
B105: Conversion of 8.0% convertible senior notes | C105: CONVERSION OF 8.0% CONVERTIBLE SENIOR NOTES | D105: 117.14 | E105: - | F105: - | G105: - | H105: - | I105: - | J105: - | K105: - | L105: - | M105: -
B106: Fair value of shares issued related to acquisition of business | C106: FAIR VALUE OF SHARES ISSUED RELATED TO ACQUISITION OF BUSINESS | D106: 302.114 | E106: - | F106: - | G106: - | H106: - | I106: - | J106: - | K106: - | L106: - | M106: -
D107: -
D108: -
D109: -
D110: -
D111: -
D112: -
D113: -
D114: -
D115: -
...

Sheet BS_Static
I1: Next Report Date: | J1: 45904 | K1: Last Refresh: | L1: 45828
I2: FYE Date: | J2: 45598
K3: Identifier | L3: CIEN-US | M3: 1 | P3: original | Q3: restated | R3: Units | S3: M
K4: Start Date | L4: -9 | O4: 1 | P4: ANN | Q4: ANN_R | R4: Billions | S4: B
K5: End Date | L5: 0 | O5: 2 | P5: QTR | Q5: QTR_R | R5: Millions | S5: M
K6: Frequency | L6: Fiscal Years | M6: ANN | N6: ANN_R | O6: 3 | P6: SEMI | Q6: SEMI_R | R6: Thousands | S6: T
K7: Report Basis | L7: Restated | M7: ANN_R | O7: 4 | P7: YTD | Q7: YTD_R
K8: Units | L8: Millions
B9: Ciena Corporation
B11: Balance Sheet | D11: 42307 | E11: 42674 | F11: 43039 | G11: 43404 | H11: 43769 | I11: 44134 | J11: 44498 | K11: 44865 | L11: 45230 | M11: 45596
B12: Total assets | C12: TA | D12: 2695.051 | E12: 2873.575 | F12: 3951.711 | G12: 3756.523 | H12: 3893.346 | I12: 4180.917 | J12: 4865.227 | K12: 5069.632 | L12: 5601.495 | M12: 5641.337
B13: Total current assets | C13: TOTAL CURRENT ASSETS | D13: 1864.21 | E13: 2013.192 | F13: 2006.311 | G13: 2142.602 | H13: 2381.802 | I13: 2611.159 | J13: 3188.906 | K13: 3385.896 | L13: 3575.779 | M13: 3544.416
B14: Cash and cash equivalents | C14: CASH AND CASH EQUIVALENTS | D14: 790.971 | E14: 777.615 | F14: 640.513 | G14: 745.423 | H14: 904.045 | I14: 1088.624 | J14: 1422.546 | K14: 994.352 | L14: 1010.618 | M14: 934.863
B15: Short-term investments | C15: SHORT-TERM INVESTMENTS | D15: 135.107 | E15: 275.248 | F15: 279.133 | G15: 148.981 | H15: 109.94 | I15: 150.667 | J15: 181.483 | K15: 153.989 | L15: 104.753 | M15: 316.343
B16: Accounts receivable, net of allowance for doubtful accounts | C16: ACCOUNTS RECEIVABLE NET OF ALLOWANCE FOR DOUBTFUL ACCOUNTS | D16: 550.792 | E16: 576.235 | F16: 622.183 | G16: 786.502 | H16: 724.854 | I16: 719.405 | J16: 884.958 | K16: 920.772 | L16: 1003.876 | M16: 908.597
B17: Inventories | C17: INVENTORIES | D17: 191.162 | E17: 211.251 | F17: 267.143 | G17: 262.751 | H17: 345.049 | I17: 344.379 | J17: 374.265 | K17: 946.73 | L17: 1050.838 | M17: 820.43
B18: Prepaid expenses and other | C18: PREPAID EXPENSES AND OTHER | D18: 196.178 | E18: 172.843 | F18: 197.339 | G18: 198.945 | H18: 297.914 | I18: 308.084 | J18: 325.654 | K18: 370.053 | L18: 405.694 | M18: 564.183
B19: Long-term investments | C19: LONG-TERM INVESTMENTS | D19: 95.105 | E19: 90.172 | F19: 49.783 | G19: 58.97 | H19: 10.014 | I19: 82.226 | J19: 70.038 | K19: 35.385 | L19: 134.278 | M19: 80.92
B20: Equipment, building, furniture and fixtures, net | C20: EQUIPMENT BUILDING FURNITURE AND FIXTURES NET | D20: 191.973 | E20: 288.406 | F20: 308.465 | G20: 292.067 | H20: 286.884 | I20: 272.377 | J20: 284.968 | K20: 267.779 | L20: 280.147 | M20: 337.722
B21: Operating lease right-of-use assets | C21: OPERATING LEASE RIGHT-OF-USE ASSETS | D21: - | E21: - | F21: - | G21: - | H21: 0 | I21: 57.026 | J21: 44.285 | K21: 45.108 | L21: 35.14 | M21: 27.417
B22: Goodwill | C22: GOODWILL | D22: 256.434 | E22: 266.974 | F22: 267.458 | G22: 297.968 | H22: 297.937 | I22: 310.847 | J22: 311.645 | K22: 328.322 | L22: 444.765 | M22: 444.707
B23: Other intangible assets, net | C23: OTHER INTANGIBLE ASSETS NET | D23: 202.673 | E23: 146.711 | F23: 100.997 | G23: 148.225 | H23: 112.781 | I23: 96.647 | J23: 65.314 | K23: 69.517 | L23: 205.627 | M23: 165.02
B24: Other long-term assets | C24: OTHER LONG-TERM ASSETS | D24: 84.656 | E24: 68.12 | F24: 1218.697 | G24: 816.691 | H24: 803.928 | I24: 750.635 | J24: 900.071 | K24: 937.625 | L24: 925.759 | M24: 1041.135
B25: Deferred tax asset, net | C25: DEFERRED TAX ASSET NET | D25: 0 | E25: 1.116 | F25: 1155.104 | G25: 745.039 | H25: 714.942 | I25: 647.805 | J25: 800.18 | K25: 824.008 | L25: 809.306 | M25: 886.441
B26: Other long-term assets excluding deferred tax asset, net | C26: OTHER LONG-TERM ASSETS EXCLUDING DEFERRED TAX ASSET NET | D26: 0 | E26: 67.004 | F26: 63.593 | G26: 71.652 | H26: 88.986 | I26: 102.83 | J26: 99.891 | K26: 113.617 | L26: 116.453 | M26: 154.694
B27: Total liabilities and stockholders’ equity / deficit | C27: LE | D27: 2695.051 | E27: 2873.575 | F27: 3951.711 | G27: 3756.523 | H27: 3893.346 | I27: 4180.917 | J27: 4865.227 | K27: 5069.632 | L27: 5601.495 | M27: 5641.337
B28: Total liabilities | C28: TOTAL LIABILITIES | D28: 2074.175 | E28: 2107.234 | F28: 1815.369 | G28: 1827.189 | H28: 1720.585 | I28: 1671.32 | J28: 1845.209 | K28: 2356.771 | L28: 2753.134 | M28: 2825.199
B29: Total current liabilities | C29: TOTAL CURRENT LIABILITIES | D29: 667.034 | E29: 891.545 | F29: 1037.743 | G29: 963.003 | H29: 845.94 | I29: 760.701 | J29: 909.03 | K29: 1040.583 | L29: 932.021 | M29: 999.84
B30: Accounts payable | C30: ACCOUNTS PAYABLE | D30: 222.14 | E30: 235.942 | F30: 260.098 | G30: 340.582 | H30: 344.819 | I30: 291.904 | J30: 356.176 | K30: 516.047 | L30: 317.828 | M30: 423.401
B31: Accrued liabilities | C31: ACCRUED LIABILITIES | D31: 316.283 | E31: 310.353 | F31: 322.934 | G31: 340.075 | H31: 382.74 | I31: 334.132 | J31: 409.285 | K31: 360.782 | L31: 431.419 | M31: 393.905
B32: Accrued liabilities excluding restructuring liabilities | C32: ACCRUED LIABILITIES EXCLUDING RESTRUCTURING LIABILITIES | D32: - | E32: - | F32: - | G32: - | H32: - | I32: - | J32: - | K32: - | L32: - | M32: -
B33: Restructuring liabilities | C33: RESTRUCTURING LIABILITIES | D33: - | E33: - | F33: - | G33: - | H33: - | I33: - | J33: - | K33: - | L33: - | M33: -
B34: Unfavorable lease commitments | C34: UNFAVORABLE LEASE COMMITMENTS | D34: - | E34: - | F34: - | G34: - | H34: - | I34: - | J34: - | K34: - | L34: - | M34: -
B35: Income tax payable | C35: INCOME TAX PAYABLE | D35: - | E35: - | F35: - | G35: - | H35: - | I35: - | J35: - | K35: - | L35: - | M35: -
B36: Deferred revenue | C36: DEFERRED REVENUE | D36: 126.111 | E36: 109.009 | F36: 102.418 | G36: 111.134 | H36: 111.381 | I36: 108.7 | J36: 118.007 | K36: 137.899 | L36: 154.419 | M36: 156.379
B37: Term loan payable | C37: TERM LOAN PAYABLE | D37: 0 | E37: 0 | F37: 0 | G37: 0 | H37: 0 | I37: 0 | J37: 0 | K37: 0 | L37: 0 | M37: 0
B38: Convertible notes payable | C38: CONVERTIBLE NOTES PAYABLE | D38: 0 | E38: 0 | F38: 0 | G38: 0 | H38: 0 | I38: 0 | J38: 0 | K38: 0 | L38: 0 | M38: 0
B39: Operating lease liabilities | C39: OPERATING LEASE LIABILITIES | D39: 0 | E39: 0 | F39: 0 | G39: 0 | H39: 0 | I39: 19.035 | J39: 18.632 | K39: 18.925 | L39: 16.655 | M39: 14.455
B40: Current portion of long-term debt | C40: CURRENT PORTION OF LONG-TERM DEBT | D40: 2.5 | E40: 236.241 | F40: 352.293 | G40: 7 | H40: 7 | I40: 6.93 | J40: 6.93 | K40: 6.93 | L40: 11.7 | M40: 11.7
B41: Debt conversion liability | C41: DEBT CONVERSION LIABILITY | D41: 0 | E41: 0 | F41: 0 | G41: 164.212 | H41: 0 | I41: 0 | J41: 0 | K41: 0 | L41: 0 | M41: 0
B42: Long-term deferred revenue | C42: LONG-TERM DEFERRED REVENUE | D42: 62.962 | E42: 73.854 | F42: 82.589 | G42: 58.323 | H42: 45.492 | I42: 49.663 | J42: 57.457 | K42: 62.336 | L42: 74.041 | M42: 81.24
B43: Long-term unfavorable lease commitments | C43: LONG-TERM UNFAVORABLE LEASE COMMITMENTS | D43: 0 | E43: 0 | F43: 0 | G43: 0 | H43: 0 | I43: 0 | J43: 0 | K43: 0 | L43: 0 | M43: 0
B44: Other long-term obligations | C44: OTHER LONG-TERM OBLIGATIONS | D44: 72.54 | E44: 124.394 | F44: 111.349 | G44: 119.413 | H44: 148.747 | I44: 123.185 | J44: 166.803 | K44: 150.335 | L44: 170.407 | M44: 185.938
B45: Long-term restructuring liabilities | C45: LONG-TERM RESTRUCTURING LIABILITIES | D45: 0 | E45: 0 | F45: 0 | G45: 0 | H45: 0 | I45: 0 | J45: 0 | K45: 0 | L45: 0 | M45: 0
B46: Other long-term obligations excluding long-term restructuring liabilities | C46: OTHER LONG-TERM OBLIGATIONS EXCLUDING LONG-TERM RESTRUCTURING LIABILITIES | D46: 0 | E46: 0 | F46: 0 | G46: 0 | H46: 0 | I46: 0 | J46: 0 | K46: 0 | L46: 0 | M46: 0
B47: Long-term term loan payable | C47: LONG-TERM TERM LOAN PAYABLE | D47: 0 | E47: 0 | F47: 0 | G47: 0 | H47: 0 | I47: 0 | J47: 0 | K47: 0 | L47: 0 | M47: 0
... B54: Accumulated other comprehensive loss / income | C54: ACCUMULATED OTHER COMPREHENSIVE LOSS / INCOME | D54: -22.126 | E54: -24.329 | F54: -11.017 | G54: -5.78 | H54: -22.084 | I54: -35.358 | J54: 0.439 | K54: -46.645 | L54: -37.767 | M54: -46.711
B55: Changes in unrealized gains / losses on investments, net of income taxes | C55: CHANGES IN UNREALIZED GAINS / LOSSES ON INVESTMENTS NET OF INCOME TAXES | D55: - | E55: - | F55: - | G55: - | H55: - | I55: - | J55: - | K55: - | L55: - | M55: -
B56: Translation adjustment | C56: TRANSLATION ADJUSTMENT | D56: - | E56: - | F56: - | G56: - | H56: - | I56: - | J56: - | K56: - | L56: - | M56: -
B57: Accumulated deficit | C57: ACCUMULATED DEFICIT | D57: -5998.79 | E57: -5926.206 | F57: -4664.253 | G57: -4947.652 | H57: -4644.413 | I57: -4283.122 | J57: -3785.132 | K57: -3632.23 | L57: -3377.403 | M57: -3293.447
D58: -
D59: -
D60: -
D61: -
D62: -
D63: -
D64: -
D65: -
D66: -
D67: -
D68: -
D69: -
... D78: -
