Workbook
Name CS: Model!$F$10
Name current_year: Model!$C$11
Name debt: Model!$F$13
Name live_case: Model!$C$12
Name live_tax: Model!$C$20
Name live_tgr: Model!$C$19
Name live_wacc: Model!$C$18
Name net_cash: Model!$F$12

Sheet WACC
B2: META-US
E4: FY2024
B5: Debt | E5: =Model!F13 -> 28298
B6: % Debt | E6: =Model!F13/Model!F11 -> 0.014603302
B7: Cost of Debt | E7: =Debt!C33*0.01 -> 0.050568872
B8: tax rate | E8: =live_tax -> 0.2
E10: 45837
B11: Equity Value | E11: =Model!F11 -> 1937780.9
B12: % Equity | E12: =1-E6 -> 0.9853967
B13: Cost of Equity | E13: =E14+E15*E16 -> 0.097801
B14: Risk free Rate | E14: 0.04281
B15: Beta | E15: 1.27
B16: Market Risk Premium | E16: 0.0433
B18: WACC | E18: =E6*E7*(1-E8)+E13*E12 -> 0.09696356

Sheet Model
B2: META-US
A5: 1 | B5: Overview
E7: Current | H7: Future
B9: Ticker | C9: Meta | E9: $/Shr | F9: 733.63 | H9: Implied $/Shr | I9: =N110 -> 444.83443
B10: Date | C10: =TODAY() -> 45837 | E10: CS | F10: 2641.36 | H10: % imp. Move | I10: =I9/F9-1 -> -0.3936529
B11: Starting Year | C11: 2024 | E11: MC | F11: =F9*F10 -> 1937780.9 | H11: Fwrd FCE | I11: =F11/J100 -> 67.701668
B12: Live Scenario | C12: 2 | E12: Net Cash | F12: 70301
E13: Debt | F13: =28298 -> 28298
E14: EV | F14: =F11-F12+F13 -> 1895777.9
B16: Live Case | E16: Bear Case | H16: Street Case | K16: Bull Case
B17: # | C17: =live_case -> 2 | E17: # | F17: 1 | H17: # | I17: 2 | K17: # | L17: 3
B18: WACC | C18: =CHOOSE($C$17,F18,I18,L18) -> 0.0969 | E18: WACC | F18: 0.12 | H18: WACC | I18: 0.0969 | K18: WACC | L18: 0.09
B19: TGR | C19: =CHOOSE($C$17,F19,I19,L19) -> 0.04 | E19: TGR | F19: 0.04 | H19: TGR | I19: 0.04 | K19: TGR | L19: 0.05
B20: Tax Rate | C20: =CHOOSE($C$17,F20,I20,L20) -> 0.2 | E20: Tax Rate | F20: 0.3 | H20: Tax Rate | I20: 0.2 | K20: Tax Rate | L20: 0.19
A27: 2 | B27: Income Statement | D27: Units
J28: 1 | K28: 2 | L28: 3 | M28: 4 | N28: 5
B29: Year Ended | E29: =F29-1 -> 2020 | F29: =G29-1 -> 2021 | G29: =H29-1 -> 2022 | H29: =I29-1 -> 2023 | I29: =current_year -> 2024 | J29: =I29+1 -> 2025 | K29: =J29+1 -> 2026 | L29: =K29+1 -> 2027 | M29: =L29+1 -> 2028 | N29: =M29+1 -> 2029
B30: Revenue | E30: ='Income Statement_Static'!H11 -> 85965 | F30: ='Income Statement_Static'!I11 -> 117929 | G30: ='Income Statement_Static'!J11 -> 116609 | H30: ='Income Statement_Static'!K11 -> 134902 | I30: ='Income Statement_Static'!L11 -> 164501
B31: % growth | F31: =F30/E30-1 -> 0.37182574 | G31: =G30/F30-1 -> -0.011193176 | H31: =H30/G30-1 -> 0.15687468 | I31: =I30/H30-1 -> 0.21941113
B33: Cost of Goods Sold | E33: ='Income Statement_Static'!H12 -> 16692 | F33: ='Income Statement_Static'!I12 -> 22649 | G33: ='Income Statement_Static'!J12 -> 23754 | H33: ='Income Statement_Static'!K12 -> 26006 | I33: ='Income Statement_Static'!L12 -> 30130
B34: % of revenue | E34: =E33/E30 -> 0.19417205 | F34: =F33/F30 -> 0.19205624 | G34: =G33/G30 -> 0.2037064 | H34: =H33/H30 -> 0.19277698 | I34: =I33/I30 -> 0.18315998
B36: Gross Profit | E36: =E30-E33 -> 69273 | F36: =F30-F33 -> 95280 | G36: =G30-G33 -> 92855 | H36: =H30-H33 -> 108896 | I36: =I30-I33 -> 134371
B37: % of sales | E37: =E36/E30 -> 0.80582795 | F37: =F36/F30 -> 0.80794376 | G37: =G36/G30 -> 0.7962936 | H37: =H36/H30 -> 0.80722302 | I37: =I36/I30 -> 0.81684002
B39: SG&A | E39: ='Income Statement_Static'!H18 -> 36602 | F39: ='Income Statement_Static'!I18 -> 48527 | G39: ='Income Statement_Static'!J18 -> 59300 | H39: ='Income Statement_Static'!K18 -> 58693 | I39: ='Income Statement_Static'!L18 -> 64602
B40: % of sales | E40: =E39/E30 -> 0.42577793 | F40: =F39/F30 -> 0.41149336 | G40: =G39/G30 -> 0.50853708 | H40: =H39/H30 -> 0.4350788 | I40: =I39/I30 -> 0.39271494
B42: EBIT | E42: =E36-E39 -> 32671 | F42: =F36-F39 -> 46753 | G42: =G36-G39 -> 33555 | H42: =H36-H39 -> 50203 | I42: =I36-I39 -> 69769
B43: % of sales | E43: =E42/E30 -> 0.38005002 | F43: =F42/F30 -> 0.39645041 | G43: =G42/G30 -> 0.28775652 | H43: =H42/H30 -> 0.37214422 | I43: =I42/I30 -> 0.42412508
B45: Taxes | E45: ='Income Statement_Static'!H50 -> 4034 | F45: ='Income Statement_Static'!I50 -> 7914 | G45: ='Income Statement_Static'!J50 -> 5619 | H45: ='Income Statement_Static'!K50 -> 8330 | I45: ='Income Statement_Static'!L50 -> 8303
B46: % of sales | E46: =E45/E30 -> 0.046926075 | F46: =F45/F30 -> 0.067108175 | G46: =G45/G30 -> 0.048186675 | H46: =H45/H30 -> 0.061748529 | I46: =I45/I30 -> 0.050473857
B48: NOPAT | E48: =E42-E45 -> 28637 | F48: =F42-F45 -> 38839 | G48: =G42-G45 -> 27936 | H48: =H42-H45 -> 41873 | I48: =I42-I45 -> 61466
B49: % growth | F49: =F48/E48-1 -> 0.3562524 | G49: =G48/F48-1 -> -0.28072298 | H49: =H48/G48-1 -> 0.49889032 | I49: =I48/H48-1 -> 0.46791489
A51: 2 | B51: Cashflow Items | D51: Units
B53: Year Ended | E53: =F53-1 -> 2020 | F53: =G53-1 -> 2021 | G53: =H53-1 -> 2022 | H53: =I53-1 -> 2023 | I53: =current_year -> 2024 | J53: =I53+1 -> 2025 | K53: =J53+1 -> 2026 | L53: =K53+1 -> 2027 | M53: =L53+1 -> 2028 | N53: =M53+1 -> 2029
B54: NOPAT | E54: =E48 -> 28637 | F54: =F48 -> 38839 | G54: =G48 -> 27936 | H54: =H48 -> 41873 | I54: =I48 -> 61466
B56: D&A | E56: ='Income Statement_Static'!H14 -> 6862 | F56: ='Income Statement_Static'!I14 -> 7967 | G56: ='Income Statement_Static'!J14 -> 8686 | H56: ='Income Statement_Static'!K14 -> 11178 | I56: ='Income Statement_Static'!L14 -> 15498
B57: % of CapEx | E57: =E56/-E65 -> 0.45398611 | F57: =F56/-F65 -> 0.42909463 | G57: =G56/-G65 -> 0.27635137 | H57: =H56/-H65 -> 0.40996112 | I57: =I56/-I65 -> 0.41598669
B59: Deferred Taxes | E59: ='Cash Flow_Static'!H16 -> -1192 | F59: ='Cash Flow_Static'!I16 -> 609 | G59: ='Cash Flow_Static'!J16 -> -3286 | H59: ='Cash Flow_Static'!K16 -> 131 | I59: ='Cash Flow_Static'!L16 -> -4738
B60: % of
B62: Changes in WC | E62: ='Cash Flow_Static'!H22 -> -2723 | F62: ='Cash Flow_Static'!I22 -> 700 | G62: ='Cash Flow_Static'!J22 -> 5683 | H62: ='Cash Flow_Static'!K22 -> 3836 | I62: ='Cash Flow_Static'!L22 -> 1048
B63: % change in sales | E63: =ABS(E62)/E30 -> 0.031675682 | F63: =ABS(F62)/F30 -> 0.0059357749 | G63: =ABS(G62)/G30 -> 0.048735518 | H63: =ABS(H62)/H30 -> 0.028435457 | I63: =ABS(I62)/I30 -> 0.0063707819
B65: CapEx | E65: ='Cash Flow_Static'!H31 -> -15115 | F65: ='Cash Flow_Static'!I31 -> -18567 | G65: ='Cash Flow_Static'!J31 -> -31431 | H65: ='Cash Flow_Static'!K31 -> -27266 | I65: ='Cash Flow_Static'!L31 -> -37256
B66: % of sales | E66: =-E65/E30 -> 0.17582737 | F66: =-F65/F30 -> 0.15744219 | G66: =-G65/G30 -> 0.2695418 | H66: =-H65/H30 -> 0.20211709 | I66: =-I65/I30 -> 0.22647887
A68: 3 | B68: DCF | D68: Units
J69: 1 | K69: =+J69+1 -> 2 | L69: =+K69+1 -> 3 | M69: =+L69+1 -> 4 | N69: =+M69+1 -> 5
B70: Year Ended | E70: =F70-1 -> 2020 | F70: =G70-1 -> 2021 | G70: =H70-1 -> 2022 | H70: =I70-1 -> 2023 | I70: =current_year -> 2024 | J70: =I70+1 -> 2025 | K70: =J70+1 -> 2026 | L70: =K70+1 -> 2027 | M70: =L70+1 -> 2028 | N70: =M70+1 -> 2029
B71: Revenue | E71: =E30 -> 85965 | F71: =F30 -> 117929 | G71: =G30 -> 116609 | H71: =H30 -> 134902 | I71: =I30 -> 164501 | J71: =I71*(1+J72) -> 189176.15 | K71: =J71*(1+K72) -> 213769.05 | L71: =K71*(1+L72) -> 238352.49 | M71: =L71*(1+M72) -> 270530.08 | N71: =M71*(1+N72) -> 301641.04
B72: % growth | E72: =IFERROR(E71/D71-1, 0) -> 0 | F72: =IFERROR(F71/E71-1, 0) -> 0.37182574 | G72: =IFERROR(G71/F71-1, 0) -> -0.011193176 | H72: =IFERROR(H71/G71-1, 0) -> 0.15687468 | I72: =IFERROR(I71/H71-1, 0) -> 0.21941113 | J72: =CHOOSE(live_case,J73,J74,J75) -> 0.15 | K72: =CHOOSE(live_case,K73,K74,K75) -> 0.13 | L72: =CHOOSE(live_case,L73,L74,L75) -> 0.115 | M72: =CHOOSE(live_case,M73,M74,M75) -> 0.135 | N72: =CHOOSE(live_case,N73,N74,N75) -> 0.115
B73: Bear Case | J73: 0.1 | K73: 0.09 | L73: 0.08 | M73: 0.07 | N73: 0.06
B74: Street Case | J74: 0.15 | K74: 0.13 | L74: 0.115 | M74: 0.135 | N74: 0.115
B75: Bull Case | J75: 0.2 | K75: 0.2 | L75: 0.19 | M75: 0.18 | N75: 0.17
B77: EBIT | E77: =E42 -> 32671 | F77: =F42 -> 46753 | G77: =G42 -> 33555 | H77: =H42 -> 50203 | I77: =I42 -> 69769 | J77: =J71*J78 -> 73778.698 | K77: =K71*K78 -> 82728.622 | L77: =L71*L78 -> 93910.881 | M77: =M71*M78 -> 108212.03 | N77: =N71*N78 -> 128197.44
B78: % of revenue | E78: =E77/E71 -> 0.38005002 | F78: =F77/F71 -> 0.39645041 | G78: =G77/G71 -> 0.28775652 | H78: =H77/H71 -> 0.37214422 | I78: =I77/I71 -> 0.42412508 | J78: =CHOOSE(live_case,J79,J80,J81) -> 0.39 | K78: =CHOOSE(live_case,K79,K80,K81) -> 0.387 | L78: =CHOOSE(live_case,L79,L80,L81) -> 0.394 | M78: =CHOOSE(live_case,M79,M80,M81) -> 0.4 | N78: =CHOOSE(live_case,N79,N80,N81) -> 0.425
B79: Bear Case | J79: 0.3 | K79: 0.3 | L79: 0.3 | M79: 0.3 | N79: 0.3
B80: Street Case | J80: 0.39 | K80: 0.387 | L80: 0.394 | M80: 0.4 | N80: 0.425
B81: Bull Case | J81: 0.45 | K81: 0.45 | L81: 0.45 | M81: 0.45 | N81: 0.45
B83: Taxes | E83: =E45 -> 4034 | F83: =F45 -> 7914 | G83: =G45 -> 5619 | H83: =H45 -> 8330 | I83: =I45 -> 8303 | J83: =J84*J77 -> 9591.2308 | K83: =K84*K77 -> 11582.007 | L83: =L84*L77 -> 13147.523 | M83: =M84*M77 -> 17313.925 | N83: =N84*N77 -> 21793.565
B84: % of EBIT | E84: =E83/E77 -> 0.12347342 | F84: =F83/F77 -> 0.16927256 | G84: =G83/G77 -> 0.16745641 | H84: =H83/H77 -> 0.16592634 | I84: =I83/I77 -> 0.11900701 | J84: =CHOOSE(live_case,J85,J86,J87) -> 0.13 | K84: =CHOOSE(live_case,K85,K86,K87) -> 0.14 | L84: =CHOOSE(live_case,L85,L86,L87) -> 0.14 | M84: =CHOOSE(live_case,M85,M86,M87) -> 0.16 | N84: =CHOOSE(live_case,N85,N86,N87) -> 0.17
B85: Bear Case | J85: 0.3 | K85: 0.3 | L85: 0.3 | M85: 0.3 | N85: 0.3
B86: Street Case | J86: 0.13 | K86: 0.14 | L86: 0.14 | M86: 0.16 | N86: 0.17
B87: Bull Case | J87: 0.15 | K87: 0.15 | L87: 0.15 | M87: 0.15 | N87: 0.15
B89: EBIAT | E89: =E77-E83 -> 28637 | F89: =F77-F83 -> 38839 | G89: =G77-G83 -> 27936 | H89: =H77-H83 -> 41873 | I89: =I77-I83 -> 61466 | J89: =J77-J83 -> 64187.468 | K89: =K77-K83 -> 71146.615 | L89: =L77-L83 -> 80763.358 | ... N89: =N77-N83 -> 106403.88
B91: D&A | E91: =E56 -> 6862 | F91: =F56 -> 7967 | G91: =G56 -> 8686 | H91: =H56 -> 11178 | I91: =I56 -> 15498 | J91: =J94*J92 -> 19295.967 | K91: =K94*K92 -> 24690.325 | L91: =L94*L92 -> 33607.701 | M91: =M94*M92 -> 40579.511 | N91: =N94*N92 -> 50358.971
B92: % of CapEx | E92: =E57 -> 0.45398611 | F92: =F57 -> 0.42909463 | G92: =G57 -> 0.27635137 | H92: =H57 -> 0.40996112 | I92: =I57 -> 0.41598669 | J92: 0.3 | K92: 0.35 | L92: 0.47 | M92: 0.5 | N92: 0.63
B94: CapEx | E94: =-E65 -> 15115 | F94: =-F65 -> 18567 | G94: =-G65 -> 31431 | H94: =-H65 -> 27266 | I94: =-I65 -> 37256 | J94: =J95*J71 -> 64319.891 | K94: =K95*K71 -> 70543.786 | L94: =L95*L71 -> 71505.747 | M94: =M95*M71 -> 81159.023 | N94: =N95*N71 -> 79934.874
B95: % of Sales | E95: =E94/E71 -> 0.17582737 | F95: =F94/F71 -> 0.15744219 | G95: =G94/G71 -> 0.2695418 | H95: =H94/H71 -> 0.20211709 | I95: =I94/I71 -> 0.22647887 | J95: 0.34 | K95: 0.33 | L95: 0.3 | M95: 0.3 | N95: 0.265
B97: Change of NWC | E97: =E62 -> -2723 | F97: =F62 -> 700 | G97: =G62 -> 5683 | H97: =H62 -> 3836 | I97: =I62 -> 1048 | J97: =J71*J98 -> 9458.8075 | K97: =K71*K98 -> 6413.0715 | L97: =L71*L98 -> 4767.0498 | M97: =M71*M98 -> 5410.6015 | N97: =N71*N98 -> 6032.8207
B98: % of Sales | E98: =E97/E71 -> -0.031675682 | F98: =F97/F71 -> 0.0059357749 | G98: =G97/G71 -> 0.048735518 | H98: =H97/H71 -> 0.028435457 | I98: =I97/I71 -> 0.0063707819 | J98: 0.05 | K98: 0.03 | L98: 0.02 | M98: 0.02 | N98: 0.02
B100: Unlevered FCF | J100: =J89+J91-J94+J97 -> 28622.351 | K100: =K89+K91-K94+K97 -> 31706.225 | L100: =L89+L91-L94+L97 -> 47632.362 | M100: =M89+M91-M94+M97 -> 55729.196 | N100: =N89+N91-N94+N97 -> 82860.792
B101: PV of FCF | J101: =J100/(1+live_wacc)^J69 -> 26093.857 | K101: =K100/(1+live_wacc)^K69 -> 26351.811 | L101: =L100/(1+live_wacc)^L69 -> 36091.174 | M101: =M100/(1+live_wacc)^M69 -> 38495.913 | N101: =N100/(1+live_wacc)^N69 -> 52181.18
B102: Terminal Value | N102: =N100*(1+live_tgr)/(live_wacc-live_tgr) -> 1514503.1
B103: Present Value of Terminal Value | N103: =N102/(1+live_wacc)^N69 -> 953750.93
B105: Enterprise Value | N105: =SUM(J101:N101)+N103 -> 1132964.9
B106: (+) Cash | N106: =net_cash -> 70301
B107: (-) Debt | N107: =debt -> 28298
B108: Equity Value | N108: =N105+N106-N107 -> 1174967.9
B109: Shares | N109: =CS -> 2641.36
B110: $/Shr | N110: =N108/N109 -> 444.83443

Sheet Debt
A1: Meta Platforms Inc Class A
A2: META 30303M102 B7TL820 NASDAQ Common stock
A5: Instrument ID | B5: Description | C5: Balance Sheet Amt Out (USD) | D5: Current Amt Out (USD) | E5: Coupon Rate | F5: Coupon Type | G5: Issue Date | H5: Maturity Date | I5: Issue Curr | J5: Seniority | K5: Price | L5: YTW | M5: OAS (LIBOR)
A6: Notes/Bonds | C6: 29000 | D6: 29000 | O6: WA
A7: 30303M8B1 (144A) | B7: Meta Platforms Inc | C7: 91.9 | D7: 91.9 | E7: 0.035 | F7: Fixed | G7: 08/22 | H7: 08/27 | I7: USD | J7: SNR Unsec | K7: 98.96 | L7: 4.01 | M7: 47.01 | N7: _ | O7: =C7/$C$27*L7 -> 0.012782927
A8: 30303M8G0 | B8: Meta Platforms Inc | C8: 2658.1 | D8: 2658.1 | E8: 0.035 | F8: Fixed | G8: 12/22 | H8: 08/27 | I8: USD | J8: SNR Unsec | K8: 98.96 | L8: 4.01 | M8: 47.01 | N8: _ | O8: =C8/$C$27*L8 -> 0.36973121
A9: 30303M8L9 | B9: Meta Platforms Inc | C9: 1500 | D9: 1500 | E9: 0.046 | F9: Fixed | G9: 05/23 | H9: 05/28 | I9: USD | J9: SNR Unsec | K9: 101.72 | L9: 3.94 | M9: 46.6 | N9: _ | O9: =C9/$C$27*L9 -> 0.20500191
A10: 30303M8S4 | B10: Meta Platforms Inc | C10: 1000 | D10: 1000 | E10: 0.043 | F10: Fixed | G10: 08/24 | H10: 08/29 | I10: USD | J10: SNR Unsec | K10: 100.79 | L10: 4.08 | M10: 62.04 | O10: =C10/$C$27*L10 -> 0.14152416
A11: 30303M8M7 | B11: Meta Platforms Inc | C11: 1000 | D11: 1000 | E11: 0.048 | F11: Fixed | G11: 05/23 | H11: 05/30 | I11: USD | J11: SNR Unsec | K11: 102.81 | L11: 4.14 | M11: 65 | O11: =C11/$C$27*L11 -> 0.1436054
A12: 30303M8T2 | B12: Meta Platforms Inc | C12: 1000 | D12: 1000 | E12: 0.0455 | F12: Fixed | G12: 08/24 | H12: 08/31 | I12: USD | J12: SNR Unsec | K12: 101.11 | L12: 4.34 | M12: 78.22 | O12: =C12/$C$27*L12 -> 0.15054286
A13: 30303M8D7 (144A) | B13: Meta Platforms Inc | C13: 21.2 | D13: 21.2 | E13: 0.0385 | F13: Fixed | G13: 08/22 | H13: 08/32 | I13: USD | J13: SNR Unsec | K13: 95.76 | L13: 4.55 | M13: 93.8 | N13: _ | O13: =C13/$C$27*L13 -> 0.0033459364
A14: 30303M8H8 | B14: Meta Platforms Inc | C14: 2978.8 | D14: 2978.8 | E14: 0.0385 | F14: Fixed | G14: 12/22 | H14: 08/32 | I14: USD | J14: SNR Unsec | K14: 95.76 | L14: 4.55 | M14: 93.8 | N14: _ | O14: =C14/$C$27*L14 -> 0.47013563
A15: 30303M8N5 | B15: Meta Platforms Inc | C15: 1750 | D15: 1750 | E15: 0.0495 | F15: Fixed | G15: 05/23 | H15: 05/33 | I15: USD | J15: SNR Unsec | K15: 101.99 | L15: 4.64 | M15: 98.51 | N15: _ | O15: =C15/$C$27*L15 -> 0.28166083
A16: 30303M8U9 | B16: Meta Platforms Inc | C16: 2500 | D16: 2500 | E16: 0.0475 | F16: Fixed | G16: 08/24 | H16: 08/34 | I16: USD | J16: SNR Unsec | K16: 99.88 | L16: 4.77 | M16: 104.75 | O16: =C16/$C$27*L16 -> 0.41364598
A17: 30303M8E5 (144A) | B17: Meta Platforms Inc | C17: 1.2 | D17: 1.2 | E17: 0.0445 | F17: Fixed | G17: 08/22 | H17: 08/52 | I17: USD | J17: SNR Unsec | K17: 83.55 | L17: 5.64 | M17: 164.58 | N17: _ | O17: =C17/$C$27*L17 -> 0.00023476361
A18: 30303M8J4 | B18: Meta Platforms Inc | C18: 2748.8 | D18: 2748.8 | E18: 0.0445 | F18: Fixed | G18: 12/22 | H18: 08/52 | I18: USD | J18: SNR Unsec | K18: 83.55 | L18: 5.64 | M18: 164.58 | O18: =C18/$C$27*L18 -> 0.53776517
A19: 30303M8Q8 | B19: Meta Platforms Inc | C19: 2500 | D19: 2500 | E19: 0.056 | F19: Fixed | G19: 05/23 | H19: 05/53 | I19: USD | J19: SNR Unsec | K19: 99.05 | L19: 5.67 | M19: 168.19 | O19: =C19/$C$27*L19 -> 0.49169239
A20: 30303M8V7 | B20: Meta Platforms Inc | C20: 3250 | D20: 3250 | E20: 0.054 | F20: Fixed | G20: 08/24 | H20: 08/54 | I20: USD | J20: SNR Unsec | K20: 96.31 | L20: 5.66 | M20: 168.22 | N20: _ | O20: =C20/$C$27*L20 -> 0.63807277
A21: 30303M8F2 (144A) | B21: Meta Platforms Inc | C21: 6 | D21: 6 | E21: 0.0465 | F21: Fixed | G21: 08/22 | H21: 08/62 | I21: USD | J21: SNR Unsec | K21: 83.28 | L21: 5.74 | M21: 185.05 | N21: _ | O21: =C21/$C$27*L21 -> 0.0011946304
A22: 30303M8K1 | B22: Meta Platforms Inc | C22: 1494 | D22: 1494 | E22: 0.0465 | F22: Fixed | G22: 12/22 | H22: 08/62 | I22: USD | J22: SNR Unsec | K22: 83.28 | L22: 5.74 | M22: 185.05 | N22: _ | O22: =C22/$C$27*L22 -> 0.29746297
A23: 30303M8R6 | B23: Meta Platforms Inc | C23: 1750 | D23: 1750 | E23: 0.0575 | F23: Fixed | G23: 05/23 | H23: 05/63 | I23: USD | J23: SNR Unsec | K23: 99.93 | L23: 5.75 | M23: 186.08 | O23: =C23/$C$27*L23 -> 0.3490409
A24: 30303M8W5 | B24: Meta Platforms Inc | C24: 2750 | D24: 2750 | E24: 0.0555 | F24: Fixed | G24: 08/24 | H24: 08/64 | I24: USD | J24: SNR Unsec | K24: 96.76 | L24: 5.76 | M24: 187.83 | N24: _ | O24: =C24/$C$27*L24 -> 0.54944674
A25: Other | C25: -171 | D25: -171
A26: - | B26: Unamortized Discount & Issuance Costs - Unsecured Bonds | C26: -171 | D26: -171 | E26: - | F26: - | G26: - | H26: - | I26: USD | J26: Other | K26: - | L26: - | M26: -
B27: LT Debt Total | C27: 28829
B28: Current Portion of LTD | C28: 0
B29: Net LT Debt Total | C29: 28829
B30: ST Debt Total | C30: 0
B31: Total Debt | C31: 28829 | D31: 28829
A32: Data as of 27 Jun '25 | B32: Amount Outstanding in millions of USD
A33: Source: FactSet DCS and FactSet Fixed Income | B33: WA COST OF DEBT | C33: =SUM(O7:O24) -> 5.0568872
A34: * The current total debt outstanding value is not considered a reconciled amount. Activity is determined on a transactional basis and there can be events that may affect amounts that are not disclosed until the next filing date.

Sheet Income Statement_Static
K2: Identifier | L2: META-US
K3: Start Date | L3: -9
K4: End Date | L4: 0
K5: Report Basis | L5: ANN_R
K6: Currency | L6: LOC | M6: USD
B7: Meta Platforms Inc Class A
B9: Income Statement | C9: 42369 | D9: 42734 | E9: 43098 | F9: 43465 | G9: 43830 | H9: 44196 | I9: 44561 | J9: 44925 | K9: 45289 | L9: 45657
C10: Final/ | D10: Final/ | E10: Final/ | F10: Final/ | G10: Final/ | H10: Final/ | I10: Final/ | J10: Final/ | K10: Final/Restate | L10: Final/
B11: Sales | C11: 17928 | D11: 27638 | E11: 40653 | F11: 55838 | G11: 70697 | H11: 85965 | I11: 117929 | J11: 116609 | K11: 134902 | L11: 164501
B12: Cost of Goods Sold (COGS) incl. D&A | C12: 2867 | D12: 3789 | E12: 5454 | F12: 9355 | G12: 12770 | H12: 16692 | I12: 22649 | J12: 23754 | K12: 26006 | L12: 30130
B13: COGS excluding D&A | C13: 922 | D13: 1447 | E13: 2429 | F13: 5040 | G13: 7029 | H13: 9830 | I13: 14682 | J13: 15068 | K13: 14828 | L13: 14632
B14: Depreciation & Amortization Expense | C14: 1945 | D14: 2342 | E14: 3025 | F14: 4315 | G14: 5741 | H14: 6862 | I14: 7967 | J14: 8686 | K14: 11178 | L14: 15498
B15: Depreciation | C15: 1215 | D15: 1591 | E15: 2333 | F15: 3675 | G15: 5179 | H15: 6389 | I15: 7560 | J15: 8501 | K15: 11017 | L15: 15287
B16: Amortization of Intangibles | C16: 730 | D16: 751 | E16: 692 | F16: 640 | G16: 562 | H16: 473 | I16: 407 | J16: 185 | K16: 161 | L16: 211
B17: Gross Income | C17: 15061 | D17: 23849 | E17: 35199 | F17: 46483 | G17: 57927 | H17: 69273 | I17: 95280 | J17: 92855 | K17: 108896 | L17: 134371
B18: SG&A Expense | C18: 8767 | D18: 11422 | E18: 14996 | F18: 21570 | G18: 28941 | H18: 36602 | I18: 48527 | J18: 59300 | K18: 58693 | L18: 64602
B19: Research & Development | C19: 4747 | D19: 5919 | E19: 7754 | F19: 10273 | G19: 13600 | H19: 18447 | I19: 24655 | J19: 33619 | K19: 36489 | L19: 43619
B20: Other SG&A | C20: 4020 | D20: 5503 | E20: 7242 | F20: 11297 | G20: 15341 | H20: 18155 | I20: 23872 | J20: 25681 | K20: 22204 | L20: 20983
B21: EBIT (Operating Income) | C21: 6294 | D21: 12427 | E21: 20203 | F21: 24913 | G21: 28986 | H21: 32671 | I21: 46753 | J21: 33555 | K21: 50203 | L21: 69769
B22: Nonoperating Income - Net | C22: -8 | D22: 91 | E22: 391 | F22: 448 | G22: 846 | H22: 509 | I22: 531 | J22: 35 | K22: 1123 | L22: 1998
B23: Nonoperating Interest Income | C23: 52 | D23: 176 | E23: 398 | F23: 661 | G23: 924 | H23: 672 | I23: 461 | J23: 436 | K23: 1639 | L23: 2517
B24: Equity in Earnings of Affiliates | C24: 0 | D24: 0 | E24: 0 | F24: 0 | G24: 0 | H24: 0 | I24: 0 | J24: 0 | K24: 0 | L24: -
B25: Other Income (Expense) | C25: -60 | D25: -85 | E25: -7 | F25: -213 | G25: -78 | H25: -163 | I25: 70 | J25: -401 | K25: -516 | L25: -519
B26: Interest Expense | C26: 23 | D26: 0 | E26: - | F26: - | G26: 20 | H26: - | I26: - | J26: 160 | K26: 446 | L26: 715
B27: Gross Interest Expense | C27: 23 | D27: 0 | E27: - | F27: - | G27: 20 | H27: - | I27: - | J27: 160 | K27: 446 | L27: 715
B28: Interest Capitalized | C28: 0 | D28: 0 | E28: 0 | F28: 0 | G28: 0 | H28: 0 | I28: 0 | J28: 0 | K28: 0 | L28: 0
B29: Unusual Expense - Net | C29: 69 | D29: - | E29: - | F29: - | G29: 5000 | H29: 0 | I29: 0 | J29: 4611 | K29: 3452 | L29: 389
B30: Impairments | C30: - | D30: - | E30: - | F30: - | G30: - | H30: - | I30: - | J30: - | K30: - | L30: -
B31: Goodwill | C31: 0 | D31: 0 | E31: 0 | F31: 0 | G31: 0 | H31: 0 | I31: 0 | J31: 0 | K31: 0 | L31: 0
B32: Property,Plant & Equipment | C32: - | D32: - | E32: - | F32: - | G32: - | H32: - | I32: - | J32: - | K32: - | L32: -
B33: Financial Fixed Assets | C33: - | D33: - | E33: - | F33: - | G33: - | H33: - | I33: - | J33: - | K33: - | L33: -
B34: Restructuring Expense | C34: 0 | D34: 0 | E34: 0 | F34: 0 | G34: 0 | H34: 0 | I34: 0 | J34: 4611 | K34: 3452 | L34: 389
B35: Legal Claim Expense | C35: - | D35: - | E35: - | F35: - | G35: 5000 | H35: 0 | I35: 0 | J35: - | K35: - | L35: -
B36: Unrealized Valuation Gain/Loss | C36: - | D36: - | E36: - | F36: - | G36: - | H36: - | I36: - | J36: - | K36: - | L36: -
B37: Investments | C37: - | D37: - | E37: - | F37: - | G37: - | H37: - | I37: - | J37: - | K37: - | L37: -
B38: Investment Property | C38: - | D38: - | E38: - | F38: - | G38: - | H38: - | I38: - | J38: - | K38: - | L38: -
B39: Biological Assets | C39: - | D39: - | E39: - | F39: - | G39: - | H39: - | I39: - | J39: - | K39: - | L39: -
B40: Hedges/Derivatives | C40: - | D40: - | E40: - | F40: - | G40: - | H40: - | I40: - | J40: - | K40: - | L40: -
B41: Other Intangibles | C41: - | D41: - | E41: - | F41: - | G41: - | H41: - | I41: - | J41: - | K41: - | L41: -
B42: Excpl Chrgs - Others | C42: - | D42: - | E42: - | F42: - | G42: - | H42: - | I42: - | J42: - | K42: - | L42: -
B43: Restructuring of Debt | C43: - | D43: - | E43: - | F43: - | G43: - | H43: - | I43: - | J43: - | K43: - | L43: -
B44: Early termination of Contracts costs (Income) | C44: - | D44: - | E44: - | F44: - | G44: - | H44: - | I44: - | J44: - | K44: - | L44: -
B45: Acquired In-Process R&D | C45: - | D45: - | E45: - | F45: - | G45: - | H45: - | I45: - | J45: - | K45: - | L45: -
B46: Calamitous Events | C46: - | D46: - | E46: - | F46: - | G46: - | H46: - | I46: - | J46: - | K46: - | L46: -
B47: Accelerated Depreciation | C47: - | D47: - | E47: - | F47: - | G47: - | H47: - | I47: - | J47: - | K47: - | L47: -
B48: Other Unusual Expense | C48: - | D48: - | E48: - | F48: - | G48: - | H48: - | I48: - | J48: - | K48: - | L48: -
B49: Pretax Income | C49: 6194 | D49: 12518 | E49: 20594 | F49: 25361 | G49: 24812 | H49: 33180 | I49: 47284 | J49: 28819 | K49: 47428 | L49: 70663
B50: Income Taxes | C50: 2506 | D50: 2301 | E50: 4660 | F50: 3249 | G50: 6327 | H50: 4034 | I50: 7914 | J50: 5619 | K50: 8330 | L50: 8303
B51: Income Taxes - Current Domestic | C51: 3195 | D51: 2563 | E51: 4645 | F51: 1923 | G51: 4886 | H51: 3820 | I51: 5519 | J51: 6968 | K51: 5511 | L51: 10344
B52: Income Taxes - Current Foreign | C52: 123 | D52: 195 | E52: 389 | F52: 1031 | G52: 1481 | H52: 1211 | I52: 1786 | J52: 1928 | K52: 2688 | L52: 2696
B53: Income Taxes - Deferred Domestic | C53: -817 | D53: -432 | E53: -329 | F53: 350 | G53: -20 | H53: -981 | I53: 628 | J53: -3181 | K53: 190 | L53: -4752
B54: Income Taxes - Deferred Foreign | C54: 5 | D54: -25 | E54: -45 | F54: -55 | G54: -20 | H54: -16 | I54: -19 | J54: -96 | K54: -59 | L54: 15
B55: Income Tax Credits | C55: 0 | D55: 0 | E55: 0 | F55: 0 | G55: 0 | H55: 0 | I55: 0 | J55: 0 | K55: 0 | L55: 0
B56: Equity in Earnings of Affiliates | C56: 0 | D56: 0 | E56: 0 | F56: 0 | G56: 0 | H56: 0 | I56: 0 | J56: 0 | K56: 0 | L56: -
B57: Consolidated Net Income | C57: 3669 | D57: 10188 | E57: 15920 | F57: 22111 | G57: 18485 | H57: 29146 | I57: 39370 | J57: 23200 | K57: 39098 | L57: 62360
B58: Minority Interest | C58: 0 | D58: 0 | E58: 0 | F58: 0 | G58: 0 | H58: 0 | I58: 0 | J58: 0 | K58: 0 | L58: 0
B59: Net Income | C59: 3669 | D59: 10188 | E59: 15920 | F59: 22111 | G59: 18485 | H59: 29146 | I59: 39370 | J59: 23200 | K59: 39098 | L59: 62360
B60: Net Income available to Common | C60: 3669 | D60: 10188 | E60: 15920 | F60: 22111 | G60: 18485 | H60: 29146 | I60: 39370 | J60: 23200 | K60: 39098 | L60: 62360
B61: Per Share
B62: EPS (recurring) | C62: 1.3096039 | D62: 3.4929915 | E62: 5.3903924 | F62: 7.5700103 | G62: 7.6442976 | H62: 10.092105 | I62: 13.770549 | J62: 9.780792 | K62: 15.790947 | L62: 23.960329
B63: EPS (basic) | C63: 1.31 | D63: 3.5585 | E63: 5.4878 | F63: 7.6509 | G63: 6.4769 | H63: 10.2231 | I63: 13.9858 | J63: 8.6342 | K63: 15.1896 | L63: 24.6093
B64: Basic Shares Outstanding (M) | C64: 2803 | D64: 2863 | E64: 2901 | F64: 2890 | G64: 2854 | H64: 2851 | I64: 2815 | J64: 2687 | K64: 2574 | L64: 2534
B65: Total Shares Outstanding (M) | C65: 2845 | D65: 2892 | E65: 2906 | F65: 2854 | G65: 2852 | H65: 2849 | I65: 2741 | J65: 2614 | K65: 2561 | L65: 2534
B66: EPS (diluted) | C66: 1.29 | D66: 3.493 | E66: 5.3904 | F66: 7.57 | G66: 6.4273 | H66: 10.0921 | I66: 13.7706 | J66: 8.5862 | K66: 14.8718 | L66: 23.8562
B67: Diluted Shares Outstanding (M) | C67: 2853 | D67: 2925 | E67: 2956 | F67: 2921 | G67: 2876 | H67: 2888 | I67: 2859 | J67: 2702 | K67: 2629 | L67: 2614
B68: Total Shares Outstanding (M) | C68: 2845 | D68: 2892 | E68: 2906 | F68: 2854 | G68: 2852 | H68: 2849 | I68: 2741 | J68: 2614 | K68: 2561 | L68: 2534
B69: Earnings Persistence | C69: 83.678 | D69: 79.447 | E69: 75.779 | F69: 77.681 | G69: 80.233 | H69: 72.629 | I69: 80.899 | J69: 83.393 | K69: 85.098 | L69: 79.577
B70: Dividends per Share | C70: 0 | D70: 0 | E70: 0 | F70: 0 | G70: 0 | H70: 0 | I70: 0 | J70: 0 | K70: 0 | L70: 2
B71: Payout Ratio | C71: 0 | D71: 0 | E71: 0 | F71: 0 | G71: 0 | H71: 0 | I71: 0 | J71: 0 | K71: 0 | L71: 8.3835649
B72: EBITDA
B73: EBITDA | C73: 8239 | D73: 14769 | E73: 23228 | F73: 29228 | G73: 34727 | H73: 39533 | I73: 54720 | J73: 42241 | K73: 61381 | L73: 85267
B74: EBIT | C74: 6294 | D74: 12427 | E74: 20203 | F74: 24913 | G74: 28986 | H74: 32671 | I74: 46753 | J74: 33555 | K74: 50203 | L74: 69769
B75: Depreciation & Amortization Expense | C75: 1945 | D75: 2342 | E75: 3025 | F75: 4315 | G75: 5741 | H75: 6862 | I75: 7967 | J75: 8686 | K75: 11178 | L75: 15498
B76: All figures in millions of USD except per share and labeled items.

Sheet Balance Sheet_Static
K2: Identifier | L2: META-US
K3: Start Date | L3: -9
K4: End Date | L4: 0
C5: ='Balance Sheet_Static'!L71+'Balance Sheet_Static'!L62-'Balance Sheet_Static'!L13 -> 5527 | K5: Report Basis | L5: ANN_R
K6: Currency | L6: LOC | M6: USD
B7: Meta Platforms Inc Class A
B9: Balance Sheet | C9: 42369 | D9: 42734 | E9: 43098 | F9: 43465 | G9: 43830 | H9: 44196 | I9: 44561 | J9: 44925 | K9: 45289 | L9: 45657
C10: Final/ | D10: Final/ | E10: Final/ | F10: Final/ | G10: Final/ | H10: Final/ | I10: Final/ | J10: Final/ | K10: Final/Restate | L10: Final/
B11: Assets
B12: Cash & Short-Term Investments | C12: 18434 | D12: 29449 | E12: 41711 | F12: 41124 | G12: 54863 | H12: 62195 | I12: 48147 | J12: 41032 | K12: 65502 | L12: 78168
B13: Cash Only | C13: 4907 | D13: 8903 | E13: 8079 | F13: 10029 | G13: 19087 | H13: 17817 | I13: 16750 | J13: 14975 | K13: 41961 | L13: 44242
B14: Total Short Term Investments | C14: 13527 | D14: 20546 | E14: 33632 | F14: 31095 | G14: 35776 | H14: 44378 | I14: 31397 | J14: 26057 | K14: 23541 | L14: 33926
B15: Short-Term Receivables | C15: 2559 | D15: 3993 | E15: 5832 | F15: 7587 | G15: 9518 | H15: 11335 | I15: 14039 | J15: 13466 | K15: 16169 | L15: 16994
B16: Accounts Receivables, Net | C16: 2559 | D16: 3993 | E16: 5832 | F16: 7587 | G16: 9518 | H16: 11335 | I16: 14039 | J16: 13466 | K16: 16169 | L16: 16994
B17: Accounts Receivables, Gross | C17: 2627 | D17: 4087 | E17: 6021 | F17: 7816 | G17: 9724 | H17: 11449 | I17: 14039 | J17: 13466 | K17: 16169 | L17: 16994
B18: Bad Debt/Doubtful Accounts | C18: -68 | D18: -94 | E18: -189 | F18: -229 | G18: -206 | H18: -114 | I18: - | J18: - | K18: - | L18: -
B19: Other Receivables | C19: 0 | D19: 0 | E19: 0 | F19: 0 | G19: 0 | H19: 0 | I19: 0 | J19: 0 | K19: 0 | L19: 0
B20: Inventories | C20: 0 | D20: 0 | E20: 0 | F20: 0 | G20: 0 | H20: 0 | I20: 0 | J20: 0 | K20: 0 | L20: 0
B21: Finished Goods | C21: 0 | D21: 0 | E21: 0 | F21: 0 | G21: 0 | H21: 0 | I21: 0 | J21: 0 | K21: 0 | L21: 0
B22: Other Current Assets | C22: 659 | D22: 959 | E22: 1020 | F22: 1769 | G22: 1844 | H22: 2140 | I22: 4480 | J22: 5051 | K22: 3694 | L22: 4883
B23: Prepaid Expenses | C23: - | D23: - | E23: - | F23: - | G23: - | H23: - | I23: - | J23: - | K23: - | L23: -
B24: Miscellaneous Current Assets | C24: 659 | D24: 959 | E24: 1020 | F24: 1769 | G24: 1844 | H24: 2140 | I24: 4480 | J24: 5051 | K24: 3694 | L24: 4883
B25: Total Current Assets | C25: 21652 | D25: 34401 | E25: 48563 | F25: 50480 | G25: 66225 | H25: 75670 | I25: 66666 | J25: 59549 | K25: 85365 | L25: 100045
B26: Net Property, Plant & Equipment | C26: 5687 | D26: 8591 | E26: 13721 | F26: 24683 | G26: 44783 | H26: 54981 | I26: 69964 | J26: 92191 | K26: 109881 | L26: 136268
B27: Property, Plant & Equipment - Gross | C27: 7819 | D27: 11803 | E27: 18337 | F27: 31573 | G27: 55446 | H27: 70399 | I27: 90044 | J27: 117166 | K27: 143015 | L27: 179585
B28: Buildings | C28: 2273 | D28: 3109 | E28: 4909 | F28: 7401 | G28: 11226 | H28: 17360 | I28: 22531 | J28: 27720 | K28: 37961 | L28: 47076
B29: Land & Improvements | C29: 596 | D29: 696 | E29: 798 | F29: 899 | G29: 1097 | H29: 1326 | I29: 1688 | J29: 1874 | K29: 2080 | L29: 2561
B30: Machinery & Equipment | C30: 3633 | D30: 5179 | E30: 7998 | F30: 13017 | G30: 17004 | H30: 22003 | I30: 25584 | J30: 39972 | K30: 46838 | L30: 68397
B31: Construction in Progress | C31: 622 | D31: 1890 | E31: 2992 | F31: 7228 | G31: 10099 | H31: 11288 | I31: 14687 | J31: 25052 | K31: 24269 | L31: 26802
B32: Leases | C32: - | D32: - | E32: - | F32: - | G32: 1635 | H32: 2295 | I32: 2840 | J32: 3353 | K32: 4185 | L32: 5384
B33: Computer Software and Equipment | C33: - | D33: - | E33: - | F33: - | G33: - | H33: - | I33: - | J33: - | K33: - | L33: -
B34: Leased Property | C34: - | D34: - | E34: - | F34: - | G34: - | H34: - | I34: - | J34: - | K34: - | L34: -
B35: Transportation Equipment | C35: - | D35: - | E35: - | F35: - | G35: - | H35: - | I35: - | J35: - | K35: - | L35: -
B36: Other Property, Plant & Equipment | C36: 695 | D36: 929 | E36: 1640 | F36: 3028 | G36: 4925 | H36: 6779 | I36: 10559 | J36: 6522 | K36: 14388 | L36: 14443
B37: Operating Lease Right-of-Use Assets | C37: - | D37: - | E37: - | F37: - | G37: 9460 | H37: 9348 | I37: 12155 | J37: 12673 | K37: 13294 | L37: 14922
B38: Accumulated Depreciation | C38: 2132 | D38: 3212 | E38: 4616 | F38: 6890 | G38: 10663 | H38: 15418 | I38: 20080 | J38: 24975 | K38: 33134 | L38: 43317
B39: Buildings | C39: - | D39: - | E39: - | F39: - | G39: - | H39: - | I39: - | J39: - | K39: - | L39: -
B40: Land & Improvements | C40: - | D40: - | E40: - | F40: - | G40: - | H40: - | I40: - | J40: - | K40: - | L40: -
B41: Machinery & Equipment | C41: - | D41: - | E41: - | F41: - | G41: - | H41: - | I41: - | J41: - | K41: - | L41: -
B42: Construction in Progress | C42: - | D42: - | E42: - | F42: - | G42: - | H42: - | I42: - | J42: - | K42: - | L42: -
B43: Leases | C43: - | D43: - | E43: - | F43: - | G43: - | H43: - | I43: - | J43: - | K43: - | L43: -
B44: Computer Software and Equipment | C44: - | D44: - | E44: - | F44: - | G44: - | H44: - | I44: - | J44: - | K44: - | L44: -
B45: Leased Property | C45: - | D45: - | E45: - | F45: - | G45: - | H45: - | I45: - | J45: - | K45: - | L45: -
B46: Transportation Equipment | C46: - | D46: - | E46: - | F46: - | G46: - | H46: - | I46: - | J46: - | K46: - | L46: -
B47: Other Property, Plant & Equipment | C47: - | D47: - | E47: - | F47: - | G47: - | H47: - | I47: - | J47: - | K47: - | L47: -
B48: Total Long-Term Investments | C48: 0 | D48: 0 | E48: 0 | F48: 95 | G48: 192 | H48: 6371 | I48: 6890 | J48: 6822 | K48: 7007 | L48: 7266
B49: LT Investment - Affiliate Companies | C49: 0 | D49: 0 | E49: 0 | F49: 0 | G49: 0 | H49: 0 | I49: 0 | J49: 0 | K49: 0 | L49: 52
B50: Other Long-Term Investments | C50: 0 | D50: 0 | E50: 0 | F50: 95 | G50: 192 | H50: 6371 | I50: 6890 | J50: 6822 | K50: 7007 | L50: 7214
B51: Long-Term Note Receivable | C51: - | D51: - | E51: - | F51: - | G51: - | H51: - | I51: - | J51: - | K51: - | L51: -
B52: Intangible Assets | C52: 21272 | D52: 20657 | E52: 20105 | F52: 19595 | G52: 19609 | H52: 19673 | I52: 19831 | J52: 21203 | K52: 21442 | L52: 21569
B53: Goodwill | C53: 18026 | D53: 18122 | E53: 18221 | F53: 18301 | G53: 18715 | H53: 19050 | I53: 19197 | J53: 20306 | K53: 20654 | L53: 20654
B54: Other Intangible Assets | C54: 3246 | D54: 2535 | E54: 1884 | F54: 1294 | G54: 894 | H54: 623 | I54: 634 | J54: 897 | K54: 788 | L54: 915
B55: Deferred Tax Assets | C55: - | D55: - | E55: - | F55: - | G55: - | H55: - | I55: - | J55: - | K55: - | L55: -
B56: Other Assets | C56: 796 | D56: 1312 | E56: 2135 | F56: 2481 | G56: 2567 | H56: 2621 | I56: 2636 | J56: 5962 | K56: 5928 | L56: 10906
B57: Deferred Charges | C57: - | D57: - | E57: - | F57: - | G57: - | H57: - | I57: - | J57: - | K57: - | L57: -
B58: Tangible Other Assets | C58: 796 | D58: 1312 | E58: 2135 | F58: 2481 | G58: 2567 | H58: 2621 | I58: 2636 | J58: 5962 | K58: 5928 | L58: 10906
B59: Total Assets | C59: 49407 | D59: 64961 | E59: 84524 | F59: 97334 | G59: 133376 | H59: 159316 | I59: 165987 | J59: 185727 | K59: 229623 | L59: 276054
B60: Liabilities & Shareholders' Equity
B61: Current
B62: ST Debt & Curr. Portion LT Debt | C62: 208 | D62: 0 | E62: 0 | F62: 500 | G62: 1146 | H62: 1091 | I62: 1217 | J62: 1513 | K62: 1713 | L62: 2018
B63: Accounts Payable | C63: 413 | D63: 582 | E63: 770 | F63: 1361 | G63: 2249 | H63: 2424 | I63: 5135 | J63: 6107 | K63: 5712 | L63: 7687
B64: Income Tax Payable | C64: - | D64: 155 | E64: 230 | F64: 491 | G64: 624 | H64: 2038 | I64: 1256 | J64: 2339 | K64: 3655 | L64: 3438
B65: Other Current Liabilities | C65: 1304 | D65: 2138 | E65: 2760 | F65: 4665 | G65: 11034 | H65: 9428 | I65: 13527 | J65: 17067 | K65: 20880 | L65: 20453
B66: Dividends Payable | C66: 0 | D66: 0 | E66: 0 | F66: 0 | G66: 0 | H66: 0 | I66: 0 | J66: 0 | K66: 0 | L66: 0
B67: Accrued Payroll | C67: 473 | D67: 636 | E67: 776 | F67: 1203 | G67: 1704 | H67: 2609 | I67: 3152 | J67: 4591 | K67: 6659 | L67: 6350
B68: Miscellaneous Current Liabilities | C68: 831 | D68: 1502 | E68: 1984 | F68: 3462 | G68: 9330 | H68: 6819 | I68: 10375 | J68: 12476 | K68: 14221 | L68: 14103
B69: Total Current Liabilities | C69: 1925 | D69: 2875 | E69: 3760 | F69: 7017 | G69: 15053 | H69: 14981 | I69: 21135 | J69: 27026 | K69: 31960 | L69: 33596
B70: Long-Term
B71: Long-Term Debt | C71: 107 | D71: 0 | E71: 72 | F71: 0 | G71: 9928 | H71: 10086 | I71: 13237 | J71: 25765 | K71: 36211 | L71: 47751
B72: Long-Term Debt excl Lease Obligations | C72: 0 | D72: 0 | E72: 0 | F72: 0 | G72: 0 | H72: 0 | I72: 0 | J72: 9923 | K72: 18385 | L72: 28826
B73: Capital and Operating Lease Obligations | C73: 107 | D73: 0 | E73: 72 | F73: 0 | G73: 9928 | H73: 10086 | I73: 13237 | J73: 15842 | K73: 17826 | L73: 18925
B74: Provision for Risks & Charges | C74: 0 | D74: 0 | E74: 0 | F74: 0 | G74: 0 | H74: 0 | I74: 0 | J74: 0 | K74: 0 | L74: 0
B75: Deferred Tax Liabilities | C75: 163 | D75: - | E75: - | F75: 673 | G75: 1039 | H75: - | I75: - | J75: 5490 | K75: 6950 | L75: 9987
B76: Other Liabilities | C76: 2994 | D76: 2892 | E76: 6345 | F76: 5517 | G76: 6302 | H76: 5959 | I76: 6736 | J76: 1733 | K76: 1334 | L76: 2083
B77: Other Liabilities (excl. Deferred Income) | C77: 2994 | D77: 2892 | E77: 6345 | F77: 5517 | G77: 6302 | H77: 5959 | I77: 6736 | J77: 1733 | K77: 1334 | L77: 2083
B78: Deferred Income | C78: - | D78: - | E78: - | F78: - | G78: - | H78: - | I78: - | J78: - | K78: - | L78: -
B79: Total Liabilities | C79: 5189 | D79: 5767 | E79: 10177 | F79: 13207 | G79: 32322 | H79: 31026 | I79: 41108 | J79: 60014 | K79: 76455 | L79: 93417
B80: Equity
B81: Common Equity | C81: 44218 | D81: 59194 | E81: 74347 | F81: 84127 | G81: 101054 | H81: 128290 | I81: 124879 | J81: 125713 | K81: 153168 | L81: 182637
B82: Common Stock Par/Carry Value | C82: 0 | D82: 0 | E82: 0 | F82: 0 | G82: 0 | H82: 0 | I82: 0 | J82: 0 | K82: 0 | L82: 0
B83: Additional Paid-In Capital/Capital Surplus | C83: 34886 | D83: 38227 | E83: 40584 | F83: 42906 | G83: 45851 | H83: 50018 | I83: 55811 | J83: 64444 | K83: 73253 | L83: 83228
B84: Retained Earnings | C84: 9787 | D84: 21670 | E84: 33990 | F84: 41981 | G84: 55692 | H84: 77345 | I84: 69761 | J84: 64799 | K84: 82070 | L84: 102506
B85: ESOP Debt Guarantee | C85: 0 | D85: 0 | E85: 0 | F85: 0 | G85: 0 | H85: 0 | I85: 0 | J85: 0 | K85: 0 | L85: 0
B86: Cumulative Translation Adjustment/Unrealized For. Exch. Gain | C86: - | D86: - | E86: - | F86: - | G86: - | H86: - | I86: - | J86: -1860 | K86: -1240 | L86: -2660
B87: Unrealized Gain/Loss Marketable Securities | C87: 0 | D87: 0 | E87: 0 | F87: 0 | G87: 0 | H87: 0 | I87: 0 | J87: 0 | K87: 0 | L87: 0
B88: Other Appropriated Reserves | C88: -455 | D88: -703 | E88: -227 | F88: -760 | G88: -489 | H88: 927 | I88: -693 | J88: -1670 | K88: -915 | L88: -437
B89: Unappropriated Reserves | C89: - | D89: - | E89: - | F89: - | G89: - | H89: - | I89: - | J89: - | K89: - | L89: -
B90: Treasury Stock | C90: 0 | D90: 0 | E90: 0 | F90: 0 | G90: 0 | H90: 0 | I90: 0 | J90: 0 | K90: 0 | L90: 0
B91: Repurchased Stock Value | C91: #NUM!
B92: Total Shareholders' Equity | C92: 44218 | D92: 59194 | E92: 74347 | F92: 84127 | G92: 101054 | H92: 128290 | I92: 124879 | J92: 125713 | K92: 153168 | L92: 182637
B93: Accumulated Minority Interest | C93: 0 | D93: 0 | E93: 0 | F93: 0 | G93: 0 | H93: 0 | I93: 0 | J93: 0 | K93: 0 | L93: 0
B94: Total Equity | C94: 44218 | D94: 59194 | E94: 74347 | F94: 84127 | G94: 101054 | H94: 128290 | I94: 124879 | J94: 125713 | K94: 153168 | L94: 182637
B95: Total Liabilities & Shareholders' Equity | C95: 49407 | D95: 64961 | E95: 84524 | F95: 97334 | G95: 133376 | H95: 159316 | I95: 165987 | J95: 185727 | K95: 229623 | L95: 276054
B96: Per Share
B97: Book Value per Share | C97: 15.54236 | D97: 20.46819 | E97: 25.58396 | F97: 29.47687 | G97: 35.43268 | H97: 45.02984 | I97: 45.55965 | J97: 48.0922 | K97: 59.80789 | L97: 72.07459
B98: Tangible Book Value per Share | C98: 8.0653779 | D98: 13.32538 | E98: 18.66552 | F98: 22.611072 | G98: 28.557153 | H98: 38.124605 | I98: 38.324699 | J98: 39.980872 | K98: 51.435377 | L98: 63.562747
B99: All figures in millions of USD except per share and labeled items.

Sheet Cash Flow_Static
K2: Identifier | L2: META-US
K3: Start Date | L3: -9
K4: End Date | L4: 0
K5: Report Basis | L5: ANN_R
K6: Currency | L6: LOC | M6: USD
B7: Meta Platforms Inc Class A
B9: Cash Flow | C9: 42369 | D9: 42734 | E9: 43098 | F9: 43465 | G9: 43830 | H9: 44196 | I9: 44561 | J9: 44925 | K9: 45289 | L9: 45657
C10: Final/ | D10: Final/ | E10: Final/ | F10: Final/ | G10: Final/ | H10: Final/ | I10: Final/ | J10: Final/ | K10: Final/Restate | L10: Final/
B11: Operating Activities
B12: Net Income / Starting Line | C12: 3688 | D12: 10217 | E12: 15934 | F12: 22112 | G12: 18485 | H12: 29146 | I12: 39370 | J12: 23200 | K12: 39098 | L12: 62360
B13: Depreciation, Depletion & Amortization | C13: 1945 | D13: 2342 | E13: 3025 | F13: 4315 | G13: 5741 | H13: 6862 | I13: 7967 | J13: 8686 | K13: 11178 | L13: 15498
B14: Depreciation and Depletion | C14: 1215 | D14: 1591 | E14: 2333 | F14: 3675 | G14: 5179 | H14: 6389 | I14: 7560 | J14: 8501 | K14: 11017 | L14: 15287
B15: Amortization of Intangible Assets | C15: 730 | D15: 751 | E15: 692 | F15: 640 | G15: 562 | H15: 473 | I15: 407 | J15: 185 | K15: 161 | L15: 211
B16: Deferred Taxes & Investment Tax Credit | C16: -795 | D16: -457 | E16: -377 | F16: 286 | G16: -37 | H16: -1192 | I16: 609 | J16: -3286 | K16: 131 | L16: -4738
B17: Deferred Taxes | C17: -795 | D17: -457 | E17: -377 | F17: 286 | G17: -37 | H17: -1192 | I17: 609 | J17: -3286 | K17: 131 | L17: -4738
B18: Investment Tax Credit | C18: - | D18: - | E18: - | F18: - | G18: - | H18: - | I18: - | J18: - | K18: - | L18: -
B19: Interest paid on Lease Liabilities - Operating | C19: - | D19: - | E19: - | F19: - | G19: - | H19: - | I19: - | J19: - | K19: - | L19: -
B20: Other Funds | C20: 2977 | D20: 3248 | E20: 3747 | F20: 4088 | G20: 4875 | H20: 6654 | I20: 9037 | J20: 16192 | K20: 16870 | L20: 17160
B21: Funds from Operations | C21: 7815 | D21: 15350 | E21: 22329 | F21: 30801 | G21: 29064 | H21: 41470 | I21: 56983 | J21: 44792 | K21: 67277 | L21: 90280
B22: Changes in Working Capital | C22: 784 | D22: 758 | E22: 1887 | F22: -1527 | G22: 7250 | H22: -2723 | I22: 700 | J22: 5683 | K22: 3836 | L22: 1048
B23: Receivables | C23: -973 | D23: -1489 | E23: -1609 | F23: -1892 | G23: -1961 | H23: -1512 | I23: -3110 | J23: 231 | K23: -2399 | L23: -1485
B24: Inventories | C24: - | D24: - | E24: - | F24: - | G24: - | H24: - | I24: - | J24: - | K24: - | L24: -
B25: Accounts Payable | C25: 35 | D25: 81 | E25: 138 | F25: 378 | G25: 461 | H25: 161 | I25: 1424 | J25: 300 | K25: -220 | L25: 373
B26: Income Taxes Payable | C26: - | D26: - | E26: - | F26: - | G26: - | H26: - | I26: - | J26: - | K26: - | L26: -
B27: Other Accruals | C27: 513 | D27: 1014 | E27: 309 | F27: 1417 | G27: 7300 | H27: -1054 | I27: 3357 | J27: 4210 | K27: 5352 | L27: 323
B28: Other Assets/Liabilities | C28: 1209 | D28: 1152 | E28: 3049 | F28: -1430 | G28: 1450 | H28: -318 | I28: -971 | J28: 942 | K28: 1103 | L28: 1837
B29: Net Operating Cash Flow | C29: 8599 | D29: 16108 | E29: 24216 | F29: 29274 | G29: 36314 | H29: 38747 | I29: 57683 | J29: 50475 | K29: 71113 | L29: 91328
B30: Investing Activities
B31: Capital Expenditures | C31: -2523 | D31: -4491 | E31: -6733 | F31: -13915 | G31: -15102 | H31: -15115 | I31: -18567 | J31: -31431 | K31: -27266 | L31: -37256
B32: Capital Expenditures (Fixed Assets) | C32: -2523 | D32: -4491 | E32: -6733 | F32: -13915 | G32: -15102 | H32: -15115 | I32: -18567 | J32: -31431 | K32: -27266 | L32: -37256
B33: Capital Expenditures (Other Assets) | C33: 0 | D33: 0 | E33: 0 | F33: - | G33: 0 | H33: 0 | I33: 0 | J33: 0 | K33: 0 | L33: 0
B34: Net Assets from Acquisitions | C34: -313 | D34: -123 | E34: -122 | F34: -137 | G34: -508 | H34: -388 | I34: -851 | J34: -1312 | K34: -629 | L34: -270
B35: Sale of Fixed Assets & Businesses | C35: - | D35: - | E35: - | F35: - | G35: 0 | H35: 0 | I35: 0 | J35: 245 | K35: 221 | L35: 0
B36: Purchase/Sale of Investments | C36: -6700 | D36: -7186 | E36: -13250 | F36: 2474 | G36: -4193 | H36: -14520 | I36: 12132 | J36: 3527 | K36: 3202 | L36: -9753
B37: Sale/Maturity of Investments | C37: 9238 | D37: 15155 | E37: 12432 | F37: 17130 | G37: 19717 | H37: 25771 | I37: 42586 | J37: 13158 | K37: 6184 | L37: 15789
B38: Other Funds | C38: 102 | D38: 61 | E38: 67 | F38: -25 | G38: -61 | H38: -36 | I38: -284 | J38: 1 | K38: -23 | L38: 129
B39: Other Uses | C39: 0 | D39: 0 | E39: 0 | F39: -25 | G39: -61 | H39: -36 | I39: -284 | J39: 0 | K39: -23 | L39: 0
B40: Other Sources | C40: 102 | D40: 61 | E40: 67 | F40: 0 | G40: 0 | H40: 0 | I40: 0 | J40: 1 | K40: 0 | L40: 129
B41: Net Investing Cash Flow | C41: -9434 | D41: -11739 | E41: -20038 | F41: -11603 | G41: -19864 | H41: -30059 | I41: -7570 | J41: -28970 | K41: -24495 | L41: -47150
B42: Financing Activities
B43: Cash Dividends Paid | C43: 0 | D43: 0 | E43: 0 | F43: 0 | G43: 0 | H43: 0 | I43: 0 | J43: 0 | K43: 0 | L43: -5072
B44: Common Dividends | C44: 0 | D44: 0 | E44: 0 | F44: 0 | G44: 0 | H44: 0 | I44: 0 | J44: 0 | K44: 0 | L44: -5072
B45: Change in Capital Stock | C45: -20 | D45: -6 | E45: -5222 | F45: -16087 | G45: -6539 | H45: -6272 | I45: -44537 | J45: -27956 | K45: -19774 | L45: -30125
B46: Repurchase of Common & Preferred Stk. | C46: 0 | D46: 0 | E46: -1976 | F46: -12879 | G46: -4202 | H46: -6272 | I46: -44537 | J46: -27956 | K46: -19774 | L46: -30125
B47: Sale of Common & Preferred Stock | C47: -20 | D47: -6 | E47: -3246 | F47: -3208 | G47: -2337 | H47: 0 | I47: 0 | J47: 0 | K47: 0 | L47: 0
B48: Proceeds from Sale of Stock | C48: -20 | D48: -6 | E48: -3246 | F48: -3208 | G48: -2337 | H48: 0 | I48: 0 | J48: 0 | K48: 0 | L48: 0
B49: Issuance/Reduction of Debt, Net | C49: -119 | D49: -312 | E49: 0 | F49: 500 | G49: -775 | H49: -580 | I49: -663 | J49: 9071 | K49: 7397 | L49: 8463
B50: Change in Current Debt | C50: 0 | D50: 0 | E50: 0 | F50: 500 | G50: -223 | H50: 24 | I50: 14 | J50: 0 | K50: 0 | L50: 0
B51: Change in Long-Term Debt | C51: -119 | D51: -312 | E51: 0 | F51: 0 | G51: -552 | H51: -604 | I51: -677 | J51: 9071 | K51: 7397 | L51: 8463
B52: Issuance of Long-Term Debt | C52: 0 | D52: 0 | E52: 0 | F52: 0 | G52: 0 | H52: 0 | I52: 0 | J52: 9921 | K52: 8455 | L52: 10432
B53: Reduction in Long-Term Debt | C53: -119 | D53: -312 | E53: 0 | F53: 0 | G53: -552 | H53: -604 | I53: -677 | J53: -850 | K53: -1058 | L53: -1969
B54: Change in Other Debt | C54: - | D54: - | E54: - | F54: - | G54: - | H54: - | I54: - | J54: - | K54: - | L54: -
B55: Repayments of Operating Lease Liabilities | C55: - | D55: - | E55: - | F55: - | G55: - | H55: - | I55: - | J55: - | K55: - | L55: -
B56: Interest paid on Lease Liabilities - Financing | C56: - | D56: - | E56: - | F56: - | G56: - | H56: - | I56: - | J56: - | K56: - | L56: -
B57: Other Funds | C57: 1721 | D57: 8 | E57: -13 | F57: 15 | G57: 15 | H57: -3440 | I57: -5528 | J57: -3251 | K57: -7123 | L57: -14047
B58: Other Uses | C58: 0 | D58: 0 | E58: -13 | F58: 0 | G58: 0 | H58: -3564 | I58: -5528 | J58: -3595 | K58: -7123 | L58: -14047
B59: Other Sources | C59: 1721 | D59: 8 | E59: 0 | F59: 15 | G59: 15 | H59: 124 | I59: 0 | J59: 344 | K59: 0 | L59: 0
B60: Net Financing Cash Flow | C60: 1582 | D60: -310 | E60: -5235 | F60: -15572 | G60: -7299 | H60: -10292 | I60: -50728 | J60: -22136 | K60: -19500 | L60: -40781
B61: All Activities
B62: Exchange Rate Effect | C62: -155 | D62: -63 | E62: 233 | F62: -179 | G62: 4 | H62: 279 | I62: -474 | J62: -638 | K62: 113 | L62: -786
B63: Net Change in Cash | C63: 592 | D63: 3996 | E63: -824 | F63: 1920 | G63: 9155 | H63: -1325 | I63: -1089 | J63: -1269 | K63: 27231 | L63: 2611
B64: Free Cash Flow | C64: 6076 | D64: 11617 | E64: 17483 | F64: 15359 | G64: 21212 | H64: 23632 | I64: 39116 | J64: 19044 | K64: 43847 | L64: 54072
B65: Free Cash Flow per Share | C65: 2.129688 | D65: 3.9716239 | E65: 5.9144114 | F65: 5.2581308 | G65: 7.3755216 | H65: 8.1828255 | I65: 13.681707 | J65: 7.0481125 | K65: 16.678205 | L65: 20.685539
B66: Free Cash Flow Yield (%) | C66: 2.0348634 | D66: 3.4520851 | E66: 3.3517009 | F66: 4.0110846 | G66: 3.5934332 | H66: 2.9956163 | I66: 4.0676994 | J66: 5.8568327 | K66: 4.7118897 | L66: 3.5329097
B67: All figures in millions of USD except per share and labeled items.

Sheet Ratio Analysis_Static
K2: Identifier | L2: META-US
K3: Start Date | L3: -9
K4: End Date | L4: 0
K5: Report Basis | L5: ANN_R
K6: Currency | L6: LOC
B7: Meta Platforms Inc Class A
B9: Ratio Analysis | C9: 42369 | D9: 42734 | E9: 43098 | F9: 43465 | G9: 43830 | H9: 44196 | I9: 44561 | J9: 44925 | K9: 45289 | L9: 45657
C10: Final/ | D10: Final/ | E10: Final/ | F10: Final/ | G10: Final/ | H10: Final/ | I10: Final/ | J10: Final/ | K10: Final/Restate | L10: Final/
B11: Profitability
B12: Gross Margin | C12: 84.008255 | D12: 86.290614 | E12: 86.584016 | F12: 83.246176 | G12: 81.936999 | H12: 80.582795 | I12: 80.794376 | J12: 79.62936 | K12: 80.722302 | L12: 81.684002
B13: SG&A to Sales | C13: 48.90116 | D13: 41.327158 | E13: 36.887807 | F13: 38.629607 | G13: 40.936673 | H13: 42.577793 | I13: 41.149336 | J13: 50.853708 | K13: 43.50788 | L13: 39.271494
B14: Operating Margin | C14: 35.107095 | D14: 44.963456 | E14: 49.696209 | F14: 44.616569 | G14: 41.000325 | H14: 38.005002 | I14: 39.645041 | J14: 28.775652 | K14: 37.214422 | L14: 42.412508
B15: Pretax Margin | C15: 34.549308 | D15: 45.292713 | E15: 50.658008 | F15: 45.41889 | G15: 35.096256 | H15: 38.597103 | I15: 40.095312 | J15: 24.714216 | K15: 35.157374 | L15: 42.95597
B16: Net Margin | C16: 20.465194 | D16: 36.862291 | E16: 39.160702 | F16: 39.598481 | G16: 26.146795 | H16: 33.904496 | I16: 33.384494 | J16: 19.895548 | K16: 28.982521 | L16: 37.908584
B17: Free Cash Flow Margin | C17: 33.89112 | D17: 42.032709 | E17: 43.005436 | F17: 27.506358 | G17: 30.004102 | H17: 27.490258 | I17: 33.16911 | J17: 16.331501 | K17: 32.502854 | L17: 32.870317
B18: Return on Assets | C18: 8.1905549 | D18: 17.816172 | E18: 21.299796 | F18: 24.316775 | G18: 16.024446 | H18: 19.915816 | I18: 24.205126 | J18: 13.192537 | K18: 18.826532 | L18: 24.663965
B19: Return on Equity | C19: 9.1366387 | D19: 19.703709 | E19: 23.842865 | F19: 27.904893 | G19: 19.964251 | H19: 25.416841 | I19: 31.101754 | J19: 18.516154 | K19: 28.0392 | L19: 37.140602
B20: Return on Common Equity | C20: 9.1366387 | D20: 19.703709 | E20: 23.842865 | F20: 27.904893 | G20: 19.964251 | H20: 25.416841 | I20: 31.101754 | J20: 18.516154 | K20: 28.0392 | L20: 37.140602
B21: Return on Total Capital | C21: 15.567263 | D21: 23.960974 | E21: 30.241069 | F21: 31.328043 | G21: 29.464054 | H21: 25.971104 | I21: 33.538737 | J21: 22.957403 | K21: 29.18075 | L21: 32.948916
B22: Return on Invested Capital | C22: 9.1110007 | D22: 19.683343 | E22: 23.830017 | F22: 27.892221 | G22: 18.948383 | H22: 23.376832 | I22: 28.47822 | J22: 16.022431 | K22: 22.940999 | L22: 29.711721
B23: Cash Flow Return on Invested Capital | C23: 21.353365 | D23: 31.120857 | E23: 36.24797 | F23: 36.928084 | G23: 37.224321 | H23: 31.077407 | I23: 41.724896 | J23: 34.859148 | K23: 41.726002 | L23: 43.513664
B24: Valuation
B25: Price/Sales | C25: 16.655231 | D25: 12.176035 | E25: 12.830929 | F25: 6.8575861 | G25: 8.3497037 | H25: 9.1768287 | I25: 8.1542678 | J25: 2.7884527 | K25: 6.8980507 | L25: 9.3040355
B26: Price/Earnings | C26: 81.131783 | D26: 32.937303 | E26: 32.735975 | F26: 17.317041 | G26: 31.934094 | H26: 27.066716 | I26: 24.425225 | J26: 14.015513 | K26: 23.80075 | L26: 24.543305
B27: Price/Book Value | C27: 6.7338551 | D27: 5.6209171 | E27: 6.8972903 | F27: 4.4472157 | G27: 5.792675 | H27: 6.0661997 | I27: 7.3826291 | J27: 2.5022769 | K27: 5.9182827 | L27: 8.1236674
B28: Price/Tangible Book Value | C28: 12.976453 | D28: 8.6338999 | E28: 9.4537952 | F28: 5.7976021 | G28: 7.1873412 | H28: 7.1649267 | I28: 8.7763246 | J28: 3.0099393 | K28: 6.8816449 | L28: 9.2115277
B29: Price/Cash Flow | C29: 34.724384 | D29: 20.89156 | E29: 21.540129 | F29: 13.080341 | G29: 16.255411 | H29: 20.359927 | I29: 16.67085 | J29: 6.4419748 | K29: 13.085664 | L29: 16.758531
B30: Price/Free Cash Flow | C30: 49.143348 | D30: 28.967999 | E30: 29.835598 | F30: 24.930913 | G30: 27.82854 | H30: 33.382112 | I30: 24.583921 | J30: 17.074075 | K30: 21.222908 | L30: 28.305281
B31: Dividend Yield (%) | C31: 0 | D31: 0 | E31: 0 | F31: 0 | G31: 0 | H31: 0 | I31: 0 | J31: 0 | K31: 0 | L31: 0.34158255
B32: Enterprise Value/EBIT | C32: 270.432 | D32: 140.87606 | E32: 86.043127 | F32: 69.628138 | G32: 58.676154 | H32: 53.307499 | I32: 37.988976 | J32: 52.666297 | K32: 36.076392 | L32: 26.138741
B33: Enterprise Value/EBITDA | C33: 206.59048 | D33: 118.53658 | E33: 74.837666 | F33: 59.348768 | G33: 48.975927 | H33: 44.05457 | I33: 32.457942 | J33: 41.836547 | K33: 29.506575 | L33: 21.387803
B34: Enterprise Value/Sales | C34: 94.940819 | D34: 63.342745 | E34: 42.760173 | F34: 31.065686 | G34: 24.057414 | H34: 20.259516 | I34: 15.060745 | J34: 15.15507 | K34: 13.425621 | L34: 11.086096
B35: Total Debt/Enterprise Value | C35: 0.00018506562 | D35: 0 | E35: 4.141908e-05 | F35: 0.00028824328 | G35: 0.0065111034 | H35: 0.0064176277 | I35: 0.0081380617 | J35: 0.015435564 | K35: 0.020939262 | L35: 0.027290517
B36: Per Share
B37: Sales per Share | C37: 6.2839117 | D37: 9.4488889 | E37: 13.752706 | F37: 19.116056 | G37: 24.581711 | H37: 29.766274 | I37: 41.248339 | J37: 43.156551 | K37: 51.313047 | L37: 62.930757
B38: EBIT (Operating Income) per Share | C38: 2.2060988 | D38: 4.248547 | E38: 6.8345737 | F38: 8.5289284 | G38: 10.078581 | H38: 11.312673 | I38: 16.352921 | J38: 12.418579 | K38: 19.095854 | L38: 26.690513
B39: EPS (recurring) | C39: 1.3096039 | D39: 3.4929915 | E39: 5.3903924 | F39: 7.5700103 | G39: 7.6442976 | H39: 10.092105 | I39: 13.770549 | J39: 9.780792 | K39: 15.790947 | L39: 23.960329
B40: EPS (basic) | C40: 1.31 | D40: 3.5585 | E40: 5.4878 | F40: 7.6509 | G40: 6.4769 | H40: 10.2231 | I40: 13.9858 | J40: 8.6342 | K40: 15.1896 | L40: 24.6093
B41: EPS (diluted) | C41: 1.29 | D41: 3.493 | E41: 5.3904 | F41: 7.57 | G41: 6.4273 | H41: 10.0921 | I41: 13.7706 | J41: 8.5862 | K41: 14.8718 | L41: 23.8562
B42: Headline EPS | C42: - | D42: - | E42: - | F42: - | G42: - | H42: - | I42: - | J42: - | K42: - | L42: -
B43: Headline EPS (diluted) | C43: - | D43: - | E43: - | F43: - | G43: - | H43: - | I43: - | J43: - | K43: - | L43: -
B44: Dividends per Share | C44: 0 | D44: 0 | E44: 0 | F44: 0 | G44: 0 | H44: 0 | I44: 0 | J44: 0 | K44: 0 | L44: 2
B45: Dividend Payout Ratio (%) | C45: 0 | D45: 0 | E45: 0 | F45: 0 | G45: 0 | H45: 0 | I45: 0 | J45: 0 | K45: 0 | L45: 8.3835649
B46: Book Value per Share | C46: 15.54236 | D46: 20.46819 | E46: 25.58396 | F46: 29.47687 | G46: 35.43268 | H46: 45.02984 | I46: 45.55965 | J46: 48.0922 | K46: 59.80789 | L46: 72.07459
B47: Tangible Book Value per Share | C47: 8.0653779 | D47: 13.32538 | E47: 18.66552 | F47: 22.611072 | G47: 28.557153 | H47: 38.124605 | I47: 38.324699 | J47: 39.980872 | K47: 51.435377 | L47: 63.562747
B48: Cash Flow per Share | C48: 3.0140203 | D48: 5.5070085 | E48: 8.1921516 | F48: 10.02191 | G48: 12.626565 | H48: 13.416551 | I48: 20.175936 | J48: 18.680607 | K48: 27.049448 | L48: 34.938026
B49: Free Cash Flow per Share | C49: 2.129688 | D49: 3.9716239 | E49: 5.9144114 | F49: 5.2581308 | G49: 7.3755216 | H49: 8.1828255 | I49: 13.681707 | J49: 7.0481125 | K49: 16.678205 | L49: 20.685539
B50: Diluted Shares Outstanding (M) (M) | C50: 2853 | D50: 2925 | E50: 2956 | F50: 2921 | G50: 2876 | H50: 2888 | I50: 2859 | J50: 2702 | K50: 2629 | L50: 2614
B51: Basic Shares Outstanding (M) (M) | C51: 2803 | D51: 2863 | E51: 2901 | F51: 2890 | G51: 2854 | H51: 2851 | I51: 2815 | J51: 2687 | K51: 2574 | L51: 2534
B52: Total Shares Outstanding (M) (M) | C52: 2845 | D52: 2892 | E52: 2906 | F52: 2854 | G52: 2852 | H52: 2849 | I52: 2741 | J52: 2614 | K52: 2561 | L52: 2534
B53: Asset Turnover Analysis
B54: Cash & ST Investments | C54: 1.2100024 | D54: 1.1543972 | E54: 1.1425801 | F54: 1.3481741 | G54: 1.4730536 | H54: 1.4687591 | I54: 2.1375179 | J54: 2.6151672 | K54: 2.5325624 | L54: 2.289984
B55: Receivables | C55: 8.4625915 | D55: 8.4365079 | E55: 8.2754198 | F55: 8.3222297 | G55: 8.2662379 | H55: 8.2448569 | I55: 9.2952629 | J55: 8.4791129 | K55: 9.1042349 | L55: 9.9207551
B56: Inventories | C56: - | D56: - | E56: - | F56: - | G56: - | H56: - | I56: - | J56: - | K56: - | L56: -
B57: Current Assets | C57: 0.82800665 | D57: 0.80340688 | E57: 0.83711879 | F57: 1.106141 | G57: 1.0675274 | H57: 1.1360513 | I57: 1.7689527 | J57: 1.9582025 | K57: 1.5802964 | L57: 1.6442701
B58: Fixed Assets | C58: 3.152453 | D58: 3.2170876 | E58: 2.9628307 | F58: 2.2622048 | G58: 1.5786571 | H58: 1.5635401 | I58: 1.6855669 | J58: 1.2648632 | K58: 1.22771 | L58: 1.2071873
B59: Total Assets | C59: 0.40021877 | D59: 0.48331701 | E59: 0.54390742 | F59: 0.61408352 | G59: 0.61286464 | H59: 0.58740929 | I59: 0.72504096 | J59: 0.6630899 | K59: 0.64958228 | L59: 0.6506169
B60: DuPont Analysis
B61: Asset Turnover (x) | C61: 0.40021877 | D61: 0.48331701 | E61: 0.54390742 | F61: 0.61408352 | G61: 0.61286464 | H61: 0.58740929 | I61: 0.72504096 | J61: 0.6630899 | K61: 0.64958228 | L61: 0.6506169
B62: x Pretax Margin (%) | C62: 34.549308 | D62: 45.292713 | E62: 50.658008 | F62: 45.41889 | G62: 35.096256 | H62: 38.597103 | I62: 40.095312 | J62: 24.714216 | K62: 35.157374 | L62: 42.95597
B63: = Pretax Return on Assets (%) | C63: 13.827282 | D63: 21.890739 | E63: 27.553266 | F63: 27.890992 | G63: 21.509254 | H63: 22.672297 | I63: 29.070743 | J63: 16.387747 | K63: 22.837607 | L63: 27.94788
B64: x Tax Rate Complement (1-Tax Rate) (%) | C64: 59.541492 | D64: 81.618469 | E64: 77.37205 | F64: 87.188991 | G64: 74.500242 | H64: 87.842074 | I64: 83.262837 | J64: 80.502446 | K64: 82.436535 | L64: 88.249862
B65: = Return on Assets (%) | C65: 8.1905549 | D65: 17.816172 | E65: 21.299796 | F65: 24.316775 | G65: 16.024446 | H65: 19.915816 | I65: 24.205126 | J65: 13.192537 | K65: 18.826532 | L65: 24.663965
B66: x Equity Multiplier (Assets/Equity) | C66: 1.1155091 | D66: 1.1059452 | E66: 1.119394 | F66: 1.1475573 | G66: 1.2458622 | H66: 1.2762139 | I66: 1.2849243 | J66: 1.4035324 | K66: 1.4893449 | L66: 1.505865
B67: = Return on Equity (%) | C67: 9.1366387 | D67: 19.703709 | E67: 23.842865 | F67: 27.904893 | G67: 19.964251 | H67: 25.416841 | I67: 31.101754 | J67: 18.516154 | K67: 28.0392 | L67: 37.140602
B68: x Earnings Retention (1-Payout) (%) | C68: 100 | D68: 100 | E68: 100 | F68: 100 | G68: 100 | H68: 100 | I68: 100 | J68: 100 | K68: 100 | L68: 91.616435
B69: = Reinvestment Rate (%) | C69: 9.1366387 | D69: 19.703709 | E69: 23.842865 | F69: 27.904893 | G69: 19.964251 | H69: 25.416841 | I69: 31.101754 | J69: 18.516154 | K69: 28.0392 | L69: 34.119802
B70: Note: EBIT Return on Assets (%) | C70: 14.050518 | D70: 21.731603 | E70: 27.030137 | F70: 27.3983 | G70: 25.127649 | H70: 22.324491 | I70: 28.744278 | J70: 19.080844 | K70: 24.173829 | L70: 27.594294
B71: Note: Interest as % Assets | C71: 0.046552108 | D71: 0 | E71: - | F71: - | G71: 0.014995202 | H71: - | I71: - | J71: 0.086147948 | K71: 0.19423141 | L71: 0.2590073
B72: Operating Efficiency
B73: Revenue/Employee (actual) | C73: 1412654.6 | D73: 1621187.2 | E73: 1619318.9 | F73: 1569056.1 | G73: 1573072 | H73: 1466879.4 | I73: 1638585.5 | J73: 1348361.5 | K73: 2003981.2 | L73: 2220975.6
B74: Net Income/Employee (actual) | C74: 289102.51 | D74: 597606.76 | E74: 634136.63 | F74: 621322.39 | G74: 411307.91 | H74: 497338.07 | I74: 547033.49 | J74: 268263.92 | K74: 580804.25 | L74: 841940.41
B75: Assets/Employee (actual) | C75: 3893073.8 | D75: 3810476.3 | E75: 3366819.4 | F75: 2735099.9 | G75: 2967736.2 | H75: 2718517.5 | I75: 2306336 | J75: 2147579.8 | K75: 3411070 | L75: 3727084.9
B76: Receivables Turnover | C76: 8.4625915 | D76: 8.4365079 | E76: 8.2754198 | F76: 8.3222297 | G76: 8.2662379 | H76: 8.2448569 | I76: 9.2952629 | J76: 8.4791129 | K76: 9.1042349 | L76: 9.9207551
B77: Inventory Turnover | C77: - | D77: - | E77: - | F77: - | G77: - | H77: - | I77: - | J77: - | K77: - | L77: -
B78: Payables Turnover | C78: 7.2491 | D78: 7.6161 | E78: 8.068 | F78: 8.7799 | G78: 7.0748 | H78: 7.144 | I78: 5.9926 | J78: 4.2259 | K78: 4.4007 | L78: 4.4974
B79: Asset Turnover | C79: 0.40021877 | D79: 0.48331701 | E79: 0.54390742 | F79: 0.61408352 | G79: 0.61286464 | H79: 0.58740929 | I79: 0.72504096 | J79: 0.6630899 | K79: 0.64958228 | L79: 0.6506169
B80: Working Capital Turnover | C80: 0.90880519 | D80: 0.87667322 | E80: 0.90737227 | F80: 1.2847249 | G80: 1.3815563 | H80: 1.416484 | I80: 2.5900815 | J80: 3.5854318 | K80: 2.5260182 | L80: 2.4755978
B81: Operating Cycle - Days
B82: Days of Inventory on Hand | C82: - | D82: - | E82: - | F82: - | G82: - | H82: - | I82: - | J82: - | K82: - | L82: -
B83: + Days of Sales Outstanding | C83: 43.130996 | D83: 43.264346 | E83: 44.106524 | F83: 43.858439 | G83: 44.155516 | H83: 44.270023 | I83: 39.267313 | J83: 43.046956 | K83: 40.091233 | L83: 36.791554
B84: = Operating Cycle | C84: - | D84: - | E84: - | F84: - | G84: - | H84: - | I84: - | J84: - | K84: - | L84: -
B85: - Days of Payables Outstanding | C85: 50.351078 | D85: 47.924791 | E85: 45.240456 | F85: 41.572227 | G85: 51.591564 | H85: 51.091825 | I85: 60.908454 | J85: 86.372134 | K85: 82.94135 | L85: 81.158002
B86: = Net Operating Cycle | C86: - | D86: - | E86: - | F86: - | G86: - | H86: - | I86: - | J86: - | K86: - | L86: -
B87: Liquidity
B88: Current Ratio (x) | C88: 11.247792 | D88: 11.965565 | E88: 12.915691 | F88: 7.1939575 | G88: 4.3994553 | H88: 5.0510647 | I88: 3.1542938 | J88: 2.2033967 | K88: 2.670995 | L88: 2.9778843
B89: Quick Ratio (x) | C89: 11.247792 | D89: 11.965565 | E89: 12.915691 | F89: 7.1939575 | G89: 4.3994553 | H89: 5.0510647 | I89: 3.1542938 | J89: 2.2033967 | K89: 2.670995 | L89: 2.9778843
B90: Cash Ratio | C90: 9.5761039 | D90: 10.24313 | E90: 11.093351 | F90: 5.8606242 | G90: 3.6446556 | H90: 4.151592 | I90: 2.2780696 | J90: 1.5182417 | K90: 2.0494994 | L90: 2.3267056
B91: Cash & ST Inv/Current Assets | C91: 85.137632 | D91: 85.60507 | E91: 85.890493 | F91: 81.465927 | G91: 82.843337 | H91: 82.192414 | I91: 72.221222 | J91: 68.9046 | K91: 76.731682 | L91: 78.13284
B92: CFO/Current Liabilities | C92: 446.7013 | D92: 560.27826 | E92: 644.04255 | F92: 417.18683 | G92: 241.24095 | H92: 258.64095 | I92: 272.92643 | J92: 186.7646 | K92: 222.50626 | L92: 271.84189
B93: Coverage
B94: Net Debt/EBITDA | C94: -2.1991747 | D94: -1.9939739 | E94: -1.792621 | F94: -1.3899001 | G94: -1.55824 | H94: -1.5600132 | I94: -0.8692617 | J94: -0.72020075 | K94: -0.75637412 | L94: -0.57036134
B95: Net Debt/(EBITDA-Capex) | C95: -3.169874 | D95: -2.8652462 | E95: -2.5243407 | F95: -2.6529093 | G95: -2.2312866 | H95: -2.0893603 | I95: -0.93195585 | J95: -1.2723404 | K95: -0.80838341 | L95: -0.59151028
B96: Total Debt/EBITDA | C96: 0.038232795 | D96: 0 | E96: 0.0030997072 | F96: 0.017106884 | G96: 0.021597028 | H96: 0.013229454 | I96: 0.01061769 | J96: 0.25117777 | K96: 0.31076392 | L96: 0.34638254
B97: EBIT/Interest Expense (Int. Coverage) | C97: 273.65217 | D97: - | E97: - | F97: - | G97: 1449.3 | H97: - | I97: - | J97: 209.71875 | K97: 112.56278 | L97: 97.579021
B98: EBITDA/Interest Expense | C98: 358.21739 | D98: - | E98: - | F98: - | G98: 1736.35 | H98: - | I98: - | J98: 264.00625 | K98: 137.62556 | L98: 119.25455
B99: Fixed-charge Coverage Ratio | C99: 273.65217 | D99: - | E99: - | F99: - | G99: 1449.3 | H99: - | I99: - | J99: 209.71875 | K99: 112.56278 | L99: 97.579021
B100: CFO/Interest Expense | C100: 373.86957 | D100: - | E100: - | F100: - | G100: 1815.7 | H100: - | I100: - | J100: 315.46875 | K100: 159.44619 | L100: 127.73147
B101: Cash Dividend Coverage Ratio | C101: - | D101: - | E101: - | F101: - | G101: - | H101: - | I101: - | J101: - | K101: - | L101: 17.799685
B102: LT Debt/EBITDA | C102: 0.012987013 | D102: 0 | E102: 0.0030997072 | F102: 0 | G102: 0.28588706 | H102: 0.25512863 | I102: 0.24190424 | J102: 0.60995242 | K102: 0.58993825 | L102: 0.56001736
...
